Workbook
Name body: '[1]资产负债表-2017'!$C$6:$H$36
Name grid: '[1]资产负债表-2017'!$C$6:$H$36
Name head: '[1]资产负债表-2017'!$A$4:$H$4
Name 合并科目名称: [2]Sheet1!$A$2:$A$908
Name 核算项目明细账: [3]核算项目明细账!$A$1:$K$157
Name 会计分录序时簿: #REF!
Name 科目余额表: #REF!
Name 明细分类账: #REF!
Name body: '[4]资产负债表-2017'!$C$6:$H$36
Name grid: '[4]资产负债表-2017'!$C$6:$H$36
Name head: '[4]资产负债表-2017'!$A$4:$H$4
Name 合并科目名称: [5]Sheet1!$A$2:$A$908
Name 核算项目明细账: [6]核算项目明细账!$A$1:$K$157
Name 会计分录序时簿: #REF!
Name 科目余额表: #REF!
Name 明细分类账: #REF!
Name body: '[4]资产负债表-2017'!$C$6:$H$36
Name grid: '[4]资产负债表-2017'!$C$6:$H$36
Name head: '[4]资产负债表-2017'!$A$4:$H$4
Name 合并科目名称: [5]Sheet1!$A$2:$A$908
Name 核算项目明细账: [6]核算项目明细账!$A$1:$K$157
Name 会计分录序时簿: #REF!
Name 科目余额表: #REF!
Name 明细分类账: #REF!
Name \555: [7]表三甲!#REF!
Name \a: [7]表三甲!#REF!
Name \b: #REF!
Name \bbb: #REF!
Name \E: #REF!
Name \k: [8]土建表三乙!#REF!
Name \kkk: [7]表三甲!#REF!
Name \m: #REF!
Name \o: [7]表三甲!#REF!
Name \p: [7]表三甲!#REF!
Name \q: [7]表三甲!#REF!
Name \r: [7]表三甲!#REF!
Name \x: [7]表三甲!#REF!
Name \xx: [7]表三甲!#REF!
Name \z: [7]表三甲!#REF!
Name \zz: [7]表三甲!#REF!
Name _: #REF!
Name _0.dbf: #REF!
Name _000.03.dbf: #REF!
Name _00103应收货款余额表.dbf: #REF!
Name _0月31日: #REF!
Name _1: #REF!
Name _1_: #REF!
Name _1_?: #REF!
Name _10_2004009P1: #REF!
Name _10Print_Area_00v00__00_00_\________0.00\_______損_鑼_T_R__z揻_?00_0_0_0__?Vo__000______000?T00000?_0_00000B0___0鞊?w_0000_0_斪_萟?00_000?_000?_0_?000000_0詶__????_?: #REF!
Name _11_2004012P1: #REF!
Name _12其他资产_开办费除外_明细表: #REF!
Name _2: #REF!
Name _2_??????: #REF!
Name _3: #REF!
Name _3_2003002K8: #REF!
Name _333: #REF!
Name _4: #REF!
Name _4_2003002KA: #REF!
Name _5: #REF!

Sheet GMV-战略需求
A1: 规模
A2: 结构 | B2: 品类
B3: 品牌
A5: 1、21年-22年商品大类增长波动 | J5: 年份 | K5: 游戏 | L5: 通信 | M5: 网娱 | N5: 网娱 | O5: 合计
J6: 43831
J7: 43862
J8: 43891
J9: 43922
J10: 43952
J11: 43983
J12: 44013
J13: 44044
J14: 44075
J15: 44105
J16: 44136
J17: 44166
... J23: 44348
A24: 2、21年-22年网娱、生活服务增长波动 | J24: 44378
J25: 44409
J26: 44440
J27: 44470
J28: 44501
J29: 44531
J30: 44562
J31: 44593
J32: 44621
J33: 44652
J34: 44682
J35: 44713
J36: 44743
... J40: 44866
A43: 3、品牌趋势波动，是否针对网娱、生活服务--22年数据波动做分析
A44: 网娱品牌 | B44: 影视会员、音频、视频直播、知识阅读
A45: 生活服务 | B45: 加油卡、网络工具、出行生活、餐饮、购物（优惠劵）、其他

Sheet 毛利-战略需求
A1: 1、收入构成 | B1: 代理 | C1: 虚拟商品采销差额收入+返点 | D1: 分商品大类-20年-22年
B2: 增值代运营 | C2: 代运营收入 | D2: 分商品大类-需要提供21年GMV
B3: 推广收入 | D3: 分商品大类-需要提供21年GMV
A8: 2、品类毛利21年-22年 | B8: 依赖第一条数据提供商品大类可以出
A18: 3、四大品类毛利/gmv
A25: 4、成长性品牌的毛利分析
A26: 生活服务
A27: 网娱
A30: 5、供应商毛利波动（前10）

Sheet 利润组成
A1: GMV | F1: 毛利收入（含税） | P1: 净利润 | AC1: 毛利率 | AH1: 净利润率 | AM1: 当月净利润 | AR1: 子公司提交资料
A2: 月份累计 | B2: 上市公司 | C2: 投资公司 | D2: 小计 | F2: 月份累计 | G2: 上市公司 | H2: 佣金手续费（元）（账面不含税金额） | I2: 佣金手续费（含税） | J2: 体内项目-衍生公司 | K2: 跨期返利(含税） | L2: 上市公司-扣除佣金手续费后、调整跨期返利后毛利收入 | M2: 投资公司 | N2: 集团小计 | P2: 月份累计 | Q2: 上市公司（审计口径） | R2: 跨期返利 | S2: 体内项目-衍生公司 | T2: H1项目分红 | U2: H1导师分红 | V2: 西藏福禄确认的上海灵盟投资损失 | W2: 上市公司调整后净利润小计 | X2: 投资公司调整前 | Y2: H1项目分红 | Z2: H1导师分红 | AA2: 集团小计 | AC2: 月份 | AD2: 上市公司（审计口径） | AE2: 投资公司 | AF2: 集团小计 | AH2: 月份 | AI2: 上市公司（审计口径） | AJ2: 投资公司 | AK2: 小计 | AM2: 月份 | AN2: 上市公司当月利润（核算）（元） | AO2: 调整跨期返利收入（元） | AP2: 调整投资公司(万元） | AR2: 月份累计 | AS2: 项目 | AT2: GMV | AU2: 毛利 | AV2: 净利润（决算口径） | AW2: 净利润（核算口径）
A3: 44562 | B3: 108052.9 | C3: 2374.0586 | D3: =B3+C3 -> 110426.96 | F3: 44562 | G3: ='毛利-收入组成'!AQ27 -> 2571.88 | H3: 2707835.9 | I3: =H3*1.06/10000 -> 287.03061 | J3: 655.10541 | K3: =R3*1.06 -> -486.04177 | L3: =G3-I3+J3-K3 -> 3425.9966 | M3: 1436.02 | N3: =L3+M3 -> 4862.0166 | P3: 44562 | Q3: 554.64112 | R3: =-4585299.71781625/10000 -> -458.52997 | S3: 160.39838 | W3: =Q3-R3+S3 -> 1173.5695 | X3: -1005.6133 | AA3: =W3+X3 -> 167.95616 | AC3: 44562 | AD3: =L3/B3 -> 0.03170666 | AE3: =M3/C3 -> 0.60487979 | AF3: =N3/D3 -> 0.044029254 | AH3: 44562 | AI3: =W3*1.06/L3 -> 0.36310125 | AJ3: =X3*1.06/M3 -> -0.74229474 | AK3: =AA3*1.06/N3 -> 0.03661722 | AM3: 44562 | AN3: 4419474.4 | AO3: =-12638207.1/3 -> -4212735.7 | AR3: 45931 | AS3: 灵工平台中心
A4: 44593 | B4: 194083.64 | C4: 4905.486 | D4: =B4+C4 -> 198989.13 | F4: 44593 | G4: ='毛利-收入组成'!AQ28 -> 4593.9912 | H4: 4898251.5 | I4: =H4*1.06/10000 -> 519.21466 | J4: 895.37 | K4: =R4*1.06 -> -952.56963 | L4: =G4-I4+J4-K4 -> 5922.7161 | M4: 3006.5654 | N4: =L4+M4 -> 8929.2816 | P4: 44593 | Q4: 632.65232 | R4: =-4585299.71781625/10000-4401206.19439752/10000 -> -898.65059 | S4: 103.02 | W4: =Q4-R4+S4 -> 1634.3229 | X4: -1072.18 | AA4: =W4+X4 -> 562.14291 | AC4: 44593 | AD4: =L4/B4 -> 0.030516307 | AE4: =M4/C4 -> 0.61289859 | AF4: =N4/D4 -> 0.044873213 | AH4: 44593 | AI4: =W4*1.06/L4 -> 0.29249794 | AJ4: =X4*1.06/M4 -> -0.37800967 | AK4: =AA4*1.06/N4 -> 0.066732299 | AM4: 44593 | AN4: 2602332.2 | AO4: =-12638207.1/3 -> -4212735.7 | AR4: 45931 | AS4: 海外权益中心
A5: 44621 | B5: 326827.75 | C5: 7834.875 | D5: =B5+C5 -> 334662.63 | F5: 44621 | G5: ='毛利-收入组成'!AQ29 -> 8008.37 | H5: 6963186.2 | I5: =H5*1.06/10000 -> 738.09774 | J5: 1265.12 | K5: =R5*1.06 -> -1339.65 | L5: =G5-I5+J5-K5 -> 9875.0423 | M5: 4720.6749 | N5: =L5+M5 -> 14595.717 | P5: 44621 | Q5: 1386.5289 | R5: -1263.8207 | S5: 203.79785 | W5: =Q5-R5+S5 -> 2854.1475 | X5: -1370.88 | AA5: =W5+X5 -> 1483.2675 | AC5: 44621 | AD5: =L5/B5 -> 0.030214822 | AE5: =M5/C5 -> 0.60252077 | AF5: =N5/D5 -> 0.043613227 | AH5: 44621 | AI5: =W5*1.06/L5 -> 0.30636794 | AJ5: =X5*1.06/M5 -> -0.3078231 | AK5: =AA5*1.06/N5 -> 0.10772088 | AM5: 44621 | AN5: 6160437 | AO5: =-12638207.1/3 -> -4212735.7 | AP5: 146.56785 | AR5: 45931 | AS5: 游戏生态电商中心 | AT5: 118797.22 | AU5: 3600.68 | AV5: 1573.3
A6: 44652 | B6: 448332.98 | C6: 8907.4138 | D6: =B6+C6 -> 457240.4 | F6: 44652 | G6: ='毛利-收入组成'!AQ30 -> 10700.565 | H6: 9273917.6 | I6: =H6*1.06/10000 -> 983.03526 | J6: 1531.8642 | K6: =R6*1.06 -> -1249.4227 | L6: =G6-I6+J6-K6 -> 12498.816 | M6: 6687.3105 | N6: =L6+M6 -> 19186.127 | P6: 44652 | Q6: 1630.6354 | R6: -1178.7007 | S6: 4.467404 | W6: =Q6-R6+S6 -> 2813.8034 | X6: -1783.2181 | AA6: =W6+X6 -> 1030.5853 | AC6: 44652 | AD6: =L6/B6 -> 0.027878423 | AE6: =M6/C6 -> 0.75075781 | AF6: =N6/D6 -> 0.0419607 | AH6: 44652 | AI6: =W6*1.06/L6 -> 0.23863313 | AJ6: =X6*1.06/M6 -> -0.28265641 | AK6: =AA6*1.06/N6 -> 0.05693804 | AM6: 44652 | AN6: 3124110.2 | AO6: 851200.46 | AP6: -11.900448
A7: 44682 | B7: 584617.02 | C7: 11251.915 | D7: =B7+C7 -> 595868.94 | F7: 44682 | G7: ='毛利-收入组成'!AQ31 -> 13310.057 | H7: 11902620 | I7: =H7*1.06/10000 -> 1261.6778 | J7: 1849.5439 | K7: =R7*1.06 -> -1388.9571 | L7: =G7-I7+J7-K7 -> 15286.88 | M7: 8601.3529 | N7: =L7+M7 -> 23888.233 | P7: 44682 | Q7: 1691.0027 | R7: =-13103368.83/10000 -> -1310.3369 | S7: 45.146767 | W7: =Q7-R7+S7 -> 3046.4863 | X7: -2102.6224 | AA7: =W7+X7 -> 943.86394 | AC7: 44682 | AD7: =L7/B7 -> 0.026148538 | AE7: =M7/C7 -> 0.76443456 | AF7: =N7/D7 -> 0.040089744 | AH7: 44682 | AI7: =W7*1.06/L7 -> 0.2112449 | AJ7: =X7*1.06/M7 -> -0.25911967 | AK7: =AA7*1.06/N7 -> 0.041882368 | AM7: 44682 | AN7: 603672.79 | AO7: =(R7-R6)*10000 -> -1316362.2 | AP7: 208.2226
A8: 44713 | B8: 727745.91 | C8: 13983.27 | D8: =B8+C8 -> 741729.18 | F8: 44713 | G8: ='毛利-收入组成'!AQ32 -> 17052.403 | H8: 15547055 | I8: =H8*1.06/10000 -> 1647.9879 | J8: 2173.8273 | K8: =R8*1.06 -> -1365.4349 | L8: =G8-I8+J8-K8 -> 18943.678 | M8: 10706.914 | N8: =L8+M8 -> 29650.592 | P8: 44713 | Q8: 3194.8382 | R8: =-12881461.65/10000 -> -1288.1462 | S8: -520.13564 | W8: =Q8-R8+S8 -> 3962.8487 | X8: -2258.997 | AA8: =W8+X8 -> 1703.8517 | AC8: 44713 | AD8: =L8/B8 -> 0.026030621 | AE8: =M8/C8 -> 0.76569461 | AF8: =N8/D8 -> 0.039974957 | AH8: 44713 | AI8: =W8*1.06/L8 -> 0.22174256 | AJ8: =X8*1.06/M8 -> -0.22364397 | AK8: =AA8*1.06/N8 -> 0.060912202 | AM8: 44713 | AN8: 15038356 | AO8: =(R8-R7)*10000 -> 221907.18 | AP8: -280.71317
A9: 44743 | B9: 850965.84 | C9: 16453.571 | D9: =B9+C9 -> 867419.41 | F9: 44743 | G9: ='毛利-收入组成'!AQ33 -> 20185.933 | H9: 18238988 | I9: =H9*1.06/10000 -> 1933.3327 | J9: 2432.4562 | K9: =R9*1.06 -> -1463.2248 | L9: =G9-I9+J9-K9 -> 22148.281 | M9: 13005.352 | N9: =L9+M9 -> 35153.633 | P9: 44743 | Q9: 3804.432 | R9: =-13804007.17/10000 -> -1380.4007 | S9: -820.04 | W9: =Q9-R9+S9 -> 4364.7927 | X9: -2988.73 | AA9: =W9+X9 -> 1376.0627 | AC9: 44743 | AD9: =L9/B9 -> 0.026027227 | AE9: =M9/C9 -> 0.79042731 | AF9: =N9/D9 -> 0.040526685 | AH9: 44743 | AI9: =W9*1.06/L9 -> 0.20889568 | AJ9: =X9*1.06/M9 -> -0.24359616 | AK9: =AA9*1.06/N9 -> 0.041492909 | AM9: 44743 | AN9: 6095938 | AO9: =(R9-R8)*10000 -> -922545.52 | AP9: 15.963167
A10: 44774 | B10: 985758.18 | C10: 19132.318 | D10: =B10+C10 -> 1004890.5 | F10: 44774 | G10: ='毛利-收入组成'!AQ34 -> 25497.365 | H10: 21451872 | I10: =H10*1.06/10000 -> 2273.8984 | J10: 3031.335 | K10: =R10*1.06 -> -1426.7573 | L10: =G10-I10+J10-K10 -> 27681.559 | M10: 15290.998 | N10: =L10+M10 -> 42972.557 | P10: 44774 | Q10: =54992357.66/10000 -> 5499.2358 | R10: =-13459974.9019033/10000 -> -1345.9975 | S10: -606.21 | W10: =Q10-R10+S10 -> 6239.0233 | X10: -3396.47 | AA10: =W10+X10 -> 2842.5533 | AC10: 44774 | AD10: =L10/B10 -> 0.02808149 | AE10: =M10/C10 -> 0.79922348 | AF10: =N10/D10 -> 0.042763423 | AH10: 44774 | AI10: =W10*1.06/L10 -> 0.23890868 | AJ10: =X10*1.06/M10 -> -0.23544952 | AK10: =AA10*1.06/N10 -> 0.070116992 | AM10: 44774 | AN10: 16948038 | AO10: =(R10-R9)*10000 -> 344032.27 | AP10: 302.64
A11: 44805 | B11: 1135221.8 | C11: 22645.071 | D11: =B11+C11 -> 1157866.9 | F11: 44805 | G11: ='毛利-收入组成'!AQ35 -> 28661.881 | H11: 24370597 | I11: =H11*1.06/10000 -> 2583.2833 | J11: 4014.432 | K11: =R11*1.06 -> -1269.1804 | L11: =G11-I11+J11-K11 -> 31362.211 | M11: 17952.319 | N11: =L11+M11 -> 49314.53 | P11: 44805 | Q11: =60424603.79/10000 -> 6042.4604 | R11: =-11973400.44662/10000 -> -1197.34 | S11: -844.98 | W11: =Q11-R11+S11 -> 6394.8204 | X11: -4007.97 | AA11: =W11+X11 -> 2386.8504 | AC11: 44805 | AD11: =L11/B11 -> 0.027626505 | AE11: =M11/C11 -> 0.79276938 | AF11: =N11/D11 -> 0.042590846 | AH11: 44805 | AI11: =W11*1.06/L11 -> 0.21613622 | AJ11: =X11*1.06/M11 -> -0.23665178 | AK11: =AA11*1.06/N11 -> 0.051304584 | AM11: 44805 | AN11: 5432246.1 | AO11: =(R11-R10)*10000 -> 1486574.5 | AP11: -155.56
A12: 44835 | B12: 1282791 | C12: 30802.29 | D12: =B12+C12 -> 1313593.3 | F12: 44835 | G12: ='毛利-收入组成'!AQ36 -> 31941.924 | H12: 27931645 | I12: =H12*1.06/10000 -> 2960.7544 | J12: 4527.9066 | K12: =R12*1.06 -> -1399.6803 | L12: =G12-I12+J12-K12 -> 34908.756 | M12: 20691.857 | N12: =L12+M12 -> 55600.613 | P12: 44835 | Q12: =70722471.56/10000 -> 7072.2472 | R12: =-13204531.4789889/10000 -> -1320.4531 | S12: -989.72 | W12: =Q12-R12+S12 -> 7402.9803 | X12: -3546.33 | AA12: =W12+X12 -> 3856.6503 | AC12: 44835 | AD12: =L12/B12 -> 0.027213129 | AE12: =M12/C12 -> 0.67176361 | AF12: =N12/D12 -> 0.042327115 | AH12: 44835 | AI12: =W12*1.06/L12 -> 0.22479057 | AJ12: =X12*1.06/M12 -> -0.18167097 | AK12: =AA12*1.06/N12 -> 0.073525256 | AM12: 44835 | AN12: 10297813 | AO12: =(R12-R11)*10000 -> -1231131 | AP12: -99.33
A13: 44866 | B13: 1458208.4 | C13: 28395.373 | D13: =B13+C13 -> 1486603.8 | F13: 44866 | G13: ='毛利-收入组成'!AQ37 -> 36141.231 | H13: 34940282 | I13: =H13*1.06/10000 -> 3703.6699 | J13: 5080.3998 | K13: =R13*1.06 -> -1487.864 | L13: =G13-I13+J13-K13 -> 39005.825 | M13: 23119.872 | N13: =L13+M13 -> 62125.697 | P13: 44866 | Q13: =75107451.42/10000 -> 7510.7451 | R13: =-14036452.5418712/10000 -> -1403.6453 | S13: -1132.02 | W13: =Q13-R13+S13 -> 7782.3704 | X13: -3545.53 | AA13: =W13+X13 -> 4236.8404 | AC13: 44866 | AD13: =L13/B13 -> 0.026749143 | AE13: =M13/C13 -> 0.81421265 | AF13: =N13/D13 -> 0.041790353 | AH13: 44866 | AI13: =W13*1.06/L13 -> 0.21148925 | AJ13: =X13*1.06/M13 -> -0.16255548 | AK13: =AA13*1.06/N13 -> 0.072289746 | AM13: 44866 | AN13: 3561925.3 | AO13: =(R13-R12)*10000 -> -831921.06 | AP13: -166.06
A14: 44896 | B14: 1630463.8 | C14: 43463.22 | D14: =B14+C14 -> 1673927 | F14: 44896 | G14: ='毛利-收入组成'!AQ38 -> 43520.124 | H14: 39830925 | I14: =H14*1.06/10000 -> 4222.0781 | J14: 6011.9066 | K14: =R14*1.06 -> -1190.8049 | L14: =G14-I14+J14-K14 -> 46500.757 | M14: 25043.454 | N14: =L14+M14 -> 71544.211 | P14: 44896 | Q14: =115027391.79/10000 -> 11502.739 | R14: =-11234008.655/10000 -> -1123.4009 | S14: -1269.48 | W14: =Q14-R14+S14 -> 11356.66 | X14: -4104.55 | AA14: =W14+X14 -> 7252.11 | AC14: 44896 | AD14: =L14/B14 -> 0.028519957 | AE14: =M14/C14 -> 0.57619877 | AF14: =N14/D14 -> 0.042740341 | AH14: 44896 | AI14: =W14*1.06/L14 -> 0.25887879 | AJ14: =X14*1.06/M14 -> -0.17373095 | AK14: =AA14*1.06/N14 -> 0.10744736 | AM14: 44896 | AN14: 18287190 | AO14: =(R14-R13)*10000 -> 2802443.9 | AP14: 184.5
A15: 44927 | B15: ='GMV表-商品大类'!T18+B71 -> 139899.12 | C15: 3494.7221 | D15: =B15+C15 -> 143393.84 | F15: 44927 | G15: ='毛利-收入组成'!AQ39 -> 4343.2834 | H15: 3630321.3 | I15: =H15*1.06/10000 -> 384.81406 | J15: 1931.3288 | K15: =R15*1.06 -> 206.06363 | L15: =G15-I15+J15-K15 -> 5683.7345 | M15: 2148.7773 | N15: =L15+M15 -> 7832.5118 | P15: 44927 | Q15: 1390.69 | R15: =1943996.50432941/10000 -> 194.39965 | S15: 785.578 | W15: =Q15-R15+S15 -> 1981.8684 | X15: 206.1331 | AA15: =W15+X15 -> 2188.0015 | AC15: 44927 | AD15: =L15/B15 -> 0.040627379 | AE15: =M15/C15 -> 0.61486355 | AF15: =N15/D15 -> 0.054622372 | AH15: 44927 | AI15: =W15*1.06/L15 -> 0.3696127 | AJ15: =X15*1.06/M15 -> 0.10168624 | AK15: =AA15*1.06/N15 -> 0.29610955 | AM15: 44927 | AN15: 13906900 | AO15: =R15*10000 -> 1943996.5 | AP15: 98.863
A16: 44958 | B16: ='GMV表-商品大类'!T19+B72 -> 273756.55 | C16: 6379.2112 | D16: =B16+C16 -> 280135.76 | F16: 44958 | G16: ='毛利-收入组成'!AQ40 -> 7467.2483 | H16: 6214995.1 | I16: =H16*1.06/10000 -> 658.78948 | J16: 2249.6399 | K16: =R16*1.06 -> -169.18257 | L16: =G16-I16+J16-K16 -> 9227.2813 | M16: 3659.1241 | N16: =L16+M16 -> 12886.405 | P16: 44958 | Q16: 2066.4314 | R16: =-1596061.9885538/10000 -> -159.6062 | S16: 597.92934 | W16: =Q16-R16+S16 -> 2823.967 | X16: 130.11791 | AA16: =W16+X16 -> 2954.0849 | AC16: 44958 | AD16: =L16/B16 -> 0.033706157 | AE16: =M16/C16 -> 0.57360134 | AF16: =N16/D16 -> 0.046000572 | AH16: 44958 | AI16: =W16*1.06/L16 -> 0.32440812 | AJ16: =X16*1.06/M16 -> 0.037693443 | AK16: =AA16*1.06/N16 -> 0.24299484 | AM16: 44958 | AN16: 6757414.1 | AO16: =(R16-R15)*10000 -> -3540058.5 | AP16: =S16-S15 -> -187.64866
A17: 44986 | B17: ='GMV表-商品大类'!T20+B73 -> 430030.64 | C17: 9120.9552 | D17: =B17+C17 -> 439151.59 | F17: 44986 | G17: ='毛利-收入组成'!AQ41 -> 10413.099 | H17: 9373428.8 | I17: =H17*1.06/10000 -> 993.58345 | J17: 2973.5557 | K17: =R17*1.06 -> 45.142784 | L17: =G17-I17+J17-K17 -> 12347.928 | M17: 5379.9146 | N17: =L17+M17 -> 17727.843 | P17: 44986 | Q17: 2269.4532 | R17: 42.587533 | S17: 365.21191 | W17: =Q17-R17+S17 -> 2592.0776 | X17: -140.70901 | AA17: =W17+X17 -> 2451.3686 | AC17: 44986 | AD17: =L17/B17 -> 0.028714067 | AE17: =M17/C17 -> 0.58984114 | AF17: =N17/D17 -> 0.04036839 | AH17: 44986 | AI17: =W17*1.06/L17 -> 0.22251524 | AJ17: =X17*1.06/M17 -> -0.027723776 | AK17: =AA17*1.06/N17 -> 0.14657455 | AM17: 44986 | AN17: 2030217.6 | AO17: =(R17-R16)*10000 -> 2021937.3 | AP17: =S17-S16 -> -232.71743
A18: 45017 | B18: ='GMV表-商品大类'!T21+B74 -> 562009.48 | C18: 11863.173 | D18: =B18+C18 -> 573872.65 | F18: 45017 | G18: ='毛利-收入组成'!AQ42 -> 12608.747 | H18: 12671634 | I18: =H18*1.06/10000 -> 1343.1932 | J18: 3381.6409 | K18: =R18*1.06 -> 39.369201 | L18: =G18-I18+J18-K18 -> 14607.826 | M18: 6902.0785 | N18: =L18+M18 -> 21509.904 | P18: 45017 | Q18: =24847709.2/10000 -> 2484.7709 | R18: =371407.553576133/10000 -> 37.140755 | S18: -115.89507 | W18: =Q18-R18+S18 -> 2331.7351 | X18: -310.77087 | AA18: =W18+X18 -> 2020.9642 | AC18: 45017 | AD18: =L18/B18 -> 0.025992134 | AE18: =M18/C18 -> 0.58180713 | AF18: =N18/D18 -> 0.037482017 | AH18: 45017 | AI18: =W18*1.06/L18 -> 0.16919966 | AJ18: =X18*1.06/M18 -> -0.047727235 | AK18: =AA18*1.06/N18 -> 0.099592357 | AM18: 45017 | AN18: 2153177.1 | AO18: =(R18-R17)*10000 -> -54467.771 | AP18: =S18-S17 -> -481.10697
A19: 45047 | B19: ='GMV表-商品大类'!T22+B75 -> 718524.9 | C19: 14129.51 | D19: =B19+C19 -> 732654.41 | F19: 45047 | G19: ='毛利-收入组成'!AQ43 -> 16236.986 | H19: 16554205 | I19: =H19*1.06/10000 -> 1754.7457 | J19: 3943.9878 | K19: =R19*1.06 -> 49.602631 | L19: =G19-I19+J19-K19 -> 18376.626 | M19: 8310.2133 | N19: =L19+M19 -> 26686.839 | P19: 45047 | Q19: =33865340.38/10000 -> 3386.534 | R19: =467949.353128217/10000 -> 46.794935 | S19: -480.00006 | W19: =Q19-R19+S19 -> 2859.739 | X19: -782.02193 | AA19: =W19+X19 -> 2077.7171 | AC19: 45047 | AD19: =L19/B19 -> 0.025575489 | AE19: =M19/C19 -> 0.58814591 | AF19: =N19/D19 -> 0.036424866 | AH19: 45047 | AI19: =W19*1.06/L19 -> 0.16495539 | AJ19: =X19*1.06/M19 -> -0.099749936 | AK19: =AA19*1.06/N19 -> 0.082526826 | AM19: 45047 | AN19: 9017631.2 | AO19: =(R19-R18)*10000 -> 96541.8 | AP19: =S19-S18 -> -364.105
A20: 45078 | B20: ='GMV表-商品大类'!T23+B76 -> 885719.33 | C20: 16876.623 | D20: =B20+C20 -> 902595.96 | F20: 45078 | G20: ='毛利-收入组成'!AQ44 -> 21479.88 | H20: 22188118 | I20: =H20*1.06/10000 -> 2351.9405 | J20: 4738.2533 | K20: =R20*1.06 -> 3.0884422 | L20: =G20-I20+J20-K20 -> 23863.104 | M20: 9775.2481 | N20: =L20+M20 -> 33638.353 | P20: 45078 | Q20: =56339633.83/10000 -> 5633.9634 | R20: =29136.2470234791/10000 -> 2.9136247 | S20: -606.53558 | W20: =Q20-R20+S20 -> 5024.5142 | X20: -595.02904 | AA20: =W20+X20 -> 4429.4851 | AC20: 45078 | AD20: =L20/B20 -> 0.026942061 | AE20: =M20/C20 -> 0.57921824 | AF20: =N20/D20 -> 0.03726845 | AH20: 45078 | AI20: =W20*1.06/L20 -> 0.22318911 | AJ20: =X20*1.06/M20 -> -0.064523251 | AK20: =AA20*1.06/N20 -> 0.13958039 | AM20: 45078 | AN20: 22474293 | AO20: =(R20-R19)*10000 -> -438813.11 | AP20: =S20-S19 -> -126.53552
A21: 45108 | B21: ='GMV表-商品大类'!T24+B77 -> 1031827.7 | C21: 19317.607 | D21: =B21+C21 -> 1051145.4 | F21: 45108 | G21: ='毛利-收入组成'!AQ45 -> 24896.668 | H21: 25343928 | I21: =H21*1.06/10000 -> 2686.4563 | J21: 5300.6635 | K21: =R21*1.06 -> 100.72932 | L21: =G21-I21+J21-K21 -> 27410.145 | M21: 11006.209 | N21: =L21+M21 -> 38416.354 | P21: 45108 | Q21: =64434719.82/10000 -> 6443.472 | R21: =950276.619611746/10000 -> 95.027662 | S21: -889.85281 | W21: =Q21-R21+S21 -> 5458.5915 | X21: -612.04319 | AA21: =W21+X21 -> 4846.5483 | AC21: 45108 | AD21: =L21/B21 -> 0.026564652 | AE21: =M21/C21 -> 0.56975012 | AF21: =N21/D21 -> 0.036547138 | AH21: 45108 | AI21: =W21*1.06/L21 -> 0.21109363 | AJ21: =X21*1.06/M21 -> -0.058945437 | AK21: =AA21*1.06/N21 -> 0.13372797 | AM21: 45108 | AN21: 8095086 | AO21: =(R21-R20)*10000 -> 921140.37 | AP21: =S21-S20 -> -283.31723
A22: 45139 | B22: ='GMV表-商品大类'!T25+B78 -> 1194307.4 | C22: 22430.295 | D22: =B22+C22 -> 1216737.7 | F22: 45139 | G22: ='毛利-收入组成'!AQ46 -> 29102.011 | H22: 29881459 | I22: =H22*1.06/10000 -> 3167.4347 | J22: 6106.3185 | K22: =R22*1.06 -> 89.892167 | L22: =G22-I22+J22-K22 -> 31951.003 | M22: 12594.133 | N22: =L22+M22 -> 44545.136 | P22: 45139 | Q22: =75519119.24/10000 -> 7551.9119 | R22: =848039.309164936/10000 -> 84.803931 | S22: -990.76869 | W22: =Q22-R22+S22 -> 6476.3393 | X22: -592.28631 | AA22: =W22+X22 -> 5884.053 | AC22: 45139 | AD22: =L22/B22 -> 0.026752747 | AE22: =M22/C22 -> 0.56147871 | AF22: =N22/D22 -> 0.036610304 | AH22: 45139 | AI22: =W22*1.06/L22 -> 0.21485772 | AJ22: =X22*1.06/M22 -> -0.049850472 | AK22: =AA22*1.06/N22 -> 0.14001745 | AM22: 45139 | AN22: 11084399 | AO22: =(R22-R21)*10000 -> -102237.31 | AP22: =S22-S21 -> -100.91588
A23: 45170 | B23: ='GMV表-商品大类'!T26+B79 -> 1339120.1 | C23: 25425.014 | D23: =B23+C23 -> 1364545.1 | F23: 45170 | G23: ='毛利-收入组成'!AQ47 -> 31954.748 | H23: 32816668 | I23: =H23*1.06/10000 -> 3478.5668 | J23: 7413.0762 | K23: =R23*1.06 -> -155.33227 | L23: =G23-I23+J23-K23 -> 36044.59 | M23: 14057.412 | N23: =L23+M23 -> 50102.002 | P23: 45170 | Q23: =83475621.39/10000 -> 8347.5621 | R23: =-1465398.79/10000 -> -146.53988 | S23: -698.13675 | W23: =Q23-R23+S23 -> 7795.9653 | X23: -570.92725 | AA23: =W23+X23 -> 7225.038 | AC23: 45170 | AD23: =L23/B23 -> 0.026916622 | AE23: =M23/C23 -> 0.55289692 | AF23: =N23/D23 -> 0.036716999 | AH23: 45170 | AI23: =W23*1.06/L23 -> 0.2292639 | AJ23: =X23*1.06/M23 -> -0.043050804 | AK23: =AA23*1.06/N23 -> 0.15285897 | AM23: 45170 | AN23: 7956502.2 | AO23: =(R23-R22)*10000 -> -2313438.1 | AP23: =S23-S22 -> 292.63194
A24: 45200 | B24: ='GMV表-商品大类'!T27+B80 -> 1446745 | C24: 28365.195 | D24: =B24+C24 -> 1475110.2 | F24: 45200 | G24: ='毛利-收入组成'!AQ48 -> 35384.217 | H24: 35555090 | I24: =H24*1.06/10000 -> 3768.8395 | J24: 8333.3067 | K24: =R24*1.06 -> 50.929116 | L24: =G24-I24+J24-K24 -> 39897.755 | M24: 15607.072 | N24: =L24+M24 -> 55504.827 | P24: 45200 | Q24: =89396323.84/10000 -> 8939.6324 | R24: =480463.357363195/10000 -> 48.046336 | S24: -747.08716 | W24: =Q24-R24+S24 -> 8144.4989 | X24: -460.83184 | AA24: =W24+X24 -> 7683.667 | AC24: 45200 | AD24: =L24/B24 -> 0.0275776 | AE24: =M24/C24 -> 0.5502191 | AF24: =N24/D24 -> 0.03762758 | AH24: 45200 | AI24: =W24*1.06/L24 -> 0.21638232 | AJ24: =X24*1.06/M24 -> -0.031298744 | AK24: =AA24*1.06/N24 -> 0.14673836 | AM24: 45200 | AN24: 5920702.5 | AO24: =(R24-R23)*10000 -> 1945862.1 | AP24: =S24-S23 -> -48.950403
A25: 45231 | B25: ='GMV表-商品大类'!T28+B81 -> 1573930.7 | C25: 32045.495 | D25: =B25+C25 -> 1605976.2 | F25: 45231 | G25: ='毛利-收入组成'!AQ49 -> 40497.763 | H25: 39818569 | I25: =H25*1.06/10000 -> 4220.7683 | J25: 9122.3132 | K25: =R25*1.06 -> -126.91095 | L25: =G25-I25+J25-K25 -> 45526.218 | M25: 16855.04 | N25: =L25+M25 -> 62381.259 | P25: 45231 | Q25: =105607329.35/10000 -> 10560.733 | R25: =-1197273.069527/10000 -> -119.72731 | S25: -669.69008 | W25: =Q25-R25+S25 -> 10010.77 | X25: -555.38892 | AA25: =W25+X25 -> 9455.3812 | AC25: 45231 | AD25: =L25/B25 -> 0.028925173 | AE25: =M25/C25 -> 0.52597222 | AF25: =N25/D25 -> 0.038843202 | AH25: 45231 | AI25: =W25*1.06/L25 -> 0.23308363 | AJ25: =X25*1.06/M25 -> -0.034927965 | AK25: =AA25*1.06/N25 -> 0.16066851 | AM25: 45231 | AN25: 16211006 | AO25: =(R25-R24)*10000 -> -1677736.4 | AP25: =S25-S24 -> 77.397076
A26: 45261 | B26: ='GMV表-商品大类'!T29+B82 -> 1683893.3 | C26: 35301.109 | D26: =B26+C26 -> 1719194.4 | F26: 45261 | G26: ='毛利-收入组成'!AQ50 -> 47538.618 | H26: 42529215 | I26: =H26*1.06/10000 -> 4508.0968 | J26: 10356.611 | K26: =R26*1.06 -> 116.10774 | L26: =G26-I26+J26-K26 -> 53271.024 | M26: 18153.929 | N26: =L26+M26 -> 71424.953 | P26: 45261 | Q26: =130338051.49/10000 -> 13033.805 | R26: =1095356.02364967/10000 -> 109.5356 | S26: -1547.2801 | W26: =Q26-R26+S26 -> 11376.989 | X26: -455.01694 | AA26: =W26+X26 -> 10921.973 | AC26: 45261 | AD26: =L26/B26 -> 0.03163563 | AE26: =M26/C26 -> 0.51425945 | AF26: =N26/D26 -> 0.041545594 | AH26: 45261 | AI26: =W26*1.06/L26 -> 0.22638215 | AJ26: =X26*1.06/M26 -> -0.026568242 | AK26: =AA26*1.06/N26 -> 0.16209028 | AM26: 45261 | AN26: 24730722 | AO26: =(R26-R25)*10000 -> 2292629.1 | AP26: =S26-S25 -> -877.58998
A27: 45292 | B27: ='GMV表-商品大类'!T30+B83 -> 101433.39 | C27: 2264.3271 | D27: =B27+C27 -> 103697.71 | F27: 45292 | G27: ='毛利-收入组成'!AQ51 -> 2786.2584 | H27: 2201641.7 | I27: =H27*1.06/10000 -> 233.37402 | J27: 1992.7764 | K27: =R27*1.06 -> -137.41391 | L27: =G27-I27+J27-K27 -> 4683.0747 | M27: 1641.7547 | N27: =L27+M27 -> 6324.8294 | P27: 45292 | Q27: =3364142.28/10000 -> 336.41423 | R27: =-1296357.68417/10000 -> -129.63577 | S27: 701.9994 | W27: =Q27-R27+S27 -> 1168.0494 | X27: 66.763345 | AA27: =W27+X27 -> 1234.8127 | AC27: 45292 | AD27: =L27/B27 -> 0.046168966 | AE27: =M27/C27 -> 0.72505193 | AF27: =N27/D27 -> 0.060992948 | AH27: 45292 | AI27: =W27*1.06/L27 -> 0.2643845 | AJ27: =X27*1.06/M27 -> 0.043105797 | AK27: =AA27*1.06/N27 -> 0.20694653 | AM27: 45292 | AN27: 3364142.3 | AO27: =R27*10000 -> -1296357.7 | AP27: =S27 -> 701.9994
A28: 45323 | B28: ='GMV表-商品大类'!T31+B84 -> 190089.48 | C28: 4490.9293 | D28: =B28+C28 -> 194580.41 | F28: 45323 | G28: ='毛利-收入组成'!AQ52 -> 5256.8072 | H28: 4535148.6 | I28: =H28*1.06/10000 -> 480.72575 | J28: 2470.0261 | K28: =R28*1.06 -> -236.35704 | L28: =G28-I28+J28-K28 -> 7482.4646 | M28: 3234.9687 | N28: =L28+M28 -> 10717.433 | P28: 45323 | Q28: 566.71745 | R28: =-2229783.36430365/10000 -> -222.97834 | S28: 664.82858 | W28: =Q28-R28+S28 -> 1454.5244 | X28: 318.4881 | AA28: =W28+X28 -> 1773.0125 | AC28: 45323 | AD28: =L28/B28 -> 0.039362855 | AE28: =M28/C28 -> 0.72033392 | AF28: =N28/D28 -> 0.055079714 | AH28: 45323 | AI28: =W28*1.06/L28 -> 0.20605454 | AJ28: =X28*1.06/M28 -> 0.10435878 | AK28: =AA28*1.06/N28 -> 0.17535852 | AM28: 45323 | AN28: 2303032.2 | AO28: =(R28-R27)*10000 -> -933425.68 | AP28: =S28-S27 -> -37.170824
A29: 45352 | B29: ='GMV表-商品大类'!T32+B85 -> 268614.84 | C29: 6554.9001 | D29: =B29+C29 -> 275169.74 | F29: 45352 | G29: ='毛利-收入组成'!AQ53 -> 8421.3423 | H29: 6411571.3 | I29: =H29*1.06/10000 -> 679.62655 | J29: 3319.7856 | K29: =R29*1.06 -> -625.33948 | L29: =G29-I29+J29-K29 -> 11686.841 | M29: 4047.3122 | N29: =L29+M29 -> 15734.153 | P29: 45352 | Q29: =19480246.9399998/10000 -> 1948.0247 | R29: =-5899429.04962477/10000 -> -589.9429 | S29: 484.12228 | W29: =Q29-R29+S29 -> 3022.0899 | X29: -142.42172 | AA29: =W29+X29 -> 2879.6682 | AC29: 45352 | AD29: =L29/B29 -> 0.043507801 | AE29: =M29/C29 -> 0.61744834 | AF29: =N29/D29 -> 0.057179809 | AH29: 45352 | AI29: =W29*1.06/L29 -> 0.27410447 | AJ29: =X29*1.06/M29 -> -0.037300564 | AK29: =AA29*1.06/N29 -> 0.19400143 | AM29: 45352 | AN29: =(Q29-Q28)*10000 -> 13813072 | AO29: =(R29-R28)*10000 -> -3669645.7 | AP29: =S29-S28 -> -180.7063
A30: 45383 | B30: ='GMV表-商品大类'!T33+B86 -> 329663.72 | C30: 7811.5825 | D30: =B30+C30 -> 337475.3 | F30: 45383 | G30: ='毛利-收入组成'!AQ54 -> 9720.5498 | H30: 8210403.3 | I30: =H30*1.06/10000 -> 870.30275 | J30: 3986.5078 | K30: =R30*1.06 -> -630.70441 | L30: =G30-I30+J30-K30 -> 13467.459 | M30: 4692.473 | N30: =L30+M30 -> 18159.932 | P30: 45383 | Q30: =17237592.6600001/10000 -> 1723.7593 | R30: =-5950041.59942243/10000 -> -595.00416 | S30: 527.01729 | W30: =Q30-R30+S30 -> 2845.7807 | X30: -364.30428 | AA30: =W30+X30 -> 2481.4764 | AC30: 45383 | AD30: =L30/B30 -> 0.040852112 | AE30: =M30/C30 -> 0.60070709 | AF30: =N30/D30 -> 0.053811144 | AH30: 45383 | AI30: =W30*1.06/L30 -> 0.22398639 | AJ30: =X30*1.06/M30 -> -0.082294036 | AK30: =AA30*1.06/N30 -> 0.14484443 | AM30: 45383 | AN30: =(Q30-Q29)*10000 -> -2242654.3 | AO30: =(R30-R29)*10000 -> -50612.55 | AP30: =S30-S29 -> 42.895009
A31: 45413 | B31: ='GMV表-商品大类'!T34+B87 -> 411711.95 | C31: 48484.603 | D31: =B31+C31 -> 460196.55 | F31: 45413 | G31: ='毛利-收入组成'!AQ55 -> 11948.968 | H31: 10009914 | I31: =H31*1.06/10000 -> 1061.0509 | J31: 4828.7836 | K31: =R31*1.06 -> -643.36516 | L31: =G31-I31+J31-K31 -> 16360.066 | M31: 5488.1957 | N31: =L31+M31 -> 21848.261 | P31: 45413 | Q31: =17363557.5599997/10000 -> 1736.3558 | R31: =-6069482.61294327/10000 -> -606.94826 | S31: 469.47202 | W31: =Q31-R31+S31 -> 2812.776 | X31: -520.88602 | AA31: =W31+X31 -> 2291.89 | AC31: 45413 | AD31: =L31/B31 -> 0.03973668 | AE31: =M31/C31 -> 0.11319461 | AF31: =N31/D31 -> 0.047475935 | AH31: 45413 | AI31: =W31*1.06/L31 -> 0.18224515 | AJ31: =X31*1.06/M31 -> -0.10060486 | AK31: =AA31*1.06/N31 -> 0.11119436 | AM31: 45413 | AN31: =(Q31-Q30)*10000 -> 125964.9 | AO31: =(R31-R30)*10000 -> -119441.01 | AP31: =S31-S30 -> -57.545267
A32: 45444 | B32: ='GMV表-商品大类'!T35+B88 -> 509385.36 | C32: 57933.49 | D32: =B32+C32 -> 567318.85 | F32: 45444 | G32: ='毛利-收入组成'!AQ56 -> 13920.387 | H32: 13079265 | I32: =H32*1.06/10000 -> 1386.402 | J32: 5206.9754 | K32: =R32*1.06 -> -648.29281 | L32: =G32-I32+J32-K32 -> 18389.253 | M32: 6076.524 | N32: =L32+M32 -> 24465.777 | P32: 45444 | Q32: =20545121.3099999/10000 -> 2054.5121 | R32: =-6115969.92496954/10000 -> -611.59699 | S32: 407.13856 | W32: =Q32-R32+S32 -> 3073.2477 | X32: -1234.8556 | AA32: =W32+X32 -> 1838.3921 | AC32: 45444 | AD32: =L32/B32 -> 0.036100867 | AE32: =M32/C32 -> 0.10488793 | AF32: =N32/D32 -> 0.043125267 | AH32: 45444 | AI32: =W32*1.06/L32 -> 0.17714926 | AJ32: =X32*1.06/M32 -> -0.21541047 | AK32: =AA32*1.06/N32 -> 0.079649857 | AM32: 45444 | AN32: =(Q32-Q31)*10000 -> 3181563.8 | AO32: =(R32-R31)*10000 -> -46487.312 | AP32: =S32-S31 -> -62.333461
A33: 45474 | B33: ='GMV表-商品大类'!T36+B89 -> 607746.8 | C33: 67786.587 | D33: =B33+C33 -> 675533.39 | F33: 45474 | G33: ='毛利-收入组成'!AQ57 -> 16860.607 | H33: 16583095 | I33: =H33*1.06/10000 -> 1757.8081 | J33: 4830.4436 | K33: =R33*1.06 -> 216.82817 | L33: =G33-I33+J33-K33 -> 19716.415 | M33: 7385.8469 | N33: =L33+M33 -> 27102.262 | P33: 45474 | Q33: =28247260.5499999/10000 -> 2824.7261 | R33: =2045548.79526134/10000 -> 204.55488 | S33: 345.70945 | W33: =Q33-R33+S33 -> 2965.8806 | X33: -914.54146 | AA33: =W33+X33 -> 2051.3392 | AC33: 45474 | AD33: =L33/B33 -> 0.032441824 | AE33: =M33/C33 -> 0.10895735 | AF33: =N33/D33 -> 0.040119796 | AH33: 45474 | AI33: =W33*1.06/L33 -> 0.15945259 | AJ33: =X33*1.06/M33 -> -0.13125292 | AK33: =AA33*1.06/N33 -> 0.080230187 | AM33: 45474 | AN33: =(Q33-Q32)*10000 -> 7702139.2 | AO33: =(R33-R32)*10000 -> 8161518.7 | AP33: =S33-S32 -> -61.429102
A34: 45505 | B34: ='GMV表-商品大类'!T37+B90 -> 688414.05 | C34: 77960.769 | D34: =B34+C34 -> 766374.82 | F34: 45505 | G34: ='毛利-收入组成'!AQ58 -> 19501.135 | H34: 17318463 | I34: =H34*1.06/10000 -> 1835.757 | J34: 6482.25 | K34: =R34*1.06 -> 163.1307 | L34: =G34-I34+J34-K34 -> 23984.497 | M34: 8433.5884 | N34: =L34+M34 -> 32418.085 | P34: 45505 | Q34: =31134501.7400001/10000 -> 3113.4502 | R34: =1538968.90630751/10000 -> 153.89689 | S34: 331.25371 | W34: =Q34-R34+S34 -> 3290.807 | X34: -916.40871 | AA34: =W34+X34 -> 2374.3983 | AC34: 45505 | AD34: =L34/B34 -> 0.03484022 | AE34: =M34/C34 -> 0.10817734 | AF34: =N34/D34 -> 0.042300562 | AH34: 45505 | AI34: =W34*1.06/L34 -> 0.14543792 | AJ34: =X34*1.06/M34 -> -0.11518148 | AK34: =AA34*1.06/N34 -> 0.077637595 | AM34: 45505 | AN34: =(Q34-Q33)*10000 -> 2887241.2 | AO34: =(R34-R33)*10000 -> -506579.89 | AP34: =S34-S33 -> -14.455746
A35: 45536 | B35: ='GMV表-商品大类'!T38+B91 -> 748878.18 | C35: 88041.301 | D35: =B35+C35 -> 836919.48 | F35: 45536 | G35: ='毛利-收入组成'!AQ59 -> 21218.058 | H35: 18819047 | I35: =H35*1.06/10000 -> 1994.819 | J35: 7755.0266 | K35: =R35*1.06 -> 163.32379 | L35: =G35-I35+J35-K35 -> 26814.942 | M35: 9463.4699 | N35: =L35+M35 -> 36278.412 | P35: 45536 | Q35: =36119147.9499995/10000 -> 3611.9148 | R35: =1540790.48672378/10000 -> 154.07905 | S35: 741.04432 | W35: =Q35-R35+S35 -> 4198.8801 | X35: -869.18632 | AA35: =W35+X35 -> 3329.6937 | AC35: 45536 | AD35: =L35/B35 -> 0.035806815 | AE35: =M35/C35 -> 0.10748898 | AF35: =N35/D35 -> 0.043347554 | AH35: 45536 | AI35: =W35*1.06/L35 -> 0.16598256 | AJ35: =X35*1.06/M35 -> -0.09735726 | AK35: =AA35*1.06/N35 -> 0.097288585 | AM35: 45536 | AN35: =(Q35-Q34)*10000 -> 4984646.2 | AO35: =(R35-R34)*10000 -> 1821.5804 | AP35: =S35-S34 -> 409.79062
A36: 45566 | B36: ='GMV表-商品大类'!T39+B92 -> 813677.8 | C36: 98052.555 | D36: =B36+C36 -> 911730.36 | F36: 45566 | G36: ='毛利-收入组成'!AQ60 -> 23238.672 | H36: 20057337 | I36: =H36*1.06/10000 -> 2126.0777 | J36: 8747.211 | K36: =R36*1.06 -> 259.79516 | L36: =G36-I36+J36-K36 -> 29600.01 | M36: 10528.913 | N36: =L36+M36 -> 40128.923 | P36: 45566 | Q36: =37390549.6399998/10000 -> 3739.055 | R36: =2450897.73613187/10000 -> 245.08977 | S36: 862.00698 | W36: =Q36-R36+S36 -> 4355.9722 | X36: -708.53098 | AA36: =W36+X36 -> 3647.4412 | AC36: 45566 | AD36: =L36/B36 -> 0.036378048 | AE36: =M36/C36 -> 0.1073803 | AF36: =N36/D36 -> 0.044014026 | AH36: 45566 | AI36: =W36*1.06/L36 -> 0.15599084 | AJ36: =X36*1.06/M36 -> -0.071331469 | AK36: =AA36*1.06/N36 -> 0.096346658 | AM36: 45566 | AN36: =(Q36-Q35)*10000 -> 1271401.7 | AO36: =(R36-R35)*10000 -> 910107.25 | AP36: =S36-S35 -> 120.96266
A37: 45597 | B37: ='GMV表-商品大类'!T40+B93 -> 882563.82 | C37: 108422.02 | D37: =B37+C37 -> 990985.84 | F37: 45597 | G37: ='毛利-收入组成'!AQ61 -> 25333.258 | H37: 19330114 | I37: =H37*1.06/10000 -> 2048.9921 | J37: 9819.6838 | K37: =R37*1.06 -> 46.743328 | L37: =G37-I37+J37-K37 -> 33057.207 | M37: 11601.376 | N37: =L37+M37 -> 44658.582 | P37: 45597 | Q37: =39282359.86/10000 -> 3928.236 | R37: =440974.792297676/10000 -> 44.097479 | S37: 1143.8451 | W37: =Q37-R37+S37 -> 5027.9836 | X37: -559.21109 | AA37: =W37+X37 -> 4468.7725 | AC37: 45597 | AD37: =L37/B37 -> 0.037455883 | AE37: =M37/C37 -> 0.10700202 | AF37: =N37/D37 -> 0.045064804 | AH37: 45597 | AI37: =W37*1.06/L37 -> 0.16122544 | AJ37: =X37*1.06/M37 -> -0.051094264 | AK37: =AA37*1.06/N37 -> 0.10606917 | AM37: 45597 | AN37: =(Q37-Q36)*10000 -> 1891810.2 | AO37: =(R37-R36)*10000 -> -2009922.9 | AP37: =S37-S36 -> 281.8381
A38: 45627 | B38: ='GMV表-商品大类'!T41+B94 -> 950049.95 | C38: 120473.04 | D38: =B38+C38 -> 1070523 | F38: 45627 | G38: ='毛利-收入组成'!AQ62 -> 28076.738 | H38: 20867964 | I38: =H38*1.06/10000 -> 2212.0042 | J38: 10371.365 | K38: =R38*1.06 -> -5.9447039 | L38: =G38-I38+J38-K38 -> 36242.044 | M38: 13216.352 | N38: =L38+M38 -> 49458.396 | P38: 45627 | Q38: =30259069.27/10000 -> 3025.9069 | R38: =-56082.1122934511/10000 -> -5.6082112 | S38: 799.44024 | W38: =Q38-R38+S38 -> 3830.9554 | X38: -191.65324 | AA38: =W38+X38 -> 3639.3021 | AC38: 45627 | AD38: =L38/B38 -> 0.038147514 | AE38: =M38/C38 -> 0.10970382 | AF38: =N38/D38 -> 0.046200219 | AH38: 45627 | AI38: =W38*1.06/L38 -> 0.11204701 | AJ38: =X38*1.06/M38 -> -0.015371294 | AK38: =AA38*1.06/N38 -> 0.077998087 | AM38: 45627 | AN38: =(Q38-Q37)*10000 -> -9023290.6 | AO38: =(R38-R37)*10000 -> -497056.9 | AP38: =S38-S37 -> -344.40485
A39: 45658 | B39: ='GMV表-商品大类'!T42+B95 -> 81145.313 | C39: 12379.049 | D39: =B39+C39 -> 93524.362 | F39: 45658 | G39: ='毛利-收入组成'!AQ63 -> 2087.8323 | H39: 1143231.9 | I39: =H39*1.06/10000 -> 121.18258 | J39: 2206.1643 | K39: =R39*1.06 -> -180.42851 | L39: =G39-I39+J39-K39 -> 4353.2426 | M39: 1241.357 | N39: =L39+M39 -> 5594.5996 | P39: 45658 | Q39: =2904342.15/10000 -> 290.43421 | R39: =-1702155.76979259/10000 -> -170.21558 | S39: 744.55228 | W39: =Q39-R39+S39 -> 1205.2021 | X39: 36.057099 | AA39: =W39+X39 -> 1241.2592 | AC39: 45658 | AD39: =L39/B39 -> 0.053647493 | AE39: =M39/C39 -> 0.10027887 | AF39: =N39/D39 -> 0.059819703 | AH39: 45658 | AI39: =W39*1.06/L39 -> 0.29346267 | AJ39: =X39*1.06/M39 -> 0.030789309 | AK39: =AA39*1.06/N39 -> 0.23517943 | AM39: 45658 | AN39: =Q39*10000 -> 2904342.1 | AO39: =R39*10000 -> -1702155.8 | AP39: =S39 -> 744.55228
A40: 45689 | B40: ='GMV表-商品大类'!T43+B96 -> 143043.59 | C40: 15190.545 | D40: =B40+C40 -> 158234.13 | F40: 45689 | G40: ='毛利-收入组成'!AQ64 -> 4874.4917 | H40: 2075803.2 | I40: =H40*1.06/10000 -> 220.03514 | J40: 2816.3186 | K40: =R40*1.06 -> -266.66127 | L40: =G40-I40+J40-K40 -> 7737.4364 | M40: 2372.3631 | N40: =L40+M40 -> 10109.8 | P40: 45689 | Q40: =14521013.01/10000 -> 1452.1013 | R40: =-2515672.38594156/10000 -> -251.56724 | S40: 771.90753 | W40: =Q40-R40+S40 -> 2475.5761 | X40: 26.999682 | AA40: =W40+X40 -> 2502.5757 | AC40: 45689 | AD40: =L40/B40 -> 0.054091459 | AE40: =M40/C40 -> 0.15617367 | AF40: =N40/D40 -> 0.063891395 | AH40: 45689 | AI40: =W40*1.06/L40 -> 0.33914471 | AJ40: =X40*1.06/M40 -> 0.012063778 | AK40: =AA40*1.06/N40 -> 0.26239198 | AM40: 45689 | AN40: =(Q40-Q39)*10000 -> 11616671 | AO40: =(R40-R39)*10000 -> -813516.62 | AP40: =(S40-S39) -> 27.355244
A41: 45717 | B41: ='GMV表-商品大类'!T44+B97 -> 210392.88 | C41: 27875.804 | D41: =B41+C41 -> 238268.68 | F41: 45717 | G41: ='毛利-收入组成'!AQ65 -> 7179.0228 | H41: 3524084.5 | I41: =H41*1.06/10000 -> 373.55295 | J41: 2586.5601 | K41: =R41*1.06 -> -308.93295 | L41: =G41-I41+J41-K41 -> 9700.9629 | M41: 3928.1127 | N41: =L41+M41 -> 13629.076 | P41: 45717 | Q41: =20008987.28/10000 -> 2000.8987 | R41: =-2914461.825889/10000 -> -291.44618 | S41: 362.73092 | W41: =Q41-R41+S41 -> 2655.0758 | X41: 351.18673 | AA41: =W41+X41 -> 3006.2626 | AC41: 45717 | AD41: =L41/B41 -> 0.046108799 | AE41: =M41/C41 -> 0.14091478 | AF41: =N41/D41 -> 0.057200449 | AH41: 45717 | AI41: =W41*1.06/L41 -> 0.29011351 | AJ41: =X41*1.06/M41 -> 0.094767631 | AK41: =AA41*1.06/N41 -> 0.23381177 | AM41: 45717 | AN41: =(Q41-Q40)*10000 -> 5487974.3 | AO41: =(R41-R40)*10000 -> -398789.44 | AP41: =(S41-S40) -> -409.17661
A42: 45748 | B42: ='GMV表-商品大类'!T45+B98 -> 278652.47 | C42: 42828.327 | D42: =B42+C42 -> 321480.8 | F42: 45748 | G42: ='毛利-收入组成'!AQ66 -> 8964.2412 | H42: 5009720.8 | I42: =H42*1.06/10000 -> 531.0304 | J42: 2814.7816 | K42: =R42*1.06 -> -345.53085 | L42: =G42-I42+J42-K42 -> 11593.523 | M42: 4813.5165 | N42: =L42+M42 -> 16407.04 | P42: 45748 | Q42: =19493947.13/10000 -> 1949.3947 | R42: =-3259725.031109/10000 -> -325.9725 | S42: 387.84907 | W42: =Q42-R42+S42 -> 2663.2163 | X42: 377.8072 | AA42: =W42+X42 -> 3041.0235 | AC42: 45748 | AD42: =L42/B42 -> 0.041605672 | AE42: =M42/C42 -> 0.11239095 | AF42: =N42/D42 -> 0.051035832 | AH42: 45748 | AI42: =W42*1.06/L42 -> 0.24349882 | AJ42: =X42*1.06/M42 -> 0.083198143 | AK42: =AA42*1.06/N42 -> 0.19646962 | AM42: 45748 | AN42: =(Q42-Q41)*10000 -> -515040.15 | AO42: =(R42-R41)*10000 -> -345263.21 | AP42: =(S42-S41) -> 25.118159
A43: 45778 | B43: ='GMV表-商品大类'!T46+B99 -> 356718.11 | C43: 54421.447 | D43: =B43+C43 -> 411139.56 | F43: 45778 | G43: ='毛利-收入组成'!AQ67 -> 11216.965 | H43: 6693457.8 | I43: =H43*1.06/10000 -> 709.50653 | J43: 3386.1268 | K43: =R43*1.06 -> -376.57449 | L43: =G43-I43+J43-K43 -> 14270.16 | M43: 6008.3066 | N43: =L43+M43 -> 20278.466 | P43: 45778 | Q43: =25241507.62/10000 -> 2524.1508 | R43: =-3552589.53177151/10000 -> -355.25895 | S43: 590.1693 | W43: =Q43-R43+S43 -> 3469.579 | X43: 527.56769 | AA43: =W43+X43 -> 3997.1467 | AC43: 45778 | AD43: =L43/B43 -> 0.040004024 | AE43: =M43/C43 -> 0.11040329 | AF43: =N43/D43 -> 0.049322586 | AH43: 45778 | AI43: =W43*1.06/L43 -> 0.25772338 | AJ43: =X43*1.06/M43 -> 0.09307477 | AK43: =AA43*1.06/N43 -> 0.20893964 | AM43: 45778 | AN43: =(Q43-Q42)*10000 -> 5747560.5 | AO43: =(R43-R42)*10000 -> -292864.5 | AP43: =(S43-S42) -> 202.32022
A44: 45809 | B44: ='GMV表-商品大类'!T47+B100 -> 424209.96 | C44: 65823.461 | D44: =B44+C44 -> 490033.43 | F44: 45809 | G44: ='毛利-收入组成'!AQ68 -> 14471.034 | H44: 8861461 | I44: =H44*1.06/10000 -> 939.31487 | J44: 3774.2073 | K44: =R44*1.06 -> -389.71032 | L44: =G44-I44+J44-K44 -> 17695.637 | M44: 7247.2979 | N44: =L44+M44 -> 24942.935 | P44: 45809 | Q44: =39303761.41/10000 -> 3930.3761 | R44: =-3676512.47794208/10000 -> -367.65125 | S44: 438.58718 | T44: 889.03 | U44: 220.17 | W44: =Q44-R44+S44-T44-U44 -> 3627.4146 | X44: 652.6366 | Y44: 137.23 | Z44: 34.31 | AA44: =W44+(X44-Y44-Z44) -> 4108.5112 | AC44: 45809 | AD44: =L44/B44 -> 0.041714335 | AE44: =M44/C44 -> 0.11010205 | AF44: =N44/D44 -> 0.050900476 | AH44: 45809 | AI44: =W44*1.06/L44 -> 0.21728856 | AJ44: =(X44-Y44-Z44)*1.06/M44 -> 0.070365866 | AK44: =AA44*1.06/N44 -> 0.17459942 | AM44: 45809 | AN44: =(Q44-Q43)*10000 -> 14062254 | AO44: =(R44-R43)*10000 -> -123922.95 | AP44: =(S44-S43) -> -151.58211
A45: 45839 | B45: ='GMV表-商品大类'!T48+B101 -> 493155.86 | C45: 77849.085 | D45: =B45+C45 -> 571004.94 | F45: 45839 | G45: ='毛利-收入组成'!AQ69 -> 16659.428 | H45: 10138585 | I45: =H45*1.06/10000 -> 1074.69 | J45: 4049.4751 | K45: =R45*1.06 -> -414.43103 | L45: =G45-I45+J45-K45 -> 20048.644 | M45: 8403.0147 | N45: =L45+M45 -> 28451.658 | P45: 45839 | Q45: =43474589.87/10000 -> 4347.459 | R45: =-3909726.72587872/10000 -> -390.97267 | S45: 289.7061 | W45: =Q45-R45+S45-T45-U45 -> 5028.1378 | X45: 881.78795 | AA45: =W45+X45 -> 5909.9257 | AC45: 45839 | AD45: =L45/B45 -> 0.040653768 | AE45: =M45/C45 -> 0.1079398 | AF45: =N45/D45 -> 0.049827342 | AH45: 45839 | AI45: =W45*1.06/L45 -> 0.26584472 | AJ45: =X45*1.06/M45 -> 0.11123332 | AK45: =AA45*1.06/N45 -> 0.22018123 | AM45: 45839 | AN45: =(Q45-Q44)*10000 -> 4170828.5 | AO45: =(R45-R44)*10000 -> -233214.25 | AP45: =(S45-S44) -> -148.88109
A46: 45870 | B46: ='GMV表-商品大类'!T49+B102 -> 571045.82 | C46: 88826.487 | D46: =B46+C46 -> 659872.31 | F46: 45870 | G46: ='毛利-收入组成'!AQ70 -> 18922.014 | H46: 12514411 | I46: =H46*1.06/10000 -> 1326.5276 | J46: 4472.722 | K46: =R46*1.06 -> -538.20253 | L46: =G46-I46+J46-K46 -> 22606.411 | M46: 9484.7749 | N46: =L46+M46 -> 32091.186 | P46: 45870 | Q46: =41156976.78/10000 -> 4115.6977 | R46: =-5077382.37443346/10000 -> -507.73824 | S46: 395.01378 | W46: =Q46-R46+S46-T46-U46 -> 5018.4497 | X46: 880.05428 | AA46: =W46+X46 -> 5898.504 | AC46: 45870 | AD46: =L46/B46 -> 0.039587736 | AE46: =M46/C46 -> 0.10677868 | AF46: =N46/D46 -> 0.048632418 | AH46: 45870 | AI46: =W46*1.06/L46 -> 0.23531186 | AJ46: =X46*1.06/M46 -> 0.098353155 | AK46: =AA46*1.06/N46 -> 0.19483275 | AM46: 45870 | AN46: =(Q46-Q45)*10000 -> -2317613.1 | AO46: =(R46-R45)*10000 -> -1167655.6 | AP46: =(S46-S45) -> 105.30768
A47: 45901 | B47: ='GMV表-商品大类'!T50+B103 -> 655764.12 | C47: 108961.5 | D47: =B47+C47 -> 764725.62 | F47: 45901 | G47: ='毛利-收入组成'!AQ71 -> 22196.954 | H47: 14113155 | I47: =H47*1.06/10000 -> 1495.9944 | J47: 5120.97 | K47: =R47*1.06 -> -515.36957 | L47: =G47-I47+J47-K47 -> 26337.299 | M47: 10421.544 | N47: =L47+M47 -> 36758.843 | P47: 45901 | Q47: =60046102.59/10000 -> 6004.6103 | R47: =-4861977.09546633/10000 -> -486.19771 | S47: 408.07795 | W47: =Q47-R47+S47-T47-U47 -> 6898.8859 | X47: 892.69028 | AA47: =W47+X47 -> 7791.5762 | AC47: 45901 | AD47: =L47/B47 -> 0.040162763 | AE47: =M47/C47 -> 0.095644277 | AF47: =N47/D47 -> 0.048068015 | AH47: 45901 | AI47: =W47*1.06/L47 -> 0.27766018 | AJ47: =X47*1.06/M47 -> 0.090797648 | AK47: =AA47*1.06/N47 -> 0.22468256 | AM47: 45901 | AN47: =(Q47-Q46)*10000 -> 18889126 | AO47: =(R47-R46)*10000 -> 215405.28 | AP47: =(S47-S46) -> 13.064176
A48: 45931 | B48: ='GMV表-商品大类'!T51+B104 -> 725220.65 | C48: 120596.57 | D48: =B48+C48 -> 845817.21 | F48: 45931 | G48: ='毛利-收入组成'!AQ72 -> 24609.144 | H48: 16310003 | I48: =H48*1.06/10000 -> 1728.8603 | J48: 5696.6165 | K48: =R48*1.06 -> -567.02664 | L48: =G48-I48+J48-K48 -> 29143.926 | M48: 11357.621 | N48: =L48+M48 -> 40501.547 | P48: 45931 | Q48: =63459874.51/10000 -> 6345.9875 | R48: =-5349307.95072856/10000 -> -534.9308 | S48: 603.31222 | W48: =Q48-R48+S48-T48-U48 -> 7484.2305 | X48: 1026.2939 | AA48: =W48+X48 -> 8510.5244 | AC48: 45931 | AD48: =L48/B48 -> 0.040186289 | AE48: =M48/C48 -> 0.09417864 | AF48: =N48/D48 -> 0.047884515 | AH48: 45931 | AI48: =W48*1.06/L48 -> 0.27221055 | AJ48: =X48*1.06/M48 -> 0.095783403 | AK48: =AA48*1.06/N48 -> 0.22273608 | AM48: 45931
A49: 45962 | B49: ='GMV表-商品大类'!T52+B105 -> 798077.96 | C49: 136314.26 | D49: =B49+C49 -> 934392.22 | F49: 45962 | G49: ='毛利-收入组成'!AQ73 -> 27613.828 | H49: 18481225 | I49: =H49*1.06/10000 -> 1959.0099 | J49: 5982.7966 | K49: =R49*1.06 -> -640.59028 | L49: =G49-I49+J49-K49 -> 32278.205 | M49: 12838.799 | N49: =L49+M49 -> 45117.004 | P49: 45962 | Q49: =66195787.6573616/10000 -> 6619.5788 | R49: =-6043304.54639876/10000 -> -604.33045 | S49: =447.8839836+249.274506 -> 697.15849 | V49: 870 | W49: =Q49-R49+S49-T49-U49+V49 -> 8791.0677 | X49: 1091.82 | AA49: =W49+X49 -> 9882.8877 | AC49: 45962 | AD49: =L49/B49 -> 0.040444927 | AE49: =M49/C49 -> 0.094185294 | AF49: =N49/D49 -> 0.048284867 | AH49: 45962 | AI49: =W49*1.06/L49 -> 0.28869424 | AJ49: =X49*1.06/M49 -> 0.09014311 | AK49: =AA49*1.06/N49 -> 0.23219319 | AM49: 45962
A50: 45992 | B50: ='GMV表-商品大类'!T53+B106 -> 890519.1 | C50: 154056.06 | D50: =B50+C50 -> 1044575.2 | F50: 45992 | G50: ='毛利-收入组成'!AQ74 -> 31162.322 | H50: 20453484 | I50: =H50*1.06/10000 -> 2168.0693 | J50: 6846.9239 | K50: =R50*1.06 -> -658.42067 | L50: =G50-I50+J50-K50 -> 36499.598 | M50: 13235.421 | N50: =L50+M50 -> 49735.019 | P50: 45992 | Q50: =57603018.93/10000 -> 5760.3019 | R50: =-6211515.78599174/10000 -> -621.15158 | S50: =547.4222716+249.274506 -> 796.69678 | V50: 870 | W50: =Q50-R50+S50-T50-U50+V50 -> 8048.1502 | X50: 156.39812 | AA50: =W50+X50 -> 8204.5484 | AC50: 45992 | AD50: =L50/B50 -> 0.040986878 | AE50: =M50/C50 -> 0.08591302 | AF50: =N50/D50 -> 0.047612677 | AH50: 45992 | AI50: =W50*1.06/L50 -> 0.23372968 | AJ50: =X50*1.06/M50 -> 0.012525631 | AK50: =AA50*1.06/N50 -> 0.17486313 | AM50: 45992
A52: 占比 | B52: =B50/D50 -> 0.85251797 | C52: =C50/D50 -> 0.14748203 | H52: =G53-I53 -> 3129.519 | I52: =G53-I53-K53+J53 -> 257.55369 | L52: =L50/N50 -> 0.73388124 | M52: =M50/N50 -> 0.26611876 | W52: =W50/AA50 -> 0.98093763 | X52: =X50/AA50 -> 0.019062368 | AN52: =SUM(AN39:AN50) -> 60046103 | AO52: =SUM(AO39:AO50) -> -4861977.1 | AP52: =SUM(AP39:AP50) -> 408.07795
A53: 同期变动 | B53: =B50-B38 -> -59530.852 | C53: =C50-C38 -> 33583.023 | D53: =D50-D38 -> -25947.828 | G53: =G50-G38 -> 3085.5841 | H53: =H50-H38 -> -414480.36 | I53: =I50-I38 -> -43.934918 | J53: =J50-J38 -> -3524.4413 | K53: =K50-K38 -> -652.47597 | L53: =L50-L38 -> 257.55369 | M53: =M50-M38 -> 19.069562 | N53: =N50-N38 -> 276.62325 | Q53: =Q50-Q38 -> 2734.395 | R53: =R50-R38 -> -615.54337 | S53: =S50-S38 -> -2.7434594 | T53: =T50-T38 -> 0 | U53: =U50-U38 -> 0 | V53: =V50-V38 -> 870 | W53: =W50-W38 -> 4217.1949 | X53: =X50-X38 -> 348.05136 | ... AA53: =AA50-AA38 -> 4565.2462 | AP53: =AP52-S47 -> 0
A54: 变动比例 | B54: =B53/B38 -> -0.06266076 | C54: =C53/C38 -> 0.27875966 | D54: =D53/D38 -> -0.02423846 | G54: =G53/G38 -> 0.10989824 | H54: =H53/H38 -> -0.019862041 | I54: =I53/I38 -> -0.019862041 | J54: =J53/J38 -> -0.33982424 | K54: =K53/K38 -> 109.75752 | L54: =L53/L38 -> 0.0071064891 | M54: =M53/M38 -> 0.0014428764 | N54: =N53/N38 -> 0.0055930494 | R54: =Q53-R53 -> 3349.9383 | S54: =Q53-R53+S53 -> 3347.1949 | W54: =W53/W38 -> 1.1008207 | X54: =X53/X38 -> -1.8160474 | AA54: =AA53/AA38 -> 1.254429
K55: =G53-I53-K53 -> 3781.995 | L55: =L53-J53 -> 3781.995
A56: 体内项目--衍生公司 | B56: GMV | C56: 收入（差额）-含税金额 | D56: 收入（差额）-不含税金额 | E56: 利润
A57: 44530 | B57: 199.78866 | C57: 51.885882 | D57: 48.948945 | E57: 38.006484
A58: 44561 | B58: 336.97535 | C58: 99.150341 | D58: 93.538058 | E58: 70.25
A59: 44562 | B59: 1374.1753 | C59: 708.69541 | D59: 668.58057 | E59: 187.75761
A60: 44593 | B60: 1994.7 | C60: 948.85 | D60: 895.14151 | E60: 102.11
A61: 44621 | B61: 2843.8 | C61: 1330.59 | D61: 1255.2736 | E61: 44.96
A62: 44652 | B62: 4082.235 | C62: 1618.1164 | D62: 1527.99 | E62: -150.02026
A63: 44682 | B63: 6922.9577 | C63: 1960.5567 | D63: 1849.5818 | E63: -321.3635
A64: 44713 | B64: 6843.5655 | C64: 2399.588 | D64: 2263.7623 | E64: -515.08559
A65: 44743 | B65: 10499.791 | C65: 2807.8764 | D65: 2648.94 | E65: -805.11
A66: 44774 | B66: 12096.444 | C66: 3477.86 | D66: 3281 | E66: -869.63
A67: 44805 | B67: 13434.896 | C67: 4614.0846 | D67: 4352.91 | E67: -850.89
A68: 44835 | B68: 18333.835 | C68: 5260.2818 | D68: 4962.53 | E68: -799.27
... A106: 45992 | B106: 98835.586 | C106: 6846.9239 | D106: 5841.4955 | E106: 547.42227
A108: 45962 | E108: 249.27451 | F108: 上海灵盟处置收益

Sheet 投资公司
A1: 2025年
A2: 类别 | B2: 葫芦藤体内项目毛利 | C2: 累计净利润 | D2: 1月利润 | E2: 2月利润 | F2: 3月利润 | G2: 4月利润 | H2: 5月利润 | I2: 6月利润 | J2: 7月利润 | K2: 8月利润 | L2: 9月利润 | M2: 10月利润 | N2: 11月利润 | O2: 12月利润
A3: 1、手游 | B3: 游戏直播 | C3: =SUM(D3:O3) -> 5.464 | I3: 7.059 | J3: =-27.65-I3 -> -34.709 | K3: -0.037 | L3: 31.138 | M3: 2.012 | N3: 0 | O3: 0.001
A4: 2、网游 | C4: =SUM(D4:O4) -> 0 | M4: 0
A5: 3、通信 | C5: =SUM(D5:O5) -> 0 | M5: 0
A6: 4、网娱 | B6: 渠道线&游戏电商&直播中心 | C6: =SUM(D6:O6) -> 418.85566 | D6: 77.701 | E6: 6.228 | F6: 106.762 | G6: 78.746 | H6: 76.203 | I6: =281.088987-7.059-(38.674+377.647) -> -142.29101 | J6: =232.934-SUM(D6:I6) -> 29.585013 | K6: 132.251 | L6: 76.318 | M6: 83.93 | N6: -147.993 | O6: =(63.035-1217774/1.06/10000)+17.31+75.955 -> 41.41566
A7: 5、生活服务 | B7: 客户发展&灵活用工项目-推广 | C7: =SUM(D7:O7) -> 671.72952 | I7: =38.674+377.647 -> 416.321 | J7: =461.05-I7 -> 44.729 | K7: 64.544117 | L7: 29.013872 | M7: 84.95648 | N7: 7.982971 | O7: =11.968+12.21408 -> 24.18208
A8: 合计 | B8: =SUM(B3:B7) -> 0 | C8: =SUM(C3:C7) -> 1096.0492 | D8: =SUM(D3:D7) -> 77.701 | E8: =SUM(E3:E7) -> 6.228 | F8: =SUM(F3:F7) -> 106.762 | G8: =SUM(G3:G7) -> 78.746 | H8: =SUM(H3:H7) -> 76.203 | I8: =SUM(I3:I7) -> 281.08899 | ... O8: =SUM(O3:O7) -> 65.59874
A9: 含税金额 | C9: =C8*1.06 -> 1161.8121 | D9: =D8*1.06 -> 82.36306 | E9: =E8*1.06 -> 6.60168 | F9: =F8*1.06 -> 113.16772 | G9: =G8*1.06 -> 83.47076 | H9: =H8*1.06 -> 80.77518 | I9: =I8*1.06 -> 297.95433 | J9: =J8*1.06 -> 41.981314 | ... O9: =O8*1.06 -> 69.534665
A11: 2024年
A12: 类别 | B12: 调整博宽&黄石福桃等渠道电商毛利 | C12: 累计净利润 | D12: 1月利润 | E12: 2月利润 | F12: 3月利润 | G12: 4月利润 | H12: 5月利润 | I12: 6月利润 | J12: 7月利润 | K12: 8月利润 | L12: 9月利润 | M12: 10月利润 | N12: 11月利润 | O12: 12月利润
A13: 1、手游
A14: 2、网游
A15: 3、通信
A16: 4、网娱 | C16: =SUM(D16:O16) -> 366.107 | D16: =377.983-2659414.53/10000 -> 112.04155 | E16: =191.57-3869946.72/10000 -> -195.42467 | F16: =-429.26--5370695.59/10000 -> 107.80956 | G16: =-29.559-2165911.16/10000 -> -246.15012 | H16: 96.61 | I16: -3.44 | J16: 191.09 | K16: 71.15 | L16: 20.14 | M16: 57.43 | N16: 209.28868 | O16: -54.438
A17: 5、生活服务
A18: 合计 | B18: =SUM(B13:B17) -> 0 | C18: =SUM(C13:C17) -> 366.107 | D18: =SUM(D13:D17) -> 112.04155 | E18: =SUM(E13:E17) -> -195.42467 | F18: =SUM(F13:F17) -> 107.80956 | G18: =SUM(G13:G17) -> -246.15012 | H18: =SUM(H13:H17) -> 96.61 | I18: =SUM(I13:I17) -> -3.44 | ... O18: =SUM(O13:O17) -> -54.438
A19: 含税金额 | C19: =C18*1.06 -> 388.07342 | D19: =D18*1.06 -> 118.76404 | E19: =E18*1.06 -> -207.15015 | F19: =F18*1.06 -> 114.27813 | G19: =G18*1.06 -> -260.91912 | H19: =H18*1.06 -> 102.4066 | I19: =I18*1.06 -> -3.6464 | J19: =J18*1.06 -> 202.5554 | ... O19: =O18*1.06 -> -57.70428
A21: 2023年
A22: 类别 | B22: 调整博宽&黄石福桃等渠道电商毛利 | C22: 累计净利润 | D22: 1月利润 | E22: 2月利润 | F22: 3月利润 | G22: 4月利润 | H22: 5月利润 | I22: 6月利润 | J22: 7月利润 | K22: 8月利润 | L22: 9月利润 | M22: 10月利润 | N22: 11月利润 | O22: 12月利润
A23: 1、手游
A24: 2、网游
A25: 3、通信
A26: 4、网娱 | C26: =SUM(D26:O26) -> 219.71 | D26: 98.863 | E26: 88.266 | F26: 112.98 | G26: -111.401 | H26: -41.707 | I26: -100.897 | J26: 160.729 | K26: 125.174 | L26: -208.57 | M26: 179.757 | N26: 53.982 | O26: -137.466
A27: 5、生活服务
A28: 合计 | B28: =SUM(B23:B27) -> 0 | C28: =SUM(C23:C27) -> 219.71 | F28: =SUM(F23:F27) -> 112.98 | G28: =SUM(G23:G27) -> -111.401 | H28: =SUM(H23:H27) -> -41.707 | I28: =SUM(I23:I27) -> -100.897 | J28: =SUM(J23:J27) -> 160.729 | K28: =SUM(K23:K27) -> 125.174 | L28: =SUM(L23:L27) -> -208.57 | M28: =SUM(M23:M27) -> 179.757 | ... O28: =SUM(O23:O27) -> -137.466
A29: 含税金额 | C29: =C28*1.06 -> 232.8926 | D29: =D28*1.06 -> 0 | E29: =E28*1.06 -> 0 | F29: =F28*1.06 -> 119.7588 | G29: =G28*1.06 -> -118.08506 | H29: =H28*1.06 -> -44.20942 | I29: =I28*1.06 -> -106.95082 | J29: =J28*1.06 -> 170.37274 | ... O29: =O28*1.06 -> -145.71396

Sheet GMV销售额波动分析（分月、年）
A1: 2025年 | B1: SP0001-网游 | C1: SP0005-手游 | D1: SP0002-通信 | E1: SP0003-网娱 | F1: SP0004-卡劵 | G1: SP0006-生活服务 | H1: 总计（含税） | I1: 体内公司GMV | J1: 月份 | K1: 2025年GMV | L1: 2024年GMV | M1: 同期增长
A2: 1月 | B2: 45102810 | C2: 75000597 | D2: 9435812.5 | E2: 2.0356185e+08 | F2: 3.6554639e+08 | G2: 277292.49 | H2: =SUM(B2:G2) -> 6.9892476e+08 | I2: =H2/10000-GMV销售平台占比!B17 -> 6.9849193e-10 | J2: 1月 | K2: =H2/100000000 -> 6.9892476 | L2: =H17/100000000 -> 8.3841662 | M2: =(K2-L2)/L2 -> -0.16637536 | N2: =K2-L2 -> -1.3949187
A3: 2月 | B3: 29914547 | C3: 33284884 | D3: 12224513 | E3: 1.8650532e+08 | F3: 2.8944267e+08 | G3: 697463.75 | H3: =SUM(B3:G3) -> 5.5206939e+08 | J3: 2月 | K3: =H3/100000000 -> 5.5206939 | L3: =H18/100000000 -> 7.6218049 | M3: =(K3-L3)/L3 -> -0.27567105
A4: 3月 | B4: 23250822 | C4: 38931285 | D4: 4582458.6 | E4: 1.8891607e+08 | F4: 4.1025231e+08 | G4: 50935.907 | H4: =SUM(B4:G4) -> 6.6598388e+08 | J4: 3月 | K4: =H4/100000000 -> 6.6598388 | L4: =H19/100000000 -> 6.6832889 | M4: =(K4-L4)/L4 -> -0.0035087704
A5: 4月 | B5: 26883010 | C5: 46615668 | D5: 3360143.8 | E5: 1.7304789e+08 | F5: 3.5350825e+08 | G5: 45091.202 | H5: =SUM(B5:G5) -> 6.0346005e+08 | J5: 4月 | K5: =H5/100000000 -> 6.0346005 | L5: =H20/100000000 -> 5.0345297 | M5: =(K5-L5)/L5 -> 0.19864235
A6: 5月 | B6: 37315216 | C6: 1.0025681e+08 | D6: 3366603.9 | E6: 1.7290566e+08 | F6: 2.90837e+08 | G6: 36996.619 | H6: =SUM(B6:G6) -> 6.0471829e+08 | J6: 5月 | K6: =H6/100000000 -> 6.0471829 | L6: =H21/100000000 -> 7.0552966 | M6: =(K6-L6)/L6 -> -0.1428875
A7: 6月 | B7: 44748189 | C7: 41902247 | D7: 2880591.8 | E7: 1.2474516e+08 | F7: 3.5477031e+08 | G7: 93346.506 | H7: =SUM(B7:G7) -> 5.6913985e+08 | J7: 6月 | K7: =H7/100000000 -> 5.6913985 | L7: =H22/100000000 -> 8.3802748 | M7: =(K7-L7)/L7 -> -0.32085777
A8: 7月 | B8: 40140017 | C8: 47381046 | D8: 2957178.4 | E8: 75125965 | F8: 4.6261523e+08 | G8: 2103107.7 | H8: =SUM(B8:G8) -> 6.3032255e+08 | J8: 7月 | K8: =H8/100000000 -> 6.3032255 | L8: =H23/100000000 -> 8.2004978 | M8: =(K8-L8)/L8 -> -0.23136063
A9: 8月 | B9: 38764101 | C9: 57682762 | D9: 3647053.4 | E9: 84315661 | F9: 5.2488302e+08 | G9: 1186092.5 | H9: =SUM(B9:G9) -> 7.1047869e+08 | I9: =H9/10000-'GMV表-商品大类'!F49 -> 0 | J9: 8月 | K9: =H9/100000000 -> 7.1047869 | L9: =H24/100000000 -> 7.5165771 | M9: =(K9-L9)/L9 -> -0.054784265
A10: 9月 | B10: 28150837 | C10: 1.0835199e+08 | D10: 3315332.7 | E10: 87118571 | F10: 5.0121265e+08 | G10: 3348273.6 | H10: =SUM(B10:G10) -> 7.3149766e+08 | J10: 9月 | K10: =H10/100000000 -> 7.3149766 | L10: =H25/100000000 -> 5.2618104 | M10: =(K10-L10)/L10 -> 0.39020146
A11: 10月 | B11: 27253234 | C11: 1.0098886e+08 | D11: 3440109.1 | E11: 92681238 | F11: 3.9677189e+08 | G11: 529975.24 | H11: =SUM(B11:G11) -> 6.2166531e+08 | J11: 10月 | K11: =H11/100000000 -> 6.2166531 | L11: =H26/100000000 -> 5.901137 | M11: =(K11-L11)/L11 -> 0.053466991
A12: 11月 | B12: 36611701 | C12: 1.0402716e+08 | D12: 3413736 | E12: 1.0587371e+08 | F12: 4.0635999e+08 | G12: 186184.83 | H12: =SUM(B12:G12) -> 6.5647248e+08 | J12: 11月 | K12: =H12/100000000 -> 6.5647248 | L12: =H27/100000000 -> 6.1812962 | M12: =(K12-L12)/L12 -> 0.062030461
A13: 12月 | B13: 35827984 | C13: =101631883.7308+11608600.18-11608600.18 -> 1.0163188e+08 | D13: 3342888.6 | E13: 1.1975211e+08 | F13: 6.1052145e+08 | G13: 1025884.7 | H13: =SUM(B13:G13) -> 8.721022e+08 | J13: 12月 | K13: =H13/100000000 -> 8.721022 | L13: =H28/100000000 -> 6.0199264 | M13: =(K13-L13)/L13 -> 0.44869247
A14: 合计 | B14: =SUM(B2:B13) -> 4.1396247e+08 | C14: =SUM(C2:C13) -> 8.560552e+08 | D14: =SUM(D2:D13) -> 55966421 | E14: =SUM(E2:E13) -> 1.6145492e+09 | F14: =SUM(F2:F13) -> 4.9667212e+09 | G14: =SUM(G2:G13) -> 9580645.1 | H14: =SUM(H2:H13) -> 7.9168351e+09 | J14: 合计（亿元） | K14: =SUM(K2:K13) -> 79.168351 | L14: =SUM(L2:L13) -> 82.240606 | M14: =(K14-L14)/L14 -> -0.037356911 | N14: =K14-L14 -> -3.072255 | O14: =N14/L14 -> -0.037356911
J15: 累计数贴PPT37
A16: 2024年 | B16: SP0001-网游 | C16: SP0005-手游 | D16: SP0002-通信 | E16: SP0003-网娱 | F16: SP0004-卡劵 | G16: SP0006-生活服务 | H16: 总计（含税） | J16: 商品大类 | K16: 2024年 | L16: 2023年 | M16: 变动额 | N16: 变动率
A17: 1月 | B17: 1.6394352e+08 | C17: 72069322 | D17: 57651169 | E17: 2.2038104e+08 | F17: 3.2436856e+08 | G17: 3015.47 | H17: 8.3841662e+08 | J17: 网游 | K17: =B14/10000 -> 41396.247 | L17: =SUM(B32:B43)/10000 -> 204213.4 | M17: =K17-L17 -> -162817.16 | N17: =M17/L17 -> -0.79728928 | O17: =K17+K18 -> 127001.77 | P17: =L17+L18 -> 288229.3
A18: 2月 | B18: 1.2902059e+08 | C18: 78670926 | D18: 51869185 | E18: 2.0630623e+08 | F18: 2.9632854e+08 | G18: -14984.47 | H18: 7.6218049e+08 | J18: 手游 | K18: =C14/10000 -> 85605.52 | L18: =SUM(C32:C43)/10000 -> 84015.899 | M18: =K18-L18 -> 1589.6209 | N18: =M18/L18 -> 0.018920477 | P18: =(O17-P17)/P17 -> -0.55937247
A19: 3月 | B19: 40868843 | C19: 40313324 | D19: 61579069 | E19: 2.4007575e+08 | F19: 2.8386047e+08 | G19: 1631435.1 | H19: 6.6832889e+08 | J19: 通信 | K19: =D14/10000 -> 5596.6421 | L19: =SUM(D32:D43)/10000 -> 212342.83 | M19: =K19-L19 -> -206746.19 | N19: =M19/L19 -> -0.97364337
A20: 4月 | B20: 36836160 | C20: 30957288 | D20: 31064079 | E20: 2.3861802e+08 | F20: 1.659334e+08 | G20: 44022.467 | H20: 5.0345297e+08 | J20: 网娱 | K20: =E14/10000 -> 161454.92 | L20: =SUM(E32:E43)/10000 -> 505603.59 | M20: =K20-L20 -> -344148.67 | N20: =M20/L20 -> -0.68066896
A21: 5月 | B21: 36434632 | C21: 80871997 | D21: 23162770 | E21: 2.994851e+08 | F21: 2.6579687e+08 | G21: -221706.87 | H21: 7.0552966e+08 | J21: 生活服务 | K21: =(F14+G14)/10000 -> 497630.18 | L21: =SUM(F32:G43)/10000 -> 554277.85 | M21: =K21-L21 -> -56647.665 | N21: =M21/L21 -> -0.10220085
A22: 6月 | B22: 77715917 | C22: 92084688 | D22: 14168628 | E22: 3.4860498e+08 | F22: 3.052408e+08 | G22: 212456.67 | H22: 8.3802748e+08 | J22: 总计（万元） | K22: =SUM(K17:K21) -> 791683.51 | L22: =SUM(L17:L21) -> 1560453.6 | M22: =SUM(M17:M21) -> -768770.07 | N22: =M22/L22 -> -0.49265808
A23: 7月 | B23: 83089797 | C23: 1.3250714e+08 | D23: 14913498 | E23: 2.4546108e+08 | F23: 3.3679378e+08 | G23: 7284483.8 | H23: 8.2004978e+08
A24: 8月 | B24: 49122371 | C24: 66704878 | D24: 25481143 | E24: 3.0002115e+08 | F24: 3.0906987e+08 | G24: 1258291.4 | H24: 7.5165771e+08
A25: 9月 | B25: 29245115 | C25: 48236433 | D25: 12906205 | E25: 2.2928796e+08 | F25: 2.0652896e+08 | G25: -23631.13 | H25: 5.2618104e+08
A26: 10月 | B26: 30810565 | C26: 55595035 | D26: 9471714.6 | E26: 2.3255981e+08 | F26: 2.6141187e+08 | G26: 264707.59 | H26: 5.901137e+08
A27: 11月 | B27: 24768660 | C27: 61722499 | D27: 6958838.9 | E27: 2.5892265e+08 | F27: 2.656238e+08 | G27: 133170.18 | H27: 6.1812962e+08
A28: 12月 | B28: 17633355 | C28: 34982091 | D28: 6161395.9 | E28: 2.6412947e+08 | F28: 2.7877715e+08 | G28: 309180.8 | H28: 6.0199264e+08
A29: 合计 | B29: =SUM(B17:B28) -> 7.1948953e+08 | C29: =SUM(C17:C28) -> 7.9471562e+08 | D29: =SUM(D17:D28) -> 3.153877e+08 | E29: =SUM(E17:E28) -> 3.0838533e+09 | F29: =SUM(F17:F28) -> 3.2997341e+09 | G29: =SUM(G17:G28) -> 10880441 | H29: =SUM(H17:H28) -> 8.2240606e+09
A31: 2023年 | B31: SP0001-网游 | C31: SP0005-手游 | D31: SP0002-通信 | E31: SP0003-网娱 | F31: SP0004-卡劵 | G31: SP0006-生活服务 | H31: 总计（含税）
A32: 1月 | B32: 1.0755749e+08 | C32: 1.2230208e+08 | D32: 2.927875e+08 | E32: 4.8836984e+08 | F32: 3.2916948e+08 | G32: 5629439.6 | H32: =SUM(B32:G32) -> 1.3458158e+09
A33: 2月 | B33: 86491645 | C33: 48095782 | D33: 3.841738e+08 | E33: 4.5017964e+08 | F33: 3.5004372e+08 | G33: 7076.29 | H33: =SUM(B33:G33) -> 1.3189917e+09
A34: 3月 | B34: 1.088094e+08 | C34: 67960161 | D34: 4.0696017e+08 | E34: =481032330.11-13500000 -> 4.6753233e+08 | F34: 4.8239142e+08 | G34: -551189.73 | H34: =SUM(B34:G34) -> 1.5331023e+09
A35: 4月 | B35: 2.050828e+08 | C35: 45919678 | D35: 1.4908958e+08 | E35: =398767570-12500000 -> 386267570 | F35: 4.6616905e+08 | G35: 4267.31 | H35: =SUM(B35:G35) -> 1.2525329e+09
A36: 5月 | B36: 3.3263003e+08 | C36: 1.0672384e+08 | D36: 1.4554824e+08 | E36: 3.4806915e+08 | F36: 5.457605e+08 | G36: -17436.15 | H36: =SUM(B36:G36) -> 1.4787143e+09
A37: 6月 | B37: 2.8460326e+08 | C37: 38830643 | D37: 1.8696408e+08 | E37: 4.0582857e+08 | F37: 6.5744036e+08 | G37: 2100.07 | H37: =SUM(B37:G37) -> 1.573669e+09
A38: 7月 | B38: 2.1237629e+08 | C38: 68821147 | D38: 1.2591962e+08 | E38: 3.5418136e+08 | F38: 5.528262e+08 | G38: 10513.11 | H38: =SUM(B38:G38) -> 1.3141351e+09
A39: 8月 | B39: 2.0523625e+08 | C39: 1.1420637e+08 | D39: 1.234218e+08 | E39: 4.1823418e+08 | F39: 6.1102003e+08 | G39: 2183.91 | H39: =SUM(B39:G39) -> 1.4721208e+09
A40: 9月 | B40: 2.1353486e+08 | C40: 51971549 | D40: 97829884 | E40: 3.9707166e+08 | F40: 4.9935928e+08 | G40: 6539.06 | H40: =SUM(B40:G40) -> 1.2597738e+09
A41: 10月 | B41: 89061955 | C41: 36377220 | D41: 72310873 | E41: 3.9956302e+08 | F41: 3.6598322e+08 | G41: -70181.51 | H41: =SUM(B41:G41) -> 9.632261e+08
A42: 11月 | B42: 1.0502672e+08 | C42: 94398013 | D42: 80242668 | E42: =538146990.5-16000000 -> 5.2214699e+08 | F42: 3.4343478e+08 | G42: -71757.87 | H42: =SUM(B42:G42) -> 1.1451774e+09
A43: 12月 | B43: 91723338 | C43: 44552509 | D43: 58180122 | E43: 4.1859163e+08 | F43: 3.3423897e+08 | G43: -10103.21 | H43: =SUM(B43:G43) -> 9.4727646e+08
A44: 合计 | B44: =SUM(B32:B43) -> 2.042134e+09 | C44: =SUM(C32:C43) -> 8.4015899e+08 | D44: =SUM(D32:D43) -> 2.1234283e+09 | E44: =SUM(E32:E43) -> 5.0560359e+09 | F44: =SUM(F32:F43) -> 5.537837e+09 | G44: =SUM(G32:G43) -> 4941450.9 | H44: =SUM(H32:H43) -> 1.5604536e+10
A46: 2022年 | B46: SP0001-网游 | C46: SP0005-手游 | D46: SP0002-通信 | E46: SP0003-网娱 | F46: SP0004-卡劵 | G46: SP0006-生活服务 | H46: 总计（含税）
A47: 1月 | B47: 1.0628656e+08 | C47: 49334662 | D47: 4.1149968e+08 | E47: 3.2432045e+08 | F47: 1.7626142e+08 | G47: 894328.11 | H47: =SUM(B47:G47) -> 1.0685971e+09
A48: 2月 | B48: 81731964 | C48: 59033084 | D48: 3.1152277e+08 | E48: 2.5233803e+08 | F48: 1.5005242e+08 | G48: 856069.92 | H48: =SUM(B48:G48) -> 8.5553434e+08
A49: 3月 | B49: 68949705 | C49: 52199439 | D49: 428174820 | E49: 4.4380459e+08 | F49: 3.2611044e+08 | G49: 578178.04 | H49: =SUM(B49:G49) -> 1.3198172e+09
A50: 4月 | B50: 82097862 | C50: 59964831 | D50: 4.5294442e+08 | E50: =361973606.9-12300000 -> 3.4967361e+08 | F50: 2.615683e+08 | G50: 44980.76 | H50: =SUM(B50:G50) -> 1.206294e+09
A51: 5月 | B51: 55852183 | C51: 36339220 | D51: 5.3111e+08 | E51: =400628075.79-9810000 -> 3.9081808e+08 | F51: 3.2527759e+08 | G51: -446223.78 | H51: =SUM(B51:G51) -> 1.3389509e+09
A52: 6月 | B52: =59490703.87-254581.5 -> 59236122 | C52: 47835531 | D52: 4.8364974e+08 | E52: =503007520.016201+254581.5 -> 5.032621e+08 | F52: 3.4107339e+08 | G52: 552492.09 | H52: =SUM(B52:G52) -> 1.4356094e+09
A53: 7月 | B53: 66359182 | C53: 60352823 | D53: 4.1179453e+08 | E53: 3.909996e+08 | F53: 2.7382979e+08 | G53: 291083.16 | H53: =SUM(B53:G53) -> 1.203627e+09
A54: 8月 | B54: 55137037 | C54: 38587463 | D54: 3.8654479e+08 | E54: 5.1219403e+08 | F54: 3.4153222e+08 | G54: 391988.85 | H54: =SUM(B54:G54) -> 1.3343875e+09
A55: 9月 | B55: 59130089 | C55: 46932898 | D55: 4.931765e+08 | E55: 6.0488792e+08 | F55: 2.8353468e+08 | G55: 15737.1 | H55: =SUM(B55:G55) -> 1.4876778e+09
A56: 10月 | B56: 74161421 | C56: 56402488 | D56: 4.3886806e+08 | E56: 5.1416646e+08 | F56: 3.4694464e+08 | G56: 46382.15 | H56: =SUM(B56:G56) -> 1.4305895e+09
A57: 11月 | B57: 70812756 | C57: 1.0385444e+08 | D57: 4.589211e+08 | E57: 7.0039856e+08 | F57: 4.1465496e+08 | G57: 7416.82 | H57: =SUM(B57:G57) -> 1.7486492e+09
A58: 12月 | B58: 81908478 | C58: 81317262 | D58: 3.6009275e+08 | E58: 7.7708158e+08 | F58: 4.1054812e+08 | G58: 1747578.1 | H58: =SUM(B58:G58) -> 1.7126958e+09
A59: 合计 | B59: =SUM(B47:B58) -> 8.6166336e+08 | C59: =SUM(C47:C58) -> 6.9215414e+08 | D59: =SUM(D47:D58) -> 5.1682992e+09 | E59: =SUM(E47:E58) -> 5.763945e+09 | F59: =SUM(F47:F58) -> 3.651388e+09 | G59: =SUM(G47:G58) -> 4980011.3 | H59: =SUM(H47:H58) -> 1.614243e+10
A61: 2021年 | B61: SP0001-网游 | C61: SP0005-手游 | D61: SP0002-通信 | E61: SP0003-网娱 | F61: SP0004-卡劵 | G61: SP0006-生活服务 | H61: 总计（含税）
A62: 1月 | B62: 98172535 | C62: 37487307 | D62: 7.3685445e+08 | E62: 2.6771902e+08 | F62: 1.254799e+08 | G62: 9730 | H62: =SUM(B62:G62) -> 1.2657229e+09
A63: 2月 | B63: 1.1438706e+08 | C63: 56178179 | D63: 7.7106765e+08 | E63: 2.538512e+08 | F63: 69655650 | G63: -174.89 | H63: =SUM(B63:G63) -> 1.2651396e+09
A64: 3月 | B64: 70384911 | C64: 47302805 | D64: 1.1137733e+09 | E64: 2.8416e+08 | F64: 1.5607186e+08 | G64: 5272.5 | H64: =SUM(B64:G64) -> 1.6716982e+09
A65: 4月 | B65: 68783211 | C65: 52890400 | D65: 1.0091175e+09 | E65: 3.3260077e+08 | F65: 1.0181567e+08 | G65: 12505.89 | H65: =SUM(B65:G65) -> 1.56522e+09
A66: 5月 | B66: 71144738 | C66: 75569781 | D66: 1.2955131e+09 | E66: 4.0443049e+08 | F66: 95654370 | G66: 1266214.1 | H66: =SUM(B66:G66) -> 1.9435787e+09
A67: 6月 | B67: 57392749 | C67: 59049683 | D67: 1.4220239e+09 | E67: 6.0471742e+08 | F67: 1.2070682e+08 | G67: 4245818 | H67: =SUM(B67:G67) -> 2.2681364e+09
A68: 7月 | B68: 76256396 | C68: 79506146 | D68: 1.4709175e+09 | E68: 4.8060161e+08 | F68: 92196914 | G68: 2850602.4 | H68: =SUM(B68:G68) -> 2.2023291e+09
A69: 8月 | B69: 64988388 | C69: 71531282 | D69: 1.8537292e+09 | E69: 5.7744733e+08 | F69: 1.1804239e+08 | G69: 2012128.5 | H69: =SUM(B69:G69) -> 2.6877508e+09
A70: 9月 | B70: 47999699 | C70: 37566406 | D70: 8.6568692e+08 | E70: 6.5861575e+08 | F70: 1.6533814e+08 | G70: 1919602.2 | H70: =SUM(B70:G70) -> 1.7771265e+09
A71: 10月 | B71: 50055574 | C71: 36047801 | D71: 7.5021656e+08 | E71: 4.2225629e+08 | F71: 1.5752591e+08 | G71: 20933.32 | H71: =SUM(B71:G71) -> 1.4161231e+09
A72: 11月 | B72: 54761540 | C72: 19889222 | D72: 9.2817321e+08 | E72: 5.997526e+08 | F72: 1.7672572e+08 | G72: 4650008.3 | H72: =SUM(B72:G72) -> 1.7839523e+09
A73: 12月 | B73: 70567624 | C73: 79920456 | D73: 6.398813e+08 | E73: 6.9189446e+08 | F73: 1.5722498e+08 | G73: 1049442 | H73: =SUM(B73:G73) -> 1.6405383e+09 | I73: =H119-'[28]GMV+收入成本（改）'!$BA$7 -> #REF!
A74: 合计 | B74: =SUM(B62:B73) -> 8.4489442e+08 | C74: =SUM(C62:C73) -> 6.5293947e+08 | D74: =SUM(D62:D73) -> 1.2856955e+10 | E74: =SUM(E62:E73) -> 5.5780469e+09 | F74: =SUM(F62:F73) -> 1.5364383e+09 | G74: =SUM(G62:G73) -> 18042082 | H74: =SUM(H62:H73) -> 2.1487316e+10
D76: =D69-D54 -> 1.4671845e+09
A81: 2024年 | B81: SP0001-网游 | C81: SP0005-手游 | D81: SP0002-通信 | E81: SP0003-网娱 | F81: SP0004-卡劵 | G81: SP0006-生活服务 | H81: 合计
A82: GMV交易 | B82: =(B14)/10000 -> 41396.247 | C82: =(C14)/10000 -> 85605.52 | D82: =(D14)/10000 -> 5596.6421 | E82: =(E14)/10000 -> 161454.92 | F82: =(F14)/10000 -> 496672.12 | G82: =(G14)/10000 -> 958.06451 | H82: =SUM(B82:G82) -> 791683.51
A83: 关联交易 | B83: =B104/10000 -> 3515.9332 | C83: =C104/10000 -> 4560.9279 | D83: =D104/10000 -> 2936.0173 | E83: =E104/10000 -> 6034.5812 | F83: =F104/10000 -> 13113.039 | G83: =G104/10000 -> 0.0027 | H83: =SUM(B83:G83) -> 30160.502
A84: 总交易 | B84: =B82+B83 -> 44912.18 | C84: =C82+C83 -> 90166.448 | D84: =D82+D83 -> 8532.6594 | E84: =E82+E83 -> 167489.5 | F84: =F82+F83 -> 509785.16 | G84: =G82+G83 -> 958.06721 | H84: =SUM(B84:G84) -> 821844.01
A85: 关联交易占比 | B85: =B83/B84 -> 0.078284625 | C85: =C83/C84 -> 0.050583427 | D85: =D83/D84 -> 0.3440917 | E85: =E83/E84 -> 0.036029609 | F85: =F83/F84 -> 0.025722678 | G85: =G83/G84 -> 2.8181739e-06 | H85: =H83/H84 -> 0.036698572
A86: GMV交易占比 | B86: =B82/B84 -> 0.92171538 | C86: =C82/C84 -> 0.94941657 | D86: =D82/D84 -> 0.6559083 | E86: =E82/E84 -> 0.96397039 | F86: =F82/F84 -> 0.97427732 | G86: =G82/G84 -> 0.99999718 | H86: =H82/H84 -> 0.96330143
A90: 关联交易
A91: 2024年 | B91: SP0001-网游 | C91: SP0005-手游 | D91: SP0002-通信 | E91: SP0003-网娱 | F91: SP0004-卡劵 | G91: SP0006-生活服务 | H91: 总计（含税）
A92: 1月 | B92: 35159332 | C92: 45609279 | D92: 29360173 | E92: 60345812 | F92: 1.3113039e+08 | G92: 27 | H92: =SUM(B92:G92) -> 3.0160502e+08
A93: 2月 | H93: =SUM(B93:G93) -> 0
A94: 3月 | H94: =SUM(B94:G94) -> 0
A95: 4月 | H95: =SUM(B95:G95) -> 0
A96: 5月 | H96: =SUM(B96:G96) -> 0
A97: 6月 | H97: =SUM(B97:G97) -> 0
A98: 7月 | H98: =SUM(B98:G98) -> 0
A99: 8月 | H99: =SUM(B99:G99) -> 0
A100: 9月 | H100: =SUM(B100:G100) -> 0
A101: 10月 | H101: =SUM(B101:G101) -> 0
A102: 11月 | H102: =SUM(B102:G102) -> 0
A103: 12月 | H103: =SUM(B103:G103) -> 0
A104: 合计 | B104: =SUM(B92:B103) -> 35159332 | C104: =SUM(C92:C103) -> 45609279 | D104: =SUM(D92:D103) -> 29360173 | E104: =SUM(E92:E103) -> 60345812 | F104: =SUM(F92:F103) -> 1.3113039e+08 | G104: =SUM(G92:G103) -> 27 | H104: =SUM(H92:H103) -> 3.0160502e+08
A107: 2023年 | B107: SP0001-网游 | C107: SP0005-手游 | D107: SP0002-通信 | E107: SP0003-网娱 | F107: SP0004-卡劵 | G107: SP0006-生活服务 | H107: 总计（含税）
A108: 1月 | B108: 61439316 | C108: 49841697 | D108: 21127312 | E108: 2.584577e+08 | F108: 86543610 | H108: =SUM(B108:G108) -> 477409631
A109: 2月 | B109: 40014907 | C109: 27864078 | D109: 25373751 | E109: 2.5892492e+08 | F109: 87178896 | H109: =SUM(B109:G109) -> 4.3935656e+08
A110: 3月 | B110: 56303318 | C110: 25086306 | D110: 21896134 | E110: =269560159.07+13500000 -> 2.8306016e+08 | F110: 1.2501429e+08 | H110: =SUM(B110:G110) -> 5.1136021e+08
A111: 4月 | B111: 71590763 | C111: 29189657 | D111: 19743273 | E111: 2.3300655e+08 | F111: 1.7781558e+08 | H111: =SUM(B111:G111) -> 5.3134582e+08
A112: 5月 | B112: 84680576 | C112: 37409990 | D112: 25699958 | E112: 1.812661e+08 | F112: 2.0459329e+08 | H112: =SUM(B112:G112) -> 5.3364992e+08
A113: 6月 | B113: 65349871 | C113: 21288750 | D113: 72965665 | E113: 2.0380316e+08 | F113: 2.7063261e+08 | H113: =SUM(B113:G113) -> 6.3404006e+08
...

Sheet GMV销售平台占比
A1: 2025年
A2: 平台 | B2: 1月 | C2: 2月 | D2: 3月 | E2: 4月 | F2: 5月 | G2: 6月 | H2: 7月 | I2: 8月 | J2: 9月 | K2: 10月 | L2: 11月 | M2: 12月 | N2: 合计 | O2: 平台GMV占比 | Q2: 平台 | R2: 2025年 | S2: 2024年 | T2: 2023年 | U2: 2022年
A3: 福禄开放平台 | B3: 55063.067 | C3: 45120.512 | D3: 57418.92 | E3: 51803.522 | F3: 45322.133 | G3: 43295.323 | H3: 48615.93 | I3: =55589.0837440203+108.94/10000 -> 55589.095 | J3: 55216.189 | K3: 44896.934 | L3: 49122.948 | M3: =71166.6857643303+11608600.18/10000-11608600.18/10000 -> 71166.686 | N3: =(SUM(B3:M3)) -> 622631.26 | O3: =ROUND(N3/$N$17,4) -> 0.7864 | P3: =N3-N22 -> 22405.68 | Q3: TOB | R3: =R13/Y13 -> 0.84717978 | S3: =R14/Y14 -> 0.7298409 | T3: =R15/Y15 -> 0.69194426 | U3: =R16/Y16 -> 0.67893398 | AB3: =N3-N22 -> 22405.68 | AC3: =AB3/N22 -> 0.037328766
A4: 福游云平台 | E4: 31.579643 | F4: 705.67017 | G4: 2546.6727 | H4: 2700.307 | I4: 4142.5863 | J4: 9701.1453 | K4: 8663.3645 | L4: 9221.6356 | M4: 9515.0403 | N4: =(SUM(B4:M4)) -> 47228.001 | O4: =ROUND(N4/$N$17,4) -> 0.0597 | Q4: 京东 | R4: =S13/Y13 -> 0.0031510534 | S4: =S14/Y14 -> 0.060596688 | T4: =S15/Y15 -> 0.095458353 | U4: =S16/Y16 -> 0.12832323
A5: TOB平台 | L5: 178.4694 | M5: 715.99161 | N5: =(SUM(B5:M5)) -> 894.46101 | O5: =ROUND(N5/$N$17,4) -> 0.0011 | Q5: 天猫 | R5: =T13/Y13 -> 0.026382133 | S5: =T14/Y14 -> 0.049586303 | T5: =T15/Y15 -> 0.062372006 | U5: =T16/Y16 -> 0.063652707
A6: 京东 | B6: 190.33022 | C6: 199.69965 | D6: 194.03104 | E6: 183.95279 | F6: 467.27444 | G6: 658.6546 | H6: 1.0980527 | I6: 97.612906 | J6: 70.949964 | K6: 148.99086 | L6: 158.97491 | M6: 123.27384 | N6: =(SUM(B6:M6)) -> 2494.8433 | O6: =ROUND(N6/$N$17,4) -> 0.0032 | P6: =O6+O7+O8 -> 0.0331 | Q6: 拼多多 | R6: =U13/Y13 -> 0.0034954953 | S6: =U14/Y14 -> 0.0037359517 | T6: =U15/Y15 -> 0.0034942153 | U6: =U16/Y16 -> 0.013988165
A7: 天猫 | B7: 2049.7325 | C7: 1846.0403 | D7: 1706.0095 | E7: 1664.0018 | F7: 2202.8411 | G7: 1977.3084 | H7: 1709.1216 | I7: 1623.5382 | J7: 841.0991 | K7: 2493.3202 | L7: 1296.4332 | M7: 1478.581 | N7: =(SUM(B7:M7)) -> 20888.027 | O7: =ROUND(N7/$N$17,4) -> 0.0264 | Q7: 支付宝小程序 | R7: =V13/Y13 -> 0.079487559 | S7: =V14/Y14 -> 0.0902878 | T7: =V15/Y15 -> 0.068240155 | U7: =V16/Y16 -> 0.030087931
A8: 拼多多 | B8: 230.92896 | C8: 199.5126 | D8: 226.99423 | E8: 171.59552 | F8: 210.09979 | G8: 259.57187 | H8: 285.84206 | I8: 223.07519 | J8: 186.76374 | K8: 231.65394 | L8: 304.51737 | M8: 236.99954 | N8: =(SUM(B8:M8)) -> 2767.5548 | O8: =ROUND(N8/$N$17,4) -> 0.0035 | Q8: 抖快 | R8: =W13/Y13 -> 0.023426601 | S8: =W14/Y14 -> 0.035960964 | T8: =W15/Y15 -> 0.041035133 | U8: =W16/Y16 -> 0.024833133
A9: 支付宝小程序 | B9: 7907.5419 | C9: 5765.9562 | D9: 5728.9415 | E9: 4580.5479 | F9: 4494.4352 | G9: 6285.4866 | H9: 7367.2304 | I9: 7398.0521 | J9: 5078.521 | K9: 3301.592 | L9: 2872.1234 | M9: 2153.7649 | N9: =(SUM(B9:M9)) -> 62934.193 | O9: =ROUND(N9/$N$17,4) -> 0.0795 | Q9: 其他 | R9: =X13/Y13 -> 0.016877376 | S9: =X14/Y14 -> 0.029991394 | T9: =X15/Y15 -> 0.037455881 | U9: =X16/Y16 -> 0.32106602
A10: 抖音 | B10: 3623.411 | C10: 1339.3877 | D10: 547.55514 | E10: 899.18485 | F10: 6022.9674 | G10: 718.47917 | H10: 1363.9833 | I10: 867.92285 | J10: 900.60897 | K10: 920.27192 | L10: 794.15799 | M10: 292.8022 | N10: =(SUM(B10:M10)) -> 18290.732 | O10: =ROUND(N10/$N$17,4) -> 0.0231 | P10: =O10+O11 -> 0.0234 | Q10: 小计 | R10: =SUM(R3:R9) -> 1 | S10: =SUM(S3:S9) -> 1 | T10: =SUM(T3:T9) -> 1 | U10: =SUM(U3:U9) -> 1.2608852
A11: 快手 | B11: 0 | C11: 0 | D11: 0 | E11: 35.226567 | F11: 27.489975 | G11: 23.483136 | H11: 67.845025 | I11: 83.636968 | J11: 12.822216 | K11: 0.8307702 | L11: 5.5903112 | M11: 0.330229 | N11: =(SUM(B11:M11)) -> 257.2552 | O11: =ROUND(N11/$N$17,4) -> 0.0003
A12: 微信 | B12: 0.00845142 | C12: 0.00939968 | D12: 1.9206678 | E12: 3.5007104 | F12: 7.2964773 | G12: 3.3149819 | H12: 32.526796 | I12: 93.968823 | J12: 4.821247 | K12: 134.05461 | L12: 3.2586008 | M12: 3.0619577 | N12: =(SUM(B12:M12)) -> 287.74272 | O12: =ROUND(N12/$N$17,4) -> 0.0004 | Q12: 渠道大类 | R12: TOB | S12: 京东 | T12: 天猫 | U12: 拼多多 | V12: 支付宝小程序 | W12: 抖快 | X12: 第三方B2B2C | Y12: 合计（万元） | Z12: TOC | AA12: 验算
A13: 第三方平台 | B13: 790.75542 | C13: 704.81211 | D13: 742.65797 | E13: 935.42259 | F13: 969.39961 | G13: 1099.4609 | H13: 858.72859 | I13: 902.99937 | J13: 1110.287 | K13: 1415.7339 | L13: 1647.8698 | M13: 1466.3648 | N13: =(SUM(B13:M13)) -> 12644.492 | O13: =ROUND(N13/$N$17,4) -> 0.016 | Q13: 2025年 | R13: =N3+N4+N5 -> 670753.72 | S13: =N6 -> 2494.8433 | T13: =N7 -> 20888.027 | U13: =N8 -> 2767.5548 | V13: =N9 -> 62934.193 | W13: =N10+N11 -> 18547.988 | X13: =Y13-SUM(R13:W13) -> 13362.645 | Y13: =N17 -> 791748.97 | Z13: =Y13-R13 -> 120995.25 | AA13: =Y13-'GMV表-商品大类'!F61 -> 65.461797
A14: 充值频道 | B14: 22.783026 | C14: 19.475482 | D14: 20.449559 | E14: 20.691139 | F14: 16.109016 | G14: 29.63618 | H14: 18.880263 | I14: 19.177948 | J14: 21.060196 | K14: 18.389809 | L14: 34.353121 | M14: 44.106587 | N14: =(SUM(B14:M14)) -> 285.11233 | O14: =ROUND(N14/$N$17,4) -> 0.0004 | Q14: 2024年 | R14: =N22 -> 600225.58 | S14: =N23 -> 49835.083 | T14: =N24 -> 40780.076 | U14: =N25 -> 3072.4693 | V14: =N26 -> 74253.234 | W14: =N27+N28 -> 29574.515 | X14: =Y14-SUM(R14:W14) -> 24665.104 | Y14: =N35 -> 822406.06 | Z14: =Y14-R14 -> 222180.48 | AA14: =Y14-'GMV表-商品大类'!F60 -> -7.3341653e-09
A15: 百度小程序 | B15: 0.00039 | C15: 0.00499048 | D15: 0.00124 | E15: 0.0007 | F15: 0.00499048 | G15: 0 | H15: 0 | I15: 0 | J15: 0 | K15: 0 | L15: 0 | M15: 0 | N15: =(SUM(B15:M15)) -> 0.01231096 | O15: =ROUND(N15/$N$17,4) -> 0 | Q15: 2023年 | R15: =N40 -> 1079746.9 | S15: =N41 -> 148958.33 | T15: =N42 -> 97328.619 | U15: =N43 -> 5452.5608 | V15: =N44 -> 106485.59 | W15: =N45+N46 -> 64033.42 | X15: =Y15-SUM(R15:W15) -> 58448.164 | Y15: =N54 -> 1560453.6 | Z15: =Y15-R15 -> 480706.69 | AA15: =Y15-'GMV表-商品大类'!F59 -> 0.00060700113
A16: mall商城 | B16: 13.916859 | C16: 11.529193 | D16: 10.90678 | E16: 16.779002 | F16: 26.107432 | G16: 16.593748 | H16: 10.761049 | I16: 6.203813 | J16: 5.4977622 | K16: 6.8559693 | L16: 6.9168687 | M16: 13.217679 | N16: =(SUM(B16:M16)) -> 145.28615 | O16: =ROUND(N16/$N$17,4) -> 0.0002 | Q16: 2022年 | R16: =N58 -> 1095964.4 | S16: =N59 -> 207144.88 | T16: =N60 -> 102750.94 | U16: =N61 -> 22580.296 | V16: =N62 -> 48569.231 | W16: =N63+N64 -> 40086.711 | X16: =Y16-SUM(R16:R16) -> 518278.57 | Y16: =N72 -> 1614243 | Z16: =Y16-R16 -> 518278.57 | AA16: =Y16-'GMV表-商品大类'!F58 -> -2.4028122e-07
A17: 合计(单位：万元） | B17: =SUM(B3:B16) -> 69892.476 | C17: =SUM(C3:C16) -> 55206.939 | D17: =SUM(D3:D16) -> 66598.388 | E17: =SUM(E3:E16) -> 60346.005 | F17: =SUM(F3:F16) -> 60471.829 | G17: =SUM(G3:G16) -> 56913.985 | H17: =SUM(H3:H16) -> 63032.255 | I17: =SUM(I3:I16) -> 71047.869 | ... O17: =SUM(O3:O16) -> 1.0002 | Q17: 变动 | R17: =R13-R14 -> 70528.143 | S17: =S13-S14 -> -47340.24 | T17: =T13-T14 -> -19892.049 | U17: =U13-U14 -> -304.91453 | V17: =V13-V14 -> -11319.041 | W17: =W13-W14 -> -11026.527 | X17: =X13-X14 -> -11302.459 | Y17: =Y13-Y14 -> -30657.088
R18: =R17/R14 -> 0.11750273 | S18: =S17/S14 -> -0.94993801 | T18: =T17/T14 -> -0.48778843 | U18: =U17/U14 -> -0.099240871 | V18: =V17/V14 -> -0.15243836 | W18: =W17/W14 -> -0.37283882 | X18: =X17/X14 -> -0.45823682 | Y18: =Y17/Y14 -> -0.037277313
A20: 2024年 | Q20: 平台 | R20: TOB | S20: 京东 | T20: 天猫 | U20: 拼多多 | V20: 支付宝小程序 | W20: 抖快 | X20: 其他 | Y20: 小计
A21: 平台 | B21: 1月 | C21: 2月 | D21: 3月 | E21: 4月 | F21: 5月 | G21: 6月 | H21: 7月 | I21: 8月 | J21: 9月 | K21: 10月 | L21: 11月 | M21: 12月 | N21: 合计 | O21: 平台GMV占比 | Q21: 2025年 | R21: =R13/$Y$13 -> 0.84717978 | S21: =S13/$Y$13 -> 0.0031510534 | T21: =T13/$Y$13 -> 0.026382133 | U21: =U13/$Y$13 -> 0.0034954953 | V21: =V13/$Y$13 -> 0.079487559 | W21: =W13/$Y$13 -> 0.023426601 | X21: =X13/$Y$13 -> 0.016877376 | Y21: =SUM(R21:X21) -> 1
A22: 福禄开放平台 | B22: 57380.332 | C22: 49703.168 | D22: 52869.612 | E22: 39772.322 | F22: 48186.498 | G22: 55691.42 | H22: 50930.264 | I22: 57429.588 | J22: 43578.641 | K22: 46612.011 | L22: 47834.971 | M22: 50236.751 | N22: =SUM(B22:M22) -> 600225.58 | O22: =ROUND(N22/$N$35,4) -> 0.7298 | Q22: 2024年 | R22: =R14/$Y$14 -> 0.7298409 | S22: =S14/$Y$14 -> 0.060596688 | T22: =T14/$Y$14 -> 0.049586303 | U22: =U14/$Y$14 -> 0.0037359517 | V22: =V14/$Y$14 -> 0.0902878 | W22: =W14/$Y$14 -> 0.035960964 | X22: =X14/$Y$14 -> 0.029991394 | Y22: =SUM(R22:X22) -> 1
A23: 京东 | B23: 7436.1819 | C23: 4795.2709 | D23: 1573.2976 | E23: 1831.6988 | F23: 5229.3072 | G23: 11708.543 | H23: 12092.34 | I23: 2723.5818 | J23: 621.1785 | K23: 1282.8291 | L23: 354.24055 | M23: 186.61391 | N23: =SUM(B23:M23) -> 49835.083 | O23: =ROUND(N23/$N$35,4) -> 0.0606 | P23: =O23+O24+O25 -> 0.1139 | Q23: 2023年 | R23: =R15/$Y$15 -> 0.69194426 | S23: =S15/$Y$15 -> 0.095458353 | T23: =T15/$Y$15 -> 0.062372006 | U23: =U15/$Y$15 -> 0.0034942153 | V23: =V15/$Y$15 -> 0.068240155 | W23: =W15/$Y$15 -> 0.041035133 | X23: =X15/$Y$15 -> 0.037455881 | Y23: =SUM(R23:X23) -> 1
A24: 天猫 | B24: 7356.2745 | C24: 6826.9474 | D24: 3343.9349 | E24: 2639.3386 | F24: 2808.5516 | G24: 3292.1818 | H24: 2281.9778 | I24: 2542.949 | J24: 1620.5124 | K24: 2614.4508 | L24: 3180.461 | M24: 2272.4962 | N24: =SUM(B24:M24) -> 40780.076 | O24: =ROUND(N24/$N$35,4) -> 0.0496
A25: 拼多多 | B25: 169.63949 | C25: 258.59786 | D25: 201.96861 | E25: 209.87979 | F25: 245.2243 | G25: 301.85235 | H25: 306.39712 | I25: 303.30276 | J25: 270.23927 | K25: 255.92196 | L25: 287.69779 | M25: 261.74802 | N25: =SUM(B25:M25) -> 3072.4693 | O25: =ROUND(N25/$N$35,4) -> 0.0037
A26: 支付宝小程序 | B26: 4835.725 | C26: 6130.6306 | D26: 4249.5636 | E26: 3138.7858 | F26: 8496.6226 | G26: 8256.9594 | H26: 8340.9431 | I26: 9739.3838 | J26: 5159.344 | K26: 5454.6605 | L26: 5035.8439 | M26: 5414.7719 | N26: =SUM(B26:M26) -> 74253.234 | O26: =ROUND(N26/$N$35,4) -> 0.0903
A27: 抖音 | B27: 978.85206 | C27: 5589.2987 | D27: 1310.5839 | E27: 856.94885 | F27: 2235.5593 | G27: 3481.126 | H27: 7230.5858 | I27: 1241.067 | J27: 611.61683 | K27: 789.61794 | L27: 4306.1958 | M27: 900.78845 | N27: =SUM(B27:M27) -> 29532.241 | O27: =ROUND(N27/$N$35,4) -> 0.0359 | P27: =O27+O28 -> 0.036
A28: 快手 | B28: 7.955893 | C28: 8.04633 | D28: 5.182013 | E28: 5.71417 | F28: 4.99868 | G28: 0.3792994 | H28: 0.86430006 | I28: -2.4889971 | J28: 6.0944412 | K28: 0.782 | L28: 2.8899 | M28: 1.8559 | N28: =SUM(B28:M28) -> 42.27393 | O28: =ROUND(N28/$N$35,4) -> 0.0001
A29: 微信 | B29: 0.137637 | C29: 0.088062 | D29: 0.16190964 | E29: 0 | F29: -1.272e-05 | G29: 1.2955172 | L29: 0.02205672 | M29: 0.01564572 | N29: =SUM(B29:M29) -> 1.7208155 | O29: =ROUND(N29/$N$35,4) -> 0
A30: 第三方平台 | B30: 2608.1562 | C30: 2087.6476 | D30: 2307.5211 | E30: 1413.6205 | F30: 2168.5868 | G30: 876.27303 | H30: 683.92585 | I30: 876.53694 | J30: 673.27937 | K30: 965.75132 | L30: 723.18587 | M30: 819.06602 | N30: =SUM(B30:M30) -> 16203.551 | O30: =ROUND(N30/$N$35,4) -> 0.0197
A31: 充值频道 | B31: 1491.8645 | C31: 151.0234 | D31: 267.63107 | E31: 294.43465 | F31: 1160.9214 | G31: 180.26779 | H31: 120.31669 | I31: 289.59872 | J31: 73.440949 | K31: 1029.4009 | L31: 76.861941 | M31: 81.4073 | N31: =SUM(B31:M31) -> 5217.1693 | O31: =ROUND(N31/$N$35,4) -> 0.0063
A32: 短信分销平台 | B32: 2.656935 | C32: 1.945017 | D32: 1.73492 | E32: 1.742468 | F32: 1.632589 | G32: 3.857593 | H32: 1.6050478 | I32: 1.1173497 | J32: 0.012545 | K32: 0.11889592 | L32: 0.001748 | M32: 0.002504 | N32: =SUM(B32:M32) -> 16.427612 | O32: =ROUND(N32/$N$35,4) -> 0
A33: 百度小程序 | B33: 1.11333 | C33: 0.404225 | D33: 12.162652 | E33: 2.36439 | F33: 0.00255 | G33: 0.00751 | H33: 0.0134056 | I33: 0.000465 | J33: 0.00078204 | K33: 0.00155796 | L33: 0 | M33: 0.002955 | N33: =SUM(B33:M33) -> 16.073823 | O33: =ROUND(N33/$N$35,4) -> 0
A34: mall商城 | B34: 1572.7729 | C34: 664.98154 | D34: 689.53527 | E34: 178.44666 | F34: 15.061236 | G34: 8.584745 | H34: 15.744394 | I34: 21.133721 | J34: 3.7441439 | K34: 5.8240984 | L34: 10.589944 | M34: 23.743412 | N34: =SUM(B34:M34) -> 3210.1621 | O34: =ROUND(N34/$N$35,4) -> 0.0039
A35: 合计(单位：万元） | B35: =SUM(B22:B34) -> 83841.662 | C35: =SUM(C22:C34) -> 76218.049 | D35: =SUM(D22:D34) -> 66832.889 | E35: =SUM(E22:E34) -> 50345.297 | F35: =SUM(F22:F34) -> 70552.966 | G35: =SUM(G22:G34) -> 83802.748 | H35: =SUM(H22:H34) -> 82004.978 | I35: =SUM(I22:I34) -> 75165.771 | ... N35: =SUM(N22:N34) -> 822406.06 | O35: =N35/$N$35 -> 1
A38: 2023年
A39: 平台 | B39: 1月 | C39: 2月 | D39: 3月 | E39: 4月 | F39: 5月 | G39: 6月 | H39: 7月 | I39: 8月 | J39: 9月 | K39: 10月 | L39: 11月 | M39: 12月 | N39: 合计 | O39: 平台GMV占比
A40: 福禄开放平台 | B40: 91365.673 | C40: 99354.621 | D40: 115570.26 | E40: 90538.163 | F40: 94368.671 | G40: =101515.297081+9043.9/10000 -> 101516.2 | H40: =91428.439399+0.39521 -> 91428.835 | I40: 98871.924 | J40: 87871.175 | K40: 67975.954 | L40: 70601.928 | M40: 70283.486 | N40: =SUM(B40:M40) -> 1079746.9 | O40: =ROUND(N40/$N$54,4) -> 0.6919
A41: 京东 | B41: 9976.2347 | C41: 7563.0608 | D41: 8790.9438 | E41: 13731.851 | F41: 21460.735 | G41: 25014.187 | H41: 13412.145 | I41: 11064.822 | J41: 10148.357 | K41: 8363.7859 | L41: 12780.064 | M41: 6652.1429 | N41: =SUM(B41:M41) -> 148958.33 | O41: =ROUND(N41/$N$54,4) -> 0.0955 | P41: =O41+O42+O43 -> 0.1614
A42: 天猫 | B42: 8600.3923 | C42: 6026.2335 | D42: =8710.422622-1350 -> 7360.4226 | E42: =8490.906362-1250 -> 7240.9064 | F42: 7482.9904 | G42: 7613.8731 | H42: 6348.3664 | I42: 8622.117 | J42: 11432.224 | K42: 7610.1162 | L42: 12712.985 | M42: 6277.992 | N42: =SUM(B42:M42) -> 97328.619 | O42: =ROUND(N42/$N$54,4) -> 0.0624
A43: 拼多多 | B43: 491.15028 | C43: 405.34202 | D43: 531.36978 | E43: 595.40474 | F43: 656.21552 | G43: 444.78814 | H43: 498.47264 | I43: 564.60724 | J43: 413.99637 | K43: 340.67903 | L43: 295.47328 | M43: 215.06176 | N43: =SUM(B43:M43) -> 5452.5608 | O43: =ROUND(N43/$N$54,4) -> 0.0035
A44: 支付宝小程序 | B44: 7749.3784 | C44: 7174.6965 | D44: 5950.3348 | E44: 6267.7191 | F44: 12374.001 | G44: 12629.482 | H44: 13953.145 | I44: 16053.31 | J44: 8450.3943 | K44: 4684.6931 | L44: 4960.0016 | M44: 6238.4391 | N44: =SUM(B44:M44) -> 106485.59 | O44: =ROUND(N44/$N$54,4) -> 0.0682
A45: 抖音 | B45: 8813.7315 | C45: 2053.4208 | D45: 2652.0708 | E45: 1378.92 | F45: 5298.9093 | G45: 2842.131 | H45: 1341.2829 | I45: 5110.8842 | J45: 1949.1342 | K45: 3241.7931 | L45: 7605.9872 | M45: 1717.0666 | N45: =SUM(B45:M45) -> 44005.332 | O45: =ROUND(N45/$N$54,4) -> 0.0282 | P45: =O45+O46 -> 0.041
A46: 快手 | B46: 1506.7266 | C46: 3922.803 | D46: 6875.1207 | E46: 1804.3476 | F46: 1463.6828 | G46: 3357.0479 | H46: 469.7671 | I46: 134.31352 | J46: 425.91863 | K46: 16.981048 | L46: 43.520617 | M46: 7.859037 | N46: =SUM(B46:M46) -> 20028.089 | O46: =ROUND(N46/$N$54,4) -> 0.0128
A47: 微信 | B47: 12.71152 | C47: 83.8174 | D47: 148.87819 | E47: 51.740939 | F47: 50.68203 | G47: 1.574439 | H47: 0.145652 | I47: 0.323576 | J47: 2.36767 | K47: 0.035244 | L47: -8.499131 | M47: 0.025892 | N47: =SUM(B47:M47) -> 343.80342 | O47: =ROUND(N47/$N$54,4) -> 0.0002
A48: 苏宁 | B48: -0.0326 | C48: 0.0929 | D48: 0.01039 | E48: 0 | F48: 0 | G48: 0 | H48: 0 | I48: 0 | J48: 0 | K48: 0 | L48: 0 | M48: 0 | N48: =SUM(B48:M48) -> 0.07069 | O48: =ROUND(N48/$N$54,4) -> 0
A49: 第三方平台 | B49: 4837.3737 | C49: 3461.295 | D49: 2134.6567 | E49: 1960.2073 | F49: 2142.2481 | G49: 2936.7975 | H49: 2748.6421 | I49: 5407.3912 | J49: 4117.676 | K49: 2612.0592 | L49: 4213.3491 | M49: 2303.0788 | N49: =SUM(B49:M49) -> 38874.775 | O49: =ROUND(N49/$N$54,4) -> 0.0249
A50: 充值频道 | B50: 596.39153 | C50: 1019.3311 | D50: 2227.2295 | E50: 714.04104 | F50: 539.45137 | G50: 623.04133 | H50: 598.59061 | I50: 714.52421 | J50: 717.4884 | K50: 985.47588 | L50: 818.13565 | M50: 424.11814 | N50: =SUM(B50:M50) -> 9977.8188 | O50: =ROUND(N50/$N$54,4) -> 0.0064
A51: 短信分销平台 | B51: 21.991233 | C51: 1.70992 | D51: 1.814556 | E51: 1.564706 | F51: 0.236379 | G51: 1.547379 | H51: 1.344699 | I51: 1.439396 | J51: 1.727021 | K51: 5.998978 | L51: 1.401985 | M51: 2.255709 | N51: =SUM(B51:M51) -> 43.031961 | O51: =ROUND(N51/$N$54,4) -> 0
A52: 百度小程序 | B52: 366.34325 | C52: 399.73345 | D52: 586.34572 | E52: 546.63817 | F52: 611.25632 | G52: 1.308647 | H52: 2.119582 | I52: 1.426591 | J52: 0.842911 | K52: 0.932406 | L52: 0.903982 | M52: 23.07937 | N52: =SUM(B52:M52) -> 2540.9304 | O52: =ROUND(N52/$N$54,4) -> 0.0016
A53: mall商城 | B53: 243.51773 | C53: 433.00997 | D53: 480.77091 | E53: 421.79059 | F53: 1422.3533 | G53: 384.92143 | H53: 610.6589 | I53: 664.99859 | J53: 446.07566 | K53: 484.10615 | L53: 492.49003 | M53: 583.04058 | N53: =SUM(B53:M53) -> 6667.7339 | O53: =ROUND(N53/$N$54,4) -> 0.0043
A54: 合计(单位：万元） | B54: =SUM(B40:B53) -> 134581.58 | C54: =SUM(C40:C53) -> 131899.17 | D54: =SUM(D40:D53) -> 153310.23 | E54: =SUM(E40:E53) -> 125253.29 | F54: =SUM(F40:F53) -> 147871.43 | G54: =SUM(G40:G53) -> 157366.9 | H54: =SUM(H40:H53) -> 131413.51 | I54: =SUM(I40:I53) -> 147212.08 | ... N54: =SUM(N40:N53) -> 1560453.6 | O54: =N54/$N$54 -> 1
C55: =C54-'GMV销售额波动分析（分月、年）'!H33/10000 -> 0.00060699994 | D55: =D54-'GMV销售额波动分析（分月、年）'!H34/10000 -> 0
A56: 2022年
A57: 平台 | B57: 1月 | C57: 2月 | D57: 3月 | E57: 4月 | F57: 5月 | G57: 6月 | H57: 7月 | I57: 8月 | J57: 9月 | K57: 10月 | L57: 11月 | M57: 12月 | N57: 合计 | O57: 平台GMV占比
A58: 福禄开放平台 | B58: 57263.076 | C58: 48717.599 | D58: 91475.411 | E58: 78598.883 | F58: 92474.126 | G58: 101701.07 | H58: 85493.075 | I58: 92410.845 | J58: 111531.34 | K58: 95225.339 | L58: 115027.85 | M58: 126045.78 | N58: =(SUM(B58:M58)) -> 1095964.4 | O58: =ROUND(N58/$N$72,4) -> 0.6789
A59: 京东 | B59: 22124.245 | C59: 15918.936 | D59: 16249.324 | E59: 18825.561 | F59: 17618.26 | G59: 17614.562 | H59: 14434.315 | I59: 13427.52 | J59: 12965.87 | K59: 17372.104 | L59: 22491.504 | M59: 18102.674 | N59: =(SUM(B59:M59)) -> 207144.88 | O59: =ROUND(N59/$N$72,4) -> 0.1283
A60: 天猫 | B60: 8746.356 | C60: 5855.7616 | D60: 6581.2168 | E60: =7204.459017-1230 -> 5974.459 | F60: 6556.9445 | G60: 8538.9737 | H60: 6582.8039 | I60: 13196.389 | J60: 9146.8697 | K60: 10329.912 | L60: 13111.603 | M60: 8129.646 | N60: =(SUM(B60:M60)) -> 102750.94 | O60: =ROUND(N60/$N$72,4) -> 0.0637
A61: 拼多多 | B61: 4235.2002 | C61: 2673.212 | D61: 3599.1433 | E61: 2921.2117 | F61: 2648.3383 | G61: 2776.3636 | H61: 618.36244 | I61: 1007.4566 | J61: 765.44164 | K61: 396.26025 | L61: 548.88793 | M61: 390.41837 | N61: =(SUM(B61:M61)) -> 22580.296 | O61: =ROUND(N61/$N$72,4) -> 0.014
A62: 支付宝小程序 | B62: 4932.9948 | C62: 4116.3175 | D62: 3888.4396 | E62: 4108.6453 | F62: 2829.7555 | G62: 2751.2738 | H62: 3017.3385 | I62: 3257.2757 | J62: 3254.2561 | K62: 5111.4118 | L62: 5544.3417 | M62: 5757.1811 | N62: =(SUM(B62:M62)) -> 48569.231 | O62: =ROUND(N62/$N$72,4) -> 0.0301
A63: 抖音 | B63: 2004.8081 | C63: 1023.7076 | D63: 1344.1383 | E63: 1672.2827 | F63: 2011.3606 | G63: 2435.5221 | H63: 3601.9845 | I63: 2434.9339 | J63: 2175.477 | K63: 6071.2049 | L63: 9962.7384 | M63: 4767.9583 | N63: =(SUM(B63:M63)) -> 39506.116 | O63: =ROUND(N63/$N$72,4) -> 0.0245
A64: 快手 | B64: 15.320737 | C64: 0.681875 | D64: 10.537209 | E64: 6.692 | F64: 47.113218 | G64: 32.665575 | H64: 21.139845 | I64: 37.186951 | J64: 19.218547 | K64: 23.587517 | L64: 61.017979 | M64: 305.43281 | N64: =(SUM(B64:M64)) -> 580.59426 | O64: =ROUND(N64/$N$72,4) -> 0.0004
A65: 微信 | B65: 13.984349 | C65: 23.39396 | D65: 15.520214 | E65: 27.460133 | F65: 18.239973 | G65: 9.805075 | H65: 4.419838 | I65: 3.884783 | J65: 2.431087 | K65: 6.385332 | L65: 4.667189 | M65: 6.160662 | N65: =(SUM(B65:M65)) -> 136.3526 | O65: =ROUND(N65/$N$72,4) -> 0.0001
A66: 苏宁 | B66: 5.38078 | C66: 116.03278 | D66: 66.165154 | E66: 56.72909 | F66: 19.445032 | G66: 13.031364 | H66: 1.46989 | I66: 2.976927 | J66: -0.0257 | K66: 0 | L66: 0.0001 | M66: 0 | N66: =(SUM(B66:M66)) -> 281.20542 | O66: =ROUND(N66/$N$72,4) -> 0.0002
A67: 第三方平台 | B67: 6843.2485 | C67: 6390.4107 | D67: 7490.3145 | E67: 6722.6756 | F67: 7874.7579 | G67: 6572.1131 | H67: 5765.7793 | I67: 6176.597 | J67: 7665.4888 | K67: 7271.7127 | L67: =6261.54231499998+435.150349 -> 6696.6927 | M67: =6862.42295999999+369.545598 -> 7231.9686 | N67: =(SUM(B67:M67)) -> 82701.759 | O67: =ROUND(N67/$N$72,4) -> 0.0512
A68: 充值频道 | B68: 641.1758 | C68: 685.87334 | D68: 1217.899 | E68: 1686.1757 | F68: 1768.0032 | G68: 1086.6228 | H68: 784.62902 | I68: 1457.2334 | J68: 1217.2864 | K68: 1232.2211 | L68: 1401.2548 | M68: 519.02557 | N68: =(SUM(B68:M68)) -> 13697.4 | O68: =ROUND(N68/$N$72,4) -> 0.0085
A69: 短信分销平台 | B69: 31.954731 | C69: 30.162219 | D69: 43.586865 | E69: 28.625395 | F69: 28.741788 | G69: 28.935553 | H69: 37.382823 | I69: 26.452599 | J69: 24.123822 | K69: 18.806453 | L69: 14.366787 | M69: 13.333285 | N69: =(SUM(B69:M69)) -> 326.47232 | O69: =ROUND(N69/$N$72,4) -> 0.0002
A70: 福禄云平台 | B70: 1.361804 | C70: 0.492491 | D70: 0 | N70: =(SUM(B70:M70)) -> 1.854295 | O70: =ROUND(N70/$N$72,4) -> 0
A71: 福禄APP | B71: 0.604221 | C71: 0.852804 | D71: 0.021165 | L71: 0.000607 | N71: =(SUM(B71:M71)) -> 1.478797 | O71: =ROUND(N71/$N$72,4) -> 0
A72: 合计(单位：万元） | B72: =SUM(B58:B71) -> 106859.71 | C72: =SUM(C58:C71) -> 85553.434 | D72: =SUM(D58:D71) -> 131981.72 | E72: =SUM(E58:E71) -> 120629.4 | F72: =SUM(F58:F71) -> 133895.09 | G72: =SUM(G58:G71) -> 143560.94 | H72: =SUM(H58:H71) -> 120362.7 | I72: =SUM(I58:I71) -> 133438.75 | ... N72: =SUM(N58:N71) -> 1614243 | O72: =N72/$N$72 -> 1
B73: =B72-'GMV销售额波动分析（分月、年）'!H47/10000 -> 0 | C73: =C72-'GMV销售额波动分析（分月、年）'!H48/10000 -> 1.891749e-10 | D73: =D72-'GMV销售额波动分析（分月、年）'!H49/10000 -> 0 | E73: =E72-'GMV销售额波动分析（分月、年）'!H50/10000 -> -5.3842086e-10 | F73: =F72-'GMV销售额波动分析（分月、年）'!H51/10000 -> -2.3996108e-07 | G73: =G72-'GMV销售额波动分析（分月、年）'!H52/10000 -> 0 | H73: =H72-'GMV销售额波动分析（分月、年）'!H53/10000 -> 0 | I73: =I72-'GMV销售额波动分析（分月、年）'!H54/10000 -> -1.193257e-09 | J73: =J72-'GMV销售额波动分析（分月、年）'!H55/10000 -> -1.0186341e-09 | K73: =K72-'GMV销售额波动分析（分月、年）'!H56/10000 -> 5.5297278e-10 | L73: =L72-'GMV销售额波动分析（分月、年）'!H57/10000 -> 0
A74: 2021年
A75: 平台 | B75: 1月 | C75: 2月 | D75: 3月 | E75: 4月 | F75: 5月 | G75: 6月 | H75: 7月 | I75: 8月 | J75: 9月 | K75: 10月 | L75: 11月 | M75: 12月 | N75: 合计 | O75: 平台GMV占比
A76: 福禄开放平台 | B76: =39423.9753359997+1.8+11366675/10000 -> 40562.443 | C76: =40951.919165+23497269/10000 -> 43301.646 | D76: =58250.0285839998+19871254/10000 -> 60237.154 | E76: =48818.376555+19827588/10000 -> 50801.135 | F76: =68007.927959+21357735/10000 -> 70143.701 | G76: =96605.077184+21327047/10000 -> 98737.782 | H76: =99417.66+15565600/10000 -> 100974.22 | I76: 105358.42 | J76: =107367.065018+6695591/10000 -> 108036.62 | K76: 85420.475 | L76: 109719.61 | M76: =107009.96952662-1098882/10000 -> 106900.08 | N76: =(SUM(B76:M76)) -> 980193.29 | O76: =ROUND(N76/$N$89,4) -> 0.4562
A77: 京东 | B77: 61176.69 | C77: 57422.696 | D77: 81422.116 | E77: 79200.967 | F77: 102417.81 | G77: 110457.44 | H77: 101707 | I77: 145034.01 | J77: 51975.055 | K77: 39140.548 | L77: =45786.486366-1490350.88/10000 -> 45637.451 | M77: 29471.594 | N77: =(SUM(B77:M77)) -> 905063.37 | O77: =ROUND(N77/$N$89,4) -> 0.4212
A78: 天猫 | B78: 15572.999 | C78: 16729.527 | D78: 15594.689 | E78: 16881.119 | F78: 14957.635 | G78: 9213.6369 | H78: 10097.426 | I78: 9429.0745 | J78: 8711.3003 | K78: 7934.5837 | L78: 11842.62 | M78: 7885.9601 | N78: =(SUM(B78:M78)) -> 144850.57 | O78: =ROUND(N78/$N$89,4) -> 0.0674
A79: 拼多多 | B79: 396.84255 | C79: 332.53945 | D79: 391.1869 | E79: 404.83364 | F79: 537.52182 | G79: 691.68664 | H79: 347.58919 | I79: 351.3668 | J79: 270.78366 | K79: 293.53961 | L79: 1828.9349 | M79: 5697.9092 | N79: =(SUM(B79:M79)) -> 11544.734 | O79: =ROUND(N79/$N$89,4) -> 0.0054
A80: 抖音 | B80: 4.99998 | C80: 1.30409 | D80: 8.797984 | E80: 10.566873 | F80: 11.817944 | G80: 209.58694 | H80: 267.65737 | I80: 748.74644 | J80: 251.18179 | K80: 1574.6299 | L80: 2197.2566 | M80: 1003.5323 | N80: =(SUM(B80:M80)) -> 6290.0781 | O80: =ROUND(N80/$N$89,4) -> 0.0029
A81: 快手 | B81: 11.41402 | C81: 69.565727 | D81: 0.007144 | E81: 0.006292 | F81: 1.073629 | G81: 52.738715 | H81: 54.057234 | I81: 1.377599 | J81: -0.050824 | K81: 3.458081 | L81: 182.34554 | M81: 21.25146 | N81: =(SUM(B81:M81)) -> 397.24461 | O81: =ROUND(N81/$N$89,4) -> 0.0002
A82: 第三方平台 | B82: 8093.4824 | C82: 7839.7969 | D82: 9038.0389 | E82: 8604.2089 | F82: 5654.2261 | G82: 6522.9374 | H82: 5880.6582 | I82: 6786.1417 | J82: 8013.0434 | K82: 6656.728 | L82: 6529.4188 | M82: 11977.974 | N82: =(SUM(B82:M82)) -> 91596.655 | O82: =ROUND(N82/$N$89,4) -> 0.0426
A83: 苏宁 | B83: 179.04565 | C83: 110.75049 | D83: 27.409568 | E83: 160.57295 | F83: 67.484508 | G83: 138.02232 | H83: 51.691404 | I83: 240.15992 | J83: 104.45614 | K83: 42.425316 | L83: 23.733068 | M83: 65.640713 | N83: =(SUM(B83:M83)) -> 1211.392 | O83: =ROUND(N83/$N$89,4) -> 0.0006
A84: 微信 | B84: 176.45688 | C84: 365.17786 | D84: 143.58598 | E84: 76.936761 | F84: 31.692688 | G84: 25.153484 | H84: 17.941346 | I84: 12.194873 | J84: 8.075669 | K84: 9.757343 | L84: 15.530333 | M84: 31.255816 | N84: =(SUM(B84:M84)) -> 913.75904 | O84: =ROUND(N84/$N$89,4) -> 0.0004
A85: 充值频道 | B85: 356.47403 | C85: 316.98726 | D85: 276.19386 | E85: 329.62943 | F85: 505.64156 | G85: 634.27797 | H85: 765.05151 | I85: 605.17902 | J85: 256.05156 | K85: 448.39175 | L85: 382.92694 | M85: 959.51346 | N85: =(SUM(B85:M85)) -> 5836.3183 | O85: =ROUND(N85/$N$89,4) -> 0.0027
A86: 短信分销平台 | B86: 30.220819 | C86: 8.815927 | D86: 20.533129 | E86: 40.769859 | F86: 15.823194 | G86: 19.139784 | H86: 64.819123 | I86: 102.58942 | J86: 85.22272 | K86: 87.770289 | L86: 35.354799 | M86: 38.590306 | N86: =(SUM(B86:M86)) -> 549.64937 | O86: =ROUND(N86/$N$89,4) -> 0.0003
A87: APP | B87: 11.19466 | C87: 15.14335 | D87: 10.103145 | E87: 11.250786 | F87: 10.332308 | G87: 111.23654 | H87: 4.803363 | I87: 105.81594 | J87: 0.90577 | K87: 0 | L87: 0.050483 | M87: 0.524047 | N87: =(SUM(B87:M87)) -> 281.36039 | O87: =ROUND(N87/$N$89,4) -> 0.0001
A88: G库 | B88: 0.0311 | C88: 0.0055 | D88: 0.0025 | E88: 0.006 | F88: 3.1065 | G88: 0.0015 | H88: 0.0035 | I88: 0.001 | J88: 0.002 | K88: 0.001 | L88: 0.001 | M88: 0 | N88: =(SUM(B88:M88)) -> 3.1616 | O88: =ROUND(N88/$N$89,4) -> 0
A89: 合计(单位：万元） | B89: =SUM(B76:B88) -> 126572.29 | C89: =SUM(C76:C88) -> 126513.96 | D89: =SUM(D76:D88) -> 167169.82 | E89: =SUM(E76:E88) -> 156522 | F89: =SUM(F76:F88) -> 194357.87 | G89: =SUM(G76:G88) -> 226813.64 | H89: =SUM(H76:H88) -> 220232.91 | I89: =SUM(I76:I88) -> 268775.08 | ... N89: =SUM(N76:N88) -> 2148731.6 | O89: =ROUND(N89/$N$89,4) -> 1
L90: =L89-'GMV销售额波动分析（分月、年）'!H72/10000 -> 0 | N90: =N89-SUM('GMV销售额波动分析（分月、年）'!H62:H73)/10000 -> -3.0150637e-05
A91: 2020年
A92: 平台 | B92: 1月 | C92: 2月 | D92: 3月 | E92: 4月 | F92: 5月 | G92: 6月 | H92: 7月 | I92: 8月 | J92: 9月 | K92: 10月 | L92: 11月 | M92: 12月 | N92: 合计 | O92: 平台GMV占比
A93: 开放平台 | B93: =78680.400901+85.91-74719884.22/10000 -> 71294.322 | C93: =92825.248135-25783045.72/10000 -> 90246.944 | D93: =105162.588587+7.89-109693990.11/10000 -> 94201.08 | E93: =97371.774742+0.6026-63605902.13/10000 -> 91011.787 | F93: =68842.153984-0.52-50369337.9/10000 -> 63804.7 | G93: =59099.8122899998+31484467.16/10000+8.29-34408693.89/10000 -> 58815.68 | H93: =37665.855537-40538243.73/10000 -> 33612.031 | I93: =42558.544539-44690221.03/10000 -> 38089.522 | J93: =45183.57061+134070.57/10000-78063313.07/10000 -> 37390.646 | K93: =41079.293538-10179102.11/10000 -> 40061.383 | L93: =46761.208714+83997.87/10000-73096942.4/10000 -> 39459.914 | M93: =55434.034117-99213147.59/10000 -> 45512.719 | N93: =(SUM(B93:J93)) -> 578466.71 | O93: =N93/$N$107 -> 0.53976625
A94: 京东 | B94: 17676.328 | C94: 15046.748 | D94: 22011.813 | E94: 18856.754 | F94: 36867.658 | G94: 49393.267 | H94: 50846.399 | I94: =41494.864346+72.719472 -> 41567.584 | J94: 51591.896 | K94: 57234.207 | L94: 62757.926 | M94: 59950.407 | N94: =(SUM(B94:J94)) -> 303858.45 | O94: =N94/$N$107 -> 0.28352977
A95: 天猫 | B95: 12208.547 | C95: =12603.12774-91.11 -> 12512.018 | D95: 13439.306 | E95: 13470.142 | F95: 14860.018 | G95: 16925.18 | H95: 16200.158 | I95: 15361.318 | J95: 14191.907 | K95: 16833.536 | L95: 23264.896 | M95: 19603.237 | N95: =(SUM(B95:J95)) -> 129168.59 | O95: =N95/$N$107 -> 0.12052698
A96: 拼多多 | B96: 608.58226 | C96: 503.59395 | D96: 254.745 | E96: 333.5462 | F96: 308.75763 | G96: 349.66423 | H96: 10.906277 | I96: 10.597887 | J96: 334.46023 | K96: 669.26409 | L96: 480.25236 | M96: 409.15772 | N96: =(SUM(B96:J96)) -> 2714.8537 | O96: =N96/$N$107 -> 0.0025332251
A97: 支付宝小程序 | B97: 2351.6964 | C97: 2279.5221 | D97: 4459.0473 | E97: 4231.7542 | F97: 4074.6688 | G97: 6094.1392 | H97: 6568.2464 | I97: 6790.008 | J97: 3917.435 | K97: 4764.8864 | L97: 3378.4368 | M97: -0.01655 | N97: =(SUM(B97:J97)) -> 40766.517 | O97: =N97/$N$107 -> 0.038039164
A98: IOS苹果卡 | B98: 4001.1056 | C98: 4641.3033 | D98: 888.47523 | N98: =(SUM(B98:J98)) -> 9530.8841 | O98: =N98/$N$107 -> 0.0088932508
A99: 苏宁 | B99: 176.96577 | C99: 264.6003 | D99: 111.69629 | E99: 122.03122 | F99: 271.5269 | G99: 636.00335 | H99: 0.027307 | I99: 0.407394 | J99: 112.80687 | K99: 434.7165 | L99: 185.12352 | M99: 689.01028 | N99: =(SUM(B99:J99)) -> 1696.0654 | O99: =N99/$N$107 -> 0.0015825956
A100: 微信 | B100: 88.226893 | C100: 144.04977 | D100: 194.45179 | E100: 148.45406 | F100: 32.871628 | G100: 55.179119 | H100: 76.697604 | I100: 142.83447 | J100: 117.74105 | K100: 149.26196 | L100: 222.24521 | M100: 244.63404 | N100: =(SUM(B100:J100)) -> 1000.5064 | O100: =N100/$N$107 -> 0.00093357071
A101: 第三方平台 | B101: 218.59009 | C101: 75.498498 | D101: 119.34302 | E101: 82.905622 | F101: 230.03195 | G101: 476.28214 | H101: 102.1481 | I101: 393.48238 | J101: 168.01642 | K101: 354.04884 | L101: 1536.1018 | M101: 7470.3573 | N101: =(SUM(B101:J101)) -> 1866.2982 | O101: =N101/$N$107 -> 0.0017414395
A102: 短信平台 | B102: 49.645955 | C102: 50.866252 | D102: 210.11419 | E102: 119.91572 | F102: 32.158862 | G102: 22.375904 | H102: =170.154629+8.35/10000 -> 170.15546 | I102: 13.872562 | J102: 20.104893 | K102: 15.716167 | L102: 25.751411 | M102: 24.026338 | N102: =(SUM(B102:J102)) -> 689.20981 | O102: =N102/$N$107 -> 0.00064310043
A103: APP | B103: 64.371113 | C103: 144.49488 | D103: 51.030485 | E103: 75.733586 | F103: 74.506003 | G103: 211.59468 | H103: 58.798072 | I103: 21.061007 | J103: 26.467035 | K103: 9.645272 | L103: 3.994273 | M103: 3.359208 | N103: =(SUM(B103:J103)) -> 728.05686 | O103: =N103/$N$107 -> 0.00067934855
...

Sheet GMV表-商品大类
A1: 支撑分析数据
A2: 1、21年-22年商品大类增长波动
A3: 2、21年-22年网娱、生活服务增长波动
A4: 代理商品大类 | H4: 代运营GMV
A5: 年份 | B5: 游戏 | C5: 通信 | D5: 网娱 | E5: 生活服务 | F5: 合计（单位：万元） | H5: 年份 | I5: 游戏 | J5: 通信 | K5: 网娱 | L5: 生活服务 | M5: 合计（单位：万元） | O5: 代理GMV年度累计 | P5: 游戏 | Q5: 通信 | R5: 网娱 | S5: 生活服务 | T5: 合计（单位：万元）
A6: 44562 | B6: 15562.122 | C6: 41149.968 | D6: 32432.045 | E6: 17715.575 | F6: =SUM(B6:E6) -> 106859.71 | H6: 44562 | I6: 4387.8546 | J6: 0 | K6: =4192.779187-10700876.86/10000 -> 3122.6915 | L6: 5.083477 | M6: =SUM(I6:L6) -> 7515.6295 | O6: 22.1月累计 | P6: =B6 -> 15562.122 | Q6: =C6 -> 41149.968 | R6: =D6 -> 32432.045 | S6: =E6 -> 17715.575 | T6: =SUM(P6:S6) -> 106859.71 | U6: =F6-T6 -> 0
A7: 44593 | B7: 14076.505 | C7: 31152.277 | D7: 25233.803 | E7: 15090.849 | F7: =SUM(B7:E7) -> 85553.434 | H7: 44593 | I7: 5990.0821 | J7: 0 | K7: 4623.5252 | L7: 5.140155 | M7: =SUM(I7:L7) -> 10618.747 | O7: 22.2月累计 | P7: =SUM(B6:B7) -> 29638.627 | Q7: =SUM(C6:C7) -> 72302.245 | R7: =SUM(D6:D7) -> 57665.848 | S7: =SUM(E6:E7) -> 32806.424 | T7: =SUM(P7:S7) -> 192413.14 | U7: =F6+F7-T7 -> 0
A8: 44621 | B8: 12114.914 | C8: 42817.482 | D8: 44380.459 | E8: 32668.862 | F8: =SUM(B8:E8) -> 131981.72 | H8: 44621 | I8: 2088.9152 | J8: 0 | K8: 4915.631 | L8: 11.129806 | M8: =SUM(I8:L8) -> 7015.676 | O8: 22.3月累计 | P8: =SUM(B6:B8) -> 41753.541 | Q8: =SUM(C6:C8) -> 115119.73 | R8: =SUM(D6:D8) -> 102046.31 | S8: =SUM(E6:E8) -> 65475.286 | T8: =SUM(P8:S8) -> 324394.86 | U8: =F6+F7+F8-T8 -> 0
A9: 44652 | B9: 14206.269 | C9: 45294.442 | D9: 34967.361 | E9: 26161.328 | F9: =SUM(B9:E9) -> 120629.4 | H9: 44652 | I9: 2976.7208 | J9: 0 | K9: 3104.262 | L9: 76.552124 | M9: =SUM(I9:L9) -> 6157.5349 | O9: 22.4月累计 | P9: =SUM(B6:B9) -> 55959.81 | Q9: =SUM(C6:C9) -> 160414.17 | R9: =SUM(D6:D9) -> 137013.67 | S9: =SUM(E6:E9) -> 91636.614 | T9: =SUM(F6:F9) -> 445024.26 | U9: =F6+F7+F8+F9-T9 -> 0
A10: 44682 | B10: 9219.1403 | C10: 53111 | D10: 39081.808 | E10: 32483.137 | F10: =SUM(B10:E10) -> 133895.09 | H10: 44682 | I10: 6742.3218 | J10: 0 | K10: 2621.4735 | L10: 146.84333 | M10: =SUM(I10:L10) -> 9510.6386 | O10: 22.5月累计 | P10: =SUM(B$6:B10) -> 65178.951 | Q10: =SUM(C$6:C10) -> 213525.17 | R10: =SUM(D$6:D10) -> 176095.48 | S10: =SUM(E$6:E10) -> 124119.75 | T10: =SUM(F$6:F10) -> 578919.35 | U10: =SUM(F$6:F10)-T10 -> 0 | BE10: =利润组成!I10 -> 2273.8984
A11: 44713 | B11: 10707.165 | C11: 48364.974 | D11: 50326.21 | E11: 34162.588 | F11: =SUM(B11:E11) -> 143560.94 | H11: 44713 | I11: 6466.8323 | J11: 0 | K11: 3633.9463 | L11: 67.908485 | M11: =SUM(I11:L11) -> 10168.687 | O11: 22.6月累计 | P11: =SUM(B$6:B11) -> 75886.116 | Q11: =SUM(C$6:C11) -> 261890.14 | R11: =SUM(D$6:D11) -> 226421.69 | S11: =SUM(E$6:E11) -> 158282.34 | T11: =SUM(F$6:F11) -> 722480.29 | U11: =SUM(F$6:F11)-T11 -> 0
A12: 44743 | B12: 12671.201 | C12: 41179.453 | D12: 39099.96 | E12: 27412.087 | F12: =SUM(B12:E12) -> 120362.7 | H12: 44743 | I12: 10035.94 | J12: 0 | K12: 2294.1256 | L12: 136.80383 | M12: =SUM(I12:L12) -> 12466.87 | O12: 22.7月累计 | P12: =SUM(B$6:B12) -> 88557.317 | Q12: =SUM(C$6:C12) -> 303069.6 | R12: =SUM(D$6:D12) -> 265521.65 | S12: =SUM(E$6:E12) -> 185694.43 | T12: =SUM(F$6:F12) -> 842842.99 | U12: =SUM(F$6:F12)-T12 -> 0
A13: 44774 | B13: 9372.45 | C13: 38654.479 | D13: 51219.403 | E13: 34192.42 | F13: =SUM(B13:E13) -> 133438.75 | H13: 44774 | I13: 10958.182 | J13: 11.8727 | K13: 2692.0308 | L13: 48.074971 | M13: =SUM(I13:L13) -> 13710.161 | O13: 22.8月累计 | P13: =SUM(B$6:B13) -> 97929.767 | Q13: =SUM(C$6:C13) -> 341724.08 | R13: =SUM(D$6:D13) -> 316741.05 | S13: =SUM(E$6:E13) -> 219886.85 | T13: =SUM(F$6:F13) -> 976281.74 | U13: =SUM(F$6:F13)-T13 -> 0
A14: 44805 | B14: 10606.299 | C14: 49317.65 | D14: 60488.792 | E14: 28355.042 | F14: =SUM(B14:E14) -> 148767.78 | H14: 44805 | I14: 4801.8929 | J14: 6.47468 | K14: 2407.4536 | L14: 48.727836 | M14: =SUM(I14:L14) -> 7264.5491 | O14: 22.9月累计 | P14: =SUM(B$6:B14) -> 108536.07 | Q14: =SUM(C$6:C14) -> 391041.73 | R14: =SUM(D$6:D14) -> 377229.84 | S14: =SUM(E$6:E14) -> 248241.89 | T14: =SUM(F$6:F14) -> 1125049.5 | U14: =SUM(F$6:F14)-T14 -> 0
A15: 44835 | B15: 13056.391 | C15: 43886.806 | D15: 51416.646 | E15: 34699.103 | F15: =SUM(B15:E15) -> 143058.95 | H15: 44835 | I15: 3925.7006 | J15: 9.18 | K15: 5752.1243 | L15: 100.50607 | M15: =SUM(I15:L15) -> 9787.5109 | O15: 22.10月累计 | P15: =SUM(B$6:B15) -> 121592.46 | Q15: =SUM(C$6:C15) -> 434928.53 | R15: =SUM(D$6:D15) -> 428646.49 | S15: =SUM(E$6:E15) -> 282940.99 | T15: =SUM(F$6:F15) -> 1268108.5 | U15: =SUM(F$6:F15)-T15 -> 0
A16: 44866 | B16: 17466.72 | C16: 45892.11 | D16: 70039.856 | E16: 41466.237 | F16: =SUM(B16:E16) -> 174864.92 | H16: 44866 | I16: 2767.0592 | J16: 16.5 | K16: 14435.598 | L16: 102.24792 | M16: =SUM(I16:L16) -> 17321.405 | O16: 22.11月累计 | P16: =SUM(B$6:B16) -> 139059.18 | Q16: =SUM(C$6:C16) -> 480820.64 | R16: =SUM(D$6:D16) -> 498686.34 | S16: =SUM(E$6:E16) -> 324407.23 | T16: =SUM(F$6:F16) -> 1442973.4 | U16: =SUM(F$6:F16)-T16 -> 0
A17: 44896 | B17: 16322.574 | C17: 36009.275 | D17: 77708.158 | E17: 41229.57 | F17: =SUM(B17:E17) -> 171269.58 | H17: 44896 | I17: 6465.6015 | J17: 12.68 | K17: 3854.7639 | L17: 48.219133 | M17: =SUM(I17:L17) -> 10381.265 | O17: 22.12月累计 | P17: =SUM(B$6:B17) -> 155381.75 | Q17: =SUM(C$6:C17) -> 516829.92 | R17: =SUM(D$6:D17) -> 576394.5 | S17: =SUM(E$6:E17) -> 365636.8 | T17: =SUM(F$6:F17) -> 1614243 | U17: =SUM(F$6:F17)-T17 -> 0
A18: 44927 | B18: 22985.957 | C18: 29278.75 | D18: 48836.984 | E18: 33479.892 | F18: =SUM(B18:E18) -> 134581.58 | H18: 44927 | I18: 8717.3265 | J18: 12.262499 | K18: 3675.8348 | L18: 181.94649 | M18: =SUM(I18:L18) -> 12587.37 | O18: 23.1月累计 | P18: =SUM(B$18:B18) -> 22985.957 | Q18: =SUM(C$18:C18) -> 29278.75 | R18: =SUM(D$18:D18) -> 48836.984 | S18: =SUM(E$18:E18) -> 33479.892 | T18: =SUM(F$18:F18) -> 134581.58 | U18: =SUM(F$18:F18)-T18 -> 0
A19: 44958 | B19: 13458.743 | C19: 38417.38 | D19: 45017.964 | E19: 35005.079 | F19: =SUM(B19:E19) -> 131899.17 | H19: 44958 | I19: 1957.218 | J19: 8.12 | K19: 3062.0267 | L19: 183.71913 | M19: =SUM(I19:L19) -> 5211.0838 | O19: 23.2月累计 | P19: =SUM(B$18:B19) -> 36444.7 | Q19: =SUM(C$18:C19) -> 67696.13 | R19: =SUM(D$18:D19) -> 93854.948 | S19: =SUM(E$18:E19) -> 68484.972 | T19: =SUM(F$18:F19) -> 266480.75 | U19: =SUM(F$18:F19)-T19 -> 0
A20: 44986 | B20: 17676.956 | C20: 40696.017 | D20: 46753.233 | E20: 48184.023 | F20: =SUM(B20:E20) -> 153310.23 | H20: 44986 | I20: 2461.8081 | J20: 9.03 | K20: 3598.4196 | L20: 346.83816 | M20: =SUM(I20:L20) -> 6416.0958 | O20: 23.3月累计 | P20: =SUM(B$18:B20) -> 54121.656 | Q20: =SUM(C$18:C20) -> 108392.15 | R20: =SUM(D$18:D20) -> 140608.18 | S20: =SUM(E$18:E20) -> 116668.99 | T20: =SUM(F$18:F20) -> 419790.98 | U20: =SUM(F$18:F20)-T20 -> 0
A21: 45017 | B21: 25100.247 | C21: 14908.958 | D21: 38626.757 | E21: 46617.332 | F21: =SUM(B21:E21) -> 125253.29 | H21: 45017 | I21: 5390.9896 | J21: 9.18 | K21: 2658.6327 | L21: 234.83171 | M21: =SUM(I21:L21) -> 8293.634 | O21: 23.4月累计 | P21: =SUM(B$18:B21) -> 79221.903 | Q21: =SUM(C$18:C21) -> 123301.1 | R21: =SUM(D$18:D21) -> 179234.94 | S21: =SUM(E$18:E21) -> 163286.33 | T21: =SUM(F$18:F21) -> 545044.27 | U21: =SUM(F$18:F21)-T21 -> 0
A22: 45047 | B22: 43935.387 | C22: 14554.824 | D22: 34806.915 | E22: 54574.306 | F22: =SUM(B22:E22) -> 147871.43 | H22: 45047 | I22: 3448.4603 | J22: 13.992 | K22: 3232.3424 | L22: 217.85892 | M22: =SUM(I22:L22) -> 6912.6536 | O22: 23.5月累计 | P22: =SUM(B$18:B22) -> 123157.29 | Q22: =SUM(C$18:C22) -> 137855.93 | R22: =SUM(D$18:D22) -> 214041.85 | S22: =SUM(E$18:E22) -> 217860.63 | T22: =SUM(F$18:F22) -> 692915.7 | U22: =SUM(F$18:F22)-T22 -> 0
A23: 45078 | B23: 32343.39 | C23: 18696.408 | D23: 40582.857 | E23: 65744.246 | F23: =SUM(B23:E23) -> 157366.9 | H23: 45078 | I23: 6201.1524 | J23: 14.215787 | K23: 7663.1537 | L23: 103.10123 | M23: =SUM(I23:L23) -> 13981.623 | O23: 23.6月累计 | P23: =SUM(B$18:B23) -> 155500.68 | Q23: =SUM(C$18:C23) -> 156552.34 | R23: =SUM(D$18:D23) -> 254624.71 | S23: =SUM(E$18:E23) -> 283604.88 | T23: =SUM(F$18:F23) -> 850282.61 | U23: =SUM(F$18:F23)-T23 -> 0
A24: 45108 | B24: 28119.744 | C24: 12591.962 | D24: 35418.136 | E24: 55283.671 | F24: =SUM(B24:E24) -> 131413.51 | H24: 45108 | I24: 4318.7701 | J24: 4.58556 | K24: 1258.7993 | L24: 153.71552 | M24: =SUM(I24:L24) -> 5735.8705 | O24: 23.7月累计 | P24: =SUM(B$18:B24) -> 183620.42 | Q24: =SUM(C$18:C24) -> 169144.3 | R24: =SUM(D$18:D24) -> 290042.85 | S24: =SUM(E$18:E24) -> 338888.55 | T24: =SUM(F$18:F24) -> 981696.12 | U24: =SUM(F$18:F24)-T24 -> 0
A25: 45139 | B25: 31944.261 | C25: 12342.18 | D25: 41823.418 | E25: 61102.222 | F25: =SUM(B25:E25) -> 147212.08 | H25: 45139 | I25: 3321.2574 | J25: 5.38556 | K25: 3013.4321 | L25: 163.52699 | M25: =SUM(I25:L25) -> 6503.6021 | O25: 23.8月累计 | P25: =SUM(B$18:B25) -> 215564.69 | Q25: =SUM(C$18:C25) -> 181486.48 | R25: =SUM(D$18:D25) -> 331866.26 | S25: =SUM(E$18:E25) -> 399990.77 | T25: =SUM(F$18:F25) -> 1128908.2 | U25: =SUM(F$18:F25)-T25 -> 0
A26: 45170 | B26: 26550.641 | C26: 9782.9884 | D26: 39707.166 | E26: 49936.582 | F26: =SUM(B26:E26) -> 125977.38 | H26: 45170 | I26: 2234.3568 | J26: 4.58556 | K26: 2310.1934 | L26: 487.66586 | M26: =SUM(I26:L26) -> 5036.8016 | O26: 23.9月累计 | P26: =SUM(B$18:B26) -> 242115.33 | Q26: =SUM(C$18:C26) -> 191269.47 | R26: =SUM(D$18:D26) -> 371573.43 | S26: =SUM(E$18:E26) -> 449927.35 | T26: =SUM(F$18:F26) -> 1254885.6 | U26: =SUM(F$18:F26)-T26 -> 0
A27: 45200 | B27: 12543.917 | C27: 7231.0873 | D27: 39956.302 | E27: 36591.304 | F27: =SUM(B27:E27) -> 96322.61 | H27: 45200 | I27: 6299.048 | J27: 4.58556 | K27: 5807.4646 | L27: 303.72356 | M27: =SUM(I27:L27) -> 12414.822 | O27: 23.10月累计 | P27: =SUM(B$18:B27) -> 254659.24 | Q27: =SUM(C$18:C27) -> 198500.56 | R27: =SUM(D$18:D27) -> 411529.73 | S27: =SUM(E$18:E27) -> 486518.66 | T27: =SUM(F$18:F27) -> 1351208.2 | U27: =SUM(F$18:F27)-T27 -> 0
A28: 45231 | B28: 19942.474 | C28: 8024.2668 | D28: 52214.699 | E28: 34336.302 | F28: =SUM(B28:E28) -> 114517.74 | H28: 45231 | I28: 3365.3592 | J28: 4.58556 | K28: 17449.895 | L28: 256.44079 | M28: =SUM(I28:L28) -> 21076.281 | O28: 23.11月累计 | P28: =SUM(B$18:B28) -> 274601.72 | Q28: =SUM(C$18:C28) -> 206524.82 | R28: =SUM(D$18:D28) -> 463744.43 | S28: =SUM(E$18:E28) -> 520854.96 | T28: =SUM(F$18:F28) -> 1465725.9 | U28: =SUM(F$18:F28)-T28 -> 0
A29: 45261 | B29: 13627.585 | C29: 5818.0122 | D29: 41859.163 | E29: 33422.887 | F29: =SUM(B29:E29) -> 94727.646 | H29: 45261 | I29: 3043.306 | J29: 1.40556 | K29: 6536.8039 | L29: 545.04105 | M29: =SUM(I29:L29) -> 10126.556 | O29: 23.12月累计 | P29: =SUM(B$18:B29) -> 288229.3 | Q29: =SUM(C$18:C29) -> 212342.83 | R29: =SUM(D$18:D29) -> 505603.59 | S29: =SUM(E$18:E29) -> 554277.85 | T29: =SUM(F$18:F29) -> 1560453.6 | U29: =SUM(F$18:F29)-T29 -> 0
A30: 45292 | B30: 23601.284 | C30: 5765.1169 | D30: 22038.104 | E30: 32437.158 | F30: =SUM(B30:E30) -> 83841.662 | H30: 45292 | I30: 2606.7452 | J30: 1.40556 | K30: 4146.2481 | L30: 408.75621 | M30: =SUM(I30:L30) -> 7163.1551 | O30: 24.1月累计 | P30: =B30 -> 23601.284 | Q30: =C30 -> 5765.1169 | R30: =D30 -> 22038.104 | S30: =E30 -> 32437.158 | T30: =SUM(F$30:F30) -> 83841.662 | U30: =SUM(F$30:F30)-T30 -> 0
A31: 45323 | B31: 20769.152 | C31: 5186.9185 | D31: 20630.623 | E31: 29631.355 | F31: =SUM(B31:E31) -> 76218.049 | H31: 45323 | I31: 10232.519 | K31: 3119.2019 | L31: 2032.2219 | M31: =SUM(I31:L31) -> 15383.942 | O31: 24.2月累计 | P31: =SUM(B$30:B31) -> 44370.436 | Q31: =SUM(C$30:C31) -> 10952.035 | R31: =SUM(D$30:D31) -> 42668.728 | S31: =SUM(E$30:E31) -> 62068.513 | T31: =SUM(F$30:F31) -> 160059.71 | U31: =SUM(F$30:F31)-T31 -> 0
A32: 45352 | B32: 8118.2167 | C32: 6157.9069 | D32: 24007.575 | E32: 28549.19 | F32: =SUM(B32:E32) -> 66832.889 | H32: 45352 | I32: 3172.7512 | K32: 3005.3106 | L32: 431.14546 | M32: =SUM(I32:L32) -> 6609.2073 | O32: 24.3月累计 | P32: =SUM(B$30:B32) -> 52488.653 | Q32: =SUM(C$30:C32) -> 17109.942 | R32: =SUM(D$30:D32) -> 66676.303 | S32: =SUM(E$30:E32) -> 90617.703 | T32: =SUM(F$30:F32) -> 226892.6 | U32: =SUM(F$30:F32)-T32 -> 0
A33: 45383 | B33: 6779.3447 | C33: 3106.4079 | D33: 23861.802 | E33: 16597.742 | F33: =SUM(B33:E33) -> 50345.297 | H33: 45383 | I33: 5056.8368 | K33: 3485.7076 | L33: 389.40499 | M33: =SUM(I33:L33) -> 8931.9493 | O33: 24.4月累计 | P33: =SUM(B$30:B33) -> 59267.997 | Q33: =SUM(C$30:C33) -> 20216.35 | R33: =SUM(D$30:D33) -> 90538.105 | S33: =SUM(E$30:E33) -> 107215.45 | T33: =SUM(F$30:F33) -> 277237.9 | U33: =SUM(F$30:F33)-T33 -> 0
A34: 45413 | B34: 11730.663 | C34: 2316.277 | D34: 29948.51 | E34: 26557.516 | F34: =SUM(B34:E34) -> 70552.966 | H34: 45413 | I34: 4967.366 | K34: 6648.8448 | L34: 531.37 | M34: =SUM(I34:L34) -> 12147.581 | O34: 24.5月累计 | P34: =SUM(B$30:B34) -> 70998.66 | Q34: =SUM(C$30:C34) -> 22532.627 | R34: =SUM(D$30:D34) -> 120486.61 | S34: =SUM(E$30:E34) -> 133772.96 | T34: =SUM(F$30:F34) -> 347790.86 | U34: =SUM(F$30:F34)-T34 -> 0
A35: 45444 | B35: 16980.061 | C35: 1416.8628 | D35: 34860.498 | E35: 30545.326 | F35: =SUM(B35:E35) -> 83802.748 | H35: 45444 | I35: 10999.47 | K35: 7520.4433 | L35: 723.3 | M35: =SUM(I35:L35) -> 19243.214 | O35: 24.6月累计 | P35: =SUM(B$30:B35) -> 87978.721 | Q35: =SUM(C$30:C35) -> 23949.49 | R35: =SUM(D$30:D35) -> 155347.11 | S35: =SUM(E$30:E35) -> 164318.29 | T35: =SUM(F$30:F35) -> 431593.61 | U35: =SUM(F$30:F35)-T35 -> 0
A36: 45474 | B36: 21559.693 | C36: 1491.3498 | D36: 24546.108 | E36: 34407.826 | F36: =SUM(B36:E36) -> 82004.978 | H36: 45474 | I36: 4406.6869 | K36: 1998.9466 | L36: 1224.3059 | M36: =SUM(I36:L36) -> 7629.9394 | O36: 24.7月累计 | P36: =SUM(B$30:B36) -> 109538.41 | Q36: =SUM(C$30:C36) -> 25440.84 | R36: =SUM(D$30:D36) -> 179893.22 | S36: =SUM(E$30:E36) -> 198726.11 | T36: =SUM(F$30:F36) -> 513598.59 | U36: =SUM(F$30:F36)-T36 -> 0
A37: 45505 | B37: 11582.725 | C37: 2548.1143 | D37: 30002.115 | E37: 31032.816 | F37: =SUM(B37:E37) -> 75165.771 | H37: 45505 | I37: 8877.5906 | K37: 3003.7321 | L37: 799.63586 | M37: =SUM(I37:L37) -> 12680.959 | O37: 24.8月累计 | P37: =SUM(B$30:B37) -> 121121.14 | Q37: =SUM(C$30:C37) -> 27988.954 | R37: =SUM(D$30:D37) -> 209895.34 | S37: =SUM(E$30:E37) -> 229758.93 | T37: =SUM(F$30:F37) -> 588764.36 | U37: =SUM(F$30:F37)-T37 -> 0
A38: 45536 | B38: 7748.1548 | C38: 1290.6205 | D38: 22928.796 | E38: 20650.533 | F38: =SUM(B38:E38) -> 52618.104 | H38: 45536 | I38: 2401.1597 | K38: 2945.145 | L38: 3606.8474 | M38: =SUM(I38:L38) -> 8953.152 | O38: 24.9月累计 | P38: =SUM(B$30:B38) -> 128869.29 | Q38: =SUM(C$30:C38) -> 29279.575 | R38: =SUM(D$30:D38) -> 232824.13 | S38: =SUM(E$30:E38) -> 250409.46 | T38: =SUM(F$30:F38) -> 641382.46 | U38: =SUM(F$30:F38)-T38 -> 0
A39: 45566 | B39: 8640.5599 | C39: 947.17146 | D39: 23255.981 | E39: 26167.658 | F39: =SUM(B39:E39) -> 59011.37 | H39: 45566 | I39: 2063.7107 | K39: 11952.29 | L39: 438.80086 | M39: =SUM(I39:L39) -> 14454.802 | O39: 24.10月累计 | P39: =SUM(B$30:B39) -> 137509.85 | Q39: =SUM(C$30:C39) -> 30226.746 | R39: =SUM(D$30:D39) -> 256080.11 | S39: =SUM(E$30:E39) -> 276577.12 | T39: =SUM(F$30:F39) -> 700393.83 | U39: =SUM(F$30:F39)-T39 -> 0
A40: 45597 | B40: 8649.1159 | C40: 695.88389 | D40: 25892.265 | E40: 26575.697 | F40: =SUM(B40:E40) -> 61812.962 | H40: 45597 | I40: 5278.1732 | J40: 0 | K40: 14752.049 | L40: 396.88679 | M40: =SUM(I40:L40) -> 20427.109 | O40: 24.11月累计 | P40: =SUM(B$30:B40) -> 146158.97 | Q40: =SUM(C$30:C40) -> 30922.63 | R40: =SUM(D$30:D40) -> 281972.38 | S40: =SUM(E$30:E40) -> 303152.82 | T40: =SUM(F$30:F40) -> 762206.8 | U40: =SUM(F$30:F40)-T40 -> 0
A41: 45627 | B41: 5261.5445 | C41: 616.13959 | D41: 26412.947 | E41: 27908.633 | F41: =SUM(B41:E41) -> 60199.264 | H41: 45627 | I41: 3527.5771 | J41: 0 | K41: 2807.241 | L41: 376.75544 | M41: =SUM(I41:L41) -> 6711.5736 | O41: 24.12月累计 | P41: =SUM(B$30:B41) -> 151420.51 | Q41: =SUM(C$30:C41) -> 31538.77 | R41: =SUM(D$30:D41) -> 308385.33 | S41: =SUM(E$30:E41) -> 331061.45 | T41: =SUM(F$30:F41) -> 822406.06 | U41: =SUM(F$30:F41)-T41 -> 0
A42: 45658 | B42: =('GMV销售额波动分析（分月、年）'!B2+'GMV销售额波动分析（分月、年）'!C2)/10000 -> 12010.341 | C42: ='GMV销售额波动分析（分月、年）'!D2/10000 -> 943.58125 | D42: ='GMV销售额波动分析（分月、年）'!E2/10000 -> 20356.185 | E42: =('GMV销售额波动分析（分月、年）'!F2+'GMV销售额波动分析（分月、年）'!G2)/10000 -> 36582.368 | F42: =SUM(B42:E42) -> 69892.476 | H42: 45658 | I42: 3873.4832 | J42: 0 | K42: 7302.5091 | L42: 7741.7946 | M42: =SUM(I42:L42) -> 18917.787 | O42: 25.1月累计 | P42: =B42 -> 12010.341 | Q42: =C42 -> 943.58125 | R42: =D42 -> 20356.185 | S42: =E42 -> 36582.368 | T42: =F42 -> 69892.476 | U42: =SUM(P42:S42)-T42 -> 0
A43: 45689 | B43: =('GMV销售额波动分析（分月、年）'!B3+'GMV销售额波动分析（分月、年）'!C3)/10000 -> 6319.9431 | C43: ='GMV销售额波动分析（分月、年）'!D3/10000 -> 1222.4513 | D43: ='GMV销售额波动分析（分月、年）'!E3/10000 -> 18650.532 | E43: =('GMV销售额波动分析（分月、年）'!F3+'GMV销售额波动分析（分月、年）'!G3)/10000 -> 29014.014 | F43: =SUM(B43:E43) -> 55206.939 | H43: 45689 | I43: 7770.2479 | J43: 0 | K43: 5671.2699 | L43: 8903.8486 | M43: =SUM(I43:L43) -> 22345.366 | O43: 25.2月累计 | P43: =SUM(B$42:B43) -> 18330.284 | Q43: =SUM(C$42:C43) -> 2166.0325 | R43: =SUM(D$42:D43) -> 39006.717 | S43: =SUM(E$42:E43) -> 65596.382 | T43: =SUM($F$42:F43) -> 125099.42 | U43: =SUM(P43:S43)-T43 -> 0
A44: 45717 | B44: =('GMV销售额波动分析（分月、年）'!B4+'GMV销售额波动分析（分月、年）'!C4)/10000 -> 6218.2107 | C44: ='GMV销售额波动分析（分月、年）'!D4/10000 -> 458.24586 | D44: ='GMV销售额波动分析（分月、年）'!E4/10000 -> 18891.607 | E44: =('GMV销售额波动分析（分月、年）'!F4+'GMV销售额波动分析（分月、年）'!G4)/10000 -> 41030.325 | F44: =SUM(B44:E44) -> 66598.388 | H44: 45717 | I44: 2919.8751 | J44: 0 | K44: 4180.5542 | L44: 9969.9799 | M44: =SUM(I44:L44) -> 17070.409 | O44: 25.3月累计 | P44: =SUM(B$42:B44) -> 24548.495 | Q44: =SUM(C$42:C44) -> 2624.2784 | R44: =SUM(D$42:D44) -> 57898.324 | S44: =SUM(E$42:E44) -> 106626.71 | T44: =SUM($F$42:F44) -> 191697.8 | U44: =SUM(P44:S44)-T44 -> 0
A45: 45748 | B45: =('GMV销售额波动分析（分月、年）'!B5+'GMV销售额波动分析（分月、年）'!C5)/10000 -> 7349.8678 | C45: ='GMV销售额波动分析（分月、年）'!D5/10000 -> 336.01438 | D45: ='GMV销售额波动分析（分月、年）'!E5/10000 -> 17304.789 | E45: =('GMV销售额波动分析（分月、年）'!F5+'GMV销售额波动分析（分月、年）'!G5)/10000 -> 35355.334 | F45: =SUM(B45:E45) -> 60346.005 | H45: 45748 | I45: 2883.8894 | J45: 0 | K45: 3460.2481 | L45: 11398.456 | M45: =SUM(I45:L45) -> 17742.593 | O45: 25.4月累计 | P45: =SUM(B$42:B45) -> 31898.362 | Q45: =SUM(C$42:C45) -> 2960.2928 | R45: =SUM(D$42:D45) -> 75203.113 | S45: =SUM(E$42:E45) -> 141982.04 | T45: =SUM($F$42:F45) -> 252043.81 | U45: =SUM(P45:S45)-T45 -> -2.910383e-10
A46: 45778 | B46: =('GMV销售额波动分析（分月、年）'!B6+'GMV销售额波动分析（分月、年）'!C6)/10000 -> 13757.203 | C46: ='GMV销售额波动分析（分月、年）'!D6/10000 -> 336.66039 | D46: ='GMV销售额波动分析（分月、年）'!E6/10000 -> 17290.566 | E46: =('GMV销售额波动分析（分月、年）'!F6+'GMV销售额波动分析（分月、年）'!G6)/10000 -> 29087.399 | F46: =SUM(B46:E46) -> 60471.829 | H46: 45778 | I46: 6031.1983 | J46: 0 | K46: 13278.392 | L46: 17001.143 | M46: =SUM(I46:L46) -> 36310.733 | O46: 25.5月累计 | P46: =SUM(B$42:B46) -> 45655.565 | Q46: =SUM(C$42:C46) -> 3296.9531 | R46: =SUM(D$42:D46) -> 92493.679 | S46: =SUM(E$42:E46) -> 171069.44 | T46: =SUM($F$42:F46) -> 312515.64 | U46: =SUM(P46:S46)-T46 -> 0
A47: 45809 | B47: =('GMV销售额波动分析（分月、年）'!B7+'GMV销售额波动分析（分月、年）'!C7)/10000 -> 8665.0436 | C47: ='GMV销售额波动分析（分月、年）'!D7/10000 -> 288.05918 | D47: ='GMV销售额波动分析（分月、年）'!E7/10000 -> 12474.516 | E47: =('GMV销售额波动分析（分月、年）'!F7+'GMV销售额波动分析（分月、年）'!G7)/10000 -> 35486.366 | F47: =SUM(B47:E47) -> 56913.985 | H47: 45809 | I47: 3554.3978 | J47: 0 | K47: 10943.31 | L47: 15068.378 | M47: =SUM(I47:L47) -> 29566.086 | O47: 25.6月累计 | P47: =SUM(B$42:B47) -> 54320.609 | Q47: =SUM(C$42:C47) -> 3585.0123 | R47: =SUM(D$42:D47) -> 104968.2 | S47: =SUM(E$42:E47) -> 206555.81 | T47: =SUM($F$42:F47) -> 369429.62 | U47: =SUM(P47:S47)-T47 -> 0
A48: 45839 | B48: =('GMV销售额波动分析（分月、年）'!B8+'GMV销售额波动分析（分月、年）'!C8)/10000 -> 8752.1063 | C48: ='GMV销售额波动分析（分月、年）'!D8/10000 -> 295.71784 | D48: ='GMV销售额波动分析（分月、年）'!E8/10000 -> 7512.5965 | E48: =('GMV销售额波动分析（分月、年）'!F8+'GMV销售额波动分析（分月、年）'!G8)/10000 -> 46471.834 | F48: =SUM(B48:E48) -> 63032.255 | H48: 45839 | I48: 4544.1218 | J48: 0 | K48: 4437.3976 | L48: 3975.4658 | M48: =SUM(I48:L48) -> 12956.985 | O48: 25.7月累计 | P48: =SUM(B$42:B48) -> 63072.715 | Q48: =SUM(C$42:C48) -> 3880.7302 | R48: =SUM(D$42:D48) -> 112480.79 | S48: =SUM(E$42:E48) -> 253027.64 | T48: =SUM($F$42:F48) -> 432461.88 | U48: =SUM(P48:S48)-T48 -> 0
A49: 45870 | B49: =('GMV销售额波动分析（分月、年）'!B9+'GMV销售额波动分析（分月、年）'!C9)/10000 -> 9644.6862 | C49: ='GMV销售额波动分析（分月、年）'!D9/10000 -> 364.70534 | D49: ='GMV销售额波动分析（分月、年）'!E9/10000 -> 8431.5661 | E49: =('GMV销售额波动分析（分月、年）'!F9+'GMV销售额波动分析（分月、年）'!G9)/10000 -> 52606.912 | F49: =SUM(B49:E49) -> 71047.869 | H49: 45870 | I49: 6020.9333 | J49: 0 | K49: 7980.4875 | L49: 2609.9911 | M49: =SUM(I49:L49) -> 16611.412 | O49: 25.8月累计 | P49: =SUM(B$42:B49) -> 72717.401 | Q49: =SUM(C$42:C49) -> 4245.4355 | R49: =SUM(D$42:D49) -> 120912.36 | S49: =SUM(E$42:E49) -> 305634.55 | T49: =SUM($F$42:F49) -> 503509.75 | U49: =SUM(P49:S49)-T49 -> 0
A50: 45901 | B50: =('GMV销售额波动分析（分月、年）'!B10+'GMV销售额波动分析（分月、年）'!C10)/10000 -> 13650.283 | C50: ='GMV销售额波动分析（分月、年）'!D10/10000 -> 331.53327 | D50: ='GMV销售额波动分析（分月、年）'!E10/10000 -> 8711.8571 | E50: =('GMV销售额波动分析（分月、年）'!F10+'GMV销售额波动分析（分月、年）'!G10)/10000 -> 50456.092 | F50: =SUM(B50:E50) -> 73149.766 | H50: 45901 | I50: 6432.069 | J50: 0 | K50: 8794.7754 | L50: 2349.2172 | M50: =SUM(I50:L50) -> 17576.062 | O50: 25.9月累计 | P50: =SUM(B$42:B50) -> 86367.684 | Q50: =SUM(C$42:C50) -> 4576.9688 | R50: =SUM(D$42:D50) -> 129624.21 | S50: =SUM(E$42:E50) -> 356090.64 | T50: =SUM($F$42:F50) -> 576659.51 | U50: =SUM(P50:S50)-T50 -> 0
A51: 45931 | B51: =('GMV销售额波动分析（分月、年）'!B11+'GMV销售额波动分析（分月、年）'!C11)/10000 -> 12824.209 | C51: ='GMV销售额波动分析（分月、年）'!D11/10000 -> 344.01091 | D51: ='GMV销售额波动分析（分月、年）'!E11/10000 -> 9268.1238 | E51: =('GMV销售额波动分析（分月、年）'!F11+'GMV销售额波动分析（分月、年）'!G11)/10000 -> 39730.187 | F51: =SUM(B51:E51) -> 62166.531 | H51: 45931 | I51: 2692.2485 | J51: 0 | K51: 23020.469 | L51: 2409.8356 | M51: =SUM(I51:L51) -> 28122.553 | O51: 25.10月累计 | P51: =SUM(B$42:B51) -> 99191.894 | Q51: =SUM(C$42:C51) -> 4920.9797 | R51: =SUM(D$42:D51) -> 138892.34 | S51: =SUM(E$42:E51) -> 395820.83 | T51: =SUM($F$42:F51) -> 638826.04 | U51: =SUM(P51:S51)-T51 -> 0
A52: 45962 | B52: =('GMV销售额波动分析（分月、年）'!B12+'GMV销售额波动分析（分月、年）'!C12)/10000 -> 14063.886 | C52: ='GMV销售额波动分析（分月、年）'!D12/10000 -> 341.3736 | D52: ='GMV销售额波动分析（分月、年）'!E12/10000 -> 10587.371 | E52: =('GMV销售额波动分析（分月、年）'!F12+'GMV销售额波动分析（分月、年）'!G12)/10000 -> 40654.617 | F52: =SUM(B52:E52) -> 65647.248 | H52: 45962 | I52: 5098.3821 | J52: 0 | K52: 21679.787 | L52: 3654.8428 | M52: =SUM(I52:L52) -> 30433.012 | O52: 25.11月累计 | P52: =SUM(B$42:B52) -> 113255.78 | Q52: =SUM(C$42:C52) -> 5262.3533 | R52: =SUM(D$42:D52) -> 149479.71 | S52: =SUM(E$42:E52) -> 436475.45 | T52: =SUM($F$42:F52) -> 704473.29 | U52: =SUM(P52:S52)-T52 -> 0
A53: 45992 | B53: =('GMV销售额波动分析（分月、年）'!B13+'GMV销售额波动分析（分月、年）'!C13)/10000 -> 13745.987 | C53: ='GMV销售额波动分析（分月、年）'!D13/10000 -> 334.28886 | D53: ='GMV销售额波动分析（分月、年）'!E13/10000 -> 11975.211 | E53: =('GMV销售额波动分析（分月、年）'!F13+'GMV销售额波动分析（分月、年）'!G13)/10000 -> 61154.734 | F53: =SUM(B53:E53) -> 87210.22 | H53: 45992 | I53: 5492.0504 | J53: 0 | K53: 14873.479 | L53: 3923.0609 | M53: =SUM(I53:L53) -> 24288.591 | O53: 25.12月累计 | P53: =SUM(B$42:B53) -> 127001.77 | Q53: =SUM(C$42:C53) -> 5596.6421 | R53: =SUM(D$42:D53) -> 161454.92 | S53: =SUM(E$42:E53) -> 497630.18 | T53: =SUM($F$42:F53) -> 791683.51 | U53: =SUM(P53:S53)-T53 -> 0
A56: 2020.1-本月 | B56: =SUM(#REF!) -> #REF! | C56: =SUM(#REF!) -> #REF! | D56: =SUM(#REF!) -> #REF! | E56: =SUM(#REF!) -> #REF! | F56: =SUM(B56:E56) -> #REF!
A57: 2021.1-本月 | B57: =SUM(#REF!) -> #REF! | C57: =SUM(#REF!) -> #REF! | D57: =SUM(#REF!) -> #REF! | E57: =SUM(#REF!) -> #REF! | F57: =SUM(B57:E57) -> #REF! | M57: =SUM(M18:M29) -> 114296.39
A58: 2022.1-本月 | B58: =SUM(B6:B17) -> 155381.75 | C58: =SUM(C6:C17) -> 516829.92 | D58: =SUM(D6:D17) -> 576394.5 | E58: =SUM(E6:E17) -> 365636.8 | F58: =SUM(B58:E58) -> 1614243 | M58: =M57-'[29]代运营店铺GMV统计2023年1-12月'!$AS$15 -> #REF!
A59: 2023.1-本月 | B59: =SUM(B18:B29) -> 288229.3 | C59: =SUM(C18:C29) -> 212342.83 | D59: =SUM(D18:D29) -> 505603.59 | E59: =SUM(E18:E29) -> 554277.85 | F59: =SUM(B59:E59) -> 1560453.6 | M59: =SUM(M42:M53) -> 271941.59
A60: 2024.1-本月 | B60: =SUM(B30:B41) -> 151420.51 | C60: =SUM(C30:C41) -> 31538.77 | D60: =SUM(D30:D41) -> 308385.33 | E60: =SUM(E30:E41) -> 331061.45 | F60: =SUM(B60:E60) -> 822406.06 | M60: =M59-'[32]代运营店铺GMV统计2025年1-12月'!$AY$15 -> 0
A61: 2025.1-本月 | B61: =SUM(B42:B53) -> 127001.77 | C61: =SUM(C42:C53) -> 5596.6421 | D61: =SUM(D42:D53) -> 161454.92 | E61: =SUM(E42:E53) -> 497630.18 | F61: =SUM(B61:E61) -> 791683.51
A63: 20年占比 | B63: =B56/$F$56 -> #REF! | C63: =C56/$F$56 -> #REF! | D63: =D56/$F$56 -> #REF! | E63: =E56/$F$56 -> #REF! | F63: =SUM(B63:E63) -> #REF!
A64: 21年占比 | B64: =B57/$F$57 -> #REF! | C64: =C57/$F$57 -> #REF! | D64: =D57/$F$57 -> #REF! | E64: =E57/$F$57 -> #REF! | F64: =SUM(B64:E64) -> #REF!
A65: 22年占比 | B65: =B58/$F$58 -> 0.09625673 | C65: =C58/$F$58 -> 0.3201686 | D65: =D58/$F$58 -> 0.357068 | E65: =E58/$F$58 -> 0.22650667 | F65: =SUM(B65:E65) -> 1
A66: 23年占比 | B66: =B59/$F$59 -> 0.18470867 | C66: =C59/$F$59 -> 0.13607764 | D66: =D59/$F$59 -> 0.32401066 | E66: =E59/$F$59 -> 0.35520303 | F66: =SUM(B66:E66) -> 1
A67: 24年占比 | B67: =B60/$F$60 -> 0.18411892 | C67: =C60/$F$60 -> 0.038349389 | D67: =D60/$F$60 -> 0.37497939 | E67: =E60/$F$60 -> 0.4025523 | F67: =SUM(B67:E67) -> 1
A68: 25年占比 | B68: =B61/$F$61 -> 0.16041987 | C68: =C61/$F$61 -> 0.0070692923 | D68: =D61/$F$61 -> 0.20393872 | E68: =E61/$F$61 -> 0.62857212 | F68: =SUM(B68:E68) -> 1
A69: 增长 | B69: =B61-B60 -> -24418.748 | C69: =C61-C60 -> -25942.127 | D69: =D61-D60 -> -146930.4 | E69: =E61-E60 -> 166568.73 | F69: =F61-F60 -> -30722.55
A70: 增长比率 | B70: =B69/B60 -> -0.16126446 | C70: =C69/C60 -> -0.82254723 | D70: =D69/D60 -> -0.4764507 | E70: =E69/E60 -> 0.50313538 | F70: =F69/F60 -> -0.037356911
A73: 45261
A74: 45627
A75: 45992

Sheet GMV表-品牌
A1: 3、品牌趋势波动，针对网娱、生活服务--22年数据波动做分析（分月）-只针对代理收入（订单差额收入+返点） | K1: 1月 | L1: 品牌分类 | M1: 求和项:调整后gmv | N1: 万元
A2: 网娱-GMV | L2: 生活-餐饮 | M2: 21763660 | N2: =M2/10000 -> 2176.366 | P2: 2024年 | Z2: 2023年 | AJ2: 2022年
A3: 月份 | B3: 网娱-影视会员 | C3: 网娱-音频 | D3: 网娱-视频直播 | E3: 网娱-知识阅读 | F3: 网娱-网络工具 | G3: 网娱-其他 | H3: 合计 | I3: check | L3: 生活-出行旅游 | M3: 7176144.8 | N3: =M3/10000 -> 717.61448 | P3: 月份 | Q3: 网娱-影视会员 | R3: 网娱-音频 | S3: 网娱-视频直播 | T3: 网娱-知识阅读 | U3: 网娱-网络工具 | V3: 网娱-其他 | W3: 合计 | X3: check | Z3: 月份 | AA3: 网娱-影视会员 | AB3: 网娱-音频 | AC3: 网娱-视频直播 | AD3: 网娱-知识阅读 | AE3: 网娱-网络工具 | AF3: 网娱-其他 | AG3: 合计 | AH3: check | AJ3: 月份 | AK3: 网娱-影视会员 | AL3: 网娱-音频 | AM3: 网娱-视频直播 | AN3: 网娱-知识阅读 | AO3: 网娱-网络工具 | AP3: 网娱-其他 | AQ3: 合计 | AR3: check
A4: 45658 | B4: =VLOOKUP(B$3,$L$1:$N$15,3,0) -> 6136.9116 | C4: =VLOOKUP(C$3,$L$1:$N$15,3,0) -> 1001.6234 | D4: =VLOOKUP(D$3,$L$1:$N$15,3,0) -> 12126.944 | E4: =VLOOKUP(E$3,$L$1:$N$15,3,0) -> 118.95727 | F4: =VLOOKUP(F$3,$L$1:$N$15,3,0) -> 990.5272 | G4: ='GMV表-商品大类'!D42-SUM(B4:F4) -> -18.777799 | H4: =SUM(B4:G4) -> 20356.185 | I4: =H4-'GMV表-商品大类'!D42 -> 0 | L4: 生活-购物（优惠劵） | M4: 3.2960084e+08 | N4: =M4/10000 -> 32960.084 | P4: 45292 | Q4: 8007.145 | R4: 1178.9017 | S4: 11963.61 | T4: 161.48681 | U4: 728.8358 | V4: =W4-SUM(Q4:U4) -> -1.87553 | W4: 22038.104 | X4: 0 | Z4: 44927 | AA4: 13288.648 | AB4: 2371.8514 | AC4: 32898.797 | AD4: 82.789323 | AE4: 231.63907 | AF4: -36.742008 | AG4: 48836.984 | AH4: 0 | AJ4: 44562 | AK4: 9884.6438 | AL4: 2395.7681 | AM4: 19925.16 | AN4: 97.152787 | AO4: 97.262358 | AP4: 32.057581 | AQ4: 32432.045 | AR4: 0
A5: 45689 | B5: =VLOOKUP(B$3,$L$18:$N$32,3,0) -> 5256.2006 | C5: =VLOOKUP(C$3,$L$18:$N$32,3,0) -> 1095.8763 | D5: =VLOOKUP(D$3,$L$18:$N$32,3,0) -> 11005.474 | E5: =VLOOKUP(E$3,$L$18:$N$32,3,0) -> 246.71841 | F5: =VLOOKUP(F$3,$L$18:$N$32,3,0) -> 1046.8678 | G5: ='GMV表-商品大类'!D43-SUM(B5:F5) -> -0.60574971 | H5: =SUM(B5:G5) -> 18650.532 | I5: =H5-'GMV表-商品大类'!D43 -> 0 | L5: 生活-加油卡 | M5: 162409.09 | N5: =M5/10000 -> 16.240909 | P5: 45323 | Q5: 8107.7725 | R5: 976.13699 | S5: 10649.628 | T5: 163.12905 | U5: 738.26716 | V5: =W5-SUM(Q5:U5) -> -4.310721 | W5: 20630.623 | X5: 0 | Z5: 44958 | AA5: 11012.898 | AB5: 2054.4455 | AC5: 31469.653 | AD5: 41.977595 | AE5: 354.57548 | AF5: 84.415525 | AG5: 45017.964 | AH5: 0 | AJ5: 44593 | AK5: 6650.3413 | AL5: 2147.2207 | AM5: 16050.732 | AN5: 59.040987 | AO5: 107.80277 | AP5: 218.66487 | AQ5: 25233.803 | AR5: 0
A6: 45717 | B6: =VLOOKUP(B$3,$L$35:$N$49,3,0) -> 4185.8648 | C6: =VLOOKUP(C$3,$L$35:$N$49,3,0) -> 886.27518 | D6: =VLOOKUP(D$3,$L$35:$N$49,3,0) -> 12420.599 | E6: =VLOOKUP(E$3,$L$35:$N$49,3,0) -> 243.3437 | F6: =VLOOKUP(F$3,$L$35:$N$49,3,0) -> 1133.7677 | G6: ='GMV表-商品大类'!D44-SUM(B6:F6) -> 21.756874 | H6: =SUM(B6:G6) -> 18891.607 | I6: =H6-'GMV表-商品大类'!D44 -> 0 | L6: 生活-健身 | M6: 4195.5 | N6: =M6/10000 -> 0.41955 | P6: 45352 | Q6: 7833.4078 | R6: 1425.4372 | S6: 13347.026 | T6: 152.42028 | U6: 1166.4472 | V6: =W6-SUM(Q6:U6) -> 82.836471 | W6: 24007.575 | X6: 0 | Z6: 44986 | AA6: 8861.1788 | AB6: 2290.5691 | AC6: 34891.966 | AD6: 58.436207 | AE6: 659.28424 | AF6: -8.201291 | AG6: 46753.233 | AH6: 0 | AJ6: 44621 | AK6: 6114.3128 | AL6: 3405.9464 | AM6: 33595.873 | AN6: 71.032405 | AO6: 717.49484 | AP6: 475.79985 | AQ6: 44380.459 | AR6: 0
A7: 45748 | B7: =VLOOKUP(B$3,$L$52:$N$66,3,0) -> 3633.7744 | C7: =VLOOKUP(C$3,$L$52:$N$66,3,0) -> 913.8416 | D7: =VLOOKUP(D$3,$L$52:$N$66,3,0) -> 11286.297 | E7: =VLOOKUP(E$3,$L$52:$N$66,3,0) -> 418.13622 | F7: =VLOOKUP(F$3,$L$52:$N$66,3,0) -> 1069.4332 | G7: ='GMV表-商品大类'!D45-SUM(B7:F7) -> -16.693418 | H7: =SUM(B7:G7) -> 17304.789 | I7: =H7-'GMV表-商品大类'!D45 -> 0 | L7: 生活-其他 | M7: 6856425.3 | N7: =M7/10000 -> 685.64253 | P7: 45383 | Q7: 8414.7986 | R7: 1072.0431 | S7: 13361.422 | T7: 181.15543 | U7: 718.46254 | V7: =W7-SUM(Q7:U7) -> 113.92023 | W7: 23861.802 | X7: 0 | Z7: 45017 | AA7: 7121.9032 | AB7: 2735.0578 | AC7: 28249.361 | AD7: 164.80577 | AE7: 362.39784 | AF7: -6.768789 | AG7: 38626.757 | AH7: 0 | AJ7: 44652 | AK7: 5045.4885 | AL7: 4748.0726 | AM7: 24625.747 | AN7: 96.921017 | AO7: 139.77051 | AP7: 311.36089 | AQ7: 34967.361 | AR7: 0
A8: 45778 | B8: =VLOOKUP(B$3,$L$69:$N$83,3,0) -> 4773.8702 | C8: =VLOOKUP(C$3,$L$69:$N$83,3,0) -> 833.37946 | D8: =VLOOKUP(D$3,$L$69:$N$83,3,0) -> 9471.5385 | E8: =VLOOKUP(E$3,$L$69:$N$83,3,0) -> 581.97345 | F8: =VLOOKUP(F$3,$L$69:$N$83,3,0) -> 1618.3066 | G8: ='GMV表-商品大类'!D46-SUM(B8:F8) -> 11.498163 | H8: =SUM(B8:G8) -> 17290.566 | I8: =H8-'GMV表-商品大类'!D46 -> 0 | L8: 网娱-其他 | M8: 15672.48 | N8: =M8/10000 -> 1.567248 | P8: 45413 | Q8: 8499.6206 | R8: 966.02983 | S8: 19570.386 | T8: 284.77214 | U8: 621.69576 | V8: =W8-SUM(Q8:U8) -> 6.0059673 | W8: 29948.51 | X8: 0 | Z8: 45047 | AA8: 10431.345 | AB8: 2253.56 | AC8: 21805.577 | AD8: 55.003518 | AE8: 265.45754 | AF8: -4.028302 | AG8: 34806.915 | AH8: 0 | AJ8: 44682 | AK8: 7991.853 | AL8: 3536.1416 | AM8: 27144.016 | AN8: 106.16313 | AO8: 142.35382 | AP8: 161.28007 | AQ8: 39081.808 | AR8: 0
A9: 45809 | B9: =VLOOKUP(B$3,$L$87:$N$101,3,0) -> 6039.9085 | C9: =VLOOKUP(C$3,$L$87:$N$101,3,0) -> 690.58656 | D9: =VLOOKUP(D$3,$L$87:$N$101,3,0) -> 3322.6469 | E9: =VLOOKUP(E$3,$L$87:$N$101,3,0) -> 524.37156 | F9: =VLOOKUP(F$3,$L$87:$N$101,3,0) -> 1892.7845 | G9: ='GMV表-商品大类'!D47-SUM(B9:F9) -> 4.2181614 | H9: =SUM(B9:G9) -> 12474.516 | I9: =H9-'GMV表-商品大类'!D47 -> 0 | L9: 网娱-视频直播 | M9: 1.2126944e+08 | N9: =M9/10000 -> 12126.944 | P9: 45444 | Q9: 7606.331 | R9: 1061.4681 | S9: 25825.334 | T9: 229.03323 | U9: 579.31108 | V9: =W9-SUM(Q9:U9) -> -440.9792 | W9: 34860.498 | X9: 0 | Z9: 45078 | AA9: 15369.437 | AB9: 3149.5073 | AC9: 21568.204 | AD9: 181.57805 | AE9: 162.29595 | AF9: 151.83503 | AG9: 40582.857 | AH9: 0 | AJ9: 44713 | AK9: 11112.306 | AL9: 4444.2431 | AM9: 34288.44 | AN9: 86.107677 | AO9: 279.1332 | AP9: 115.98048 | AQ9: 50326.21 | AR9: 0
A10: 45839 | B10: =VLOOKUP(B$3,$L$105:$N$119,3,0) -> 2908.1989 | C10: =VLOOKUP(C$3,$L$105:$N$119,3,0) -> 809.56797 | D10: =VLOOKUP(D$3,$L$105:$N$119,3,0) -> 2149.1404 | E10: =VLOOKUP(E$3,$L$105:$N$119,3,0) -> 423.09725 | F10: =VLOOKUP(F$3,$L$105:$N$119,3,0) -> 1215.4211 | G10: ='GMV表-商品大类'!D48-SUM(B10:F10) -> 7.1708805 | H10: =SUM(B10:G10) -> 7512.5965 | I10: =H10-'GMV表-商品大类'!D48 -> 0 | L10: 网娱-网络工具 | M10: 9905272 | N10: =M10/10000 -> 990.5272 | P10: 45474 | Q10: 4572.8206 | R10: 665.63075 | S10: 18787.386 | T10: 141.31103 | U10: 351.29139 | V10: =W10-SUM(Q10:U10) -> 27.668088 | W10: 24546.108 | X10: 0 | Z10: 45108 | AA10: 10216.145 | AB10: 844.93033 | AC10: 23913.598 | AD10: 55.022786 | AE10: 377.89675 | AF10: 10.543836 | AG10: 35418.136 | AH10: 0 | AJ10: 44743 | AK10: 6927.9175 | AL10: 3863.3423 | AM10: 27571.984 | AN10: 83.446368 | AO10: 568.88 | AP10: 84.389438 | AQ10: 39099.96 | AR10: 0
A11: 45870 | B11: =VLOOKUP(B$3,$L$123:$N$137,3,0) -> 4488.4522 | C11: =VLOOKUP(C$3,$L$123:$N$137,3,0) -> 849.62185 | D11: =VLOOKUP(D$3,$L$123:$N$137,3,0) -> 2146.4039 | E11: =VLOOKUP(E$3,$L$123:$N$137,3,0) -> 481.77783 | F11: =VLOOKUP(F$3,$L$123:$N$137,3,0) -> 554.13239 | G11: ='GMV表-商品大类'!D49-SUM(B11:F11) -> -88.822085 | H11: =SUM(B11:G11) -> 8431.5661 | I11: =H11-'GMV表-商品大类'!D49 -> 0 | L11: 网娱-音频 | M11: 10016234 | N11: =M11/10000 -> 1001.6234 | P11: 45505 | Q11: 5399.8301 | R11: 1309.9135 | S11: 22646.513 | T11: 190.63347 | U11: 417.68975 | V11: =W11-SUM(Q11:U11) -> 37.535276 | W11: 30002.115 | X11: 0 | Z11: 45139 | AA11: 12282.884 | AB11: 2893.3351 | AC11: 26302.745 | AD11: 113.38709 | AE11: 181.33369 | AF11: 49.73385 | AG11: 41823.418 | AH11: 0 | AJ11: 44774 | AK11: 10210.136 | AL11: 5164.4147 | AM11: 35440.571 | AN11: 138.62084 | AO11: 210.15898 | AP11: 55.501406 | AQ11: 51219.403 | AR11: 0
A12: 45901 | B12: =VLOOKUP(B$3,$L$141:$N$156,3,0) -> 5056.4016 | C12: =VLOOKUP(C$3,$L$141:$N$156,3,0) -> 652.74497 | D12: =VLOOKUP(D$3,$L$141:$N$156,3,0) -> 837.70507 | E12: =VLOOKUP(E$3,$L$141:$N$156,3,0) -> 492.5133 | F12: =VLOOKUP(F$3,$L$141:$N$156,3,0) -> 867.88198 | G12: ='GMV表-商品大类'!D50-SUM(B12:F12) -> 804.61011 | H12: =SUM(B12:G12) -> 8711.8571 | I12: =H12-'GMV表-商品大类'!D50 -> 0 | L12: 网娱-影视会员 | M12: 61369116 | N12: =M12/10000 -> 6136.9116 | P12: 45536 | Q12: 5591.8829 | R12: 1000.2826 | S12: 15574.485 | T12: 163.61239 | U12: 628.20774 | V12: =W12-SUM(Q12:U12) -> -29.674593 | W12: 22928.796 | X12: 0 | Z12: 45170 | AA12: 9903.629 | AB12: 1782.8105 | AC12: 27656.213 | AD12: 67.001426 | AE12: 204.13624 | AF12: 93.375472 | AG12: 39707.166 | AH12: 0 | AJ12: 44805 | AK12: 9354.7391 | AL12: 3448.5099 | AM12: 47059.399 | AN12: 50.914779 | AO12: 531.49097 | AP12: 43.73871 | AQ12: 60488.792 | AR12: 0
A13: 45931 | B13: =VLOOKUP(B$3,$L$159:$N$173,3,0) -> 4046.9897 | C13: =VLOOKUP(C$3,$L$159:$N$173,3,0) -> 986.23359 | D13: =VLOOKUP(D$3,$L$159:$N$173,3,0) -> 1470.3084 | E13: =VLOOKUP(E$3,$L$159:$N$173,3,0) -> 628.13432 | F13: =VLOOKUP(F$3,$L$159:$N$173,3,0) -> 1581.2068 | G13: ='GMV表-商品大类'!D51-SUM(B13:F13) -> 555.25101 | H13: =SUM(B13:G13) -> 9268.1238 | I13: =H13-'GMV表-商品大类'!D51 -> 0 | L13: 网娱-知识阅读 | M13: 1189572.7 | N13: =M13/10000 -> 118.95727 | P13: 45566 | Q13: 6468.5198 | R13: 1404.5234 | S13: 14117.225 | T13: 335.07355 | U13: 905.78774 | V13: =W13-SUM(Q13:U13) -> 24.851996 | W13: 23255.981 | X13: 0 | Z13: 45200 | AA13: 12285.089 | AB13: 2025.4978 | AC13: 25105.259 | AD13: 409.81748 | AE13: 122.34653 | AF13: 8.292424 | AG13: 39956.302 | AH13: 0 | AJ13: 44835 | AK13: 11006.977 | AL13: 3568.4804 | AM13: 36415.133 | AN13: 49.642019 | AO13: 334.6951 | AP13: 41.718834 | AQ13: 51416.646 | AR13: 0
A14: 45962 | B14: =VLOOKUP(B$3,$L$177:$N$191,3,0) -> 3408.8709 | C14: =VLOOKUP(C$3,$L$177:$N$191,3,0) -> 798.49938 | D14: =VLOOKUP(D$3,$L$177:$N$191,3,0) -> 3813.9662 | E14: =VLOOKUP(E$3,$L$177:$N$191,3,0) -> 553.67925 | F14: =VLOOKUP(F$3,$L$177:$N$191,3,0) -> 1976.5254 | G14: ='GMV表-商品大类'!D52-SUM(B14:F14) -> 35.8302 | H14: =SUM(B14:G14) -> 10587.371 | I14: =H14-'GMV表-商品大类'!D52 -> 0 | L14: #N/A | M14: 1.2973523e+08 | N14: =M14/10000 -> 12973.523 | P14: 45597 | Q14: 6842.708 | R14: 2232.4843 | S14: 15441.868 | T14: 248.02302 | U14: 1146.8351 | V14: =W14-SUM(Q14:U14) -> -19.653273 | W14: 25892.265 | X14: 0 | Z14: 45231 | AA14: 20147.536 | AB14: 3621.0938 | AC14: 27859.796 | AD14: 248.62431 | AE14: 361.73383 | AF14: -24.084945 | AG14: 52214.699 | AH14: 0 | AJ14: 44866 | AK14: 17588.434 | AL14: 4638.7749 | AM14: 47244.208 | AN14: 174.5533 | AO14: 234.21075 | AP14: 159.67442 | AQ14: 70039.856 | AR14: 0
A15: 45992 | B15: =VLOOKUP(B$3,$L$195:$N$209,3,0) -> 4206.7072 | C15: =VLOOKUP(C$3,$L$195:$N$209,3,0) -> 856.27 | D15: =VLOOKUP(D$3,$L$195:$N$209,3,0) -> 3824.9187 | E15: =VLOOKUP(E$3,$L$195:$N$209,3,0) -> 355.26055 | F15: =VLOOKUP(F$3,$L$195:$N$209,3,0) -> 2639.8593 | G15: ='GMV表-商品大类'!D53-SUM(B15:F15) -> 92.194949 | H15: =SUM(B15:G15) -> 11975.211 | I15: =H15-'GMV表-商品大类'!D53 -> 0 | L15: 总计 | M15: =SUM(M2:M14) -> 6.9906421e+08 | N15: =SUM(N2:N14) -> 69906.421 | P15: 45627 | Q15: 5009.3885 | R15: 1217.7879 | S15: 18798.896 | T15: 205.09285 | U15: 1071.1167 | V15: =W15-SUM(Q15:U15) -> 110.66501 | W15: 26412.947 | X15: 0 | Z15: 45261 | AA15: 9294.4974 | AB15: 3250.161 | AC15: 28589.034 | AD15: 110.71617 | AE15: 633.28795 | AF15: -18.534297 | AG15: 41859.163 | AH15: 0 | AJ15: 44896 | AK15: 9207.6291 | AL15: 3740.0809 | AM15: 63841.177 | AN15: 58.520539 | AO15: 694.86699 | AP15: 165.88354 | AQ15: 77708.158 | AR15: 0
A16: 合计 | B16: =SUM(B4:B15) -> 54142.151 | C16: =SUM(C4:C15) -> 10374.52 | D16: =SUM(D4:D15) -> 73875.942 | E16: =SUM(E4:E15) -> 5067.9631 | F16: =SUM(F4:F15) -> 16586.714 | G16: =SUM(G4:G15) -> 1407.6313 | H16: =SUM(H4:H15) -> 161454.92 | I16: =H16-'GMV表-商品大类'!D61 -> 0 | P16: 合计 | Q16: =SUM(Q4:Q15) -> 82354.225 | R16: =SUM(R4:R15) -> 14510.639 | S16: =SUM(S4:S15) -> 200083.78 | T16: =SUM(T4:T15) -> 2455.7433 | U16: =SUM(U4:U15) -> 9073.948 | V16: =SUM(V4:V15) -> -93.010272 | W16: =SUM(W4:W15) -> 308385.33 | X16: 0 | Z16: 合计 | AA16: =SUM(AA4:AA15) -> 140215.19 | AB16: =SUM(AB4:AB15) -> 29272.82 | AC16: =SUM(AC4:AC15) -> 330310.2 | AD16: =SUM(AD4:AD15) -> 1589.1597 | AE16: =SUM(AE4:AE15) -> 3916.3851 | AF16: =SUM(AF4:AF15) -> 299.83651 | AG16: =SUM(AG4:AG15) -> 505603.59 | AH16: 0 | AJ16: 合计 | AK16: =SUM(AK4:AK15) -> 111094.78 | AL16: =SUM(AL4:AL15) -> 45100.996 | AM16: =SUM(AM4:AM15) -> 413202.44 | AN16: =SUM(AN4:AN15) -> 1072.1158 | AO16: =SUM(AO4:AO15) -> 4058.1203 | AP16: =SUM(AP4:AP15) -> 1866.0501 | AQ16: =SUM(AQ4:AQ15) -> 576394.5 | AR16: 0
A17: 占比 | B17: =B16/$H$16 -> 0.33533912 | C17: =C16/$H$16 -> 0.064256451 | D17: =D16/$H$16 -> 0.45756389 | E17: =E16/$H$16 -> 0.031389338 | F17: =F16/$H$16 -> 0.10273279 | G17: =G16/$H$16 -> 0.0087184168 | P17: 占比 | Q17: =Q16/$W$16 -> 0.26704975 | R17: =R16/$W$16 -> 0.047053599 | S17: =S16/$W$16 -> 0.64881096 | T17: =T16/$W$16 -> 0.00796323 | U17: =U16/$W$16 -> 0.029424059 | V17: =V16/$W$16 -> -0.00030160408 | Z17: 占比 | AA17: =AA16/$AG$16 -> 0.27732237 | AB17: =AB16/$AG$16 -> 0.057896779 | AC17: =AC16/$AG$16 -> 0.65329877 | AD17: =AD16/$AG$16 -> 0.0031430942 | AE17: =AE16/$AG$16 -> 0.0077459598 | AF17: =AF16/$AG$16 -> 0.00059302685 | AJ17: 占比 | AK17: 0.1927409 | AL17: 0.078246749 | AM17: 0.71687436 | AN17: 0.0018600383 | AO17: 0.0070405257 | AP17: 0.003237453
A18: 变动 | B18: =B16-Q16 -> -28212.075 | C18: =C16-R16 -> -4136.1192 | D18: =D16-S16 -> -126207.84 | E18: =E16-T16 -> 2612.2198 | F18: =F16-U16 -> 7512.766 | G18: =G16-V16 -> 1500.6416 | H18: =H16-W16 -> -146930.4 | I18: =H18-'GMV表-商品大类'!D69 -> 0 | K18: 2月 | L18: 品牌分类 | M18: 求和项:调整后gmv | N18: 万元 | Z18: 22年 | AJ18: 21年
L19: 生活-餐饮 | M19: 22290274 | N19: =M19/10000 -> 2229.0274 | Z19: 变动 | AJ19: 变动 | AK19: -51717.326 | AL19: -14847.966 | AM19: -270913.06
A20: 生活服务-GMV | L20: 生活-出行旅游 | M20: 2530736.5 | N20: =M20/10000 -> 253.07365 | P20: 生活服务-GMV | S20: -0.37569884 | Z20: 生活服务-GMV | AJ20: 生活服务-GMV
A21: 月份 | B21: 生活-加油卡 | C21: 生活-出行旅游 | D21: 生活-餐饮 | E21: 生活-立减金 | F21: 生活-购物（优惠劵） | G21: 生活-其他 | H21: 合计 | I21: check | L21: 生活-购物（优惠劵） | M21: 2.599457e+08 | N21: =M21/10000 -> 25994.57 | P21: 月份 | Q21: 生活-加油卡 | R21: 生活-出行旅游 | S21: 生活-餐饮 | T21: 生活-立减金 | U21: 生活-购物（优惠劵） | V21: 生活-其他 | W21: 合计 | X21: check | Z21: 月份 | AA21: 生活-加油卡 | AB21: 生活-出行旅游 | AC21: 生活-餐饮 | AD21: 生活-立减金 | AE21: 生活-购物（优惠劵） | AF21: 生活-其他 | AG21: 合计 | AH21: check | AJ21: 月份 | AK21: 生活-加油卡 | AL21: 生活-出行旅游 | AM21: 生活-餐饮 | AN21: 生活-购物（优惠劵） | AO21: 生活-健身 | AP21: 生活-其他 | AQ21: 合计 | AR21: check
A22: 45658 | B22: =VLOOKUP(B$21,$L$1:$N$15,3,0) -> 16.240909 | C22: =VLOOKUP(C$21,$L$1:$N$15,3,0) -> 717.61448 | D22: =VLOOKUP(D$21,$L$1:$N$15,3,0) -> 2176.366 | E22: 13624.119 | F22: 19335.966 | G22: 712.0628 | H22: =SUM(B22:G22) -> 36582.368 | I22: =H22-'GMV表-商品大类'!E42 -> 0 | L22: 生活-加油卡 | M22: 87658.978 | N22: =M22/10000 -> 8.7658978 | P22: 45292 | Q22: 774.98675 | R22: 1247.3083 | S22: 1721.638 | T22: 7067.389 | U22: 20395.537 | V22: 1230.2989 | W22: =SUM(Q22:V22) -> 32437.158 | X22: =W22-'GMV表-商品大类'!E30 -> 0 | Z22: 44927 | AA22: 2320.3047 | AB22: 344.54953 | AC22: 1931.8029 | AD22: 3357.8495 | AE22: 24795.952 | AF22: 729.43384 | AG22: =SUM(AA22:AF22) -> 33479.892 | AH22: =AG22-'GMV表-商品大类'!E18 -> 0 | AJ22: 44562 | AK22: 74.12923 | AL22: 154.06231 | AM22: 358.47435 | AN22: 16549.654 | AO22: 32.36919 | AP22: 546.88552 | AQ22: 17715.575 | AR22: 0
A23: 45689 | B23: =VLOOKUP(B$21,$L$18:$N$32,3,0) -> 8.7658978 | C23: =VLOOKUP(C$21,$L$18:$N$32,3,0) -> 253.07365 | D23: =VLOOKUP(D$21,$L$18:$N$32,3,0) -> 2229.0274 | E23: 10803.75 | F23: 15190.819 | G23: 528.57693 | H23: =SUM(B23:G23) -> 29014.014 | I23: =H23-'GMV表-商品大类'!E43 -> 0 | L23: 生活-健身 | M23: 25975 | N23: =M23/10000 -> 2.5975 | P23: 45323 | Q23: 585.78005 | R23: 649.93174 | S23: 911.10369 | T23: 7258.5837 | U23: 18963.563 | V23: 1262.3931 | W23: =SUM(Q23:V23) -> 29631.355 | X23: =W23-'GMV表-商品大类'!E31 -> 0 | Z23: 44958 | AA23: 2426.2952 | AB23: 219.01917 | AC23: 771.20349 | AD23: 4562.7184 | AE23: 26789.712 | AF23: 236.13134 | AG23: =SUM(AA23:AF23) -> 35005.079 | AH23: =AG23-'GMV表-商品大类'!E19 -> 0 | AJ23: 44593 | AK23: 224.42404 | AL23: 159.39662 | AM23: 275.87252 | AN23: 13563.388 | AO23: 132.21854 | AP23: 735.54984 | AQ23: 15090.849 | AR23: 0
A24: 45717 | B24: =VLOOKUP(B$21,$L$35:$N$49,3,0) -> 17.792376 | C24: =VLOOKUP(C$21,$L$35:$N$49,3,0) -> 283.6972 | D24: =VLOOKUP(D$21,$L$35:$N$49,3,0) -> 3225.0303 | E24: 19966.904 | F24: 17220.54 | G24: 316.35997 | H24: =SUM(B24:G24) -> 41030.325 | I24: =H24-'GMV表-商品大类'!E44 -> 0 | L24: 生活-其他 | M24: 4974963.1 | N24: =M24/10000 -> 497.49631 | P24: 45352 | Q24: 584.41559 | R24: 704.90748 | S24: 1110.0432 | T24: 6473.6521 | U24: 19058.409 | V24: 617.76292 | W24: =SUM(Q24:V24) -> 28549.19 | X24: =W24-'GMV表-商品大类'!E32 -> 0 | Z24: 44986 | AA24: 3214.7873 | AB24: 491.15597 | AC24: 994.09227 | AD24: 8101.0441 | AE24: 35280.266 | AF24: 102.67792 | AG24: =SUM(AA24:AF24) -> 48184.023 | AH24: =AG24-'GMV表-商品大类'!E20 -> 0 | AJ24: 44621 | AK24: 635.023 | AL24: 210.43086 | AM24: 289.14662 | AN24: 30733.179 | AO24: 69.596241 | AP24: 731.48659 | AQ24: 32668.862 | AR24: 0
A25: 45748 | B25: =VLOOKUP(B$21,$L$52:$N$66,3,0) -> 30.265324 | C25: =VLOOKUP(C$21,$L$52:$N$66,3,0) -> 236.21053 | D25: =VLOOKUP(D$21,$L$52:$N$66,3,0) -> 1843.3546 | E25: 17616.708 | F25: 15440.981 | G25: 187.81491 | H25: =SUM(B25:G25) -> 35355.334 | I25: =H25-'GMV表-商品大类'!E45 -> 0 | L25: 网娱-其他 | N25: =M25/10000 -> 0 | P25: 45383 | Q25: 372.05521 | R25: 653.52619 | S25: 1707.2602 | T25: 3110.0743 | U25: 10627.836 | V25: 126.99053 | W25: =SUM(Q25:V25) -> 16597.742 | X25: =W25-'GMV表-商品大类'!E33 -> 0 | Z25: 45017 | AA25: 2699.1103 | AB25: 925.30509 | AC25: 1324.4729 | AD25: 10136.698 | AE25: 31186.052 | AF25: 345.69369 | AG25: =SUM(AA25:AF25) -> 46617.332 | AH25: =AG25-'GMV表-商品大类'!E21 -> 0 | AJ25: 44652 | AK25: 1390.7422 | AL25: 137.69217 | AM25: 311.86764 | AN25: 23405.072 | AO25: 36.415092 | AP25: 879.53822 | AQ25: 26161.328 | AR25: 0
A26: 45778 | B26: =VLOOKUP(B$21,$L$69:$N$83,3,0) -> 185.68592 | C26: =VLOOKUP(C$21,$L$69:$N$83,3,0) -> 450.33723 | D26: =VLOOKUP(D$21,$L$69:$N$83,3,0) -> 1038.5219 | E26: =VLOOKUP(E$21,$L$69:$N$83,3,0) -> 14953.656 | F26: =VLOOKUP(F$21,$L$69:$N$83,3,0) -> 12292.89 | G26: ='GMV表-商品大类'!E46-SUM(B26:F26) -> 166.30813 | H26: =SUM(B26:G26) -> 29087.399 | I26: =H26-'GMV表-商品大类'!E46 -> 0 | L26: 网娱-视频直播 | M26: 1.1005474e+08 | N26: =M26/10000 -> 11005.474 | P26: 45413 | Q26: 322.62111 | R26: 1082.0517 | S26: 3449.8878 | T26: 5123.7166 | U26: 16430.59 | V26: 148.64891 | W26: =SUM(Q26:V26) -> 26557.516 | X26: =W26-'GMV表-商品大类'!E34 -> 0 | Z26: 45047 | AA26: 2460.1169 | AB26: 1032.281 | AC26: 4523.382 | AD26: 11405.169 | AE26: 34527.547 | AF26: 625.81047 | AG26: =SUM(AA26:AF26) -> 54574.306 | AH26: =AG26-'GMV表-商品大类'!E22 -> 0 | AJ26: 44682 | AK26: 1223.0405 | AL26: 290.91444 | AM26: 367.3219 | AN26: 30278.131 | AO26: 46.410383 | AP26: 277.31865 | AQ26: 32483.137 | AR26: 0
A27: 45809 | B27: =VLOOKUP(B$21,$L$87:$N$101,3,0) -> 101.09751 | C27: =VLOOKUP(C$21,$L$87:$N$101,3,0) -> 396.92262 | D27: =VLOOKUP(D$21,$L$87:$N$101,3,0) -> 1422.6918 | E27: =VLOOKUP(E$21,$L$87:$N$101,3,0) -> 19088.456 | F27: =VLOOKUP(F$21,$L$87:$N$101,3,0) -> 14425.521 | G27: ='GMV表-商品大类'!E47-SUM(B27:F27) -> 51.677497 | H27: =SUM(B27:G27) -> 35486.366 | I27: =H27-'GMV表-商品大类'!E47 -> 0 | L27: 网娱-网络工具 | M27: 10468678 | N27: =M27/10000 -> 1046.8678 | P27: 45444 | Q27: 427.31041 | R27: 1091.9993 | S27: 4832.8963 | T27: 10732.796 | U27: 13441.759 | V27: 18.56536 | W27: =SUM(Q27:V27) -> 30545.326 | X27: =W27-'GMV表-商品大类'!E35 -> 0 | Z27: 45078 | AA27: 2044.5297 | AB27: 1056.508 | AC27: 7100.4265 | AD27: 11254.686 | AE27: 42579.007 | AF27: 1709.0887 | AG27: =SUM(AA27:AF27) -> 65744.246 | AH27: =AG27-'GMV表-商品大类'!E23 -> 0 | AJ27: 44713 | AK27: 1416.3376 | AL27: 335.26406 | AM27: 4303.0048 | AN27: 27891.418 | AO27: 63.937918 | AP27: 152.6255 | AQ27: 34162.588 | AR27: 0
A28: 45839 | B28: =VLOOKUP(B$21,$L$105:$N$119,3,0) -> 37.199618 | C28: =VLOOKUP(C$21,$L$105:$N$119,3,0) -> 334.70417 | D28: =VLOOKUP(D$21,$L$105:$N$119,3,0) -> 847.26855 | E28: =VLOOKUP(E$21,$L$105:$N$119,3,0) -> 33418.898 | F28: =VLOOKUP(F$21,$L$105:$N$119,3,0) -> 11301.806 | G28: ='GMV表-商品大类'!E48-SUM(B28:F28) -> 531.95756 | H28: =SUM(B28:G28) -> 46471.834 | I28: =H28-'GMV表-商品大类'!E48 -> 0 | L28: 网娱-音频 | M28: 10958763 | N28: =M28/10000 -> 1095.8763 | P28: 45474 | Q28: 510.97318 | R28: 843.1376 | S28: 6740.2832 | T28: 13168.655 | U28: 13332.027 | V28: -187.24976 | W28: =SUM(Q28:V28) -> 34407.826 | X28: =W28-'GMV表-商品大类'!E36 -> 0 | Z28: 45108 | AA28: 2042.5626 | AB28: 1022.4824 | AC28: 4563.9616 | AD28: 9871.2431 | AE28: 36648.973 | AF28: 1134.4485 | AG28: =SUM(AA28:AF28) -> 55283.671 | AH28: =AG28-'GMV表-商品大类'!E24 -> 0 | AJ28: 44743 | AK28: 1500.1141 | AL28: 307.84026 | AM28: 1099.1747 | AN28: 24170.129 | AO28: 103.11988 | AP28: 231.70886 | AQ28: 27412.087 | AR28: 0
A29: 45870 | B29: =VLOOKUP(B$21,$L$123:$N$137,3,0) -> 11.819629 | C29: =VLOOKUP(C$21,$L$123:$N$137,3,0) -> 163.62227 | D29: =VLOOKUP(D$21,$L$123:$N$137,3,0) -> 1598.2663 | E29: =VLOOKUP(E$21,$L$123:$N$137,3,0) -> 38309.543 | F29: =VLOOKUP(F$21,$L$123:$N$137,3,0) -> 11809.012 | G29: ='GMV表-商品大类'!E49-SUM(B29:F29) -> 714.64854 | H29: =SUM(B29:G29) -> 52606.912 | I29: =H29-'GMV表-商品大类'!E49 -> 0 | L29: 网娱-影视会员 | M29: 52562006 | N29: =M29/10000 -> 5256.2006 | P29: 45505 | Q29: 361.77207 | R29: 687.82097 | S29: 4493.332 | T29: 10974.94 | U29: 14228.812 | V29: 286.1384 | W29: =SUM(Q29:V29) -> 31032.816 | X29: =W29-'GMV表-商品大类'!E37 -> 0 | Z29: 45139 | AA29: 2262.2778 | AB29: 2377.4195 | AC29: 4585.2274 | AD29: 9710.7038 | AE29: 40803.705 | AF29: 1362.8887 | AG29: =SUM(AA29:AF29) -> 61102.222 | AH29: =AG29-'GMV表-商品大类'!E25 -> 0 | AJ29: 44774 | AK29: 1478.3301 | AL29: 205.52819 | AM29: 2845.4653 | AN29: 29241.323 | AO29: 81.081032 | AP29: 340.69249 | AQ29: 34192.42 | AR29: 0
A30: 45901 | B30: =VLOOKUP(B$21,$L$141:$N$156,3,0) -> 17.87711 | C30: =VLOOKUP(C$21,$L$141:$N$156,3,0) -> 199.77796 | D30: =VLOOKUP(D$21,$L$141:$N$156,3,0) -> 2063.6522 | E30: =VLOOKUP(E$21,$L$141:$N$156,3,0) -> 35231.122 | F30: =VLOOKUP(F$21,$L$141:$N$156,3,0) -> 12463.468 | G30: ='GMV表-商品大类'!E50-SUM(B30:F30) -> 480.19568 | H30: =SUM(B30:G30) -> 50456.092 | I30: =H30-'GMV表-商品大类'!E50 -> 0 | L30: 网娱-知识阅读 | M30: 2467184.1 | N30: =M30/10000 -> 246.71841 | P30: 45536 | Q30: 287.56652 | R30: 585.61905 | S30: 2377.4264 | T30: 5421.0431 | U30: =9893.04944759228+19348723.985/10000 -> 11827.922 | V30: =2085.82866757591-19348723.985/10000 -> 150.95627 | W30: =SUM(Q30:V30) -> 20650.533 | X30: =W30-'GMV表-商品大类'!E38 -> 0 | Z30: 45170 | AA30: 2358.2411 | AB30: 1562.9219 | AC30: 3820.7577 | AD30: 6609.6405 | AE30: 34169.961 | AF30: 1415.0599 | AG30: =SUM(AA30:AF30) -> 49936.582 | AH30: =AG30-'GMV表-商品大类'!E26 -> 0 | AJ30: 44805 | AK30: 1808.6165 | AL30: 288.56608 | AM30: 1683.6405 | AN30: 24763.29 | AO30: 75.289404 | AP30: -264.36099 | AQ30: 28355.042 | AR30: 0
A31: 45931 | B31: =VLOOKUP(B$21,$L$159:$N$173,3,0) -> 64.369594 | C31: =VLOOKUP(C$21,$L$159:$N$173,3,0) -> 209.27048 | D31: =VLOOKUP(D$21,$L$159:$N$173,3,0) -> 1945.439 | E31: =VLOOKUP(E$21,$L$159:$N$173,3,0) -> 25806.099 | F31: =VLOOKUP(F$21,$L$159:$N$173,3,0) -> 11398.239 | G31: ='GMV表-商品大类'!E51-SUM(B31:F31) -> 306.76936 | H31: =SUM(B31:G31) -> 39730.187 | I31: =H31-'GMV表-商品大类'!E51 -> 0 | L31: #N/A | M31: 75726106 | N31: =M31/10000 -> 7572.6106 | P31: 45566 | Q31: 146.47428 | R31: 437.1078 | S31: 2222.2342 | T31: 10464.26 | U31: 12772.541 | V31: 125.03994 | W31: =SUM(Q31:V31) -> 26167.658 | X31: =W31-'GMV表-商品大类'!E39 -> 0 | Z31: 45200 | AA31: 1188.37 | AB31: 917.27159 | AC31: 2244.7133 | AD31: 7900.8875 | AE31: 23421.308 | AF31: 918.75362 | AG31: =SUM(AA31:AF31) -> 36591.304 | AH31: =AG31-'GMV表-商品大类'!E27 -> 0 | AJ31: 44835 | AK31: 1649.7526 | AL31: 227.4447 | AM31: 2058.0657 | AN31: 30586.804 | AO31: 52.265159 | AP31: 124.77012 | AQ31: 34699.103 | AR31: 0
A32: 45962 | B32: =VLOOKUP(B$21,$L$177:$N$191,3,0) -> 61.000113 | C32: =VLOOKUP(C$21,$L$177:$N$191,3,0) -> 166.49962 | D32: =VLOOKUP(D$21,$L$177:$N$191,3,0) -> 1694.3297 | E32: =VLOOKUP(E$21,$L$177:$N$191,3,0) -> 28110.921 | F32: =VLOOKUP(F$21,$L$177:$N$191,3,0) -> 10324.723 | G32: ='GMV表-商品大类'!E52-SUM(B32:F32) -> 297.14389 | H32: =SUM(B32:G32) -> 40654.617 | I32: =H32-'GMV表-商品大类'!E52 -> 0 | L32: 总计 | M32: =SUM(M19:M31) -> 5.5209278e+08 | N32: =M32/10000 -> 55209.278 | P32: 45597 | Q32: 166.48479 | R32: 416.45484 | S32: 2192.1625 | T32: 10392.71 | U32: 13399.111 | V32: 8.7738543 | W32: =SUM(Q32:V32) -> 26575.697 | X32: =W32-'GMV表-商品大类'!E40 -> 0 | Z32: 45231 | AA32: 682.40415 | AB32: 1010.0297 | AC32: 4440.3454 | AD32: 7109.8297 | AE32: 20246.64 | AF32: 847.05302 | AG32: =SUM(AA32:AF32) -> 34336.302 | AH32: =AG32-'GMV表-商品大类'!E28 -> 0 | AJ32: 44866 | AK32: 3087.4398 | AL32: 208.57969 | AM32: 1237.5814 | AN32: 36750.997 | AO32: 124.94814 | AP32: 56.691197 | AQ32: 41466.237 | AR32: 0
A33: 45992 | B33: =VLOOKUP(B$21,$L$195:$N$209,3,0) -> 53.415092 | C33: =VLOOKUP(C$21,$L$195:$N$209,3,0) -> 136.09846 | D33: =VLOOKUP(D$21,$L$195:$N$209,3,0) -> 2631.0601 | E33: =VLOOKUP(E$21,$L$195:$N$209,3,0) -> 37983.184 | F33: =VLOOKUP(F$21,$L$195:$N$209,3,0) -> 19139.159 | G33: ='GMV表-商品大类'!E53-SUM(B33:F33) -> 1211.8171 | H33: =SUM(B33:G33) -> 61154.734 | I33: =H33-'GMV表-商品大类'!E53 -> 0 | P33: 45627 | Q33: 204.39099 | R33: 579.48263 | S33: 1757.7109 | T33: 9407.0092 | U33: 16146.442 | V33: -186.4033 | W33: =SUM(Q33:V33) -> 27908.633 | X33: =W33-'GMV表-商品大类'!E41 -> 4.7293724e-11 | Z33: 45261 | AA33: 692.71149 | AB33: 1307.1377 | AC33: 2325.5692 | AD33: 6914.5904 | AE33: 20605.033 | AF33: 1577.8452 | AG33: =SUM(AA33:AF33) -> 33422.887 | AH33: =AG33-'GMV表-商品大类'!E29 -> 0 | AJ33: 44896 | AK33: 2930.7455 | AL33: 318.80902 | AM33: 929.46532 | AN33: 36809.705 | AO33: 74.946251 | AP33: 165.89879 | AQ33: 41229.57 | AR33: 0
A34: 合计 | B34: =SUM(B22:B33) -> 605.5291 | C34: =SUM(C22:C33) -> 3547.8287 | D34: =SUM(D22:D33) -> 22715.008 | E34: =SUM(E22:E33) -> 294913.36 | F34: =SUM(F22:F33) -> 170343.12 | G34: =SUM(G22:G33) -> 5505.3324 | H34: =SUM(H22:H33) -> 497630.18 | I34: =H34-'GMV表-商品大类'!E61 -> 0 | P34: 合计 | Q34: =SUM(Q22:Q33) -> 4744.831 | R34: =SUM(R22:R33) -> 8979.3476 | S34: =SUM(S22:S33) -> 33515.978 | T34: =SUM(T22:T33) -> 99594.83 | U34: =SUM(U22:U33) -> 180624.55 | V34: =SUM(V22:V33) -> 3601.9151 | W34: =SUM(W22:W33) -> 331061.45 | Z34: 合计 | AA34: =SUM(AA22:AA33) -> 24391.711 | AB34: =SUM(AB22:AB33) -> 12266.082 | AC34: =SUM(AC22:AC33) -> 38625.955 | AD34: =SUM(AD22:AD33) -> 96935.061 | AE34: =SUM(AE22:AE33) -> 371054.15 | AF34: =SUM(AF22:AF33) -> 11004.885 | AG34: =SUM(AG22:AG33) -> 554277.85 | AH34: 0 | AJ34: 合计 | AK34: =SUM(AK22:AK33) -> 17418.695 | AL34: =SUM(AL22:AL33) -> 2844.5284 | AM34: =SUM(AM22:AM33) -> 15759.081 | AN34: =SUM(AN22:AN33) -> 324743.09 | AO34: =SUM(AO22:AO33) -> 892.59722 | AP34: =SUM(AP22:AP33) -> 3978.8048 | AQ34: =SUM(AK34:AP34) -> 365636.8 | AR34: 0
A35: 占比 | B35: =B34/$H$34 -> 0.0012168255 | C35: =C34/$H$34 -> 0.0071294484 | D35: =D34/$H$34 -> 0.045646363 | E35: =E34/$H$34 -> 0.5926356 | F35: =F34/$H$34 -> 0.34230866 | G35: =G34/$H$34 -> 0.0110631 | K35: 3月 | L35: 品牌分类 | M35: 求和项:调整后gmv | N35: 万元 | P35: 占比 | Q35: =Q34/$W$34 -> 0.014332176 | R35: =R34/$W$34 -> 0.027122903 | S35: =S34/$W$34 -> 0.10123794 | T35: =T34/$W$34 -> 0.30083487 | U35: =U34/$W$34 -> 0.54559221 | V35: =V34/$W$34 -> 0.010879899 | Z35: 占比 | AA35: =AA34/$AG$34 -> 0.044006289 | AB35: =AB34/$AG$34 -> 0.022129843 | AC35: =AC34/$AG$34 -> 0.06968699 | AD35: =AD34/$AG$34 -> 0.17488532 | AE35: =AE34/$AG$34 -> 0.6694371 | AF35: =AF34/$AG$34 -> 0.019854456 | AJ35: 占比 | AK35: 0.04763934 | AL35: 0.0077796558 | AM35: 0.043100368 | AN35: 0.88815757 | AO35: 0.0024412128 | AP35: 0.01088185
A36: 变动 | B36: =B34-Q34 -> -4139.3019 | C36: =C34-R34 -> -5431.519 | D36: =D34-S34 -> -10800.971 | E36: =E34-T34 -> 195318.53 | F36: =F34-U34 -> -10281.426 | G36: =G34-V34 -> 1903.4173 | H36: =H34-W34 -> 166568.73 | I36: =H36-'GMV表-商品大类'!E69 -> 0 | L36: 生活-餐饮 | M36: 32250303 | N36: =M36/10000 -> 3225.0303
L37: 生活-出行旅游 | M37: 2836972 | N37: =M37/10000 -> 283.6972
L38: 生活-购物（优惠劵） | M38: 3.7187445e+08 | N38: =M38/10000 -> 37187.445
A39: 45261 | L39: 生活-加油卡 | M39: 177923.76 | N39: =M39/10000 -> 17.792376
A40: 45627 | L40: 生活-健身 | M40: 67003.54 | N40: =M40/10000 -> 6.700354
A41: 45992 | L41: 生活-其他 | M41: 2776757.8 | N41: =M41/10000 -> 277.67578
L42: 网娱-其他 | M42: 174347.7 | N42: =M42/10000 -> 17.43477
L43: 网娱-视频直播 | M43: 1.2420599e+08 | N43: =M43/10000 -> 12420.599
L44: 网娱-网络工具 | M44: 11337677 | N44: =M44/10000 -> 1133.7677
L45: 网娱-音频 | M45: 8862751.8 | N45: =M45/10000 -> 886.27518
L46: 网娱-影视会员 | M46: 41858648 | N46: =M46/10000 -> 4185.8648
L47: 网娱-知识阅读 | M47: 2433437 | N47: =M47/10000 -> 243.3437
L48: #N/A | M48: 67970733 | N48: =M48/10000 -> 6797.0733
L49: 总计 | M49: =SUM(M36:M48) -> 6.6682699e+08 | N49: =M49/10000 -> 66682.699
K52: 4月 | L52: 品牌分类 | M52: 求和项:调整后gmv | N52: 万元
L53: 生活-餐饮 | M53: 18433546 | N53: =M53/10000 -> 1843.3546
L54: 生活-出行旅游 | M54: 2362105.3 | N54: =M54/10000 -> 236.21053
L55: 生活-购物（优惠劵） | M55: 3.3057688e+08 | N55: =M55/10000 -> 33057.688
L56: 生活-加油卡 | M56: 302653.24 | N56: =M56/10000 -> 30.265324
L57: 生活-健身 | M57: 8665.72 | N57: =M57/10000 -> 0.866572
L58: 生活-其他 | M58: 1744349.1 | N58: =M58/10000 -> 174.43491
L59: 网娱-其他 | M59: 29.6 | N59: =M59/10000 -> 0.00296
L60: 网娱-视频直播 | M60: 1.1286297e+08 | N60: =M60/10000 -> 11286.297
L61: 网娱-网络工具 | M61: 10694332 | N61: =M61/10000 -> 1069.4332
L62: 网娱-音频 | M62: 9138416 | N62: =M62/10000 -> 913.8416
L63: 网娱-影视会员 | M63: 36337744 | N63: =M63/10000 -> 3633.7744
L64: 网娱-知识阅读 | M64: 4181362.2 | N64: =M64/10000 -> 418.13622
L65: #N/A | M65: 77419759 | N65: =M65/10000 -> 7741.9759
L66: 总计 | M66: 6.0406282e+08 | N66: =SUM(N53:N65) -> 60406.282
K69: 5月 | L69: 品牌分类 | M69: 求和项:调整后gmv | N69: 万元
L70: 生活-餐饮 | M70: 10385219 | N70: =M70/10000 -> 1038.5219
L71: 生活-出行旅游 | M71: 4503372.3 | N71: =M71/10000 -> 450.33723
L72: 生活-购物（优惠劵） | M72: 1.229289e+08 | N72: =M72/10000 -> 12292.89
L73: 生活-加油卡 | M73: 1856859.2 | N73: =M73/10000 -> 185.68592
L74: 生活-健身 | M74: 44819.2 | N74: =M74/10000 -> 4.48192
L75: 生活-立减金 | M75: 1.4953656e+08 | N75: =M75/10000 -> 14953.656
L76: 生活-其他 | M76: 1785949.4 | N76: =M76/10000 -> 178.59494
L77: 网娱-其他 | M77: 25159.99 | N77: =M77/10000 -> 2.515999
L78: 网娱-视频直播 | M78: 94715385 | N78: =M78/10000 -> 9471.5385
L79: 网娱-网络工具 | M79: 16183066 | N79: =M79/10000 -> 1618.3066
L80: 网娱-音频 | M80: 8333794.6 | N80: =M80/10000 -> 833.37946
L81: 网娱-影视会员 | M81: 47738702 | N81: =M81/10000 -> 4773.8702
L82: 网娱-知识阅读 | M82: 5819734.5 | N82: =M82/10000 -> 581.97345
L83: #N/A | M83: 1.4154374e+08 | N83: =M83/10000 -> 14154.374
L84: 总计 | M84: 6.0540126e+08 | N84: =M84/10000 -> 60540.126
K87: 6月 | L87: 品牌分类 | M87: 求和项:调整后gmv | N87: 万元
L88: 生活-餐饮 | M88: 14226918 | N88: =M88/10000 -> 1422.6918
L89: 生活-出行旅游 | M89: 3969226.2 | N89: =M89/10000 -> 396.92262
L90: 生活-购物（优惠劵） | M90: 1.4425521e+08 | N90: =M90/10000 -> 14425.521
L91: 生活-加油卡 | M91: 1010975.1 | N91: =M91/10000 -> 101.09751
L92: 生活-健身 | M92: 18669.82 | N92: =M92/10000 -> 1.866982
L93: 生活-立减金 | M93: 1.9088456e+08 | N93: =M93/10000 -> 19088.456
L94: 生活-其他 | M94: 425860.81 | N94: =M94/10000 -> 42.586081
L95: 网娱-其他 | M95: 5629.01 | N95: =M95/10000 -> 0.562901
L96: 网娱-视频直播 | M96: 33226469 | N96: =M96/10000 -> 3322.6469
L97: 网娱-网络工具 | M97: 18927845 | N97: =M97/10000 -> 1892.7845
L98: 网娱-音频 | M98: 6905865.6 | N98: =M98/10000 -> 690.58656
L99: 网娱-影视会员 | M99: 60399085 | N99: =M99/10000 -> 6039.9085
L100: 网娱-知识阅读 | M100: 5243715.6 | N100: =M100/10000 -> 524.37156
L101: #N/A | M101: 91531242 | N101: =M101/10000 -> 9153.1242
L102: 总计 | M102: 6.0148254e+08 | N102: =SUM(N88:N101) -> 57103.127
K105: 7月 | L105: 品牌分类 | M105: 求和项:调整后gmv | N105: 万元
L106: 生活-餐饮 | M106: 8472685.5 | N106: =M106/10000 -> 847.26855
L107: 生活-出行旅游 | M107: 3347041.7 | N107: =M107/10000 -> 334.70417
L108: 生活-购物（优惠劵） | M108: 1.1301806e+08 | N108: =M108/10000 -> 11301.806
...

Sheet 毛利-收入组成
A1: 代理收入（虚拟商品充值差额收入+返点） | I1: 增值代运营收入 | P1: 推广收入：按总额反映GMV，按差额反映收入 | X1: 经纪服务+平台服务+游戏开发 | AE1: 合计收入（含税） | AL1: 年累计毛利（贴PPT） | AZ1: 代理收入（虚拟商品充值差额收入+返点）
A2: 月份 | B2: 游戏 | C2: 通信 | D2: 网娱 | E2: 生活服务 | F2: 合计（单位：万元） | I2: 月份 | J2: 游戏 | K2: 通信 | L2: 网娱 | M2: 生活服务 | N2: 合计（单位：万元） | P2: 月份 | Q2: 游戏 | R2: 通信 | S2: 网娱 | T2: 生活服务 | U2: 合计（单位：万元） | W2: 月份 | X2: 游戏 | Y2: 通信 | Z2: 网娱 | AA2: 生活服务 | AB2: 合计（单位：万元） | AD2: 月份 | AE2: 游戏 | AF2: 通信 | AG2: 网娱 | AH2: 生活服务 | AI2: 合计（单位：万元） | AJ2: check | AL2: 月度累计 | AM2: 游戏 | AN2: 通信 | AO2: 网娱 | AP2: 生活服务 | AQ2: 合计（单位：万元） | AS2: 占比 | AT2: 游戏 | AU2: 通信 | AV2: 网娱 | AW2: 生活服务 | AX2: 合计（单位：万元） | AZ2: 月份累计 | BA2: 游戏 | BB2: 通信 | BC2: 网娱 | BD2: 生活服务 | BE2: 合计（单位：万元）
A3: 43831 | B3: 1548.737 | C3: 259.54229 | D3: 907.34143 | E3: 54.659191 | F3: =SUM(B3:E3) -> 2770.2799 | I3: 43831 | J3: 0 | K3: 0 | L3: 235.27324 | M3: 0 | N3: =SUM(J3:M3) -> 235.27324 | P3: 43831 | T3: 0 | U3: =SUM(Q3:T3) -> 0 | W3: 43831 | AB3: =SUM(X3:AA3) -> 0 | AD3: 43831 | AE3: =B3+J3+Q3+X3 -> 1548.737 | AF3: =C3+K3+R3+Y3 -> 259.54229 | AG3: =D3+L3+S3+Z3 -> 1142.6147 | AH3: =E3+M3+T3+AA3 -> 54.659191 | AI3: =F3+N3+U3+AB3 -> 3005.5532 | AJ3: =SUM(AE3:AH3)-AI3 -> 0 | AL3: 20.1月累计 | AM3: =AE3 -> 1548.737 | AN3: =AF3 -> 259.54229 | AO3: =AG3 -> 1142.6147 | AP3: =AH3 -> 54.659191 | AQ3: =SUM(AM3:AP3) -> 3005.5532 | AS3: 20.1月累计 | AT3: =AM3/$AQ3 -> 0.51529184 | AU3: =AN3/$AQ3 -> 0.086354251 | AV3: =AO3/$AQ3 -> 0.38016784 | AW3: =AP3/$AQ3 -> 0.018186067 | AX3: =SUM(AT3:AW3) -> 1 | AZ3: 20.1月累计 | BA3: 1548.737 | BB3: 259.54229 | BC3: 907.34143 | BD3: 54.659191 | BE3: 2770.2799
A4: 43862 | B4: 1011.5544 | C4: 241.3401 | D4: 1075.261 | E4: 30.525706 | F4: =SUM(B4:E4) -> 2358.6812 | I4: 43862 | J4: 0.1777249 | K4: 0 | L4: 89.380825 | M4: 0 | N4: =SUM(J4:M4) -> 89.55855 | P4: 43862 | T4: -0.49117114 | U4: =SUM(Q4:T4) -> -0.49117114 | W4: 43862 | X4: 172.7398 | AB4: =SUM(X4:AA4) -> 172.7398 | AD4: 43862 | AE4: =B4+J4+Q4+X4 -> 1184.472 | AF4: =C4+K4+R4+Y4 -> 241.3401 | AG4: =D4+L4+S4+Z4 -> 1164.6418 | AH4: =E4+M4+T4+AA4 -> 30.034535 | AI4: =F4+N4+U4+AB4 -> 2620.4884 | AJ4: =SUM(AE4:AH4)-AI4 -> 0 | AL4: 20.2月累计 | AM4: =SUM(AE3:AE4) -> 2733.209 | AN4: =SUM(AF3:AF4) -> 500.88239 | AO4: =SUM(AG3:AG4) -> 2307.2565 | AP4: =SUM(AH3:AH4) -> 84.693726 | AQ4: =SUM(AM4:AP4) -> 5626.0416 | AS4: 20.2月累计 | AT4: =AM4/$AQ4 -> 0.48581386 | AU4: =AN4/$AQ4 -> 0.089029273 | AV4: =AO4/$AQ4 -> 0.41010299 | AW4: =AP4/$AQ4 -> 0.015053875 | AX4: =SUM(AT4:AW4) -> 1 | AZ4: 20.2月累计 | BA4: 2560.2915 | BB4: 500.88239 | BC4: 1982.6024 | BD4: 85.184897 | BE4: 5128.9612
A5: 43891 | B5: 1275.1451 | C5: 296.77485 | D5: 1946.1266 | E5: 63.006912 | F5: =SUM(B5:E5) -> 3581.0535 | I5: 43891 | J5: 0.51642776 | K5: 0 | L5: 95.105844 | M5: 0 | N5: =SUM(J5:M5) -> 95.622271 | P5: 43891 | T5: 0.05747956 | U5: =SUM(Q5:T5) -> 0.05747956 | W5: 43891 | AB5: =SUM(X5:AA5) -> 0 | AD5: 43891 | AE5: =B5+J5+Q5+X5 -> 1275.6615 | AF5: =C5+K5+R5+Y5 -> 296.77485 | AG5: =D5+L5+S5+Z5 -> 2041.2325 | AH5: =E5+M5+T5+AA5 -> 63.064391 | AI5: =F5+N5+U5+AB5 -> 3676.7332 | AJ5: =SUM(AE5:AH5)-AI5 -> 0 | AL5: 20.3月累计 | AM5: =SUM(AE3:AE5) -> 4008.8705 | AN5: =SUM(AF3:AF5) -> 797.65724 | AO5: =SUM(AG3:AG5) -> 4348.489 | AP5: =SUM(AH3:AH5) -> 147.75812 | AQ5: =SUM(AM5:AP5) -> 9302.7749 | AS5: 20.3月累计 | AT5: =AM5/$AQ5 -> 0.43093277 | AU5: =AN5/$AQ5 -> 0.085744013 | AV5: =AO5/$AQ5 -> 0.46743999 | AW5: =AP5/$AQ5 -> 0.015883231 | AX5: =SUM(AT5:AW5) -> 1 | AZ5: 20.3月累计 | BA5: 3835.4366 | BB5: 797.65724 | BC5: 3928.7291 | BD5: 148.19181 | BE5: 8710.0147
A6: 43922 | B6: 863.87824 | C6: 249.75354 | D6: 935.38316 | E6: 61.917787 | F6: =SUM(B6:E6) -> 2110.9327 | I6: 43922 | J6: 32.957292 | K6: 0 | L6: 105.91362 | M6: 0 | N6: =SUM(J6:M6) -> 138.87091 | P6: 43922 | T6: 4.8315701 | U6: =SUM(Q6:T6) -> 4.8315701 | W6: 43922 | X6: 5.8475038 | AB6: =SUM(X6:AA6) -> 5.8475038 | AD6: 43922 | AE6: =B6+J6+Q6+X6 -> 902.68303 | AF6: =C6+K6+R6+Y6 -> 249.75354 | AG6: =D6+L6+S6+Z6 -> 1041.2968 | AH6: =E6+M6+T6+AA6 -> 66.749357 | AI6: =F6+N6+U6+AB6 -> 2260.4827 | AJ6: =SUM(AE6:AH6)-AI6 -> 0 | AL6: 20.4月累计 | AM6: =SUM(AE3:AE6) -> 4911.5535 | AN6: =SUM(AF3:AF6) -> 1047.4108 | AO6: =SUM(AG3:AG6) -> 5389.7858 | AP6: =SUM(AH3:AH6) -> 214.50747 | AQ6: =SUM(AM6:AP6) -> 11563.258 | AS6: 20.4月累计 | AT6: =AM6/$AQ6 -> 0.42475518 | AU6: =AN6/$AQ6 -> 0.090580944 | AV6: =AO6/$AQ6 -> 0.46611309 | AW6: =AP6/$AQ6 -> 0.018550782 | AX6: =SUM(AT6:AW6) -> 1 | AZ6: 20.4月累计 | BA6: 4699.3148 | BB6: 1047.4108 | BC6: 4864.1122 | BD6: 210.1096 | BE6: 10820.947
A7: 43952 | B7: 968.37973 | C7: 534.51915 | D7: 1000.5782 | E7: 166.81088 | F7: =SUM(B7:E7) -> 2670.288 | I7: 43952 | J7: -32.432601 | K7: 0 | L7: 105.2062 | M7: 0 | N7: =SUM(J7:M7) -> 72.773599 | P7: 43952 | T7: 39.540319 | U7: =SUM(Q7:T7) -> 39.540319 | W7: 43952 | X7: 15.6502 | AB7: =SUM(X7:AA7) -> 15.6502 | AD7: 43952 | AE7: =B7+J7+Q7+X7 -> 951.59733 | AF7: =C7+K7+R7+Y7 -> 534.51915 | AG7: =D7+L7+S7+Z7 -> 1105.7844 | AH7: =E7+M7+T7+AA7 -> 206.3512 | AI7: =F7+N7+U7+AB7 -> 2798.2521 | AJ7: =SUM(AE7:AH7)-AI7 -> 0 | AL7: 20.5月累计 | AM7: =SUM(AE3:AE7) -> 5863.1509 | AN7: =SUM(AF3:AF7) -> 1581.9299 | AO7: =SUM(AG3:AG7) -> 6495.5702 | AP7: =SUM(AH3:AH7) -> 420.85868 | AQ7: =SUM(AM7:AP7) -> 14361.51 | AS7: 20.5月累计 | AT7: =AM7/$AQ7 -> 0.4082545 | AU7: =AN7/$AQ7 -> 0.11015067 | AV7: =AO7/$AQ7 -> 0.45229021 | AW7: =AP7/$AQ7 -> 0.029304627 | AX7: =SUM(AT7:AW7) -> 1 | AZ7: 20.5月累计 | BA7: 5667.6945 | BB7: 1581.9299 | BC7: 5864.6904 | BD7: 376.92048 | BE7: 13491.235
A8: 43983 | B8: 771.13742 | C8: 400.11929 | D8: 1396.0129 | E8: 308.42395 | F8: =SUM(B8:E8) -> 2875.6936 | I8: 43983 | J8: 5.0356275 | K8: 0 | L8: 112.28006 | M8: 0 | N8: =SUM(J8:M8) -> 117.31569 | P8: 43983 | T8: 5.03417 | U8: =SUM(Q8:T8) -> 5.03417 | W8: 43983 | X8: 0.01000004 | AB8: =SUM(X8:AA8) -> 0.01000004 | AD8: 43983 | AE8: =B8+J8+Q8+X8 -> 776.18305 | AF8: =C8+K8+R8+Y8 -> 400.11929 | AG8: =D8+L8+S8+Z8 -> 1508.293 | AH8: =E8+M8+T8+AA8 -> 313.45812 | AI8: =F8+N8+U8+AB8 -> 2998.0535 | AJ8: =SUM(AE8:AH8)-AI8 -> 0 | AL8: 20.6月累计 | AM8: =SUM(AE3:AE8) -> 6639.3339 | AN8: =SUM(AF3:AF8) -> 1982.0492 | AO8: =SUM(AG3:AG8) -> 8003.8632 | AP8: =SUM(AH3:AH8) -> 734.31679 | AQ8: =SUM(AM8:AP8) -> 17359.563 | AS8: 20.6月累计 | AT8: =AM8/$AQ8 -> 0.38245974 | AU8: =AN8/$AQ8 -> 0.11417622 | AV8: =AO8/$AQ8 -> 0.46106363 | AW8: =AP8/$AQ8 -> 0.042300419 | AX8: =SUM(AT8:AW8) -> 1 | AZ8: 20.6月累计 | BA8: 6438.8319 | BB8: 1982.0492 | BC8: 7260.7034 | BD8: 685.34443 | BE8: 16366.929
A9: 44013 | B9: 692.78796 | C9: 541.30515 | D9: 739.32796 | E9: 171.63185 | F9: =SUM(B9:E9) -> 2145.0529 | I9: 44013 | J9: 0.02328396 | K9: 0 | L9: 105.77402 | M9: 0 | N9: =SUM(J9:M9) -> 105.79731 | P9: 44013 | T9: 10.452123 | U9: =SUM(Q9:T9) -> 10.452123 | W9: 44013 | AB9: =SUM(X9:AA9) -> 0 | AD9: 44013 | AE9: =B9+J9+Q9+X9 -> 692.81124 | AF9: =C9+K9+R9+Y9 -> 541.30515 | AG9: =D9+L9+S9+Z9 -> 845.10199 | AH9: =E9+M9+T9+AA9 -> 182.08398 | AI9: =F9+N9+U9+AB9 -> 2261.3024 | AJ9: =SUM(AE9:AH9)-AI9 -> 0 | AL9: 20.7月累计 | AM9: =SUM(AE3:AE9) -> 7332.1452 | AN9: =SUM(AF3:AF9) -> 2523.3544 | AO9: =SUM(AG3:AG9) -> 8848.9652 | AP9: =SUM(AH3:AH9) -> 916.40077 | AQ9: =SUM(AM9:AP9) -> 19620.865 | AS9: 20.7月累计 | AT9: =AM9/$AQ9 -> 0.37369122 | AU9: =AN9/$AQ9 -> 0.12860566 | AV9: =AO9/$AQ9 -> 0.4509977 | AW9: =AP9/$AQ9 -> 0.04670542 | AX9: =SUM(AT9:AW9) -> 1 | AZ9: 20.7月累计 | BA9: 7131.6199 | BB9: 2523.3544 | BC9: 8000.0313 | BD9: 856.97628 | BE9: 18511.982
A10: 44044 | B10: 976.97592 | C10: 375.32022 | D10: 937.49061 | E10: 427.87452 | F10: =SUM(B10:E10) -> 2717.6613 | I10: 44044 | J10: 0.27428454 | K10: 0.763412 | L10: 198.73142 | M10: 0 | N10: =SUM(J10:M10) -> 199.76912 | P10: 44044 | T10: 5.3365223 | U10: =SUM(Q10:T10) -> 5.3365223 | W10: 44044 | X10: 65.1 | AB10: =SUM(X10:AA10) -> 65.1 | AD10: 44044 | AE10: =B10+J10+Q10+X10 -> 1042.3502 | AF10: =C10+K10+R10+Y10 -> 376.08363 | AG10: =D10+L10+S10+Z10 -> 1136.222 | AH10: =E10+M10+T10+AA10 -> 433.21105 | AI10: =F10+N10+U10+AB10 -> 2987.8669 | AJ10: =SUM(AE10:AH10)-AI10 -> 0 | AL10: 20.8月累计 | AM10: =SUM(AE3:AE10) -> 8374.4954 | AN10: =SUM(AF3:AF10) -> 2899.438 | AO10: =SUM(AG3:AG10) -> 9985.1872 | AP10: =SUM(AH3:AH10) -> 1349.6118 | AQ10: =SUM(AM10:AP10) -> 22608.732 | AS10: 20.8月累计 | AT10: =AM10/$AQ10 -> 0.37040977 | AU10: =AN10/$AQ10 -> 0.12824416 | AV10: =AO10/$AQ10 -> 0.44165179 | AW10: =AP10/$AQ10 -> 0.059694272 | AX10: =SUM(AT10:AW10) -> 1 | AZ10: 20.8月累计 | BA10: 8108.5958 | BB10: 2898.6746 | BC10: 8937.522 | BD10: 1284.8508 | BE10: 21229.643
A11: 44075 | B11: 1085.1145 | C11: 422.72242 | D11: 1053.0637 | E11: 258.89113 | F11: =SUM(B11:E11) -> 2819.7918 | I11: 44075 | J11: 0.48239752 | K11: 0.245602 | L11: 134.96318 | M11: 0.28263734 | N11: =SUM(J11:M11) -> 135.97382 | P11: 44075 | T11: -7.2231039 | U11: =SUM(Q11:T11) -> -7.2231039 | W11: 44075 | X11: 41.9 | AB11: =SUM(X11:AA11) -> 41.9 | AD11: 44075 | AE11: =B11+J11+Q11+X11 -> 1127.4969 | AF11: =C11+K11+R11+Y11 -> 422.96802 | AG11: =D11+L11+S11+Z11 -> 1188.0269 | AH11: =E11+M11+T11+AA11 -> 251.95066 | AI11: =F11+N11+U11+AB11 -> 2990.4425 | AJ11: =SUM(AE11:AH11)-AI11 -> 0 | AL11: 20.9月累计 | AM11: =SUM(AE3:AE11) -> 9501.9923 | AN11: =SUM(AF3:AF11) -> 3322.406 | AO11: =SUM(AG3:AG11) -> 11173.214 | AP11: =SUM(AH3:AH11) -> 1601.5625 | AQ11: =SUM(AM11:AP11) -> 25599.175 | AS11: 20.9月累计 | AT11: =AM11/$AQ11 -> 0.37118354 | AU11: =AN11/$AQ11 -> 0.12978567 | AV11: =AO11/$AQ11 -> 0.43646774 | AW11: =AP11/$AQ11 -> 0.062563051 | AX11: =SUM(AT11:AW11) -> 1 | AZ11: 20.9月累计 | BA11: 9193.7104 | BB11: 3321.397 | BC11: 9990.5856 | BD11: 1543.7419 | BE11: 24049.435
A12: 44105 | B12: 243.65397 | C12: 563.52158 | D12: 858.34334 | E12: 441.92058 | F12: =SUM(B12:E12) -> 2107.4395 | I12: 44105 | J12: -0.00801148 | K12: 0 | L12: 183.27774 | M12: 0.2340533 | N12: =SUM(J12:M12) -> 183.50378 | P12: 44105 | T12: 2.6016969 | U12: =SUM(Q12:T12) -> 2.6016969 | W12: 44105 | X12: 62.85 | AB12: =SUM(X12:AA12) -> 62.85 | AD12: 44105 | AE12: =B12+J12+Q12+X12 -> 306.49596 | AF12: =C12+K12+R12+Y12 -> 563.52158 | AG12: =D12+L12+S12+Z12 -> 1041.6211 | AH12: =E12+M12+T12+AA12 -> 444.75633 | AI12: =F12+N12+U12+AB12 -> 2356.395 | AJ12: =SUM(AE12:AH12)-AI12 -> 0 | AL12: 20.10月累计 | AM12: =SUM(AE3:AE12) -> 9808.4883 | AN12: =SUM(AF3:AF12) -> 3885.9276 | AO12: =SUM(AG3:AG12) -> 12214.835 | AP12: =SUM(AH3:AH12) -> 2046.3188 | AQ12: =SUM(AM12:AP12) -> 27955.57 | AS12: 20.10月累计 | AT12: =AM12/$AQ12 -> 0.35085989 | AU12: =AN12/$AQ12 -> 0.1390037 | AV12: =AO12/$AQ12 -> 0.43693744 | AW12: =AP12/$AQ12 -> 0.073198966 | AX12: =SUM(AT12:AW12) -> 1 | AZ12: 20.10月累计 | BA12: 9437.3643 | BB12: 3884.9186 | BC12: 10848.929 | BD12: 1985.6625 | BE12: 26156.874
A13: 44136 | B13: 679.46555 | C13: 630.52893 | D13: 2092.6453 | E13: 180.99483 | F13: =SUM(B13:E13) -> 3583.6346 | I13: 44136 | J13: 0.25087444 | K13: 0 | L13: 598.84461 | M13: 0.22402782 | N13: =SUM(J13:M13) -> 599.31951 | P13: 44136 | T13: 13.905538 | U13: =SUM(Q13:T13) -> 13.905538 | W13: 44136 | AB13: =SUM(X13:AA13) -> 0 | AD13: 44136 | AE13: =B13+J13+Q13+X13 -> 679.71643 | AF13: =C13+K13+R13+Y13 -> 630.52893 | AG13: =D13+L13+S13+Z13 -> 2691.4899 | AH13: =E13+M13+T13+AA13 -> 195.1244 | AI13: =F13+N13+U13+AB13 -> 4196.8596 | AJ13: =SUM(AE13:AH13)-AI13 -> 0 | AL13: 20.11月累计 | AM13: =SUM(AE3:AE13) -> 10488.205 | AN13: =SUM(AF3:AF13) -> 4516.4565 | AO13: =SUM(AG3:AG13) -> 14906.325 | AP13: =SUM(AH3:AH13) -> 2241.4432 | AQ13: =SUM(AM13:AP13) -> 32152.429 | AS13: 20.11月累计 | AT13: =AM13/$AQ13 -> 0.32620256 | AU13: =AN13/$AQ13 -> 0.14047015 | AV13: =AO13/$AQ13 -> 0.46361427 | AW13: =AP13/$AQ13 -> 0.069713028 | AX13: =SUM(AT13:AW13) -> 1 | AZ13: 20.11月累计 | BA13: 10116.83 | BB13: 4515.4475 | BC13: 12941.574 | BD13: 2166.6573 | BE13: 29740.509
A14: 44166 | B14: 899.32654 | C14: 500.97601 | D14: 2715.5892 | E14: 402.79689 | F14: =SUM(B14:E14) -> 4518.6887 | I14: 44166 | J14: 1.3039537 | K14: 0 | L14: 145.9554 | M14: 2.5722617 | N14: =SUM(J14:M14) -> 149.83162 | P14: 44166 | T14: 89.509654 | U14: =SUM(Q14:T14) -> 89.509654 | W14: 44166 | X14: 84.091998 | AB14: =SUM(X14:AA14) -> 84.091998 | AD14: 44166 | AE14: =B14+J14+Q14+X14 -> 984.72249 | AF14: =C14+K14+R14+Y14 -> 500.97601 | AG14: =D14+L14+S14+Z14 -> 2861.5446 | AH14: =E14+M14+T14+AA14 -> 494.8788 | AI14: =F14+N14+U14+AB14 -> 4842.1219 | AJ14: =SUM(AE14:AH14)-AI14 -> 0 | AL14: 20.12月累计 | AM14: =SUM(AE3:AE14) -> 11472.927 | AN14: =SUM(AF3:AF14) -> 5017.4325 | AO14: =SUM(AG3:AG14) -> 17767.87 | AP14: =SUM(AH3:AH14) -> 2736.322 | AQ14: =SUM(AM14:AP14) -> 36994.551 | AS14: 20.12月累计 | AT14: =AM14/$AQ14 -> 0.31012478 | AU14: =AN14/$AQ14 -> 0.13562626 | AV14: =AO14/$AQ14 -> 0.48028342 | AW14: =AP14/$AQ14 -> 0.073965541 | AX14: =SUM(AT14:AW14) -> 1 | AZ14: 20.12月累计 | BA14: 11016.156 | BB14: 5016.4235 | BC14: 15657.163 | BD14: 2569.4542 | BE14: 34259.198
A15: 44197 | B15: 402.27823 | C15: 559.51924 | D15: 1607.6583 | E15: 507.68088 | F15: =SUM(B15:E15) -> 3077.1366 | I15: 44197 | J15: 14.183812 | K15: 0 | L15: 156.18729 | M15: 1.0140585 | N15: =SUM(J15:M15) -> 171.38516 | P15: 44197 | Q15: 0 | R15: 0 | S15: 0 | T15: 19.113534 | U15: =SUM(Q15:T15) -> 19.113534 | W15: 44197 | X15: 0.0515955 | Y15: 0 | Z15: 0 | AA15: -0.05951476 | AB15: =SUM(X15:AA15) -> -0.00791926 | AD15: 44197 | AE15: =B15+J15+Q15+X15 -> 416.51364 | AF15: =C15+K15+R15+Y15 -> 559.51924 | AG15: =D15+L15+S15+Z15 -> 1763.8455 | AH15: =E15+M15+T15+AA15 -> 527.74896 | AI15: =F15+N15+U15+AB15 -> 3267.6274 | AJ15: =SUM(AE15:AH15)-AI15 -> 0 | AL15: 21.1月累计 | AM15: =AE15 -> 416.51364 | AN15: =AF15 -> 559.51924 | AO15: =AG15 -> 1763.8455 | AP15: =AH15 -> 527.74896 | AQ15: =SUM(AM15:AP15) -> 3267.6274 | AS15: 21.1月累计 | AT15: =AM15/$AQ15 -> 0.12746669 | AU15: =AN15/$AQ15 -> 0.17123104 | AV15: =AO15/$AQ15 -> 0.53979397 | AW15: =AP15/$AQ15 -> 0.16150831 | AX15: =SUM(AT15:AW15) -> 1 | AZ15: 21.1月累计 | BA15: 402.27823 | BB15: 559.51924 | BC15: 1607.6583 | BD15: 507.68088 | BE15: 3077.1366
A16: 44228 | B16: 488.58875 | C16: 542.10398 | D16: 1137.1924 | E16: 282.05379 | F16: =SUM(B16:E16) -> 2449.939 | I16: 44228 | J16: 546.48274 | K16: 0 | L16: 201.93547 | M16: 0.86096592 | N16: =SUM(J16:M16) -> 749.27918 | P16: 44228 | Q16: 0 | R16: 0 | S16: 0 | T16: -15.10292 | U16: =SUM(Q16:T16) -> -15.10292 | W16: 44228 | X16: 1.5389875 | Y16: 0 | Z16: 0 | AA16: 0.06840392 | AB16: =SUM(X16:AA16) -> 1.6073914 | AD16: 44228 | AE16: =B16+J16+Q16+X16 -> 1036.6105 | AF16: =C16+K16+R16+Y16 -> 542.10398 | AG16: =D16+L16+S16+Z16 -> 1339.1279 | AH16: =E16+M16+T16+AA16 -> 267.88024 | AI16: =F16+N16+U16+AB16 -> 3185.7226 | AJ16: =SUM(AE16:AH16)-AI16 -> 0 | AL16: 21.2月累计 | AM16: =SUM(AE15:AE16) -> 1453.1241 | AN16: =SUM(AF15:AF16) -> 1101.6232 | AO16: =SUM(AG15:AG16) -> 3102.9735 | AP16: =SUM(AH15:AH16) -> 795.6292 | AQ16: =SUM(AM16:AP16) -> 6453.35 | AS16: 21.2月累计 | AT16: =AM16/$AQ16 -> 0.22517361 | AU16: =AN16/$AQ16 -> 0.17070564 | AV16: =AO16/$AQ16 -> 0.48083142 | AW16: =AP16/$AQ16 -> 0.12328933 | AX16: =SUM(AT16:AW16) -> 1 | AZ16: 21.2月累计 | BA16: 890.86698 | BB16: 1101.6232 | BC16: 2744.8507 | BD16: 789.73468 | BE16: 5527.0756
A17: 44256 | B17: 356.5353 | C17: 728.13222 | D17: 2787.0571 | E17: 365.72309 | F17: =SUM(B17:E17) -> 4237.4477 | I17: 44256 | J17: 330.32726 | K17: 0 | L17: 154.32761 | M17: 9.9237115 | N17: =SUM(J17:M17) -> 494.57858 | P17: 44256 | Q17: 0 | R17: 0 | S17: 0 | T17: -17.595791 | U17: =SUM(Q17:T17) -> -17.595791 | W17: 44256 | X17: 2.0169192 | Y17: 0 | Z17: 0 | AA17: 0 | AB17: =SUM(X17:AA17) -> 2.0169192 | AD17: 44256 | AE17: =B17+J17+Q17+X17 -> 688.87947 | AF17: =C17+K17+R17+Y17 -> 728.13222 | AG17: =D17+L17+S17+Z17 -> 2941.3847 | AH17: =E17+M17+T17+AA17 -> 358.05101 | AI17: =F17+N17+U17+AB17 -> 4716.4474 | AJ17: =SUM(AE17:AH17)-AI17 -> 0 | AL17: 21.3月累计 | AM17: =SUM(AE15:AE17) -> 2142.0036 | AN17: =SUM(AF15:AF17) -> 1829.7554 | AO17: =SUM(AG15:AG17) -> 6044.3581 | AP17: =SUM(AH15:AH17) -> 1153.6802 | AQ17: =SUM(AM17:AP17) -> 11169.797 | AS17: 21.3月累计 | AT17: =AM17/$AQ17 -> 0.19176745 | AU17: =AN17/$AQ17 -> 0.16381277 | AV17: =AO17/$AQ17 -> 0.54113409 | AW17: =AP17/$AQ17 -> 0.10328569 | AX17: =SUM(AT17:AW17) -> 1 | AZ17: 21.3月累计 | BA17: 1247.4023 | BB17: 1829.7554 | BC17: 5531.9078 | BD17: 1155.4578 | BE17: 9764.5233
A18: 44287 | B18: 236.52163 | C18: 813.21296 | D18: 639.93242 | E18: 329.58635 | F18: =SUM(B18:E18) -> 2019.2534 | I18: 44287 | J18: 28.478805 | K18: 0 | L18: 153.53373 | M18: 0.37578484 | N18: =SUM(J18:M18) -> 182.38832 | P18: 44287 | Q18: 0 | R18: 0 | S18: 0 | T18: 27.92591 | U18: =SUM(Q18:T18) -> 27.92591 | W18: 44287 | X18: 45.293797 | Y18: 0 | Z18: 0 | AA18: 1.5037817 | AB18: =SUM(X18:AA18) -> 46.797579 | AD18: 44287 | AE18: =B18+J18+Q18+X18 -> 310.29423 | AF18: =C18+K18+R18+Y18 -> 813.21296 | AG18: =D18+L18+S18+Z18 -> 793.46615 | AH18: =E18+M18+T18+AA18 -> 359.39183 | AI18: =F18+N18+U18+AB18 -> 2276.3652 | AJ18: =SUM(AE18:AH18)-AI18 -> 0 | AL18: 21.4月累计 | AM18: =SUM(AE15:AE18) -> 2452.2978 | AN18: =SUM(AF15:AF18) -> 2642.9684 | AO18: =SUM(AG15:AG18) -> 6837.8243 | AP18: =SUM(AH15:AH18) -> 1513.072 | AQ18: =SUM(AM18:AP18) -> 13446.163 | AS18: 21.4月累计 | AT18: =AM18/$AQ18 -> 0.18237901 | AU18: =AN18/$AQ18 -> 0.19655931 | AV18: =AO18/$AQ18 -> 0.50853351 | AW18: =AP18/$AQ18 -> 0.11252817 | AX18: =SUM(AT18:AW18) -> 1 | AZ18: 21.4月累计 | BA18: 1483.9239 | BB18: 2642.9684 | BC18: 6171.8402 | BD18: 1485.0441 | BE18: 11783.777
A19: 44317 | B19: 256.6498 | C19: 1101.2379 | D19: 1111.4885 | E19: 340.37551 | F19: =SUM(B19:E19) -> 2809.7517 | I19: 44317 | J19: 226.573 | K19: 0 | L19: 146.84182 | M19: 10.728323 | N19: =SUM(J19:M19) -> 384.14314 | P19: 44317 | Q19: 0 | R19: 0 | S19: 0 | T19: 10.131292 | U19: =SUM(Q19:T19) -> 10.131292 | W19: 44317 | X19: 1.5670044 | Y19: 0 | Z19: 0 | AA19: 0.1399995 | AB19: =SUM(X19:AA19) -> 1.7070039 | AD19: 44317 | AE19: =B19+J19+Q19+X19 -> 484.78981 | AF19: =C19+K19+R19+Y19 -> 1101.2379 | AG19: =D19+L19+S19+Z19 -> 1258.3304 | AH19: =E19+M19+T19+AA19 -> 361.37513 | AI19: =F19+N19+U19+AB19 -> 3205.7331 | AJ19: =SUM(AE19:AH19)-AI19 -> 0 | AL19: 21.5月累计 | AM19: =SUM(AE15:AE19) -> 2937.0876 | AN19: =SUM(AF15:AF19) -> 3744.2063 | AO19: =SUM(AG15:AG19) -> 8096.1546 | AP19: =SUM(AH15:AH19) -> 1874.4472 | AQ19: =SUM(AM19:AP19) -> 16651.896 | AS19: 21.5月累计 | AT19: =AM19/$AQ19 -> 0.17638158 | AU19: =AN19/$AQ19 -> 0.22485165 | AV19: =AO19/$AQ19 -> 0.48620018 | AW19: =AP19/$AQ19 -> 0.11256659 | AX19: =SUM(AT19:AW19) -> 1 | AZ19: 21.5月累计 | BA19: 1740.5737 | BB19: 3744.2063 | BC19: 7283.3287 | BD19: 1825.4196 | BE19: 14593.528
A20: 44348 | B20: 460.4562 | C20: 1107.4281 | D20: 2248.0557 | E20: =267.930894339999+897733.18/10000 -> 357.70421 | F20: =SUM(B20:E20) -> 4173.6442 | I20: 44348 | J20: 387.50775 | K20: 0 | L20: 194.94649 | M20: 0.9571482 | N20: =SUM(J20:M20) -> 583.41138 | P20: 44348 | Q20: 0 | R20: 0 | S20: 0 | T20: 75.23211 | U20: =SUM(Q20:T20) -> 75.23211 | W20: 44348 | X20: 174.97704 | Y20: 0 | Z20: 0 | AA20: 6.1661302 | AB20: =SUM(X20:AA20) -> 181.14317 | AD20: 44348 | AE20: =B20+J20+Q20+X20 -> 1022.941 | AF20: =C20+K20+R20+Y20 -> 1107.4281 | AG20: =D20+L20+S20+Z20 -> 2443.0021 | AH20: =E20+M20+T20+AA20 -> 440.0596 | AI20: =F20+N20+U20+AB20 -> 5013.4309 | AJ20: =SUM(AE20:AH20)-AI20 -> 0 | AL20: 21.6月累计 | AM20: =SUM(AE15:AE20) -> 3960.0286 | AN20: =SUM(AF15:AF20) -> 4851.6344 | AO20: =SUM(AG15:AG20) -> 10539.157 | AP20: =SUM(AH15:AH20) -> 2314.5068 | AQ20: =SUM(AM20:AP20) -> 21665.327 | AS20: 21.6月累计 | AT20: =AM20/$AQ20 -> 0.18278186 | AU20: =AN20/$AQ20 -> 0.22393544 | AV20: =AO20/$AQ20 -> 0.48645271 | AW20: =AP20/$AQ20 -> 0.10683 | AX20: =SUM(AT20:AW20) -> 1 | AZ20: 21.6月累计 | BA20: 2201.0299 | BB20: 4851.6344 | BC20: 9531.3844 | BD20: 2183.1238 | BE20: 18767.173
A21: 44378 | B21: 286.43738 | C21: 860.61755 | D21: 671.29109 | E21: 216.76834 | F21: =SUM(B21:E21) -> 2035.1144 | I21: 44378 | J21: 115.30655 | K21: 0 | L21: 239.27565 | M21: 0.51343644 | N21: =SUM(J21:M21) -> 355.09564 | P21: 44378 | Q21: 0 | R21: 0 | S21: 0 | T21: 35.531281 | U21: =SUM(Q21:T21) -> 35.531281 | W21: 44378 | X21: 0.18943684 | Y21: 0 | Z21: 0 | AA21: 5.6012838 | AB21: =SUM(X21:AA21) -> 5.7907206 | AD21: 44378 | AE21: =B21+J21+Q21+X21 -> 401.93337 | AF21: =C21+K21+R21+Y21 -> 860.61755 | AG21: =D21+L21+S21+Z21 -> 910.56674 | AH21: =E21+M21+T21+AA21 -> 258.41434 | AI21: =F21+N21+U21+AB21 -> 2431.532 | AJ21: =SUM(AE21:AH21)-AI21 -> 0 | AL21: 21.7月累计 | AM21: =SUM(AE15:AE21) -> 4361.962 | AN21: =SUM(AF15:AF21) -> 5712.2519 | AO21: =SUM(AG15:AG21) -> 11449.724 | AP21: =SUM(AH15:AH21) -> 2572.9211 | AQ21: =SUM(AM21:AP21) -> 24096.859 | AS21: 21.7月累计 | AT21: =AM21/$AQ21 -> 0.18101787 | AU21: =AN21/$AQ21 -> 0.2370538 | AV21: =AO21/$AQ21 -> 0.4751542 | AW21: =AP21/$AQ21 -> 0.10677413 | AX21: =SUM(AT21:AW21) -> 1 | AZ21: 21.7月累计 | BA21: 2487.4673 | BB21: 5712.2519 | BC21: 10202.675 | BD21: 2399.8922 | BE21: 20802.287
A22: 44409 | B22: 242.47369 | C22: 1083.1079 | D22: 2403.4055 | E22: 355.56105 | F22: =SUM(B22:E22) -> 4084.5481 | I22: 44409 | J22: 120.2148 | K22: 0 | L22: 165.66233 | M22: 0.78503918 | N22: =SUM(J22:M22) -> 286.66217 | P22: 44409 | Q22: 5.0756266 | R22: 0 | S22: 0 | T22: 18.268923 | U22: =SUM(Q22:T22) -> 23.34455 | W22: 44409 | X22: 0.11049016 | Y22: 0 | Z22: 0 | AA22: 6.7807522 | AB22: =SUM(X22:AA22) -> 6.8912423 | AD22: 44409 | AE22: =B22+J22+Q22+X22 -> 367.87461 | AF22: =C22+K22+R22+Y22 -> 1083.1079 | AG22: =D22+L22+S22+Z22 -> 2569.0679 | AH22: =E22+M22+T22+AA22 -> 381.39576 | AI22: =F22+N22+U22+AB22 -> 4401.4461 | AJ22: =SUM(AE22:AH22)-AI22 -> 0 | AL22: 21.8月累计 | AM22: =SUM(AE15:AE22) -> 4729.8366 | AN22: =SUM(AF15:AF22) -> 6795.3598 | AO22: =SUM(AG15:AG22) -> 14018.791 | AP22: =SUM(AH15:AH22) -> 2954.3169 | AQ22: =SUM(AM22:AP22) -> 28498.305 | AS22: 21.8月累计 | AT22: =AM22/$AQ22 -> 0.16596905 | AU22: =AN22/$AQ22 -> 0.23844786 | AV22: =AO22/$AQ22 -> 0.49191668 | AW22: =AP22/$AQ22 -> 0.10366641 | AX22: =SUM(AT22:AW22) -> 1 | AZ22: 21.8月累计 | BA22: 2729.941 | BB22: 6795.3598 | BC22: 12606.081 | BD22: 2755.4532 | BE22: 24886.835
A23: 44440 | B23: 487.32455 | C23: 550.62367 | D23: 1512.2165 | E23: 215.69798 | F23: =SUM(B23:E23) -> 2765.8627 | I23: 44440 | J23: 271.61449 | K23: 0 | L23: 290.27186 | M23: 8.7018304 | N23: =SUM(J23:M23) -> 570.58818 | P23: 44440 | Q23: -4.9999999 | R23: 0 | S23: 0 | T23: 2.4987634 | U23: =SUM(Q23:T23) -> -2.5012364 | W23: 44440 | X23: 6.0879923 | Y23: 0 | Z23: 0 | AA23: 3.2931073 | AB23: =SUM(X23:AA23) -> 9.3810996 | AD23: 44440 | AE23: =B23+J23+Q23+X23 -> 760.02703 | AF23: =C23+K23+R23+Y23 -> 550.62367 | AG23: =D23+L23+S23+Z23 -> 1802.4884 | AH23: =E23+M23+T23+AA23 -> 230.19168 | AI23: =F23+N23+U23+AB23 -> 3343.3307 | AJ23: =SUM(AE23:AH23)-AI23 -> 0 | AL23: 21.9月累计 | AM23: =SUM(AE15:AE23) -> 5489.8636 | AN23: =SUM(AF15:AF23) -> 7345.9835 | AO23: =SUM(AG15:AG23) -> 15821.28 | AP23: =SUM(AH15:AH23) -> 3184.5085 | AQ23: =SUM(AM23:AP23) -> 31841.635 | AS23: 21.9月累计 | AT23: =AM23/$AQ23 -> 0.17241148 | AU23: =AN23/$AQ23 -> 0.23070371 | AV23: =AO23/$AQ23 -> 0.49687397 | AW23: =AP23/$AQ23 -> 0.10001084 | AX23: =SUM(AT23:AW23) -> 1 | AZ23: 21.9月累计 | BA23: 3217.2655 | BB23: 7345.9835 | BC23: 14118.297 | BD23: 2971.1512 | BE23: 27652.698
A24: 44470 | B24: 223.60998 | C24: 533.78761 | D24: 842.03755 | E24: 333.63151 | F24: =SUM(B24:E24) -> 1933.0667 | I24: 44470 | J24: 100.33987 | K24: 0 | L24: 144.0338 | M24: 4.4653178 | N24: =SUM(J24:M24) -> 248.83899 | P24: 44470 | Q24: 0 | R24: 0 | S24: 0.57000016 | T24: -56.131241 | U24: =SUM(Q24:T24) -> -55.561241 | W24: 44470 | X24: 15.109671 | Y24: 0 | Z24: 0 | AA24: 5.6083328 | AB24: =SUM(X24:AA24) -> 20.718004 | AD24: 44470 | AE24: =B24+J24+Q24+X24 -> 339.05952 | AF24: =C24+K24+R24+Y24 -> 533.78761 | AG24: =D24+L24+S24+Z24 -> 986.64135 | AH24: =E24+M24+T24+AA24 -> 287.57392 | AI24: =F24+N24+U24+AB24 -> 2147.0624 | AJ24: =SUM(AE24:AH24)-AI24 -> 0 | AL24: 21.10月累计 | AM24: =SUM(AE15:AE24) -> 5828.9232 | AN24: =SUM(AF15:AF24) -> 7879.7711 | AO24: =SUM(AG15:AG24) -> 16807.921 | AP24: =SUM(AH15:AH24) -> 3472.0825 | AQ24: =SUM(AM24:AP24) -> 33988.698 | AS24: 21.10月累计 | AT24: =AM24/$AQ24 -> 0.17149592 | AU24: =AN24/$AQ24 -> 0.23183504 | AV24: =AO24/$AQ24 -> 0.49451501 | AW24: =AP24/$AQ24 -> 0.10215403 | AX24: =SUM(AT24:AW24) -> 1 | AZ24: 21.10月累计 | BA24: 3440.8755 | BB24: 7879.7711 | BC24: 14960.335 | BD24: 3304.7827 | BE24: 29585.764
A25: 44501 | B25: 462.20496 | C25: 453.20138 | D25: 1766.856 | E25: 181.29137 | F25: =SUM(B25:E25) -> 2863.5538 | I25: 44501 | J25: 444.20086 | K25: 0 | L25: =1017.12313038 -> 1017.1231 | M25: 0.47012166 | N25: =SUM(J25:M25) -> 1461.7941 | P25: 44501 | Q25: 2.2174532 | R25: 0 | S25: 0 | T25: 323.37468 | U25: =SUM(Q25:T25) -> 325.59214 | W25: 44501 | X25: -3.9701007 | Y25: 0 | Z25: 0 | AA25: 7.4908737 | AB25: =SUM(X25:AA25) -> 3.520773 | AD25: 44501 | AE25: =B25+J25+Q25+X25 -> 904.65318 | AF25: =C25+K25+R25+Y25 -> 453.20138 | AG25: =D25+L25+S25+Z25 -> 2783.9792 | AH25: =E25+M25+T25+AA25 -> 512.62704 | AI25: =F25+N25+U25+AB25 -> 4654.4608 | AJ25: =SUM(AE25:AH25)-AI25 -> 0 | AL25: 21.11月累计 | AM25: =SUM(AE15:AE25) -> 6733.5763 | AN25: =SUM(AF15:AF25) -> 8332.9725 | AO25: =SUM(AG15:AG25) -> 19591.9 | AP25: =SUM(AH15:AH25) -> 3984.7095 | AQ25: =SUM(AM25:AP25) -> 38643.159 | AS25: 21.11月累计 | AT25: =AM25/$AQ25 -> 0.17425015 | AU25: =AN25/$AQ25 -> 0.21563901 | AV25: =AO25/$AQ25 -> 0.50699531 | AW25: =AP25/$AQ25 -> 0.10311552 | AX25: =SUM(AT25:AW25) -> 1 | AZ25: 21.11月累计 | BA25: 3903.0805 | BB25: 8332.9725 | BC25: 16727.191 | BD25: 3486.0741 | BE25: 32449.318
A26: 44531 | B26: -54.879802 | C26: 286.93702 | D26: =3497.65611226+3013980.6/10000-1126936.84*1.06/10000+1145995.76/10000 -> 3794.1984 | E26: =169.845578359999+785557.6/10000 -> 248.40134 | F26: =SUM(B26:E26) -> 4274.657 | I26: 44531 | J26: 137.75379 | K26: 0 | L26: 273.04713 | M26: 31.827787 | N26: =SUM(J26:M26) -> 442.6287 | P26: 44531 | Q26: 6.0362304 | R26: 0 | S26: 0.72400014 | T26: 11.319376 | U26: =SUM(Q26:T26) -> 18.079607 | W26: 44531 | X26: 17.845633 | Y26: 0 | Z26: 0 | AA26: 6.7942714 | AB26: =SUM(X26:AA26) -> 24.639905 | AD26: 44531 | AE26: =B26+J26+Q26+X26 -> 106.75585 | AF26: =C26+K26+R26+Y26 -> 286.93702 | AG26: =D26+L26+S26+Z26 -> 4067.9696 | AH26: =E26+M26+T26+AA26 -> 298.34277 | AI26: =F26+N26+U26+AB26 -> 4760.0052 | AJ26: =SUM(AE26:AH26)-AI26 -> 0 | AL26: 21.12月累计 | AM26: =SUM(AE15:AE26) -> 6840.3322 | AN26: =SUM(AF15:AF26) -> 8619.9095 | AO26: =SUM(AG15:AG26) -> 23659.87 | AP26: =SUM(AH15:AH26) -> 4283.0523 | AQ26: =SUM(AM26:AP26) -> 43403.164 | AS26: 21.12月累计 | AT26: =AM26/$AQ26 -> 0.15759985 | AU26: =AN26/$AQ26 -> 0.19860095 | AV26: =AO26/$AQ26 -> 0.54511855 | AW26: =AP26/$AQ26 -> 0.098680647 | AX26: =SUM(AT26:AW26) -> 1 | AZ26: 21.12月累计 | BA26: 3848.2007 | BB26: 8619.9095 | BC26: 20521.39 | BD26: 3734.4754 | BE26: 36723.975
A27: 44562 | B27: 415.71994 | C27: 174.16113 | D27: 1453.4084 | E27: 373.95052 | F27: =SUM(B27:E27) -> 2417.24 | I27: 44562 | J27: -51.173207 | K27: 0 | L27: 202.54345 | M27: 10.352368 | N27: =SUM(J27:M27) -> 161.72261 | P27: 44562 | Q27: -1.6937517 | R27: 0 | S27: 0 | T27: -14.262493 | U27: =SUM(Q27:T27) -> -15.956245 | W27: 44562 | X27: 0.25894634 | Y27: 0 | Z27: 0 | AA27: 8.6146688 | AB27: =SUM(X27:AA27) -> 8.8736151 | AD27: 44562 | AE27: =B27+J27+Q27+X27 -> 363.11193 | AF27: =C27+K27+R27+Y27 -> 174.16113 | AG27: =D27+L27+S27+Z27 -> 1655.9519 | AH27: =E27+M27+T27+AA27 -> 378.65507 | AI27: =F27+N27+U27+AB27 -> 2571.88 | AJ27: =SUM(AE27:AH27)-AI27 -> 0 | AL27: 22.1月累计 | AM27: =AE27 -> 363.11193 | AN27: =AF27 -> 174.16113 | AO27: =AG27 -> 1655.9519 | AP27: =AH27 -> 378.65507 | AQ27: =SUM(AM27:AP27) -> 2571.88 | AS27: 22.1月累计 | AT27: =AM27/$AQ27 -> 0.14118541 | AU27: =AN27/$AQ27 -> 0.067717441 | AV27: =AO27/$AQ27 -> 0.64386825 | AW27: =AP27/$AQ27 -> 0.1472289 | AX27: =SUM(AT27:AW27) -> 1 | AZ27: 22.1月累计 | BA27: 415.71994 | BB27: 174.16113 | BC27: 1453.4084 | BD27: 373.95052 | BE27: 2417.24
A28: 44593 | B28: 221.05127 | C28: 278.82654 | D28: 647.55649 | E28: 262.57617 | F28: =SUM(B28:E28) -> 1410.0105 | I28: 44593 | J28: 502.32814 | K28: 0 | L28: 193.02708 | M28: 3.484379 | N28: =SUM(J28:M28) -> 698.8396 | P28: 44593 | Q28: 0.10716918 | R28: 0 | S28: 9.4499996 | T28: -106.62474 | U28: =SUM(Q28:T28) -> -97.067569 | W28: 44593 | X28: 0.85740538 | Y28: 0 | Z28: 0 | AA28: 9.4712982 | AB28: =SUM(X28:AA28) -> 10.328704 | AD28: 44593 | AE28: =B28+J28+Q28+X28 -> 724.34398 | AF28: =C28+K28+R28+Y28 -> 278.82654 | AG28: =D28+L28+S28+Z28 -> 850.03358 | AH28: =E28+M28+T28+AA28 -> 168.90711 | AI28: =F28+N28+U28+AB28 -> 2022.1112 | AJ28: =SUM(AE28:AH28)-AI28 -> 0 | AL28: 22.2月累计 | AM28: =SUM(AE27:AE28) -> 1087.4559 | AN28: =SUM(AF27:AF28) -> 452.98767 | AO28: =SUM(AG27:AG28) -> 2505.9854 | AP28: =SUM(AH27:AH28) -> 547.56217 | AQ28: =SUM(AM28:AP28) -> 4593.9912 | AS28: 22.2月累计 | AT28: =AM28/$AQ28 -> 0.23671267 | AU28: =AN28/$AQ28 -> 0.098604385 | AV28: =AO28/$AQ28 -> 0.545492 | AW28: =AP28/$AQ28 -> 0.11919095 | AX28: =SUM(AT28:AW28) -> 1 | AZ28: 22.2月累计 | BA28: 636.77121 | BB28: 452.98767 | BC28: 2100.9649 | BD28: 636.52669 | BE28: 3827.2505
A29: 44621 | B29: 462.08028 | C29: 221.16107 | D29: =1749.7701880402+146.567852*1.06 -> 1905.1321 | E29: 454.04892 | F29: =SUM(B29:E29) -> 3042.4224 | I29: 44621 | J29: 23.709202 | K29: 0 | L29: 327.83535 | M29: 10.966806 | N29: =SUM(J29:M29) -> 362.51136 | P29: 44621 | Q29: 0.06497588 | R29: 0 | S29: 11.42586 | T29: -40.1706 | U29: =SUM(Q29:T29) -> -28.679764 | W29: 44621 | X29: 22.29 | Y29: 0 | Z29: 0 | AA29: 15.834884 | AB29: =SUM(X29:AA29) -> 38.124884 | AD29: 44621 | AE29: =B29+J29+Q29+X29 -> 508.14446 | AF29: =C29+K29+R29+Y29 -> 221.16107 | AG29: =D29+L29+S29+Z29 -> 2244.3933 | AH29: =E29+M29+T29+AA29 -> 440.68001 | AI29: =F29+N29+U29+AB29 -> 3414.3789 | AJ29: =SUM(AE29:AH29)-AI29 -> 0 | AL29: 22.3月累计 | AM29: =SUM(AE27:AE29) -> 1595.6004 | AN29: =SUM(AF27:AF29) -> 674.14874 | AO29: =SUM(AG27:AG29) -> 4750.3788 | AP29: =SUM(AH27:AH29) -> 988.24218 | AQ29: =SUM(AM29:AP29) -> 8008.37 | AS29: 22.3月累计 | AT29: =AM29/$AQ29 -> 0.19924159 | AU29: =AN29/$AQ29 -> 0.084180519 | AV29: =AO29/$AQ29 -> 0.59317673 | AW29: =AP29/$AQ29 -> 0.12340116 | AX29: =SUM(AT29:AW29) -> 1 | AZ29: 22.3月累计 | BA29: 1098.8515 | BB29: 674.14874 | BC29: 4006.097 | BD29: 1090.5756 | BE29: 6869.6728
A30: 44652 | B30: 483.34263 | C30: 235.77166 | D30: =1278.9378202401-11.900448*1.06 -> 1266.3233 | E30: 479.26413 | F30: =SUM(B30:E30) -> 2464.7018 | I30: 44652 | J30: 13.367994 | K30: 0 | L30: 225.45435 | M30: 6.0244697 | N30: =SUM(J30:M30) -> 244.84681 | P30: 44652 | Q30: 0.13202724 | R30: 0 | S30: 14.63615 | T30: -33.565074 | U30: =SUM(Q30:T30) -> -18.796896 | W30: 44652 | X30: 0.70618684 | Y30: 0 | Z30: 0 | AA30: 0.7369385 | AB30: =SUM(X30:AA30) -> 1.4431253 | AD30: 44652 | AE30: =B30+J30+Q30+X30 -> 497.54884 | AF30: =C30+K30+R30+Y30 -> 235.77166 | AG30: =D30+L30+S30+Z30 -> 1506.4138 | AH30: =E30+M30+T30+AA30 -> 452.46046 | AI30: =F30+N30+U30+AB30 -> 2692.1948 | AJ30: =SUM(AE30:AH30)-AI30 -> 0 | AL30: 22.4月累计 | AM30: =SUM(AE27:AE30) -> 2093.1492 | AN30: =SUM(AF27:AF30) -> 909.9204 | AO30: =SUM(AG27:AG30) -> 6256.7926 | AP30: =SUM(AH27:AH30) -> 1440.7026 | AQ30: =SUM(AM30:AP30) -> 10700.565 | AS30: 22.4月累计 | AT30: =AM30/$AQ30 -> 0.19561109 | AU30: =AN30/$AQ30 -> 0.085034801 | AV30: =AO30/$AQ30 -> 0.58471611 | AW30: =AP30/$AQ30 -> 0.134638 | AX30: =SUM(AT30:AW30) -> 1 | AZ30: 22.4月累计 | BA30: 1582.1941 | BB30: 909.9204 | BC30: 5272.4204 | BD30: 1569.8397 | BE30: 9334.3746
A31: 44682 | B31: 255.90417 | C31: 261.19858 | D31: =1781.82149948+208.222596*1.06 -> 2002.5375 | E31: -74.263538 | F31: =SUM(B31:E31) -> 2445.3767 | I31: 44682 | J31: -25.468793 | K31: 0 | L31: 146.70191 | M31: 15.15283 | N31: =SUM(J31:M31) -> 136.38595 | P31: 44682 | Q31: 0 | R31: 0 | S31: 46.690704 | T31: -40.045665 | U31: =SUM(Q31:T31) -> 6.6450393 | W31: 44682 | X31: 13.000614 | Y31: 0 | Z31: 0 | AA31: 8.083914 | AB31: =SUM(X31:AA31) -> 21.084528 | AD31: 44682 | AE31: =B31+J31+Q31+X31 -> 243.43599 | AF31: =C31+K31+R31+Y31 -> 261.19858 | AG31: =D31+L31+S31+Z31 -> 2195.9301 | AH31: =E31+M31+T31+AA31 -> -91.072458 | AI31: =F31+N31+U31+AB31 -> 2609.4922 | AJ31: =SUM(AE31:AH31)-AI31 -> 0 | AL31: 22.5月累计 | AM31: =SUM(AE$27:AE31) -> 2336.5852 | AN31: =SUM(AF$27:AF31) -> 1171.119 | AO31: =SUM(AG$27:AG31) -> 8452.7227 | AP31: =SUM(AH$27:AH31) -> 1349.6302 | AQ31: =SUM(AM31:AP31) -> 13310.057 | AS31: 22.5月累计 | AT31: =AM31/$AQ31 -> 0.17555035 | AU31: =AN31/$AQ31 -> 0.087987525 | AV31: =AO31/$AQ31 -> 0.63506284 | AW31: =AP31/$AQ31 -> 0.10139928 | AX31: =SUM(AT31:AW31) -> 1 | AZ31: 22.5月累计 | BA31: 1838.0983 | BB31: 1171.119 | BC31: 7274.9578 | BD31: 1495.5762 | BE31: 11779.751
A32: 44713 | B32: 461.15657 | C32: 318.10306 | D32: =2397.19591002-280.713167*1.06 -> 2099.64 | E32: 209.55085 | F32: =SUM(B32:E32) -> 3088.4504 | I32: 44713 | J32: =821.37546696-4002426.4402/10000 -> 421.13282 | K32: 0 | L32: 270.34051 | M32: 5.5147602 | N32: =SUM(J32:M32) -> 696.98809 | P32: 44713 | Q32: 0 | R32: 0 | S32: 11.429556 | T32: =-20.51372314-461458.76/10000 -> -66.659599 | U32: =SUM(Q32:T32) -> -55.230043 | W32: 44713 | X32: 6.6461067 | Y32: 0 | Z32: 0 | AA32: =144.16042612-1386687.6116/10000 -> 5.491665 | AB32: =SUM(X32:AA32) -> 12.137772 | AD32: 44713 | AE32: =B32+J32+Q32+X32 -> 888.9355 | AF32: =C32+K32+R32+Y32 -> 318.10306 | AG32: =D32+L32+S32+Z32 -> 2381.41 | AH32: =E32+M32+T32+AA32 -> 153.89767 | AI32: =F32+N32+U32+AB32 -> 3742.3463 | AJ32: =SUM(AE32:AH32)-AI32 -> 0 | AL32: 22.6月累计 | AM32: =SUM(AE$27:AE32) -> 3225.5207 | AN32: =SUM(AF$27:AF32) -> 1489.222 | AO32: =SUM(AG$27:AG32) -> 10834.133 | AP32: =SUM(AH$27:AH32) -> 1503.5279 | AQ32: =SUM(AM32:AP32) -> 17052.403 | AS32: 22.6月累计 | AT32: =AM32/$AQ32 -> 0.18915344 | AU32: =AN32/$AQ32 -> 0.087332092 | AV32: =AO32/$AQ32 -> 0.63534345 | AW32: =AP32/$AQ32 -> 0.088171024 | AX32: =SUM(AT32:AW32) -> 1 | AZ32: 22.6月累计 | BA32: 2299.2549 | BB32: 1489.222 | BC32: 9374.5978 | BD32: 1705.127 | BE32: 14868.202
A33: 44743 | B33: 357.68883 | C33: 328.75448 | D33: =1407.25765466+15.963167*1.06 -> 1424.1786 | E33: 431.43086 | F33: =SUM(B33:E33) -> 2542.0528 | I33: 44743 | J33: 323.63539 | K33: 0 | L33: 123.408 | M33: 22.723197 | N33: =SUM(J33:M33) -> 469.76658 | P33: 44743 | Q33: 0 | R33: 0 | S33: 49.488972 | T33: 56.668524 | U33: =SUM(Q33:T33) -> 106.1575 | W33: 44743 | X33: 13.248181 | Y33: 0 | Z33: -0.0342645 | AA33: 2.338784 | AB33: =SUM(X33:AA33) -> 15.552701 | AD33: 44743 | AE33: =B33+J33+Q33+X33 -> 694.5724 | AF33: =C33+K33+R33+Y33 -> 328.75448 | AG33: =D33+L33+S33+Z33 -> 1597.0413 | AH33: =E33+M33+T33+AA33 -> 513.16136 | AI33: =F33+N33+U33+AB33 -> 3133.5296 | AJ33: =SUM(AE33:AH33)-AI33 -> 0 | AL33: 22.7月累计 | AM33: =SUM(AE$27:AE33) -> 3920.0931 | AN33: =SUM(AF$27:AF33) -> 1817.9765 | AO33: =SUM(AG$27:AG33) -> 12431.174 | AP33: =SUM(AH$27:AH33) -> 2016.6892 | AQ33: =SUM(AM33:AP33) -> 20185.933 | AS33: 22.7月累计 | AT33: =AM33/$AQ33 -> 0.19419925 | AU33: =AN33/$AQ33 -> 0.090061556 | AV33: =AO33/$AQ33 -> 0.61583352 | AW33: =AP33/$AQ33 -> 0.099905674 | AX33: =SUM(AT33:AW33) -> 1 | AZ33: 22.7月累计 | BA33: 2656.9437 | BB33: 1817.9765 | BC33: 10798.776 | BD33: 2136.5579 | BE33: 17410.254
A34: 44774 | B34: 511.07195 | C34: 80.130754 | D34: =2412.31793416+302.64*1.06 -> 2733.1163 | E34: 1445.501 | F34: =SUM(B34:E34) -> 4769.82 | I34: 44774 | J34: =332.1508251-50.912318 -> 281.23851 | K34: 12 | L34: =213.8241646-55.804324 -> 158.01984 | M34: 7.9129541 | N34: =SUM(J34:M34) -> 459.1713 | P34: 44774 | Q34: 0 | R34: 0 | S34: 12.203367 | T34: 55.524902 | U34: =SUM(Q34:T34) -> 67.728269 | W34: 44774 | X34: =-153.87611582+109.402302+51.577694 -> 7.1038802 | Y34: 0 | Z34: =-197.06060592+196.948106 -> -0.11249992 | AA34: =72.84941796-65.12811296 -> 7.721305 | AB34: =SUM(X34:AA34) -> 14.712685 | AD34: 44774 | AE34: =B34+J34+Q34+X34 -> 799.41434 | AF34: =C34+K34+R34+Y34 -> 92.130754 | AG34: =D34+L34+S34+Z34 -> 2903.227 | AH34: =E34+M34+T34+AA34 -> 1516.6602 | AI34: =F34+N34+U34+AB34 -> 5311.4323 | AJ34: =SUM(AE34:AH34)-AI34 -> 0 | AL34: 22.8月累计 | AM34: =SUM(AE$27:AE34) -> 4719.5074 | AN34: =SUM(AF$27:AF34) -> 1910.1073 | AO34: =SUM(AG$27:AG34) -> 15334.401 | AP34: =SUM(AH$27:AH34) -> 3533.3494 | AQ34: =SUM(AM34:AP34) -> 25497.365 | AS34: 22.8月累计 | AT34: =AM34/$AQ34 -> 0.18509785 | AU34: =AN34/$AQ34 -> 0.074913908 | AV34: =AO34/$AQ34 -> 0.6014112 | AW34: =AP34/$AQ34 -> 0.13857704 | AX34: =SUM(AT34:AW34) -> 1 | AZ34: 22.8月累计 | BA34: 3168.0156 | BB34: 1898.1073 | BC34: 13531.893 | BD34: 3582.0589 | BE34: 22180.075
A35: 44805 | B35: 292.783 | C35: 391.08025 | D35: =1965.91679622-155.56*1.06 -> 1801.0232 | E35: 380.51313 | F35: =SUM(B35:E35) -> 2865.3996 | I35: 44805 | J35: 31.628182 | K35: 9.9663468 | L35: =130.84519584-15.262596 -> 115.5826 | M35: 3.2185925 | N35: =SUM(J35:M35) -> 160.39572 | P35: 44805 | Q35: 0 | R35: 0 | S35: -16.543812 | T35: 147.74788 | U35: =SUM(Q35:T35) -> 131.20407 | W35: 44805 | X35: 5.4964424 | Y35: -3 | Z35: -4.428062 | AA35: 9.4485591 | AB35: =SUM(X35:AA35) -> 7.5169395 | AD35: 44805 | AE35: =B35+J35+Q35+X35 -> 329.90762 | AF35: =C35+K35+R35+Y35 -> 398.04659 | AG35: =D35+L35+S35+Z35 -> 1895.6339 | AH35: =E35+M35+T35+AA35 -> 540.92816 | AI35: =F35+N35+U35+AB35 -> 3164.5163 | AJ35: =SUM(AE35:AH35)-AI35 -> 0 | AL35: 22.9月累计 | AM35: =SUM(AE$27:AE35) -> 5049.4151 | AN35: =SUM(AF$27:AF35) -> 2308.1539 | AO35: =SUM(AG$27:AG35) -> 17230.035 | AP35: =SUM(AH$27:AH35) -> 4074.2775 | AQ35: =SUM(AM35:AP35) -> 28661.881 | AS35: 22.9月累计 | AT35: =AM35/$AQ35 -> 0.17617179 | AU35: =AN35/$AQ35 -> 0.080530438 | AV35: =AO35/$AQ35 -> 0.60114808 | AW35: =AP35/$AQ35 -> 0.14214969 | AX35: =SUM(AT35:AW35) -> 1 | AZ35: 22.9月累计 | BA35: 3460.7986 | BB35: 2289.1875 | BC35: 15332.916 | BD35: 3962.572 | BE35: 25045.474
A36: 44835 | B36: 440.93172 | C36: 275.49147 | D36: =1522.96789702-99.33*1.06 -> 1417.6781 | E36: 706.14962 | F36: =SUM(B36:E36) -> 2840.2509 | I36: 44835 | J36: =374.78072956-3346001.91/10000 -> 40.180539 | K36: 9.2037351 | L36: =492.69261312-1201974.45/10000-54.48/10000 -> 372.48972 | M36: 9.7715135 | N36: =SUM(J36:M36) -> 431.64551 | P36: 44835 | Q36: 0 | R36: 0 | S36: -24.089556 | T36: 19.95907 | U36: =SUM(Q36:T36) -> -4.1304861 | W36: 44835 | X36: 5.6153945 | Y36: 0 | Z36: =-19.65784946+196578.49/10000 -> -4.6e-07 | AA36: =85.28447512-786236.3/10000 -> 6.6608451 | AB36: =SUM(X36:AA36) -> 12.276239 | AD36: 44835 | AE36: =B36+J36+Q36+X36 -> 486.72765 | AF36: =C36+K36+R36+Y36 -> 284.6952 | AG36: =D36+L36+S36+Z36 -> 1766.0783 | AH36: =E36+M36+T36+AA36 -> 742.54105 | AI36: =F36+N36+U36+AB36 -> 3280.0422 | AJ36: =SUM(AE36:AH36)-AI36 -> 0 | AL36: 22.10月累计 | AM36: =SUM(AE$27:AE36) -> 5536.1427 | AN36: =SUM(AF$27:AF36) -> 2592.8491 | AO36: =SUM(AG$27:AG36) -> 18996.113 | AP36: =SUM(AH$27:AH36) -> 4816.8186 | AQ36: =SUM(AM36:AP36) -> 31941.924 | AS36: 22.10月累计 | AT36: =AM36/$AQ36 -> 0.17331901 | AU36: =AN36/$AQ36 -> 0.081173855 | AV36: =AO36/$AQ36 -> 0.59470787 | AW36: =AP36/$AQ36 -> 0.15079926 | AX36: =SUM(AT36:AW36) -> 1 | AZ36: 22.10月累计 | BA36: 3901.7304 | BB36: 2564.679 | BC36: 16750.594 | BD36: 4668.7217 | BE36: 27885.725
A37: 44866 | B37: 564.82093 | C37: 247.67335 | D37: =2235.59010302+1551151.72*1.06/10000-166.06*1.06 -> 2223.9886 | E37: -77.440811 | F37: =SUM(B37:E37) -> 2959.0421 | I37: 44866 | J37: =-456.7482071+4817798.29*1.06/10000 -> 53.938412 | K37: 16.328455 | L37: =1871.99484962-1584219.13/10000-654996.22/10000-4817798.29*1.06/10000 -> 1137.3867 | M37: 9.2344942 | N37: =SUM(J37:M37) -> 1216.8881 | P37: 44866 | Q37: 0 | R37: 0 | S37: -9.5518667 | T37: 2.9561248 | U37: =SUM(Q37:T37) -> -6.5957419 | W37: 44866 | X37: =7.51957958+68942.33/10000 -> 14.413813 | Y37: 0 | Z37: -0.04880028 | AA37: 15.608001 | AB37: =SUM(X37:AA37) -> 29.973013 | AD37: 44866 | AE37: =B37+J37+Q37+X37 -> 633.17316 | AF37: =C37+K37+R37+Y37 -> 264.00181 | AG37: =D37+L37+S37+Z37 -> 3351.7746 | AH37: =E37+M37+T37+AA37 -> -49.642191 | AI37: =F37+N37+U37+AB37 -> 4199.3074 | AJ37: =SUM(AE37:AH37)-AI37 -> 0 | AL37: 22.11月累计 | AM37: =SUM(AE$27:AE37) -> 6169.3159 | AN37: =SUM(AF$27:AF37) -> 2856.8509 | AO37: =SUM(AG$27:AG37) -> 22347.888 | AP37: =SUM(AH$27:AH37) -> 4767.1764 | AQ37: =SUM(AM37:AP37) -> 36141.231 | AS37: 22.11月累计 | AT37: =AM37/$AQ37 -> 0.17070021 | AU37: =AN37/$AQ37 -> 0.079046861 | AV37: =AO37/$AQ37 -> 0.61834883 | AW37: =AP37/$AQ37 -> 0.1319041 | AX37: =SUM(AT37:AW37) -> 1 | AZ37: 22.11月累计 | BA37: 4466.5513 | BB37: 2812.3523 | BC37: 18974.583 | BD37: 4591.2808 | BE37: 30844.767
A38: 44896 | B38: 653.70418 | C38: 349.49868 | D38: =4991.5440916+184.5*1.06 -> 5187.1141 | E38: 703.90856 | F38: =SUM(B38:E38) -> 6894.2255 | I38: 44896 | J38: =296.25635462-194385.3/10000 -> 276.81782 | K38: 9.0396005 | L38: =394.10007226-1262440.96/10000 -> 267.85598 | M38: =-10.737429+194385.3/10000 -> 8.701101 | N38: =SUM(J38:M38) -> 562.4145 | P38: 44896 | Q38: 0 | R38: 0 | S38: 0.17901068 | T38: 17.199883 | U38: =SUM(Q38:T38) -> 17.378894 | W38: 44896 | X38: =146.27517276-1462653.77/10000 -> 0.00979576 | Y38: 0 | Z38: =-801.46041486+7727106.553/10000 -> -28.74976 | AA38: =-47.38925146-189966.92/10000 -> -66.385943 | AB38: =SUM(X38:AA38) -> -95.125907 | AD38: 44896 | AE38: =B38+J38+Q38+X38 -> 930.5318 | AF38: =C38+K38+R38+Y38 -> 358.53828 | AG38: =D38+L38+S38+Z38 -> 5426.3993 | AH38: =E38+M38+T38+AA38 -> 663.4236 | AI38: =F38+N38+U38+AB38 -> 7378.893 | AJ38: =SUM(AE38:AH38)-AI38 -> 0 | AL38: 22.12月累计 | AM38: =SUM(AE$27:AE38) -> 7099.8477 | AN38: =SUM(AF$27:AF38) -> 3215.3892 | AO38: =SUM(AG$27:AG38) -> 27774.287 | AP38: =SUM(AH$27:AH38) -> 5430.6 | AQ38: =SUM(AM38:AP38) -> 43520.124 | AS38: 22.12月累计 | AT38: =AM38/$AQ38 -> 0.16313942 | AU38: =AN38/$AQ38 -> 0.073882812 | AV38: =AO38/$AQ38 -> 0.63819412 | AW38: =AP38/$AQ38 -> 0.12478365 | AX38: =SUM(AT38:AW38) -> 1 | AZ38: 22.12月累计 | BA38: 5120.2555 | BB38: 3161.851 | BC38: 24161.697 | BD38: 5295.1894 | BE38: 37738.993
A39: 44927 | B39: 817.4072 | C39: 88.942809 | D39: =2153.97856182+投资公司!D26*1.06 -> 2258.7733 | E39: 563.54075 | F39: =SUM(B39:E39) -> 3728.6641 | I39: 44927 | J39: 327.65234 | K39: 12.262499 | L39: 268.21922 | M39: 7.1585542 | N39: =SUM(J39:M39) -> 615.29261 | P39: 44927 | Q39: 14.832 | R39: 0 | S39: 0.03200034 | T39: -25.598343 | U39: =SUM(Q39:T39) -> -10.734342 | W39: 44927 | X39: 0.20580324 | Y39: 0 | Z39: 0 | AA39: 9.8552493 | AB39: =SUM(X39:AA39) -> 10.061053 | AD39: 44927 | AE39: =B39+J39+Q39+X39 -> 1160.0973 | AF39: =C39+K39+R39+Y39 -> 101.20531 | AG39: =D39+L39+S39+Z39 -> 2527.0246 | AH39: =E39+M39+T39+AA39 -> 554.95621 | AI39: =F39+N39+U39+AB39 -> 4343.2834 | AJ39: =SUM(AE39:AH39)-AI39 -> 0 | AL39: 23.1月累计 | AM39: =SUM(AE$39:AE39) -> 1160.0973 | AN39: =SUM(AF$39:AF39) -> 101.20531 | AO39: =SUM(AG$39:AG39) -> 2527.0246 | AP39: =SUM(AH$39:AH39) -> 554.95621 | AQ39: =SUM(AM39:AP39) -> 4343.2834 | AS39: 23.1月累计 | AT39: =AM39/$AQ39 -> 0.26710146 | AU39: =AN39/$AQ39 -> 0.023301566 | AV39: =AO39/$AQ39 -> 0.58182355 | AW39: =AP39/$AQ39 -> 0.12777343 | AX39: =SUM(AT39:AW39) -> 1 | AZ39: 23.1月累计 | BA39: 817.4072 | BB39: 88.942809 | BC39: 2258.7733 | BD39: 563.54075 | BE39: 3728.6641
A40: 44958 | B40: 307.96654 | C40: 53.569763 | D40: =1701.70774596+投资公司!E26*1.06 -> 1795.2697 | E40: 723.25259 | F40: =SUM(B40:E40) -> 2880.0586 | I40: 44958 | J40: 30.652414 | K40: 7.3825004 | L40: =234.45925138-473567.99/10000 -> 187.10245 | M40: =7.95893474 -> 7.9589347 | N40: =SUM(J40:M40) -> 233.0963 | P40: 44958 | Q40: 33.5 | R40: 0 | S40: 0.0391882 | T40: -25.669839 | U40: =SUM(Q40:T40) -> 7.8693499 | W40: 44958 | X40: 0.22532738 | Y40: 0 | Z40: 0 | AA40: 2.7152769 | AB40: =SUM(X40:AA40) -> 2.9406043 | AD40: 44958 | AE40: =B40+J40+Q40+X40 -> 372.34428 | AF40: =C40+K40+R40+Y40 -> 60.952263 | AG40: =D40+L40+S40+Z40 -> 1982.4113 | AH40: =E40+M40+T40+AA40 -> 708.25697 | AI40: =F40+N40+U40+AB40 -> 3123.9649 | AJ40: =SUM(AE40:AH40)-AI40 -> 0 | AL40: 23.2月累计 | AM40: =SUM(AE$39:AE40) -> 1532.4416 | AN40: =SUM(AF$39:AF40) -> 162.15757 | AO40: =SUM(AG$39:AG40) -> 4509.4359 | AP40: =SUM(AH$39:AH40) -> 1263.2132 | AQ40: =SUM(AM40:AP40) -> 7467.2483 | AS40: 23.2月累计 | AT40: =AM40/$AQ40 -> 0.20522173 | AU40: =AN40/$AQ40 -> 0.02171584 | AV40: =AO40/$AQ40 -> 0.60389527 | AW40: =AP40/$AQ40 -> 0.16916716 | AX40: =SUM(AT40:AW40) -> 1 | AZ40: 23.2月累计 | BA40: 1125.3737 | BB40: 142.51257 | BC40: 4054.043 | BD40: 1286.7933 | BE40: 6608.7227
