Workbook
Name body: '[1]资产负债表-2017'!$C$6:$H$36
Name grid: '[1]资产负债表-2017'!$C$6:$H$36
Name head: '[1]资产负债表-2017'!$A$4:$H$4
Name 合并科目名称: [2]Sheet1!$A$2:$A$908
Name 核算项目明细账: [3]核算项目明细账!$A$1:$K$157
Name 会计分录序时簿: #REF!
Name 科目余额表: #REF!
Name 明细分类账: #REF!
Name 会计分录序时簿: #REF!
Name 科目余额表: #REF!
Name 明细分类账: #REF!
Name 会计分录序时簿: #REF!
Name 科目余额表: #REF!
Name 明细分类账: #REF!
Name body: '[4]资产负债表-2017'!$C$6:$H$36
Name grid: '[4]资产负债表-2017'!$C$6:$H$36
Name head: '[4]资产负债表-2017'!$A$4:$H$4
Name 合并科目名称: [5]Sheet1!$A$2:$A$908
Name 核算项目明细账: [6]核算项目明细账!$A$1:$K$157
Name 会计分录序时簿: #REF!
Name 科目余额表: #REF!
Name 明细分类账: #REF!
Name body: '[4]资产负债表-2017'!$C$6:$H$36
Name grid: '[4]资产负债表-2017'!$C$6:$H$36
Name head: '[4]资产负债表-2017'!$A$4:$H$4
Name 合并科目名称: [5]Sheet1!$A$2:$A$908
Name 核算项目明细账: [6]核算项目明细账!$A$1:$K$157
Name 会计分录序时簿: #REF!
Name 科目余额表: #REF!
Name 明细分类账: #REF!
Name body: '[4]资产负债表-2017'!$C$6:$H$36
Name grid: '[4]资产负债表-2017'!$C$6:$H$36
Name head: '[4]资产负债表-2017'!$A$4:$H$4
Name 合并科目名称: [5]Sheet1!$A$2:$A$908
Name 核算项目明细账: [6]核算项目明细账!$A$1:$K$157
Name 会计分录序时簿: #REF!
Name 科目余额表: #REF!
Name 明细分类账: #REF!
Name \555: [10]表三甲!#REF!
Name \a: [10]表三甲!#REF!
Name \b: #REF!
Name \bbb: #REF!
Name \E: #REF!
Name \k: [11]土建表三乙!#REF!
Name \kkk: [10]表三甲!#REF!
Name \m: #REF!
Name \o: [10]表三甲!#REF!
Name \p: [10]表三甲!#REF!
Name \q: [10]表三甲!#REF!
Name \r: [10]表三甲!#REF!
Name \x: [10]表三甲!#REF!
Name \xx: [10]表三甲!#REF!
Name \z: [10]表三甲!#REF!
Name \zz: [10]表三甲!#REF!
Name _: #REF!
Name _0.dbf: #REF!
Name _000.03.dbf: #REF!
Name _00103应收货款余额表.dbf: #REF!
Name _0月31日: #REF!
Name _1: #REF!

Sheet 范围确认
A1: 1、涉及业务线 | B1: 游戏电商、渠道线、业务发展
A2: 2、涉及年限 | B2: 2020年1-22年
A3: 3、5月13号提供数据
A4: 4、单位：万元

Sheet GMV-战略需求
A1: 规模
A2: 结构 | B2: 品类
B3: 品牌
A5: 1、21年-22年商品大类增长波动 | J5: 年份 | K5: 游戏 | L5: 通信 | M5: 网娱 | N5: 网娱 | O5: 合计
J6: 43831
J7: 43862
J8: 43891
J9: 43922
J10: 43952
J11: 43983
J12: 44013
J13: 44044
J14: 44075
J15: 44105
J16: 44136
J17: 44166
... J23: 44348
A24: 2、21年-22年网娱、生活服务增长波动 | J24: 44378
J25: 44409
J26: 44440
J27: 44470
J28: 44501
J29: 44531
J30: 44562
J31: 44593
J32: 44621
J33: 44652
J34: 44682
J35: 44713
J36: 44743
... J40: 44866
A43: 3、品牌趋势波动，是否针对网娱、生活服务--22年数据波动做分析
A44: 网娱品牌 | B44: 影视会员、音频、视频直播、知识阅读
A45: 生活服务 | B45: 加油卡、网络工具、出行生活、餐饮、购物（优惠劵）、其他

Sheet 毛利-战略需求
A1: 1、收入构成 | B1: 代理 | C1: 虚拟商品采销差额收入+返点 | D1: 分商品大类-20年-22年
B2: 增值代运营 | C2: 代运营收入 | D2: 分商品大类-需要提供21年GMV
B3: 推广收入 | D3: 分商品大类-需要提供21年GMV
A8: 2、品类毛利21年-22年 | B8: 依赖第一条数据提供商品大类可以出
A18: 3、四大品类毛利/gmv
A25: 4、成长性品牌的毛利分析
A26: 生活服务
A27: 网娱
A30: 5、供应商毛利波动（前10）

Sheet 上市公司经营概况
A1: 体系内公司经营概况整体变化情况
A2: 单位：万元
A3: 项目 | B3: 2022年1-6月体系内公司经营概况 | C3: 2021年1-6月体系内公司经营概况 | D3: 2020年1-6月体系内公司经营概况 | E3: 增长总数对比额
E4: 累计增长额 | F4: 增长比率
A5: 集团GMV | B5: ='GMV表-商品大类'!T35 -> 722480.29 | C5: ='GMV表-商品大类'!T23 -> 997949.58 | D5: ='GMV表-商品大类'!T11 -> 753470.03 | E5: =B5-C5 -> -275469.29 | F5: =E5/C5 -> -0.27603528
A6: 毛利收入（含税） | B6: =SUM('毛利-收入组成'!AH27:AH32) -> 17052.403 | C6: =SUM('毛利-收入组成'!AH15:AH20) -> 21665.327 | D6: =SUM('毛利-收入组成'!AH3:AH8) -> 17359.563 | E6: =B6-C6 -> -4612.9233 | F6: =E6/C6 -> -0.21291732
A7: 净利润（核算报表) | B7: ='[9]财务报表--EAS（原表）'!$S$53/10000+投资公司!C19 -> #REF! | C7: ='[9]财务报表--EAS（原表）'!$G$53/10000 -> #REF! | D7: =[8]经营概况整体变化情况!$C$7 -> #REF! | E7: =B7-C7 -> #REF! | F7: =E7/C7 -> #REF!
A8: 净利润（审计口径) | B8: =B7-(-12881461.65/10000) -> #REF! | C8: ='[9]权责制经营报表-EAS 2206（审计口径）'!$H$48/10000-766.444582 -> #REF! | D8: =[8]经营概况整体变化情况!$C$8 -> #REF! | E8: =B8-C8 -> #REF! | F8: =E8/C8 -> #REF! | G8: 合并报表-跨期返点收入+审计补计提在21年费用
A9: 净利润（扣非) | B9: =B8+'[9]权责制经营报表-EAS 2206（审计口径）'!$T$53/10000 -> #REF! | C9: =C8+'[9]权责制经营报表-EAS 2206（审计口径）'!$H$53/10000+'[9]权责制经营报表-EAS 2206（审计口径）'!$H$54/10000 -> #REF! | D9: =[8]经营概况整体变化情况!$C$9 -> #REF! | E9: =B9-C9 -> #REF! | F9: =E9/C9 -> #REF! | G9: 合并报表-跨期返点收入+调整IPO费用+调整汇兑损益+权益股份
A10: 留存率 | B10: =B6/B5 -> 0.023602586 | C10: =C6/C5 -> 0.021709841 | D10: =D6/D5 -> 0.023039487
A11: 利润率 | B11: =B8*1.06/B6 -> #REF! | C11: =C8*1.06/C6 -> #REF! | D11: =D8*1.06/D6 -> #REF!
B13: =B8-B9 -> #REF! | C13: =C8-C9 -> #REF! | D13: =E6-[7]成本费用分布!$AA$16 -> #REF!
A17: 调整项： | B17: 1、体内扣非、不扣给，都要调整采购返点未实现部分
B18: 2、体外岚晨，公会费用按总额法核算，同时调整收入和费用
A21: 项目 | B21: 管理报表数 | C21: 净利润（审计口径） | D21: 净利润（扣非）
A22: 2022年1-6月 | B22: =B7 -> #REF! | C22: =B8 -> #REF! | D22: =B9 -> #REF! | E22: =D22-B9 -> #REF!
A23: 2021年1-6月 | B23: =C7 -> #REF! | C23: =C8 -> #REF! | D23: =C9 -> #REF!
A24: 变动值 | B24: =B22-B23 -> #REF! | C24: =C22-C23 -> #REF! | D24: =D22-D23 -> #REF!
A25: 增长率 | B25: =B24/B23 -> #REF! | C25: =C24/C23 -> #REF! | D25: =D24/D23 -> #REF!

Sheet 利润调整

Sheet 利润组成
A1: GMV | F1: 毛利收入（含税） | P1: 净利润 | AB1: 毛利率 | AG1: 净利润率 | AL1: 当月净利润
A2: 月份累计 | B2: 上市公司 | C2: 投资公司 | D2: 小计 | F2: 月份累计 | G2: 上市公司 | H2: 佣金手续费（元）（账面不含税金额） | I2: 佣金手续费（含税） | J2: 体内项目-葫芦藤延伸公司 | K2: 跨期返利(含税） | L2: 上市公司-扣除佣金手续费后、调整跨期返利后毛利收入 | M2: 投资公司 | N2: 集团小计 | P2: 月份累计 | Q2: 上市公司（审计口径） | R2: 跨期返利 | S2: 体内项目-葫芦藤延伸公司 | T2: H1项目分红 | U2: H1导师分红 | V2: 上市公司调整后净利润小计 | W2: 投资公司调整前 | X2: H1项目分红 | Y2: H1导师分红 | Z2: 集团小计 | AB2: 月份 | AC2: 上市公司（审计口径） | AD2: 投资公司 | AE2: 集团小计 | AG2: 月份 | AH2: 上市公司（审计口径） | AI2: 投资公司 | AJ2: 小计 | AL2: 月份 | AM2: 上市公司当月利润（核算）（元） | AN2: 调整跨期返利收入（元） | AO2: 调整投资公司(万元）
A3: 43831 | B3: 108855.57 | C3: 0 | D3: =B3+C3 -> 108855.57 | F3: 43831 | G3: ='毛利-收入组成'!AP3 -> 3005.5532 | H3: 2267566.2 | I3: =H3*1.06/10000 -> 240.36202 | L3: =G3-I3+J3-K3 -> 2765.1912 | M3: 0 | N3: =L3+M3 -> 2765.1912 | P3: 43831 | Q3: 1461.1357 | V3: =Q3-R3+S3 -> 1461.1357 | W3: 0 | Z3: =V3+W3 -> 1461.1357 | AB3: 43831 | AC3: =L3/B3 -> 0.025402387 | AD3: =M3/C3 -> #DIV/0! | AE3: =N3/D3 -> 0.025402387 | AG3: 43831 | AH3: =V3*1.06/L3 -> 0.56010732 | AI3: =W3*1.06/M3 -> #DIV/0! | AJ3: =Z3*1.06/N3 -> 0.56010732 | AL3: 43831
A4: 43862 | B4: 234834.11 | C4: 0 | D4: =B4+C4 -> 234834.11 | F4: 43862 | G4: ='毛利-收入组成'!AP4 -> 5626.0416 | H4: 4138698.7 | I4: =H4*1.06/10000 -> 438.70206 | L4: =G4-I4+J4-K4 -> 5187.3395 | M4: 0 | N4: =L4+M4 -> 5187.3395 | P4: 43862 | Q4: 2772.2185 | V4: =Q4-R4+S4 -> 2772.2185 | W4: 0 | Z4: =V4+W4 -> 2772.2185 | AB4: 43862 | AC4: =L4/B4 -> 0.022089379 | AD4: =M4/C4 -> #DIV/0! | AE4: =N4/D4 -> 0.022089379 | AG4: 43862 | AH4: =V4*1.06/L4 -> 0.56648529 | AI4: =W4*1.06/M4 -> #DIV/0! | AJ4: =Z4*1.06/N4 -> 0.56648529 | AL4: 43862
A5: 43891 | B5: 371037.83 | C5: 0 | D5: =B5+C5 -> 371037.83 | F5: 43891 | G5: ='毛利-收入组成'!AP5 -> 9302.7749 | H5: 7022628.5 | I5: =H5*1.06/10000 -> 744.39862 | L5: =G5-I5+J5-K5 -> 8558.3762 | M5: 0 | N5: =L5+M5 -> 8558.3762 | P5: 43891 | Q5: 4900.3466 | V5: =Q5-R5+S5 -> 4900.3466 | W5: 0 | Z5: =V5+W5 -> 4900.3466 | AB5: 43891 | AC5: =L5/B5 -> 0.023066048 | AD5: =M5/C5 -> #DIV/0! | AE5: =N5/D5 -> 0.023066048 | AG5: 43891 | AH5: =V5*1.06/L5 -> 0.60693376 | AI5: =W5*1.06/M5 -> #DIV/0! | AJ5: =Z5*1.06/N5 -> 0.60693376 | AL5: 43891
A6: 43922 | B6: 499627.82 | C6: 1683.13 | D6: =B6+C6 -> 501310.95 | F6: 43922 | G6: ='毛利-收入组成'!AP6 -> 11563.258 | H6: 9398075.9 | I6: =H6*1.06/10000 -> 996.19605 | L6: =G6-I6+J6-K6 -> 10567.062 | M6: 985.5668 | N6: =L6+M6 -> 11552.628 | P6: 43922 | Q6: 5201.3962 | R6: -12.490192 | V6: =Q6-R6+S6 -> 5213.8864 | W6: 152.41 | Z6: =V6+W6 -> 5366.2964 | AB6: 43922 | AC6: =L6/B6 -> 0.021149866 | AD6: =M6/C6 -> 0.58555596 | AE6: =N6/D6 -> 0.023044835 | AG6: 43922 | AH6: =V6*1.06/L6 -> 0.52301386 | AI6: =W6*1.06/M6 -> 0.1639205 | AJ6: =Z6*1.06/N6 -> 0.49237923 | AL6: 43922
A7: 43952 | B7: 620327.46 | C7: 2274.839 | D7: =B7+C7 -> 622602.3 | F7: 43952 | G7: ='毛利-收入组成'!AP7 -> 14361.51 | H7: 12574211 | I7: =H7*1.06/10000 -> 1332.8664 | L7: =G7-I7+J7-K7 -> 13028.643 | M7: 1307.1454 | N7: =L7+M7 -> 14335.789 | P7: 43952 | Q7: 5946.4111 | R7: 262.44255 | V7: =Q7-R7+S7 -> 5683.9685 | W7: 263.82746 | Z7: =V7+W7 -> 5947.796 | AB7: 43952 | AC7: =L7/B7 -> 0.021002848 | AD7: =M7/C7 -> 0.57461004 | AE7: =N7/D7 -> 0.023025595 | AG7: 43952 | AH7: =V7*1.06/L7 -> 0.46244313 | AI7: =W7*1.06/M7 -> 0.21394492 | AJ7: =Z7*1.06/N7 -> 0.43978493 | AL7: 43952
A8: 43983 | B8: 753470.03 | C8: 2614.3009 | D8: =B8+C8 -> 756084.33 | F8: 43983 | G8: ='毛利-收入组成'!AP8 -> 17359.563 | H8: 16502507 | I8: =H8*1.06/10000 -> 1749.2657 | L8: =G8-I8+J8-K8 -> 15610.297 | M8: 1553.5218 | N8: =L8+M8 -> 17163.819 | P8: 43983 | Q8: =V8+R8 -> 7553.8477 | R8: 431.57644 | V8: =71222712.99/10000 -> 7122.2713 | W8: 299.95646 | Z8: =V8+W8 -> 7422.2278 | AB8: 43983 | AC8: =L8/B8 -> 0.020717874 | AD8: =M8/C8 -> 0.59423986 | AE8: =N8/D8 -> 0.022700932 | AG8: 43983 | AH8: =V8*1.06/L8 -> 0.48362996 | AI8: =W8*1.06/M8 -> 0.20466648 | AJ8: =Z8*1.06/N8 -> 0.45838058 | AL8: 43983
A9: 44013 | B9: 861281.71 | C9: 3169.0978 | D9: =B9+C9 -> 864450.8 | F9: 44013 | G9: ='毛利-收入组成'!AP9 -> 19620.865 | H9: 20753792 | I9: =H9*1.06/10000 -> 2199.902 | L9: =G9-I9+J9-K9 -> 17420.964 | M9: 1894.8863 | N9: =L9+M9 -> 19315.85 | P9: 44013 | Q9: 7363.7605 | R9: 150.29162 | V9: =Q9-R9+S9 -> 7213.4688 | W9: 392.87593 | Z9: =V9+W9 -> 7606.3448 | AB9: 44013 | AC9: =L9/B9 -> 0.020226789 | AD9: =M9/C9 -> 0.5979261 | AE9: =N9/D9 -> 0.022344649 | AG9: 44013 | AH9: =V9*1.06/L9 -> 0.4389124 | AI9: =W9*1.06/M9 -> 0.21977492 | AJ9: =Z9*1.06/N9 -> 0.417415 | AL9: 44013
A10: 44044 | B10: 963744.17 | C10: 3907.6229 | D10: =B10+C10 -> 967651.79 | F10: 44044 | G10: ='毛利-收入组成'!AP10 -> 22608.732 | H10: 24741203 | I10: =H10*1.06/10000 -> 2622.5675 | L10: =G10-I10+J10-K10 -> 19986.165 | M10: 2452.8894 | N10: =L10+M10 -> 22439.054 | P10: 44044 | Q10: 8315.3341 | R10: 149.08987 | V10: =Q10-R10+S10 -> 8166.2442 | W10: 655.03143 | Z10: =V10+W10 -> 8821.2757 | AB10: 44044 | AC10: =L10/B10 -> 0.02073804 | AD10: =M10/C10 -> 0.62771906 | AE10: =N10/D10 -> 0.023189183 | AG10: 44044 | AH10: =V10*1.06/L10 -> 0.43311055 | AI10: =W10*1.06/M10 -> 0.28306752 | AJ10: =Z10*1.06/N10 -> 0.41670884 | AL10: 44044
A11: 44075 | B11: 1071698.6 | C11: 4482.1392 | D11: =B11+C11 -> 1076180.7 | F11: 44075 | G11: ='毛利-收入组成'!AP11 -> 25599.175 | H11: 28841287 | I11: =H11*1.06/10000 -> 3057.1764 | L11: =G11-I11+J11-K11 -> 22541.998 | M11: 2887.029 | N11: =L11+M11 -> 25429.028 | P11: 44075 | Q11: 8938.9383 | R11: 197.12663 | V11: =Q11-R11+S11 -> 8741.8117 | W11: 570.89724 | Z11: =V11+W11 -> 9312.7089 | AB11: 44075 | AC11: =L11/B11 -> 0.021033898 | AD11: =M11/C11 -> 0.64411856 | AE11: =N11/D11 -> 0.023628957 | AG11: 44075 | AH11: =V11*1.06/L11 -> 0.41106916 | AI11: =W11*1.06/M11 -> 0.20961032 | AJ11: =Z11*1.06/N11 -> 0.38819697 | AL11: 44075
A12: 44105 | B12: 1192298.3 | C12: 5181.8237 | D12: =B12+C12 -> 1197480.1 | F12: 44105 | G12: ='毛利-收入组成'!AP12 -> 27955.57 | H12: 32592117 | I12: =H12*1.06/10000 -> 3454.7644 | L12: =G12-I12+J12-K12 -> 24500.805 | M12: 3471.1219 | N12: =L12+M12 -> 27971.927 | P12: 44105 | Q12: 9119.9746 | R12: 451.08295 | V12: =Q12-R12+S12 -> 8668.8917 | W12: 581.18029 | Z12: =V12+W12 -> 9250.072 | AB12: 44105 | AC12: =L12/B12 -> 0.020549225 | AD12: =M12/C12 -> 0.66986492 | AE12: =N12/D12 -> 0.023358991 | AG12: 44105 | AH12: =V12*1.06/L12 -> 0.37504992 | AI12: =W12*1.06/M12 -> 0.17747896 | AJ12: =Z12*1.06/N12 -> 0.35053274 | AL12: 44105
A13: 44136 | B13: 1323765.4 | C13: 5964.1379 | D13: =B13+C13 -> 1329729.5 | F13: 44136 | G13: ='毛利-收入组成'!AP13 -> 32152.429 | H13: 37425284 | I13: =H13*1.06/10000 -> 3967.0801 | L13: =G13-I13+J13-K13 -> 28185.349 | M13: 4022.961 | N13: =L13+M13 -> 32208.31 | P13: 44136 | Q13: 10096.153 | R13: 435.37173 | V13: =Q13-R13+S13 -> 9660.7811 | W13: 167.55656 | Z13: =V13+W13 -> 9828.3377 | AB13: 44136 | AC13: =L13/B13 -> 0.021291802 | AD13: =M13/C13 -> 0.67452514 | AE13: =N13/D13 -> 0.024221701 | AG13: 44136 | AH13: =V13*1.06/L13 -> 0.3633245 | AI13: =W13*1.06/M13 -> 0.044149061 | AJ13: =Z13*1.06/N13 -> 0.32345807 | AL13: 44136
A14: 44166 | B14: 1457884 | C14: 5878.4142 | D14: =B14+C14 -> 1463762.4 | F14: 44166 | G14: ='毛利-收入组成'!AP14 -> 36994.551 | H14: 42520356 | I14: =H14*1.06/10000 -> 4507.1578 | L14: =G14-I14+J14-K14 -> 32487.394 | M14: 4489.3097 | N14: =L14+M14 -> 36976.703 | P14: 44166 | Q14: 11872.702 | R14: 1082.9923 | V14: =Q14-R14+S14 -> 10789.71 | W14: -288.12588 | Z14: =V14+W14 -> 10501.584 | AB14: 44166 | AC14: =L14/B14 -> 0.022283936 | AD14: =M14/C14 -> 0.76369401 | AE14: =N14/D14 -> 0.025261411 | AG14: 44166 | AH14: =V14*1.06/L14 -> 0.35204708 | AI14: =W14*1.06/M14 -> -0.06803127 | AJ14: =Z14*1.06/N14 -> 0.30104573 | AL14: 44166
A15: 44197 | B15: 126572.29 | C15: 1250.12 | D15: =B15+C15 -> 127822.41 | F15: 44197 | G15: ='毛利-收入组成'!AP15 -> 3267.6274 | H15: 4151308 | I15: =H15*1.06/10000 -> 440.03865 | L15: =G15-I15+J15-K15 -> 2827.5887 | M15: 631.95525 | N15: =L15+M15 -> 3459.544 | P15: 44197 | Q15: 1259.6255 | R15: =2059085.54115382/10000 -> 205.90855 | V15: =Q15-R15+S15 -> 1053.717 | W15: -170.35 | Z15: =V15+W15 -> 883.36699 | AB15: 44197 | AC15: =L15/B15 -> 0.022339713 | AD15: =M15/C15 -> 0.50551567 | AE15: =N15/D15 -> 0.027065237 | AG15: 44197 | AH15: =V15*1.06/L15 -> 0.39501501 | AI15: =W15*1.06/M15 -> -0.28573384 | AJ15: =Z15*1.06/N15 -> 0.27066255 | AL15: 44197
A16: 44228 | B16: 253086.25 | C16: 2870.11 | D16: =B16+C16 -> 255956.36 | F16: 44228 | G16: ='毛利-收入组成'!AP16 -> 6453.35 | H16: 8209257.9 | I16: =H16*1.06/10000 -> 870.18133 | L16: =G16-I16+J16-K16 -> 5583.1687 | M16: 1530.8654 | N16: =L16+M16 -> 7114.0341 | P16: 44228 | Q16: 2643.0176 | R16: =2059085.54115382/10000+5981296.97843144/10000 -> 804.03825 | V16: =Q16-R16+S16 -> 1838.9794 | W16: -210.67 | Z16: =V16+W16 -> 1628.3094 | AB16: 44228 | AC16: =L16/B16 -> 0.02206034 | AD16: =M16/C16 -> 0.53338214 | AE16: =N16/D16 -> 0.027793934 | AG16: 44228 | AH16: =V16*1.06/L16 -> 0.3491419 | AI16: =W16*1.06/M16 -> -0.14587187 | AJ16: =Z16*1.06/N16 -> 0.24262014 | AL16: 44228
A17: 44256 | B17: 420256.07 | C17: 3989.14 | D17: =B17+C17 -> 424245.21 | F17: 44256 | G17: ='毛利-收入组成'!AP17 -> 11169.797 | H17: 12929115 | I17: =H17*1.06/10000 -> 1370.4861 | L17: =G17-I17+J17-K17 -> 9799.3112 | M17: 2212.245 | N17: =L17+M17 -> 12011.556 | P17: 44256 | Q17: 5626.5008 | R17: 1056.3554 | V17: =Q17-R17+S17 -> 4570.1454 | W17: -440.97 | Z17: =V17+W17 -> 4129.1754 | AB17: 44256 | AC17: =L17/B17 -> 0.023317477 | AD17: =M17/C17 -> 0.5545669 | AE17: =N17/D17 -> 0.028312768 | AG17: 44256 | AH17: =V17*1.06/L17 -> 0.49435659 | AI17: =W17*1.06/M17 -> -0.21129134 | AJ17: =Z17*1.06/N17 -> 0.36439291 | AL17: 44256
A18: 44287 | B18: 576778.07 | C18: 5126.1593 | D18: =B18+C18 -> 581904.23 | F18: 44287 | G18: ='毛利-收入组成'!AP18 -> 13446.163 | H18: 17509484 | I18: =H18*1.06/10000 -> 1856.0053 | L18: =G18-I18+J18-K18 -> 11590.157 | M18: 2770.0335 | N18: =L18+M18 -> 14360.191 | P18: 44287 | Q18: 5424.4488 | R18: 922.42937 | V18: =Q18-R18+S18 -> 4502.0194 | W18: -1136.0004 | Z18: =V18+W18 -> 3366.019 | AB18: 44287 | AC18: =L18/B18 -> 0.020094657 | AD18: =M18/C18 -> 0.5403721 | AE18: =N18/D18 -> 0.024677928 | AG18: 44287 | AH18: =V18*1.06/L18 -> 0.4117408 | AI18: =W18*1.06/M18 -> -0.43470972 | AJ18: =Z18*1.06/N18 -> 0.24846328 | AL18: 44287
A19: 44317 | B19: 771135.94 | C19: 5636.3654 | D19: =B19+C19 -> 776772.31 | F19: 44317 | G19: ='毛利-收入组成'!AP19 -> 16651.896 | H19: 22355194 | I19: =H19*1.06/10000 -> 2369.6505 | L19: =G19-I19+J19-K19 -> 14282.245 | M19: 3359.428 | N19: =L19+M19 -> 17641.673 | P19: 44317 | Q19: 5772.8294 | R19: 593.88748 | V19: =Q19-R19+S19 -> 5178.9419 | W19: -1642.0427 | Z19: =V19+W19 -> 3536.8992 | AB19: 44317 | AC19: =L19/B19 -> 0.018521047 | AD19: =M19/C19 -> 0.59602737 | AE19: =N19/D19 -> 0.022711511 | AG19: 44317 | AH19: =V19*1.06/L19 -> 0.38437083 | AI19: =W19*1.06/M19 -> -0.51811358 | AJ19: =Z19*1.06/N19 -> 0.2125146 | AL19: 44317
A20: 44348 | B20: 997949.58 | C20: 8217.612 | D20: =B20+C20 -> 1006167.2 | F20: 44348 | G20: ='毛利-收入组成'!AP20 -> 21665.327 | H20: 27674170 | I20: =H20*1.06/10000 -> 2933.4621 | L20: =G20-I20+J20-K20 -> 18731.865 | M20: 3775.6411 | N20: =L20+M20 -> 22507.506 | P20: 44348 | Q20: =V20+R20 -> 7603.2288 | R20: =3569650.9/10000 -> 356.96509 | V20: =Q20-R20+S20 -> 0 | W20: -2396.6821 | Z20: =V20+W20 -> 4849.5816 | AB20: 44348 | AC20: =L20/B20 -> 0.018770352 | AD20: =M20/C20 -> 0.45945721 | AE20: =N20/D20 -> 0.022369548 | AG20: 44348 | AH20: =V20*1.06/L20 -> 0.41005205 | AI20: =W20*1.06/M20 -> -0.67286138 | AJ20: =Z20*1.06/N20 -> 0.22839299 | AL20: 44348
A21: 44378 | B21: 1218182.5 | C21: 12572.54 | D21: =B21+C21 -> 1230755 | F21: 44378 | G21: ='毛利-收入组成'!AP21 -> 24096.859 | H21: 33458555 | I21: =H21*1.06/10000 -> 3546.6069 | L21: =G21-I21+J21-K21 -> 20550.252 | M21: 4601.6992 | N21: =L21+M21 -> 25151.951 | P21: 44378 | Q21: 7910.5746 | R21: 112.48696 | V21: =Q21-R21+S21 -> 7798.0877 | W21: -3142.9056 | Z21: =V21+W21 -> 4655.1821 | AB21: 44378 | AC21: =L21/B21 -> 0.0168696 | AD21: =M21/C21 -> 0.36601191 | AE21: =N21/D21 -> 0.020436196 | AG21: 44378 | AH21: =V21*1.06/L21 -> 0.4022322 | AI21: =W21*1.06/M21 -> -0.72396734 | AJ21: =Z21*1.06/N21 -> 0.19618729 | AL21: 44378
A22: 44409 | B22: 1486957.6 | C22: 17899.22 | D22: =B22+C22 -> 1504856.8 | F22: 44409 | G22: ='毛利-收入组成'!AP22 -> 28498.305 | H22: 38539023 | I22: =H22*1.06/10000 -> 4085.1365 | L22: =G22-I22+J22-K22 -> 24413.168 | M22: 5710.0711 | N22: =L22+M22 -> 30123.239 | P22: 44409 | Q22: 9563.2288 | R22: 887.64735 | V22: =Q22-R22+S22 -> 8675.5815 | W22: -4186.9176 | Z22: =V22+W22 -> 4488.6639 | AB22: 44409 | AC22: =L22/B22 -> 0.016418201 | AD22: =M22/C22 -> 0.3190123 | AE22: =N22/D22 -> 0.020017346 | AG22: 44409 | AH22: =V22*1.06/L22 -> 0.37668673 | AI22: =W22*1.06/M22 -> -0.77724647 | AJ22: =Z22*1.06/N22 -> 0.1579506 | AL22: 44409
A23: 44440 | B23: 1664670.2 | C23: 22068.8 | D23: =B23+C23 -> 1686739 | F23: 44440 | G23: ='毛利-收入组成'!AP23 -> 31841.635 | H23: 41417901 | I23: =H23*1.06/10000 -> 4390.2975 | L23: =G23-I23+J23-K23 -> 27451.338 | M23: 7194.8592 | N23: =L23+M23 -> 34646.197 | P23: 44440 | Q23: 10693.952 | R23: 777.15114 | V23: =Q23-R23+S23 -> 9916.8012 | W23: -4721.5095 | Z23: =V23+W23 -> 5195.2918 | AB23: 44440 | AC23: =L23/B23 -> 0.016490556 | AD23: =M23/C23 -> 0.3260195 | AE23: =N23/D23 -> 0.020540342 | AG23: 44440 | AH23: =V23*1.06/L23 -> 0.38292521 | AI23: =W23*1.06/M23 -> -0.69560778 | AJ23: =Z23*1.06/N23 -> 0.15894989 | AL23: 44440
A24: 44470 | B24: 1806282.5 | C24: 27398.839 | D24: =B24+C24 -> 1833681.4 | F24: 44470 | G24: ='毛利-收入组成'!AP24 -> 33988.698 | H24: 43956682 | I24: =H24*1.06/10000 -> 4659.4083 | L24: =G24-I24+J24-K24 -> 29329.29 | M24: 9048.694 | N24: =L24+M24 -> 38377.983 | P24: 44470 | Q24: 12165.082 | R24: 307.9756 | V24: =Q24-R24+S24 -> 11857.106 | W24: -6032.2274 | Z24: =V24+W24 -> 5824.8786 | AB24: 44470 | AC24: =L24/B24 -> 0.016237377 | AD24: =M24/C24 -> 0.3302583 | AE24: =N24/D24 -> 0.020929472 | AG24: 44470 | AH24: =V24*1.06/L24 -> 0.42853177 | AI24: =W24*1.06/M24 -> -0.70663911 | AJ24: =Z24*1.06/N24 -> 0.16088316 | AL24: 44470
A25: 44501 | B25: 1984677.8 | C25: 34131.113 | D25: =B25+C25 -> 2018808.9 | F25: 44501 | G25: ='毛利-收入组成'!AP25 -> 38643.159 | H25: 47344757 | I25: =H25*1.06/10000 -> 5018.5442 | J25: 0 | L25: =G25-I25+J25-K25 -> 33624.614 | M25: 9572.8058 | N25: =L25+M25 -> 43197.42 | P25: 44501 | Q25: 13533.2 | R25: 113.85843 | V25: =Q25-R25+S25 -> 13419.342 | W25: -6850.5275 | Z25: =V25+W25 -> 6568.8143 | AB25: 44501 | AC25: =L25/B25 -> 0.016942103 | AD25: =M25/C25 -> 0.28047154 | AE25: =N25/D25 -> 0.021397479 | AG25: 44501 | AH25: =V25*1.06/L25 -> 0.42303838 | AI25: =W25*1.06/M25 -> -0.75856122 | AJ25: =Z25*1.06/N25 -> 0.16118886 | AL25: 44501
A26: 44531 | B26: 2148731.6 | C26: 42339.291 | D26: =B26+C26 -> 2191070.9 | F26: 44531 | G26: ='毛利-收入组成'!AP26 -> 43403.164 | H26: 48802379 | I26: =H26*1.06/10000 -> 5173.0522 | J26: 0 | L26: =G26-I26+J26-K26 -> 38230.112 | M26: 11140.604 | N26: =L26+M26 -> 49370.716 | P26: 44531 | Q26: =151608372.83/10000 -> 15160.837 | R26: 1486.718 | V26: =Q26-R26+S26 -> 13674.119 | W26: -7655.0039 | Z26: =V26+W26 -> 6019.1155 | AB26: 44531 | AC26: =L26/B26 -> 0.017791944 | AD26: =M26/C26 -> 0.26312684 | AE26: =N26/D26 -> 0.022532688 | AG26: 44531 | AH26: =V26*1.06/L26 -> 0.37914005 | AI26: =W26*1.06/M26 -> -0.72835406 | AJ26: =Z26*1.06/N26 -> 0.12923172 | AL26: 44531
A27: 44562 | B27: 108052.9 | C27: 2374.0586 | D27: =B27+C27 -> 110426.96 | F27: 44562 | G27: ='毛利-收入组成'!AP27 -> 2571.88 | H27: 2707835.9 | I27: =H27*1.06/10000 -> 287.03061 | J27: 655.10541 | K27: =R27*1.06 -> -486.04177 | L27: =G27-I27+J27-K27 -> 3425.9966 | M27: 1436.02 | N27: =L27+M27 -> 4862.0166 | P27: 44562 | Q27: 554.64112 | R27: =-4585299.71781625/10000 -> -458.52997 | S27: 160.39838 | V27: =Q27-R27+S27 -> 1173.5695 | W27: -1005.6133 | Z27: =V27+W27 -> 167.95616 | AB27: 44562 | AC27: =L27/B27 -> 0.03170666 | AD27: =M27/C27 -> 0.60487979 | AE27: =N27/D27 -> 0.044029254 | AG27: 44562 | AH27: =V27*1.06/L27 -> 0.36310125 | AI27: =W27*1.06/M27 -> -0.74229474 | AJ27: =Z27*1.06/N27 -> 0.03661722 | AL27: 44562 | AM27: 4419474.4 | AN27: =-12638207.1/3 -> -4212735.7
A28: 44593 | B28: 194083.64 | C28: 4905.486 | D28: =B28+C28 -> 198989.13 | F28: 44593 | G28: ='毛利-收入组成'!AP28 -> 4593.9912 | H28: 4898251.5 | I28: =H28*1.06/10000 -> 519.21466 | J28: 895.37 | K28: =R28*1.06 -> -952.56963 | L28: =G28-I28+J28-K28 -> 5922.7161 | M28: 3006.5654 | N28: =L28+M28 -> 8929.2816 | P28: 44593 | Q28: 632.65232 | R28: =-4585299.71781625/10000-4401206.19439752/10000 -> -898.65059 | S28: 103.02 | V28: =Q28-R28+S28 -> 1634.3229 | W28: -1072.18 | Z28: =V28+W28 -> 562.14291 | AB28: 44593 | AC28: =L28/B28 -> 0.030516307 | AD28: =M28/C28 -> 0.61289859 | AE28: =N28/D28 -> 0.044873213 | AG28: 44593 | AH28: =V28*1.06/L28 -> 0.29249794 | AI28: =W28*1.06/M28 -> -0.37800967 | AJ28: =Z28*1.06/N28 -> 0.066732299 | AL28: 44593 | AM28: 2602332.2 | AN28: =-12638207.1/3 -> -4212735.7
A29: 44621 | B29: 326827.75 | C29: 7834.875 | D29: =B29+C29 -> 334662.63 | F29: 44621 | G29: ='毛利-收入组成'!AP29 -> 8008.37 | H29: 6963186.2 | I29: =H29*1.06/10000 -> 738.09774 | J29: 1265.12 | K29: =R29*1.06 -> -1339.65 | L29: =G29-I29+J29-K29 -> 9875.0423 | M29: 4720.6749 | N29: =L29+M29 -> 14595.717 | P29: 44621 | Q29: 1386.5289 | R29: -1263.8207 | S29: 203.79785 | V29: =Q29-R29+S29 -> 2854.1475 | W29: -1370.88 | Z29: =V29+W29 -> 1483.2675 | AB29: 44621 | AC29: =L29/B29 -> 0.030214822 | AD29: =M29/C29 -> 0.60252077 | AE29: =N29/D29 -> 0.043613227 | AG29: 44621 | AH29: =V29*1.06/L29 -> 0.30636794 | AI29: =W29*1.06/M29 -> -0.3078231 | AJ29: =Z29*1.06/N29 -> 0.10772088 | AL29: 44621 | AM29: 6160437 | AN29: =-12638207.1/3 -> -4212735.7 | AO29: 146.56785
A30: 44652 | B30: 448332.98 | C30: 8907.4138 | D30: =B30+C30 -> 457240.4 | F30: 44652 | G30: ='毛利-收入组成'!AP30 -> 10700.565 | H30: 9273917.6 | I30: =H30*1.06/10000 -> 983.03526 | J30: 1531.8642 | K30: =R30*1.06 -> -1249.4227 | L30: =G30-I30+J30-K30 -> 12498.816 | M30: 6687.3105 | N30: =L30+M30 -> 19186.127 | P30: 44652 | Q30: 1630.6354 | R30: -1178.7007 | S30: 4.467404 | V30: =Q30-R30+S30 -> 2813.8034 | W30: -1783.2181 | Z30: =V30+W30 -> 1030.5853 | AB30: 44652 | AC30: =L30/B30 -> 0.027878423 | AD30: =M30/C30 -> 0.75075781 | AE30: =N30/D30 -> 0.0419607 | AG30: 44652 | AH30: =V30*1.06/L30 -> 0.23863313 | AI30: =W30*1.06/M30 -> -0.28265641 | AJ30: =Z30*1.06/N30 -> 0.05693804 | AL30: 44652 | AM30: 3124110.2 | AN30: 851200.46 | AO30: -11.900448
A31: 44682 | B31: 584617.02 | C31: 11251.915 | D31: =B31+C31 -> 595868.94 | F31: 44682 | G31: ='毛利-收入组成'!AP31 -> 13310.057 | H31: 11902620 | I31: =H31*1.06/10000 -> 1261.6778 | J31: 1849.5439 | K31: =R31*1.06 -> -1388.9571 | L31: =G31-I31+J31-K31 -> 15286.88 | M31: 8601.3529 | N31: =L31+M31 -> 23888.233 | P31: 44682 | Q31: 1691.0027 | R31: =-13103368.83/10000 -> -1310.3369 | S31: 45.146767 | V31: =Q31-R31+S31 -> 3046.4863 | W31: -2102.6224 | Z31: =V31+W31 -> 943.86394 | AB31: 44682 | AC31: =L31/B31 -> 0.026148538 | AD31: =M31/C31 -> 0.76443456 | AE31: =N31/D31 -> 0.040089744 | AG31: 44682 | AH31: =V31*1.06/L31 -> 0.2112449 | AI31: =W31*1.06/M31 -> -0.25911967 | AJ31: =Z31*1.06/N31 -> 0.041882368 | AL31: 44682 | AM31: 603672.79 | AN31: =(R31-R30)*10000 -> -1316362.2 | AO31: 208.2226
A32: 44713 | B32: 727745.91 | C32: 13983.27 | D32: =B32+C32 -> 741729.18 | F32: 44713 | G32: ='毛利-收入组成'!AP32 -> 17052.403 | H32: 15547055 | I32: =H32*1.06/10000 -> 1647.9879 | J32: 2173.8273 | K32: =R32*1.06 -> -1365.4349 | L32: =G32-I32+J32-K32 -> 18943.678 | M32: 10706.914 | N32: =L32+M32 -> 29650.592 | P32: 44713 | Q32: 3194.8382 | R32: =-12881461.65/10000 -> -1288.1462 | S32: -520.13564 | V32: =Q32-R32+S32 -> 3962.8487 | W32: -2258.997 | Z32: =V32+W32 -> 1703.8517 | AB32: 44713 | AC32: =L32/B32 -> 0.026030621 | AD32: =M32/C32 -> 0.76569461 | AE32: =N32/D32 -> 0.039974957 | AG32: 44713 | AH32: =V32*1.06/L32 -> 0.22174256 | AI32: =W32*1.06/M32 -> -0.22364397 | AJ32: =Z32*1.06/N32 -> 0.060912202 | AL32: 44713 | AM32: 15038356 | AN32: =(R32-R31)*10000 -> 221907.18 | AO32: -280.71317
A33: 44743 | B33: 850965.84 | C33: 16453.571 | D33: =B33+C33 -> 867419.41 | F33: 44743 | G33: ='毛利-收入组成'!AP33 -> 20185.933 | H33: 18238988 | I33: =H33*1.06/10000 -> 1933.3327 | J33: 2432.4562 | K33: =R33*1.06 -> -1463.2248 | L33: =G33-I33+J33-K33 -> 22148.281 | M33: 13005.352 | N33: =L33+M33 -> 35153.633 | P33: 44743 | Q33: 3804.432 | R33: =-13804007.17/10000 -> -1380.4007 | S33: -820.04 | V33: =Q33-R33+S33 -> 4364.7927 | W33: -2988.73 | Z33: =V33+W33 -> 1376.0627 | AB33: 44743 | AC33: =L33/B33 -> 0.026027227 | AD33: =M33/C33 -> 0.79042731 | AE33: =N33/D33 -> 0.040526685 | AG33: 44743 | AH33: =V33*1.06/L33 -> 0.20889568 | AI33: =W33*1.06/M33 -> -0.24359616 | AJ33: =Z33*1.06/N33 -> 0.041492909 | AL33: 44743 | AM33: 6095938 | AN33: =(R33-R32)*10000 -> -922545.52 | AO33: 15.963167
A34: 44774 | B34: 985758.18 | C34: 19132.318 | D34: =B34+C34 -> 1004890.5 | F34: 44774 | G34: ='毛利-收入组成'!AP34 -> 25497.365 | H34: 21451872 | I34: =H34*1.06/10000 -> 2273.8984 | J34: 3031.335 | K34: =R34*1.06 -> -1426.7573 | L34: =G34-I34+J34-K34 -> 27681.559 | M34: 15290.998 | N34: =L34+M34 -> 42972.557 | P34: 44774 | Q34: =54992357.66/10000 -> 5499.2358 | R34: =-13459974.9019033/10000 -> -1345.9975 | S34: -606.21 | V34: =Q34-R34+S34 -> 6239.0233 | W34: -3396.47 | Z34: =V34+W34 -> 2842.5533 | AB34: 44774 | AC34: =L34/B34 -> 0.02808149 | AD34: =M34/C34 -> 0.79922348 | AE34: =N34/D34 -> 0.042763423 | AG34: 44774 | AH34: =V34*1.06/L34 -> 0.23890868 | AI34: =W34*1.06/M34 -> -0.23544952 | AJ34: =Z34*1.06/N34 -> 0.070116992 | AL34: 44774 | AM34: 16948038 | AN34: =(R34-R33)*10000 -> 344032.27 | AO34: 302.64
A35: 44805 | B35: 1135221.8 | C35: 22645.071 | D35: =B35+C35 -> 1157866.9 | F35: 44805 | G35: ='毛利-收入组成'!AP35 -> 28661.881 | H35: 24370597 | I35: =H35*1.06/10000 -> 2583.2833 | J35: 4014.432 | K35: =R35*1.06 -> -1269.1804 | L35: =G35-I35+J35-K35 -> 31362.211 | M35: 17952.319 | N35: =L35+M35 -> 49314.53 | P35: 44805 | Q35: =60424603.79/10000 -> 6042.4604 | R35: =-11973400.44662/10000 -> -1197.34 | S35: -844.98 | V35: =Q35-R35+S35 -> 6394.8204 | W35: -4007.97 | Z35: =V35+W35 -> 2386.8504 | AB35: 44805 | AC35: =L35/B35 -> 0.027626505 | AD35: =M35/C35 -> 0.79276938 | AE35: =N35/D35 -> 0.042590846 | AG35: 44805 | AH35: =V35*1.06/L35 -> 0.21613622 | AI35: =W35*1.06/M35 -> -0.23665178 | AJ35: =Z35*1.06/N35 -> 0.051304584 | AL35: 44805 | AM35: 5432246.1 | AN35: =(R35-R34)*10000 -> 1486574.5 | AO35: -155.56
A36: 44835 | B36: 1282791 | C36: 30802.29 | D36: =B36+C36 -> 1313593.3 | F36: 44835 | G36: ='毛利-收入组成'!AP36 -> 31941.924 | H36: 27931645 | I36: =H36*1.06/10000 -> 2960.7544 | J36: 4527.9066 | K36: =R36*1.06 -> -1399.6803 | L36: =G36-I36+J36-K36 -> 34908.756 | M36: 20691.857 | N36: =L36+M36 -> 55600.613 | P36: 44835 | Q36: =70722471.56/10000 -> 7072.2472 | R36: =-13204531.4789889/10000 -> -1320.4531 | S36: -989.72 | V36: =Q36-R36+S36 -> 7402.9803 | W36: -3546.33 | Z36: =V36+W36 -> 3856.6503 | AB36: 44835 | AC36: =L36/B36 -> 0.027213129 | AD36: =M36/C36 -> 0.67176361 | AE36: =N36/D36 -> 0.042327115 | AG36: 44835 | AH36: =V36*1.06/L36 -> 0.22479057 | AI36: =W36*1.06/M36 -> -0.18167097 | AJ36: =Z36*1.06/N36 -> 0.073525256 | AL36: 44835 | AM36: 10297813 | AN36: =(R36-R35)*10000 -> -1231131 | AO36: -99.33
A37: 44866 | B37: 1458208.4 | C37: 28395.373 | D37: =B37+C37 -> 1486603.8 | F37: 44866 | G37: ='毛利-收入组成'!AP37 -> 36141.231 | H37: 34940282 | I37: =H37*1.06/10000 -> 3703.6699 | J37: 5080.3998 | K37: =R37*1.06 -> -1487.864 | L37: =G37-I37+J37-K37 -> 39005.825 | M37: 23119.872 | N37: =L37+M37 -> 62125.697 | P37: 44866 | Q37: =75107451.42/10000 -> 7510.7451 | R37: =-14036452.5418712/10000 -> -1403.6453 | S37: -1132.02 | V37: =Q37-R37+S37 -> 7782.3704 | W37: -3545.53 | Z37: =V37+W37 -> 4236.8404 | AB37: 44866 | AC37: =L37/B37 -> 0.026749143 | AD37: =M37/C37 -> 0.81421265 | AE37: =N37/D37 -> 0.041790353 | AG37: 44866 | AH37: =V37*1.06/L37 -> 0.21148925 | AI37: =W37*1.06/M37 -> -0.16255548 | AJ37: =Z37*1.06/N37 -> 0.072289746 | AL37: 44866 | AM37: 3561925.3 | AN37: =(R37-R36)*10000 -> -831921.06 | AO37: -166.06
A38: 44896 | B38: 1630463.8 | C38: 43463.22 | D38: =B38+C38 -> 1673927 | F38: 44896 | G38: ='毛利-收入组成'!AP38 -> 43520.124 | H38: 39830925 | I38: =H38*1.06/10000 -> 4222.0781 | J38: 6011.9066 | K38: =R38*1.06 -> -1190.8049 | L38: =G38-I38+J38-K38 -> 46500.757 | M38: 25043.454 | N38: =L38+M38 -> 71544.211 | P38: 44896 | Q38: =115027391.79/10000 -> 11502.739 | R38: =-11234008.655/10000 -> -1123.4009 | S38: -1269.48 | V38: =Q38-R38+S38 -> 11356.66 | W38: -4104.55 | Z38: =V38+W38 -> 7252.11 | AB38: 44896 | AC38: =L38/B38 -> 0.028519957 | AD38: =M38/C38 -> 0.57619877 | AE38: =N38/D38 -> 0.042740341 | AG38: 44896 | AH38: =V38*1.06/L38 -> 0.25887879 | AI38: =W38*1.06/M38 -> -0.17373095 | AJ38: =Z38*1.06/N38 -> 0.10744736 | AL38: 44896 | AM38: 18287190 | AN38: =(R38-R37)*10000 -> 2802443.9 | AO38: 184.5
A39: 44927 | B39: ='GMV表-商品大类'!T42+B95 -> 139899.12 | C39: 3494.7221 | D39: =B39+C39 -> 143393.84 | F39: 44927 | G39: ='毛利-收入组成'!AP39 -> 4343.2834 | H39: 3630321.3 | I39: =H39*1.06/10000 -> 384.81406 | J39: 1931.3288 | K39: =R39*1.06 -> 206.06363 | L39: =G39-I39+J39-K39 -> 5683.7345 | M39: 2148.7773 | N39: =L39+M39 -> 7832.5118 | P39: 44927 | Q39: 1390.69 | R39: =1943996.50432941/10000 -> 194.39965 | S39: 785.578 | V39: =Q39-R39+S39 -> 1981.8684 | W39: 206.1331 | Z39: =V39+W39 -> 2188.0015 | AB39: 44927 | AC39: =L39/B39 -> 0.040627379 | AD39: =M39/C39 -> 0.61486355 | AE39: =N39/D39 -> 0.054622372 | AG39: 44927 | AH39: =V39*1.06/L39 -> 0.3696127 | AI39: =W39*1.06/M39 -> 0.10168624 | AJ39: =Z39*1.06/N39 -> 0.29610955 | AL39: 44927 | AM39: 13906900 | AN39: =R39*10000 -> 1943996.5 | AO39: 98.863
A40: 44958 | B40: ='GMV表-商品大类'!T43+B96 -> 273756.55 | C40: 6379.2112 | D40: =B40+C40 -> 280135.76 | F40: 44958 | G40: ='毛利-收入组成'!AP40 -> 7467.2483 | H40: 6214995.1 | I40: =H40*1.06/10000 -> 658.78948 | J40: 2249.6399 | K40: =R40*1.06 -> -169.18257 | L40: =G40-I40+J40-K40 -> 9227.2813 | M40: 3659.1241 | N40: =L40+M40 -> 12886.405 | P40: 44958 | Q40: 2066.4314 | R40: =-1596061.9885538/10000 -> -159.6062 | S40: 597.92934 | V40: =Q40-R40+S40 -> 2823.967 | W40: 130.11791 | Z40: =V40+W40 -> 2954.0849 | AB40: 44958 | AC40: =L40/B40 -> 0.033706157 | AD40: =M40/C40 -> 0.57360134 | AE40: =N40/D40 -> 0.046000572 | AG40: 44958 | AH40: =V40*1.06/L40 -> 0.32440812 | AI40: =W40*1.06/M40 -> 0.037693443 | AJ40: =Z40*1.06/N40 -> 0.24299484 | AL40: 44958 | AM40: 6757414.1 | AN40: =(R40-R39)*10000 -> -3540058.5 | AO40: =S40-S39 -> -187.64866
A41: 44986 | B41: ='GMV表-商品大类'!T44+B97 -> 430030.64 | C41: 9120.9552 | D41: =B41+C41 -> 439151.59 | F41: 44986 | G41: ='毛利-收入组成'!AP41 -> 10413.099 | H41: 9373428.8 | I41: =H41*1.06/10000 -> 993.58345 | J41: 2973.5557 | K41: =R41*1.06 -> 45.142784 | L41: =G41-I41+J41-K41 -> 12347.928 | M41: 5379.9146 | N41: =L41+M41 -> 17727.843 | P41: 44986 | Q41: 2269.4532 | R41: 42.587533 | S41: 365.21191 | V41: =Q41-R41+S41 -> 2592.0776 | W41: -140.70901 | Z41: =V41+W41 -> 2451.3686 | AB41: 44986 | AC41: =L41/B41 -> 0.028714067 | AD41: =M41/C41 -> 0.58984114 | AE41: =N41/D41 -> 0.04036839 | AG41: 44986 | AH41: =V41*1.06/L41 -> 0.22251524 | AI41: =W41*1.06/M41 -> -0.027723776 | AJ41: =Z41*1.06/N41 -> 0.14657455 | AL41: 44986 | AM41: 2030217.6 | AN41: =(R41-R40)*10000 -> 2021937.3 | AO41: =S41-S40 -> -232.71743
A42: 45017 | B42: ='GMV表-商品大类'!T45+B98 -> 562009.48 | C42: 11863.173 | D42: =B42+C42 -> 573872.65 | F42: 45017 | G42: ='毛利-收入组成'!AP42 -> 12608.747 | H42: 12671634 | I42: =H42*1.06/10000 -> 1343.1932 | J42: 3381.6409 | K42: =R42*1.06 -> 39.369201 | L42: =G42-I42+J42-K42 -> 14607.826 | M42: 6902.0785 | N42: =L42+M42 -> 21509.904 | P42: 45017 | Q42: =24847709.2/10000 -> 2484.7709 | R42: =371407.553576133/10000 -> 37.140755 | S42: -115.89507 | V42: =Q42-R42+S42 -> 2331.7351 | W42: -310.77087 | Z42: =V42+W42 -> 2020.9642 | AB42: 45017 | AC42: =L42/B42 -> 0.025992134 | AD42: =M42/C42 -> 0.58180713 | AE42: =N42/D42 -> 0.037482017 | AG42: 45017 | AH42: =V42*1.06/L42 -> 0.16919966 | AI42: =W42*1.06/M42 -> -0.047727235 | AJ42: =Z42*1.06/N42 -> 0.099592357 | AL42: 45017 | AM42: 2153177.1 | AN42: =(R42-R41)*10000 -> -54467.771 | AO42: =S42-S41 -> -481.10697
A43: 45047 | B43: ='GMV表-商品大类'!T46+B99 -> 718524.9 | C43: 14129.51 | D43: =B43+C43 -> 732654.41 | F43: 45047 | G43: ='毛利-收入组成'!AP43 -> 16236.986 | H43: 16554205 | I43: =H43*1.06/10000 -> 1754.7457 | J43: 3943.9878 | K43: =R43*1.06 -> 49.602631 | L43: =G43-I43+J43-K43 -> 18376.626 | M43: 8310.2133 | N43: =L43+M43 -> 26686.839 | P43: 45047 | Q43: =33865340.38/10000 -> 3386.534 | R43: =467949.353128217/10000 -> 46.794935 | S43: -480.00006 | V43: =Q43-R43+S43 -> 2859.739 | W43: -782.02193 | Z43: =V43+W43 -> 2077.7171 | AB43: 45047 | AC43: =L43/B43 -> 0.025575489 | AD43: =M43/C43 -> 0.58814591 | AE43: =N43/D43 -> 0.036424866 | AG43: 45047 | AH43: =V43*1.06/L43 -> 0.16495539 | AI43: =W43*1.06/M43 -> -0.099749936 | AJ43: =Z43*1.06/N43 -> 0.082526826 | AL43: 45047 | AM43: 9017631.2 | AN43: =(R43-R42)*10000 -> 96541.8 | AO43: =S43-S42 -> -364.105
A44: 45078 | B44: ='GMV表-商品大类'!T47+B100 -> 885719.33 | C44: 16876.623 | D44: =B44+C44 -> 902595.96 | F44: 45078 | G44: ='毛利-收入组成'!AP44 -> 21479.88 | H44: 22188118 | I44: =H44*1.06/10000 -> 2351.9405 | J44: 4738.2533 | K44: =R44*1.06 -> 3.0884422 | L44: =G44-I44+J44-K44 -> 23863.104 | M44: 9775.2481 | N44: =L44+M44 -> 33638.353 | P44: 45078 | Q44: =56339633.83/10000 -> 5633.9634 | R44: =29136.2470234791/10000 -> 2.9136247 | S44: -606.53558 | V44: =Q44-R44+S44 -> 5024.5142 | W44: -595.02904 | Z44: =V44+W44 -> 4429.4851 | AB44: 45078 | AC44: =L44/B44 -> 0.026942061 | AD44: =M44/C44 -> 0.57921824 | AE44: =N44/D44 -> 0.03726845 | AG44: 45078 | AH44: =V44*1.06/L44 -> 0.22318911 | AI44: =W44*1.06/M44 -> -0.064523251 | AJ44: =Z44*1.06/N44 -> 0.13958039 | AL44: 45078 | AM44: 22474293 | AN44: =(R44-R43)*10000 -> -438813.11 | AO44: =S44-S43 -> -126.53552
A45: 45108 | B45: ='GMV表-商品大类'!T48+B101 -> 1031827.7 | C45: 19317.607 | D45: =B45+C45 -> 1051145.4 | F45: 45108 | G45: ='毛利-收入组成'!AP45 -> 24896.668 | H45: 25343928 | I45: =H45*1.06/10000 -> 2686.4563 | J45: 5300.6635 | K45: =R45*1.06 -> 100.72932 | L45: =G45-I45+J45-K45 -> 27410.145 | M45: 11006.209 | N45: =L45+M45 -> 38416.354 | P45: 45108 | Q45: =64434719.82/10000 -> 6443.472 | R45: =950276.619611746/10000 -> 95.027662 | S45: -889.85281 | V45: =Q45-R45+S45 -> 5458.5915 | W45: -612.04319 | Z45: =V45+W45 -> 4846.5483 | AB45: 45108 | AC45: =L45/B45 -> 0.026564652 | AD45: =M45/C45 -> 0.56975012 | AE45: =N45/D45 -> 0.036547138 | AG45: 45108 | AH45: =V45*1.06/L45 -> 0.21109363 | AI45: =W45*1.06/M45 -> -0.058945437 | AJ45: =Z45*1.06/N45 -> 0.13372797 | AL45: 45108 | AM45: 8095086 | AN45: =(R45-R44)*10000 -> 921140.37 | AO45: =S45-S44 -> -283.31723
A46: 45139 | B46: ='GMV表-商品大类'!T49+B102 -> 1194307.4 | C46: 22430.295 | D46: =B46+C46 -> 1216737.7 | F46: 45139 | G46: ='毛利-收入组成'!AP46 -> 29102.011 | H46: 29881459 | I46: =H46*1.06/10000 -> 3167.4347 | J46: 6106.3185 | K46: =R46*1.06 -> 89.892167 | L46: =G46-I46+J46-K46 -> 31951.003 | M46: 12594.133 | N46: =L46+M46 -> 44545.136 | P46: 45139 | Q46: =75519119.24/10000 -> 7551.9119 | R46: =848039.309164936/10000 -> 84.803931 | S46: -990.76869 | V46: =Q46-R46+S46 -> 6476.3393 | W46: -592.28631 | Z46: =V46+W46 -> 5884.053 | AB46: 45139 | AC46: =L46/B46 -> 0.026752747 | AD46: =M46/C46 -> 0.56147871 | AE46: =N46/D46 -> 0.036610304 | AG46: 45139 | AH46: =V46*1.06/L46 -> 0.21485772 | AI46: =W46*1.06/M46 -> -0.049850472 | AJ46: =Z46*1.06/N46 -> 0.14001745 | AL46: 45139 | AM46: 11084399 | AN46: =(R46-R45)*10000 -> -102237.31 | AO46: =S46-S45 -> -100.91588
A47: 45170 | B47: ='GMV表-商品大类'!T50+B103 -> 1339120.1 | C47: 25425.014 | D47: =B47+C47 -> 1364545.1 | F47: 45170 | G47: ='毛利-收入组成'!AP47 -> 31954.748 | H47: 32816668 | I47: =H47*1.06/10000 -> 3478.5668 | J47: 7413.0762 | K47: =R47*1.06 -> -155.33227 | L47: =G47-I47+J47-K47 -> 36044.59 | M47: 14057.412 | N47: =L47+M47 -> 50102.002 | P47: 45170 | Q47: =83475621.39/10000 -> 8347.5621 | R47: =-1465398.79/10000 -> -146.53988 | S47: -698.13675 | V47: =Q47-R47+S47 -> 7795.9653 | W47: -570.92725 | Z47: =V47+W47 -> 7225.038 | AB47: 45170 | AC47: =L47/B47 -> 0.026916622 | AD47: =M47/C47 -> 0.55289692 | AE47: =N47/D47 -> 0.036716999 | AG47: 45170 | AH47: =V47*1.06/L47 -> 0.2292639 | AI47: =W47*1.06/M47 -> -0.043050804 | AJ47: =Z47*1.06/N47 -> 0.15285897 | AL47: 45170 | AM47: 7956502.2 | AN47: =(R47-R46)*10000 -> -2313438.1 | AO47: =S47-S46 -> 292.63194
A48: 45200 | B48: ='GMV表-商品大类'!T51+B104 -> 1446745 | C48: 28365.195 | D48: =B48+C48 -> 1475110.2 | F48: 45200 | G48: ='毛利-收入组成'!AP48 -> 35384.217 | H48: 35555090 | I48: =H48*1.06/10000 -> 3768.8395 | J48: 8333.3067 | K48: =R48*1.06 -> 50.929116 | L48: =G48-I48+J48-K48 -> 39897.755 | M48: 15607.072 | N48: =L48+M48 -> 55504.827 | P48: 45200 | Q48: =89396323.84/10000 -> 8939.6324 | R48: =480463.357363195/10000 -> 48.046336 | S48: -747.08716 | V48: =Q48-R48+S48 -> 8144.4989 | W48: -460.83184 | Z48: =V48+W48 -> 7683.667 | AB48: 45200 | AC48: =L48/B48 -> 0.0275776 | AD48: =M48/C48 -> 0.5502191 | AE48: =N48/D48 -> 0.03762758 | AG48: 45200 | AH48: =V48*1.06/L48 -> 0.21638232 | AI48: =W48*1.06/M48 -> -0.031298744 | AJ48: =Z48*1.06/N48 -> 0.14673836 | AL48: 45200 | AM48: 5920702.5 | AN48: =(R48-R47)*10000 -> 1945862.1 | AO48: =S48-S47 -> -48.950403
A49: 45231 | B49: ='GMV表-商品大类'!T52+B105 -> 1573930.7 | C49: 32045.495 | D49: =B49+C49 -> 1605976.2 | F49: 45231 | G49: ='毛利-收入组成'!AP49 -> 40497.763 | H49: 39818569 | I49: =H49*1.06/10000 -> 4220.7683 | J49: 9122.3132 | K49: =R49*1.06 -> -126.91095 | L49: =G49-I49+J49-K49 -> 45526.218 | M49: 16855.04 | N49: =L49+M49 -> 62381.259 | P49: 45231 | Q49: =105607329.35/10000 -> 10560.733 | R49: =-1197273.069527/10000 -> -119.72731 | S49: -669.69008 | V49: =Q49-R49+S49 -> 10010.77 | W49: -555.38892 | Z49: =V49+W49 -> 9455.3812 | AB49: 45231 | AC49: =L49/B49 -> 0.028925173 | AD49: =M49/C49 -> 0.52597222 | AE49: =N49/D49 -> 0.038843202 | AG49: 45231 | AH49: =V49*1.06/L49 -> 0.23308363 | AI49: =W49*1.06/M49 -> -0.034927965 | AJ49: =Z49*1.06/N49 -> 0.16066851 | AL49: 45231 | AM49: 16211006 | AN49: =(R49-R48)*10000 -> -1677736.4 | AO49: =S49-S48 -> 77.397076
A50: 45261 | B50: ='GMV表-商品大类'!T53+B106 -> 1683893.3 | C50: 35301.109 | D50: =B50+C50 -> 1719194.4 | F50: 45261 | G50: ='毛利-收入组成'!AP50 -> 47538.618 | H50: 42529215 | I50: =H50*1.06/10000 -> 4508.0968 | J50: 10356.611 | K50: =R50*1.06 -> 116.10774 | L50: =G50-I50+J50-K50 -> 53271.024 | M50: 18153.929 | N50: =L50+M50 -> 71424.953 | P50: 45261 | Q50: =130338051.49/10000 -> 13033.805 | R50: =1095356.02364967/10000 -> 109.5356 | S50: -1547.2801 | V50: =Q50-R50+S50 -> 11376.989 | W50: -455.01694 | Z50: =V50+W50 -> 10921.973 | AB50: 45261 | AC50: =L50/B50 -> 0.03163563 | AD50: =M50/C50 -> 0.51425945 | AE50: =N50/D50 -> 0.041545594 | AG50: 45261 | AH50: =V50*1.06/L50 -> 0.22638215 | AI50: =W50*1.06/M50 -> -0.026568242 | AJ50: =Z50*1.06/N50 -> 0.16209028 | AL50: 45261 | AM50: 24730722 | AN50: =(R50-R49)*10000 -> 2292629.1 | AO50: =S50-S49 -> -877.58998
A51: 45292 | B51: ='GMV表-商品大类'!T54+B107 -> 101433.39 | C51: 2264.3271 | D51: =B51+C51 -> 103697.71 | F51: 45292 | G51: ='毛利-收入组成'!AP51 -> 2786.2584 | H51: 2201641.7 | I51: =H51*1.06/10000 -> 233.37402 | J51: 1992.7764 | K51: =R51*1.06 -> -137.41391 | L51: =G51-I51+J51-K51 -> 4683.0747 | M51: 1641.7547 | N51: =L51+M51 -> 6324.8294 | P51: 45292 | Q51: =3364142.28/10000 -> 336.41423 | R51: =-1296357.68417/10000 -> -129.63577 | S51: 701.9994 | V51: =Q51-R51+S51 -> 1168.0494 | W51: 66.763345 | Z51: =V51+W51 -> 1234.8127 | AB51: 45292 | AC51: =L51/B51 -> 0.046168966 | AD51: =M51/C51 -> 0.72505193 | AE51: =N51/D51 -> 0.060992948 | AG51: 45292 | AH51: =V51*1.06/L51 -> 0.2643845 | AI51: =W51*1.06/M51 -> 0.043105797 | AJ51: =Z51*1.06/N51 -> 0.20694653 | AL51: 45292 | AM51: 3364142.3 | AN51: =R51*10000 -> -1296357.7 | AO51: =S51 -> 701.9994
A52: 45323 | B52: ='GMV表-商品大类'!T55+B108 -> 190089.48 | C52: 4490.9293 | D52: =B52+C52 -> 194580.41 | F52: 45323 | G52: ='毛利-收入组成'!AP52 -> 5256.8072 | H52: 4535148.6 | I52: =H52*1.06/10000 -> 480.72575 | J52: 2470.0261 | K52: =R52*1.06 -> -236.35704 | L52: =G52-I52+J52-K52 -> 7482.4646 | M52: 3234.9687 | N52: =L52+M52 -> 10717.433 | P52: 45323 | Q52: 566.71745 | R52: =-2229783.36430365/10000 -> -222.97834 | S52: 664.82858 | V52: =Q52-R52+S52 -> 1454.5244 | W52: 318.4881 | Z52: =V52+W52 -> 1773.0125 | AB52: 45323 | AC52: =L52/B52 -> 0.039362855 | AD52: =M52/C52 -> 0.72033392 | AE52: =N52/D52 -> 0.055079714 | AG52: 45323 | AH52: =V52*1.06/L52 -> 0.20605454 | AI52: =W52*1.06/M52 -> 0.10435878 | AJ52: =Z52*1.06/N52 -> 0.17535852 | AL52: 45323 | AM52: 2303032.2 | AN52: =(R52-R51)*10000 -> -933425.68 | AO52: =S52-S51 -> -37.170824
A53: 45352 | B53: ='GMV表-商品大类'!T56+B109 -> 268614.84 | C53: 6554.9001 | D53: =B53+C53 -> 275169.74 | F53: 45352 | G53: ='毛利-收入组成'!AP53 -> 8421.3423 | H53: 6411571.3 | I53: =H53*1.06/10000 -> 679.62655 | J53: 3319.7856 | K53: =R53*1.06 -> -625.33948 | L53: =G53-I53+J53-K53 -> 11686.841 | M53: 4047.3122 | N53: =L53+M53 -> 15734.153 | P53: 45352 | Q53: =19480246.9399998/10000 -> 1948.0247 | R53: =-5899429.04962477/10000 -> -589.9429 | S53: 484.12228 | V53: =Q53-R53+S53 -> 3022.0899 | W53: -142.42172 | Z53: =V53+W53 -> 2879.6682 | AB53: 45352 | AC53: =L53/B53 -> 0.043507801 | AD53: =M53/C53 -> 0.61744834 | AE53: =N53/D53 -> 0.057179809 | AG53: 45352 | AH53: =V53*1.06/L53 -> 0.27410447 | AI53: =W53*1.06/M53 -> -0.037300564 | AJ53: =Z53*1.06/N53 -> 0.19400143 | AL53: 45352 | AM53: =(Q53-Q52)*10000 -> 13813072 | AN53: =(R53-R52)*10000 -> -3669645.7 | AO53: =S53-S52 -> -180.7063
A54: 45383 | B54: ='GMV表-商品大类'!T57+B110 -> 329663.72 | C54: 7811.5825 | D54: =B54+C54 -> 337475.3 | F54: 45383 | G54: ='毛利-收入组成'!AP54 -> 9720.5498 | H54: 8210403.3 | I54: =H54*1.06/10000 -> 870.30275 | J54: 3986.5078 | K54: =R54*1.06 -> -630.70441 | L54: =G54-I54+J54-K54 -> 13467.459 | M54: 4692.473 | N54: =L54+M54 -> 18159.932 | P54: 45383 | Q54: =17237592.6600001/10000 -> 1723.7593 | R54: =-5950041.59942243/10000 -> -595.00416 | S54: 527.01729 | V54: =Q54-R54+S54 -> 2845.7807 | W54: -364.30428 | Z54: =V54+W54 -> 2481.4764 | AB54: 45383 | AC54: =L54/B54 -> 0.040852112 | AD54: =M54/C54 -> 0.60070709 | AE54: =N54/D54 -> 0.053811144 | AG54: 45383 | AH54: =V54*1.06/L54 -> 0.22398639 | AI54: =W54*1.06/M54 -> -0.082294036 | AJ54: =Z54*1.06/N54 -> 0.14484443 | AL54: 45383 | AM54: =(Q54-Q53)*10000 -> -2242654.3 | AN54: =(R54-R53)*10000 -> -50612.55 | AO54: =S54-S53 -> 42.895009
A55: 45413 | B55: ='GMV表-商品大类'!T58+B111 -> 411711.95 | C55: 48484.603 | D55: =B55+C55 -> 460196.55 | F55: 45413 | G55: ='毛利-收入组成'!AP55 -> 11948.968 | H55: 10009914 | I55: =H55*1.06/10000 -> 1061.0509 | J55: 4828.7836 | K55: =R55*1.06 -> -643.36516 | L55: =G55-I55+J55-K55 -> 16360.066 | M55: 5488.1957 | N55: =L55+M55 -> 21848.261 | P55: 45413 | Q55: =17363557.5599997/10000 -> 1736.3558 | R55: =-6069482.61294327/10000 -> -606.94826 | S55: 469.47202 | V55: =Q55-R55+S55 -> 2812.776 | W55: -520.88602 | Z55: =V55+W55 -> 2291.89 | AB55: 45413 | AC55: =L55/B55 -> 0.03973668 | AD55: =M55/C55 -> 0.11319461 | AE55: =N55/D55 -> 0.047475935 | AG55: 45413 | AH55: =V55*1.06/L55 -> 0.18224515 | AI55: =W55*1.06/M55 -> -0.10060486 | AJ55: =Z55*1.06/N55 -> 0.11119436 | AL55: 45413 | AM55: =(Q55-Q54)*10000 -> 125964.9 | AN55: =(R55-R54)*10000 -> -119441.01 | AO55: =S55-S54 -> -57.545267
A56: 45444 | B56: ='GMV表-商品大类'!T59+B112 -> 509385.36 | C56: 57933.49 | D56: =B56+C56 -> 567318.85 | F56: 45444 | G56: ='毛利-收入组成'!AP56 -> 13920.387 | H56: 13079265 | I56: =H56*1.06/10000 -> 1386.402 | J56: 5206.9754 | K56: =R56*1.06 -> -648.29281 | L56: =G56-I56+J56-K56 -> 18389.253 | M56: 6076.524 | N56: =L56+M56 -> 24465.777 | P56: 45444 | Q56: =20545121.3099999/10000 -> 2054.5121 | R56: =-6115969.92496954/10000 -> -611.59699 | S56: 407.13856 | V56: =Q56-R56+S56 -> 3073.2477 | W56: -1234.8556 | Z56: =V56+W56 -> 1838.3921 | AB56: 45444 | AC56: =L56/B56 -> 0.036100867 | AD56: =M56/C56 -> 0.10488793 | AE56: =N56/D56 -> 0.043125267 | AG56: 45444 | AH56: =V56*1.06/L56 -> 0.17714926 | AI56: =W56*1.06/M56 -> -0.21541047 | AJ56: =Z56*1.06/N56 -> 0.079649857 | AL56: 45444 | AM56: =(Q56-Q55)*10000 -> 3181563.8 | AN56: =(R56-R55)*10000 -> -46487.312 | AO56: =S56-S55 -> -62.333461
A57: 45474 | B57: ='GMV表-商品大类'!T60+B113 -> 607746.8 | C57: 67786.587 | D57: =B57+C57 -> 675533.39 | F57: 45474 | G57: ='毛利-收入组成'!AP57 -> 16860.607 | H57: 16583095 | I57: =H57*1.06/10000 -> 1757.8081 | J57: 4830.4436 | K57: =R57*1.06 -> 216.82817 | L57: =G57-I57+J57-K57 -> 19716.415 | M57: 7385.8469 | N57: =L57+M57 -> 27102.262 | P57: 45474 | Q57: =28247260.5499999/10000 -> 2824.7261 | R57: =2045548.79526134/10000 -> 204.55488 | S57: 345.70945 | V57: =Q57-R57+S57 -> 2965.8806 | W57: -914.54146 | Z57: =V57+W57 -> 2051.3392 | AB57: 45474 | AC57: =L57/B57 -> 0.032441824 | AD57: =M57/C57 -> 0.10895735 | AE57: =N57/D57 -> 0.040119796 | AG57: 45474 | AH57: =V57*1.06/L57 -> 0.15945259 | AI57: =W57*1.06/M57 -> -0.13125292 | AJ57: =Z57*1.06/N57 -> 0.080230187 | AL57: 45474 | AM57: =(Q57-Q56)*10000 -> 7702139.2 | AN57: =(R57-R56)*10000 -> 8161518.7 | AO57: =S57-S56 -> -61.429102
A58: 45505 | B58: ='GMV表-商品大类'!T61+B114 -> 688414.05 | C58: 77960.769 | D58: =B58+C58 -> 766374.82 | F58: 45505 | G58: ='毛利-收入组成'!AP58 -> 19501.135 | H58: 17318463 | I58: =H58*1.06/10000 -> 1835.757 | J58: 6482.25 | K58: =R58*1.06 -> 163.1307 | L58: =G58-I58+J58-K58 -> 23984.497 | M58: 8433.5884 | N58: =L58+M58 -> 32418.085 | P58: 45505 | Q58: =31134501.7400001/10000 -> 3113.4502 | R58: =1538968.90630751/10000 -> 153.89689 | S58: 331.25371 | V58: =Q58-R58+S58 -> 3290.807 | W58: -916.40871 | Z58: =V58+W58 -> 2374.3983 | AB58: 45505 | AC58: =L58/B58 -> 0.03484022 | AD58: =M58/C58 -> 0.10817734 | AE58: =N58/D58 -> 0.042300562 | AG58: 45505 | AH58: =V58*1.06/L58 -> 0.14543792 | AI58: =W58*1.06/M58 -> -0.11518148 | AJ58: =Z58*1.06/N58 -> 0.077637595 | AL58: 45505 | AM58: =(Q58-Q57)*10000 -> 2887241.2 | AN58: =(R58-R57)*10000 -> -506579.89 | AO58: =S58-S57 -> -14.455746
A59: 45536 | B59: ='GMV表-商品大类'!T62+B115 -> 748878.18 | C59: 88041.301 | D59: =B59+C59 -> 836919.48 | F59: 45536 | G59: ='毛利-收入组成'!AP59 -> 21218.058 | H59: 18819047 | I59: =H59*1.06/10000 -> 1994.819 | J59: 7755.0266 | K59: =R59*1.06 -> 163.32379 | L59: =G59-I59+J59-K59 -> 26814.942 | M59: 9463.4699 | N59: =L59+M59 -> 36278.412 | P59: 45536 | Q59: =36119147.9499995/10000 -> 3611.9148 | R59: =1540790.48672378/10000 -> 154.07905 | S59: 741.04432 | V59: =Q59-R59+S59 -> 4198.8801 | W59: -869.18632 | Z59: =V59+W59 -> 3329.6937 | AB59: 45536 | AC59: =L59/B59 -> 0.035806815 | AD59: =M59/C59 -> 0.10748898 | AE59: =N59/D59 -> 0.043347554 | AG59: 45536 | AH59: =V59*1.06/L59 -> 0.16598256 | AI59: =W59*1.06/M59 -> -0.09735726 | AJ59: =Z59*1.06/N59 -> 0.097288585 | AL59: 45536 | AM59: =(Q59-Q58)*10000 -> 4984646.2 | AN59: =(R59-R58)*10000 -> 1821.5804 | AO59: =S59-S58 -> 409.79062
A60: 45566 | B60: ='GMV表-商品大类'!T63+B116 -> 813677.8 | C60: 98052.555 | D60: =B60+C60 -> 911730.36 | F60: 45566 | G60: ='毛利-收入组成'!AP60 -> 23238.672 | H60: 20057337 | I60: =H60*1.06/10000 -> 2126.0777 | J60: 8747.211 | K60: =R60*1.06 -> 259.79516 | L60: =G60-I60+J60-K60 -> 29600.01 | M60: 10528.913 | N60: =L60+M60 -> 40128.923 | P60: 45566 | Q60: =37390549.6399998/10000 -> 3739.055 | R60: =2450897.73613187/10000 -> 245.08977 | S60: 862.00698 | V60: =Q60-R60+S60 -> 4355.9722 | W60: -708.53098 | Z60: =V60+W60 -> 3647.4412 | AB60: 45566 | AC60: =L60/B60 -> 0.036378048 | AD60: =M60/C60 -> 0.1073803 | AE60: =N60/D60 -> 0.044014026 | AG60: 45566 | AH60: =V60*1.06/L60 -> 0.15599084 | AI60: =W60*1.06/M60 -> -0.071331469 | AJ60: =Z60*1.06/N60 -> 0.096346658 | AL60: 45566 | AM60: =(Q60-Q59)*10000 -> 1271401.7 | AN60: =(R60-R59)*10000 -> 910107.25 | AO60: =S60-S59 -> 120.96266
A61: 45597 | B61: ='GMV表-商品大类'!T64+B117 -> 882563.82 | C61: 108422.02 | D61: =B61+C61 -> 990985.84 | F61: 45597 | G61: ='毛利-收入组成'!AP61 -> 25333.258 | H61: 19330114 | I61: =H61*1.06/10000 -> 2048.9921 | J61: 9819.6838 | K61: =R61*1.06 -> 46.743328 | L61: =G61-I61+J61-K61 -> 33057.207 | M61: 11601.376 | N61: =L61+M61 -> 44658.582 | P61: 45597 | Q61: =39282359.86/10000 -> 3928.236 | R61: =440974.792297676/10000 -> 44.097479 | S61: 1143.8451 | V61: =Q61-R61+S61 -> 5027.9836 | W61: -559.21109 | Z61: =V61+W61 -> 4468.7725 | AB61: 45597 | AC61: =L61/B61 -> 0.037455883 | AD61: =M61/C61 -> 0.10700202 | AE61: =N61/D61 -> 0.045064804 | AG61: 45597 | AH61: =V61*1.06/L61 -> 0.16122544 | AI61: =W61*1.06/M61 -> -0.051094264 | AJ61: =Z61*1.06/N61 -> 0.10606917 | AL61: 45597 | AM61: =(Q61-Q60)*10000 -> 1891810.2 | AN61: =(R61-R60)*10000 -> -2009922.9 | AO61: =S61-S60 -> 281.8381
A62: 45627 | B62: ='GMV表-商品大类'!T65+B118 -> 950049.95 | C62: 120473.04 | D62: =B62+C62 -> 1070523 | F62: 45627 | G62: ='毛利-收入组成'!AP62 -> 28076.738 | H62: 20867964 | I62: =H62*1.06/10000 -> 2212.0042 | J62: 10371.365 | K62: =R62*1.06 -> -5.9447039 | L62: =G62-I62+J62-K62 -> 36242.044 | M62: 13216.352 | N62: =L62+M62 -> 49458.396 | P62: 45627 | Q62: =40657623.89/10000 -> 4065.7624 | R62: =-56082.1122934511/10000 -> -5.6082112 | S62: 799.44024 | V62: =Q62-R62+S62 -> 4870.8108 | W62: -191.65324 | Z62: =V62+W62 -> 4679.1576 | AB62: 45627 | AC62: =L62/B62 -> 0.038147514 | AD62: =M62/C62 -> 0.10970382 | AE62: =N62/D62 -> 0.046200219 | AG62: 45627 | AH62: =V62*1.06/L62 -> 0.14246049 | AI62: =W62*1.06/M62 -> -0.015371294 | AJ62: =Z62*1.06/N62 -> 0.10028443 | AL62: 45627 | AM62: =(Q62-Q61)*10000 -> 1375264 | AN62: =(R62-R61)*10000 -> -497056.9 | AO62: =S62-S61 -> -344.40485
A63: 45658 | B63: ='GMV表-商品大类'!T66+B119 -> 81145.313 | C63: 12379.049 | D63: =B63+C63 -> 93524.362 | F63: 45658 | G63: ='毛利-收入组成'!AP63 -> 2075.3523 | H63: 1143231.9 | I63: =H63*1.06/10000 -> 121.18258 | J63: 2206.1643 | K63: =R63*1.06 -> -180.42851 | L63: =G63-I63+J63-K63 -> 4340.7626 | M63: 1241.357 | N63: =L63+M63 -> 5582.1196 | P63: 45658 | Q63: =2904342.15/10000 -> 290.43421 | R63: =-1702155.76979259/10000 -> -170.21558 | S63: 744.55228 | V63: =Q63-R63+S63 -> 1205.2021 | W63: 36.057099 | Z63: =V63+W63 -> 1241.2592 | AB63: 45658 | AC63: =L63/B63 -> 0.053493695 | AD63: =M63/C63 -> 0.10027887 | AE63: =N63/D63 -> 0.059686262 | AG63: 45658 | AH63: =V63*1.06/L63 -> 0.2943064 | AI63: =W63*1.06/M63 -> 0.030789309 | AJ63: =Z63*1.06/N63 -> 0.23570522 | AL63: 45658 | AM63: =Q63*10000 -> 2904342.1 | AN63: =R63*10000 -> -1702155.8 | AO63: =S63 -> 744.55228
A64: 45689 | B64: ='GMV表-商品大类'!T67+B120 -> 143043.59 | C64: 15190.545 | D64: =B64+C64 -> 158234.13 | F64: 45689 | G64: ='毛利-收入组成'!AP64 -> 4860.198 | H64: 2075803.2 | I64: =H64*1.06/10000 -> 220.03514 | J64: 2816.3186 | K64: =R64*1.06 -> -266.66127 | L64: =G64-I64+J64-K64 -> 7723.1428 | M64: 2372.3631 | N64: =L64+M64 -> 10095.506 | P64: 45689 | Q64: =14521013.01/10000 -> 1452.1013 | R64: =-2515672.38594156/10000 -> -251.56724 | S64: 771.90753 | V64: =Q64-R64+S64 -> 2475.5761 | W64: 26.999682 | Z64: =V64+W64 -> 2502.5757 | AB64: 45689 | AC64: =L64/B64 -> 0.053991534 | AD64: =M64/C64 -> 0.15617367 | AE64: =N64/D64 -> 0.063801062 | AG64: 45689 | AH64: =V64*1.06/L64 -> 0.33977238 | AI64: =W64*1.06/M64 -> 0.012063778 | AJ64: =Z64*1.06/N64 -> 0.26276348 | AL64: 45689 | AM64: =(Q64-Q63)*10000 -> 11616671 | AN64: =(R64-R63)*10000 -> -813516.62 | AO64: =(S64-S63) -> 27.355244
A65: 45717 | B65: ='GMV表-商品大类'!T68+B121 -> 210392.88 | C65: 27875.804 | D65: =B65+C65 -> 238268.68 | F65: 45717 | G65: ='毛利-收入组成'!AP65 -> 7154.8956 | H65: 3524084.5 | I65: =H65*1.06/10000 -> 373.55295 | J65: 2586.5601 | K65: =R65*1.06 -> -308.93295 | L65: =G65-I65+J65-K65 -> 9676.8357 | M65: 3928.1127 | N65: =L65+M65 -> 13604.948 | P65: 45717 | Q65: =20008987.28/10000 -> 2000.8987 | R65: =-2914461.825889/10000 -> -291.44618 | S65: 362.73092 | V65: =Q65-R65+S65 -> 2655.0758 | W65: 351.18673 | Z65: =V65+W65 -> 3006.2626 | AB65: 45717 | AC65: =L65/B65 -> 0.045994122 | AD65: =M65/C65 -> 0.14091478 | AE65: =N65/D65 -> 0.057099188 | AG65: 45717 | AH65: =V65*1.06/L65 -> 0.29083685 | AI65: =W65*1.06/M65 -> 0.094767631 | AJ65: =Z65*1.06/N65 -> 0.23422642 | AL65: 45717 | AM65: =(Q65-Q64)*10000 -> 5487974.3 | AN65: =(R65-R64)*10000 -> -398789.44 | AO65: =(S65-S64) -> -409.17661
A66: 45748 | B66: ='GMV表-商品大类'!T69+B122 -> 278652.47 | C66: 42828.327 | D66: =B66+C66 -> 321480.8 | F66: 45748 | G66: ='毛利-收入组成'!AP66 -> 8940.1139 | H66: 5009720.8 | I66: =H66*1.06/10000 -> 531.0304 | J66: 2814.7816 | K66: =R66*1.06 -> -345.53085 | L66: =G66-I66+J66-K66 -> 11569.396 | M66: 4813.5165 | N66: =L66+M66 -> 16382.913 | P66: 45748 | Q66: =19493947.13/10000 -> 1949.3947 | R66: =-3259725.031109/10000 -> -325.9725 | S66: 387.84907 | V66: =Q66-R66+S66 -> 2663.2163 | W66: 377.8072 | Z66: =V66+W66 -> 3041.0235 | AB66: 45748 | AC66: =L66/B66 -> 0.041519087 | AD66: =M66/C66 -> 0.11239095 | AE66: =N66/D66 -> 0.050960781 | AG66: 45748 | AH66: =V66*1.06/L66 -> 0.24400662 | AI66: =W66*1.06/M66 -> 0.083198143 | AJ66: =Z66*1.06/N66 -> 0.19675896 | AL66: 45748 | AM66: =(Q66-Q65)*10000 -> -515040.15 | AN66: =(R66-R65)*10000 -> -345263.21 | AO66: =(S66-S65) -> 25.118159
A67: 45778 | B67: ='GMV表-商品大类'!T70+B123 -> 356718.11 | C67: 54421.447 | D67: =B67+C67 -> 411139.56 | F67: 45778 | G67: ='毛利-收入组成'!AP67 -> 11192.838 | H67: 6693457.8 | I67: =H67*1.06/10000 -> 709.50653 | J67: 3386.1306 | K67: =R67*1.06 -> -376.57449 | L67: =G67-I67+J67-K67 -> 14246.036 | M67: 6008.3066 | N67: =L67+M67 -> 20254.343 | P67: 45778 | Q67: =25241507.62/10000 -> 2524.1508 | R67: =-3552589.53177151/10000 -> -355.25895 | S67: 590.17286 | V67: =Q67-R67+S67 -> 3469.5826 | W67: 527.56413 | Z67: =V67+W67 -> 3997.1467 | AB67: 45778 | AC67: =L67/B67 -> 0.039936398 | AD67: =M67/C67 -> 0.11040329 | AE67: =N67/D67 -> 0.049263912 | AG67: 45778 | AH67: =V67*1.06/L67 -> 0.25816006 | AI67: =W67*1.06/M67 -> 0.093074142 | AJ67: =Z67*1.06/N67 -> 0.2091885 | AL67: 45778 | AM67: =(Q67-Q66)*10000 -> 5747560.5 | AN67: =(R67-R66)*10000 -> -292864.5 | AO67: =(S67-S66) -> 202.32378
A68: 45809 | B68: ='GMV表-商品大类'!T71+B124 -> 424209.96 | C68: 65823.461 | D68: =B68+C68 -> 490033.43 | F68: 45809 | G68: ='毛利-收入组成'!AP68 -> 14446.907 | H68: 8861461 | I68: =H68*1.06/10000 -> 939.31487 | J68: 3774.2859 | K68: =R68*1.06 -> -389.71032 | L68: =G68-I68+J68-K68 -> 17671.588 | M68: 7247.2979 | N68: =L68+M68 -> 24918.886 | P68: 45809 | Q68: =39303761.41/10000 -> 3930.3761 | R68: =-3676512.47794208/10000 -> -367.65125 | S68: 438.66133 | T68: 889.03 | U68: 220.17 | V68: =Q68-R68+S68-T68-U68 -> 3627.4887 | W68: 652.56245 | X68: 137.23 | Y68: 34.31 | Z68: =V68+(W68-X68-Y68) -> 4108.5112 | AB68: 45809 | AC68: =L68/B68 -> 0.041657645 | AD68: =M68/C68 -> 0.11010205 | AE68: =N68/D68 -> 0.0508514 | AG68: 45809 | AH68: =V68*1.06/L68 -> 0.21758871 | AI68: =(W68-X68-Y68)*1.06/M68 -> 0.070355021 | AJ68: =Z68*1.06/N68 -> 0.17476792 | AL68: 45809 | AM68: =(Q68-Q67)*10000 -> 14062254 | AN68: =(R68-R67)*10000 -> -123922.95 | AO68: =(S68-S67) -> -151.51153
A69: 45839 | B69: ='GMV表-商品大类'!T72+B125 -> 493155.86 | C69: 77849.085 | D69: =B69+C69 -> 571004.94 | F69: 45839 | G69: ='毛利-收入组成'!AP69 -> 16609.066 | H69: 10138585 | I69: =H69*1.06/10000 -> 1074.69 | J69: 4049.7735 | K69: =R69*1.06 -> -414.43103 | L69: =G69-I69+J69-K69 -> 19998.58 | M69: 8402.7163 | N69: =L69+M69 -> 28401.297 | P69: 45839 | Q69: =43474589.87/10000 -> 4347.459 | R69: =-3909726.72587872/10000 -> -390.97267 | S69: 289.98765 | V69: =Q69-R69+S69-T69-U69 -> 5028.4193 | W69: 881.5064 | Z69: =V69+W69 -> 5909.9257 | AB69: 45839 | AC69: =L69/B69 -> 0.040552252 | AD69: =M69/C69 -> 0.10793597 | AE69: =N69/D69 -> 0.049739143 | AG69: 45839 | AH69: =V69*1.06/L69 -> 0.26652514 | AI69: =W69*1.06/M69 -> 0.11120175 | AJ69: =Z69*1.06/N69 -> 0.22057166 | AL69: 45839 | AM69: =(Q69-Q68)*10000 -> 4170828.5 | AN69: =(R69-R68)*10000 -> -233214.25 | AO69: =(S69-S68) -> -148.67368
A70: 45870 | F70: 45870 | P70: 45870 | AB70: 45870 | AG70: 45870 | AL70: 45870
A71: 45901 | F71: 45901 | P71: 45901 | AB71: 45901 | AG71: 45901 | AL71: 45901
A72: 45931 | F72: 45931 | P72: 45931 | AB72: 45931 | AG72: 45931 | AL72: 45931
A73: 45962 | F73: 45962 | P73: 45962 | AB73: 45962 | AG73: 45962 | AL73: 45962
A74: 45992 | F74: 45992 | P74: 45992 | AB74: 45992 | AG74: 45992 | AL74: 45992
A76: 占比 | B76: =B69/D69 -> 0.86366303 | C76: =C69/D69 -> 0.13633697 | H76: =G77-I77 -> 431.57672 | I76: =G77-I77-K77+J77 -> 282.16578 | L76: =L69/N69 -> 0.70414322 | M76: =M69/N69 -> 0.29585678 | V76: =V69/Z69 -> 0.85084307 | AM76: =SUM(AM63:AM74) -> 43474590 | AN76: =SUM(AN63:AN74) -> -3909726.7 | AO76: =SUM(AO63:AO74) -> 289.98765
A77: 同期变动 | B77: =B69-B57 -> -114590.95 | C77: =C69-C57 -> 10062.498 | D77: =D69-D57 -> -104528.45 | G77: =G69-G57 -> -251.54142 | H77: =H69-H57 -> -6444510.8 | I77: =I69-I57 -> -683.11814 | J77: =J69-J57 -> -780.67014 | K77: =K69-K57 -> -631.25921 | L77: =L69-L57 -> 282.16578 | M77: =M69-M57 -> 1016.8694 | N77: =N69-N57 -> 1299.0351 | Q77: =Q69-Q57 -> 1522.7329 | R77: =R69-R57 -> -595.52755 | S77: =S69-S57 -> -55.721809 | T77: =T69-T57 -> 0 | U77: =U69-U57 -> 0 | V77: =V69-V57 -> 2062.5387 | W77: =W69-W57 -> 1796.0479 | X77: =X69-X57 -> 0 | ... Z77: =Z69-Z57 -> 3858.5865 | AO77: =AO76-S69 -> 0
A78: 变动比例 | B78: =B77/B57 -> -0.18855047 | C78: =C77/C57 -> 0.1484438 | D78: =D77/D57 -> -0.15473469 | G78: =G77/G57 -> -0.014918883 | H78: =H77/H57 -> -0.38861929 | I78: =I77/I57 -> -0.38861929 | J78: =J77/J57 -> -0.16161458 | K78: =K77/K57 -> -2.9113339 | L78: =L77/L57 -> 0.014311211 | M78: =M77/M57 -> 0.1376781 | N78: =N77/N57 -> 0.047930876 | R78: =Q77-R77 -> 2118.2605 | S78: =Q77-R77+S77 -> 2062.5387 | V78: =V77/V57 -> 0.69542201 | Z78: =Z77/Z57 -> 1.8810086
K79: =G77-I77-K77 -> 1062.8359 | L79: =L77-J77 -> 1062.8359
A80: 体内项目--葫芦藤衍生公司 | B80: GMV | C80: 收入（差额）-含税金额 | D80: 收入（差额）-不含税金额 | E80: 利润 | G80: 企业福利&襄阳福穗 | H80: GMV | I80: 收入（差额）-含税金额 | J80: 收入（差额）-不含税金额 | K80: 利润
A81: 44530 | B81: 199.78866 | C81: 51.885882 | D81: 48.948945 | E81: 38.006484 | G81: 44530 | H81: 0 | I81: 0 | J81: 0 | K81: 0
A82: 44561 | B82: 336.97535 | C82: 99.150341 | D82: 93.538058 | E82: 70.25 | G82: 44561 | H82: 0 | I82: 0 | J82: 0 | K82: 0 | Q82: =G77-Q77 -> -1774.2744 | S82: =Q77-R77+S77 -> 2062.5387
A83: 44562 | B83: 1374.1753 | C83: 708.69541 | D83: 668.58057 | E83: 187.75761 | G83: 44562 | H83: 1193.1893 | I83: 655.10541 | J83: 618.02397 | K83: 160.39838
A84: 44593 | B84: 1994.7 | C84: 948.85 | D84: 895.14151 | E84: 102.11 | G84: 44593 | H84: 1670.5 | I84: 895.37 | J84: 844.68868 | K84: 103.02
A85: 44621 | B85: 2843.8 | C85: 1330.59 | D85: 1255.2736 | E85: 44.96 | G85: 44621 | H85: 2432.89 | I85: 1265.12 | J85: 1193.5094 | K85: 57.23
A86: 44652 | B86: 4082.235 | C86: 1618.1164 | D86: 1527.99 | E86: -150.02026 | G86: 44652 | H86: 3308.722 | I86: 1531.8642 | J86: 1446.62 | K86: -130.2
A87: 44682 | B87: 6922.9577 | C87: 1960.5567 | D87: 1849.5818 | E87: -321.3635 | G87: 44682 | H87: 5697.6754 | I87: 1849.5439 | J87: 1744.8528 | K87: -297.74617
A88: 44713 | B88: 6843.5655 | C88: 2399.588 | D88: 2263.7623 | E88: -515.08559 | G88: 44713 | H88: 5265.6212 | I88: 2173.8273 | J88: 2050.7804 | K88: -582.31248
A89: 44743 | B89: 10499.791 | C89: 2807.8764 | D89: 2648.94 | E89: -805.11 | G89: 44743 | H89: 8122.8571 | I89: 2432.4562 | J89: 2294.77 | K89: -898.18
A90: 44774 | B90: 12096.444 | C90: 3477.86 | D90: 3281 | E90: -869.63 | G90: 44774 | H90: 9476.4443 | I90: 3031.335 | J90: 2859.75 | K90: -986.99
A91: 44805 | B91: 13434.896 | C91: 4614.0846 | D91: 4352.91 | E91: -850.89 | G91: 44805 | H91: 10172.275 | I91: 4014.432 | J91: 3787.2 | K91: -1070.2
A92: 44835 | B92: 18333.835 | C92: 5260.2818 | D92: 4962.53 | E92: -799.27 | G92: 44835 | H92: 14682.528 | I92: 4527.9066 | J92: 4271.61 | K92: -1115.61
A93: 44866 | B93: 19300.489 | C93: 5829.152 | D93: 5499.2 | E93: -888.83 | G93: 44866 | H93: 15235.021 | I93: 5080.3998 | J93: 4792.83 | K93: -1091.85
A94: 44896 | B94: 20765.91 | C94: 7004.9464 | D94: 6608.44 | E94: -1160.91 | G94: 44896 | H94: 16220.83 | I94: 6011.9066 | J94: 5671.61 | K94: -1413.81
... A96: 44958 | B96: 7275.8006 | C96: 2249.6399 | D96: 2118.8362 | E96: 597.92934 | G96: 44958 | H96: 6461.8703 | I96: 2106.8454 | J96: 1987.59 | K96: 565.364
A97: 44986 | B97: 10239.661 | C97: 2973.5557 | D97: 2799.681 | E97: 365.21191 | G97: 44986 | H97: 8178.5582 | I97: 2753.9542 | J97: 2598.07 | K97: =-428.92+(452+300) -> 323.08
A98: 45017 | B98: 16965.206 | C98: 3381.6409 | D98: 3180.2152 | E98: -115.89507 | G98: 45017 | H98: 11021.433 | I98: 3302.0378 | J98: 3115.13 | K98: =-413.51+(452+300-300) -> 38.49
A99: 45047 | B99: 25609.196 | C99: 3943.9878 | D99: 3699.7903 | E99: -480.00006 | G99: 45047 | H99: 14392.666 | I99: 3915.6718 | J99: 3694.03 | K99: =-644.695+(452+300-300)-561.668+561.668 -> -192.695
A100: 45078 | B100: 35436.727 | C100: 4738.2533 | D100: 4416.8293 | E100: -606.53558 | G100: 45078 | H100: 18109.606 | I100: 4828.5438 | J100: 4555.23 | K100: =-164.62-651.81/10000 -> -164.68518
A101: 45108 | B101: 50131.627 | C101: 5300.6635 | D101: 4925.3126 | E101: -889.85281 | G101: 45108 | H101: 20832.636 | I101: 5450.6578 | J101: 5142.13 | K101: =-295.471-131806.45/10000 -> -308.65164
A102: 45139 | B102: 65399.171 | C102: 6106.3185 | D102: 5488.1822 | E102: -990.76869 | G102: 45139 | H102: 23055.482 | I102: 6072.4432 | J102: 5728.72 | K102: =-545.53-162938.67/10000 -> -561.82387
...

Sheet 投资公司
A1: 2025年
A2: 类别 | B2: 调整博宽&黄石福桃等渠道电商毛利 | C2: 累计净利润 | D2: 1月利润 | E2: 2月利润 | F2: 3月利润 | G2: 4月利润 | H2: 5月利润 | I2: 6月利润 | J2: 7月利润 | K2: 8月利润 | L2: 9月利润 | M2: 10月利润 | N2: 11月利润 | O2: 12月利润
A3: 1、手游 | C3: =SUM(D3:O3) -> -27.65 | I3: 7.059 | J3: =-27.65-I3 -> -34.709 | P3: -27.65
A4: 2、网游 | C4: =SUM(D4:O4) -> 0
A5: 3、通信 | C5: =SUM(D5:O5) -> 0
A6: 4、网娱 | C6: =SUM(D6:O6) -> 232.934 | D6: 77.701 | E6: 6.228 | F6: 106.762 | G6: 78.746 | H6: 76.203 | I6: =281.088987-7.059-(38.674+377.647) -> -142.29101 | J6: =232.934-SUM(D6:I6) -> 29.585013 | P6: 232.934
A7: 5、生活服务 | C7: =SUM(D7:O7) -> 461.05 | I7: =38.674+377.647 -> 416.321 | J7: =461.05-I7 -> 44.729 | P7: 461.05
A8: 合计 | B8: =SUM(B3:B7) -> 0 | C8: =SUM(C3:C7) -> 666.334 | D8: =SUM(D3:D7) -> 77.701 | E8: =SUM(E3:E7) -> 6.228 | F8: =SUM(F3:F7) -> 106.762 | G8: =SUM(G3:G7) -> 78.746 | H8: =SUM(H3:H7) -> 76.203 | I8: =SUM(I3:I7) -> 281.08899 | ... O8: =SUM(O3:O7) -> 0 | P8: ='[37]简表底稿 (万元)'!$L$2 -> 666.334 | Q8: =P8-C8 -> 0
A10: 含税金额 | C10: =C8*1.06 -> 706.31404 | D10: =D8*1.06 -> 82.36306 | E10: =E8*1.06 -> 6.60168 | F10: =F8*1.06 -> 113.16772 | G10: =G8*1.06 -> 83.47076 | H10: =H8*1.06 -> 80.77518 | I10: =I8*1.06 -> 297.95433 | J10: =J8*1.06 -> 41.981314 | ... O10: =O8*1.06 -> 0
A12: 2024年
A13: 类别 | B13: 调整博宽&黄石福桃等渠道电商毛利 | C13: 累计净利润 | D13: 1月利润 | E13: 2月利润 | F13: 3月利润 | G13: 4月利润 | H13: 5月利润 | I13: 6月利润 | J13: 7月利润 | K13: 8月利润 | L13: 9月利润 | M13: 10月利润 | N13: 11月利润 | O13: 12月利润
A14: 1、手游
A15: 2、网游
A16: 3、通信
A17: 4、网娱 | C17: =SUM(D17:O17) -> 366.107 | D17: =377.983-2659414.53/10000 -> 112.04155 | E17: =191.57-3869946.72/10000 -> -195.42467 | F17: =-429.26--5370695.59/10000 -> 107.80956 | G17: =-29.559-2165911.16/10000 -> -246.15012 | H17: 96.61 | I17: -3.44 | J17: 191.09 | K17: 71.15 | L17: 20.14 | M17: 57.43 | N17: 209.28868 | O17: -54.438
A18: 5、生活服务
A19: 合计 | B19: =SUM(B14:B18) -> 0 | C19: =SUM(C14:C18) -> 366.107 | D19: =SUM(D14:D18) -> 112.04155 | E19: =SUM(E14:E18) -> -195.42467 | F19: =SUM(F14:F18) -> 107.80956 | G19: =SUM(G14:G18) -> -246.15012 | H19: =SUM(H14:H18) -> 96.61 | I19: =SUM(I14:I18) -> -3.44 | ... O19: =SUM(O14:O18) -> -54.438
A21: 含税金额 | C21: =C19*1.06 -> 388.07342 | D21: =D19*1.06 -> 118.76404 | E21: =E19*1.06 -> -207.15015 | F21: =F19*1.06 -> 114.27813 | G21: =G19*1.06 -> -260.91912 | H21: =H19*1.06 -> 102.4066 | I21: =I19*1.06 -> -3.6464 | J21: =J19*1.06 -> 202.5554 | ... O21: =O19*1.06 -> -57.70428
A23: 2023年
A24: 类别 | B24: 调整博宽&黄石福桃等渠道电商毛利 | C24: 累计净利润 | D24: 1月利润 | E24: 2月利润 | F24: 3月利润 | G24: 4月利润 | H24: 5月利润 | I24: 6月利润 | J24: 7月利润 | K24: 8月利润 | L24: 9月利润 | M24: 10月利润 | N24: 11月利润 | O24: 12月利润
A25: 1、手游
A26: 2、网游
A27: 3、通信
A28: 4、网娱 | C28: =SUM(D28:O28) -> 219.71 | D28: 98.863 | E28: 88.266 | F28: 112.98 | G28: -111.401 | H28: -41.707 | I28: -100.897 | J28: 160.729 | K28: 125.174 | L28: -208.57 | M28: 179.757 | N28: 53.982 | O28: -137.466
A29: 5、生活服务
A30: 合计 | B30: =SUM(B25:B29) -> 0 | C30: =SUM(C25:C29) -> 219.71 | F30: =SUM(F25:F29) -> 112.98 | G30: =SUM(G25:G29) -> -111.401 | H30: =SUM(H25:H29) -> -41.707 | I30: =SUM(I25:I29) -> -100.897 | J30: =SUM(J25:J29) -> 160.729 | K30: =SUM(K25:K29) -> 125.174 | L30: =SUM(L25:L29) -> -208.57 | M30: =SUM(M25:M29) -> 179.757 | ... O30: =SUM(O25:O29) -> -137.466
A32: 含税金额 | C32: =C30*1.06 -> 232.8926 | D32: =D30*1.06 -> 0 | E32: =E30*1.06 -> 0 | F32: =F30*1.06 -> 119.7588 | G32: =G30*1.06 -> -118.08506 | H32: =H30*1.06 -> -44.20942 | I32: =I30*1.06 -> -106.95082 | J32: =J30*1.06 -> 170.37274 | ... O32: =O30*1.06 -> -145.71396
B39: 公司全称 | C39: 剔除后利润2410 | D39: 剔除后利润2411 | E39: 剔除后利润2412
B40: 北京萌桃网络科技有限公司 | C40: -1030348.8 | D40: -903225.23 | E40: 891317.98 | F40: =E40-D40 -> 1794543.2
B41: 黄石长驱网络科技有限公司 | C41: -101116.56 | D41: -121183.48 | E41: -159339.02 | F41: =E41-D41 -> -38155.54
B42: 南京梦澄网络科技有限公司 | C42: 39450.92 | D42: 36003.91 | E42: 27371.62 | F42: =E42-D42 -> -8632.29
B43: 南京逐电网络科技有限公司 | C43: -2854.26 | D43: -2898.17 | E43: -11201.47 | F43: =E43-D43 -> -8303.3
B44: 长沙雷厉网络科技有限公司 | C44: -2098.94 | D44: -2283.59 | E44: -2283.59 | F44: =E44-D44 -> 0
B45: 长沙星合网络科技有限公司 | C45: 118205.04 | D45: 232964.01 | E45: 154874.19 | F45: =E45-D45 -> -78089.82
B46: 武汉双立网络科技有限公司 | C46: -483876.71 | D46: -558336.91 | E46: -671481.83 | F46: =E46-D46 -> -113144.92
B47: 武汉铭柏网络科技有限公司 | C47: 1101715.3 | D47: 1529010.8 | E47: 451698.26 | F47: =E47-D47 -> -1077312.6
B48: 武汉市萌想家网络科技有限公司 | C48: 0 | D48: 0 | E48: -47112.72 | F48: =E48-D48 -> -47112.72
B49: 重分类调整 | C49: -442821.91 | D49: 8007.07 | E49: 6588.28 | F49: =E49-D49 -> -1418.79
B52: 客户发展中心 | C52: 47.351 | D52: 69.186 | E52: 92.599 | F52: =E52-D52 -> 23.413
B53: 渠道线项目 | C53: -80.375 | D53: 21.806 | E53: 64.043 | F53: =E53-D53 -> 42.237
B54: 游戏电商项目 | C54: 244.284 | D54: 329.553 | E54: 209.465 | F54: =E54-D54 -> -120.088

Sheet GMV销售额波动分析（分月、年）
A1: 2025年 | B1: SP0001-网游 | C1: SP0005-手游 | D1: SP0002-通信 | E1: SP0003-网娱 | F1: SP0004-卡劵 | G1: SP0006-生活服务 | H1: 总计（含税） | I1: 体内公司GMV | J1: 月份 | K1: 2025年GMV | L1: 2024年GMV | M1: 同期增长
A2: 1月 | B2: 45102810 | C2: 75000597 | D2: 9435812.5 | E2: 2.0356185e+08 | F2: 3.6554639e+08 | G2: 277292.49 | H2: =SUM(B2:G2) -> 6.9892476e+08 | I2: =H2/10000-GMV销售平台占比!B16 -> 7.1304385e-10 | J2: 1月 | K2: =H2/100000000 -> 6.9892476 | L2: =H17/100000000 -> 8.3841662 | M2: =(K2-L2)/L2 -> -0.16637536 | N2: =K2-L2 -> -1.3949187
A3: 2月 | B3: 29914547 | C3: 33284884 | D3: 12224513 | E3: 1.8650532e+08 | F3: 2.8944267e+08 | G3: 697463.75 | H3: =SUM(B3:G3) -> 5.5206939e+08 | J3: 2月 | K3: =H3/100000000 -> 5.5206939 | L3: =H18/100000000 -> 7.6218049 | M3: =(K3-L3)/L3 -> -0.27567105
A4: 3月 | B4: 23250822 | C4: 38931285 | D4: 4582458.6 | E4: 1.8891607e+08 | F4: 4.1025231e+08 | G4: 50935.907 | H4: =SUM(B4:G4) -> 6.6598388e+08 | J4: 3月 | K4: =H4/100000000 -> 6.6598388 | L4: =H19/100000000 -> 6.6832889 | M4: =(K4-L4)/L4 -> -0.0035087704
A5: 4月 | B5: 26883010 | C5: 46615668 | D5: 3360143.8 | E5: 1.7304789e+08 | F5: 3.5350825e+08 | G5: 45091.202 | H5: =SUM(B5:G5) -> 6.0346005e+08 | J5: 4月 | K5: =H5/100000000 -> 6.0346005 | L5: =H20/100000000 -> 5.0345297 | M5: =(K5-L5)/L5 -> 0.19864235
A6: 5月 | B6: 37315216 | C6: 1.0025681e+08 | D6: 3366603.9 | E6: 1.7290566e+08 | F6: 2.90837e+08 | G6: 36996.619 | H6: =SUM(B6:G6) -> 6.0471829e+08 | J6: 5月 | K6: =H6/100000000 -> 6.0471829 | L6: =H21/100000000 -> 7.0552966 | M6: =(K6-L6)/L6 -> -0.1428875
A7: 6月 | B7: 44748189 | C7: 41902247 | D7: 2880591.8 | E7: 1.2474516e+08 | F7: 3.5477031e+08 | G7: 93346.506 | H7: =SUM(B7:G7) -> 5.6913985e+08 | J7: 6月 | K7: =H7/100000000 -> 5.6913985 | L7: =H22/100000000 -> 8.3802748 | M7: =(K7-L7)/L7 -> -0.32085777
A8: 7月 | B8: 40140017 | C8: 47381046 | D8: 2957178.4 | E8: 75125965 | F8: 4.6261523e+08 | G8: 2103107.7 | H8: =SUM(B8:G8) -> 6.3032255e+08 | J8: 7月 | K8: =H8/100000000 -> 6.3032255 | L8: =H23/100000000 -> 8.2004978 | M8: =(K8-L8)/L8 -> -0.23136063
A9: 8月 | H9: =SUM(B9:G9) -> 0 | J9: 8月 | K9: =H9/100000000 -> 0 | L9: =H24/100000000 -> 7.5165771 | M9: =(K9-L9)/L9 -> -1
A10: 9月 | H10: =SUM(B10:G10) -> 0 | J10: 9月 | K10: =H10/100000000 -> 0 | L10: =H25/100000000 -> 5.2618104 | M10: =(K10-L10)/L10 -> -1
A11: 10月 | H11: =SUM(B11:G11) -> 0 | J11: 10月 | K11: =H11/100000000 -> 0 | L11: =H26/100000000 -> 5.901137 | M11: =(K11-L11)/L11 -> -1
A12: 11月 | H12: =SUM(B12:G12) -> 0 | J12: 11月 | K12: =H12/100000000 -> 0 | L12: =H27/100000000 -> 6.1812962 | M12: =(K12-L12)/L12 -> -1
A13: 12月 | H13: =SUM(B13:G13) -> 0 | J13: 12月 | K13: =H13/100000000 -> 0 | L13: =H28/100000000 -> 6.0199264 | M13: =(K13-L13)/L13 -> -1
A14: 合计 | B14: =SUM(B2:B13) -> 2.4735461e+08 | C14: =SUM(C2:C13) -> 3.8337254e+08 | D14: =SUM(D2:D13) -> 38807302 | E14: =SUM(E2:E13) -> 1.1248079e+09 | F14: =SUM(F2:F13) -> 2.5269722e+09 | G14: =SUM(G2:G13) -> 3304234.2 | H14: =SUM(H2:H13) -> 4.3246188e+09 | J14: 合计（亿元） | K14: =SUM(K2:K13) -> 43.246188 | L14: =SUM(L2:L8) -> 51.359859 | M14: =(K14-L14)/L14 -> -0.1579769 | N14: =K14-L14 -> -8.1136713 | O14: =N14/L14 -> -0.1579769
J15: 累计数贴PPT37
A16: 2024年 | B16: SP0001-网游 | C16: SP0005-手游 | D16: SP0002-通信 | E16: SP0003-网娱 | F16: SP0004-卡劵 | G16: SP0006-生活服务 | H16: 总计（含税） | J16: 商品大类 | K16: 2024年 | L16: 2023年 | M16: 变动额 | N16: 变动率
A17: 1月 | B17: 1.6394352e+08 | C17: 72069322 | D17: 57651169 | E17: 2.2038104e+08 | F17: 3.2436856e+08 | G17: 3015.47 | H17: 8.3841662e+08 | J17: 网游 | K17: =B14/10000 -> 24735.461 | L17: =SUM(B32:B43)/10000 -> 204213.4 | M17: =K17-L17 -> -179477.94 | N17: =M17/L17 -> -0.87887445 | O17: =K17+K18 -> 63072.715 | P17: =L17+L18 -> 288229.3
A18: 2月 | B18: 1.2902059e+08 | C18: 78670926 | D18: 51869185 | E18: 2.0630623e+08 | F18: 2.9632854e+08 | G18: -14984.47 | H18: 7.6218049e+08 | J18: 手游 | K18: =C14/10000 -> 38337.254 | L18: =SUM(C32:C43)/10000 -> 84015.899 | M18: =K18-L18 -> -45678.645 | N18: =M18/L18 -> -0.54369049 | P18: =(O17-P17)/P17 -> -0.78117175
A19: 3月 | B19: 40868843 | C19: 40313324 | D19: 61579069 | E19: 2.4007575e+08 | F19: 2.8386047e+08 | G19: 1631435.1 | H19: 6.6832889e+08 | J19: 通信 | K19: =D14/10000 -> 3880.7302 | L19: =SUM(D32:D43)/10000 -> 212342.83 | M19: =K19-L19 -> -208462.1 | N19: =M19/L19 -> -0.98172422
A20: 4月 | B20: 36836160 | C20: 30957288 | D20: 31064079 | E20: 2.3861802e+08 | F20: 1.659334e+08 | G20: 44022.467 | H20: 5.0345297e+08 | J20: 网娱 | K20: =E14/10000 -> 112480.79 | L20: =SUM(E32:E43)/10000 -> 505603.59 | M20: =K20-L20 -> -393122.8 | N20: =M20/L20 -> -0.77753166
A21: 5月 | B21: 36434632 | C21: 80871997 | D21: 23162770 | E21: 2.994851e+08 | F21: 2.6579687e+08 | G21: -221706.87 | H21: 7.0552966e+08 | J21: 生活服务 | K21: =(F14+G14)/10000 -> 253027.64 | L21: =SUM(F32:G43)/10000 -> 554277.85 | M21: =K21-L21 -> -301250.21 | N21: =M21/L21 -> -0.54350036
A22: 6月 | B22: 77715917 | C22: 92084688 | D22: 14168628 | E22: 3.4860498e+08 | F22: 3.052408e+08 | G22: 212456.67 | H22: 8.3802748e+08 | J22: 总计（万元） | K22: =SUM(K17:K21) -> 432461.88 | L22: =SUM(L17:L21) -> 1560453.6 | M22: =SUM(M17:M21) -> -1127991.7 | N22: =M22/L22 -> -0.72286143
A23: 7月 | B23: 83089797 | C23: 1.3250714e+08 | D23: 14913498 | E23: 2.4546108e+08 | F23: 3.3679378e+08 | G23: 7284483.8 | H23: 8.2004978e+08
A24: 8月 | B24: 49122371 | C24: 66704878 | D24: 25481143 | E24: 3.0002115e+08 | F24: 3.0906987e+08 | G24: 1258291.4 | H24: 7.5165771e+08
A25: 9月 | B25: 29245115 | C25: 48236433 | D25: 12906205 | E25: 2.2928796e+08 | F25: 2.0652896e+08 | G25: -23631.13 | H25: 5.2618104e+08
A26: 10月 | B26: 30810565 | C26: 55595035 | D26: 9471714.6 | E26: 2.3255981e+08 | F26: 2.6141187e+08 | G26: 264707.59 | H26: 5.901137e+08
A27: 11月 | B27: 24768660 | C27: 61722499 | D27: 6958838.9 | E27: 2.5892265e+08 | F27: 2.656238e+08 | G27: 133170.18 | H27: 6.1812962e+08
A28: 12月 | B28: 17633355 | C28: 34982091 | D28: 6161395.9 | E28: 2.6412947e+08 | F28: 2.7877715e+08 | G28: 309180.8 | H28: 6.0199264e+08
A29: 合计 | B29: =SUM(B17:B28) -> 7.1948953e+08 | C29: =SUM(C17:C28) -> 7.9471562e+08 | D29: =SUM(D17:D28) -> 3.153877e+08 | E29: =SUM(E17:E28) -> 3.0838533e+09 | F29: =SUM(F17:F28) -> 3.2997341e+09 | G29: =SUM(G17:G28) -> 10880441 | H29: =SUM(H17:H28) -> 8.2240606e+09
A31: 2023年 | B31: SP0001-网游 | C31: SP0005-手游 | D31: SP0002-通信 | E31: SP0003-网娱 | F31: SP0004-卡劵 | G31: SP0006-生活服务 | H31: 总计（含税）
A32: 1月 | B32: 1.0755749e+08 | C32: 1.2230208e+08 | D32: 2.927875e+08 | E32: 4.8836984e+08 | F32: 3.2916948e+08 | G32: 5629439.6 | H32: =SUM(B32:G32) -> 1.3458158e+09
A33: 2月 | B33: 86491645 | C33: 48095782 | D33: 3.841738e+08 | E33: 4.5017964e+08 | F33: 3.5004372e+08 | G33: 7076.29 | H33: =SUM(B33:G33) -> 1.3189917e+09
A34: 3月 | B34: 1.088094e+08 | C34: 67960161 | D34: 4.0696017e+08 | E34: =481032330.11-13500000 -> 4.6753233e+08 | F34: 4.8239142e+08 | G34: -551189.73 | H34: =SUM(B34:G34) -> 1.5331023e+09
A35: 4月 | B35: 2.050828e+08 | C35: 45919678 | D35: 1.4908958e+08 | E35: =398767570-12500000 -> 386267570 | F35: 4.6616905e+08 | G35: 4267.31 | H35: =SUM(B35:G35) -> 1.2525329e+09
A36: 5月 | B36: 3.3263003e+08 | C36: 1.0672384e+08 | D36: 1.4554824e+08 | E36: 3.4806915e+08 | F36: 5.457605e+08 | G36: -17436.15 | H36: =SUM(B36:G36) -> 1.4787143e+09
A37: 6月 | B37: 2.8460326e+08 | C37: 38830643 | D37: 1.8696408e+08 | E37: 4.0582857e+08 | F37: 6.5744036e+08 | G37: 2100.07 | H37: =SUM(B37:G37) -> 1.573669e+09
A38: 7月 | B38: 2.1237629e+08 | C38: 68821147 | D38: 1.2591962e+08 | E38: 3.5418136e+08 | F38: 5.528262e+08 | G38: 10513.11 | H38: =SUM(B38:G38) -> 1.3141351e+09
A39: 8月 | B39: 2.0523625e+08 | C39: 1.1420637e+08 | D39: 1.234218e+08 | E39: 4.1823418e+08 | F39: 6.1102003e+08 | G39: 2183.91 | H39: =SUM(B39:G39) -> 1.4721208e+09
A40: 9月 | B40: 2.1353486e+08 | C40: 51971549 | D40: 97829884 | E40: 3.9707166e+08 | F40: 4.9935928e+08 | G40: 6539.06 | H40: =SUM(B40:G40) -> 1.2597738e+09
A41: 10月 | B41: 89061955 | C41: 36377220 | D41: 72310873 | E41: 3.9956302e+08 | F41: 3.6598322e+08 | G41: -70181.51 | H41: =SUM(B41:G41) -> 9.632261e+08
A42: 11月 | B42: 1.0502672e+08 | C42: 94398013 | D42: 80242668 | E42: =538146990.5-16000000 -> 5.2214699e+08 | F42: 3.4343478e+08 | G42: -71757.87 | H42: =SUM(B42:G42) -> 1.1451774e+09
A43: 12月 | B43: 91723338 | C43: 44552509 | D43: 58180122 | E43: 4.1859163e+08 | F43: 3.3423897e+08 | G43: -10103.21 | H43: =SUM(B43:G43) -> 9.4727646e+08
A44: 合计 | B44: =SUM(B32:B43) -> 2.042134e+09 | C44: =SUM(C32:C43) -> 8.4015899e+08 | D44: =SUM(D32:D43) -> 2.1234283e+09 | E44: =SUM(E32:E43) -> 5.0560359e+09 | F44: =SUM(F32:F43) -> 5.537837e+09 | G44: =SUM(G32:G43) -> 4941450.9 | H44: =SUM(H32:H43) -> 1.5604536e+10
A46: 2022年 | B46: SP0001-网游 | C46: SP0005-手游 | D46: SP0002-通信 | E46: SP0003-网娱 | F46: SP0004-卡劵 | G46: SP0006-生活服务 | H46: 总计（含税）
A47: 1月 | B47: 1.0628656e+08 | C47: 49334662 | D47: 4.1149968e+08 | E47: 3.2432045e+08 | F47: 1.7626142e+08 | G47: 894328.11 | H47: =SUM(B47:G47) -> 1.0685971e+09
A48: 2月 | B48: 81731964 | C48: 59033084 | D48: 3.1152277e+08 | E48: 2.5233803e+08 | F48: 1.5005242e+08 | G48: 856069.92 | H48: =SUM(B48:G48) -> 8.5553434e+08
A49: 3月 | B49: 68949705 | C49: 52199439 | D49: 428174820 | E49: 4.4380459e+08 | F49: 3.2611044e+08 | G49: 578178.04 | H49: =SUM(B49:G49) -> 1.3198172e+09
A50: 4月 | B50: 82097862 | C50: 59964831 | D50: 4.5294442e+08 | E50: =361973606.9-12300000 -> 3.4967361e+08 | F50: 2.615683e+08 | G50: 44980.76 | H50: =SUM(B50:G50) -> 1.206294e+09
A51: 5月 | B51: 55852183 | C51: 36339220 | D51: 5.3111e+08 | E51: =400628075.79-9810000 -> 3.9081808e+08 | F51: 3.2527759e+08 | G51: -446223.78 | H51: =SUM(B51:G51) -> 1.3389509e+09
A52: 6月 | B52: =59490703.87-254581.5 -> 59236122 | C52: 47835531 | D52: 4.8364974e+08 | E52: =503007520.016201+254581.5 -> 5.032621e+08 | F52: 3.4107339e+08 | G52: 552492.09 | H52: =SUM(B52:G52) -> 1.4356094e+09
A53: 7月 | B53: 66359182 | C53: 60352823 | D53: 4.1179453e+08 | E53: 3.909996e+08 | F53: 2.7382979e+08 | G53: 291083.16 | H53: =SUM(B53:G53) -> 1.203627e+09
A54: 8月 | B54: 55137037 | C54: 38587463 | D54: 3.8654479e+08 | E54: 5.1219403e+08 | F54: 3.4153222e+08 | G54: 391988.85 | H54: =SUM(B54:G54) -> 1.3343875e+09
A55: 9月 | B55: 59130089 | C55: 46932898 | D55: 4.931765e+08 | E55: 6.0488792e+08 | F55: 2.8353468e+08 | G55: 15737.1 | H55: =SUM(B55:G55) -> 1.4876778e+09
A56: 10月 | B56: 74161421 | C56: 56402488 | D56: 4.3886806e+08 | E56: 5.1416646e+08 | F56: 3.4694464e+08 | G56: 46382.15 | H56: =SUM(B56:G56) -> 1.4305895e+09
A57: 11月 | B57: 70812756 | C57: 1.0385444e+08 | D57: 4.589211e+08 | E57: 7.0039856e+08 | F57: 4.1465496e+08 | G57: 7416.82 | H57: =SUM(B57:G57) -> 1.7486492e+09
A58: 12月 | B58: 81908478 | C58: 81317262 | D58: 3.6009275e+08 | E58: 7.7708158e+08 | F58: 4.1054812e+08 | G58: 1747578.1 | H58: =SUM(B58:G58) -> 1.7126958e+09
A59: 合计 | B59: =SUM(B47:B58) -> 8.6166336e+08 | C59: =SUM(C47:C58) -> 6.9215414e+08 | D59: =SUM(D47:D58) -> 5.1682992e+09 | E59: =SUM(E47:E58) -> 5.763945e+09 | F59: =SUM(F47:F58) -> 3.651388e+09 | G59: =SUM(G47:G58) -> 4980011.3 | H59: =SUM(H47:H58) -> 1.614243e+10
A61: 2021年 | B61: SP0001-网游 | C61: SP0005-手游 | D61: SP0002-通信 | E61: SP0003-网娱 | F61: SP0004-卡劵 | G61: SP0006-生活服务 | H61: 总计（含税）
A62: 1月 | B62: 98172535 | C62: 37487307 | D62: 7.3685445e+08 | E62: 2.6771902e+08 | F62: 1.254799e+08 | G62: 9730 | H62: =SUM(B62:G62) -> 1.2657229e+09
A63: 2月 | B63: 1.1438706e+08 | C63: 56178179 | D63: 7.7106765e+08 | E63: 2.538512e+08 | F63: 69655650 | G63: -174.89 | H63: =SUM(B63:G63) -> 1.2651396e+09
A64: 3月 | B64: 70384911 | C64: 47302805 | D64: 1.1137733e+09 | E64: 2.8416e+08 | F64: 1.5607186e+08 | G64: 5272.5 | H64: =SUM(B64:G64) -> 1.6716982e+09
A65: 4月 | B65: 68783211 | C65: 52890400 | D65: 1.0091175e+09 | E65: 3.3260077e+08 | F65: 1.0181567e+08 | G65: 12505.89 | H65: =SUM(B65:G65) -> 1.56522e+09
A66: 5月 | B66: 71144738 | C66: 75569781 | D66: 1.2955131e+09 | E66: 4.0443049e+08 | F66: 95654370 | G66: 1266214.1 | H66: =SUM(B66:G66) -> 1.9435787e+09
A67: 6月 | B67: 57392749 | C67: 59049683 | D67: 1.4220239e+09 | E67: 6.0471742e+08 | F67: 1.2070682e+08 | G67: 4245818 | H67: =SUM(B67:G67) -> 2.2681364e+09
A68: 7月 | B68: 76256396 | C68: 79506146 | D68: 1.4709175e+09 | E68: 4.8060161e+08 | F68: 92196914 | G68: 2850602.4 | H68: =SUM(B68:G68) -> 2.2023291e+09
A69: 8月 | B69: 64988388 | C69: 71531282 | D69: 1.8537292e+09 | E69: 5.7744733e+08 | F69: 1.1804239e+08 | G69: 2012128.5 | H69: =SUM(B69:G69) -> 2.6877508e+09
A70: 9月 | B70: 47999699 | C70: 37566406 | D70: 8.6568692e+08 | E70: 6.5861575e+08 | F70: 1.6533814e+08 | G70: 1919602.2 | H70: =SUM(B70:G70) -> 1.7771265e+09
A71: 10月 | B71: 50055574 | C71: 36047801 | D71: 7.5021656e+08 | E71: 4.2225629e+08 | F71: 1.5752591e+08 | G71: 20933.32 | H71: =SUM(B71:G71) -> 1.4161231e+09
A72: 11月 | B72: 54761540 | C72: 19889222 | D72: 9.2817321e+08 | E72: 5.997526e+08 | F72: 1.7672572e+08 | G72: 4650008.3 | H72: =SUM(B72:G72) -> 1.7839523e+09
A73: 12月 | B73: 70567624 | C73: 79920456 | D73: 6.398813e+08 | E73: 6.9189446e+08 | F73: 1.5722498e+08 | G73: 1049442 | H73: =SUM(B73:G73) -> 1.6405383e+09 | I73: =H119-'[32]GMV+收入成本（改）'!$BA$7 -> #REF!
A74: 合计 | B74: =SUM(B62:B73) -> 8.4489442e+08 | C74: =SUM(C62:C73) -> 6.5293947e+08 | D74: =SUM(D62:D73) -> 1.2856955e+10 | E74: =SUM(E62:E73) -> 5.5780469e+09 | F74: =SUM(F62:F73) -> 1.5364383e+09 | G74: =SUM(G62:G73) -> 18042082 | H74: =SUM(H62:H73) -> 2.1487316e+10
D76: =D69-D54 -> 1.4671845e+09
A81: 2024年 | B81: SP0001-网游 | C81: SP0005-手游 | D81: SP0002-通信 | E81: SP0003-网娱 | F81: SP0004-卡劵 | G81: SP0006-生活服务 | H81: 合计
A82: GMV交易 | B82: =(B14)/10000 -> 24735.461 | C82: =(C14)/10000 -> 38337.254 | D82: =(D14)/10000 -> 3880.7302 | E82: =(E14)/10000 -> 112480.79 | F82: =(F14)/10000 -> 252697.22 | G82: =(G14)/10000 -> 330.42342 | H82: =SUM(B82:G82) -> 432461.88
A83: 关联交易 | B83: =B104/10000 -> 3515.9332 | C83: =C104/10000 -> 4560.9279 | D83: =D104/10000 -> 2936.0173 | E83: =E104/10000 -> 6034.5812 | F83: =F104/10000 -> 13113.039 | G83: =G104/10000 -> 0.0027 | H83: =SUM(B83:G83) -> 30160.502
A84: 总交易 | B84: =B82+B83 -> 28251.394 | C84: =C82+C83 -> 42898.182 | D84: =D82+D83 -> 6816.7475 | E84: =E82+E83 -> 118515.37 | F84: =F82+F83 -> 265810.25 | G84: =G82+G83 -> 330.42612 | H84: =SUM(B84:G84) -> 462622.38
A85: 关联交易占比 | B85: =B83/B84 -> 0.12445167 | C85: =C83/C84 -> 0.10631984 | D85: =D83/D84 -> 0.43070648 | E85: =E83/E84 -> 0.05091813 | F85: =F83/F84 -> 0.04933233 | G85: =G83/G84 -> 8.1712668e-06 | H85: =H83/H84 -> 0.065194645
A86: GMV交易占比 | B86: =B82/B84 -> 0.87554833 | C86: =C82/C84 -> 0.89368016 | D86: =D82/D84 -> 0.56929352 | E86: =E82/E84 -> 0.94908187 | F86: =F82/F84 -> 0.95066767 | G86: =G82/G84 -> 0.99999183 | H86: =H82/H84 -> 0.93480536
A90: 关联交易
A91: 2024年 | B91: SP0001-网游 | C91: SP0005-手游 | D91: SP0002-通信 | E91: SP0003-网娱 | F91: SP0004-卡劵 | G91: SP0006-生活服务 | H91: 总计（含税）
A92: 1月 | B92: 35159332 | C92: 45609279 | D92: 29360173 | E92: 60345812 | F92: 1.3113039e+08 | G92: 27 | H92: =SUM(B92:G92) -> 3.0160502e+08
A93: 2月 | H93: =SUM(B93:G93) -> 0
A94: 3月 | H94: =SUM(B94:G94) -> 0
A95: 4月 | H95: =SUM(B95:G95) -> 0
A96: 5月 | H96: =SUM(B96:G96) -> 0
A97: 6月 | H97: =SUM(B97:G97) -> 0
A98: 7月 | H98: =SUM(B98:G98) -> 0
A99: 8月 | H99: =SUM(B99:G99) -> 0
A100: 9月 | H100: =SUM(B100:G100) -> 0
A101: 10月 | H101: =SUM(B101:G101) -> 0
A102: 11月 | H102: =SUM(B102:G102) -> 0
A103: 12月 | H103: =SUM(B103:G103) -> 0
A104: 合计 | B104: =SUM(B92:B103) -> 35159332 | C104: =SUM(C92:C103) -> 45609279 | D104: =SUM(D92:D103) -> 29360173 | E104: =SUM(E92:E103) -> 60345812 | F104: =SUM(F92:F103) -> 1.3113039e+08 | G104: =SUM(G92:G103) -> 27 | H104: =SUM(H92:H103) -> 3.0160502e+08
A107: 2023年 | B107: SP0001-网游 | C107: SP0005-手游 | D107: SP0002-通信 | E107: SP0003-网娱 | F107: SP0004-卡劵 | G107: SP0006-生活服务 | H107: 总计（含税）
A108: 1月 | B108: 61439316 | C108: 49841697 | D108: 21127312 | E108: 2.584577e+08 | F108: 86543610 | H108: =SUM(B108:G108) -> 477409631
A109: 2月 | B109: 40014907 | C109: 27864078 | D109: 25373751 | E109: 2.5892492e+08 | F109: 87178896 | H109: =SUM(B109:G109) -> 4.3935656e+08
A110: 3月 | B110: 56303318 | C110: 25086306 | D110: 21896134 | E110: =269560159.07+13500000 -> 2.8306016e+08 | F110: 1.2501429e+08 | H110: =SUM(B110:G110) -> 5.1136021e+08
A111: 4月 | B111: 71590763 | C111: 29189657 | D111: 19743273 | E111: 2.3300655e+08 | F111: 1.7781558e+08 | H111: =SUM(B111:G111) -> 5.3134582e+08
A112: 5月 | B112: 84680576 | C112: 37409990 | D112: 25699958 | E112: 1.812661e+08 | F112: 2.0459329e+08 | H112: =SUM(B112:G112) -> 5.3364992e+08
A113: 6月 | B113: 65349871 | C113: 21288750 | D113: 72965665 | E113: 2.0380316e+08 | F113: 2.7063261e+08 | H113: =SUM(B113:G113) -> 6.3404006e+08
...

Sheet GMV销售平台占比
A1: 2025年
A2: 平台 | B2: 1月 | C2: 2月 | D2: 3月 | E2: 4月 | F2: 5月 | G2: 6月 | H2: 7月 | I2: 8月 | J2: 9月 | K2: 10月 | L2: 11月 | M2: 12月 | N2: 合计 | O2: 平台GMV占比 | Q2: 平台 | R2: 2025年 | S2: 2024年 | T2: 2023年 | U2: 2022年
A3: 福禄开放平台 | B3: 55063.067 | C3: 45120.512 | D3: 57418.92 | E3: 51803.522 | F3: 45322.133 | G3: 43295.323 | H3: 48615.93 | N3: =(SUM(B3:M3)) -> 346639.41 | O3: =ROUND(N3/$N$16,4) -> 0.8015 | Q3: TOB | R3: =R13/Y13 -> 0.81538664 | S3: =R14/Y14 -> 0.6902932 | T3: =R15/Y15 -> 0.69689837 | U3: =R16/Y16 -> 0.67893398
A4: 福游云平台 | E4: 31.579643 | F4: 705.67017 | G4: 2546.6727 | H4: 2700.307 | N4: =(SUM(B4:M4)) -> 5984.2295 | O4: =ROUND(N4/$N$16,4) -> 0.0138 | Q4: 京东 | R4: =S13/Y13 -> 0.0043819835 | S4: =S14/Y14 -> 0.086967994 | T4: =S15/Y15 -> 0.10181272 | U4: =S16/Y16 -> 0.12832323
A5: 京东 | B5: 190.33022 | C5: 199.69965 | D5: 194.03104 | E5: 183.95279 | F5: 467.27444 | G5: 658.6546 | H5: 1.0980527 | N5: =(SUM(B5:M5)) -> 1895.0408 | O5: =ROUND(N5/$N$16,4) -> 0.0044 | P5: =O5+O6+O7 -> 0.0385 | Q5: 天猫 | R5: =T13/Y13 -> 0.030418994 | S5: =T14/Y14 -> 0.055586614 | T5: =T15/Y15 -> 0.051617994 | U5: =T16/Y16 -> 0.063652707
A6: 天猫 | B6: 2049.7325 | C6: 1846.0403 | D6: 1706.0095 | E6: 1664.0018 | F6: 2202.8411 | G6: 1977.3084 | H6: 1709.1216 | N6: =(SUM(B6:M6)) -> 13155.055 | O6: =ROUND(N6/$N$16,4) -> 0.0304 | Q6: 拼多多 | R6: =U13/Y13 -> 0.0036640109 | S6: =U14/Y14 -> 0.003297438 | T6: =U15/Y15 -> 0.0036902897 | U6: =U16/Y16 -> 0.013988165
A7: 拼多多 | B7: 230.92896 | C7: 199.5126 | D7: 226.99423 | E7: 171.59552 | F7: 210.09979 | G7: 259.57187 | H7: 285.84206 | N7: =(SUM(B7:M7)) -> 1584.545 | O7: =ROUND(N7/$N$16,4) -> 0.0037 | Q7: 支付宝小程序 | R7: =V13/Y13 -> 0.097419315 | S7: =V14/Y14 -> 0.084597643 | T7: =V15/Y15 -> 0.067331178 | U7: =V16/Y16 -> 0.030087931
A8: 支付宝小程序 | B8: 7907.5419 | C8: 5765.9562 | D8: 5728.9415 | E8: 4580.5479 | F8: 4494.4352 | G8: 6285.4866 | H8: 7367.2304 | N8: =(SUM(B8:M8)) -> 42130.14 | O8: =ROUND(N8/$N$16,4) -> 0.0974 | Q8: 抖快 | R8: =W13/Y13 -> 0.033919783 | S8: =W14/Y14 -> 0.042282233 | T8: =W15/Y15 -> 0.044596246 | U8: =W16/Y16 -> 0.024833133
A9: 抖音 | B9: 3623.411 | C9: 1339.3877 | D9: 547.55514 | E9: 899.18485 | F9: 6022.9674 | G9: 718.47917 | H9: 1363.9833 | N9: =(SUM(B9:M9)) -> 14514.968 | O9: =ROUND(N9/$N$16,4) -> 0.0336 | P9: =O9+O10 -> 0.034 | Q9: 其他 | R9: =X13/Y13 -> 0.014809272 | S9: =X14/Y14 -> 0.036974874 | T9: =X15/Y15 -> 0.0340532 | U9: =X16/Y16 -> 0.32106602
A10: 快手 | B10: 0 | C10: 0 | D10: 0 | E10: 35.226567 | F10: 27.489975 | G10: 23.483136 | H10: 67.845025 | N10: =(SUM(B10:M10)) -> 154.0447 | O10: =ROUND(N10/$N$16,4) -> 0.0004 | Q10: 小计 | R10: =SUM(R3:R9) -> 1 | S10: =SUM(S3:S9) -> 1 | T10: =SUM(T3:T9) -> 1 | U10: =SUM(U3:U9) -> 1.2608852
A11: 微信 | B11: 0.00845142 | C11: 0.00939968 | D11: 1.9206678 | E11: 3.5007104 | F11: 7.2964773 | G11: 3.3149819 | H11: 32.526796 | N11: =(SUM(B11:M11)) -> 48.577485 | O11: =ROUND(N11/$N$16,4) -> 0.0001
A12: 第三方平台 | B12: 790.75542 | C12: 704.81211 | D12: 742.65797 | E12: 935.42259 | F12: 969.39961 | G12: 1099.4609 | H12: 858.72859 | N12: =(SUM(B12:M12)) -> 6101.2371 | O12: =ROUND(N12/$N$16,4) -> 0.0141 | Q12: 渠道大类 | R12: TOB | S12: 京东 | T12: 天猫 | U12: 拼多多 | V12: 支付宝小程序 | W12: 抖快 | X12: 第三方B2B2C | Y12: 合计（万元） | Z12: TOC | AA12: 验算
A13: 充值频道 | B13: 22.783026 | C13: 19.475482 | D13: 20.449559 | E13: 20.691139 | F13: 16.109016 | G13: 29.63618 | H13: 18.880263 | N13: =(SUM(B13:M13)) -> 148.02466 | O13: =ROUND(N13/$N$16,4) -> 0.0003 | Q13: 2025年 | R13: =N3+N4 -> 352623.64 | S13: =N5 -> 1895.0408 | T13: =N6 -> 13155.055 | U13: =N7 -> 1584.545 | V13: =N8 -> 42130.14 | W13: =N9+N10 -> 14669.013 | X13: =Y13-SUM(R13:W13) -> 6404.4457 | Y13: =N16 -> 432461.88 | Z13: =Y13-R13 -> 79838.239 | AA13: =Y13-'GMV表-商品大类'!F85 -> -5.0058588e-09
A14: 百度小程序 | B14: 0.00039 | C14: 0.00499048 | D14: 0.00124 | E14: 0.0007 | F14: 0.00499048 | G14: 0 | H14: 0 | N14: =(SUM(B14:M14)) -> 0.01231096 | O14: =ROUND(N14/$N$16,4) -> 0 | Q14: 2024年 | R14: =N21 -> 354533.62 | S14: =N22 -> 44666.639 | T14: =N23 -> 28549.207 | U14: =N24 -> 1693.5595 | V14: =N25 -> 43449.23 | W14: =N26+N27 -> 21716.095 | X14: =Y14-SUM(R14:W14) -> 18990.243 | Y14: =N34 -> 513598.59 | Z14: =Y14-R14 -> 159064.97 | AA14: =Y14-'GMV表-商品大类'!F84 -> 1.9790605e-09
A15: mall商城 | B15: 13.916859 | C15: 11.529193 | D15: 10.90678 | E15: 16.779002 | F15: 26.107432 | G15: 16.593748 | H15: 10.761049 | N15: =(SUM(B15:M15)) -> 106.59406 | O15: =ROUND(N15/$N$16,4) -> 0.0002 | Q15: 2023年 | R15: =N39 -> 684142.42 | S15: =N40 -> 99949.157 | T15: =N41 -> 50673.185 | U15: =N42 -> 3622.7431 | V15: =N43 -> 66098.756 | W15: =N44+N45 -> 43779.962 | X15: =Y15-SUM(R15:W15) -> 33429.895 | Y15: =N53 -> 981696.12 | Z15: =Y15-R15 -> 297553.7 | AA15: =Y15-'GMV表-商品大类'!F83 -> 0.00060700206
A16: 合计(单位：万元） | B16: =SUM(B3:B15) -> 69892.476 | C16: =SUM(C3:C15) -> 55206.939 | D16: =SUM(D3:D15) -> 66598.388 | E16: =SUM(E3:E15) -> 60346.005 | F16: =SUM(F3:F15) -> 60471.829 | G16: =SUM(G3:G15) -> 56913.985 | H16: =SUM(H3:H15) -> 63032.255 | I16: =SUM(I3:I15) -> 0 | ... O16: =SUM(O3:O15) -> 0.9999 | Q16: 2022年 | R16: =N57 -> 1095964.4 | S16: =N58 -> 207144.88 | T16: =N59 -> 102750.94 | U16: =N60 -> 22580.296 | V16: =N61 -> 48569.231 | W16: =N62+N63 -> 40086.711 | X16: =Y16-SUM(R16:R16) -> 518278.57 | Y16: =N71 -> 1614243 | Z16: =Y16-R16 -> 518278.57 | AA16: =Y16-'GMV表-商品大类'!F82 -> -2.4028122e-07
Q17: 变动 | R17: =R13-R14 -> -1909.9784 | S17: =S13-S14 -> -42771.598 | T17: =T13-T14 -> -15394.151 | U17: =U13-U14 -> -109.0145 | V17: =V13-V14 -> -1319.0906 | W17: =W13-W14 -> -7047.0822 | X17: =X13-X14 -> -12585.798 | Y17: =Y13-Y14 -> -81136.713
R18: =R17/R14 -> -0.0053872986 | S18: =S17/S14 -> -0.95757369 | T18: =T17/T14 -> -0.53921468 | U18: =U17/U14 -> -0.064370041 | V18: =V17/V14 -> -0.030359354 | W18: =W17/W14 -> -0.32450963 | X18: =X17/X14 -> -0.66275073 | Y18: =Y17/Y14 -> -0.1579769
A19: 2024年
A20: 平台 | B20: 1月 | C20: 2月 | D20: 3月 | E20: 4月 | F20: 5月 | G20: 6月 | H20: 7月 | I20: 8月 | J20: 9月 | K20: 10月 | L20: 11月 | M20: 12月 | N20: 合计 | O20: 平台GMV占比 | Q20: 平台 | R20: TOB | S20: 京东 | T20: 天猫 | U20: 拼多多 | V20: 支付宝小程序 | W20: 抖快 | X20: 其他 | Y20: 小计
A21: 福禄开放平台 | B21: 57380.332 | C21: 49703.168 | D21: 52869.612 | E21: 39772.322 | F21: 48186.498 | G21: 55691.42 | H21: 50930.264 | I21: 57429.588 | J21: 43578.641 | K21: 46612.011 | L21: 47834.971 | M21: 50236.751 | N21: =SUM(B21:H21) -> 354533.62 | O21: =ROUND(N21/$N$34,4) -> 0.6903 | Q21: 2025年 | R21: =R13/$Y$13 -> 0.81538664 | S21: =S13/$Y$13 -> 0.0043819835 | T21: =T13/$Y$13 -> 0.030418994 | U21: =U13/$Y$13 -> 0.0036640109 | V21: =V13/$Y$13 -> 0.097419315 | W21: =W13/$Y$13 -> 0.033919783 | X21: =X13/$Y$13 -> 0.014809272 | Y21: =SUM(R21:X21) -> 1
A22: 京东 | B22: 7436.1819 | C22: 4795.2709 | D22: 1573.2976 | E22: 1831.6988 | F22: 5229.3072 | G22: 11708.543 | H22: 12092.34 | I22: 2723.5818 | J22: 621.1785 | K22: 1282.8291 | L22: 354.24055 | M22: 186.61391 | N22: =SUM(B22:H22) -> 44666.639 | O22: =ROUND(N22/$N$34,4) -> 0.087 | P22: =O22+O23+O24 -> 0.1459 | Q22: 2024年 | R22: =R14/$Y$14 -> 0.6902932 | S22: =S14/$Y$14 -> 0.086967994 | T22: =T14/$Y$14 -> 0.055586614 | U22: =U14/$Y$14 -> 0.003297438 | V22: =V14/$Y$14 -> 0.084597643 | W22: =W14/$Y$14 -> 0.042282233 | X22: =X14/$Y$14 -> 0.036974874 | Y22: =SUM(R22:X22) -> 1
A23: 天猫 | B23: 7356.2745 | C23: 6826.9474 | D23: 3343.9349 | E23: 2639.3386 | F23: 2808.5516 | G23: 3292.1818 | H23: 2281.9778 | I23: 2542.949 | J23: 1620.5124 | K23: 2614.4508 | L23: 3180.461 | M23: 2272.4962 | N23: =SUM(B23:H23) -> 28549.207 | O23: =ROUND(N23/$N$34,4) -> 0.0556 | Q23: 2023年 | R23: =R15/$Y$15 -> 0.69689837 | S23: =S15/$Y$15 -> 0.10181272 | T23: =T15/$Y$15 -> 0.051617994 | U23: =U15/$Y$15 -> 0.0036902897 | V23: =V15/$Y$15 -> 0.067331178 | W23: =W15/$Y$15 -> 0.044596246 | X23: =X15/$Y$15 -> 0.0340532 | Y23: =SUM(R23:X23) -> 1
A24: 拼多多 | B24: 169.63949 | C24: 258.59786 | D24: 201.96861 | E24: 209.87979 | F24: 245.2243 | G24: 301.85235 | H24: 306.39712 | I24: 303.30276 | J24: 270.23927 | K24: 255.92196 | L24: 287.69779 | M24: 261.74802 | N24: =SUM(B24:H24) -> 1693.5595 | O24: =ROUND(N24/$N$34,4) -> 0.0033
A25: 支付宝小程序 | B25: 4835.725 | C25: 6130.6306 | D25: 4249.5636 | E25: 3138.7858 | F25: 8496.6226 | G25: 8256.9594 | H25: 8340.9431 | I25: 9739.3838 | J25: 5159.344 | K25: 5454.6605 | L25: 5035.8439 | M25: 5414.7719 | N25: =SUM(B25:H25) -> 43449.23 | O25: =ROUND(N25/$N$34,4) -> 0.0846
A26: 抖音 | B26: 978.85206 | C26: 5589.2987 | D26: 1310.5839 | E26: 856.94885 | F26: 2235.5593 | G26: 3481.126 | H26: 7230.5858 | I26: 1241.067 | J26: 611.61683 | K26: 789.61794 | L26: 4306.1958 | M26: 900.78845 | N26: =SUM(B26:H26) -> 21682.955 | O26: =ROUND(N26/$N$34,4) -> 0.0422 | P26: =O26+O27 -> 0.0423
A27: 快手 | B27: 7.955893 | C27: 8.04633 | D27: 5.182013 | E27: 5.71417 | F27: 4.99868 | G27: 0.3792994 | H27: 0.86430006 | I27: -2.4889971 | J27: 6.0944412 | K27: 0.782 | L27: 2.8899 | M27: 1.8559 | N27: =SUM(B27:H27) -> 33.140685 | O27: =ROUND(N27/$N$34,4) -> 0.0001
A28: 微信 | B28: 0.137637 | C28: 0.088062 | D28: 0.16190964 | E28: 0 | F28: -1.272e-05 | G28: 1.2955172 | L28: 0.02205672 | M28: 0.01564572 | N28: =SUM(B28:H28) -> 1.6831131 | O28: =ROUND(N28/$N$34,4) -> 0
A29: 第三方平台 | B29: 2608.1562 | C29: 2087.6476 | D29: 2307.5211 | E29: 1413.6205 | F29: 2168.5868 | G29: 876.27303 | H29: 683.92585 | I29: 876.53694 | J29: 673.27937 | K29: 965.75132 | L29: 723.18587 | M29: 819.06602 | N29: =SUM(B29:H29) -> 12145.731 | O29: =ROUND(N29/$N$34,4) -> 0.0236
A30: 充值频道 | B30: 1491.8645 | C30: 151.0234 | D30: 267.63107 | E30: 294.43465 | F30: 1160.9214 | G30: 180.26779 | H30: 120.31669 | I30: 289.59872 | J30: 73.440949 | K30: 1029.4009 | L30: 76.861941 | M30: 81.4073 | N30: =SUM(B30:H30) -> 3666.4595 | O30: =ROUND(N30/$N$34,4) -> 0.0071
A31: 短信分销平台 | B31: 2.656935 | C31: 1.945017 | D31: 1.73492 | E31: 1.742468 | F31: 1.632589 | G31: 3.857593 | H31: 1.6050478 | I31: 1.1173497 | J31: 0.012545 | K31: 0.11889592 | L31: 0.001748 | M31: 0.002504 | N31: =SUM(B31:H31) -> 15.17457 | O31: =ROUND(N31/$N$34,4) -> 0
A32: 百度小程序 | B32: 1.11333 | C32: 0.404225 | D32: 12.162652 | E32: 2.36439 | F32: 0.00255 | G32: 0.00751 | H32: 0.0134056 | I32: 0.000465 | J32: 0.00078204 | K32: 0.00155796 | L32: 0 | M32: 0.002955 | N32: =SUM(B32:H32) -> 16.068063 | O32: =ROUND(N32/$N$34,4) -> 0
A33: mall商城 | B33: 1572.7729 | C33: 664.98154 | D33: 689.53527 | E33: 178.44666 | F33: 15.061236 | G33: 8.584745 | H33: 15.744394 | I33: 21.133721 | J33: 3.7441439 | K33: 5.8240984 | L33: 10.589944 | M33: 23.743412 | N33: =SUM(B33:H33) -> 3145.1268 | O33: =ROUND(N33/$N$34,4) -> 0.0061
A34: 合计(单位：万元） | B34: =SUM(B21:B33) -> 83841.662 | C34: =SUM(C21:C33) -> 76218.049 | D34: =SUM(D21:D33) -> 66832.889 | E34: =SUM(E21:E33) -> 50345.297 | F34: =SUM(F21:F33) -> 70552.966 | G34: =SUM(G21:G33) -> 83802.748 | H34: =SUM(H21:H33) -> 82004.978 | I34: =SUM(I21:I33) -> 75165.771 | ... N34: =SUM(N21:N33) -> 513598.59 | O34: =N34/$N$34 -> 1
A37: 2023年
A38: 平台 | B38: 1月 | C38: 2月 | D38: 3月 | E38: 4月 | F38: 5月 | G38: 6月 | H38: 7月 | I38: 8月 | J38: 9月 | K38: 10月 | L38: 11月 | M38: 12月 | N38: 合计 | O38: 平台GMV占比
A39: 福禄开放平台 | B39: 91365.673 | C39: 99354.621 | D39: 115570.26 | E39: 90538.163 | F39: 94368.671 | G39: =101515.297081+9043.9/10000 -> 101516.2 | H39: =91428.439399+0.39521 -> 91428.835 | I39: 98871.924 | J39: 87871.175 | K39: 67975.954 | L39: 70601.928 | M39: 70283.486 | N39: =SUM(B39:H39) -> 684142.42 | O39: =ROUND(N39/$N$53,4) -> 0.6969
A40: 京东 | B40: 9976.2347 | C40: 7563.0608 | D40: 8790.9438 | E40: 13731.851 | F40: 21460.735 | G40: 25014.187 | H40: 13412.145 | I40: 11064.822 | J40: 10148.357 | K40: 8363.7859 | L40: 12780.064 | M40: 6652.1429 | N40: =SUM(B40:H40) -> 99949.157 | O40: =ROUND(N40/$N$53,4) -> 0.1018 | P40: =O40+O41+O42 -> 0.1571
A41: 天猫 | B41: 8600.3923 | C41: 6026.2335 | D41: =8710.422622-1350 -> 7360.4226 | E41: =8490.906362-1250 -> 7240.9064 | F41: 7482.9904 | G41: 7613.8731 | H41: 6348.3664 | I41: 8622.117 | J41: 11432.224 | K41: 7610.1162 | L41: 12712.985 | M41: 6277.992 | N41: =SUM(B41:H41) -> 50673.185 | O41: =ROUND(N41/$N$53,4) -> 0.0516
A42: 拼多多 | B42: 491.15028 | C42: 405.34202 | D42: 531.36978 | E42: 595.40474 | F42: 656.21552 | G42: 444.78814 | H42: 498.47264 | I42: 564.60724 | J42: 413.99637 | K42: 340.67903 | L42: 295.47328 | M42: 215.06176 | N42: =SUM(B42:H42) -> 3622.7431 | O42: =ROUND(N42/$N$53,4) -> 0.0037
A43: 支付宝小程序 | B43: 7749.3784 | C43: 7174.6965 | D43: 5950.3348 | E43: 6267.7191 | F43: 12374.001 | G43: 12629.482 | H43: 13953.145 | I43: 16053.31 | J43: 8450.3943 | K43: 4684.6931 | L43: 4960.0016 | M43: 6238.4391 | N43: =SUM(B43:H43) -> 66098.756 | O43: =ROUND(N43/$N$53,4) -> 0.0673
A44: 抖音 | B44: 8813.7315 | C44: 2053.4208 | D44: 2652.0708 | E44: 1378.92 | F44: 5298.9093 | G44: 2842.131 | H44: 1341.2829 | I44: 5110.8842 | J44: 1949.1342 | K44: 3241.7931 | L44: 7605.9872 | M44: 1717.0666 | N44: =SUM(B44:H44) -> 24380.466 | O44: =ROUND(N44/$N$53,4) -> 0.0248 | P44: =O44+O45 -> 0.0446
A45: 快手 | B45: 1506.7266 | C45: 3922.803 | D45: 6875.1207 | E45: 1804.3476 | F45: 1463.6828 | G45: 3357.0479 | H45: 469.7671 | I45: 134.31352 | J45: 425.91863 | K45: 16.981048 | L45: 43.520617 | M45: 7.859037 | N45: =SUM(B45:H45) -> 19399.496 | O45: =ROUND(N45/$N$53,4) -> 0.0198
A46: 微信 | B46: 12.71152 | C46: 83.8174 | D46: 148.87819 | E46: 51.740939 | F46: 50.68203 | G46: 1.574439 | H46: 0.145652 | I46: 0.323576 | J46: 2.36767 | K46: 0.035244 | L46: -8.499131 | M46: 0.025892 | N46: =SUM(B46:H46) -> 349.55016 | O46: =ROUND(N46/$N$53,4) -> 0.0004
A47: 苏宁 | B47: -0.0326 | C47: 0.0929 | D47: 0.01039 | E47: 0 | F47: 0 | G47: 0 | H47: 0 | I47: 0 | J47: 0 | K47: 0 | L47: 0 | M47: 0 | N47: =SUM(B47:H47) -> 0.07069 | O47: =ROUND(N47/$N$53,4) -> 0
A48: 第三方平台 | B48: 4837.3737 | C48: 3461.295 | D48: 2134.6567 | E48: 1960.2073 | F48: 2142.2481 | G48: 2936.7975 | H48: 2748.6421 | I48: 5407.3912 | J48: 4117.676 | K48: 2612.0592 | L48: 4213.3491 | M48: 2303.0788 | N48: =SUM(B48:H48) -> 20221.22 | O48: =ROUND(N48/$N$53,4) -> 0.0206
A49: 充值频道 | B49: 596.39153 | C49: 1019.3311 | D49: 2227.2295 | E49: 714.04104 | F49: 539.45137 | G49: 623.04133 | H49: 598.59061 | I49: 714.52421 | J49: 717.4884 | K49: 985.47588 | L49: 818.13565 | M49: 424.11814 | N49: =SUM(B49:H49) -> 6318.0765 | O49: =ROUND(N49/$N$53,4) -> 0.0064
A50: 短信分销平台 | B50: 21.991233 | C50: 1.70992 | D50: 1.814556 | E50: 1.564706 | F50: 0.236379 | G50: 1.547379 | H50: 1.344699 | I50: 1.439396 | J50: 1.727021 | K50: 5.998978 | L50: 1.401985 | M50: 2.255709 | N50: =SUM(B50:H50) -> 30.208872 | O50: =ROUND(N50/$N$53,4) -> 0
A51: 百度小程序 | B51: 366.34325 | C51: 399.73345 | D51: 586.34572 | E51: 546.63817 | F51: 611.25632 | G51: 1.308647 | H51: 2.119582 | I51: 1.426591 | J51: 0.842911 | K51: 0.932406 | L51: 0.903982 | M51: 23.07937 | N51: =SUM(B51:H51) -> 2513.7451 | O51: =ROUND(N51/$N$53,4) -> 0.0026
A52: mall商城 | B52: 243.51773 | C52: 433.00997 | D52: 480.77091 | E52: 421.79059 | F52: 1422.3533 | G52: 384.92143 | H52: 610.6589 | I52: 664.99859 | J52: 446.07566 | K52: 484.10615 | L52: 492.49003 | M52: 583.04058 | N52: =SUM(B52:H52) -> 3997.0228 | O52: =ROUND(N52/$N$53,4) -> 0.0041
A53: 合计(单位：万元） | B53: =SUM(B39:B52) -> 134581.58 | C53: =SUM(C39:C52) -> 131899.17 | D53: =SUM(D39:D52) -> 153310.23 | E53: =SUM(E39:E52) -> 125253.29 | F53: =SUM(F39:F52) -> 147871.43 | G53: =SUM(G39:G52) -> 157366.9 | H53: =SUM(H39:H52) -> 131413.51 | I53: =SUM(I39:I52) -> 147212.08 | ... N53: =SUM(N39:N52) -> 981696.12 | O53: =N53/$N$53 -> 1
C54: =C53-'GMV销售额波动分析（分月、年）'!H33/10000 -> 0.00060700023 | D54: =D53-'GMV销售额波动分析（分月、年）'!H34/10000 -> -3.2014214e-10
A55: 2022年
A56: 平台 | B56: 1月 | C56: 2月 | D56: 3月 | E56: 4月 | F56: 5月 | G56: 6月 | H56: 7月 | I56: 8月 | J56: 9月 | K56: 10月 | L56: 11月 | M56: 12月 | N56: 合计 | O56: 平台GMV占比
A57: 福禄开放平台 | B57: 57263.076 | C57: 48717.599 | D57: 91475.411 | E57: 78598.883 | F57: 92474.126 | G57: 101701.07 | H57: 85493.075 | I57: 92410.845 | J57: 111531.34 | K57: 95225.339 | L57: 115027.85 | M57: 126045.78 | N57: =(SUM(B57:M57)) -> 1095964.4 | O57: =ROUND(N57/$N$71,4) -> 0.6789
A58: 京东 | B58: 22124.245 | C58: 15918.936 | D58: 16249.324 | E58: 18825.561 | F58: 17618.26 | G58: 17614.562 | H58: 14434.315 | I58: 13427.52 | J58: 12965.87 | K58: 17372.104 | L58: 22491.504 | M58: 18102.674 | N58: =(SUM(B58:M58)) -> 207144.88 | O58: =ROUND(N58/$N$71,4) -> 0.1283
A59: 天猫 | B59: 8746.356 | C59: 5855.7616 | D59: 6581.2168 | E59: =7204.459017-1230 -> 5974.459 | F59: 6556.9445 | G59: 8538.9737 | H59: 6582.8039 | I59: 13196.389 | J59: 9146.8697 | K59: 10329.912 | L59: 13111.603 | M59: 8129.646 | N59: =(SUM(B59:M59)) -> 102750.94 | O59: =ROUND(N59/$N$71,4) -> 0.0637
A60: 拼多多 | B60: 4235.2002 | C60: 2673.212 | D60: 3599.1433 | E60: 2921.2117 | F60: 2648.3383 | G60: 2776.3636 | H60: 618.36244 | I60: 1007.4566 | J60: 765.44164 | K60: 396.26025 | L60: 548.88793 | M60: 390.41837 | N60: =(SUM(B60:M60)) -> 22580.296 | O60: =ROUND(N60/$N$71,4) -> 0.014
A61: 支付宝小程序 | B61: 4932.9948 | C61: 4116.3175 | D61: 3888.4396 | E61: 4108.6453 | F61: 2829.7555 | G61: 2751.2738 | H61: 3017.3385 | I61: 3257.2757 | J61: 3254.2561 | K61: 5111.4118 | L61: 5544.3417 | M61: 5757.1811 | N61: =(SUM(B61:M61)) -> 48569.231 | O61: =ROUND(N61/$N$71,4) -> 0.0301
A62: 抖音 | B62: 2004.8081 | C62: 1023.7076 | D62: 1344.1383 | E62: 1672.2827 | F62: 2011.3606 | G62: 2435.5221 | H62: 3601.9845 | I62: 2434.9339 | J62: 2175.477 | K62: 6071.2049 | L62: 9962.7384 | M62: 4767.9583 | N62: =(SUM(B62:M62)) -> 39506.116 | O62: =ROUND(N62/$N$71,4) -> 0.0245
A63: 快手 | B63: 15.320737 | C63: 0.681875 | D63: 10.537209 | E63: 6.692 | F63: 47.113218 | G63: 32.665575 | H63: 21.139845 | I63: 37.186951 | J63: 19.218547 | K63: 23.587517 | L63: 61.017979 | M63: 305.43281 | N63: =(SUM(B63:M63)) -> 580.59426 | O63: =ROUND(N63/$N$71,4) -> 0.0004
A64: 微信 | B64: 13.984349 | C64: 23.39396 | D64: 15.520214 | E64: 27.460133 | F64: 18.239973 | G64: 9.805075 | H64: 4.419838 | I64: 3.884783 | J64: 2.431087 | K64: 6.385332 | L64: 4.667189 | M64: 6.160662 | N64: =(SUM(B64:M64)) -> 136.3526 | O64: =ROUND(N64/$N$71,4) -> 0.0001
A65: 苏宁 | B65: 5.38078 | C65: 116.03278 | D65: 66.165154 | E65: 56.72909 | F65: 19.445032 | G65: 13.031364 | H65: 1.46989 | I65: 2.976927 | J65: -0.0257 | K65: 0 | L65: 0.0001 | M65: 0 | N65: =(SUM(B65:M65)) -> 281.20542 | O65: =ROUND(N65/$N$71,4) -> 0.0002
A66: 第三方平台 | B66: 6843.2485 | C66: 6390.4107 | D66: 7490.3145 | E66: 6722.6756 | F66: 7874.7579 | G66: 6572.1131 | H66: 5765.7793 | I66: 6176.597 | J66: 7665.4888 | K66: 7271.7127 | L66: =6261.54231499998+435.150349 -> 6696.6927 | M66: =6862.42295999999+369.545598 -> 7231.9686 | N66: =(SUM(B66:M66)) -> 82701.759 | O66: =ROUND(N66/$N$71,4) -> 0.0512
A67: 充值频道 | B67: 641.1758 | C67: 685.87334 | D67: 1217.899 | E67: 1686.1757 | F67: 1768.0032 | G67: 1086.6228 | H67: 784.62902 | I67: 1457.2334 | J67: 1217.2864 | K67: 1232.2211 | L67: 1401.2548 | M67: 519.02557 | N67: =(SUM(B67:M67)) -> 13697.4 | O67: =ROUND(N67/$N$71,4) -> 0.0085
A68: 短信分销平台 | B68: 31.954731 | C68: 30.162219 | D68: 43.586865 | E68: 28.625395 | F68: 28.741788 | G68: 28.935553 | H68: 37.382823 | I68: 26.452599 | J68: 24.123822 | K68: 18.806453 | L68: 14.366787 | M68: 13.333285 | N68: =(SUM(B68:M68)) -> 326.47232 | O68: =ROUND(N68/$N$71,4) -> 0.0002
A69: 福禄云平台 | B69: 1.361804 | C69: 0.492491 | D69: 0 | N69: =(SUM(B69:M69)) -> 1.854295 | O69: =ROUND(N69/$N$71,4) -> 0
A70: 福禄APP | B70: 0.604221 | C70: 0.852804 | D70: 0.021165 | L70: 0.000607 | N70: =(SUM(B70:M70)) -> 1.478797 | O70: =ROUND(N70/$N$71,4) -> 0
A71: 合计(单位：万元） | B71: =SUM(B57:B70) -> 106859.71 | C71: =SUM(C57:C70) -> 85553.434 | D71: =SUM(D57:D70) -> 131981.72 | E71: =SUM(E57:E70) -> 120629.4 | F71: =SUM(F57:F70) -> 133895.09 | G71: =SUM(G57:G70) -> 143560.94 | H71: =SUM(H57:H70) -> 120362.7 | I71: =SUM(I57:I70) -> 133438.75 | ... N71: =SUM(N57:N70) -> 1614243 | O71: =N71/$N$71 -> 1
B72: =B71-'GMV销售额波动分析（分月、年）'!H47/10000 -> 0 | C72: =C71-'GMV销售额波动分析（分月、年）'!H48/10000 -> 1.891749e-10 | D72: =D71-'GMV销售额波动分析（分月、年）'!H49/10000 -> 0 | E72: =E71-'GMV销售额波动分析（分月、年）'!H50/10000 -> -8.1490725e-10 | F72: =F71-'GMV销售额波动分析（分月、年）'!H51/10000 -> -2.3999019e-07 | G72: =G71-'GMV销售额波动分析（分月、年）'!H52/10000 -> -2.910383e-10 | H72: =H71-'GMV销售额波动分析（分月、年）'!H53/10000 -> -2.7648639e-10 | I72: =I71-'GMV销售额波动分析（分月、年）'!H54/10000 -> -1.5133992e-09 | J72: =J71-'GMV销售额波动分析（分月、年）'!H55/10000 -> -1.2223609e-09 | K72: =K71-'GMV销售额波动分析（分月、年）'!H56/10000 -> 4.3655746e-10 | L72: =L71-'GMV销售额波动分析（分月、年）'!H57/10000 -> -2.910383e-10
A73: 2021年
A74: 平台 | B74: 1月 | C74: 2月 | D74: 3月 | E74: 4月 | F74: 5月 | G74: 6月 | H74: 7月 | I74: 8月 | J74: 9月 | K74: 10月 | L74: 11月 | M74: 12月 | N74: 合计 | O74: 平台GMV占比
A75: 福禄开放平台 | B75: =39423.9753359997+1.8+11366675/10000 -> 40562.443 | C75: =40951.919165+23497269/10000 -> 43301.646 | D75: =58250.0285839998+19871254/10000 -> 60237.154 | E75: =48818.376555+19827588/10000 -> 50801.135 | F75: =68007.927959+21357735/10000 -> 70143.701 | G75: =96605.077184+21327047/10000 -> 98737.782 | H75: =99417.66+15565600/10000 -> 100974.22 | I75: 105358.42 | J75: =107367.065018+6695591/10000 -> 108036.62 | K75: 85420.475 | L75: 109719.61 | M75: =107009.96952662-1098882/10000 -> 106900.08 | N75: =(SUM(B75:M75)) -> 980193.29 | O75: =ROUND(N75/$N$88,4) -> 0.4562
A76: 京东 | B76: 61176.69 | C76: 57422.696 | D76: 81422.116 | E76: 79200.967 | F76: 102417.81 | G76: 110457.44 | H76: 101707 | I76: 145034.01 | J76: 51975.055 | K76: 39140.548 | L76: =45786.486366-1490350.88/10000 -> 45637.451 | M76: 29471.594 | N76: =(SUM(B76:M76)) -> 905063.37 | O76: =ROUND(N76/$N$88,4) -> 0.4212
A77: 天猫 | B77: 15572.999 | C77: 16729.527 | D77: 15594.689 | E77: 16881.119 | F77: 14957.635 | G77: 9213.6369 | H77: 10097.426 | I77: 9429.0745 | J77: 8711.3003 | K77: 7934.5837 | L77: 11842.62 | M77: 7885.9601 | N77: =(SUM(B77:M77)) -> 144850.57 | O77: =ROUND(N77/$N$88,4) -> 0.0674
A78: 拼多多 | B78: 396.84255 | C78: 332.53945 | D78: 391.1869 | E78: 404.83364 | F78: 537.52182 | G78: 691.68664 | H78: 347.58919 | I78: 351.3668 | J78: 270.78366 | K78: 293.53961 | L78: 1828.9349 | M78: 5697.9092 | N78: =(SUM(B78:M78)) -> 11544.734 | O78: =ROUND(N78/$N$88,4) -> 0.0054
A79: 抖音 | B79: 4.99998 | C79: 1.30409 | D79: 8.797984 | E79: 10.566873 | F79: 11.817944 | G79: 209.58694 | H79: 267.65737 | I79: 748.74644 | J79: 251.18179 | K79: 1574.6299 | L79: 2197.2566 | M79: 1003.5323 | N79: =(SUM(B79:M79)) -> 6290.0781 | O79: =ROUND(N79/$N$88,4) -> 0.0029
A80: 快手 | B80: 11.41402 | C80: 69.565727 | D80: 0.007144 | E80: 0.006292 | F80: 1.073629 | G80: 52.738715 | H80: 54.057234 | I80: 1.377599 | J80: -0.050824 | K80: 3.458081 | L80: 182.34554 | M80: 21.25146 | N80: =(SUM(B80:M80)) -> 397.24461 | O80: =ROUND(N80/$N$88,4) -> 0.0002
A81: 第三方平台 | B81: 8093.4824 | C81: 7839.7969 | D81: 9038.0389 | E81: 8604.2089 | F81: 5654.2261 | G81: 6522.9374 | H81: 5880.6582 | I81: 6786.1417 | J81: 8013.0434 | K81: 6656.728 | L81: 6529.4188 | M81: 11977.974 | N81: =(SUM(B81:M81)) -> 91596.655 | O81: =ROUND(N81/$N$88,4) -> 0.0426
A82: 苏宁 | B82: 179.04565 | C82: 110.75049 | D82: 27.409568 | E82: 160.57295 | F82: 67.484508 | G82: 138.02232 | H82: 51.691404 | I82: 240.15992 | J82: 104.45614 | K82: 42.425316 | L82: 23.733068 | M82: 65.640713 | N82: =(SUM(B82:M82)) -> 1211.392 | O82: =ROUND(N82/$N$88,4) -> 0.0006
A83: 微信 | B83: 176.45688 | C83: 365.17786 | D83: 143.58598 | E83: 76.936761 | F83: 31.692688 | G83: 25.153484 | H83: 17.941346 | I83: 12.194873 | J83: 8.075669 | K83: 9.757343 | L83: 15.530333 | M83: 31.255816 | N83: =(SUM(B83:M83)) -> 913.75904 | O83: =ROUND(N83/$N$88,4) -> 0.0004
A84: 充值频道 | B84: 356.47403 | C84: 316.98726 | D84: 276.19386 | E84: 329.62943 | F84: 505.64156 | G84: 634.27797 | H84: 765.05151 | I84: 605.17902 | J84: 256.05156 | K84: 448.39175 | L84: 382.92694 | M84: 959.51346 | N84: =(SUM(B84:M84)) -> 5836.3183 | O84: =ROUND(N84/$N$88,4) -> 0.0027
A85: 短信分销平台 | B85: 30.220819 | C85: 8.815927 | D85: 20.533129 | E85: 40.769859 | F85: 15.823194 | G85: 19.139784 | H85: 64.819123 | I85: 102.58942 | J85: 85.22272 | K85: 87.770289 | L85: 35.354799 | M85: 38.590306 | N85: =(SUM(B85:M85)) -> 549.64937 | O85: =ROUND(N85/$N$88,4) -> 0.0003
A86: APP | B86: 11.19466 | C86: 15.14335 | D86: 10.103145 | E86: 11.250786 | F86: 10.332308 | G86: 111.23654 | H86: 4.803363 | I86: 105.81594 | J86: 0.90577 | K86: 0 | L86: 0.050483 | M86: 0.524047 | N86: =(SUM(B86:M86)) -> 281.36039 | O86: =ROUND(N86/$N$88,4) -> 0.0001
A87: G库 | B87: 0.0311 | C87: 0.0055 | D87: 0.0025 | E87: 0.006 | F87: 3.1065 | G87: 0.0015 | H87: 0.0035 | I87: 0.001 | J87: 0.002 | K87: 0.001 | L87: 0.001 | M87: 0 | N87: =(SUM(B87:M87)) -> 3.1616 | O87: =ROUND(N87/$N$88,4) -> 0
A88: 合计(单位：万元） | B88: =SUM(B75:B87) -> 126572.29 | C88: =SUM(C75:C87) -> 126513.96 | D88: =SUM(D75:D87) -> 167169.82 | E88: =SUM(E75:E87) -> 156522 | F88: =SUM(F75:F87) -> 194357.87 | G88: =SUM(G75:G87) -> 226813.64 | H88: =SUM(H75:H87) -> 220232.91 | I88: =SUM(I75:I87) -> 268775.08 | ... N88: =SUM(N75:N87) -> 2148731.6 | O88: =ROUND(N88/$N$88,4) -> 1
L89: =L88-'GMV销售额波动分析（分月、年）'!H72/10000 -> 3.4924597e-10 | N89: =N88-SUM('GMV销售额波动分析（分月、年）'!H62:H73)/10000 -> -3.0150637e-05
A90: 2020年
A91: 平台 | B91: 1月 | C91: 2月 | D91: 3月 | E91: 4月 | F91: 5月 | G91: 6月 | H91: 7月 | I91: 8月 | J91: 9月 | K91: 10月 | L91: 11月 | M91: 12月 | N91: 合计 | O91: 平台GMV占比
A92: 开放平台 | B92: =78680.400901+85.91-74719884.22/10000 -> 71294.322 | C92: =92825.248135-25783045.72/10000 -> 90246.944 | D92: =105162.588587+7.89-109693990.11/10000 -> 94201.08 | E92: =97371.774742+0.6026-63605902.13/10000 -> 91011.787 | F92: =68842.153984-0.52-50369337.9/10000 -> 63804.7 | G92: =59099.8122899998+31484467.16/10000+8.29-34408693.89/10000 -> 58815.68 | H92: =37665.855537-40538243.73/10000 -> 33612.031 | I92: =42558.544539-44690221.03/10000 -> 38089.522 | J92: =45183.57061+134070.57/10000-78063313.07/10000 -> 37390.646 | K92: =41079.293538-10179102.11/10000 -> 40061.383 | L92: =46761.208714+83997.87/10000-73096942.4/10000 -> 39459.914 | M92: =55434.034117-99213147.59/10000 -> 45512.719 | N92: =(SUM(B92:J92)) -> 578466.71 | O92: =N92/$N$106 -> 0.53976625
A93: 京东 | B93: 17676.328 | C93: 15046.748 | D93: 22011.813 | E93: 18856.754 | F93: 36867.658 | G93: 49393.267 | H93: 50846.399 | I93: =41494.864346+72.719472 -> 41567.584 | J93: 51591.896 | K93: 57234.207 | L93: 62757.926 | M93: 59950.407 | N93: =(SUM(B93:J93)) -> 303858.45 | O93: =N93/$N$106 -> 0.28352977
A94: 天猫 | B94: 12208.547 | C94: =12603.12774-91.11 -> 12512.018 | D94: 13439.306 | E94: 13470.142 | F94: 14860.018 | G94: 16925.18 | H94: 16200.158 | I94: 15361.318 | J94: 14191.907 | K94: 16833.536 | L94: 23264.896 | M94: 19603.237 | N94: =(SUM(B94:J94)) -> 129168.59 | O94: =N94/$N$106 -> 0.12052698
A95: 拼多多 | B95: 608.58226 | C95: 503.59395 | D95: 254.745 | E95: 333.5462 | F95: 308.75763 | G95: 349.66423 | H95: 10.906277 | I95: 10.597887 | J95: 334.46023 | K95: 669.26409 | L95: 480.25236 | M95: 409.15772 | N95: =(SUM(B95:J95)) -> 2714.8537 | O95: =N95/$N$106 -> 0.0025332251
A96: 支付宝小程序 | B96: 2351.6964 | C96: 2279.5221 | D96: 4459.0473 | E96: 4231.7542 | F96: 4074.6688 | G96: 6094.1392 | H96: 6568.2464 | I96: 6790.008 | J96: 3917.435 | K96: 4764.8864 | L96: 3378.4368 | M96: -0.01655 | N96: =(SUM(B96:J96)) -> 40766.517 | O96: =N96/$N$106 -> 0.038039164
A97: IOS苹果卡 | B97: 4001.1056 | C97: 4641.3033 | D97: 888.47523 | N97: =(SUM(B97:J97)) -> 9530.8841 | O97: =N97/$N$106 -> 0.0088932508
A98: 苏宁 | B98: 176.96577 | C98: 264.6003 | D98: 111.69629 | E98: 122.03122 | F98: 271.5269 | G98: 636.00335 | H98: 0.027307 | I98: 0.407394 | J98: 112.80687 | K98: 434.7165 | L98: 185.12352 | M98: 689.01028 | N98: =(SUM(B98:J98)) -> 1696.0654 | O98: =N98/$N$106 -> 0.0015825956
A99: 微信 | B99: 88.226893 | C99: 144.04977 | D99: 194.45179 | E99: 148.45406 | F99: 32.871628 | G99: 55.179119 | H99: 76.697604 | I99: 142.83447 | J99: 117.74105 | K99: 149.26196 | L99: 222.24521 | M99: 244.63404 | N99: =(SUM(B99:J99)) -> 1000.5064 | O99: =N99/$N$106 -> 0.00093357071
A100: 第三方平台 | B100: 218.59009 | C100: 75.498498 | D100: 119.34302 | E100: 82.905622 | F100: 230.03195 | G100: 476.28214 | H100: 102.1481 | I100: 393.48238 | J100: 168.01642 | K100: 354.04884 | L100: 1536.1018 | M100: 7470.3573 | N100: =(SUM(B100:J100)) -> 1866.2982 | O100: =N100/$N$106 -> 0.0017414395
A101: 短信平台 | B101: 49.645955 | C101: 50.866252 | D101: 210.11419 | E101: 119.91572 | F101: 32.158862 | G101: 22.375904 | H101: =170.154629+8.35/10000 -> 170.15546 | I101: 13.872562 | J101: 20.104893 | K101: 15.716167 | L101: 25.751411 | M101: 24.026338 | N101: =(SUM(B101:J101)) -> 689.20981 | O101: =N101/$N$106 -> 0.00064310043
A102: APP | B102: 64.371113 | C102: 144.49488 | D102: 51.030485 | E102: 75.733586 | F102: 74.506003 | G102: 211.59468 | H102: 58.798072 | I102: 21.061007 | J102: 26.467035 | K102: 9.645272 | L102: 3.994273 | M102: 3.359208 | N102: =(SUM(B102:J102)) -> 728.05686 | O102: =N102/$N$106 -> 0.00067934855
...

Sheet GMV表-商品大类
A1: 支撑分析数据
A2: 1、21年-22年商品大类增长波动
A3: 2、21年-22年网娱、生活服务增长波动
A4: 代理商品大类 | H4: 代运营GMV
A5: 年份 | B5: 游戏 | C5: 通信 | D5: 网娱 | E5: 生活服务 | F5: 合计（单位：万元） | H5: 年份 | I5: 游戏 | J5: 通信 | K5: 网娱 | L5: 生活服务 | M5: 合计（单位：万元） | O5: 代理GMV年度累计 | P5: 游戏 | Q5: 通信 | R5: 网娱 | S5: 生活服务 | T5: 合计（单位：万元）
A6: 43831 | B6: 26733.731 | C6: 68544.632 | D6: 10654.409 | E6: 2922.7941 | F6: =SUM(B6:E6) -> 108855.57 | H6: 43831 | I6: 4766.0089 | J6: 0 | K6: 1558.2318 | L6: 0 | M6: =SUM(I6:L6) -> 6324.2407 | O6: 20.1月累计 | P6: =B6 -> 26733.731 | Q6: =C6 -> 68544.632 | R6: =D6 -> 10654.409 | S6: =E6 -> 2922.7941 | T6: =SUM(P6:S6) -> 108855.57 | U6: =F6-T6 -> 0
A7: 43862 | B7: 19821.24 | C7: 92007.291 | D7: 12820.087 | E7: 1329.9212 | F7: =SUM(B7:E7) -> 125978.54 | H7: 43862 | I7: 1147.842 | J7: 0 | K7: 1533.8891 | L7: 0 | M7: =SUM(I7:L7) -> 2681.731 | O7: 20.2月累计 | P7: =SUM(B6:B7) -> 46554.971 | Q7: =SUM(C6:C7) -> 160551.92 | R7: =SUM(D6:D7) -> 23474.497 | S7: =SUM(E6:E7) -> 4252.7153 | T7: =SUM(P7:S7) -> 234834.11 | U7: =F6+F7-T7 -> 0
A8: 43891 | B8: 17486.651 | C8: 97094.875 | D8: 15877.69 | E8: 5744.5058 | F8: =SUM(B8:E8) -> 136203.72 | H8: 43891 | I8: 9868.8997 | J8: 0 | K8: 1669.5443 | L8: 0 | M8: =SUM(I8:L8) -> 11538.444 | O8: 20.3月累计 | P8: =SUM(B6:B8) -> 64041.622 | Q8: =SUM(C6:C8) -> 257646.8 | R8: =SUM(D6:D8) -> 39352.186 | S8: =SUM(E6:E8) -> 9997.221 | T8: =SUM(P8:S8) -> 371037.83 | U8: =F6+F7+F8-T8 -> 0
A9: 43922 | B9: 15860.841 | C9: 93890.904 | D9: 15845.447 | E9: 2992.8043 | F9: =SUM(B9:E9) -> 128590 | H9: 43922 | I9: 6360.5902 | J9: 0 | K9: 1162.3167 | L9: 0 | M9: =SUM(I9:L9) -> 7522.9069 | O9: 20.4月累计 | P9: =SUM(B6:B9) -> 79902.463 | Q9: =SUM(C6:C9) -> 351537.7 | R9: =SUM(D6:D9) -> 55197.633 | S9: =SUM(E6:E9) -> 12990.025 | T9: =SUM(F6:F9) -> 499627.82 | U9: =F6+F7+F8+F9-T9 -> 0
A10: 43952 | B10: 16779.883 | C10: 83018.52 | D10: 17482.749 | E10: 3418.4836 | F10: =SUM(B10:E10) -> 120699.64 | H10: 43952 | I10: 5036.9338 | J10: 0 | K10: 1174.8589 | L10: 0 | M10: =SUM(I10:L10) -> 6211.7926 | O10: 20.5月累计 | P10: =SUM(B6:B10) -> 96682.346 | Q10: =SUM(C6:C10) -> 434556.22 | R10: =SUM(D6:D10) -> 72680.382 | S10: =SUM(E6:E10) -> 16408.509 | T10: =SUM(P10:S10) -> 620327.46 | U10: =F6+F7+F8+F9+F10-T10 -> 0
A11: 43983 | B11: 14015.746 | C11: 85266.828 | D11: 26479.396 | E11: 7380.6022 | F11: =SUM(B11:E11) -> 133142.57 | H11: 43983 | I11: 3440.8604 | J11: 0 | K11: 2146.6143 | L11: 0.7181 | M11: =SUM(I11:L11) -> 5588.1928 | O11: 20.6月累计 | P11: =SUM(B6:B11) -> 110698.09 | Q11: =SUM(C6:C11) -> 519823.05 | R11: =SUM(D6:D11) -> 99159.778 | S11: =SUM(E6:E11) -> 23789.111 | T11: =SUM(P11:S11) -> 753470.03 | U11: =F6+F7+F8+F9+F10+F11-T11 -> 0
A12: 44013 | B12: 16231.545 | C12: 64424.976 | D12: 22574.644 | E12: 4580.5085 | F12: =SUM(B12:E12) -> 107811.67 | H12: 44013 | I12: 4053.8244 | J12: 0 | K12: 1813.2527 | L12: 3.5087 | M12: =SUM(I12:L12) -> 5870.5857 | O12: 20.7月累计 | P12: =SUM(B6:B12) -> 126929.64 | Q12: =SUM(C6:C12) -> 584248.03 | R12: =SUM(D6:D12) -> 121734.42 | S12: =SUM(E6:E12) -> 28369.62 | T12: =SUM(P12:S12) -> 861281.71 | U12: =F6+F7+F8+F9+F10+F11+F12-T12 -> 0
A13: 44044 | B13: 14517.382 | C13: 57241.885 | D13: 26337.265 | E13: 4365.9292 | F13: =SUM(B13:E13) -> 102462.46 | H13: 44044 | I13: 4469.0221 | J13: 0 | K13: 2259.0279 | L13: 1.6854 | M13: =SUM(I13:L13) -> 6729.7354 | O13: 20.8月累计 | P13: =SUM(B6:B13) -> 141447.02 | Q13: =SUM(C6:C13) -> 641489.91 | R13: =SUM(D6:D13) -> 148071.69 | S13: =SUM(E6:E13) -> 32735.549 | T13: =SUM(P13:S13) -> 963744.17 | U13: =F6+F7+F8+F9+F10+F11+F12+F13-T13 -> 0
A14: 44075 | B14: 13843.132 | C14: 67326.285 | D14: 21292.801 | E14: 5492.1823 | F14: =SUM(B14:E14) -> 107954.4 | H14: 44075 | I14: 7806.3313 | J14: 0 | K14: 2382.1591 | L14: 8.0147 | M14: =SUM(I14:L14) -> 10196.505 | O14: 20.9月累计 | P14: =SUM(B6:B14) -> 155290.15 | Q14: =SUM(C6:C14) -> 708816.2 | R14: =SUM(D6:D14) -> 169364.49 | S14: =SUM(E6:E14) -> 38227.731 | T14: =SUM(P14:S14) -> 1071698.6 | U14: =F6+F7+F8+F9+F10+F11+F12+F13+F14-T14 -> 0
A15: 44105 | B15: 12454.221 | C15: 80743.043 | D15: 20441.246 | E15: 6961.2069 | F15: =SUM(B15:E15) -> 120599.72 | H15: 44105 | I15: 1017.6096 | J15: 0 | K15: 2938.2835 | L15: 3.6837 | M15: =SUM(I15:L15) -> 3959.5768 | O15: 20.10月累计 | P15: =SUM(B6:B15) -> 167744.37 | Q15: =SUM(C6:C15) -> 789559.24 | R15: =SUM(D6:D15) -> 189805.73 | S15: =SUM(E6:E15) -> 45188.938 | T15: =SUM(P15:S15) -> 1192298.3 | U15: =F6+F7+F8+F9+F10+F11+F12+F13+F14+F15-T15 -> 0
A16: 44136 | B16: 7898.8587 | C16: 80478.372 | D16: 34128.761 | E16: 8961.0764 | F16: =SUM(B16:E16) -> 131467.07 | H16: 44136 | I16: 7317.3002 | J16: 0 | K16: 6164.3861 | L16: 3.0146 | M16: =SUM(I16:L16) -> 13484.701 | O16: 20.11月累计 | P16: =SUM(B6:B16) -> 175643.23 | Q16: =SUM(C6:C16) -> 870037.61 | R16: =SUM(D6:D16) -> 223934.5 | S16: =SUM(E6:E16) -> 54150.015 | T16: =SUM(P16:S16) -> 1323765.4 | U16: =F6+F7+F8+F9+F10+F11+F12+F13+F14+F15+F16-T16 -> 0
A17: 44166 | B17: 8347.7624 | C17: 80236.037 | D17: 34262.011 | E17: 11272.807 | F17: =SUM(B17:E17) -> 134118.62 | H17: 44166 | I17: 9920.1826 | J17: 0 | K17: 1953.6527 | L17: 6.60804 | M17: =SUM(I17:L17) -> 11880.443 | O17: 20.12月累计 | P17: =SUM(B6:B17) -> 183990.99 | Q17: =SUM(C6:C17) -> 950273.65 | R17: =SUM(D6:D17) -> 258196.51 | S17: =SUM(E6:E17) -> 65422.821 | T17: =SUM(P17:S17) -> 1457884 | U17: =F6+F7+F8+F9+F10+F11+F12+F13+F14+F15+F16+F17-T17 -> 0
A18: 44197 | B18: 13565.984 | C18: 73685.445 | D18: 26771.902 | E18: 12548.963 | F18: =SUM(B18:E18) -> 126572.29 | H18: 44197 | I18: 4288.1461 | K18: 2011.235 | L18: 9.82059 | M18: =SUM(I18:L18) -> 6309.2017 | O18: 21.1月累计 | P18: =B18 -> 13565.984 | Q18: =C18 -> 73685.445 | R18: =D18 -> 26771.902 | S18: =E18 -> 12548.963 | T18: =SUM(P18:S18) -> 126572.29 | U18: =F18-T18 -> 0
A19: 44228 | B19: 17056.524 | C19: 77106.765 | D19: 25385.12 | E19: 6965.5475 | F19: =SUM(B19:E19) -> 126513.96 | H19: 44228 | I19: 10337.843 | K19: 2618.8775 | L19: 9.288253 | M19: =SUM(I19:L19) -> 12966.008 | O19: 21.2月累计 | P19: =SUM(B18:B19) -> 30622.508 | Q19: =SUM(C18:C19) -> 150792.21 | R19: =SUM(D18:D19) -> 52157.022 | S19: =SUM(E18:E19) -> 19514.51 | T19: =SUM(P19:S19) -> 253086.25 | U19: =F18+F19-T19 -> 0
A20: 44256 | B20: 11768.772 | C20: 111377.33 | D20: 28416 | E20: 15607.713 | F20: =SUM(B20:E20) -> 167169.82 | H20: 44256 | I20: 9167.8411 | K20: 2259.0912 | L20: 1206.6146 | M20: =SUM(I20:L20) -> 12633.547 | O20: 21.3月累计 | P20: =SUM(B18:B20) -> 42391.28 | Q20: =SUM(C18:C20) -> 262169.54 | R20: =SUM(D18:D20) -> 80573.022 | S20: =SUM(E18:E20) -> 35122.223 | T20: =SUM(P20:S20) -> 420256.07 | U20: =F18+F19+F20-T20 -> 0
A21: 44287 | B21: 12167.361 | C21: 100911.75 | D21: 33260.077 | E21: 10182.818 | F21: =SUM(B21:E21) -> 156522 | H21: 44287 | I21: 5026.1324 | K21: 2142.9022 | L21: 15.599387 | M21: =SUM(I21:L21) -> 7184.634 | O21: 21.4月累计 | P21: =SUM(B18:B21) -> 54558.641 | Q21: =SUM(C18:C21) -> 363081.29 | R21: =SUM(D18:D21) -> 113833.1 | S21: =SUM(E18:E21) -> 45305.041 | T21: =SUM(F18:F21) -> 576778.07 | U21: =F18+F19+F20+F21-T21 -> 0
A22: 44317 | B22: 14671.452 | C22: 129551.31 | D22: 40443.049 | E22: 9692.0584 | F22: =SUM(B22:E22) -> 194357.87 | H22: 44317 | I22: 9897.2254 | K22: 1594.0361 | L22: 13.442304 | M22: =SUM(I22:L22) -> 11504.704 | O22: 21.5月累计 | P22: =SUM(B18:B22) -> 69230.093 | Q22: =SUM(C18:C22) -> 492632.6 | R22: =SUM(D18:D22) -> 154276.15 | S22: =SUM(E18:E22) -> 54997.099 | T22: =SUM(P22:S22) -> 771135.94 | U22: =F18+F19+F20+F21+F22-T22 -> 0
A23: 44348 | B23: 11644.243 | C23: 142202.39 | D23: 60471.742 | E23: 12495.264 | F23: =SUM(B23:E23) -> 226813.64 | H23: 44348 | I23: 14562.249 | K23: 4742.9221 | L23: 10.22323 | M23: =SUM(I23:L23) -> 19315.394 | O23: 21.6月累计 | P23: =SUM(B18:B23) -> 80874.336 | Q23: =SUM(C18:C23) -> 634834.99 | R23: =SUM(D18:D23) -> 214747.89 | S23: =SUM(E18:E23) -> 67492.363 | T23: =SUM(P23:S23) -> 997949.58 | U23: =F18+F19+F20+F21+F22+F23-T23 -> 0
A24: 44378 | B24: 15576.254 | C24: 147091.75 | D24: 48060.161 | E24: 9504.7517 | F24: =SUM(B24:E24) -> 220232.91 | H24: 44378 | I24: 11482.456 | K24: 1096.0712 | L24: 9.51328 | M24: =SUM(I24:L24) -> 12588.04 | O24: 21.7月累计 | P24: =SUM(B18:B24) -> 96450.59 | Q24: =SUM(C18:C24) -> 781926.74 | R24: =SUM(D18:D24) -> 262808.05 | S24: =SUM(E18:E24) -> 76997.115 | T24: =SUM(P24:S24) -> 1218182.5 | U24: =F18+F19+F20+F21+F22+F23+F24-T24 -> 0
A25: 44409 | B25: 13651.967 | C25: 185372.92 | D25: 57744.733 | E25: 12005.452 | F25: =SUM(B25:E25) -> 268775.08 | H25: 44409 | I25: 11398.244 | K25: 1746.9965 | L25: 8.1921625 | M25: =SUM(I25:L25) -> 13153.433 | O25: 21.8月累计 | P25: =SUM(B18:B25) -> 110102.56 | Q25: =SUM(C18:C25) -> 967299.66 | R25: =SUM(D18:D25) -> 320552.78 | S25: =SUM(E18:E25) -> 89002.567 | T25: =SUM(P25:S25) -> 1486957.6 | U25: =F18+F19+F20+F21+F22+F23+F24+F25-T25 -> 0
A26: 44440 | B26: 8556.6106 | C26: 86568.692 | D26: 65861.575 | E26: 16725.774 | F26: =SUM(B26:E26) -> 177712.65 | H26: 44440 | I26: 9632.0406 | K26: 6784.2403 | L26: 6.62331 | M26: =SUM(I26:L26) -> 16422.904 | O26: 21.9月累计 | P26: =SUM(B18:B26) -> 118659.17 | Q26: =SUM(C18:C26) -> 1053868.4 | R26: =SUM(D18:D26) -> 386414.36 | S26: =SUM(E18:E26) -> 105728.34 | T26: =SUM(P26:S26) -> 1664670.2 | U26: =F18+F19+F20+F21+F22+F23+F24+F25+F26-T26 -> 0
A27: 44470 | B27: 8610.3375 | C27: 75021.656 | D27: 42225.629 | E27: 15754.684 | F27: =SUM(B27:E27) -> 141612.31 | H27: 44470 | I27: 6518.1578 | K27: 5265.7692 | L27: 3.6836885 | M27: =SUM(I27:L27) -> 11787.611 | O27: 21.10月累计 | P27: =SUM(B18:B27) -> 127269.5 | Q27: =SUM(C18:C27) -> 1128890 | R27: =SUM(D18:D27) -> 428639.99 | S27: =SUM(E18:E27) -> 121483.03 | T27: =SUM(P27:S27) -> 1806282.5 | U27: =F18+F19+F20+F21+F22+F23+F24+F25+F26+F27-T27 -> 0
A28: 44501 | B28: 7465.0763 | C28: 92817.321 | D28: 59975.26 | E28: 18137.573 | F28: =SUM(B28:E28) -> 178395.23 | H28: 44501 | I28: 12228.259 | K28: 13763.025 | L28: 1.764252 | M28: =SUM(I28:L28) -> 25993.049 | O28: 21.11月累计 | P28: =SUM(B18:B28) -> 134734.58 | Q28: =SUM(C18:C28) -> 1221707.3 | R28: =SUM(D18:D28) -> 488615.25 | S28: =SUM(E18:E28) -> 139620.6 | T28: =SUM(P28:S28) -> 1984677.8 | U28: =F18+F19+F20+F21+F22+F23+F24+F25+F26+F27+F28-T28 -> 0
A29: 44531 | B29: 15048.808 | C29: 63988.13 | D29: 69189.446 | E29: 15827.442 | F29: =SUM(B29:E29) -> 164053.83 | H29: 44531 | I29: 7541.2044 | K29: 6390.664 | L29: 5.19598 | M29: =SUM(I29:L29) -> 13937.064 | O29: 21.12月累计 | P29: =SUM(B18:B29) -> 149783.39 | Q29: =SUM(C18:C29) -> 1285695.5 | R29: =SUM(D18:D29) -> 557804.69 | S29: =SUM(E18:E29) -> 155448.04 | T29: =SUM(P29:S29) -> 2148731.6 | U29: =F18+F19+F20+F21+F22+F23+F24+F25+F26+F27+F28+F29-T29 -> 0
A30: 44562 | B30: 15562.122 | C30: 41149.968 | D30: 32432.045 | E30: 17715.575 | F30: =SUM(B30:E30) -> 106859.71 | H30: 44562 | I30: 4387.8546 | J30: 0 | K30: =4192.779187-10700876.86/10000 -> 3122.6915 | L30: 5.083477 | M30: =SUM(I30:L30) -> 7515.6295 | O30: 22.1月累计 | P30: =B30 -> 15562.122 | Q30: =C30 -> 41149.968 | R30: =D30 -> 32432.045 | S30: =E30 -> 17715.575 | T30: =SUM(P30:S30) -> 106859.71 | U30: =F30-T30 -> 0
A31: 44593 | B31: 14076.505 | C31: 31152.277 | D31: 25233.803 | E31: 15090.849 | F31: =SUM(B31:E31) -> 85553.434 | H31: 44593 | I31: 5990.0821 | J31: 0 | K31: 4623.5252 | L31: 5.140155 | M31: =SUM(I31:L31) -> 10618.747 | O31: 22.2月累计 | P31: =SUM(B30:B31) -> 29638.627 | Q31: =SUM(C30:C31) -> 72302.245 | R31: =SUM(D30:D31) -> 57665.848 | S31: =SUM(E30:E31) -> 32806.424 | T31: =SUM(P31:S31) -> 192413.14 | U31: =F30+F31-T31 -> 0
A32: 44621 | B32: 12114.914 | C32: 42817.482 | D32: 44380.459 | E32: 32668.862 | F32: =SUM(B32:E32) -> 131981.72 | H32: 44621 | I32: 2088.9152 | J32: 0 | K32: 4915.631 | L32: 11.129806 | M32: =SUM(I32:L32) -> 7015.676 | O32: 22.3月累计 | P32: =SUM(B30:B32) -> 41753.541 | Q32: =SUM(C30:C32) -> 115119.73 | R32: =SUM(D30:D32) -> 102046.31 | S32: =SUM(E30:E32) -> 65475.286 | T32: =SUM(P32:S32) -> 324394.86 | U32: =F30+F31+F32-T32 -> 0
A33: 44652 | B33: 14206.269 | C33: 45294.442 | D33: 34967.361 | E33: 26161.328 | F33: =SUM(B33:E33) -> 120629.4 | H33: 44652 | I33: 2976.7208 | J33: 0 | K33: 3104.262 | L33: 76.552124 | M33: =SUM(I33:L33) -> 6157.5349 | O33: 22.4月累计 | P33: =SUM(B30:B33) -> 55959.81 | Q33: =SUM(C30:C33) -> 160414.17 | R33: =SUM(D30:D33) -> 137013.67 | S33: =SUM(E30:E33) -> 91636.614 | T33: =SUM(F30:F33) -> 445024.26 | U33: =F30+F31+F32+F33-T33 -> 0
A34: 44682 | B34: 9219.1403 | C34: 53111 | D34: 39081.808 | E34: 32483.137 | F34: =SUM(B34:E34) -> 133895.09 | H34: 44682 | I34: 6742.3218 | J34: 0 | K34: 2621.4735 | L34: 146.84333 | M34: =SUM(I34:L34) -> 9510.6386 | O34: 22.5月累计 | P34: =SUM(B$30:B34) -> 65178.951 | Q34: =SUM(C$30:C34) -> 213525.17 | R34: =SUM(D$30:D34) -> 176095.48 | S34: =SUM(E$30:E34) -> 124119.75 | T34: =SUM(F$30:F34) -> 578919.35 | U34: =SUM(F$30:F34)-T34 -> 0 | BE34: =利润组成!I34 -> 2273.8984
A35: 44713 | B35: 10707.165 | C35: 48364.974 | D35: 50326.21 | E35: 34162.588 | F35: =SUM(B35:E35) -> 143560.94 | H35: 44713 | I35: 6466.8323 | J35: 0 | K35: 3633.9463 | L35: 67.908485 | M35: =SUM(I35:L35) -> 10168.687 | O35: 22.6月累计 | P35: =SUM(B$30:B35) -> 75886.116 | Q35: =SUM(C$30:C35) -> 261890.14 | R35: =SUM(D$30:D35) -> 226421.69 | S35: =SUM(E$30:E35) -> 158282.34 | T35: =SUM(F$30:F35) -> 722480.29 | U35: =SUM(F$30:F35)-T35 -> 0
A36: 44743 | B36: 12671.201 | C36: 41179.453 | D36: 39099.96 | E36: 27412.087 | F36: =SUM(B36:E36) -> 120362.7 | H36: 44743 | I36: 10035.94 | J36: 0 | K36: 2294.1256 | L36: 136.80383 | M36: =SUM(I36:L36) -> 12466.87 | O36: 22.7月累计 | P36: =SUM(B$30:B36) -> 88557.317 | Q36: =SUM(C$30:C36) -> 303069.6 | R36: =SUM(D$30:D36) -> 265521.65 | S36: =SUM(E$30:E36) -> 185694.43 | T36: =SUM(F$30:F36) -> 842842.99 | U36: =SUM(F$30:F36)-T36 -> 0
A37: 44774 | B37: 9372.45 | C37: 38654.479 | D37: 51219.403 | E37: 34192.42 | F37: =SUM(B37:E37) -> 133438.75 | H37: 44774 | I37: 10958.182 | J37: 11.8727 | K37: 2692.0308 | L37: 48.074971 | M37: =SUM(I37:L37) -> 13710.161 | O37: 22.8月累计 | P37: =SUM(B$30:B37) -> 97929.767 | Q37: =SUM(C$30:C37) -> 341724.08 | R37: =SUM(D$30:D37) -> 316741.05 | S37: =SUM(E$30:E37) -> 219886.85 | T37: =SUM(F$30:F37) -> 976281.74 | U37: =SUM(F$30:F37)-T37 -> 0
A38: 44805 | B38: 10606.299 | C38: 49317.65 | D38: 60488.792 | E38: 28355.042 | F38: =SUM(B38:E38) -> 148767.78 | H38: 44805 | I38: 4801.8929 | J38: 6.47468 | K38: 2407.4536 | L38: 48.727836 | M38: =SUM(I38:L38) -> 7264.5491 | O38: 22.9月累计 | P38: =SUM(B$30:B38) -> 108536.07 | Q38: =SUM(C$30:C38) -> 391041.73 | R38: =SUM(D$30:D38) -> 377229.84 | S38: =SUM(E$30:E38) -> 248241.89 | T38: =SUM(F$30:F38) -> 1125049.5 | U38: =SUM(F$30:F38)-T38 -> 0
A39: 44835 | B39: 13056.391 | C39: 43886.806 | D39: 51416.646 | E39: 34699.103 | F39: =SUM(B39:E39) -> 143058.95 | H39: 44835 | I39: 3925.7006 | J39: 9.18 | K39: 5752.1243 | L39: 100.50607 | M39: =SUM(I39:L39) -> 9787.5109 | O39: 22.10月累计 | P39: =SUM(B$30:B39) -> 121592.46 | Q39: =SUM(C$30:C39) -> 434928.53 | R39: =SUM(D$30:D39) -> 428646.49 | S39: =SUM(E$30:E39) -> 282940.99 | T39: =SUM(F$30:F39) -> 1268108.5 | U39: =SUM(F$30:F39)-T39 -> 0
A40: 44866 | B40: 17466.72 | C40: 45892.11 | D40: 70039.856 | E40: 41466.237 | F40: =SUM(B40:E40) -> 174864.92 | H40: 44866 | I40: 2767.0592 | J40: 16.5 | K40: 14435.598 | L40: 102.24792 | M40: =SUM(I40:L40) -> 17321.405 | O40: 22.11月累计 | P40: =SUM(B$30:B40) -> 139059.18 | Q40: =SUM(C$30:C40) -> 480820.64 | R40: =SUM(D$30:D40) -> 498686.34 | S40: =SUM(E$30:E40) -> 324407.23 | T40: =SUM(F$30:F40) -> 1442973.4 | U40: =SUM(F$30:F40)-T40 -> 0
A41: 44896 | B41: 16322.574 | C41: 36009.275 | D41: 77708.158 | E41: 41229.57 | F41: =SUM(B41:E41) -> 171269.58 | H41: 44896 | I41: 6465.6015 | J41: 12.68 | K41: 3854.7639 | L41: 48.219133 | M41: =SUM(I41:L41) -> 10381.265 | O41: 22.12月累计 | P41: =SUM(B$30:B41) -> 155381.75 | Q41: =SUM(C$30:C41) -> 516829.92 | R41: =SUM(D$30:D41) -> 576394.5 | S41: =SUM(E$30:E41) -> 365636.8 | T41: =SUM(F$30:F41) -> 1614243 | U41: =SUM(F$30:F41)-T41 -> 0
A42: 44927 | B42: 22985.957 | C42: 29278.75 | D42: 48836.984 | E42: 33479.892 | F42: =SUM(B42:E42) -> 134581.58 | H42: 44927 | I42: 8717.3265 | J42: 12.262499 | K42: 3675.8348 | L42: 181.94649 | M42: =SUM(I42:L42) -> 12587.37 | O42: 23.1月累计 | P42: =SUM(B$42:B42) -> 22985.957 | Q42: =SUM(C$42:C42) -> 29278.75 | R42: =SUM(D$42:D42) -> 48836.984 | S42: =SUM(E$42:E42) -> 33479.892 | T42: =SUM(F$42:F42) -> 134581.58 | U42: =SUM(F$42:F42)-T42 -> 0
A43: 44958 | B43: 13458.743 | C43: 38417.38 | D43: 45017.964 | E43: 35005.079 | F43: =SUM(B43:E43) -> 131899.17 | H43: 44958 | I43: 1957.218 | J43: 8.12 | K43: 3062.0267 | L43: 183.71913 | M43: =SUM(I43:L43) -> 5211.0838 | O43: 23.2月累计 | P43: =SUM(B$42:B43) -> 36444.7 | Q43: =SUM(C$42:C43) -> 67696.13 | R43: =SUM(D$42:D43) -> 93854.948 | S43: =SUM(E$42:E43) -> 68484.972 | T43: =SUM(F$42:F43) -> 266480.75 | U43: =SUM(F$42:F43)-T43 -> 0
A44: 44986 | B44: 17676.956 | C44: 40696.017 | D44: 46753.233 | E44: 48184.023 | F44: =SUM(B44:E44) -> 153310.23 | H44: 44986 | I44: 2461.8081 | J44: 9.03 | K44: 3598.4196 | L44: 346.83816 | M44: =SUM(I44:L44) -> 6416.0958 | O44: 23.3月累计 | P44: =SUM(B$42:B44) -> 54121.656 | Q44: =SUM(C$42:C44) -> 108392.15 | R44: =SUM(D$42:D44) -> 140608.18 | S44: =SUM(E$42:E44) -> 116668.99 | T44: =SUM(F$42:F44) -> 419790.98 | U44: =SUM(F$42:F44)-T44 -> 0
A45: 45017 | B45: 25100.247 | C45: 14908.958 | D45: 38626.757 | E45: 46617.332 | F45: =SUM(B45:E45) -> 125253.29 | H45: 45017 | I45: 5390.9896 | J45: 9.18 | K45: 2658.6327 | L45: 234.83171 | M45: =SUM(I45:L45) -> 8293.634 | O45: 23.4月累计 | P45: =SUM(B$42:B45) -> 79221.903 | Q45: =SUM(C$42:C45) -> 123301.1 | R45: =SUM(D$42:D45) -> 179234.94 | S45: =SUM(E$42:E45) -> 163286.33 | T45: =SUM(F$42:F45) -> 545044.27 | U45: =SUM(F$42:F45)-T45 -> 0
A46: 45047 | B46: 43935.387 | C46: 14554.824 | D46: 34806.915 | E46: 54574.306 | F46: =SUM(B46:E46) -> 147871.43 | H46: 45047 | I46: 3448.4603 | J46: 13.992 | K46: 3232.3424 | L46: 217.85892 | M46: =SUM(I46:L46) -> 6912.6536 | O46: 23.5月累计 | P46: =SUM(B$42:B46) -> 123157.29 | Q46: =SUM(C$42:C46) -> 137855.93 | R46: =SUM(D$42:D46) -> 214041.85 | S46: =SUM(E$42:E46) -> 217860.63 | T46: =SUM(F$42:F46) -> 692915.7 | U46: =SUM(F$42:F46)-T46 -> 0
A47: 45078 | B47: 32343.39 | C47: 18696.408 | D47: 40582.857 | E47: 65744.246 | F47: =SUM(B47:E47) -> 157366.9 | H47: 45078 | I47: 6201.1524 | J47: 14.215787 | K47: 7663.1537 | L47: 103.10123 | M47: =SUM(I47:L47) -> 13981.623 | O47: 23.6月累计 | P47: =SUM(B$42:B47) -> 155500.68 | Q47: =SUM(C$42:C47) -> 156552.34 | R47: =SUM(D$42:D47) -> 254624.71 | S47: =SUM(E$42:E47) -> 283604.88 | T47: =SUM(F$42:F47) -> 850282.61 | U47: =SUM(F$42:F47)-T47 -> 0
A48: 45108 | B48: 28119.744 | C48: 12591.962 | D48: 35418.136 | E48: 55283.671 | F48: =SUM(B48:E48) -> 131413.51 | H48: 45108 | I48: 4318.7701 | J48: 4.58556 | K48: 1258.7993 | L48: 153.71552 | M48: =SUM(I48:L48) -> 5735.8705 | O48: 23.7月累计 | P48: =SUM(B$42:B48) -> 183620.42 | Q48: =SUM(C$42:C48) -> 169144.3 | R48: =SUM(D$42:D48) -> 290042.85 | S48: =SUM(E$42:E48) -> 338888.55 | T48: =SUM(F$42:F48) -> 981696.12 | U48: =SUM(F$42:F48)-T48 -> 0
A49: 45139 | B49: 31944.261 | C49: 12342.18 | D49: 41823.418 | E49: 61102.222 | F49: =SUM(B49:E49) -> 147212.08 | H49: 45139 | I49: 3321.2574 | J49: 5.38556 | K49: 3013.4321 | L49: 163.52699 | M49: =SUM(I49:L49) -> 6503.6021 | O49: 23.8月累计 | P49: =SUM(B$42:B49) -> 215564.69 | Q49: =SUM(C$42:C49) -> 181486.48 | R49: =SUM(D$42:D49) -> 331866.26 | S49: =SUM(E$42:E49) -> 399990.77 | T49: =SUM(F$42:F49) -> 1128908.2 | U49: =SUM(F$42:F49)-T49 -> 0
A50: 45170 | B50: 26550.641 | C50: 9782.9884 | D50: 39707.166 | E50: 49936.582 | F50: =SUM(B50:E50) -> 125977.38 | H50: 45170 | I50: 2234.3568 | J50: 4.58556 | K50: 2310.1934 | L50: 487.66586 | M50: =SUM(I50:L50) -> 5036.8016 | O50: 23.9月累计 | P50: =SUM(B$42:B50) -> 242115.33 | Q50: =SUM(C$42:C50) -> 191269.47 | R50: =SUM(D$42:D50) -> 371573.43 | S50: =SUM(E$42:E50) -> 449927.35 | T50: =SUM(F$42:F50) -> 1254885.6 | U50: =SUM(F$42:F50)-T50 -> 0
A51: 45200 | B51: 12543.917 | C51: 7231.0873 | D51: 39956.302 | E51: 36591.304 | F51: =SUM(B51:E51) -> 96322.61 | H51: 45200 | I51: 6299.048 | J51: 4.58556 | K51: 5807.4646 | L51: 303.72356 | M51: =SUM(I51:L51) -> 12414.822 | O51: 23.10月累计 | P51: =SUM(B$42:B51) -> 254659.24 | Q51: =SUM(C$42:C51) -> 198500.56 | R51: =SUM(D$42:D51) -> 411529.73 | S51: =SUM(E$42:E51) -> 486518.66 | T51: =SUM(F$42:F51) -> 1351208.2 | U51: =SUM(F$42:F51)-T51 -> 0
A52: 45231 | B52: 19942.474 | C52: 8024.2668 | D52: 52214.699 | E52: 34336.302 | F52: =SUM(B52:E52) -> 114517.74 | H52: 45231 | I52: 3365.3592 | J52: 4.58556 | K52: 17449.895 | L52: 256.44079 | M52: =SUM(I52:L52) -> 21076.281 | O52: 23.11月累计 | P52: =SUM(B$42:B52) -> 274601.72 | Q52: =SUM(C$42:C52) -> 206524.82 | R52: =SUM(D$42:D52) -> 463744.43 | S52: =SUM(E$42:E52) -> 520854.96 | T52: =SUM(F$42:F52) -> 1465725.9 | U52: =SUM(F$42:F52)-T52 -> 0
A53: 45261 | B53: 13627.585 | C53: 5818.0122 | D53: 41859.163 | E53: 33422.887 | F53: =SUM(B53:E53) -> 94727.646 | H53: 45261 | I53: 3043.306 | J53: 1.40556 | K53: 6536.8039 | L53: 545.04105 | M53: =SUM(I53:L53) -> 10126.556 | O53: 23.12月累计 | P53: =SUM(B$42:B53) -> 288229.3 | Q53: =SUM(C$42:C53) -> 212342.83 | R53: =SUM(D$42:D53) -> 505603.59 | S53: =SUM(E$42:E53) -> 554277.85 | T53: =SUM(F$42:F53) -> 1560453.6 | U53: =SUM(F$42:F53)-T53 -> 0
A54: 45292 | B54: 23601.284 | C54: 5765.1169 | D54: 22038.104 | E54: 32437.158 | F54: =SUM(B54:E54) -> 83841.662 | H54: 45292 | I54: 2606.7452 | J54: 1.40556 | K54: 4146.2481 | L54: 408.75621 | M54: =SUM(I54:L54) -> 7163.1551 | O54: 24.1月累计 | P54: =B54 -> 23601.284 | Q54: =C54 -> 5765.1169 | R54: =D54 -> 22038.104 | S54: =E54 -> 32437.158 | T54: =SUM(F$54:F54) -> 83841.662 | U54: =SUM(F$54:F54)-T54 -> 0
A55: 45323 | B55: 20769.152 | C55: 5186.9185 | D55: 20630.623 | E55: 29631.355 | F55: =SUM(B55:E55) -> 76218.049 | H55: 45323 | I55: 10232.519 | K55: 3119.2019 | L55: 2032.2219 | M55: =SUM(I55:L55) -> 15383.942 | O55: 24.2月累计 | P55: =SUM(B$54:B55) -> 44370.436 | Q55: =SUM(C$54:C55) -> 10952.035 | R55: =SUM(D$54:D55) -> 42668.728 | S55: =SUM(E$54:E55) -> 62068.513 | T55: =SUM(F$54:F55) -> 160059.71 | U55: =SUM(F$54:F55)-T55 -> 0
A56: 45352 | B56: 8118.2167 | C56: 6157.9069 | D56: 24007.575 | E56: 28549.19 | F56: =SUM(B56:E56) -> 66832.889 | H56: 45352 | I56: 3172.7512 | K56: 3005.3106 | L56: 431.14546 | M56: =SUM(I56:L56) -> 6609.2073 | O56: 24.3月累计 | P56: =SUM(B$54:B56) -> 52488.653 | Q56: =SUM(C$54:C56) -> 17109.942 | R56: =SUM(D$54:D56) -> 66676.303 | S56: =SUM(E$54:E56) -> 90617.703 | T56: =SUM(F$54:F56) -> 226892.6 | U56: =SUM(F$54:F56)-T56 -> 0
A57: 45383 | B57: 6779.3447 | C57: 3106.4079 | D57: 23861.802 | E57: 16597.742 | F57: =SUM(B57:E57) -> 50345.297 | H57: 45383 | I57: 5056.8368 | K57: 3485.7076 | L57: 389.40499 | M57: =SUM(I57:L57) -> 8931.9493 | O57: 24.4月累计 | P57: =SUM(B$54:B57) -> 59267.997 | Q57: =SUM(C$54:C57) -> 20216.35 | R57: =SUM(D$54:D57) -> 90538.105 | S57: =SUM(E$54:E57) -> 107215.45 | T57: =SUM(F$54:F57) -> 277237.9 | U57: =SUM(F$54:F57)-T57 -> 0
A58: 45413 | B58: 11730.663 | C58: 2316.277 | D58: 29948.51 | E58: 26557.516 | F58: =SUM(B58:E58) -> 70552.966 | H58: 45413 | I58: 4967.366 | K58: 6648.8448 | L58: 531.37 | M58: =SUM(I58:L58) -> 12147.581 | O58: 24.5月累计 | P58: =SUM(B$54:B58) -> 70998.66 | Q58: =SUM(C$54:C58) -> 22532.627 | R58: =SUM(D$54:D58) -> 120486.61 | S58: =SUM(E$54:E58) -> 133772.96 | T58: =SUM(F$54:F58) -> 347790.86 | U58: =SUM(F$54:F58)-T58 -> 0
A59: 45444 | B59: 16980.061 | C59: 1416.8628 | D59: 34860.498 | E59: 30545.326 | F59: =SUM(B59:E59) -> 83802.748 | H59: 45444 | I59: 10999.47 | K59: 7520.4433 | L59: 723.3 | M59: =SUM(I59:L59) -> 19243.214 | O59: 24.6月累计 | P59: =SUM(B$54:B59) -> 87978.721 | Q59: =SUM(C$54:C59) -> 23949.49 | R59: =SUM(D$54:D59) -> 155347.11 | S59: =SUM(E$54:E59) -> 164318.29 | T59: =SUM(F$54:F59) -> 431593.61 | U59: =SUM(F$54:F59)-T59 -> 0
A60: 45474 | B60: 21559.693 | C60: 1491.3498 | D60: 24546.108 | E60: 34407.826 | F60: =SUM(B60:E60) -> 82004.978 | H60: 45474 | I60: 4406.6869 | K60: 1998.9466 | L60: 1224.3059 | M60: =SUM(I60:L60) -> 7629.9394 | O60: 24.7月累计 | P60: =SUM(B$54:B60) -> 109538.41 | Q60: =SUM(C$54:C60) -> 25440.84 | R60: =SUM(D$54:D60) -> 179893.22 | S60: =SUM(E$54:E60) -> 198726.11 | T60: =SUM(F$54:F60) -> 513598.59 | U60: =SUM(F$54:F60)-T60 -> 0
A61: 45505 | B61: 11582.725 | C61: 2548.1143 | D61: 30002.115 | E61: 31032.816 | F61: =SUM(B61:E61) -> 75165.771 | H61: 45505 | I61: 8877.5906 | K61: 3003.7321 | L61: 799.63586 | M61: =SUM(I61:L61) -> 12680.959 | O61: 24.8月累计 | P61: =SUM(B$54:B61) -> 121121.14 | Q61: =SUM(C$54:C61) -> 27988.954 | R61: =SUM(D$54:D61) -> 209895.34 | S61: =SUM(E$54:E61) -> 229758.93 | T61: =SUM(F$54:F61) -> 588764.36 | U61: =SUM(F$54:F61)-T61 -> 0
A62: 45536 | B62: 7748.1548 | C62: 1290.6205 | D62: 22928.796 | E62: 20650.533 | F62: =SUM(B62:E62) -> 52618.104 | H62: 45536 | I62: 2401.1597 | K62: 2945.145 | L62: 3606.8474 | M62: =SUM(I62:L62) -> 8953.152 | O62: 24.9月累计 | P62: =SUM(B$54:B62) -> 128869.29 | Q62: =SUM(C$54:C62) -> 29279.575 | R62: =SUM(D$54:D62) -> 232824.13 | S62: =SUM(E$54:E62) -> 250409.46 | T62: =SUM(F$54:F62) -> 641382.46 | U62: =SUM(F$54:F62)-T62 -> 0
A63: 45566 | B63: 8640.5599 | C63: 947.17146 | D63: 23255.981 | E63: 26167.658 | F63: =SUM(B63:E63) -> 59011.37 | H63: 45566 | I63: 2063.7107 | K63: 11952.29 | L63: 438.80086 | M63: =SUM(I63:L63) -> 14454.802 | O63: 24.10月累计 | P63: =SUM(B$54:B63) -> 137509.85 | Q63: =SUM(C$54:C63) -> 30226.746 | R63: =SUM(D$54:D63) -> 256080.11 | S63: =SUM(E$54:E63) -> 276577.12 | T63: =SUM(F$54:F63) -> 700393.83 | U63: =SUM(F$54:F63)-T63 -> 0
A64: 45597 | B64: 8649.1159 | C64: 695.88389 | D64: 25892.265 | E64: 26575.697 | F64: =SUM(B64:E64) -> 61812.962 | H64: 45597 | I64: 5278.1732 | J64: 0 | K64: 14752.049 | L64: 396.88679 | M64: =SUM(I64:L64) -> 20427.109 | O64: 24.11月累计 | P64: =SUM(B$54:B64) -> 146158.97 | Q64: =SUM(C$54:C64) -> 30922.63 | R64: =SUM(D$54:D64) -> 281972.38 | S64: =SUM(E$54:E64) -> 303152.82 | T64: =SUM(F$54:F64) -> 762206.8 | U64: =SUM(F$54:F64)-T64 -> 0
A65: 45627 | B65: 5261.5445 | C65: 616.13959 | D65: 26412.947 | E65: 27908.633 | F65: =SUM(B65:E65) -> 60199.264 | H65: 45627 | I65: 3527.5771 | J65: 0 | K65: 2807.241 | L65: 376.75544 | M65: =SUM(I65:L65) -> 6711.5736 | O65: 24.12月累计 | P65: =SUM(B$54:B65) -> 151420.51 | Q65: =SUM(C$54:C65) -> 31538.77 | R65: =SUM(D$54:D65) -> 308385.33 | S65: =SUM(E$54:E65) -> 331061.45 | T65: =SUM(F$54:F65) -> 822406.06 | U65: =SUM(F$54:F65)-T65 -> 0
A66: 45658 | B66: =('GMV销售额波动分析（分月、年）'!B2+'GMV销售额波动分析（分月、年）'!C2)/10000 -> 12010.341 | C66: ='GMV销售额波动分析（分月、年）'!D2/10000 -> 943.58125 | D66: ='GMV销售额波动分析（分月、年）'!E2/10000 -> 20356.185 | E66: =('GMV销售额波动分析（分月、年）'!F2+'GMV销售额波动分析（分月、年）'!G2)/10000 -> 36582.368 | F66: =SUM(B66:E66) -> 69892.476 | H66: 45658 | I66: 3873.4832 | J66: 0 | K66: 6787.7506 | L66: 7741.7946 | M66: =SUM(I66:L66) -> 18403.028 | O66: 25.1月累计 | P66: =B66 -> 12010.341 | Q66: =C66 -> 943.58125 | R66: =D66 -> 20356.185 | S66: =E66 -> 36582.368 | T66: =F66 -> 69892.476 | U66: =SUM(P66:S66)-T66 -> 0
A67: 45689 | B67: =('GMV销售额波动分析（分月、年）'!B3+'GMV销售额波动分析（分月、年）'!C3)/10000 -> 6319.9431 | C67: ='GMV销售额波动分析（分月、年）'!D3/10000 -> 1222.4513 | D67: ='GMV销售额波动分析（分月、年）'!E3/10000 -> 18650.532 | E67: =('GMV销售额波动分析（分月、年）'!F3+'GMV销售额波动分析（分月、年）'!G3)/10000 -> 29014.014 | F67: =SUM(B67:E67) -> 55206.939 | H67: 45689 | I67: 7770.2479 | J67: 0 | K67: 5019.5682 | L67: 8903.8486 | M67: =SUM(I67:L67) -> 21693.665 | O67: 25.2月累计 | P67: =SUM(B$66:B67) -> 18330.284 | Q67: =SUM(C$66:C67) -> 2166.0325 | R67: =SUM(D$66:D67) -> 39006.717 | S67: =SUM(E$66:E67) -> 65596.382 | T67: =SUM($F$66:F67) -> 125099.42 | U67: =SUM(P67:S67)-T67 -> 0
A68: 45717 | B68: =('GMV销售额波动分析（分月、年）'!B4+'GMV销售额波动分析（分月、年）'!C4)/10000 -> 6218.2107 | C68: ='GMV销售额波动分析（分月、年）'!D4/10000 -> 458.24586 | D68: ='GMV销售额波动分析（分月、年）'!E4/10000 -> 18891.607 | E68: =('GMV销售额波动分析（分月、年）'!F4+'GMV销售额波动分析（分月、年）'!G4)/10000 -> 41030.325 | F68: =SUM(B68:E68) -> 66598.388 | H68: 45717 | I68: 2919.8751 | J68: 0 | K68: 3716.8678 | L68: 9969.9799 | M68: =SUM(I68:L68) -> 16606.723 | O68: 25.3月累计 | P68: =SUM(B$66:B68) -> 24548.495 | Q68: =SUM(C$66:C68) -> 2624.2784 | R68: =SUM(D$66:D68) -> 57898.324 | S68: =SUM(E$66:E68) -> 106626.71 | T68: =SUM($F$66:F68) -> 191697.8 | U68: =SUM(P68:S68)-T68 -> 0
A69: 45748 | B69: =('GMV销售额波动分析（分月、年）'!B5+'GMV销售额波动分析（分月、年）'!C5)/10000 -> 7349.8678 | C69: ='GMV销售额波动分析（分月、年）'!D5/10000 -> 336.01438 | D69: ='GMV销售额波动分析（分月、年）'!E5/10000 -> 17304.789 | E69: =('GMV销售额波动分析（分月、年）'!F5+'GMV销售额波动分析（分月、年）'!G5)/10000 -> 35355.334 | F69: =SUM(B69:E69) -> 60346.005 | H69: 45748 | I69: 2883.8894 | J69: 0 | K69: 2811.4682 | L69: 11398.456 | M69: =SUM(I69:L69) -> 17093.813 | O69: 25.4月累计 | P69: =SUM(B$66:B69) -> 31898.362 | Q69: =SUM(C$66:C69) -> 2960.2928 | R69: =SUM(D$66:D69) -> 75203.113 | S69: =SUM(E$66:E69) -> 141982.04 | T69: =SUM($F$66:F69) -> 252043.81 | U69: =SUM(P69:S69)-T69 -> 0
A70: 45778 | B70: =('GMV销售额波动分析（分月、年）'!B6+'GMV销售额波动分析（分月、年）'!C6)/10000 -> 13757.203 | C70: ='GMV销售额波动分析（分月、年）'!D6/10000 -> 336.66039 | D70: ='GMV销售额波动分析（分月、年）'!E6/10000 -> 17290.566 | E70: =('GMV销售额波动分析（分月、年）'!F6+'GMV销售额波动分析（分月、年）'!G6)/10000 -> 29087.399 | F70: =SUM(B70:E70) -> 60471.829 | H70: 45778 | I70: 6031.1983 | J70: 0 | K70: 10702.347 | L70: 17000.655 | M70: =SUM(I70:L70) -> 33734.2 | O70: 25.5月累计 | P70: =SUM(B$66:B70) -> 45655.565 | Q70: =SUM(C$66:C70) -> 3296.9531 | R70: =SUM(D$66:D70) -> 92493.679 | S70: =SUM(E$66:E70) -> 171069.44 | T70: =SUM($F$66:F70) -> 312515.64 | U70: =SUM(P70:S70)-T70 -> 0
A71: 45809 | B71: =('GMV销售额波动分析（分月、年）'!B7+'GMV销售额波动分析（分月、年）'!C7)/10000 -> 8665.0436 | C71: ='GMV销售额波动分析（分月、年）'!D7/10000 -> 288.05918 | D71: ='GMV销售额波动分析（分月、年）'!E7/10000 -> 12474.516 | E71: =('GMV销售额波动分析（分月、年）'!F7+'GMV销售额波动分析（分月、年）'!G7)/10000 -> 35486.366 | F71: =SUM(B71:E71) -> 56913.985 | H71: 45809 | I71: 3554.3978 | J71: 0 | K71: 9380.5161 | L71: 15064.778 | M71: =SUM(I71:L71) -> 27999.692 | O71: 25.6月累计 | P71: =SUM(B$66:B71) -> 54320.609 | Q71: =SUM(C$66:C71) -> 3585.0123 | R71: =SUM(D$66:D71) -> 104968.2 | S71: =SUM(E$66:E71) -> 206555.81 | T71: =SUM($F$66:F71) -> 369429.62 | U71: =SUM(P71:S71)-T71 -> 0
A72: 45839 | B72: =('GMV销售额波动分析（分月、年）'!B8+'GMV销售额波动分析（分月、年）'!C8)/10000 -> 8752.1063 | C72: ='GMV销售额波动分析（分月、年）'!D8/10000 -> 295.71784 | D72: ='GMV销售额波动分析（分月、年）'!E8/10000 -> 7512.5965 | E72: =('GMV销售额波动分析（分月、年）'!F8+'GMV销售额波动分析（分月、年）'!G8)/10000 -> 46471.834 | F72: =SUM(B72:E72) -> 63032.255 | H72: 45839 | I72: 4542.4174 | J72: 0 | K72: 3666.3547 | L72: 4206.1797 | M72: =SUM(I72:L72) -> 12414.952 | O72: 25.7月累计 | P72: =SUM(B$66:B72) -> 63072.715 | Q72: =SUM(C$66:C72) -> 3880.7302 | R72: =SUM(D$66:D72) -> 112480.79 | S72: =SUM(E$66:E72) -> 253027.64 | T72: =SUM($F$66:F72) -> 432461.88 | U72: =SUM(P72:S72)-T72 -> 0
A73: 45870 | F73: =SUM(B73:E73) -> 0 | H73: 45870 | M73: =SUM(I73:L73) -> 0 | O73: 25.8月累计 | P73: =SUM(B$66:B73) -> 63072.715 | Q73: =SUM(C$66:C73) -> 3880.7302 | R73: =SUM(D$66:D73) -> 112480.79 | S73: =SUM(E$66:E73) -> 253027.64 | T73: =SUM($F$66:F73) -> 432461.88 | U73: =SUM(P73:S73)-T73 -> 0
A74: 45901 | F74: =SUM(B74:E74) -> 0 | H74: 45901 | M74: =SUM(I74:L74) -> 0 | O74: 25.9月累计 | P74: =SUM(B$66:B74) -> 63072.715 | Q74: =SUM(C$66:C74) -> 3880.7302 | R74: =SUM(D$66:D74) -> 112480.79 | S74: =SUM(E$66:E74) -> 253027.64 | T74: =SUM($F$66:F74) -> 432461.88 | U74: =SUM(P74:S74)-T74 -> 0
A75: 45931 | F75: =SUM(B75:E75) -> 0 | H75: 45931 | M75: =SUM(I75:L75) -> 0 | O75: 25.10月累计 | P75: =SUM(B$66:B75) -> 63072.715 | Q75: =SUM(C$66:C75) -> 3880.7302 | R75: =SUM(D$66:D75) -> 112480.79 | S75: =SUM(E$66:E75) -> 253027.64 | T75: =SUM($F$66:F75) -> 432461.88 | U75: =SUM(P75:S75)-T75 -> 0
A76: 45962 | F76: =SUM(B76:E76) -> 0 | H76: 45962 | M76: =SUM(I76:L76) -> 0 | O76: 25.11月累计 | P76: =SUM(B$66:B76) -> 63072.715 | Q76: =SUM(C$66:C76) -> 3880.7302 | R76: =SUM(D$66:D76) -> 112480.79 | S76: =SUM(E$66:E76) -> 253027.64 | T76: =SUM($F$66:F76) -> 432461.88 | U76: =SUM(P76:S76)-T76 -> 0
A77: 45992 | F77: =SUM(B77:E77) -> 0 | H77: 45992 | M77: =SUM(I77:L77) -> 0 | O77: 25.12月累计 | P77: =SUM(B$66:B77) -> 63072.715 | Q77: =SUM(C$66:C77) -> 3880.7302 | R77: =SUM(D$66:D77) -> 112480.79 | S77: =SUM(E$66:E77) -> 253027.64 | T77: =SUM($F$66:F77) -> 432461.88 | U77: =SUM(P77:S77)-T77 -> 0
A80: 2020.1-本月 | B80: =SUM(B6:B17) -> 183990.99 | C80: =SUM(C6:C17) -> 950273.65 | D80: =SUM(D6:D17) -> 258196.51 | E80: =SUM(E6:E17) -> 65422.821 | F80: =SUM(B80:E80) -> 1457884
A81: 2021.1-本月 | B81: =SUM(B18:B29) -> 149783.39 | C81: =SUM(C18:C29) -> 1285695.5 | D81: =SUM(D18:D29) -> 557804.69 | E81: =SUM(E18:E29) -> 155448.04 | F81: =SUM(B81:E81) -> 2148731.6 | M81: =SUM(M42:M53) -> 114296.39
A82: 2022.1-本月 | B82: =SUM(B30:B41) -> 155381.75 | C82: =SUM(C30:C41) -> 516829.92 | D82: =SUM(D30:D41) -> 576394.5 | E82: =SUM(E30:E41) -> 365636.8 | F82: =SUM(B82:E82) -> 1614243 | M82: =M81-'[33]代运营店铺GMV统计2023年1-12月'!$AS$15 -> #REF!
A83: 2023.1-本月 | B83: =SUM(B42:B48) -> 183620.42 | C83: =SUM(C42:C48) -> 169144.3 | D83: =SUM(D42:D48) -> 290042.85 | E83: =SUM(E42:E48) -> 338888.55 | F83: =SUM(B83:E83) -> 981696.12 | M83: =SUM(M66:M77) -> 147946.07 | O83: 变动 | P83: =P72-P60 -> -46465.699 | Q83: =Q72-Q60 -> -21560.11 | R83: =R72-R60 -> -67412.43 | S83: =S72-S60 -> 54301.525 | T83: =T72-T60 -> -81136.713
A84: 2024.1-本月 | B84: =SUM(B54:B60) -> 109538.41 | C84: =SUM(C54:C60) -> 25440.84 | D84: =SUM(D54:D60) -> 179893.22 | E84: =SUM(E54:E60) -> 198726.11 | F84: =SUM(B84:E84) -> 513598.59 | M84: =M83-'[36]代运营店铺GMV统计2025年1-12月'!$AR$14/10000 -> 0 | P84: =P83/P60 -> -0.42419547 | Q84: =Q83/Q60 -> -0.84746061 | R84: =R83/R60 -> -0.3747358 | S84: =S83/S60 -> 0.27324806 | T84: =T83/T60 -> -0.1579769
A85: 2025.1-本月 | B85: =SUM(B66:B77) -> 63072.715 | C85: =SUM(C66:C77) -> 3880.7302 | D85: =SUM(D66:D77) -> 112480.79 | E85: =SUM(E66:E77) -> 253027.64 | F85: =SUM(B85:E85) -> 432461.88
A87: 20年占比 | B87: =B80/$F$80 -> 0.12620414 | C87: =C80/$F$80 -> 0.65181706 | D87: =D80/$F$80 -> 0.1771036 | E87: =E80/$F$80 -> 0.044875191 | F87: =SUM(B87:E87) -> 1
A88: 21年占比 | B88: =B81/$F$81 -> 0.069707818 | C88: =C81/$F$81 -> 0.59835089 | D88: =D81/$F$81 -> 0.2595972 | E88: =E81/$F$81 -> 0.072344094 | F88: =SUM(B88:E88) -> 1
A89: 22年占比 | B89: =B82/$F$82 -> 0.09625673 | C89: =C82/$F$82 -> 0.3201686 | D89: =D82/$F$82 -> 0.357068 | E89: =E82/$F$82 -> 0.22650667 | F89: =SUM(B89:E89) -> 1
A90: 23年占比 | B90: =B83/$F$83 -> 0.18704406 | C90: =C83/$F$83 -> 0.17229802 | D90: =D83/$F$83 -> 0.29545074 | E90: =E83/$F$83 -> 0.34520718 | F90: =SUM(B90:E90) -> 1
A91: 24年占比 | B91: =B84/$F$84 -> 0.21327631 | C91: =C84/$F$84 -> 0.049534481 | D91: =D84/$F$84 -> 0.35026035 | E91: =E84/$F$84 -> 0.38692885 | F91: =SUM(B91:E91) -> 1
A92: 25年占比 | B92: =B85/$F$85 -> 0.14584572 | C92: =C85/$F$85 -> 0.0089735775 | D92: =D85/$F$85 -> 0.26009412 | E92: =E85/$F$85 -> 0.58508658 | F92: =SUM(B92:E92) -> 1
A93: 增长 | B93: =B85-B84 -> -46465.699 | C93: =C85-C84 -> -21560.11 | D93: =D85-D84 -> -67412.43 | E93: =E85-E84 -> 54301.525 | F93: =F85-F84 -> -81136.713
A94: 增长比率 | B94: =B93/B84 -> -0.42419547 | C94: =C93/C84 -> -0.84746061 | D94: =D93/D84 -> -0.3747358 | E94: =E93/E84 -> 0.27324806 | F94: =F93/F84 -> -0.1579769
A97: 45108
A98: 45474
A99: 45839

Sheet GMV表-品牌
A1: 3、品牌趋势波动，针对网娱、生活服务--22年数据波动做分析（分月）-只针对代理收入（订单差额收入+返点） | K1: 1月 | L1: 品牌分类 | M1: 求和项:调整后gmv | N1: 万元
A2: 网娱-GMV | L2: 生活-餐饮 | M2: 21763660 | N2: =M2/10000 -> 2176.366 | P2: 2024年 | Z2: 2023年 | AJ2: 2022年
A3: 月份 | B3: 网娱-影视会员 | C3: 网娱-音频 | D3: 网娱-视频直播 | E3: 网娱-知识阅读 | F3: 网娱-网络工具 | G3: 网娱-其他 | H3: 合计 | I3: check | L3: 生活-出行旅游 | M3: 7176144.8 | N3: =M3/10000 -> 717.61448 | P3: 月份 | Q3: 网娱-影视会员 | R3: 网娱-音频 | S3: 网娱-视频直播 | T3: 网娱-知识阅读 | U3: 网娱-网络工具 | V3: 网娱-其他 | W3: 合计 | X3: check | Z3: 月份 | AA3: 网娱-影视会员 | AB3: 网娱-音频 | AC3: 网娱-视频直播 | AD3: 网娱-知识阅读 | AE3: 网娱-网络工具 | AF3: 网娱-其他 | AG3: 合计 | AH3: check | AJ3: 月份 | AK3: 网娱-影视会员 | AL3: 网娱-音频 | AM3: 网娱-视频直播 | AN3: 网娱-知识阅读 | AO3: 网娱-网络工具 | AP3: 网娱-其他 | AQ3: 合计 | AR3: check
A4: 45658 | B4: =VLOOKUP(B$3,$L$1:$N$15,3,0) -> 6136.9116 | C4: =VLOOKUP(C$3,$L$1:$N$15,3,0) -> 1001.6234 | D4: =VLOOKUP(D$3,$L$1:$N$15,3,0) -> 12126.944 | E4: =VLOOKUP(E$3,$L$1:$N$15,3,0) -> 118.95727 | F4: =VLOOKUP(F$3,$L$1:$N$15,3,0) -> 990.5272 | G4: ='GMV表-商品大类'!D66-SUM(B4:F4) -> -18.777799 | H4: =SUM(B4:G4) -> 20356.185 | I4: =H4-'GMV表-商品大类'!D66 -> 0 | L4: 生活-购物（优惠劵） | M4: 3.2960084e+08 | N4: =M4/10000 -> 32960.084 | P4: 45292 | Q4: 8007.145 | R4: 1178.9017 | S4: 11963.61 | T4: 161.48681 | U4: 728.8358 | V4: =W4-SUM(Q4:U4) -> -1.87553 | W4: 22038.104 | X4: 0 | Z4: 44927 | AA4: 13288.648 | AB4: 2371.8514 | AC4: 32898.797 | AD4: 82.789323 | AE4: 231.63907 | AF4: -36.742008 | AG4: 48836.984 | AH4: 0 | AJ4: 44562 | AK4: 9884.6438 | AL4: 2395.7681 | AM4: 19925.16 | AN4: 97.152787 | AO4: 97.262358 | AP4: 32.057581 | AQ4: 32432.045 | AR4: 0
A5: 45689 | B5: =VLOOKUP(B$3,$L$18:$N$32,3,0) -> 5256.2006 | C5: =VLOOKUP(C$3,$L$18:$N$32,3,0) -> 1095.8763 | D5: =VLOOKUP(D$3,$L$18:$N$32,3,0) -> 11005.474 | E5: =VLOOKUP(E$3,$L$18:$N$32,3,0) -> 246.71841 | F5: =VLOOKUP(F$3,$L$18:$N$32,3,0) -> 1046.8678 | G5: ='GMV表-商品大类'!D67-SUM(B5:F5) -> -0.60574971 | H5: =SUM(B5:G5) -> 18650.532 | I5: =H5-'GMV表-商品大类'!D67 -> 0 | L5: 生活-加油卡 | M5: 162409.09 | N5: =M5/10000 -> 16.240909 | P5: 45323 | Q5: 8107.7725 | R5: 976.13699 | S5: 10649.628 | T5: 163.12905 | U5: 738.26716 | V5: =W5-SUM(Q5:U5) -> -4.310721 | W5: 20630.623 | X5: 0 | Z5: 44958 | AA5: 11012.898 | AB5: 2054.4455 | AC5: 31469.653 | AD5: 41.977595 | AE5: 354.57548 | AF5: 84.415525 | AG5: 45017.964 | AH5: 0 | AJ5: 44593 | AK5: 6650.3413 | AL5: 2147.2207 | AM5: 16050.732 | AN5: 59.040987 | AO5: 107.80277 | AP5: 218.66487 | AQ5: 25233.803 | AR5: 0
A6: 45717 | B6: =VLOOKUP(B$3,$L$35:$N$49,3,0) -> 4185.8648 | C6: =VLOOKUP(C$3,$L$35:$N$49,3,0) -> 886.27518 | D6: =VLOOKUP(D$3,$L$35:$N$49,3,0) -> 12420.599 | E6: =VLOOKUP(E$3,$L$35:$N$49,3,0) -> 243.3437 | F6: =VLOOKUP(F$3,$L$35:$N$49,3,0) -> 1133.7677 | G6: ='GMV表-商品大类'!D68-SUM(B6:F6) -> 21.756874 | H6: =SUM(B6:G6) -> 18891.607 | I6: =H6-'GMV表-商品大类'!D68 -> 0 | L6: 生活-健身 | M6: 4195.5 | N6: =M6/10000 -> 0.41955 | P6: 45352 | Q6: 7833.4078 | R6: 1425.4372 | S6: 13347.026 | T6: 152.42028 | U6: 1166.4472 | V6: =W6-SUM(Q6:U6) -> 82.836471 | W6: 24007.575 | X6: 0 | Z6: 44986 | AA6: 8861.1788 | AB6: 2290.5691 | AC6: 34891.966 | AD6: 58.436207 | AE6: 659.28424 | AF6: -8.201291 | AG6: 46753.233 | AH6: 0 | AJ6: 44621 | AK6: 6114.3128 | AL6: 3405.9464 | AM6: 33595.873 | AN6: 71.032405 | AO6: 717.49484 | AP6: 475.79985 | AQ6: 44380.459 | AR6: 0
A7: 45748 | B7: =VLOOKUP(B$3,$L$52:$N$66,3,0) -> 3633.7744 | C7: =VLOOKUP(C$3,$L$52:$N$66,3,0) -> 913.8416 | D7: =VLOOKUP(D$3,$L$52:$N$66,3,0) -> 11286.297 | E7: =VLOOKUP(E$3,$L$52:$N$66,3,0) -> 418.13622 | F7: =VLOOKUP(F$3,$L$52:$N$66,3,0) -> 1069.4332 | G7: ='GMV表-商品大类'!D69-SUM(B7:F7) -> -16.693418 | H7: =SUM(B7:G7) -> 17304.789 | I7: =H7-'GMV表-商品大类'!D69 -> 0 | L7: 生活-其他 | M7: 6856425.3 | N7: =M7/10000 -> 685.64253 | P7: 45383 | Q7: 8414.7986 | R7: 1072.0431 | S7: 13361.422 | T7: 181.15543 | U7: 718.46254 | V7: =W7-SUM(Q7:U7) -> 113.92023 | W7: 23861.802 | X7: 0 | Z7: 45017 | AA7: 7121.9032 | AB7: 2735.0578 | AC7: 28249.361 | AD7: 164.80577 | AE7: 362.39784 | AF7: -6.768789 | AG7: 38626.757 | AH7: 0 | AJ7: 44652 | AK7: 5045.4885 | AL7: 4748.0726 | AM7: 24625.747 | AN7: 96.921017 | AO7: 139.77051 | AP7: 311.36089 | AQ7: 34967.361 | AR7: 0
A8: 45778 | B8: =VLOOKUP(B$3,$L$69:$N$83,3,0) -> 4773.8702 | C8: =VLOOKUP(C$3,$L$69:$N$83,3,0) -> 833.37946 | D8: =VLOOKUP(D$3,$L$69:$N$83,3,0) -> 9471.5385 | E8: =VLOOKUP(E$3,$L$69:$N$83,3,0) -> 581.97345 | F8: =VLOOKUP(F$3,$L$69:$N$83,3,0) -> 1618.3066 | G8: ='GMV表-商品大类'!D70-SUM(B8:F8) -> 11.498163 | H8: =SUM(B8:G8) -> 17290.566 | I8: =H8-'GMV表-商品大类'!D70 -> 0 | L8: 网娱-其他 | M8: 15672.48 | N8: =M8/10000 -> 1.567248 | P8: 45413 | Q8: 8499.6206 | R8: 966.02983 | S8: 19570.386 | T8: 284.77214 | U8: 621.69576 | V8: =W8-SUM(Q8:U8) -> 6.0059673 | W8: 29948.51 | X8: 0 | Z8: 45047 | AA8: 10431.345 | AB8: 2253.56 | AC8: 21805.577 | AD8: 55.003518 | AE8: 265.45754 | AF8: -4.028302 | AG8: 34806.915 | AH8: 0 | AJ8: 44682 | AK8: 7991.853 | AL8: 3536.1416 | AM8: 27144.016 | AN8: 106.16313 | AO8: 142.35382 | AP8: 161.28007 | AQ8: 39081.808 | AR8: 0
A9: 45809 | B9: =VLOOKUP(B$3,$L$87:$N$101,3,0) -> 6039.9085 | C9: =VLOOKUP(C$3,$L$87:$N$101,3,0) -> 690.58656 | D9: =VLOOKUP(D$3,$L$87:$N$101,3,0) -> 3322.6469 | E9: =VLOOKUP(E$3,$L$87:$N$101,3,0) -> 524.37156 | F9: =VLOOKUP(F$3,$L$87:$N$101,3,0) -> 1892.7845 | G9: ='GMV表-商品大类'!D71-SUM(B9:F9) -> 4.2181614 | H9: =SUM(B9:G9) -> 12474.516 | I9: =H9-'GMV表-商品大类'!D71 -> 0 | L9: 网娱-视频直播 | M9: 1.2126944e+08 | N9: =M9/10000 -> 12126.944 | P9: 45444 | Q9: 7606.331 | R9: 1061.4681 | S9: 25825.334 | T9: 229.03323 | U9: 579.31108 | V9: =W9-SUM(Q9:U9) -> -440.9792 | W9: 34860.498 | X9: 0 | Z9: 45078 | AA9: 15369.437 | AB9: 3149.5073 | AC9: 21568.204 | AD9: 181.57805 | AE9: 162.29595 | AF9: 151.83503 | AG9: 40582.857 | AH9: 0 | AJ9: 44713 | AK9: 11112.306 | AL9: 4444.2431 | AM9: 34288.44 | AN9: 86.107677 | AO9: 279.1332 | AP9: 115.98048 | AQ9: 50326.21 | AR9: 0
A10: 45839 | B10: =VLOOKUP(B$3,$L$105:$N$119,3,0) -> 2908.1989 | C10: =VLOOKUP(C$3,$L$105:$N$119,3,0) -> 809.56797 | D10: =VLOOKUP(D$3,$L$105:$N$119,3,0) -> 2149.1404 | E10: =VLOOKUP(E$3,$L$105:$N$119,3,0) -> 423.09725 | F10: =VLOOKUP(F$3,$L$105:$N$119,3,0) -> 1215.4211 | G10: ='GMV表-商品大类'!D72-SUM(B10:F10) -> 7.1708805 | H10: =SUM(B10:G10) -> 7512.5965 | I10: =H10-'GMV表-商品大类'!D72 -> 0 | L10: 网娱-网络工具 | M10: 9905272 | N10: =M10/10000 -> 990.5272 | P10: 45474 | Q10: 4572.8206 | R10: 665.63075 | S10: 18787.386 | T10: 141.31103 | U10: 351.29139 | V10: =W10-SUM(Q10:U10) -> 27.668088 | W10: 24546.108 | X10: 0 | Z10: 45108 | AA10: 10216.145 | AB10: 844.93033 | AC10: 23913.598 | AD10: 55.022786 | AE10: 377.89675 | AF10: 10.543836 | AG10: 35418.136 | AH10: 0 | AJ10: 44743 | AK10: 6927.9175 | AL10: 3863.3423 | AM10: 27571.984 | AN10: 83.446368 | AO10: 568.88 | AP10: 84.389438 | AQ10: 39099.96 | AR10: 0
A11: 45870 | B11: =VLOOKUP(B$3,$L$123:$N$137,3,0) -> 0 | C11: =VLOOKUP(C$3,$L$123:$N$137,3,0) -> 0 | D11: =VLOOKUP(D$3,$L$123:$N$137,3,0) -> 0 | E11: =VLOOKUP(E$3,$L$123:$N$137,3,0) -> 0 | F11: =VLOOKUP(F$3,$L$123:$N$137,3,0) -> 0 | G11: ='GMV表-商品大类'!D73-SUM(B11:F11) -> 0 | H11: =SUM(B11:G11) -> 0 | I11: =H11-'GMV表-商品大类'!D73 -> 0 | L11: 网娱-音频 | M11: 10016234 | N11: =M11/10000 -> 1001.6234 | P11: 45505 | Q11: 5399.8301 | R11: 1309.9135 | S11: 22646.513 | T11: 190.63347 | U11: 417.68975 | V11: =W11-SUM(Q11:U11) -> 37.535276 | W11: 30002.115 | X11: 0 | Z11: 45139 | AA11: 12282.884 | AB11: 2893.3351 | AC11: 26302.745 | AD11: 113.38709 | AE11: 181.33369 | AF11: 49.73385 | AG11: 41823.418 | AH11: 0 | AJ11: 44774 | AK11: 10210.136 | AL11: 5164.4147 | AM11: 35440.571 | AN11: 138.62084 | AO11: 210.15898 | AP11: 55.501406 | AQ11: 51219.403 | AR11: 0
A12: 45901 | B12: =VLOOKUP(B$3,$L$141:$N$156,3,0) -> 0 | C12: =VLOOKUP(C$3,$L$141:$N$156,3,0) -> 0 | D12: =VLOOKUP(D$3,$L$141:$N$156,3,0) -> 0 | E12: =VLOOKUP(E$3,$L$141:$N$156,3,0) -> 0 | F12: =VLOOKUP(F$3,$L$141:$N$156,3,0) -> 0 | G12: ='GMV表-商品大类'!D74-SUM(B12:F12) -> 0 | H12: =SUM(B12:G12) -> 0 | I12: =H12-'GMV表-商品大类'!D74 -> 0 | L12: 网娱-影视会员 | M12: 61369116 | N12: =M12/10000 -> 6136.9116 | P12: 45536 | Q12: 5591.8829 | R12: 1000.2826 | S12: 15574.485 | T12: 163.61239 | U12: 628.20774 | V12: =W12-SUM(Q12:U12) -> -29.674593 | W12: 22928.796 | X12: 0 | Z12: 45170 | AA12: 9903.629 | AB12: 1782.8105 | AC12: 27656.213 | AD12: 67.001426 | AE12: 204.13624 | AF12: 93.375472 | AG12: 39707.166 | AH12: 0 | AJ12: 44805 | AK12: 9354.7391 | AL12: 3448.5099 | AM12: 47059.399 | AN12: 50.914779 | AO12: 531.49097 | AP12: 43.73871 | AQ12: 60488.792 | AR12: 0
A13: 45931 | B13: =VLOOKUP(B$3,$L$159:$N$173,3,0) -> 0 | C13: =VLOOKUP(C$3,$L$159:$N$173,3,0) -> 0 | D13: =VLOOKUP(D$3,$L$159:$N$173,3,0) -> 0 | E13: =VLOOKUP(E$3,$L$159:$N$173,3,0) -> 0 | F13: =VLOOKUP(F$3,$L$159:$N$173,3,0) -> 0 | G13: ='GMV表-商品大类'!D75-SUM(B13:F13) -> 0 | H13: =SUM(B13:G13) -> 0 | I13: =H13-'GMV表-商品大类'!D75 -> 0 | L13: 网娱-知识阅读 | M13: 1189572.7 | N13: =M13/10000 -> 118.95727 | P13: 45566 | Q13: 6468.5198 | R13: 1404.5234 | S13: 14117.225 | T13: 335.07355 | U13: 905.78774 | V13: =W13-SUM(Q13:U13) -> 24.851996 | W13: 23255.981 | X13: 0 | Z13: 45200 | AA13: 12285.089 | AB13: 2025.4978 | AC13: 25105.259 | AD13: 409.81748 | AE13: 122.34653 | AF13: 8.292424 | AG13: 39956.302 | AH13: 0 | AJ13: 44835 | AK13: 11006.977 | AL13: 3568.4804 | AM13: 36415.133 | AN13: 49.642019 | AO13: 334.6951 | AP13: 41.718834 | AQ13: 51416.646 | AR13: 0
A14: 45962 | B14: =VLOOKUP(B$3,$L$177:$N$191,3,0) -> 0 | C14: =VLOOKUP(C$3,$L$177:$N$191,3,0) -> 0 | D14: =VLOOKUP(D$3,$L$177:$N$191,3,0) -> 0 | E14: =VLOOKUP(E$3,$L$177:$N$191,3,0) -> 0 | F14: =VLOOKUP(F$3,$L$177:$N$191,3,0) -> 0 | G14: ='GMV表-商品大类'!D76-SUM(B14:F14) -> 0 | H14: =SUM(B14:G14) -> 0 | I14: =H14-'GMV表-商品大类'!D76 -> 0 | L14: #N/A | M14: 1.2973523e+08 | N14: =M14/10000 -> 12973.523 | P14: 45597 | Q14: 6842.708 | R14: 2232.4843 | S14: 15441.868 | T14: 248.02302 | U14: 1146.8351 | V14: =W14-SUM(Q14:U14) -> -19.653273 | W14: 25892.265 | X14: 0 | Z14: 45231 | AA14: 20147.536 | AB14: 3621.0938 | AC14: 27859.796 | AD14: 248.62431 | AE14: 361.73383 | AF14: -24.084945 | AG14: 52214.699 | AH14: 0 | AJ14: 44866 | AK14: 17588.434 | AL14: 4638.7749 | AM14: 47244.208 | AN14: 174.5533 | AO14: 234.21075 | AP14: 159.67442 | AQ14: 70039.856 | AR14: 0
A15: 45992 | B15: =VLOOKUP(B$3,$L$195:$N$209,3,0) -> 0 | C15: =VLOOKUP(C$3,$L$195:$N$209,3,0) -> 0 | D15: =VLOOKUP(D$3,$L$195:$N$209,3,0) -> 0 | E15: =VLOOKUP(E$3,$L$195:$N$209,3,0) -> 0 | F15: =VLOOKUP(F$3,$L$195:$N$209,3,0) -> 0 | G15: ='GMV表-商品大类'!D77-SUM(B15:F15) -> 0 | H15: =SUM(B15:G15) -> 0 | I15: =H15-'GMV表-商品大类'!D77 -> 0 | L15: 总计 | M15: =SUM(M2:M14) -> 6.9906421e+08 | N15: =SUM(N2:N14) -> 69906.421 | P15: 45627 | Q15: 5009.3885 | R15: 1217.7879 | S15: 18798.896 | T15: 205.09285 | U15: 1071.1167 | V15: =W15-SUM(Q15:U15) -> 110.66501 | W15: 26412.947 | X15: 0 | Z15: 45261 | AA15: 9294.4974 | AB15: 3250.161 | AC15: 28589.034 | AD15: 110.71617 | AE15: 633.28795 | AF15: -18.534297 | AG15: 41859.163 | AH15: 0 | AJ15: 44896 | AK15: 9207.6291 | AL15: 3740.0809 | AM15: 63841.177 | AN15: 58.520539 | AO15: 694.86699 | AP15: 165.88354 | AQ15: 77708.158 | AR15: 0
A16: 合计 | B16: =SUM(B4:B15) -> 32934.729 | C16: =SUM(C4:C15) -> 6231.1505 | D16: =SUM(D4:D15) -> 61782.639 | E16: =SUM(E4:E15) -> 2556.5979 | F16: =SUM(F4:F15) -> 8967.1081 | G16: =SUM(G4:G15) -> 8.5671119 | H16: =SUM(H4:H15) -> 112480.79 | I16: =H16-'GMV表-商品大类'!D85 -> 0 | P16: 合计 | Q16: =SUM(Q4:Q10) -> 53041.896 | R16: =SUM(R4:R10) -> 7345.6477 | S16: =SUM(S4:S10) -> 113504.79 | T16: =SUM(T4:T10) -> 1313.308 | U16: =SUM(U4:U10) -> 4904.311 | V16: =SUM(V4:V10) -> -216.73469 | W16: =SUM(W4:W10) -> 179893.22 | X16: 0 | Z16: 合计 | AA16: =SUM(AA4:AA10) -> 76301.554 | AB16: =SUM(AB4:AB10) -> 15699.921 | AC16: =SUM(AC4:AC10) -> 194797.16 | AD16: =SUM(AD4:AD10) -> 639.61325 | AE16: =SUM(AE4:AE10) -> 2413.5469 | AF16: =SUM(AF4:AF10) -> 191.054 | AG16: =SUM(AG4:AG10) -> 290042.85 | AH16: 0 | AJ16: 合计 | AK16: =SUM(AK4:AK15) -> 111094.78 | AL16: =SUM(AL4:AL15) -> 45100.996 | AM16: =SUM(AM4:AM15) -> 413202.44 | AN16: =SUM(AN4:AN15) -> 1072.1158 | AO16: =SUM(AO4:AO15) -> 4058.1203 | AP16: =SUM(AP4:AP15) -> 1866.0501 | AQ16: =SUM(AQ4:AQ15) -> 576394.5 | AR16: 0
A17: 占比 | B17: =B16/$H$16 -> 0.29280314 | C17: =C16/$H$16 -> 0.055397463 | D17: =D16/$H$16 -> 0.5492728 | E17: =E16/$H$16 -> 0.022729195 | F17: =F16/$H$16 -> 0.079721239 | G17: =G16/$H$16 -> 7.616511e-05 | P17: 占比 | Q17: =Q16/$W$16 -> 0.29485211 | R17: =R16/$W$16 -> 0.040833377 | S17: =S16/$W$16 -> 0.63095648 | T17: =T16/$W$16 -> 0.0073004862 | U17: =U16/$W$16 -> 0.027262344 | V17: =V16/$W$16 -> -0.0012047963 | Z17: 占比 | AA17: =AA16/$AG$16 -> 0.26306994 | AB17: =AB16/$AG$16 -> 0.054129663 | AC17: =AC16/$AG$16 -> 0.6716151 | AD17: =AD16/$AG$16 -> 0.0022052371 | AE17: =AE16/$AG$16 -> 0.008321346 | AF17: =AF16/$AG$16 -> 0.00065870958 | AJ17: 占比 | AK17: 0.1927409 | AL17: 0.078246749 | AM17: 0.71687436 | AN17: 0.0018600383 | AO17: 0.0070405257 | AP17: 0.003237453
A18: 变动 | B18: =B16-Q16 -> -20107.167 | C18: =C16-R16 -> -1114.4972 | D18: =D16-S16 -> -51722.154 | E18: =E16-T16 -> 1243.2899 | F18: =F16-U16 -> 4062.7971 | G18: =G16-V16 -> 225.3018 | H18: =H16-W16 -> -67412.43 | I18: =H18-'GMV表-商品大类'!D93 -> 0 | K18: 2月 | L18: 品牌分类 | M18: 求和项:调整后gmv | N18: 万元 | Z18: 22年 | AJ18: 21年
L19: 生活-餐饮 | M19: 22290274 | N19: =M19/10000 -> 2229.0274 | Z19: 变动 | AJ19: 变动 | AK19: -51717.326 | AL19: -14847.966 | AM19: -270913.06
A20: 生活服务-GMV | L20: 生活-出行旅游 | M20: 2530736.5 | N20: =M20/10000 -> 253.07365 | P20: 生活服务-GMV | S20: -0.37569884 | Z20: 生活服务-GMV | AJ20: 生活服务-GMV
A21: 月份 | B21: 生活-加油卡 | C21: 生活-出行旅游 | D21: 生活-餐饮 | E21: 生活-立减金 | F21: 生活-购物（优惠劵） | G21: 生活-其他 | H21: 合计 | I21: check | L21: 生活-购物（优惠劵） | M21: 2.599457e+08 | N21: =M21/10000 -> 25994.57 | P21: 月份 | Q21: 生活-加油卡 | R21: 生活-出行旅游 | S21: 生活-餐饮 | T21: 生活-立减金 | U21: 生活-购物（优惠劵） | V21: 生活-其他 | W21: 合计 | X21: check | Z21: 月份 | AA21: 生活-加油卡 | AB21: 生活-出行旅游 | AC21: 生活-餐饮 | AD21: 生活-立减金 | AE21: 生活-购物（优惠劵） | AF21: 生活-其他 | AG21: 合计 | AH21: check | AJ21: 月份 | AK21: 生活-加油卡 | AL21: 生活-出行旅游 | AM21: 生活-餐饮 | AN21: 生活-购物（优惠劵） | AO21: 生活-健身 | AP21: 生活-其他 | AQ21: 合计 | AR21: check
A22: 45658 | B22: =VLOOKUP(B$21,$L$1:$N$15,3,0) -> 16.240909 | C22: =VLOOKUP(C$21,$L$1:$N$15,3,0) -> 717.61448 | D22: =VLOOKUP(D$21,$L$1:$N$15,3,0) -> 2176.366 | E22: 13624.119 | F22: 19335.966 | G22: 712.0628 | H22: =SUM(B22:G22) -> 36582.368 | I22: =H22-'GMV表-商品大类'!E66 -> 0 | L22: 生活-加油卡 | M22: 87658.978 | N22: =M22/10000 -> 8.7658978 | P22: 45292 | Q22: 774.98675 | R22: 1247.3083 | S22: 1721.638 | T22: 7067.389 | U22: 20395.537 | V22: 1230.2989 | W22: =SUM(Q22:V22) -> 32437.158 | X22: =W22-'GMV表-商品大类'!E54 -> 0 | Z22: 44927 | AA22: 2320.3047 | AB22: 344.54953 | AC22: 1931.8029 | AD22: 3357.8495 | AE22: 24795.952 | AF22: 729.43384 | AG22: =SUM(AA22:AF22) -> 33479.892 | AH22: =AG22-'GMV表-商品大类'!E42 -> 0 | AJ22: 44562 | AK22: 74.12923 | AL22: 154.06231 | AM22: 358.47435 | AN22: 16549.654 | AO22: 32.36919 | AP22: 546.88552 | AQ22: 17715.575 | AR22: 0
A23: 45689 | B23: =VLOOKUP(B$21,$L$18:$N$32,3,0) -> 8.7658978 | C23: =VLOOKUP(C$21,$L$18:$N$32,3,0) -> 253.07365 | D23: =VLOOKUP(D$21,$L$18:$N$32,3,0) -> 2229.0274 | E23: 10803.75 | F23: 15190.819 | G23: 528.57693 | H23: =SUM(B23:G23) -> 29014.014 | I23: =H23-'GMV表-商品大类'!E67 -> 0 | L23: 生活-健身 | M23: 25975 | N23: =M23/10000 -> 2.5975 | P23: 45323 | Q23: 585.78005 | R23: 649.93174 | S23: 911.10369 | T23: 7258.5837 | U23: 18963.563 | V23: 1262.3931 | W23: =SUM(Q23:V23) -> 29631.355 | X23: =W23-'GMV表-商品大类'!E55 -> 0 | Z23: 44958 | AA23: 2426.2952 | AB23: 219.01917 | AC23: 771.20349 | AD23: 4562.7184 | AE23: 26789.712 | AF23: 236.13134 | AG23: =SUM(AA23:AF23) -> 35005.079 | AH23: =AG23-'GMV表-商品大类'!E43 -> 0 | AJ23: 44593 | AK23: 224.42404 | AL23: 159.39662 | AM23: 275.87252 | AN23: 13563.388 | AO23: 132.21854 | AP23: 735.54984 | AQ23: 15090.849 | AR23: 0
A24: 45717 | B24: =VLOOKUP(B$21,$L$35:$N$49,3,0) -> 17.792376 | C24: =VLOOKUP(C$21,$L$35:$N$49,3,0) -> 283.6972 | D24: =VLOOKUP(D$21,$L$35:$N$49,3,0) -> 3225.0303 | E24: 19966.904 | F24: 17220.54 | G24: 316.35997 | H24: =SUM(B24:G24) -> 41030.325 | I24: =H24-'GMV表-商品大类'!E68 -> 0 | L24: 生活-其他 | M24: 4974963.1 | N24: =M24/10000 -> 497.49631 | P24: 45352 | Q24: 584.41559 | R24: 704.90748 | S24: 1110.0432 | T24: 6473.6521 | U24: 19058.409 | V24: 617.76292 | W24: =SUM(Q24:V24) -> 28549.19 | X24: =W24-'GMV表-商品大类'!E56 -> 0 | Z24: 44986 | AA24: 3214.7873 | AB24: 491.15597 | AC24: 994.09227 | AD24: 8101.0441 | AE24: 35280.266 | AF24: 102.67792 | AG24: =SUM(AA24:AF24) -> 48184.023 | AH24: =AG24-'GMV表-商品大类'!E44 -> 0 | AJ24: 44621 | AK24: 635.023 | AL24: 210.43086 | AM24: 289.14662 | AN24: 30733.179 | AO24: 69.596241 | AP24: 731.48659 | AQ24: 32668.862 | AR24: 0
A25: 45748 | B25: =VLOOKUP(B$21,$L$52:$N$66,3,0) -> 30.265324 | C25: =VLOOKUP(C$21,$L$52:$N$66,3,0) -> 236.21053 | D25: =VLOOKUP(D$21,$L$52:$N$66,3,0) -> 1843.3546 | E25: 17616.708 | F25: 15440.981 | G25: 187.81491 | H25: =SUM(B25:G25) -> 35355.334 | I25: =H25-'GMV表-商品大类'!E69 -> 0 | L25: 网娱-其他 | N25: =M25/10000 -> 0 | P25: 45383 | Q25: 372.05521 | R25: 653.52619 | S25: 1707.2602 | T25: 3110.0743 | U25: 10627.836 | V25: 126.99053 | W25: =SUM(Q25:V25) -> 16597.742 | X25: =W25-'GMV表-商品大类'!E57 -> 0 | Z25: 45017 | AA25: 2699.1103 | AB25: 925.30509 | AC25: 1324.4729 | AD25: 10136.698 | AE25: 31186.052 | AF25: 345.69369 | AG25: =SUM(AA25:AF25) -> 46617.332 | AH25: =AG25-'GMV表-商品大类'!E45 -> 0 | AJ25: 44652 | AK25: 1390.7422 | AL25: 137.69217 | AM25: 311.86764 | AN25: 23405.072 | AO25: 36.415092 | AP25: 879.53822 | AQ25: 26161.328 | AR25: 0
A26: 45778 | B26: =VLOOKUP(B$21,$L$69:$N$83,3,0) -> 185.68592 | C26: =VLOOKUP(C$21,$L$69:$N$83,3,0) -> 450.33723 | D26: =VLOOKUP(D$21,$L$69:$N$83,3,0) -> 1038.5219 | E26: =VLOOKUP(E$21,$L$69:$N$83,3,0) -> 14953.656 | F26: =VLOOKUP(F$21,$L$69:$N$83,3,0) -> 12292.89 | G26: ='GMV表-商品大类'!E70-SUM(B26:F26) -> 166.30813 | H26: =SUM(B26:G26) -> 29087.399 | I26: =H26-'GMV表-商品大类'!E70 -> 0 | L26: 网娱-视频直播 | M26: 1.1005474e+08 | N26: =M26/10000 -> 11005.474 | P26: 45413 | Q26: 322.62111 | R26: 1082.0517 | S26: 3449.8878 | T26: 5123.7166 | U26: 16430.59 | V26: 148.64891 | W26: =SUM(Q26:V26) -> 26557.516 | X26: =W26-'GMV表-商品大类'!E58 -> 0 | Z26: 45047 | AA26: 2460.1169 | AB26: 1032.281 | AC26: 4523.382 | AD26: 11405.169 | AE26: 34527.547 | AF26: 625.81047 | AG26: =SUM(AA26:AF26) -> 54574.306 | AH26: =AG26-'GMV表-商品大类'!E46 -> 0 | AJ26: 44682 | AK26: 1223.0405 | AL26: 290.91444 | AM26: 367.3219 | AN26: 30278.131 | AO26: 46.410383 | AP26: 277.31865 | AQ26: 32483.137 | AR26: 0
A27: 45809 | B27: =VLOOKUP(B$21,$L$87:$N$101,3,0) -> 101.09751 | C27: =VLOOKUP(C$21,$L$87:$N$101,3,0) -> 396.92262 | D27: =VLOOKUP(D$21,$L$87:$N$101,3,0) -> 1422.6918 | E27: =VLOOKUP(E$21,$L$87:$N$101,3,0) -> 19088.456 | F27: =VLOOKUP(F$21,$L$87:$N$101,3,0) -> 14425.521 | G27: ='GMV表-商品大类'!E71-SUM(B27:F27) -> 51.677497 | H27: =SUM(B27:G27) -> 35486.366 | I27: =H27-'GMV表-商品大类'!E71 -> 0 | L27: 网娱-网络工具 | M27: 10468678 | N27: =M27/10000 -> 1046.8678 | P27: 45444 | Q27: 427.31041 | R27: 1091.9993 | S27: 4832.8963 | T27: 10732.796 | U27: 13441.759 | V27: 18.56536 | W27: =SUM(Q27:V27) -> 30545.326 | X27: =W27-'GMV表-商品大类'!E59 -> 0 | Z27: 45078 | AA27: 2044.5297 | AB27: 1056.508 | AC27: 7100.4265 | AD27: 11254.686 | AE27: 42579.007 | AF27: 1709.0887 | AG27: =SUM(AA27:AF27) -> 65744.246 | AH27: =AG27-'GMV表-商品大类'!E47 -> 0 | AJ27: 44713 | AK27: 1416.3376 | AL27: 335.26406 | AM27: 4303.0048 | AN27: 27891.418 | AO27: 63.937918 | AP27: 152.6255 | AQ27: 34162.588 | AR27: 0
A28: 45839 | B28: =VLOOKUP(B$21,$L$105:$N$119,3,0) -> 37.199618 | C28: =VLOOKUP(C$21,$L$105:$N$119,3,0) -> 334.70417 | D28: =VLOOKUP(D$21,$L$105:$N$119,3,0) -> 847.26855 | E28: =VLOOKUP(E$21,$L$105:$N$119,3,0) -> 33418.898 | F28: =VLOOKUP(F$21,$L$105:$N$119,3,0) -> 11301.806 | G28: ='GMV表-商品大类'!E72-SUM(B28:F28) -> 531.95756 | H28: =SUM(B28:G28) -> 46471.834 | I28: =H28-'GMV表-商品大类'!E72 -> 0 | L28: 网娱-音频 | M28: 10958763 | N28: =M28/10000 -> 1095.8763 | P28: 45474 | Q28: 510.97318 | R28: 843.1376 | S28: 6740.2832 | T28: 13168.655 | U28: 13332.027 | V28: -187.24976 | W28: =SUM(Q28:V28) -> 34407.826 | X28: =W28-'GMV表-商品大类'!E60 -> 0 | Z28: 45108 | AA28: 2042.5626 | AB28: 1022.4824 | AC28: 4563.9616 | AD28: 9871.2431 | AE28: 36648.973 | AF28: 1134.4485 | AG28: =SUM(AA28:AF28) -> 55283.671 | AH28: =AG28-'GMV表-商品大类'!E48 -> 0 | AJ28: 44743 | AK28: 1500.1141 | AL28: 307.84026 | AM28: 1099.1747 | AN28: 24170.129 | AO28: 103.11988 | AP28: 231.70886 | AQ28: 27412.087 | AR28: 0
A29: 45870 | B29: =VLOOKUP(B$21,$L$123:$N$137,3,0) -> 0 | C29: =VLOOKUP(C$21,$L$123:$N$137,3,0) -> 0 | D29: =VLOOKUP(D$21,$L$123:$N$137,3,0) -> 0 | E29: =VLOOKUP(E$21,$L$123:$N$137,3,0) -> 0 | F29: =VLOOKUP(F$21,$L$123:$N$137,3,0) -> 0 | G29: ='GMV表-商品大类'!E73-SUM(B29:F29) -> 0 | H29: =SUM(B29:G29) -> 0 | I29: =H29-'GMV表-商品大类'!E73 -> 0 | L29: 网娱-影视会员 | M29: 52562006 | N29: =M29/10000 -> 5256.2006 | P29: 45505 | Q29: 361.77207 | R29: 687.82097 | S29: 4493.332 | T29: 10974.94 | U29: 14228.812 | V29: 286.1384 | W29: =SUM(Q29:V29) -> 31032.816 | X29: =W29-'GMV表-商品大类'!E61 -> 0 | Z29: 45139 | AA29: 2262.2778 | AB29: 2377.4195 | AC29: 4585.2274 | AD29: 9710.7038 | AE29: 40803.705 | AF29: 1362.8887 | AG29: =SUM(AA29:AF29) -> 61102.222 | AH29: =AG29-'GMV表-商品大类'!E49 -> 0 | AJ29: 44774 | AK29: 1478.3301 | AL29: 205.52819 | AM29: 2845.4653 | AN29: 29241.323 | AO29: 81.081032 | AP29: 340.69249 | AQ29: 34192.42 | AR29: 0
A30: 45901 | B30: =VLOOKUP(B$21,$L$141:$N$156,3,0) -> 0 | C30: =VLOOKUP(C$21,$L$141:$N$156,3,0) -> 0 | D30: =VLOOKUP(D$21,$L$141:$N$156,3,0) -> 0 | E30: =VLOOKUP(E$21,$L$141:$N$156,3,0) -> 0 | F30: =VLOOKUP(F$21,$L$141:$N$156,3,0) -> 0 | G30: ='GMV表-商品大类'!E74-SUM(B30:F30) -> 0 | H30: =SUM(B30:G30) -> 0 | I30: =H30-'GMV表-商品大类'!E74 -> 0 | L30: 网娱-知识阅读 | M30: 2467184.1 | N30: =M30/10000 -> 246.71841 | P30: 45536 | Q30: 287.56652 | R30: 585.61905 | S30: 2377.4264 | T30: 5421.0431 | U30: =9893.04944759228+19348723.985/10000 -> 11827.922 | V30: =2085.82866757591-19348723.985/10000 -> 150.95627 | W30: =SUM(Q30:V30) -> 20650.533 | X30: =W30-'GMV表-商品大类'!E62 -> 0 | Z30: 45170 | AA30: 2358.2411 | AB30: 1562.9219 | AC30: 3820.7577 | AD30: 6609.6405 | AE30: 34169.961 | AF30: 1415.0599 | AG30: =SUM(AA30:AF30) -> 49936.582 | AH30: =AG30-'GMV表-商品大类'!E50 -> 0 | AJ30: 44805 | AK30: 1808.6165 | AL30: 288.56608 | AM30: 1683.6405 | AN30: 24763.29 | AO30: 75.289404 | AP30: -264.36099 | AQ30: 28355.042 | AR30: 0
A31: 45931 | B31: =VLOOKUP(B$21,$L$159:$N$173,3,0) -> 0 | C31: =VLOOKUP(C$21,$L$159:$N$173,3,0) -> 0 | D31: =VLOOKUP(D$21,$L$159:$N$173,3,0) -> 0 | E31: =VLOOKUP(E$21,$L$159:$N$173,3,0) -> 0 | F31: =VLOOKUP(F$21,$L$159:$N$173,3,0) -> 0 | G31: ='GMV表-商品大类'!E75-SUM(B31:F31) -> 0 | H31: =SUM(B31:G31) -> 0 | I31: =H31-'GMV表-商品大类'!E75 -> 0 | L31: #N/A | M31: 75726106 | N31: =M31/10000 -> 7572.6106 | P31: 45566 | Q31: 146.47428 | R31: 437.1078 | S31: 2222.2342 | T31: 10464.26 | U31: 12772.541 | V31: 125.03994 | W31: =SUM(Q31:V31) -> 26167.658 | X31: =W31-'GMV表-商品大类'!E63 -> 0 | Z31: 45200 | AA31: 1188.37 | AB31: 917.27159 | AC31: 2244.7133 | AD31: 7900.8875 | AE31: 23421.308 | AF31: 918.75362 | AG31: =SUM(AA31:AF31) -> 36591.304 | AH31: =AG31-'GMV表-商品大类'!E51 -> 0 | AJ31: 44835 | AK31: 1649.7526 | AL31: 227.4447 | AM31: 2058.0657 | AN31: 30586.804 | AO31: 52.265159 | AP31: 124.77012 | AQ31: 34699.103 | AR31: 0
A32: 45962 | B32: =VLOOKUP(B$21,$L$177:$N$191,3,0) -> 0 | C32: =VLOOKUP(C$21,$L$177:$N$191,3,0) -> 0 | D32: =VLOOKUP(D$21,$L$177:$N$191,3,0) -> 0 | E32: =VLOOKUP(E$21,$L$177:$N$191,3,0) -> 0 | F32: =VLOOKUP(F$21,$L$177:$N$191,3,0) -> 0 | G32: ='GMV表-商品大类'!E76-SUM(B32:F32) -> 0 | H32: =SUM(B32:G32) -> 0 | I32: =H32-'GMV表-商品大类'!E76 -> 0 | L32: 总计 | M32: =SUM(M19:M31) -> 5.5209278e+08 | N32: =M32/10000 -> 55209.278 | P32: 45597 | Q32: 166.48479 | R32: 416.45484 | S32: 2192.1625 | T32: 10392.71 | U32: 13399.111 | V32: 8.7738543 | W32: =SUM(Q32:V32) -> 26575.697 | X32: =W32-'GMV表-商品大类'!E64 -> 0 | Z32: 45231 | AA32: 682.40415 | AB32: 1010.0297 | AC32: 4440.3454 | AD32: 7109.8297 | AE32: 20246.64 | AF32: 847.05302 | AG32: =SUM(AA32:AF32) -> 34336.302 | AH32: =AG32-'GMV表-商品大类'!E52 -> 0 | AJ32: 44866 | AK32: 3087.4398 | AL32: 208.57969 | AM32: 1237.5814 | AN32: 36750.997 | AO32: 124.94814 | AP32: 56.691197 | AQ32: 41466.237 | AR32: 0
A33: 45992 | B33: =VLOOKUP(B$21,$L$195:$N$209,3,0) -> 0 | C33: =VLOOKUP(C$21,$L$195:$N$209,3,0) -> 0 | D33: =VLOOKUP(D$21,$L$195:$N$209,3,0) -> 0 | E33: =VLOOKUP(E$21,$L$195:$N$209,3,0) -> 0 | F33: =VLOOKUP(F$21,$L$195:$N$209,3,0) -> 0 | G33: ='GMV表-商品大类'!E77-SUM(B33:F33) -> 0 | H33: =SUM(B33:G33) -> 0 | I33: =H33-'GMV表-商品大类'!E77 -> 0 | P33: 45627 | Q33: 204.39099 | R33: 579.48263 | S33: 1757.7109 | T33: 9407.0092 | U33: 16146.442 | V33: -186.4033 | W33: =SUM(Q33:V33) -> 27908.633 | X33: =W33-'GMV表-商品大类'!E65 -> 4.7293724e-11 | Z33: 45261 | AA33: 692.71149 | AB33: 1307.1377 | AC33: 2325.5692 | AD33: 6914.5904 | AE33: 20605.033 | AF33: 1577.8452 | AG33: =SUM(AA33:AF33) -> 33422.887 | AH33: =AG33-'GMV表-商品大类'!E53 -> 0 | AJ33: 44896 | AK33: 2930.7455 | AL33: 318.80902 | AM33: 929.46532 | AN33: 36809.705 | AO33: 74.946251 | AP33: 165.89879 | AQ33: 41229.57 | AR33: 0
A34: 合计 | B34: =SUM(B22:B33) -> 397.04756 | C34: =SUM(C22:C33) -> 2672.5599 | D34: =SUM(D22:D33) -> 12782.26 | E34: =SUM(E22:E33) -> 129472.49 | F34: =SUM(F22:F33) -> 105208.52 | G34: =SUM(G22:G33) -> 2494.7578 | H34: =SUM(H22:H33) -> 253027.64 | P34: 合计 | Q34: =SUM(Q22:Q28) -> 3578.1423 | R34: =SUM(R22:R28) -> 6272.8623 | S34: =SUM(S22:S28) -> 20473.112 | T34: =SUM(T22:T28) -> 52934.866 | U34: =SUM(U22:U28) -> 112249.72 | V34: =SUM(V22:V28) -> 3217.4099 | W34: =SUM(W22:W28) -> 198726.11 | Z34: 合计 | AA34: =SUM(AA22:AA28) -> 17207.707 | AB34: =SUM(AB22:AB28) -> 5091.3011 | AC34: =SUM(AC22:AC28) -> 21209.342 | AD34: =SUM(AD22:AD28) -> 58689.409 | AE34: =SUM(AE22:AE28) -> 231807.51 | AF34: =SUM(AF22:AF28) -> 4883.2845 | AG34: =SUM(AG22:AG28) -> 338888.55 | AH34: 0 | AJ34: 合计 | AK34: =SUM(AK22:AK33) -> 17418.695 | AL34: =SUM(AL22:AL33) -> 2844.5284 | AM34: =SUM(AM22:AM33) -> 15759.081 | AN34: =SUM(AN22:AN33) -> 324743.09 | AO34: =SUM(AO22:AO33) -> 892.59722 | AP34: =SUM(AP22:AP33) -> 3978.8048 | AQ34: =SUM(AK34:AP34) -> 365636.8 | AR34: 0
A35: 占比 | B35: =B34/$H$34 -> 0.0015691865 | C35: =C34/$H$34 -> 0.010562324 | D35: =D34/$H$34 -> 0.05051725 | E35: =E34/$H$34 -> 0.51169308 | F35: =F34/$H$34 -> 0.41579854 | G35: =G34/$H$34 -> 0.0098596256 | K35: 3月 | L35: 品牌分类 | M35: 求和项:调整后gmv | N35: 万元 | P35: 占比 | Q35: =Q34/$W$34 -> 0.018005396 | R35: =R34/$W$34 -> 0.031565365 | S35: =S34/$W$34 -> 0.10302175 | T35: =T34/$W$34 -> 0.26637096 | U35: =U34/$W$34 -> 0.56484635 | V35: =V34/$W$34 -> 0.016190172 | Z35: 占比 | AA35: =AA34/$AG$34 -> 0.05077689 | AB35: =AB34/$AG$34 -> 0.015023527 | AC35: =AC34/$AG$34 -> 0.062585005 | AD35: =AD34/$AG$34 -> 0.17318204 | AE35: =AE34/$AG$34 -> 0.68402284 | AF35: =AF34/$AG$34 -> 0.014409706 | AJ35: 占比 | AK35: 0.04763934 | AL35: 0.0077796558 | AM35: 0.043100368 | AN35: 0.88815757 | AO35: 0.0024412128 | AP35: 0.01088185
A36: 变动 | B36: =B34-Q34 -> -3181.0948 | C36: =C34-R34 -> -3600.3025 | D36: =D34-S34 -> -7690.8519 | E36: =E34-T34 -> 76537.625 | F36: =F34-U34 -> -7041.1979 | G36: =G34-V34 -> -722.65212 | H36: =H34-W34 -> 54301.525 | I36: =H36-'GMV表-商品大类'!E93 -> -2.8376235e-10 | L36: 生活-餐饮 | M36: 32250303 | N36: =M36/10000 -> 3225.0303
L37: 生活-出行旅游 | M37: 2836972 | N37: =M37/10000 -> 283.6972
L38: 生活-购物（优惠劵） | M38: 3.7187445e+08 | N38: =M38/10000 -> 37187.445
A39: 45108 | L39: 生活-加油卡 | M39: 177923.76 | N39: =M39/10000 -> 17.792376
A40: 45474 | L40: 生活-健身 | M40: 67003.54 | N40: =M40/10000 -> 6.700354
A41: 45839 | L41: 生活-其他 | M41: 2776757.8 | N41: =M41/10000 -> 277.67578
L42: 网娱-其他 | M42: 174347.7 | N42: =M42/10000 -> 17.43477
L43: 网娱-视频直播 | M43: 1.2420599e+08 | N43: =M43/10000 -> 12420.599
L44: 网娱-网络工具 | M44: 11337677 | N44: =M44/10000 -> 1133.7677
L45: 网娱-音频 | M45: 8862751.8 | N45: =M45/10000 -> 886.27518
L46: 网娱-影视会员 | M46: 41858648 | N46: =M46/10000 -> 4185.8648
L47: 网娱-知识阅读 | M47: 2433437 | N47: =M47/10000 -> 243.3437
L48: #N/A | M48: 67970733 | N48: =M48/10000 -> 6797.0733
L49: 总计 | M49: =SUM(M36:M48) -> 6.6682699e+08 | N49: =M49/10000 -> 66682.699
K52: 4月 | L52: 品牌分类 | M52: 求和项:调整后gmv | N52: 万元
L53: 生活-餐饮 | M53: 18433546 | N53: =M53/10000 -> 1843.3546
L54: 生活-出行旅游 | M54: 2362105.3 | N54: =M54/10000 -> 236.21053
L55: 生活-购物（优惠劵） | M55: 3.3057688e+08 | N55: =M55/10000 -> 33057.688
L56: 生活-加油卡 | M56: 302653.24 | N56: =M56/10000 -> 30.265324
L57: 生活-健身 | M57: 8665.72 | N57: =M57/10000 -> 0.866572
L58: 生活-其他 | M58: 1744349.1 | N58: =M58/10000 -> 174.43491
L59: 网娱-其他 | M59: 29.6 | N59: =M59/10000 -> 0.00296
L60: 网娱-视频直播 | M60: 1.1286297e+08 | N60: =M60/10000 -> 11286.297
L61: 网娱-网络工具 | M61: 10694332 | N61: =M61/10000 -> 1069.4332
L62: 网娱-音频 | M62: 9138416 | N62: =M62/10000 -> 913.8416
L63: 网娱-影视会员 | M63: 36337744 | N63: =M63/10000 -> 3633.7744
L64: 网娱-知识阅读 | M64: 4181362.2 | N64: =M64/10000 -> 418.13622
L65: #N/A | M65: 77419759 | N65: =M65/10000 -> 7741.9759
L66: 总计 | M66: 6.0406282e+08 | N66: =SUM(N53:N65) -> 60406.282
K69: 5月 | L69: 品牌分类 | M69: 求和项:调整后gmv | N69: 万元
L70: 生活-餐饮 | M70: 10385219 | N70: =M70/10000 -> 1038.5219
L71: 生活-出行旅游 | M71: 4503372.3 | N71: =M71/10000 -> 450.33723
L72: 生活-购物（优惠劵） | M72: 1.229289e+08 | N72: =M72/10000 -> 12292.89
L73: 生活-加油卡 | M73: 1856859.2 | N73: =M73/10000 -> 185.68592
L74: 生活-健身 | M74: 44819.2 | N74: =M74/10000 -> 4.48192
L75: 生活-立减金 | M75: 1.4953656e+08 | N75: =M75/10000 -> 14953.656
L76: 生活-其他 | M76: 1785949.4 | N76: =M76/10000 -> 178.59494
L77: 网娱-其他 | M77: 25159.99 | N77: =M77/10000 -> 2.515999
L78: 网娱-视频直播 | M78: 94715385 | N78: =M78/10000 -> 9471.5385
L79: 网娱-网络工具 | M79: 16183066 | N79: =M79/10000 -> 1618.3066
L80: 网娱-音频 | M80: 8333794.6 | N80: =M80/10000 -> 833.37946
L81: 网娱-影视会员 | M81: 47738702 | N81: =M81/10000 -> 4773.8702
L82: 网娱-知识阅读 | M82: 5819734.5 | N82: =M82/10000 -> 581.97345
L83: #N/A | M83: 1.4154374e+08 | N83: =M83/10000 -> 14154.374
L84: 总计 | M84: 6.0540126e+08 | N84: =M84/10000 -> 60540.126
K87: 6月 | L87: 品牌分类 | M87: 求和项:调整后gmv | N87: 万元
L88: 生活-餐饮 | M88: 14226918 | N88: =M88/10000 -> 1422.6918
L89: 生活-出行旅游 | M89: 3969226.2 | N89: =M89/10000 -> 396.92262
L90: 生活-购物（优惠劵） | M90: 1.4425521e+08 | N90: =M90/10000 -> 14425.521
L91: 生活-加油卡 | M91: 1010975.1 | N91: =M91/10000 -> 101.09751
L92: 生活-健身 | M92: 18669.82 | N92: =M92/10000 -> 1.866982
L93: 生活-立减金 | M93: 1.9088456e+08 | N93: =M93/10000 -> 19088.456
L94: 生活-其他 | M94: 425860.81 | N94: =M94/10000 -> 42.586081
L95: 网娱-其他 | M95: 5629.01 | N95: =M95/10000 -> 0.562901
L96: 网娱-视频直播 | M96: 33226469 | N96: =M96/10000 -> 3322.6469
L97: 网娱-网络工具 | M97: 18927845 | N97: =M97/10000 -> 1892.7845
L98: 网娱-音频 | M98: 6905865.6 | N98: =M98/10000 -> 690.58656
L99: 网娱-影视会员 | M99: 60399085 | N99: =M99/10000 -> 6039.9085
L100: 网娱-知识阅读 | M100: 5243715.6 | N100: =M100/10000 -> 524.37156
L101: #N/A | M101: 91531242 | N101: =M101/10000 -> 9153.1242
L102: 总计 | M102: 6.0148254e+08 | N102: =SUM(N88:N101) -> 57103.127
K105: 7月 | L105: 品牌分类 | M105: 求和项:调整后gmv | N105: 万元
L106: 生活-餐饮 | M106: 8472685.5 | N106: =M106/10000 -> 847.26855
L107: 生活-出行旅游 | M107: 3347041.7 | N107: =M107/10000 -> 334.70417
L108: 生活-购物（优惠劵） | M108: 1.1301806e+08 | N108: =M108/10000 -> 11301.806
...

Sheet 毛利-收入组成
A1: 代理收入（虚拟商品充值差额收入+返点） | H1: 增值代运营收入 | O1: 推广收入：按总额反映GMV，按差额反映收入 | W1: 经纪服务+平台服务+游戏开发 | AD1: 合计收入（含税） | AK1: 年累计毛利（贴PPT） | AY1: 代理收入（虚拟商品充值差额收入+返点）
A2: 月份 | B2: 游戏 | C2: 通信 | D2: 网娱 | E2: 生活服务 | F2: 合计（单位：万元） | H2: 月份 | I2: 游戏 | J2: 通信 | K2: 网娱 | L2: 生活服务 | M2: 合计（单位：万元） | O2: 月份 | P2: 游戏 | Q2: 通信 | R2: 网娱 | S2: 生活服务 | T2: 合计（单位：万元） | V2: 月份 | W2: 游戏 | X2: 通信 | Y2: 网娱 | Z2: 生活服务 | AA2: 合计（单位：万元） | AC2: 月份 | AD2: 游戏 | AE2: 通信 | AF2: 网娱 | AG2: 生活服务 | AH2: 合计（单位：万元） | AI2: check | AK2: 月度累计 | AL2: 游戏 | AM2: 通信 | AN2: 网娱 | AO2: 生活服务 | AP2: 合计（单位：万元） | AR2: 占比 | AS2: 游戏 | AT2: 通信 | AU2: 网娱 | AV2: 生活服务 | AW2: 合计（单位：万元） | AY2: 月份累计 | AZ2: 游戏 | BA2: 通信 | BB2: 网娱 | BC2: 生活服务 | BD2: 合计（单位：万元）
A3: 43831 | B3: 1548.737 | C3: 259.54229 | D3: 907.34143 | E3: 54.659191 | F3: =SUM(B3:E3) -> 2770.2799 | H3: 43831 | I3: 0 | J3: 0 | K3: 235.27324 | L3: 0 | M3: =SUM(I3:L3) -> 235.27324 | O3: 43831 | S3: 0 | T3: =SUM(P3:S3) -> 0 | V3: 43831 | AA3: =SUM(W3:Z3) -> 0 | AC3: 43831 | AD3: =B3+I3+P3+W3 -> 1548.737 | AE3: =C3+J3+Q3+X3 -> 259.54229 | AF3: =D3+K3+R3+Y3 -> 1142.6147 | AG3: =E3+L3+S3+Z3 -> 54.659191 | AH3: =F3+M3+T3+AA3 -> 3005.5532 | AI3: =SUM(AD3:AG3)-AH3 -> 0 | AK3: 20.1月累计 | AL3: =AD3 -> 1548.737 | AM3: =AE3 -> 259.54229 | AN3: =AF3 -> 1142.6147 | AO3: =AG3 -> 54.659191 | AP3: =SUM(AL3:AO3) -> 3005.5532 | AR3: 20.1月累计 | AS3: =AL3/$AP3 -> 0.51529184 | AT3: =AM3/$AP3 -> 0.086354251 | AU3: =AN3/$AP3 -> 0.38016784 | AV3: =AO3/$AP3 -> 0.018186067 | AW3: =SUM(AS3:AV3) -> 1 | AY3: 20.1月累计 | AZ3: 1548.737 | BA3: 259.54229 | BB3: 907.34143 | BC3: 54.659191 | BD3: 2770.2799
A4: 43862 | B4: 1011.5544 | C4: 241.3401 | D4: 1075.261 | E4: 30.525706 | F4: =SUM(B4:E4) -> 2358.6812 | H4: 43862 | I4: 0.1777249 | J4: 0 | K4: 89.380825 | L4: 0 | M4: =SUM(I4:L4) -> 89.55855 | O4: 43862 | S4: -0.49117114 | T4: =SUM(P4:S4) -> -0.49117114 | V4: 43862 | W4: 172.7398 | AA4: =SUM(W4:Z4) -> 172.7398 | AC4: 43862 | AD4: =B4+I4+P4+W4 -> 1184.472 | AE4: =C4+J4+Q4+X4 -> 241.3401 | AF4: =D4+K4+R4+Y4 -> 1164.6418 | AG4: =E4+L4+S4+Z4 -> 30.034535 | AH4: =F4+M4+T4+AA4 -> 2620.4884 | AI4: =SUM(AD4:AG4)-AH4 -> 0 | AK4: 20.2月累计 | AL4: =SUM(AD3:AD4) -> 2733.209 | AM4: =SUM(AE3:AE4) -> 500.88239 | AN4: =SUM(AF3:AF4) -> 2307.2565 | AO4: =SUM(AG3:AG4) -> 84.693726 | AP4: =SUM(AL4:AO4) -> 5626.0416 | AR4: 20.2月累计 | AS4: =AL4/$AP4 -> 0.48581386 | AT4: =AM4/$AP4 -> 0.089029273 | AU4: =AN4/$AP4 -> 0.41010299 | AV4: =AO4/$AP4 -> 0.015053875 | AW4: =SUM(AS4:AV4) -> 1 | AY4: 20.2月累计 | AZ4: 2560.2915 | BA4: 500.88239 | BB4: 1982.6024 | BC4: 85.184897 | BD4: 5128.9612
A5: 43891 | B5: 1275.1451 | C5: 296.77485 | D5: 1946.1266 | E5: 63.006912 | F5: =SUM(B5:E5) -> 3581.0535 | H5: 43891 | I5: 0.51642776 | J5: 0 | K5: 95.105844 | L5: 0 | M5: =SUM(I5:L5) -> 95.622271 | O5: 43891 | S5: 0.05747956 | T5: =SUM(P5:S5) -> 0.05747956 | V5: 43891 | AA5: =SUM(W5:Z5) -> 0 | AC5: 43891 | AD5: =B5+I5+P5+W5 -> 1275.6615 | AE5: =C5+J5+Q5+X5 -> 296.77485 | AF5: =D5+K5+R5+Y5 -> 2041.2325 | AG5: =E5+L5+S5+Z5 -> 63.064391 | AH5: =F5+M5+T5+AA5 -> 3676.7332 | AI5: =SUM(AD5:AG5)-AH5 -> 0 | AK5: 20.3月累计 | AL5: =SUM(AD3:AD5) -> 4008.8705 | AM5: =SUM(AE3:AE5) -> 797.65724 | AN5: =SUM(AF3:AF5) -> 4348.489 | AO5: =SUM(AG3:AG5) -> 147.75812 | AP5: =SUM(AL5:AO5) -> 9302.7749 | AR5: 20.3月累计 | AS5: =AL5/$AP5 -> 0.43093277 | AT5: =AM5/$AP5 -> 0.085744013 | AU5: =AN5/$AP5 -> 0.46743999 | AV5: =AO5/$AP5 -> 0.015883231 | AW5: =SUM(AS5:AV5) -> 1 | AY5: 20.3月累计 | AZ5: 3835.4366 | BA5: 797.65724 | BB5: 3928.7291 | BC5: 148.19181 | BD5: 8710.0147
A6: 43922 | B6: 863.87824 | C6: 249.75354 | D6: 935.38316 | E6: 61.917787 | F6: =SUM(B6:E6) -> 2110.9327 | H6: 43922 | I6: 32.957292 | J6: 0 | K6: 105.91362 | L6: 0 | M6: =SUM(I6:L6) -> 138.87091 | O6: 43922 | S6: 4.8315701 | T6: =SUM(P6:S6) -> 4.8315701 | V6: 43922 | W6: 5.8475038 | AA6: =SUM(W6:Z6) -> 5.8475038 | AC6: 43922 | AD6: =B6+I6+P6+W6 -> 902.68303 | AE6: =C6+J6+Q6+X6 -> 249.75354 | AF6: =D6+K6+R6+Y6 -> 1041.2968 | AG6: =E6+L6+S6+Z6 -> 66.749357 | AH6: =F6+M6+T6+AA6 -> 2260.4827 | AI6: =SUM(AD6:AG6)-AH6 -> 0 | AK6: 20.4月累计 | AL6: =SUM(AD3:AD6) -> 4911.5535 | AM6: =SUM(AE3:AE6) -> 1047.4108 | AN6: =SUM(AF3:AF6) -> 5389.7858 | AO6: =SUM(AG3:AG6) -> 214.50747 | AP6: =SUM(AL6:AO6) -> 11563.258 | AR6: 20.4月累计 | AS6: =AL6/$AP6 -> 0.42475518 | AT6: =AM6/$AP6 -> 0.090580944 | AU6: =AN6/$AP6 -> 0.46611309 | AV6: =AO6/$AP6 -> 0.018550782 | AW6: =SUM(AS6:AV6) -> 1 | AY6: 20.4月累计 | AZ6: 4699.3148 | BA6: 1047.4108 | BB6: 4864.1122 | BC6: 210.1096 | BD6: 10820.947
A7: 43952 | B7: 968.37973 | C7: 534.51915 | D7: 1000.5782 | E7: 166.81088 | F7: =SUM(B7:E7) -> 2670.288 | H7: 43952 | I7: -32.432601 | J7: 0 | K7: 105.2062 | L7: 0 | M7: =SUM(I7:L7) -> 72.773599 | O7: 43952 | S7: 39.540319 | T7: =SUM(P7:S7) -> 39.540319 | V7: 43952 | W7: 15.6502 | AA7: =SUM(W7:Z7) -> 15.6502 | AC7: 43952 | AD7: =B7+I7+P7+W7 -> 951.59733 | AE7: =C7+J7+Q7+X7 -> 534.51915 | AF7: =D7+K7+R7+Y7 -> 1105.7844 | AG7: =E7+L7+S7+Z7 -> 206.3512 | AH7: =F7+M7+T7+AA7 -> 2798.2521 | AI7: =SUM(AD7:AG7)-AH7 -> 0 | AK7: 20.5月累计 | AL7: =SUM(AD3:AD7) -> 5863.1509 | AM7: =SUM(AE3:AE7) -> 1581.9299 | AN7: =SUM(AF3:AF7) -> 6495.5702 | AO7: =SUM(AG3:AG7) -> 420.85868 | AP7: =SUM(AL7:AO7) -> 14361.51 | AR7: 20.5月累计 | AS7: =AL7/$AP7 -> 0.4082545 | AT7: =AM7/$AP7 -> 0.11015067 | AU7: =AN7/$AP7 -> 0.45229021 | AV7: =AO7/$AP7 -> 0.029304627 | AW7: =SUM(AS7:AV7) -> 1 | AY7: 20.5月累计 | AZ7: 5667.6945 | BA7: 1581.9299 | BB7: 5864.6904 | BC7: 376.92048 | BD7: 13491.235
A8: 43983 | B8: 771.13742 | C8: 400.11929 | D8: 1396.0129 | E8: 308.42395 | F8: =SUM(B8:E8) -> 2875.6936 | H8: 43983 | I8: 5.0356275 | J8: 0 | K8: 112.28006 | L8: 0 | M8: =SUM(I8:L8) -> 117.31569 | O8: 43983 | S8: 5.03417 | T8: =SUM(P8:S8) -> 5.03417 | V8: 43983 | W8: 0.01000004 | AA8: =SUM(W8:Z8) -> 0.01000004 | AC8: 43983 | AD8: =B8+I8+P8+W8 -> 776.18305 | AE8: =C8+J8+Q8+X8 -> 400.11929 | AF8: =D8+K8+R8+Y8 -> 1508.293 | AG8: =E8+L8+S8+Z8 -> 313.45812 | AH8: =F8+M8+T8+AA8 -> 2998.0535 | AI8: =SUM(AD8:AG8)-AH8 -> 0 | AK8: 20.6月累计 | AL8: =SUM(AD3:AD8) -> 6639.3339 | AM8: =SUM(AE3:AE8) -> 1982.0492 | AN8: =SUM(AF3:AF8) -> 8003.8632 | AO8: =SUM(AG3:AG8) -> 734.31679 | AP8: =SUM(AL8:AO8) -> 17359.563 | AR8: 20.6月累计 | AS8: =AL8/$AP8 -> 0.38245974 | AT8: =AM8/$AP8 -> 0.11417622 | AU8: =AN8/$AP8 -> 0.46106363 | AV8: =AO8/$AP8 -> 0.042300419 | AW8: =SUM(AS8:AV8) -> 1 | AY8: 20.6月累计 | AZ8: 6438.8319 | BA8: 1982.0492 | BB8: 7260.7034 | BC8: 685.34443 | BD8: 16366.929
A9: 44013 | B9: 692.78796 | C9: 541.30515 | D9: 739.32796 | E9: 171.63185 | F9: =SUM(B9:E9) -> 2145.0529 | H9: 44013 | I9: 0.02328396 | J9: 0 | K9: 105.77402 | L9: 0 | M9: =SUM(I9:L9) -> 105.79731 | O9: 44013 | S9: 10.452123 | T9: =SUM(P9:S9) -> 10.452123 | V9: 44013 | AA9: =SUM(W9:Z9) -> 0 | AC9: 44013 | AD9: =B9+I9+P9+W9 -> 692.81124 | AE9: =C9+J9+Q9+X9 -> 541.30515 | AF9: =D9+K9+R9+Y9 -> 845.10199 | AG9: =E9+L9+S9+Z9 -> 182.08398 | AH9: =F9+M9+T9+AA9 -> 2261.3024 | AI9: =SUM(AD9:AG9)-AH9 -> 0 | AK9: 20.7月累计 | AL9: =SUM(AD3:AD9) -> 7332.1452 | AM9: =SUM(AE3:AE9) -> 2523.3544 | AN9: =SUM(AF3:AF9) -> 8848.9652 | AO9: =SUM(AG3:AG9) -> 916.40077 | AP9: =SUM(AL9:AO9) -> 19620.865 | AR9: 20.7月累计 | AS9: =AL9/$AP9 -> 0.37369122 | AT9: =AM9/$AP9 -> 0.12860566 | AU9: =AN9/$AP9 -> 0.4509977 | AV9: =AO9/$AP9 -> 0.04670542 | AW9: =SUM(AS9:AV9) -> 1 | AY9: 20.7月累计 | AZ9: 7131.6199 | BA9: 2523.3544 | BB9: 8000.0313 | BC9: 856.97628 | BD9: 18511.982
A10: 44044 | B10: 976.97592 | C10: 375.32022 | D10: 937.49061 | E10: 427.87452 | F10: =SUM(B10:E10) -> 2717.6613 | H10: 44044 | I10: 0.27428454 | J10: 0.763412 | K10: 198.73142 | L10: 0 | M10: =SUM(I10:L10) -> 199.76912 | O10: 44044 | S10: 5.3365223 | T10: =SUM(P10:S10) -> 5.3365223 | V10: 44044 | W10: 65.1 | AA10: =SUM(W10:Z10) -> 65.1 | AC10: 44044 | AD10: =B10+I10+P10+W10 -> 1042.3502 | AE10: =C10+J10+Q10+X10 -> 376.08363 | AF10: =D10+K10+R10+Y10 -> 1136.222 | AG10: =E10+L10+S10+Z10 -> 433.21105 | AH10: =F10+M10+T10+AA10 -> 2987.8669 | AI10: =SUM(AD10:AG10)-AH10 -> 0 | AK10: 20.8月累计 | AL10: =SUM(AD3:AD10) -> 8374.4954 | AM10: =SUM(AE3:AE10) -> 2899.438 | AN10: =SUM(AF3:AF10) -> 9985.1872 | AO10: =SUM(AG3:AG10) -> 1349.6118 | AP10: =SUM(AL10:AO10) -> 22608.732 | AR10: 20.8月累计 | AS10: =AL10/$AP10 -> 0.37040977 | AT10: =AM10/$AP10 -> 0.12824416 | AU10: =AN10/$AP10 -> 0.44165179 | AV10: =AO10/$AP10 -> 0.059694272 | AW10: =SUM(AS10:AV10) -> 1 | AY10: 20.8月累计 | AZ10: 8108.5958 | BA10: 2898.6746 | BB10: 8937.522 | BC10: 1284.8508 | BD10: 21229.643
A11: 44075 | B11: 1085.1145 | C11: 422.72242 | D11: 1053.0637 | E11: 258.89113 | F11: =SUM(B11:E11) -> 2819.7918 | H11: 44075 | I11: 0.48239752 | J11: 0.245602 | K11: 134.96318 | L11: 0.28263734 | M11: =SUM(I11:L11) -> 135.97382 | O11: 44075 | S11: -7.2231039 | T11: =SUM(P11:S11) -> -7.2231039 | V11: 44075 | W11: 41.9 | AA11: =SUM(W11:Z11) -> 41.9 | AC11: 44075 | AD11: =B11+I11+P11+W11 -> 1127.4969 | AE11: =C11+J11+Q11+X11 -> 422.96802 | AF11: =D11+K11+R11+Y11 -> 1188.0269 | AG11: =E11+L11+S11+Z11 -> 251.95066 | AH11: =F11+M11+T11+AA11 -> 2990.4425 | AI11: =SUM(AD11:AG11)-AH11 -> 0 | AK11: 20.9月累计 | AL11: =SUM(AD3:AD11) -> 9501.9923 | AM11: =SUM(AE3:AE11) -> 3322.406 | AN11: =SUM(AF3:AF11) -> 11173.214 | AO11: =SUM(AG3:AG11) -> 1601.5625 | AP11: =SUM(AL11:AO11) -> 25599.175 | AR11: 20.9月累计 | AS11: =AL11/$AP11 -> 0.37118354 | AT11: =AM11/$AP11 -> 0.12978567 | AU11: =AN11/$AP11 -> 0.43646774 | AV11: =AO11/$AP11 -> 0.062563051 | AW11: =SUM(AS11:AV11) -> 1 | AY11: 20.9月累计 | AZ11: 9193.7104 | BA11: 3321.397 | BB11: 9990.5856 | BC11: 1543.7419 | BD11: 24049.435
A12: 44105 | B12: 243.65397 | C12: 563.52158 | D12: 858.34334 | E12: 441.92058 | F12: =SUM(B12:E12) -> 2107.4395 | H12: 44105 | I12: -0.00801148 | J12: 0 | K12: 183.27774 | L12: 0.2340533 | M12: =SUM(I12:L12) -> 183.50378 | O12: 44105 | S12: 2.6016969 | T12: =SUM(P12:S12) -> 2.6016969 | V12: 44105 | W12: 62.85 | AA12: =SUM(W12:Z12) -> 62.85 | AC12: 44105 | AD12: =B12+I12+P12+W12 -> 306.49596 | AE12: =C12+J12+Q12+X12 -> 563.52158 | AF12: =D12+K12+R12+Y12 -> 1041.6211 | AG12: =E12+L12+S12+Z12 -> 444.75633 | AH12: =F12+M12+T12+AA12 -> 2356.395 | AI12: =SUM(AD12:AG12)-AH12 -> 0 | AK12: 20.10月累计 | AL12: =SUM(AD3:AD12) -> 9808.4883 | AM12: =SUM(AE3:AE12) -> 3885.9276 | AN12: =SUM(AF3:AF12) -> 12214.835 | AO12: =SUM(AG3:AG12) -> 2046.3188 | AP12: =SUM(AL12:AO12) -> 27955.57 | AR12: 20.10月累计 | AS12: =AL12/$AP12 -> 0.35085989 | AT12: =AM12/$AP12 -> 0.1390037 | AU12: =AN12/$AP12 -> 0.43693744 | AV12: =AO12/$AP12 -> 0.073198966 | AW12: =SUM(AS12:AV12) -> 1 | AY12: 20.10月累计 | AZ12: 9437.3643 | BA12: 3884.9186 | BB12: 10848.929 | BC12: 1985.6625 | BD12: 26156.874
A13: 44136 | B13: 679.46555 | C13: 630.52893 | D13: 2092.6453 | E13: 180.99483 | F13: =SUM(B13:E13) -> 3583.6346 | H13: 44136 | I13: 0.25087444 | J13: 0 | K13: 598.84461 | L13: 0.22402782 | M13: =SUM(I13:L13) -> 599.31951 | O13: 44136 | S13: 13.905538 | T13: =SUM(P13:S13) -> 13.905538 | V13: 44136 | AA13: =SUM(W13:Z13) -> 0 | AC13: 44136 | AD13: =B13+I13+P13+W13 -> 679.71643 | AE13: =C13+J13+Q13+X13 -> 630.52893 | AF13: =D13+K13+R13+Y13 -> 2691.4899 | AG13: =E13+L13+S13+Z13 -> 195.1244 | AH13: =F13+M13+T13+AA13 -> 4196.8596 | AI13: =SUM(AD13:AG13)-AH13 -> 0 | AK13: 20.11月累计 | AL13: =SUM(AD3:AD13) -> 10488.205 | AM13: =SUM(AE3:AE13) -> 4516.4565 | AN13: =SUM(AF3:AF13) -> 14906.325 | AO13: =SUM(AG3:AG13) -> 2241.4432 | AP13: =SUM(AL13:AO13) -> 32152.429 | AR13: 20.11月累计 | AS13: =AL13/$AP13 -> 0.32620256 | AT13: =AM13/$AP13 -> 0.14047015 | AU13: =AN13/$AP13 -> 0.46361427 | AV13: =AO13/$AP13 -> 0.069713028 | AW13: =SUM(AS13:AV13) -> 1 | AY13: 20.11月累计 | AZ13: 10116.83 | BA13: 4515.4475 | BB13: 12941.574 | BC13: 2166.6573 | BD13: 29740.509
A14: 44166 | B14: 899.32654 | C14: 500.97601 | D14: 2715.5892 | E14: 402.79689 | F14: =SUM(B14:E14) -> 4518.6887 | H14: 44166 | I14: 1.3039537 | J14: 0 | K14: 145.9554 | L14: 2.5722617 | M14: =SUM(I14:L14) -> 149.83162 | O14: 44166 | S14: 89.509654 | T14: =SUM(P14:S14) -> 89.509654 | V14: 44166 | W14: 84.091998 | AA14: =SUM(W14:Z14) -> 84.091998 | AC14: 44166 | AD14: =B14+I14+P14+W14 -> 984.72249 | AE14: =C14+J14+Q14+X14 -> 500.97601 | AF14: =D14+K14+R14+Y14 -> 2861.5446 | AG14: =E14+L14+S14+Z14 -> 494.8788 | AH14: =F14+M14+T14+AA14 -> 4842.1219 | AI14: =SUM(AD14:AG14)-AH14 -> 0 | AK14: 20.12月累计 | AL14: =SUM(AD3:AD14) -> 11472.927 | AM14: =SUM(AE3:AE14) -> 5017.4325 | AN14: =SUM(AF3:AF14) -> 17767.87 | AO14: =SUM(AG3:AG14) -> 2736.322 | AP14: =SUM(AL14:AO14) -> 36994.551 | AR14: 20.12月累计 | AS14: =AL14/$AP14 -> 0.31012478 | AT14: =AM14/$AP14 -> 0.13562626 | AU14: =AN14/$AP14 -> 0.48028342 | AV14: =AO14/$AP14 -> 0.073965541 | AW14: =SUM(AS14:AV14) -> 1 | AY14: 20.12月累计 | AZ14: 11016.156 | BA14: 5016.4235 | BB14: 15657.163 | BC14: 2569.4542 | BD14: 34259.198
A15: 44197 | B15: 402.27823 | C15: 559.51924 | D15: 1607.6583 | E15: 507.68088 | F15: =SUM(B15:E15) -> 3077.1366 | H15: 44197 | I15: 14.183812 | J15: 0 | K15: 156.18729 | L15: 1.0140585 | M15: =SUM(I15:L15) -> 171.38516 | O15: 44197 | P15: 0 | Q15: 0 | R15: 0 | S15: 19.113534 | T15: =SUM(P15:S15) -> 19.113534 | V15: 44197 | W15: 0.0515955 | X15: 0 | Y15: 0 | Z15: -0.05951476 | AA15: =SUM(W15:Z15) -> -0.00791926 | AC15: 44197 | AD15: =B15+I15+P15+W15 -> 416.51364 | AE15: =C15+J15+Q15+X15 -> 559.51924 | AF15: =D15+K15+R15+Y15 -> 1763.8455 | AG15: =E15+L15+S15+Z15 -> 527.74896 | AH15: =F15+M15+T15+AA15 -> 3267.6274 | AI15: =SUM(AD15:AG15)-AH15 -> 0 | AK15: 21.1月累计 | AL15: =AD15 -> 416.51364 | AM15: =AE15 -> 559.51924 | AN15: =AF15 -> 1763.8455 | AO15: =AG15 -> 527.74896 | AP15: =SUM(AL15:AO15) -> 3267.6274 | AR15: 21.1月累计 | AS15: =AL15/$AP15 -> 0.12746669 | AT15: =AM15/$AP15 -> 0.17123104 | AU15: =AN15/$AP15 -> 0.53979397 | AV15: =AO15/$AP15 -> 0.16150831 | AW15: =SUM(AS15:AV15) -> 1 | AY15: 21.1月累计 | AZ15: 402.27823 | BA15: 559.51924 | BB15: 1607.6583 | BC15: 507.68088 | BD15: 3077.1366
A16: 44228 | B16: 488.58875 | C16: 542.10398 | D16: 1137.1924 | E16: 282.05379 | F16: =SUM(B16:E16) -> 2449.939 | H16: 44228 | I16: 546.48274 | J16: 0 | K16: 201.93547 | L16: 0.86096592 | M16: =SUM(I16:L16) -> 749.27918 | O16: 44228 | P16: 0 | Q16: 0 | R16: 0 | S16: -15.10292 | T16: =SUM(P16:S16) -> -15.10292 | V16: 44228 | W16: 1.5389875 | X16: 0 | Y16: 0 | Z16: 0.06840392 | AA16: =SUM(W16:Z16) -> 1.6073914 | AC16: 44228 | AD16: =B16+I16+P16+W16 -> 1036.6105 | AE16: =C16+J16+Q16+X16 -> 542.10398 | AF16: =D16+K16+R16+Y16 -> 1339.1279 | AG16: =E16+L16+S16+Z16 -> 267.88024 | AH16: =F16+M16+T16+AA16 -> 3185.7226 | AI16: =SUM(AD16:AG16)-AH16 -> 0 | AK16: 21.2月累计 | AL16: =SUM(AD15:AD16) -> 1453.1241 | AM16: =SUM(AE15:AE16) -> 1101.6232 | AN16: =SUM(AF15:AF16) -> 3102.9735 | AO16: =SUM(AG15:AG16) -> 795.6292 | AP16: =SUM(AL16:AO16) -> 6453.35 | AR16: 21.2月累计 | AS16: =AL16/$AP16 -> 0.22517361 | AT16: =AM16/$AP16 -> 0.17070564 | AU16: =AN16/$AP16 -> 0.48083142 | AV16: =AO16/$AP16 -> 0.12328933 | AW16: =SUM(AS16:AV16) -> 1 | AY16: 21.2月累计 | AZ16: 890.86698 | BA16: 1101.6232 | BB16: 2744.8507 | BC16: 789.73468 | BD16: 5527.0756
A17: 44256 | B17: 356.5353 | C17: 728.13222 | D17: 2787.0571 | E17: 365.72309 | F17: =SUM(B17:E17) -> 4237.4477 | H17: 44256 | I17: 330.32726 | J17: 0 | K17: 154.32761 | L17: 9.9237115 | M17: =SUM(I17:L17) -> 494.57858 | O17: 44256 | P17: 0 | Q17: 0 | R17: 0 | S17: -17.595791 | T17: =SUM(P17:S17) -> -17.595791 | V17: 44256 | W17: 2.0169192 | X17: 0 | Y17: 0 | Z17: 0 | AA17: =SUM(W17:Z17) -> 2.0169192 | AC17: 44256 | AD17: =B17+I17+P17+W17 -> 688.87947 | AE17: =C17+J17+Q17+X17 -> 728.13222 | AF17: =D17+K17+R17+Y17 -> 2941.3847 | AG17: =E17+L17+S17+Z17 -> 358.05101 | AH17: =F17+M17+T17+AA17 -> 4716.4474 | AI17: =SUM(AD17:AG17)-AH17 -> 0 | AK17: 21.3月累计 | AL17: =SUM(AD15:AD17) -> 2142.0036 | AM17: =SUM(AE15:AE17) -> 1829.7554 | AN17: =SUM(AF15:AF17) -> 6044.3581 | AO17: =SUM(AG15:AG17) -> 1153.6802 | AP17: =SUM(AL17:AO17) -> 11169.797 | AR17: 21.3月累计 | AS17: =AL17/$AP17 -> 0.19176745 | AT17: =AM17/$AP17 -> 0.16381277 | AU17: =AN17/$AP17 -> 0.54113409 | AV17: =AO17/$AP17 -> 0.10328569 | AW17: =SUM(AS17:AV17) -> 1 | AY17: 21.3月累计 | AZ17: 1247.4023 | BA17: 1829.7554 | BB17: 5531.9078 | BC17: 1155.4578 | BD17: 9764.5233
A18: 44287 | B18: 236.52163 | C18: 813.21296 | D18: 639.93242 | E18: 329.58635 | F18: =SUM(B18:E18) -> 2019.2534 | H18: 44287 | I18: 28.478805 | J18: 0 | K18: 153.53373 | L18: 0.37578484 | M18: =SUM(I18:L18) -> 182.38832 | O18: 44287 | P18: 0 | Q18: 0 | R18: 0 | S18: 27.92591 | T18: =SUM(P18:S18) -> 27.92591 | V18: 44287 | W18: 45.293797 | X18: 0 | Y18: 0 | Z18: 1.5037817 | AA18: =SUM(W18:Z18) -> 46.797579 | AC18: 44287 | AD18: =B18+I18+P18+W18 -> 310.29423 | AE18: =C18+J18+Q18+X18 -> 813.21296 | AF18: =D18+K18+R18+Y18 -> 793.46615 | AG18: =E18+L18+S18+Z18 -> 359.39183 | AH18: =F18+M18+T18+AA18 -> 2276.3652 | AI18: =SUM(AD18:AG18)-AH18 -> 0 | AK18: 21.4月累计 | AL18: =SUM(AD15:AD18) -> 2452.2978 | AM18: =SUM(AE15:AE18) -> 2642.9684 | AN18: =SUM(AF15:AF18) -> 6837.8243 | AO18: =SUM(AG15:AG18) -> 1513.072 | AP18: =SUM(AL18:AO18) -> 13446.163 | AR18: 21.4月累计 | AS18: =AL18/$AP18 -> 0.18237901 | AT18: =AM18/$AP18 -> 0.19655931 | AU18: =AN18/$AP18 -> 0.50853351 | AV18: =AO18/$AP18 -> 0.11252817 | AW18: =SUM(AS18:AV18) -> 1 | AY18: 21.4月累计 | AZ18: 1483.9239 | BA18: 2642.9684 | BB18: 6171.8402 | BC18: 1485.0441 | BD18: 11783.777
A19: 44317 | B19: 256.6498 | C19: 1101.2379 | D19: 1111.4885 | E19: 340.37551 | F19: =SUM(B19:E19) -> 2809.7517 | H19: 44317 | I19: 226.573 | J19: 0 | K19: 146.84182 | L19: 10.728323 | M19: =SUM(I19:L19) -> 384.14314 | O19: 44317 | P19: 0 | Q19: 0 | R19: 0 | S19: 10.131292 | T19: =SUM(P19:S19) -> 10.131292 | V19: 44317 | W19: 1.5670044 | X19: 0 | Y19: 0 | Z19: 0.1399995 | AA19: =SUM(W19:Z19) -> 1.7070039 | AC19: 44317 | AD19: =B19+I19+P19+W19 -> 484.78981 | AE19: =C19+J19+Q19+X19 -> 1101.2379 | AF19: =D19+K19+R19+Y19 -> 1258.3304 | AG19: =E19+L19+S19+Z19 -> 361.37513 | AH19: =F19+M19+T19+AA19 -> 3205.7331 | AI19: =SUM(AD19:AG19)-AH19 -> 0 | AK19: 21.5月累计 | AL19: =SUM(AD15:AD19) -> 2937.0876 | AM19: =SUM(AE15:AE19) -> 3744.2063 | AN19: =SUM(AF15:AF19) -> 8096.1546 | AO19: =SUM(AG15:AG19) -> 1874.4472 | AP19: =SUM(AL19:AO19) -> 16651.896 | AR19: 21.5月累计 | AS19: =AL19/$AP19 -> 0.17638158 | AT19: =AM19/$AP19 -> 0.22485165 | AU19: =AN19/$AP19 -> 0.48620018 | AV19: =AO19/$AP19 -> 0.11256659 | AW19: =SUM(AS19:AV19) -> 1 | AY19: 21.5月累计 | AZ19: 1740.5737 | BA19: 3744.2063 | BB19: 7283.3287 | BC19: 1825.4196 | BD19: 14593.528
A20: 44348 | B20: 460.4562 | C20: 1107.4281 | D20: 2248.0557 | E20: =267.930894339999+897733.18/10000 -> 357.70421 | F20: =SUM(B20:E20) -> 4173.6442 | H20: 44348 | I20: 387.50775 | J20: 0 | K20: 194.94649 | L20: 0.9571482 | M20: =SUM(I20:L20) -> 583.41138 | O20: 44348 | P20: 0 | Q20: 0 | R20: 0 | S20: 75.23211 | T20: =SUM(P20:S20) -> 75.23211 | V20: 44348 | W20: 174.97704 | X20: 0 | Y20: 0 | Z20: 6.1661302 | AA20: =SUM(W20:Z20) -> 181.14317 | AC20: 44348 | AD20: =B20+I20+P20+W20 -> 1022.941 | AE20: =C20+J20+Q20+X20 -> 1107.4281 | AF20: =D20+K20+R20+Y20 -> 2443.0021 | AG20: =E20+L20+S20+Z20 -> 440.0596 | AH20: =F20+M20+T20+AA20 -> 5013.4309 | AI20: =SUM(AD20:AG20)-AH20 -> 0 | AK20: 21.6月累计 | AL20: =SUM(AD15:AD20) -> 3960.0286 | AM20: =SUM(AE15:AE20) -> 4851.6344 | AN20: =SUM(AF15:AF20) -> 10539.157 | AO20: =SUM(AG15:AG20) -> 2314.5068 | AP20: =SUM(AL20:AO20) -> 21665.327 | AR20: 21.6月累计 | AS20: =AL20/$AP20 -> 0.18278186 | AT20: =AM20/$AP20 -> 0.22393544 | AU20: =AN20/$AP20 -> 0.48645271 | AV20: =AO20/$AP20 -> 0.10683 | AW20: =SUM(AS20:AV20) -> 1 | AY20: 21.6月累计 | AZ20: 2201.0299 | BA20: 4851.6344 | BB20: 9531.3844 | BC20: 2183.1238 | BD20: 18767.173
A21: 44378 | B21: 286.43738 | C21: 860.61755 | D21: 671.29109 | E21: 216.76834 | F21: =SUM(B21:E21) -> 2035.1144 | H21: 44378 | I21: 115.30655 | J21: 0 | K21: 239.27565 | L21: 0.51343644 | M21: =SUM(I21:L21) -> 355.09564 | O21: 44378 | P21: 0 | Q21: 0 | R21: 0 | S21: 35.531281 | T21: =SUM(P21:S21) -> 35.531281 | V21: 44378 | W21: 0.18943684 | X21: 0 | Y21: 0 | Z21: 5.6012838 | AA21: =SUM(W21:Z21) -> 5.7907206 | AC21: 44378 | AD21: =B21+I21+P21+W21 -> 401.93337 | AE21: =C21+J21+Q21+X21 -> 860.61755 | AF21: =D21+K21+R21+Y21 -> 910.56674 | AG21: =E21+L21+S21+Z21 -> 258.41434 | AH21: =F21+M21+T21+AA21 -> 2431.532 | AI21: =SUM(AD21:AG21)-AH21 -> 0 | AK21: 21.7月累计 | AL21: =SUM(AD15:AD21) -> 4361.962 | AM21: =SUM(AE15:AE21) -> 5712.2519 | AN21: =SUM(AF15:AF21) -> 11449.724 | AO21: =SUM(AG15:AG21) -> 2572.9211 | AP21: =SUM(AL21:AO21) -> 24096.859 | AR21: 21.7月累计 | AS21: =AL21/$AP21 -> 0.18101787 | AT21: =AM21/$AP21 -> 0.2370538 | AU21: =AN21/$AP21 -> 0.4751542 | AV21: =AO21/$AP21 -> 0.10677413 | AW21: =SUM(AS21:AV21) -> 1 | AY21: 21.7月累计 | AZ21: 2487.4673 | BA21: 5712.2519 | BB21: 10202.675 | BC21: 2399.8922 | BD21: 20802.287
A22: 44409 | B22: 242.47369 | C22: 1083.1079 | D22: 2403.4055 | E22: 355.56105 | F22: =SUM(B22:E22) -> 4084.5481 | H22: 44409 | I22: 120.2148 | J22: 0 | K22: 165.66233 | L22: 0.78503918 | M22: =SUM(I22:L22) -> 286.66217 | O22: 44409 | P22: 5.0756266 | Q22: 0 | R22: 0 | S22: 18.268923 | T22: =SUM(P22:S22) -> 23.34455 | V22: 44409 | W22: 0.11049016 | X22: 0 | Y22: 0 | Z22: 6.7807522 | AA22: =SUM(W22:Z22) -> 6.8912423 | AC22: 44409 | AD22: =B22+I22+P22+W22 -> 367.87461 | AE22: =C22+J22+Q22+X22 -> 1083.1079 | AF22: =D22+K22+R22+Y22 -> 2569.0679 | AG22: =E22+L22+S22+Z22 -> 381.39576 | AH22: =F22+M22+T22+AA22 -> 4401.4461 | AI22: =SUM(AD22:AG22)-AH22 -> 0 | AK22: 21.8月累计 | AL22: =SUM(AD15:AD22) -> 4729.8366 | AM22: =SUM(AE15:AE22) -> 6795.3598 | AN22: =SUM(AF15:AF22) -> 14018.791 | AO22: =SUM(AG15:AG22) -> 2954.3169 | AP22: =SUM(AL22:AO22) -> 28498.305 | AR22: 21.8月累计 | AS22: =AL22/$AP22 -> 0.16596905 | AT22: =AM22/$AP22 -> 0.23844786 | AU22: =AN22/$AP22 -> 0.49191668 | AV22: =AO22/$AP22 -> 0.10366641 | AW22: =SUM(AS22:AV22) -> 1 | AY22: 21.8月累计 | AZ22: 2729.941 | BA22: 6795.3598 | BB22: 12606.081 | BC22: 2755.4532 | BD22: 24886.835
