Workbook

Sheet 备忘录
A1: 被审计单位：福禄福擎网络科技有限公司 | E1: 项目 | F1: 名称 | G1: 链接 | H1: 问题描述 | I1: 相关支撑资料 | J1: 问题定性 | K1: 管理层回应/整改措施 | L1: 状态(已解决/持续监控)
A2: 财务报表截止日：2025/9/30 | C2: 日期：2025/10/30 | E2: 货币资金 | F2: 货币资金明细表 | G2: HBZJ-1
A3: 财务报表期间：2025.1-2025.9 | C3: 日期：2025/10/31 | F3: 流水分析 | G3: LSFX-1
E4: 库存商品 | F4: 库存商品明细表 | G4: KCSP-1
F5: 库存商品分析表 | G5: KCSPFX-1
E6: 固定资产 | F6: 固定资产明细表 | G6: GDZC-1
F7: 固定资产测算表 | G7: GDZCCS-1
E8: 无形资产 | F8: 无形资产明细表 | G8: WXZC-1
F9: 无形资产测算表 | G9: WXZCCS-1
E10: 其他流动资产 | F10: 其他流动资产明细表 | G10: QTLDZC-1
E11: 往来 | F11: 应收账款明细表 | G11: YSZK-1
F12: 预付账款明细表 | G12: YFZK-1
F13: 其他应收款明细表 | G13: QTYSK-1
F14: 应付账款明细表 | G14: YFZK-1
F15: 预收账款明细表 | G15: YSZK-1
F16: 其他应付款明细表 | G16: QTYFK-1
F17: 关联方交易核对 | G17: GLFJY-1
E18: 应付职工薪酬 | F18: 应付职工薪酬明细表 | G18: YFZGXCMX-1
F19: 应付职工薪酬检查表 | G19: YFZGXCJC-1
E20: 应交税费 | F20: 应交税费明细表 | G20: YJSF-1
F21: 应交增值税明细表 | G21: YJSF-2
E22: 收入、成本 | F22: 营业收入明细表 | G22: YYSR-1
F23: 营业成本明细表 | G23: YYCB-1
F24: 毛利率分析表 | G24: MLLFX-1
E25: 费用 | F25: 销售费用明细表 | G25: XSFY-1
F26: 销售费用比例分析 | G26: XSFY-2
F27: 管理费用明细表 | G27: GLFY-1
F28: 管理费用比例分析 | G28: GLFY-2
F29: 财务费用明细表 | G29: CWFY-1

Sheet 实际执行程序表（资产负债）
A1: 序号 | B1: 科目名称 | C1: 计划实施的实质性程序 | D1: 审计结论 | E1: 财务报表认定
E2: 存在/发生 | F2: 完整性 | G2: 权利/义务 | H2: 计价 | I2: 列报
A3: 1 | B3: 货币资金 | C3: 获取或编制货币资金明细表 | H3: √
A4: 2 | B4: 货币资金 | C4: 取得被审计单位银行存款及其他货币资金的银行余额对账单，检查被审计单位提供的银行对账单是否存在涂改或修改的情况，确定银行对账单金额的正确性，并与账面余额核对，确认是否一致； | E4: √ | F4: √ | H4: √
A5: 3 | B5: 货币资金 | C5: 抽查大额库存现金收支。检查原始凭证是否齐全、记账凭证与原始凭证是否相符、账务处理是否正确、是否记录于恰当的会计期间、是否经过授权批准等项内容。 | E5: √ | H5: √
A6: 4 | B6: 货币资金 | C6: 抽查大额银行存款收支的原始凭证，检查原始凭证是否齐全、有无授权批准、记账凭证与原始凭证是否相符、账务处理是否正确、是否记录于恰当的会计期间等项内容。 检查是否存在非营业目的的大额货币资金转移，并核对相关账户的进账情况；如有与被审计单位生产经营无关的收支事项，应查明原因并作相应的记录。 | E6: √ | H6: √
A7: 5 | B7: 货币资金 | C7: 抽查大额其他货币资金收付记录。检查原始凭证是否齐全、记账凭证与原始凭证是否相符、账务处理是否正确、是否记录于恰当的会计期间等项内容。 | E7: √ | H7: √
A8: 6 | B8: 货币资金 | C8: 关注是否有质押、冻结等对变现有限制、或存放在境外、或有潜在回收风险的款项，并已恰当披露。 | I8: √
A9: 7 | B9: 库存商品 | C9: 获取或编制库存商品的明细表，复核加计是否正确，并与总账数、明细账合计数核对是否相符。 检查库存商品明细表中是否有异常或负余额（包括数量为负或金额为负）的项目 | E9: √ | F9: √ | H9: √
A10: 8 | B10: 库存商品 | C10: 如发生关联方交易：(1)了解交易的商业理由；(检查与关联方的购销业务是否正常) (2)检查证实交易的支持性文件；（例如发票、合同、协议及入库单据等相关文件，并关注交易价格、交易金额的真实性及合理性) | E10: √ | F10: √ | G10: √ | H10: √
A11: 9 | B11: 库存商品 | C11: 审阅库存商品明细账，检查有无长期挂账的库存商品，如有，应查明原因并作适当处理。 | E11: √ | H11: √
A12: 10 | B12: 固定资产 | C12: 获取或编制固定资产、累计折旧、减值准备明细表，复核加计是否正确，并与总账数和明细账合计数、报表数核对是否相符，结合累计折旧和固定资产减值准备与报表数核对是否相符。 | H12: √
A13: 11 | B13: 固定资产 | C13: 检查固定资产的所有权或控制权：(1)对外购的机器设备等固定资产，审核采购发票、采购合同等； (2)对于房地产类固定资产，查阅有关的合同、产权证明、财产税单、抵押借款的还款凭据、保险单等书面文件； (3)对汽车等运输设备，检查有关运营证件等； | G13: √
A14: 12 | B14: 固定资产 | C14: 检查累计折旧：(1)获取或编制累计折旧分类汇总表，复核加计正确，并与总账数和明细合计数核对。 (2)复核本期折旧费用的计提是否正确 (3)检查累计折旧的减少是否合理，会计处理是否正确 | H14: √
A15: 13 | B15: 无形资产 | C15: 获取或编制无形资产明细表，复核加计是否正确，并与总账数和明细账合计数核对是否相符；结合累计摊销、无形资产减值准备科目与报表数核对是否相符。 | H15: √
A16: 14 | B16: 无形资产 | C16: 检查无形资产的权属证书原件、非专利技术的持有和保密状况等，并获取有关协议和董事会纪要等文件、资料，检查无形资产的性质、构成内容、计价依据、使用状况和受益期限，确定无形资产是否存在，并由被审计单位拥有或控制。 | E16: √ | G16: √
A17: 15 | B17: 无形资产 | C17: 检查使用寿命有限的无形资产的摊销：(1)获取或编制无形资产累计摊销明细表，复核加计正确，并与总账数和明细账合计数核对相符。 (2)检查无形资产摊销政策是否符合有关规定，是否与上期一致，若改变摊销政策，检查其依据是否充分。 (3)复核本期摊销是否正确。 | H17: √
A18: 16 | B18: 应收账款 | C18: 获取或编制应收账款明细表：复核加计是否正确，并与总账数和明细账合计数核对是否相符；结合坏账准备科目与报表数核对是否相符；分析有贷方余额的项目，查明原因，必要时，作重分类调整； | H18: √
A19: 17 | B19: 应收账款 | C19: 结合其他应收款、预收账款等往来项目的明细余额，调查有无同一客户多处挂账、异常余额或与销售无关的其他款项。如有，应做出记录，必要时作调整； | H19: √
A20: 18 | B20: 应收账款 | C20: 获取或编制应收账款账龄分析表，对重要客户的主要信息进行背景调查； | H20: √
A21: 19 | B21: 应收账款 | C21: 对重大应收账款余额进行核对。 | E21: √ | G21: √ | H21: √
A22: 20 | B22: 预付账款 | C22: 获取或编制预付款项明细表：复核加计是否正确，并与总账数和明细账合计数核对是否相符，结合坏账准备科目与报表数核对是否相符；分析出现贷方余额的项目，查明原因，必要的建议进行重新分类调整； | H22: √
A23: 21 | B23: 预付账款 | C23: 结合应付账款明细账审计，查核有无重复付款情况或在收到由预付款项购买的物资时未冲减预付款项而增加应付款项的情况（即在预付款项和应付账款两个科目中同时挂账)； | H23: √
A24: 22 | B24: 预付账款 | C24: 获取或编制预付账款账龄分析表，对重要客户的主要信息进行背景调查； | H24: √
A25: 23 | B25: 预付账款 | C25: 对重大预付账款余额进行核对。 | E25: √ | G25: √ | H25: √
A26: 24 | B26: 其他应收款 | C26: 获取或编制其他应收款明细表：复核加计正确，并与总账数和明细账合计数核对是否相符，结合坏账准备科目与报表数核对是否相符；分析有贷方余额的项目，查明原因，必要时，作重分类调整； | H26: √
A27: 25 | B27: 其他应收款 | C27: 结合其他应收款、其他应付款等明细余额，检查是否有同时挂账的项目，核算内容是否重复，必要时作出适当调整； | H27: √
A28: 26 | B28: 其他应收款 | C28: 获取或编制其他应收款账龄分析表，对重要客户的主要信息进行背景调查； | H28: √
A29: 27 | B29: 其他应收款 | C29: 对重大其他应收款余额进行核对。 | E29: √ | G29: √ | H29: √
A30: 28 | B30: 应付账款 | C30: 获取或编制应付账款明细表：复核加计正确，并与报表数、总账数和明细账合计数核对是否相符；分析出现借方余额的项目，查明原因，必要时，作重分类调整； | H30: √
A31: 29 | B31: 应付账款 | C31: 结合预付账款等往来项目的明细余额，调查有无同挂的项目、异常余额或与购货无关的其他款项（如关联方账户或雇员账户），如有，应做出记录，必要时作调整； | H31: √
A32: 30 | B32: 应付账款 | C32: 获取被审计单位与其供应商之间的对账单，以及被审计单位编制的差异调节表，确定应付账款金额的正确性。 应考虑从非财务部门获取上述资料，如：采购部门。查找有无未入账的应付账款，确定是否表明存在错报。 | H32: √
A33: 31 | B33: 应付账款 | C33: 如存在应付关联方的款项：（1）了解交易的商业理由；（2）检查证实交易的支持性文件（例如发票、合同、协议及入库等相关文件）。 | H33: √
A34: 32 | B34: 应付账款 | C34: 获取或编制应付账款账龄分析表，对重要客户的主要信息进行背景调查； | H34: √
A35: 33 | B35: 应付账款 | C35: 对重大应付账款余额进行核对。 | E35: √ | G35: √ | H35: √
A36: 34 | B36: 预收账款 | C36: 获取或编制预收款项明细表：复核加计是否正确，并与报表数、总账数和明细账合计数核对是否相符；比较期初、期末预收款项余额，分析其变动原因；检查是否存在借方余额，必要时进行重分类调整； | H36: √
A37: 35 | B37: 预收账款 | C37: 结合应收账款等往来款项目的明细余额，检查是否存在应收、预收两方挂账的项目，必要时做出调整； | H37: √
A38: 36 | B38: 预收账款 | C38: 获取或编制预收款项账龄分析表，并对期末账龄在上年账龄基础上递增的合理性进行分析，并检查预收款项长期挂账的原因，并作出记录，必要时提请被审计单位予以调整。 | H38: √
A39: 37 | B39: 预收账款 | C39: 如存在预收关联方[包括持股5%以上(含5%)股东]的款项：（1）了解交易的商业理由、交易类型、交易定价政策等，形成必要记录。（2）检查证实交易的支持性文件；例如发票、合同、协议、入库单等文件 | H39: √
A40: 38 | B40: 预收账款 | C40: 获取或编制预收账款账龄分析表，对重要客户的主要信息进行背景调查； | H40: √
A41: 39 | B41: 预收账款 | C41: 对重大预收账款余额进行核对。 | E41: √ | G41: √ | H41: √
A42: 40 | B42: 其他应付款 | C42: 获取或编制其他应付款明细表：复核加计是否正确，并与总账数和明细账合计数核对是否相符；分析有借方余额的项目，查明原因，必要时，作重分类调整； | H42: √
A43: 41 | B43: 其他应付款 | C43: 结合应付账款、其他应收款等往来项目的明细余额，调查有无同挂的项目、异常余额或与本科目核算无关的其他款项，如有，应做出记录，必要时作调整； | H43: √
A44: 42 | B44: 其他应付款 | C44: 如存在应付关联方的款项：（1）了解交易的商业理由；（2）检查证实交易的支持性文件（例如发票、合同、协议及入库等相关文件）。 | H44: √
A45: 43 | B45: 其他应付款 | C45: 获取或编制其他应付款账龄分析表，对重要客户的主要信息进行背景调查； | H45: √
A46: 44 | B46: 其他应付款 | C46: 对重大其他应付款余额进行核对。 | E46: √ | G46: √ | H46: √
A47: 45 | B47: 应交税费 | C47: 获取或编制应交税费明细表：复核加计是否正确，并与报表数、总账数和明细账合计数核对是否相符；分析存在借方余额的项目，查明原因，判断是否由被审计单位预缴税款引起； | H47: √
A48: 46 | B48: 应交税费 | C48: 检查应交增值税：(1)获取或编制应交增值税明细表，加计复核其正确性，并与明细账核对相符；(2)将应交增值税明细表与被审计单位增值税纳税申报表进行核对，比较两者是否总体相符，并分析其差额的原因；(10)抽查本期已交增值税资料，确定已交款数的正确性。 | E48: √ | F48: √ | H48: √
A49: 47 | B49: 应付职工薪酬 | C49: 获取或编制应付职工薪酬明细表,复核加计是否正确,并与报表数、总账数和明细账合计数核对是否相符。 | H49: √
A50: 48 | B50: 应付职工薪酬 | C50: 检查应付职工薪酬本期的发生： (1)对按照职工提供服务情况和工资标准计算的职工薪酬（如工资），获取工资计算表，将工资标准与有关规定进行核对，选取样本进行测试 | H50: √
A51: 49 | B51: 应付职工薪酬 | C51: 检查应付职工薪酬的确认，与生产成本、制造费用、在建工程等相关账项进行核对，确定会计处理是否符合企业会计准则的规定 1)应由生产产品、提供劳务负担的职工薪酬，计入产品成本或劳务成本； 2)应由在建工程、无形资产负担的职工薪酬，计入建造固定资产或无形资产； 4)其他职工薪酬，计入当期损益； | E51: √ | F51: √ | H51: √
A52: 50 | B52: 其他流动资产 | C52: 获取或编制其他流动资产明细表，复核加计是否正确，并与总账数和明细账合计数核对是否相符，与报表数核对是否相符。 | H52: √
A53: 51 | B53: 其他流动资产 | C53: 分析明细账余额，对于出现贷方余额的项目，应查明原因。 | H53: √
A54: 52 | B54: 其他流动资产 | C54: 检查其他流动资产所核算内容的分类是否正确。 | I54: √

Sheet 实际执行程序表（利润）
A1: 序号 | B1: 科目名称 | C1: 计划实施的实质性程序 | D1: 审计结论 | E1: 财务报表认定
E2: 发生 | F2: 完整性 | G2: 准确性 | H2: 截止 | I2: 分类 | J2: 列报
A3: 1 | B3: 营业收入 | C3: 获取或编制主营业务收入明细表：(1)复核加计是否正确，并与总账数和明细账合计数核对是否相符，结合其他业务收入科目与报表数核对是否相符； | G3: √
A4: 2 | B4: 营业收入 | C4: (1)按收入类别或产品名称对销售数量、主营业务收入、毛利率等进行趋势分析、结构分析和价格变动分析，确定异常或应关注的领域或区间，并查明重大波动原因； | E4: √ | F4: √ | G4: √
A5: 3 | B5: 营业收入 | C5: (2)按月度对本期和上期毛利率进行比较分析，检查是否存在异常，各期之间是否存在重大波动，查明原因； | E5: √ | F5: √ | G5: √
A6: 4 | B6: 营业收入 | C6: (3)比较本期各月各类主营业务收入的波动情况，分析其变动趋势是否正常，是否符合被审计单位季节性、周期性的经营规律，查明异常现象和重大波动的原因； | E6: √ | F6: √ | G6: √
A7: 5 | B7: 营业收入 | C7: 检查收入确认会计政策及会计估计的判断是否恰当：(1)了解被审计单位的销售模式或经营模式，结合在了解被审计单位及其环境时获取的信息，并结合合同检查主营业务收入的确认条件、方法是否符合企业会计准则规定；前后期是否一致； | E7: √ | F7: √ | G7: √ | H7: √
A8: 6 | B8: 营业收入 | C8: 获取产品价格目录，抽查售价是否符合价格政策，并注意销售给关联方或关系密切的重要客户的产品价格是否合理，有无以低价或高价结算的方法，相互之间有无转移利润的现象。 | G8: √
A9: 7 | B9: 营业收入 | C9: 如发生关联方交易：检查证实交易的支持性文件（例如发票、合同、协议及入库等相关文件）。 将关联方交易的频率、规模、价格和账款结算条件，与非关联方对比，确定关联交易价格是否远远高于或低于非关联方交易价格，分析被审计单位利用关联方交易虚构业务或调节利润或利益输送的可能性。 | E9: √ | G9: √
A10: 8 | B10: 营业收入 | C10: 获取或编制其他业务收入明细表，复核加计是否正确，并与总账数和明细账合计数核对是否相符，结合主营业务收入科目与营业收入报表数核对是否相符。 | G10: √
A11: 9 | B11: 营业收入 | C11: 检查营业收入是否已按照企业会计准则的规定在财务报表中作出恰当列报。 | J11: √
A12: 10 | B12: 营业成本 | C12: 获取或编制主营业务成本明细表，复核加计是否正确，并与总账数和明细账合计数核对是否相符，结合其他业务成本科目与营业成本报表数核对是否相符。 | E12: √ | F12: √ | G12: √
A13: 11 | B13: 营业成本 | C13: 对主营业务成本进行分析：（1）将本期和上期主营业务成本按月度进行比较分析 （2）将本期和上期的主要产品单位成本进行比较分析 （3）对异常情况的项目做进一步的调查 | F13: √ | G13: √ | H13: √
A14: 12 | B14: 营业成本 | C14: 抽查月主营业务成本结转明细清单，比较计入主营业务成本的品种、规格、数量和主营业务收入的口径是否一致，是否符合配比原则。 | E14: √ | F14: √
A15: 13 | B15: 营业成本 | C15: 检查营业成本是否已按照企业会计准则的规定在财务报表中作出恰当列报。 | J15: √
A16: 14 | B16: 销售费用 | C16: 获取或编制销售费用明细表： (1)复核其加计数是否正确，并与报表数、总账数和明细账合计数核对是否相符； (2)将销售费用中的工资、折旧等与相关的资产、负债科目核对，检查其勾稽关系的合理性。
A17: 15 | B17: 销售费用 | C17: 对销售费用进行分析：(1)计算分析各个月份销售费用总额及主要项目金额占主营业务收入的比率，并与上一年度进行比较，判断变动的合理性；(2)计算分析各个月份销售费用中主要项目发生额及占销售费用总额的比率，并与上一年度进行比较，判断其变动的合理性。
A18: 16 | B18: 销售费用 | C18: 对本期发生的销售费用，选取样本，检查其支付性文件，确定原始凭证是否齐全，记账凭证与原始凭证是否相符以及账务处理是否正确。
A19: 17 | B19: 销售费用 | C19: （1）检查销售佣金支出是否符合规定，审批手续是否健全，是否取得有效的原始凭证；如超过规定，是否按规定进行了纳税调整。
A20: 18 | B20: 销售费用 | C20: （2）检查广告费、宣传费、业务招待费的支出是否合理，审批手续是否健全，是否取得有效的原始凭证；如超过规定限额，应在计算应纳税所得额时调整。
A21: 19 | B21: 销售费用 | C21: （3）选择重要或异常的销售费用，检查销售费用各项目开支标准是否符合有关规定，开支内容是否与被审计单位的产品销售或专设销售机构的经费有关，计算是否正确，原始凭证是否合法，会计处理是否正确。
A22: 20 | B22: 销售费用 | C22: 检查销售费用是否已按照企业会计准则在财务报表中作出恰当的列报和披露。
A23: 21 | B23: 管理费用 | C23: 获取或编制管理费用明细表：(1)复核加计是否正确，并与报表数、总账数及明细账合计数核对是否相符。(2)将管理费用中的职工薪酬、无形资产摊销、长期待摊费用摊销额等项目与各有关账户进行核对，分析其勾稽关系的合理性，并作出相应记录。 | G23: √
A24: 22 | B24: 管理费用 | C24: 对管理费用进行分析，并汇总并评价差异结果：(1)计算分析管理费用中各项目发生额及占费用总额的比率，将本期、上期管理费用各主要明细项目作比较分析，判断其变动的合理性。(2)比较本期各月份管理费用，对有重大波动和异常情况的项目应查明原因，必要时作适当处理。 | E24: √ | F24: √ | G24: √
A25: 23 | B25: 管理费用 | C25: 对本期发生的管理费用，选取样本，检查其支付性文件，确定原始凭证是否齐全，记账凭证与原始凭证是否相符以及账务处理是否正确。 | E25: √ | G25: √ | H25: √ | I25: √
A26: 24 | B26: 管理费用 | C26: (1)检查公司经费(包括行政管理部门职工薪酬、物料消耗、低值易耗品摊销、办公费和差旅费)是否系经营管理中发生或应由公司统一负担，检查相关费用报销内部管理办法，是否有合法原始凭证支持。 | E26: √ | G26: √ | H26: √ | I26: √
A27: 25 | B27: 管理费用 | C27: (2)检查董事会费(包括董事会成员津贴、会议费和差旅费等)，检查相关董事会及股东会决议，是否在合规范围内开支费用。 | E27: √ | G27: √ | H27: √ | I27: √
A28: 26 | B28: 管理费用 | C28: (3)检查聘请中介机构费、咨询费(含顾问费)，检查是否按合同规定支付费用，有无涉及到诉讼及赔偿款项支出。 | E28: √ | G28: √ | H28: √ | I28: √
A29: 27 | B29: 管理费用 | C29: (4)检查业务招待费的支出是否合理，如超过规定限额，应在计算应纳税所得额时调整。 | E29: √ | G29: √ | H29: √ | I29: √
A30: 28 | B30: 管理费用 | C30: 检查诉讼费用并结合或有事项审计,检查涉及的相关重大诉讼事项是否已在附注中进行披露，还需进一步关注诉讼状态，判断有无或有负债，或是否存在损失已发生而未入账的事项。如发生诉讼和索赔费用，完成“诉讼和索赔事项”工作底稿。 | E30: √ | F30: √ | G30: √
A31: 29 | B31: 管理费用 | C31: 根据评估的舞弊风险等因素增加的其他审计程序。（1）检查大额或异常费用开支的适当性 （2）检查高层管理人员提交的费用报告的适当性和金额 | E31: √ | F31: √ | G31: √
A32: 30 | B32: 管理费用 | C32: 确定管理费用是否已按照企业会计准则的规定在财务报表中作出恰当的列报和披露。 | J32: √
A33: 31 | B33: 财务费用 | C33: 获取或编制财务费用明细表，复核其加计数是否正确，并与报表数、总账数和明细账合计数核对是否相符。 | G33: √
A34: 32 | B34: 财务费用 | C34: 将本期财务费用各明细项目与上期进行对比，必要时比较本期各月份财务费用，如有重大波动和异常情况应追查原因； | E34: √ | F34: √ | G34: √
A35: 33 | B35: 财务费用 | C35: 检查财务费用明细项目的设置是否符合规定的核算内容与范围，是否划清财务费用与其他费用的界限。 | J35: √
A36: 34 | B36: 财务费用 | C36: 检查财务费用是否已按照企业会计准则的规定在财务报表中作出恰当的列报。 | J36: √

Sheet 细节测试汇总
A1: 细节测试汇总表
A2: =备忘录!$A$1 -> 被审计单位：福禄福擎网络科技有限公司 | F2: 编制人：刘喜琴 | K2: =备忘录!$C$2 -> 日期：2025/10/30
A3: =备忘录!$A$2 -> 财务报表截止日：2025/9/30 | F3: 复核人：赵玮 | K3: =备忘录!$C$3 -> 日期：2025/10/31
A4: 序号 | B4: 记账日期 | C4: 凭证号 | D4: 摘要 | E4: 科目名称 | F4: 借方 | G4: 贷方 | H4: 对账单数据 | I4: 差异 | J4: 附件及支持性文件说明 | K4: 备注
A6: 1
A7: 2
A8: 3
A9: 4
A10: 5
A11: 6
A12: 7
A13: 8
A14: 9
A15: 10
A16: 11
A17: 12
... A30: 25
A31: 测试金额小计 | G31: =SUM(G6:G30) -> 0 | H31: =SUM(H6:H30) -> 0 | I31: =SUM(I6:I30) -> 0
A36: 备注：抽样明细内容来自序时账

Sheet 货币资金
A1: 货币资金明细表
A2: =备忘录!$A$1 -> 被审计单位：福禄福擎网络科技有限公司 | E2: 编制人：刘喜琴 | H2: =备忘录!$C$2 -> 日期：2025/10/30
A3: =备忘录!$A$2 -> 财务报表截止日：2025/9/30 | E3: 复核人：赵玮 | H3: =备忘录!$C$3 -> 日期：2025/10/31
A4: 序号 | B4: 科目名称 | C4: 核算项目 | D4: 账面数据 | H4: 银行对账单金额 | I4: 差异 | J4: 账户性质 | K4: 备注
D5: 期初金额 | E5: 本期借方 | F5: 本期贷方 | G5: 期末金额
A6: 库存现金 | D6: =ROUND(SUM(D7),2) -> 0 | E6: =ROUND(SUM(E7),2) -> 0 | F6: =ROUND(SUM(F7),2) -> 0 | G6: =ROUND(SUM(G7),2) -> 0 | H6: =ROUND(SUM(H7),2) -> 0
A7: 1 | G7: =ROUND(D7+E7-F7,2) -> 0 | I7: =ROUND(G7-H7,2) -> 0
A8: 银行存款_活期存款 | D8: =ROUND(SUM(D9:D17),2) -> 0 | E8: =ROUND(SUM(E9:E17),2) -> 0 | F8: =ROUND(SUM(F9:F17),2) -> 0 | G8: =ROUND(SUM(G9:G17),2) -> 0 | H8: =ROUND(SUM(H9:H17),2) -> 0 | I8: =ROUND(SUM(I9:I17),2) -> 0
A9: 1 | G9: =ROUND(D9+E9-F9,2) -> 0 | I9: =ROUND(G9-H9,2) -> 0
A10: 2 | G10: =ROUND(D10+E10-F10,2) -> 0 | I10: =ROUND(G10-H10,2) -> 0
A11: 3 | G11: =ROUND(D11+E11-F11,2) -> 0 | I11: =ROUND(G11-H11,2) -> 0
A12: 4 | G12: =ROUND(D12+E12-F12,2) -> 0 | I12: =ROUND(G12-H12,2) -> 0
A13: 5 | G13: =ROUND(D13+E13-F13,2) -> 0 | I13: =ROUND(G13-H13,2) -> 0
A14: 6 | G14: =ROUND(D14+E14-F14,2) -> 0 | I14: =ROUND(G14-H14,2) -> 0
A15: 7 | G15: =ROUND(D15+E15-F15,2) -> 0 | I15: =ROUND(G15-H15,2) -> 0
A16: 8 | G16: =ROUND(D16+E16-F16,2) -> 0 | I16: =ROUND(G16-H16,2) -> 0
A17: 9 | G17: =ROUND(D17+E17-F17,2) -> 0 | I17: =ROUND(G17-H17,2) -> 0
A18: 其他货币资金 | D18: =ROUND(SUM(D19:D30),2) -> 0 | E18: =ROUND(SUM(E19:E30),2) -> 0 | F18: =ROUND(SUM(F19:F30),2) -> 0 | G18: =ROUND(SUM(G19:G30),2) -> 0 | H18: =ROUND(SUM(H19:H30),2) -> 0 | I18: =ROUND(SUM(I19:I30),2) -> 0
A19: 1 | G19: =ROUND(D19+E19-F19,2) -> 0 | I19: =ROUND(G19-H19,2) -> 0
A20: 2 | G20: =ROUND(D20+E20-F20,2) -> 0 | I20: =ROUND(G20-H20,2) -> 0
A21: 3 | G21: =ROUND(D21+E21-F21,2) -> 0 | I21: =ROUND(G21-H21,2) -> 0
A22: 4 | G22: =ROUND(D22+E22-F22,2) -> 0 | I22: =ROUND(G22-H22,2) -> 0
A23: 5 | G23: =ROUND(D23+E23-F23,2) -> 0 | I23: =ROUND(G23-H23,2) -> 0
A24: 6 | G24: =ROUND(D24+E24-F24,2) -> 0 | I24: =ROUND(G24-H24,2) -> 0
A25: 7 | G25: =ROUND(D25+E25-F25,2) -> 0 | I25: =ROUND(G25-H25,2) -> 0
A26: 8 | G26: =ROUND(D26+E26-F26,2) -> 0 | I26: =ROUND(G26-H26,2) -> 0
A27: 9 | G27: =ROUND(D27+E27-F27,2) -> 0 | I27: =ROUND(G27-H27,2) -> 0
A28: 10 | G28: =ROUND(D28+E28-F28,2) -> 0 | I28: =ROUND(G28-H28,2) -> 0
A29: 11 | G29: =ROUND(D29+E29-F29,2) -> 0 | I29: =ROUND(G29-H29,2) -> 0
A30: 12 | G30: =ROUND(D30+E30-F30,2) -> 0 | I30: =ROUND(G30-H30,2) -> 0
A31: 合计 | D31: =ROUND(D6+D8+D18,2) -> 0 | E31: =ROUND(E6+E8+E18,2) -> 0 | F31: =ROUND(F6+F8+F18,2) -> 0 | G31: =ROUND(G6+G8+G18,2) -> 0 | H31: =ROUND(H6+H8+H18,2) -> 0 | I31: =ROUND(I6+I8+I18,2) -> 0
B33: 审计说明：

Sheet 流水分析-银行1
A1: 对账单流水与银行日记账流水月度核对分析
A2: =备忘录!$A$1 -> 被审计单位：福禄福擎网络科技有限公司 | E2: 编制人：刘喜琴 | H2: =备忘录!$C$2 -> 日期：2025/10/30
A3: =备忘录!$A$2 -> 财务报表截止日：2025/9/30 | E3: 复核人：赵玮 | H3: =备忘录!$C$3 -> 日期：2025/10/31
A4: 开户行 | D4: 账号
A5: 项目 | B5: 银行对账单 | F5: 银行日记账 | J5: 核对差异
B6: 月初金额 | C6: 借方发生额 本月汇总 | D6: 贷方发生额 本月汇总 | E6: 月末金额 | F6: 月初金额 | G6: 借方发生额 | H6: 贷方发生额 | I6: 月末金额 | J6: 借方发生额 | K6: 贷方发生额 | L6: 差异分析
A7: 1月 | E7: =ROUND(B7+C7-D7,2) -> 0 | I7: =ROUND(F7+G7-H7,2) -> 0 | J7: =C7-G7 -> 0 | K7: =D7-H7 -> 0
A8: 2月 | B8: =E7 -> 0 | E8: =ROUND(B8+C8-D8,2) -> 0 | F8: =I7 -> 0 | I8: =ROUND(F8+G8-H8,2) -> 0 | J8: =C8-G8 -> 0 | K8: =D8-H8 -> 0
A9: 3月 | B9: =E8 -> 0 | E9: =ROUND(B9+C9-D9,2) -> 0 | F9: =I8 -> 0 | I9: =ROUND(F9+G9-H9,2) -> 0 | J9: =C9-G9 -> 0 | K9: =D9-H9 -> 0
A10: 4月 | B10: =E9 -> 0 | E10: =ROUND(B10+C10-D10,2) -> 0 | F10: =I9 -> 0 | I10: =ROUND(F10+G10-H10,2) -> 0 | J10: =C10-G10 -> 0 | K10: =D10-H10 -> 0
A11: 5月 | B11: =E10 -> 0 | E11: =ROUND(B11+C11-D11,2) -> 0 | F11: =I10 -> 0 | I11: =ROUND(F11+G11-H11,2) -> 0 | J11: =C11-G11 -> 0 | K11: =D11-H11 -> 0
A12: 6月 | B12: =E11 -> 0 | E12: =ROUND(B12+C12-D12,2) -> 0 | F12: =I11 -> 0 | I12: =ROUND(F12+G12-H12,2) -> 0 | J12: =C12-G12 -> 0 | K12: =D12-H12 -> 0
A13: 7月 | B13: =E12 -> 0 | E13: =ROUND(B13+C13-D13,2) -> 0 | F13: =I12 -> 0 | I13: =ROUND(F13+G13-H13,2) -> 0 | J13: =C13-G13 -> 0 | K13: =D13-H13 -> 0
A14: 8月 | B14: =E13 -> 0 | E14: =ROUND(B14+C14-D14,2) -> 0 | F14: =I13 -> 0 | I14: =ROUND(F14+G14-H14,2) -> 0 | J14: =C14-G14 -> 0 | K14: =D14-H14 -> 0
A15: 9月 | B15: =E14 -> 0 | E15: =ROUND(B15+C15-D15,2) -> 0 | F15: =I14 -> 0 | I15: =ROUND(F15+G15-H15,2) -> 0 | J15: =C15-G15 -> 0 | K15: =D15-H15 -> 0
A16: 10月 | B16: =E15 -> 0 | E16: =ROUND(B16+C16-D16,2) -> 0 | F16: =I15 -> 0 | I16: =ROUND(F16+G16-H16,2) -> 0 | J16: =C16-G16 -> 0 | K16: =D16-H16 -> 0
A17: 11月 | B17: =E16 -> 0 | E17: =ROUND(B17+C17-D17,2) -> 0 | F17: =I16 -> 0 | I17: =ROUND(F17+G17-H17,2) -> 0 | J17: =C17-G17 -> 0 | K17: =D17-H17 -> 0
A18: 12月 | B18: =E17 -> 0 | E18: =ROUND(B18+C18-D18,2) -> 0 | F18: =I17 -> 0 | I18: =ROUND(F18+G18-H18,2) -> 0 | J18: =C18-G18 -> 0 | K18: =D18-H18 -> 0
A19: 合计 | B19: =B7 -> 0 | C19: =SUM(C7:C18) -> 0 | D19: =SUM(D7:D18) -> 0 | E19: =ROUND(B19+C19-D19,2) -> 0 | F19: =F7 -> 0 | G19: =SUM(G7:G18) -> 0 | H19: =SUM(H7:H18) -> 0 | I19: =ROUND(F19+G19-H19,2) -> 0 | J19: =SUM(J7:J18) -> 0 | K19: =SUM(K7:K18) -> 0
A20: 核对差异 | G20: =C19-G19 -> 0 | H20: =D19-H19 -> 0

Sheet 流水分析-银行2
A1: 对账单流水与银行日记账流水月度核对分析
A2: =备忘录!$A$1 -> 被审计单位：福禄福擎网络科技有限公司 | E2: 编制人：刘喜琴 | H2: =备忘录!$C$2 -> 日期：2025/10/30
A3: =备忘录!$A$2 -> 财务报表截止日：2025/9/30 | E3: 复核人：赵玮 | H3: =备忘录!$C$3 -> 日期：2025/10/31
A4: 开户行 | D4: 账号
A5: 项目 | B5: 银行对账单 | F5: 银行日记账 | J5: 核对差异
B6: 月初金额 | C6: 借方发生额 本月汇总 | D6: 贷方发生额 本月汇总 | E6: 月末金额 | F6: 月初金额 | G6: 借方发生额 | H6: 贷方发生额 | I6: 月末金额 | J6: 借方发生额 | K6: 贷方发生额 | L6: 差异分析
A7: 1月 | E7: =ROUND(B7+C7-D7,2) -> 0 | I7: =ROUND(F7+G7-H7,2) -> 0 | J7: =C7-G7 -> 0 | K7: =D7-H7 -> 0
A8: 2月 | B8: =E7 -> 0 | E8: =ROUND(B8+C8-D8,2) -> 0 | F8: =I7 -> 0 | I8: =ROUND(F8+G8-H8,2) -> 0 | J8: =C8-G8 -> 0 | K8: =D8-H8 -> 0
A9: 3月 | B9: =E8 -> 0 | E9: =ROUND(B9+C9-D9,2) -> 0 | F9: =I8 -> 0 | I9: =ROUND(F9+G9-H9,2) -> 0 | J9: =C9-G9 -> 0 | K9: =D9-H9 -> 0
A10: 4月 | B10: =E9 -> 0 | E10: =ROUND(B10+C10-D10,2) -> 0 | F10: =I9 -> 0 | I10: =ROUND(F10+G10-H10,2) -> 0 | J10: =C10-G10 -> 0 | K10: =D10-H10 -> 0
A11: 5月 | B11: =E10 -> 0 | E11: =ROUND(B11+C11-D11,2) -> 0 | F11: =I10 -> 0 | I11: =ROUND(F11+G11-H11,2) -> 0 | J11: =C11-G11 -> 0 | K11: =D11-H11 -> 0
A12: 6月 | B12: =E11 -> 0 | E12: =ROUND(B12+C12-D12,2) -> 0 | F12: =I11 -> 0 | I12: =ROUND(F12+G12-H12,2) -> 0 | J12: =C12-G12 -> 0 | K12: =D12-H12 -> 0
A13: 7月 | B13: =E12 -> 0 | E13: =ROUND(B13+C13-D13,2) -> 0 | F13: =I12 -> 0 | I13: =ROUND(F13+G13-H13,2) -> 0 | J13: =C13-G13 -> 0 | K13: =D13-H13 -> 0
A14: 8月 | B14: =E13 -> 0 | E14: =ROUND(B14+C14-D14,2) -> 0 | F14: =I13 -> 0 | I14: =ROUND(F14+G14-H14,2) -> 0 | J14: =C14-G14 -> 0 | K14: =D14-H14 -> 0
A15: 9月 | B15: =E14 -> 0 | E15: =ROUND(B15+C15-D15,2) -> 0 | F15: =I14 -> 0 | I15: =ROUND(F15+G15-H15,2) -> 0 | J15: =C15-G15 -> 0 | K15: =D15-H15 -> 0
A16: 10月 | B16: =E15 -> 0 | E16: =ROUND(B16+C16-D16,2) -> 0 | F16: =I15 -> 0 | I16: =ROUND(F16+G16-H16,2) -> 0 | J16: =C16-G16 -> 0 | K16: =D16-H16 -> 0
A17: 11月 | B17: =E16 -> 0 | E17: =ROUND(B17+C17-D17,2) -> 0 | F17: =I16 -> 0 | I17: =ROUND(F17+G17-H17,2) -> 0 | J17: =C17-G17 -> 0 | K17: =D17-H17 -> 0
A18: 12月 | B18: =E17 -> 0 | E18: =ROUND(B18+C18-D18,2) -> 0 | F18: =I17 -> 0 | I18: =ROUND(F18+G18-H18,2) -> 0 | J18: =C18-G18 -> 0 | K18: =D18-H18 -> 0
A19: 合计 | B19: =B7 -> 0 | C19: =SUM(C7:C18) -> 0 | D19: =SUM(D7:D18) -> 0 | E19: =ROUND(B19+C19-D19,2) -> 0 | F19: =F7 -> 0 | G19: =SUM(G7:G18) -> 0 | H19: =SUM(H7:H18) -> 0 | I19: =ROUND(F19+G19-H19,2) -> 0 | J19: =SUM(J7:J18) -> 0 | K19: =SUM(K7:K18) -> 0
A20: 核对差异 | G20: =C19-G19 -> 0 | H20: =D19-H19 -> 0

Sheet 流水分析-银行3
A1: 对账单流水与银行日记账流水月度核对分析
A2: =备忘录!$A$1 -> 被审计单位：福禄福擎网络科技有限公司 | E2: 编制人：刘喜琴 | H2: =备忘录!$C$2 -> 日期：2025/10/30
A3: =备忘录!$A$2 -> 财务报表截止日：2025/9/30 | E3: 复核人：赵玮 | H3: =备忘录!$C$3 -> 日期：2025/10/31
A4: 开户行 | D4: 账号
A5: 项目 | B5: 银行对账单 | F5: 银行日记账 | J5: 核对差异
B6: 月初金额 | C6: 借方发生额 本月汇总 | D6: 贷方发生额 本月汇总 | E6: 月末金额 | F6: 月初金额 | G6: 借方发生额 | H6: 贷方发生额 | I6: 月末金额 | J6: 借方发生额 | K6: 贷方发生额 | L6: 差异分析
A7: 1月 | E7: =ROUND(B7+C7-D7,2) -> 0 | I7: =ROUND(F7+G7-H7,2) -> 0 | J7: =C7-G7 -> 0 | K7: =D7-H7 -> 0
A8: 2月 | B8: =E7 -> 0 | E8: =ROUND(B8+C8-D8,2) -> 0 | F8: =I7 -> 0 | I8: =ROUND(F8+G8-H8,2) -> 0 | J8: =C8-G8 -> 0 | K8: =D8-H8 -> 0
A9: 3月 | B9: =E8 -> 0 | E9: =ROUND(B9+C9-D9,2) -> 0 | F9: =I8 -> 0 | I9: =ROUND(F9+G9-H9,2) -> 0 | J9: =C9-G9 -> 0 | K9: =D9-H9 -> 0
A10: 4月 | B10: =E9 -> 0 | E10: =ROUND(B10+C10-D10,2) -> 0 | F10: =I9 -> 0 | I10: =ROUND(F10+G10-H10,2) -> 0 | J10: =C10-G10 -> 0 | K10: =D10-H10 -> 0
A11: 5月 | B11: =E10 -> 0 | E11: =ROUND(B11+C11-D11,2) -> 0 | F11: =I10 -> 0 | I11: =ROUND(F11+G11-H11,2) -> 0 | J11: =C11-G11 -> 0 | K11: =D11-H11 -> 0
A12: 6月 | B12: =E11 -> 0 | E12: =ROUND(B12+C12-D12,2) -> 0 | F12: =I11 -> 0 | I12: =ROUND(F12+G12-H12,2) -> 0 | J12: =C12-G12 -> 0 | K12: =D12-H12 -> 0
A13: 7月 | B13: =E12 -> 0 | E13: =ROUND(B13+C13-D13,2) -> 0 | F13: =I12 -> 0 | I13: =ROUND(F13+G13-H13,2) -> 0 | J13: =C13-G13 -> 0 | K13: =D13-H13 -> 0
A14: 8月 | B14: =E13 -> 0 | E14: =ROUND(B14+C14-D14,2) -> 0 | F14: =I13 -> 0 | I14: =ROUND(F14+G14-H14,2) -> 0 | J14: =C14-G14 -> 0 | K14: =D14-H14 -> 0
A15: 9月 | B15: =E14 -> 0 | E15: =ROUND(B15+C15-D15,2) -> 0 | F15: =I14 -> 0 | I15: =ROUND(F15+G15-H15,2) -> 0 | J15: =C15-G15 -> 0 | K15: =D15-H15 -> 0
A16: 10月 | B16: =E15 -> 0 | E16: =ROUND(B16+C16-D16,2) -> 0 | F16: =I15 -> 0 | I16: =ROUND(F16+G16-H16,2) -> 0 | J16: =C16-G16 -> 0 | K16: =D16-H16 -> 0
A17: 11月 | B17: =E16 -> 0 | E17: =ROUND(B17+C17-D17,2) -> 0 | F17: =I16 -> 0 | I17: =ROUND(F17+G17-H17,2) -> 0 | J17: =C17-G17 -> 0 | K17: =D17-H17 -> 0
A18: 12月 | B18: =E17 -> 0 | E18: =ROUND(B18+C18-D18,2) -> 0 | F18: =I17 -> 0 | I18: =ROUND(F18+G18-H18,2) -> 0 | J18: =C18-G18 -> 0 | K18: =D18-H18 -> 0
A19: 合计 | B19: =B7 -> 0 | C19: =SUM(C7:C18) -> 0 | D19: =SUM(D7:D18) -> 0 | E19: =ROUND(B19+C19-D19,2) -> 0 | F19: =F7 -> 0 | G19: =SUM(G7:G18) -> 0 | H19: =SUM(H7:H18) -> 0 | I19: =ROUND(F19+G19-H19,2) -> 0 | J19: =SUM(J7:J18) -> 0 | K19: =SUM(K7:K18) -> 0
A20: 核对差异 | G20: =C19-G19 -> 0 | H20: =D19-H19 -> 0

Sheet 开户清单核对
A1: 银行账户清单与已开立银行结算账户清单核对
A2: =备忘录!$A$1 -> 被审计单位：福禄福擎网络科技有限公司 | E2: 编制人：刘喜琴 | H2: =备忘录!$C$2 -> 日期：2025/10/30
A3: =备忘录!$A$2 -> 财务报表截止日：2025/9/30 | E3: 复核人：赵玮 | H3: =备忘录!$C$3 -> 日期：2025/10/31
A4: 序号 | B4: 企业提供的银行账户实际信息 | G4: 与已开立银行结算账户清单核对 | M4: 是否由被审计单位实际使用 | N4: 备注
B5: 开户银行 | C5: 银行账号 | D5: 币种 | E5: 账户性质 | F5: 账户状态 | G5: 开户银行是否相符 | H5: 银行账号是否相符 | I5: 账户性质是否相符 | J5: 账户状态是否相符 | K5: 销户日期 | L5: 久悬日期
A6: 一、银行存款账户
A7: 1 | B7: =货币资金!B9 -> 0 | C7: =货币资金!C9 -> 0
A8: 2 | B8: =货币资金!B10 -> 0 | C8: =货币资金!C10 -> 0
A9: 3 | B9: =货币资金!B11 -> 0 | C9: =货币资金!C11 -> 0
A10: 4 | B10: =货币资金!B12 -> 0 | C10: =货币资金!C12 -> 0
A11: 5 | B11: =货币资金!B13 -> 0 | C11: =货币资金!C13 -> 0
A12: 6 | B12: =货币资金!B14 -> 0 | C12: =货币资金!C14 -> 0
A13: 7 | B13: =货币资金!B15 -> 0 | C13: =货币资金!C15 -> 0
A14: 8 | B14: =货币资金!B16 -> 0 | C14: =货币资金!C16 -> 0
A15: 9 | B15: =货币资金!B17 -> 0 | C15: =货币资金!C17 -> 0
A16: 二、其他货币资金账户
A17: 1 | B17: =货币资金!B19 -> 0 | C17: =货币资金!C19 -> 0
A18: 2 | B18: =货币资金!B20 -> 0 | C18: =货币资金!C20 -> 0
A19: 3 | B19: =货币资金!B21 -> 0 | C19: =货币资金!C21 -> 0
A20: 4 | B20: =货币资金!B22 -> 0 | C20: =货币资金!C22 -> 0
A21: 5 | B21: =货币资金!B23 -> 0 | C21: =货币资金!C23 -> 0
A22: 6 | B22: =货币资金!B24 -> 0 | C22: =货币资金!C24 -> 0
A23: 7 | B23: =货币资金!B25 -> 0 | C23: =货币资金!C25 -> 0
A24: 8 | B24: =货币资金!B26 -> 0 | C24: =货币资金!C26 -> 0
A25: 9 | B25: =货币资金!B27 -> 0 | C25: =货币资金!C27 -> 0
A26: 10 | B26: =货币资金!B28 -> 0 | C26: =货币资金!C28 -> 0
A27: 11 | B27: =货币资金!B29 -> 0 | C27: =货币资金!C29 -> 0
A28: 12 | B28: =货币资金!B30 -> 0 | C28: =货币资金!C30 -> 0
A30: 审计说明：
A31: 1、被审计单位未提供但开户信息上存在的银行账户情况：
A32: 序号 | B32: 开户银行 | C32: 银行账号 | D32: 币种 | E32: 账户性质 | F32: 账户状态 | G32: 处理意见及依据
A33: 1
A35: 2、被审计单位账户清单上存在但开户信息上不存在的银行账户情况：
A38: 3、开户银行截图：

Sheet 库存商品
A1: 库存商品明细表
A2: =备忘录!$A$1 -> 被审计单位：福禄福擎网络科技有限公司 | F2: 编制人：刘喜琴 | I2: =备忘录!$C$2 -> 日期：2025/10/30
A3: =备忘录!$A$2 -> 财务报表截止日：2025/9/30 | F3: 复核人：赵玮 | I3: =备忘录!$C$3 -> 日期：2025/10/31
A4: 序号 | B4: 科目名称 | C4: 核算项目1 | D4: 核算项目2 | E4: 账面数据 | K4: 审计调整 | L4: 期末审定数 | M4: 备注
E5: 期初金额 | F5: 本期借方 | G5: 本期贷方 | H5: 期末金额 | I5: 企业调整 | J5: 期末报表列报
A6: 一、外购库存商品
A7: 1 | B7: 库存商品_直充 | H7: =E7+F7-G7 -> 0 | J7: =H7+I7 -> 0 | L7: =J7+K7 -> 0
A8: 2 | B8: 库存商品_卡密 | H8: =E8+F8-G8 -> 0 | J8: =H8+I8 -> 0 | L8: =J8+K8 -> 0
A9: 3 | H9: =E9+F9-G9 -> 0 | J9: =H9+I9 -> 0 | L9: =J9+K9 -> 0
A10: 4 | H10: =E10+F10-G10 -> 0 | J10: =H10+I10 -> 0 | L10: =J10+K10 -> 0
A11: 5 | H11: =E11+F11-G11 -> 0 | J11: =H11+I11 -> 0 | L11: =J11+K11 -> 0
A12: 6 | H12: =E12+F12-G12 -> 0 | J12: =H12+I12 -> 0 | L12: =J12+K12 -> 0
A13: 7 | H13: =E13+F13-G13 -> 0 | J13: =H13+I13 -> 0 | L13: =J13+K13 -> 0
A14: 8 | H14: =E14+F14-G14 -> 0 | J14: =H14+I14 -> 0 | L14: =J14+K14 -> 0
A15: 9 | H15: =E15+F15-G15 -> 0 | J15: =H15+I15 -> 0 | L15: =J15+K15 -> 0
A16: 10 | H16: =E16+F16-G16 -> 0 | J16: =H16+I16 -> 0 | L16: =J16+K16 -> 0
A17: 11 | H17: =E17+F17-G17 -> 0 | J17: =H17+I17 -> 0 | L17: =J17+K17 -> 0
A18: 12 | H18: =E18+F18-G18 -> 0 | J18: =H18+I18 -> 0 | L18: =J18+K18 -> 0
A19: 13 | H19: =E19+F19-G19 -> 0 | J19: =H19+I19 -> 0 | L19: =J19+K19 -> 0
A20: 14 | H20: =E20+F20-G20 -> 0 | J20: =H20+I20 -> 0 | L20: =J20+K20 -> 0
A21: 15 | H21: =E21+F21-G21 -> 0 | J21: =H21+I21 -> 0 | L21: =J21+K21 -> 0
A22: 小计 | E22: =SUM(E7:E21) -> 0 | F22: =SUM(F7:F21) -> 0 | G22: =SUM(G7:G21) -> 0 | H22: =SUM(H7:H21) -> 0 | I22: =SUM(I7:I21) -> 0 | J22: =SUM(J7:J21) -> 0 | K22: =SUM(K7:K21) -> 0 | L22: =SUM(L7:L21) -> 0
B24: 审计说明：

Sheet 库存商品分析表
A1: 库存商品月发生额分析表
A2: =备忘录!$A$1 -> 被审计单位：福禄福擎网络科技有限公司 | E2: 编制人：刘喜琴 | H2: =备忘录!$C$2 -> 日期：2025/10/30
A3: =备忘录!$A$2 -> 财务报表截止日：2025/9/30 | E3: 复核人：赵玮 | H3: =备忘录!$C$3 -> 日期：2025/10/31
A4: 月份 | B4: 借方发生额合计 | E4: 贷方发生额 | I4: 期末余额
B5: 完工产品转入 | C5: 外购库存商品 | D5: 借方合计 | E5: 转入主营成本 | F5: 转入发出商品 | G5: 转入应收退货成本 | H5: 贷方小计
A6: 期初余额
A7: 1月 | D7: =SUM(B7:C7) -> 0 | H7: =SUM(E7:G7) -> 0 | I7: =I6+D7-H7 -> 0
A8: 2月 | D8: =SUM(B8:C8) -> 0 | H8: =SUM(E8:G8) -> 0 | I8: =I7+D8-H8 -> 0
A9: 3月 | D9: =SUM(B9:C9) -> 0 | H9: =SUM(E9:G9) -> 0 | I9: =I8+D9-H9 -> 0
A10: 4月 | D10: =SUM(B10:C10) -> 0 | H10: =SUM(E10:G10) -> 0 | I10: =I9+D10-H10 -> 0
A11: 5月 | D11: =SUM(B11:C11) -> 0 | H11: =SUM(E11:G11) -> 0 | I11: =I10+D11-H11 -> 0
A12: 6月 | D12: =SUM(B12:C12) -> 0 | H12: =SUM(E12:G12) -> 0 | I12: =I11+D12-H12 -> 0
A13: 7月 | D13: =SUM(B13:C13) -> 0 | H13: =SUM(E13:G13) -> 0 | I13: =I12+D13-H13 -> 0
A14: 8月 | D14: =SUM(B14:C14) -> 0 | H14: =SUM(E14:G14) -> 0 | I14: =I13+D14-H14 -> 0
A15: 9月 | D15: =SUM(B15:C15) -> 0 | H15: =SUM(E15:G15) -> 0 | I15: =I14+D15-H15 -> 0
A16: 10月 | D16: =SUM(B16:C16) -> 0 | H16: =SUM(E16:G16) -> 0 | I16: =I15+D16-H16 -> 0
A17: 11月 | D17: =SUM(B17:C17) -> 0 | H17: =SUM(E17:G17) -> 0 | I17: =I16+D17-H17 -> 0
A18: 12月 | D18: =SUM(B18:C18) -> 0 | H18: =SUM(E18:G18) -> 0 | I18: =I17+D18-H18 -> 0
A19: 合计 | B19: =SUM(B7:B18) -> 0 | C19: =SUM(C7:C18) -> 0 | D19: =SUM(D7:D18) -> 0 | E19: =SUM(E7:E18) -> 0 | F19: =SUM(F7:F18) -> 0 | G19: =SUM(G7:G18) -> 0 | H19: =SUM(H7:H18) -> 0
B21: 审计说明：

Sheet 固定资产
A1: 固定资产、累计折旧、减值准备明细表
A2: =备忘录!$A$1 -> 被审计单位：福禄福擎网络科技有限公司 | M2: 编制人：刘喜琴 | V2: =备忘录!$C$2 -> 日期：2025/10/30
A3: =备忘录!$A$2 -> 财务报表截止日：2025/9/30 | M3: 复核人：赵玮 | V3: =备忘录!$C$3 -> 日期：2025/10/31
A4: 序号 | B4: 资产名称 | C4: 资产类别 | D4: 取得时间 | E4: 使用年限 | F4: 到期日 | G4: 计量单位 | H4: 期末 数量 | I4: 原值 | M4: 累计折旧 | Q4: 减值准备 | U4: 原值调整 | W4: 累计折旧调整 | Y4: 减值准备调整 | AA4: 审定数 | AE4: 使用状态
I5: 期初原值 | J5: 本期增加 | K5: 本期减少 | L5: 期末原值 | M5: 期初累计折旧 | N5: 本期增加 | O5: 本期减少 | P5: 期末累计折旧 | Q5: 期初减值准备 | R5: 本期增加 | S5: 本期减少 | T5: 期末减值准备 | U5: 本期增加 | V5: 本期减少 | W5: 本期增加 | X5: 本期减少 | Y5: 本期增加 | Z5: 本期减少 | AA5: 原值 | AB5: 累计折旧 | AC5: 减值准备 | AD5: 净值
A6: 1 | F6: =IF(D6="",0,IF(DAY(D6)=1,IF(D6=0,0,DATE(YEAR(D6),MONTH(D6)+E6*12,DAY(D6))),IF(D6=0,0,DATE(YEAR(D6),MONTH(D6)+E6*12,DAY(D6)-1)))) -> 0 | L6: =I6+J6-K6 -> 0 | P6: =M6+N6-O6 -> 0 | T6: =Q6+R6-S6 -> 0 | AA6: =L6+U6-V6 -> 0 | AB6: =P6+W6-X6 -> 0 | AC6: =T6+Y6-Z6 -> 0 | AD6: =ROUND(AA6-AB6-AC6,2) -> 0
A7: 2 | F7: =IF(D7="",0,IF(DAY(D7)=1,IF(D7=0,0,DATE(YEAR(D7),MONTH(D7)+E7*12,DAY(D7))),IF(D7=0,0,DATE(YEAR(D7),MONTH(D7)+E7*12,DAY(D7)-1)))) -> 0 | L7: =I7+J7-K7 -> 0 | P7: =M7+N7-O7 -> 0 | T7: =Q7+R7-S7 -> 0 | AA7: =L7+U7-V7 -> 0 | AB7: =P7+W7-X7 -> 0 | AC7: =T7+Y7-Z7 -> 0 | AD7: =ROUND(AA7-AB7-AC7,2) -> 0
A8: 3 | F8: =IF(D8="",0,IF(DAY(D8)=1,IF(D8=0,0,DATE(YEAR(D8),MONTH(D8)+E8*12,DAY(D8))),IF(D8=0,0,DATE(YEAR(D8),MONTH(D8)+E8*12,DAY(D8)-1)))) -> 0 | L8: =I8+J8-K8 -> 0 | P8: =M8+N8-O8 -> 0 | T8: =Q8+R8-S8 -> 0 | AA8: =L8+U8-V8 -> 0 | AB8: =P8+W8-X8 -> 0 | AC8: =T8+Y8-Z8 -> 0 | AD8: =ROUND(AA8-AB8-AC8,2) -> 0
A9: 4 | F9: =IF(D9="",0,IF(DAY(D9)=1,IF(D9=0,0,DATE(YEAR(D9),MONTH(D9)+E9*12,DAY(D9))),IF(D9=0,0,DATE(YEAR(D9),MONTH(D9)+E9*12,DAY(D9)-1)))) -> 0 | L9: =I9+J9-K9 -> 0 | P9: =M9+N9-O9 -> 0 | T9: =Q9+R9-S9 -> 0 | AA9: =L9+U9-V9 -> 0 | AB9: =P9+W9-X9 -> 0 | AC9: =T9+Y9-Z9 -> 0 | AD9: =ROUND(AA9-AB9-AC9,2) -> 0
A10: 5 | F10: =IF(D10="",0,IF(DAY(D10)=1,IF(D10=0,0,DATE(YEAR(D10),MONTH(D10)+E10*12,DAY(D10))),IF(D10=0,0,DATE(YEAR(D10),MONTH(D10)+E10*12,DAY(D10)-1)))) -> 0 | L10: =I10+J10-K10 -> 0 | P10: =M10+N10-O10 -> 0 | T10: =Q10+R10-S10 -> 0 | AA10: =L10+U10-V10 -> 0 | AB10: =P10+W10-X10 -> 0 | AC10: =T10+Y10-Z10 -> 0 | AD10: =ROUND(AA10-AB10-AC10,2) -> 0
A11: 6 | F11: =IF(D11="",0,IF(DAY(D11)=1,IF(D11=0,0,DATE(YEAR(D11),MONTH(D11)+E11*12,DAY(D11))),IF(D11=0,0,DATE(YEAR(D11),MONTH(D11)+E11*12,DAY(D11)-1)))) -> 0 | L11: =I11+J11-K11 -> 0 | P11: =M11+N11-O11 -> 0 | T11: =Q11+R11-S11 -> 0 | AA11: =L11+U11-V11 -> 0 | AB11: =P11+W11-X11 -> 0 | AC11: =T11+Y11-Z11 -> 0 | AD11: =ROUND(AA11-AB11-AC11,2) -> 0
A12: 7 | F12: =IF(D12="",0,IF(DAY(D12)=1,IF(D12=0,0,DATE(YEAR(D12),MONTH(D12)+E12*12,DAY(D12))),IF(D12=0,0,DATE(YEAR(D12),MONTH(D12)+E12*12,DAY(D12)-1)))) -> 0 | L12: =I12+J12-K12 -> 0 | P12: =M12+N12-O12 -> 0 | T12: =Q12+R12-S12 -> 0 | AA12: =L12+U12-V12 -> 0 | AB12: =P12+W12-X12 -> 0 | AC12: =T12+Y12-Z12 -> 0 | AD12: =ROUND(AA12-AB12-AC12,2) -> 0
A13: 8 | F13: =IF(D13="",0,IF(DAY(D13)=1,IF(D13=0,0,DATE(YEAR(D13),MONTH(D13)+E13*12,DAY(D13))),IF(D13=0,0,DATE(YEAR(D13),MONTH(D13)+E13*12,DAY(D13)-1)))) -> 0 | L13: =I13+J13-K13 -> 0 | P13: =M13+N13-O13 -> 0 | T13: =Q13+R13-S13 -> 0 | AA13: =L13+U13-V13 -> 0 | AB13: =P13+W13-X13 -> 0 | AC13: =T13+Y13-Z13 -> 0 | AD13: =ROUND(AA13-AB13-AC13,2) -> 0
A14: 9 | F14: =IF(D14="",0,IF(DAY(D14)=1,IF(D14=0,0,DATE(YEAR(D14),MONTH(D14)+E14*12,DAY(D14))),IF(D14=0,0,DATE(YEAR(D14),MONTH(D14)+E14*12,DAY(D14)-1)))) -> 0 | L14: =I14+J14-K14 -> 0 | P14: =M14+N14-O14 -> 0 | T14: =Q14+R14-S14 -> 0 | AA14: =L14+U14-V14 -> 0 | AB14: =P14+W14-X14 -> 0 | AC14: =T14+Y14-Z14 -> 0 | AD14: =ROUND(AA14-AB14-AC14,2) -> 0
A15: 10 | F15: =IF(D15="",0,IF(DAY(D15)=1,IF(D15=0,0,DATE(YEAR(D15),MONTH(D15)+E15*12,DAY(D15))),IF(D15=0,0,DATE(YEAR(D15),MONTH(D15)+E15*12,DAY(D15)-1)))) -> 0 | L15: =I15+J15-K15 -> 0 | P15: =M15+N15-O15 -> 0 | T15: =Q15+R15-S15 -> 0 | AA15: =L15+U15-V15 -> 0 | AB15: =P15+W15-X15 -> 0 | AC15: =T15+Y15-Z15 -> 0 | AD15: =ROUND(AA15-AB15-AC15,2) -> 0
A16: 11 | F16: =IF(D16="",0,IF(DAY(D16)=1,IF(D16=0,0,DATE(YEAR(D16),MONTH(D16)+E16*12,DAY(D16))),IF(D16=0,0,DATE(YEAR(D16),MONTH(D16)+E16*12,DAY(D16)-1)))) -> 0 | L16: =I16+J16-K16 -> 0 | P16: =M16+N16-O16 -> 0 | T16: =Q16+R16-S16 -> 0 | AA16: =L16+U16-V16 -> 0 | AB16: =P16+W16-X16 -> 0 | AC16: =T16+Y16-Z16 -> 0 | AD16: =ROUND(AA16-AB16-AC16,2) -> 0
A17: 12 | F17: =IF(D17="",0,IF(DAY(D17)=1,IF(D17=0,0,DATE(YEAR(D17),MONTH(D17)+E17*12,DAY(D17))),IF(D17=0,0,DATE(YEAR(D17),MONTH(D17)+E17*12,DAY(D17)-1)))) -> 0 | L17: =I17+J17-K17 -> 0 | P17: =M17+N17-O17 -> 0 | T17: =Q17+R17-S17 -> 0 | AA17: =L17+U17-V17 -> 0 | AB17: =P17+W17-X17 -> 0 | AC17: =T17+Y17-Z17 -> 0 | AD17: =ROUND(AA17-AB17-AC17,2) -> 0
... A34: 29 | F34: =IF(D34="",0,IF(DAY(D34)=1,IF(D34=0,0,DATE(YEAR(D34),MONTH(D34)+E34*12,DAY(D34))),IF(D34=0,0,DATE(YEAR(D34),MONTH(D34)+E34*12,DAY(D34)-1)))) -> 0 | L34: =I34+J34-K34 -> 0 | P34: =M34+N34-O34 -> 0 | T34: =Q34+R34-S34 -> 0 | AA34: =L34+U34-V34 -> 0 | AB34: =P34+W34-X34 -> 0 | AC34: =T34+Y34-Z34 -> 0 | AD34: =ROUND(AA34-AB34-AC34,2) -> 0
A35: 合计 | I35: =ROUND(SUM(I6:I34),2) -> 0 | J35: =ROUND(SUM(J6:J34),2) -> 0 | K35: =ROUND(SUM(K6:K34),2) -> 0 | L35: =ROUND(SUM(L6:L34),2) -> 0 | M35: =ROUND(SUM(M6:M34),2) -> 0 | N35: =ROUND(SUM(N6:N34),2) -> 0 | O35: =ROUND(SUM(O6:O34),2) -> 0 | P35: =ROUND(SUM(P6:P34),2) -> 0 | ... AD35: =ROUND(SUM(AD6:AD34),2) -> 0
B37: 审计说明：

Sheet 固定资产测算表
A1: 固定资产折旧测算（未计提减值情况下适用）
A2: =备忘录!$A$1 -> 被审计单位：福禄福擎网络科技有限公司 | H2: 编制人：刘喜琴 | N2: =备忘录!$C$2 -> 日期：2025/10/30
A3: =备忘录!$A$2 -> 财务报表截止日：2025/9/30 | H3: 复核人：赵玮 | N3: =备忘录!$C$3 -> 日期：2025/10/31
A4: 期初日期 | C4: 45658 | D4: 期末日期 | E4: 45930
A5: 序号 | B5: 资产名称 | C5: 类别名称 | D5: 管理部门 | E5: 审定原值 | F5: 未审 累计折旧 | G5: 开始使用 日期 | H5: 使用年限 | I5: 残值率 | J5: 固定资产卡片记录的年折旧额 | K5: 使用月限 | L5: 测算到期日 | M5: 已提折旧月份 | N5: 本期折 旧月份 | O5: 测算月折旧 | P5: 测算当期折旧费用 | Q5: 当期折旧额与固定资产卡片核对差异 | R5: 累计折旧费用 | S5: 累计折旧额差异
A6: 1 | B6: =固定资产!B6 -> 0 | C6: =固定资产!C6 -> 0 | E6: =固定资产!AA6 -> 0 | F6: =固定资产!P6 -> 0 | G6: =固定资产!D6 -> 0 | H6: =固定资产!E6 -> 0 | K6: =IF(H6=0,0,IF(RIGHT(H6,1)<>"年",H6*12,IF(LEN(H6)=3,VALUE(LEFT(H6,2))*12,IF(LEN(H6)=2,VALUE(LEFT(H6,1))*12,"??")))) -> 0 | L6: =IF(DAY(G6)=1,IF(G6=0,0,DATE(YEAR(G6),MONTH(G6)+K6,DAY(G6))),IF(G6=0,0,DATE(YEAR(G6),MONTH(G6)+K6,DAY(G6)-1))) -> 0 | M6: =MIN(IF(AND(DAY($E$4)=30,DAY(G6)=31),IF(OR(G6=0,G6=$E$4),0,IF(L6>$E$4,VALUE(DATEDIF(G6,MIN($E$4,L6),"m"))+1,VALUE(DATEDIF(G6,MIN($E$4,L6),"m")+2))),IF(OR(G6=0,G6=$E$4),0,IF(L6>$E$4,DATEDIF(G6,MIN($E$4,L6),"m"),VALUE(DATEDIF(G6,MIN($E$4,L6),"m")+1)))),K6) -> 0 | N6: =IF(AND(YEAR(G6)=YEAR($E$4),DAY($E$4)=30,DAY(G6)=31),IF(OR(G6=0,L6<$C$4),0,IF(AND(G6<$C$4,L6>$E$4),VALUE(DATEDIF($C$4,$E$4,"m")+2),IF(AND(G6<$C$4,L6<=$E$4),VALUE(DATEDIF($C$4,L6,"m")+2),IF(AND(G6>=$C$4,L6>$E$4),VALUE(DATEDIF(G6,$E$4,"m")+1),IF(AND(G6>=$C$4,L6<=$E$4),VALUE(DATEDIF(G6,L6,"m")+2),))))),IF(OR(G6=0,L6<$C$4),0,IF(AND(G6<$C$4,L6>$E$4),VALUE(DATEDIF($C$4,$E$4,"m")+1),IF(AND(G6<$C$4,L6<=$E$4),VALUE(DATEDIF($C$4,L6,"m")+1),IF(AND(G6>=$C$4,L6>$E$4),VALUE(DATEDIF(G6,$E$4,"m")),IF(AND(G6>=$C$4,L6<=$E$4),VALUE(DATEDIF(G6,L6,"m")+1),)))))) -> 0 | O6: =IF(K6=0,0,ROUND(((1-I6)/K6)*E6,4)) -> 0 | P6: =ROUND(O6*N6,2) -> 0 | Q6: =IF(J6="","",ROUND(J6-P6,2)) | R6: =ROUND(O6*M6,2) -> 0 | S6: =ROUND(F6-R6,2) -> 0
A7: 2 | B7: =固定资产!B7 -> 0 | C7: =固定资产!C7 -> 0 | E7: =固定资产!AA7 -> 0 | F7: =固定资产!P7 -> 0 | G7: =固定资产!D7 -> 0 | H7: =固定资产!E7 -> 0 | K7: =IF(H7=0,0,IF(RIGHT(H7,1)<>"年",H7*12,IF(LEN(H7)=3,VALUE(LEFT(H7,2))*12,IF(LEN(H7)=2,VALUE(LEFT(H7,1))*12,"??")))) -> 0 | L7: =IF(DAY(G7)=1,IF(G7=0,0,DATE(YEAR(G7),MONTH(G7)+K7,DAY(G7))),IF(G7=0,0,DATE(YEAR(G7),MONTH(G7)+K7,DAY(G7)-1))) -> 0 | M7: =MIN(IF(AND(DAY($E$4)=30,DAY(G7)=31),IF(OR(G7=0,G7=$E$4),0,IF(L7>$E$4,VALUE(DATEDIF(G7,MIN($E$4,L7),"m"))+1,VALUE(DATEDIF(G7,MIN($E$4,L7),"m")+2))),IF(OR(G7=0,G7=$E$4),0,IF(L7>$E$4,DATEDIF(G7,MIN($E$4,L7),"m"),VALUE(DATEDIF(G7,MIN($E$4,L7),"m")+1)))),K7) -> 0 | N7: =IF(AND(YEAR(G7)=YEAR($E$4),DAY($E$4)=30,DAY(G7)=31),IF(OR(G7=0,L7<$C$4),0,IF(AND(G7<$C$4,L7>$E$4),VALUE(DATEDIF($C$4,$E$4,"m")+2),IF(AND(G7<$C$4,L7<=$E$4),VALUE(DATEDIF($C$4,L7,"m")+2),IF(AND(G7>=$C$4,L7>$E$4),VALUE(DATEDIF(G7,$E$4,"m")+1),IF(AND(G7>=$C$4,L7<=$E$4),VALUE(DATEDIF(G7,L7,"m")+2),))))),IF(OR(G7=0,L7<$C$4),0,IF(AND(G7<$C$4,L7>$E$4),VALUE(DATEDIF($C$4,$E$4,"m")+1),IF(AND(G7<$C$4,L7<=$E$4),VALUE(DATEDIF($C$4,L7,"m")+1),IF(AND(G7>=$C$4,L7>$E$4),VALUE(DATEDIF(G7,$E$4,"m")),IF(AND(G7>=$C$4,L7<=$E$4),VALUE(DATEDIF(G7,L7,"m")+1),)))))) -> 0 | O7: =IF(K7=0,0,ROUND(((1-I7)/K7)*E7,4)) -> 0 | P7: =ROUND(O7*N7,2) -> 0 | Q7: =IF(J7="","",ROUND(J7-P7,2)) | R7: =ROUND(O7*M7,2) -> 0 | S7: =ROUND(F7-R7,2) -> 0
A8: 3 | B8: =固定资产!B8 -> 0 | C8: =固定资产!C8 -> 0 | E8: =固定资产!AA8 -> 0 | F8: =固定资产!P8 -> 0 | G8: =固定资产!D8 -> 0 | H8: =固定资产!E8 -> 0 | K8: =IF(H8=0,0,IF(RIGHT(H8,1)<>"年",H8*12,IF(LEN(H8)=3,VALUE(LEFT(H8,2))*12,IF(LEN(H8)=2,VALUE(LEFT(H8,1))*12,"??")))) -> 0 | L8: =IF(DAY(G8)=1,IF(G8=0,0,DATE(YEAR(G8),MONTH(G8)+K8,DAY(G8))),IF(G8=0,0,DATE(YEAR(G8),MONTH(G8)+K8,DAY(G8)-1))) -> 0 | M8: =MIN(IF(AND(DAY($E$4)=30,DAY(G8)=31),IF(OR(G8=0,G8=$E$4),0,IF(L8>$E$4,VALUE(DATEDIF(G8,MIN($E$4,L8),"m"))+1,VALUE(DATEDIF(G8,MIN($E$4,L8),"m")+2))),IF(OR(G8=0,G8=$E$4),0,IF(L8>$E$4,DATEDIF(G8,MIN($E$4,L8),"m"),VALUE(DATEDIF(G8,MIN($E$4,L8),"m")+1)))),K8) -> 0 | N8: =IF(AND(YEAR(G8)=YEAR($E$4),DAY($E$4)=30,DAY(G8)=31),IF(OR(G8=0,L8<$C$4),0,IF(AND(G8<$C$4,L8>$E$4),VALUE(DATEDIF($C$4,$E$4,"m")+2),IF(AND(G8<$C$4,L8<=$E$4),VALUE(DATEDIF($C$4,L8,"m")+2),IF(AND(G8>=$C$4,L8>$E$4),VALUE(DATEDIF(G8,$E$4,"m")+1),IF(AND(G8>=$C$4,L8<=$E$4),VALUE(DATEDIF(G8,L8,"m")+2),))))),IF(OR(G8=0,L8<$C$4),0,IF(AND(G8<$C$4,L8>$E$4),VALUE(DATEDIF($C$4,$E$4,"m")+1),IF(AND(G8<$C$4,L8<=$E$4),VALUE(DATEDIF($C$4,L8,"m")+1),IF(AND(G8>=$C$4,L8>$E$4),VALUE(DATEDIF(G8,$E$4,"m")),IF(AND(G8>=$C$4,L8<=$E$4),VALUE(DATEDIF(G8,L8,"m")+1),)))))) -> 0 | O8: =IF(K8=0,0,ROUND(((1-I8)/K8)*E8,4)) -> 0 | P8: =ROUND(O8*N8,2) -> 0 | Q8: =IF(J8="","",ROUND(J8-P8,2)) | R8: =ROUND(O8*M8,2) -> 0 | S8: =ROUND(F8-R8,2) -> 0
A9: 4 | B9: =固定资产!B9 -> 0 | C9: =固定资产!C9 -> 0 | E9: =固定资产!AA9 -> 0 | F9: =固定资产!P9 -> 0 | G9: =固定资产!D9 -> 0 | H9: =固定资产!E9 -> 0 | K9: =IF(H9=0,0,IF(RIGHT(H9,1)<>"年",H9*12,IF(LEN(H9)=3,VALUE(LEFT(H9,2))*12,IF(LEN(H9)=2,VALUE(LEFT(H9,1))*12,"??")))) -> 0 | L9: =IF(DAY(G9)=1,IF(G9=0,0,DATE(YEAR(G9),MONTH(G9)+K9,DAY(G9))),IF(G9=0,0,DATE(YEAR(G9),MONTH(G9)+K9,DAY(G9)-1))) -> 0 | M9: =MIN(IF(AND(DAY($E$4)=30,DAY(G9)=31),IF(OR(G9=0,G9=$E$4),0,IF(L9>$E$4,VALUE(DATEDIF(G9,MIN($E$4,L9),"m"))+1,VALUE(DATEDIF(G9,MIN($E$4,L9),"m")+2))),IF(OR(G9=0,G9=$E$4),0,IF(L9>$E$4,DATEDIF(G9,MIN($E$4,L9),"m"),VALUE(DATEDIF(G9,MIN($E$4,L9),"m")+1)))),K9) -> 0 | N9: =IF(AND(YEAR(G9)=YEAR($E$4),DAY($E$4)=30,DAY(G9)=31),IF(OR(G9=0,L9<$C$4),0,IF(AND(G9<$C$4,L9>$E$4),VALUE(DATEDIF($C$4,$E$4,"m")+2),IF(AND(G9<$C$4,L9<=$E$4),VALUE(DATEDIF($C$4,L9,"m")+2),IF(AND(G9>=$C$4,L9>$E$4),VALUE(DATEDIF(G9,$E$4,"m")+1),IF(AND(G9>=$C$4,L9<=$E$4),VALUE(DATEDIF(G9,L9,"m")+2),))))),IF(OR(G9=0,L9<$C$4),0,IF(AND(G9<$C$4,L9>$E$4),VALUE(DATEDIF($C$4,$E$4,"m")+1),IF(AND(G9<$C$4,L9<=$E$4),VALUE(DATEDIF($C$4,L9,"m")+1),IF(AND(G9>=$C$4,L9>$E$4),VALUE(DATEDIF(G9,$E$4,"m")),IF(AND(G9>=$C$4,L9<=$E$4),VALUE(DATEDIF(G9,L9,"m")+1),)))))) -> 0 | O9: =IF(K9=0,0,ROUND(((1-I9)/K9)*E9,4)) -> 0 | P9: =ROUND(O9*N9,2) -> 0 | Q9: =IF(J9="","",ROUND(J9-P9,2)) | R9: =ROUND(O9*M9,2) -> 0 | S9: =ROUND(F9-R9,2) -> 0
A10: 5 | B10: =固定资产!B10 -> 0 | C10: =固定资产!C10 -> 0 | E10: =固定资产!AA10 -> 0 | F10: =固定资产!P10 -> 0 | G10: =固定资产!D10 -> 0 | H10: =固定资产!E10 -> 0 | K10: =IF(H10=0,0,IF(RIGHT(H10,1)<>"年",H10*12,IF(LEN(H10)=3,VALUE(LEFT(H10,2))*12,IF(LEN(H10)=2,VALUE(LEFT(H10,1))*12,"??")))) -> 0 | L10: =IF(DAY(G10)=1,IF(G10=0,0,DATE(YEAR(G10),MONTH(G10)+K10,DAY(G10))),IF(G10=0,0,DATE(YEAR(G10),MONTH(G10)+K10,DAY(G10)-1))) -> 0 | M10: =MIN(IF(AND(DAY($E$4)=30,DAY(G10)=31),IF(OR(G10=0,G10=$E$4),0,IF(L10>$E$4,VALUE(DATEDIF(G10,MIN($E$4,L10),"m"))+1,VALUE(DATEDIF(G10,MIN($E$4,L10),"m")+2))),IF(OR(G10=0,G10=$E$4),0,IF(L10>$E$4,DATEDIF(G10,MIN($E$4,L10),"m"),VALUE(DATEDIF(G10,MIN($E$4,L10),"m")+1)))),K10) -> 0 | N10: =IF(AND(YEAR(G10)=YEAR($E$4),DAY($E$4)=30,DAY(G10)=31),IF(OR(G10=0,L10<$C$4),0,IF(AND(G10<$C$4,L10>$E$4),VALUE(DATEDIF($C$4,$E$4,"m")+2),IF(AND(G10<$C$4,L10<=$E$4),VALUE(DATEDIF($C$4,L10,"m")+2),IF(AND(G10>=$C$4,L10>$E$4),VALUE(DATEDIF(G10,$E$4,"m")+1),IF(AND(G10>=$C$4,L10<=$E$4),VALUE(DATEDIF(G10,L10,"m")+2),))))),IF(OR(G10=0,L10<$C$4),0,IF(AND(G10<$C$4,L10>$E$4),VALUE(DATEDIF($C$4,$E$4,"m")+1),IF(AND(G10<$C$4,L10<=$E$4),VALUE(DATEDIF($C$4,L10,"m")+1),IF(AND(G10>=$C$4,L10>$E$4),VALUE(DATEDIF(G10,$E$4,"m")),IF(AND(G10>=$C$4,L10<=$E$4),VALUE(DATEDIF(G10,L10,"m")+1),)))))) -> 0 | O10: =IF(K10=0,0,ROUND(((1-I10)/K10)*E10,4)) -> 0 | P10: =ROUND(O10*N10,2) -> 0 | Q10: =IF(J10="","",ROUND(J10-P10,2)) | R10: =ROUND(O10*M10,2) -> 0 | S10: =ROUND(F10-R10,2) -> 0
A11: 6 | B11: =固定资产!B11 -> 0 | C11: =固定资产!C11 -> 0 | E11: =固定资产!AA11 -> 0 | F11: =固定资产!P11 -> 0 | G11: =固定资产!D11 -> 0 | H11: =固定资产!E11 -> 0 | K11: =IF(H11=0,0,IF(RIGHT(H11,1)<>"年",H11*12,IF(LEN(H11)=3,VALUE(LEFT(H11,2))*12,IF(LEN(H11)=2,VALUE(LEFT(H11,1))*12,"??")))) -> 0 | L11: =IF(DAY(G11)=1,IF(G11=0,0,DATE(YEAR(G11),MONTH(G11)+K11,DAY(G11))),IF(G11=0,0,DATE(YEAR(G11),MONTH(G11)+K11,DAY(G11)-1))) -> 0 | M11: =MIN(IF(AND(DAY($E$4)=30,DAY(G11)=31),IF(OR(G11=0,G11=$E$4),0,IF(L11>$E$4,VALUE(DATEDIF(G11,MIN($E$4,L11),"m"))+1,VALUE(DATEDIF(G11,MIN($E$4,L11),"m")+2))),IF(OR(G11=0,G11=$E$4),0,IF(L11>$E$4,DATEDIF(G11,MIN($E$4,L11),"m"),VALUE(DATEDIF(G11,MIN($E$4,L11),"m")+1)))),K11) -> 0 | N11: =IF(AND(YEAR(G11)=YEAR($E$4),DAY($E$4)=30,DAY(G11)=31),IF(OR(G11=0,L11<$C$4),0,IF(AND(G11<$C$4,L11>$E$4),VALUE(DATEDIF($C$4,$E$4,"m")+2),IF(AND(G11<$C$4,L11<=$E$4),VALUE(DATEDIF($C$4,L11,"m")+2),IF(AND(G11>=$C$4,L11>$E$4),VALUE(DATEDIF(G11,$E$4,"m")+1),IF(AND(G11>=$C$4,L11<=$E$4),VALUE(DATEDIF(G11,L11,"m")+2),))))),IF(OR(G11=0,L11<$C$4),0,IF(AND(G11<$C$4,L11>$E$4),VALUE(DATEDIF($C$4,$E$4,"m")+1),IF(AND(G11<$C$4,L11<=$E$4),VALUE(DATEDIF($C$4,L11,"m")+1),IF(AND(G11>=$C$4,L11>$E$4),VALUE(DATEDIF(G11,$E$4,"m")),IF(AND(G11>=$C$4,L11<=$E$4),VALUE(DATEDIF(G11,L11,"m")+1),)))))) -> 0 | O11: =IF(K11=0,0,ROUND(((1-I11)/K11)*E11,4)) -> 0 | P11: =ROUND(O11*N11,2) -> 0 | Q11: =IF(J11="","",ROUND(J11-P11,2)) | R11: =ROUND(O11*M11,2) -> 0 | S11: =ROUND(F11-R11,2) -> 0
A12: 7 | B12: =固定资产!B12 -> 0 | C12: =固定资产!C12 -> 0 | E12: =固定资产!AA12 -> 0 | F12: =固定资产!P12 -> 0 | G12: =固定资产!D12 -> 0 | H12: =固定资产!E12 -> 0 | K12: =IF(H12=0,0,IF(RIGHT(H12,1)<>"年",H12*12,IF(LEN(H12)=3,VALUE(LEFT(H12,2))*12,IF(LEN(H12)=2,VALUE(LEFT(H12,1))*12,"??")))) -> 0 | L12: =IF(DAY(G12)=1,IF(G12=0,0,DATE(YEAR(G12),MONTH(G12)+K12,DAY(G12))),IF(G12=0,0,DATE(YEAR(G12),MONTH(G12)+K12,DAY(G12)-1))) -> 0 | M12: =MIN(IF(AND(DAY($E$4)=30,DAY(G12)=31),IF(OR(G12=0,G12=$E$4),0,IF(L12>$E$4,VALUE(DATEDIF(G12,MIN($E$4,L12),"m"))+1,VALUE(DATEDIF(G12,MIN($E$4,L12),"m")+2))),IF(OR(G12=0,G12=$E$4),0,IF(L12>$E$4,DATEDIF(G12,MIN($E$4,L12),"m"),VALUE(DATEDIF(G12,MIN($E$4,L12),"m")+1)))),K12) -> 0 | N12: =IF(AND(YEAR(G12)=YEAR($E$4),DAY($E$4)=30,DAY(G12)=31),IF(OR(G12=0,L12<$C$4),0,IF(AND(G12<$C$4,L12>$E$4),VALUE(DATEDIF($C$4,$E$4,"m")+2),IF(AND(G12<$C$4,L12<=$E$4),VALUE(DATEDIF($C$4,L12,"m")+2),IF(AND(G12>=$C$4,L12>$E$4),VALUE(DATEDIF(G12,$E$4,"m")+1),IF(AND(G12>=$C$4,L12<=$E$4),VALUE(DATEDIF(G12,L12,"m")+2),))))),IF(OR(G12=0,L12<$C$4),0,IF(AND(G12<$C$4,L12>$E$4),VALUE(DATEDIF($C$4,$E$4,"m")+1),IF(AND(G12<$C$4,L12<=$E$4),VALUE(DATEDIF($C$4,L12,"m")+1),IF(AND(G12>=$C$4,L12>$E$4),VALUE(DATEDIF(G12,$E$4,"m")),IF(AND(G12>=$C$4,L12<=$E$4),VALUE(DATEDIF(G12,L12,"m")+1),)))))) -> 0 | O12: =IF(K12=0,0,ROUND(((1-I12)/K12)*E12,4)) -> 0 | P12: =ROUND(O12*N12,2) -> 0 | Q12: =IF(J12="","",ROUND(J12-P12,2)) | R12: =ROUND(O12*M12,2) -> 0 | S12: =ROUND(F12-R12,2) -> 0
A13: 8 | B13: =固定资产!B13 -> 0 | C13: =固定资产!C13 -> 0 | E13: =固定资产!AA13 -> 0 | F13: =固定资产!P13 -> 0 | G13: =固定资产!D13 -> 0 | H13: =固定资产!E13 -> 0 | K13: =IF(H13=0,0,IF(RIGHT(H13,1)<>"年",H13*12,IF(LEN(H13)=3,VALUE(LEFT(H13,2))*12,IF(LEN(H13)=2,VALUE(LEFT(H13,1))*12,"??")))) -> 0 | L13: =IF(DAY(G13)=1,IF(G13=0,0,DATE(YEAR(G13),MONTH(G13)+K13,DAY(G13))),IF(G13=0,0,DATE(YEAR(G13),MONTH(G13)+K13,DAY(G13)-1))) -> 0 | M13: =MIN(IF(AND(DAY($E$4)=30,DAY(G13)=31),IF(OR(G13=0,G13=$E$4),0,IF(L13>$E$4,VALUE(DATEDIF(G13,MIN($E$4,L13),"m"))+1,VALUE(DATEDIF(G13,MIN($E$4,L13),"m")+2))),IF(OR(G13=0,G13=$E$4),0,IF(L13>$E$4,DATEDIF(G13,MIN($E$4,L13),"m"),VALUE(DATEDIF(G13,MIN($E$4,L13),"m")+1)))),K13) -> 0 | N13: =IF(AND(YEAR(G13)=YEAR($E$4),DAY($E$4)=30,DAY(G13)=31),IF(OR(G13=0,L13<$C$4),0,IF(AND(G13<$C$4,L13>$E$4),VALUE(DATEDIF($C$4,$E$4,"m")+2),IF(AND(G13<$C$4,L13<=$E$4),VALUE(DATEDIF($C$4,L13,"m")+2),IF(AND(G13>=$C$4,L13>$E$4),VALUE(DATEDIF(G13,$E$4,"m")+1),IF(AND(G13>=$C$4,L13<=$E$4),VALUE(DATEDIF(G13,L13,"m")+2),))))),IF(OR(G13=0,L13<$C$4),0,IF(AND(G13<$C$4,L13>$E$4),VALUE(DATEDIF($C$4,$E$4,"m")+1),IF(AND(G13<$C$4,L13<=$E$4),VALUE(DATEDIF($C$4,L13,"m")+1),IF(AND(G13>=$C$4,L13>$E$4),VALUE(DATEDIF(G13,$E$4,"m")),IF(AND(G13>=$C$4,L13<=$E$4),VALUE(DATEDIF(G13,L13,"m")+1),)))))) -> 0 | O13: =IF(K13=0,0,ROUND(((1-I13)/K13)*E13,4)) -> 0 | P13: =ROUND(O13*N13,2) -> 0 | Q13: =IF(J13="","",ROUND(J13-P13,2)) | R13: =ROUND(O13*M13,2) -> 0 | S13: =ROUND(F13-R13,2) -> 0
A14: 9 | B14: =固定资产!B14 -> 0 | C14: =固定资产!C14 -> 0 | E14: =固定资产!AA14 -> 0 | F14: =固定资产!P14 -> 0 | G14: =固定资产!D14 -> 0 | H14: =固定资产!E14 -> 0 | K14: =IF(H14=0,0,IF(RIGHT(H14,1)<>"年",H14*12,IF(LEN(H14)=3,VALUE(LEFT(H14,2))*12,IF(LEN(H14)=2,VALUE(LEFT(H14,1))*12,"??")))) -> 0 | L14: =IF(DAY(G14)=1,IF(G14=0,0,DATE(YEAR(G14),MONTH(G14)+K14,DAY(G14))),IF(G14=0,0,DATE(YEAR(G14),MONTH(G14)+K14,DAY(G14)-1))) -> 0 | M14: =MIN(IF(AND(DAY($E$4)=30,DAY(G14)=31),IF(OR(G14=0,G14=$E$4),0,IF(L14>$E$4,VALUE(DATEDIF(G14,MIN($E$4,L14),"m"))+1,VALUE(DATEDIF(G14,MIN($E$4,L14),"m")+2))),IF(OR(G14=0,G14=$E$4),0,IF(L14>$E$4,DATEDIF(G14,MIN($E$4,L14),"m"),VALUE(DATEDIF(G14,MIN($E$4,L14),"m")+1)))),K14) -> 0 | N14: =IF(AND(YEAR(G14)=YEAR($E$4),DAY($E$4)=30,DAY(G14)=31),IF(OR(G14=0,L14<$C$4),0,IF(AND(G14<$C$4,L14>$E$4),VALUE(DATEDIF($C$4,$E$4,"m")+2),IF(AND(G14<$C$4,L14<=$E$4),VALUE(DATEDIF($C$4,L14,"m")+2),IF(AND(G14>=$C$4,L14>$E$4),VALUE(DATEDIF(G14,$E$4,"m")+1),IF(AND(G14>=$C$4,L14<=$E$4),VALUE(DATEDIF(G14,L14,"m")+2),))))),IF(OR(G14=0,L14<$C$4),0,IF(AND(G14<$C$4,L14>$E$4),VALUE(DATEDIF($C$4,$E$4,"m")+1),IF(AND(G14<$C$4,L14<=$E$4),VALUE(DATEDIF($C$4,L14,"m")+1),IF(AND(G14>=$C$4,L14>$E$4),VALUE(DATEDIF(G14,$E$4,"m")),IF(AND(G14>=$C$4,L14<=$E$4),VALUE(DATEDIF(G14,L14,"m")+1),)))))) -> 0 | O14: =IF(K14=0,0,ROUND(((1-I14)/K14)*E14,4)) -> 0 | P14: =ROUND(O14*N14,2) -> 0 | Q14: =IF(J14="","",ROUND(J14-P14,2)) | R14: =ROUND(O14*M14,2) -> 0 | S14: =ROUND(F14-R14,2) -> 0
A15: 10 | B15: =固定资产!B15 -> 0 | C15: =固定资产!C15 -> 0 | E15: =固定资产!AA15 -> 0 | F15: =固定资产!P15 -> 0 | G15: =固定资产!D15 -> 0 | H15: =固定资产!E15 -> 0 | K15: =IF(H15=0,0,IF(RIGHT(H15,1)<>"年",H15*12,IF(LEN(H15)=3,VALUE(LEFT(H15,2))*12,IF(LEN(H15)=2,VALUE(LEFT(H15,1))*12,"??")))) -> 0 | L15: =IF(DAY(G15)=1,IF(G15=0,0,DATE(YEAR(G15),MONTH(G15)+K15,DAY(G15))),IF(G15=0,0,DATE(YEAR(G15),MONTH(G15)+K15,DAY(G15)-1))) -> 0 | M15: =MIN(IF(AND(DAY($E$4)=30,DAY(G15)=31),IF(OR(G15=0,G15=$E$4),0,IF(L15>$E$4,VALUE(DATEDIF(G15,MIN($E$4,L15),"m"))+1,VALUE(DATEDIF(G15,MIN($E$4,L15),"m")+2))),IF(OR(G15=0,G15=$E$4),0,IF(L15>$E$4,DATEDIF(G15,MIN($E$4,L15),"m"),VALUE(DATEDIF(G15,MIN($E$4,L15),"m")+1)))),K15) -> 0 | N15: =IF(AND(YEAR(G15)=YEAR($E$4),DAY($E$4)=30,DAY(G15)=31),IF(OR(G15=0,L15<$C$4),0,IF(AND(G15<$C$4,L15>$E$4),VALUE(DATEDIF($C$4,$E$4,"m")+2),IF(AND(G15<$C$4,L15<=$E$4),VALUE(DATEDIF($C$4,L15,"m")+2),IF(AND(G15>=$C$4,L15>$E$4),VALUE(DATEDIF(G15,$E$4,"m")+1),IF(AND(G15>=$C$4,L15<=$E$4),VALUE(DATEDIF(G15,L15,"m")+2),))))),IF(OR(G15=0,L15<$C$4),0,IF(AND(G15<$C$4,L15>$E$4),VALUE(DATEDIF($C$4,$E$4,"m")+1),IF(AND(G15<$C$4,L15<=$E$4),VALUE(DATEDIF($C$4,L15,"m")+1),IF(AND(G15>=$C$4,L15>$E$4),VALUE(DATEDIF(G15,$E$4,"m")),IF(AND(G15>=$C$4,L15<=$E$4),VALUE(DATEDIF(G15,L15,"m")+1),)))))) -> 0 | O15: =IF(K15=0,0,ROUND(((1-I15)/K15)*E15,4)) -> 0 | P15: =ROUND(O15*N15,2) -> 0 | Q15: =IF(J15="","",ROUND(J15-P15,2)) | R15: =ROUND(O15*M15,2) -> 0 | S15: =ROUND(F15-R15,2) -> 0
A16: 11 | B16: =固定资产!B16 -> 0 | C16: =固定资产!C16 -> 0 | E16: =固定资产!AA16 -> 0 | F16: =固定资产!P16 -> 0 | G16: =固定资产!D16 -> 0 | H16: =固定资产!E16 -> 0 | K16: =IF(H16=0,0,IF(RIGHT(H16,1)<>"年",H16*12,IF(LEN(H16)=3,VALUE(LEFT(H16,2))*12,IF(LEN(H16)=2,VALUE(LEFT(H16,1))*12,"??")))) -> 0 | L16: =IF(DAY(G16)=1,IF(G16=0,0,DATE(YEAR(G16),MONTH(G16)+K16,DAY(G16))),IF(G16=0,0,DATE(YEAR(G16),MONTH(G16)+K16,DAY(G16)-1))) -> 0 | M16: =MIN(IF(AND(DAY($E$4)=30,DAY(G16)=31),IF(OR(G16=0,G16=$E$4),0,IF(L16>$E$4,VALUE(DATEDIF(G16,MIN($E$4,L16),"m"))+1,VALUE(DATEDIF(G16,MIN($E$4,L16),"m")+2))),IF(OR(G16=0,G16=$E$4),0,IF(L16>$E$4,DATEDIF(G16,MIN($E$4,L16),"m"),VALUE(DATEDIF(G16,MIN($E$4,L16),"m")+1)))),K16) -> 0 | N16: =IF(AND(YEAR(G16)=YEAR($E$4),DAY($E$4)=30,DAY(G16)=31),IF(OR(G16=0,L16<$C$4),0,IF(AND(G16<$C$4,L16>$E$4),VALUE(DATEDIF($C$4,$E$4,"m")+2),IF(AND(G16<$C$4,L16<=$E$4),VALUE(DATEDIF($C$4,L16,"m")+2),IF(AND(G16>=$C$4,L16>$E$4),VALUE(DATEDIF(G16,$E$4,"m")+1),IF(AND(G16>=$C$4,L16<=$E$4),VALUE(DATEDIF(G16,L16,"m")+2),))))),IF(OR(G16=0,L16<$C$4),0,IF(AND(G16<$C$4,L16>$E$4),VALUE(DATEDIF($C$4,$E$4,"m")+1),IF(AND(G16<$C$4,L16<=$E$4),VALUE(DATEDIF($C$4,L16,"m")+1),IF(AND(G16>=$C$4,L16>$E$4),VALUE(DATEDIF(G16,$E$4,"m")),IF(AND(G16>=$C$4,L16<=$E$4),VALUE(DATEDIF(G16,L16,"m")+1),)))))) -> 0 | O16: =IF(K16=0,0,ROUND(((1-I16)/K16)*E16,4)) -> 0 | P16: =ROUND(O16*N16,2) -> 0 | Q16: =IF(J16="","",ROUND(J16-P16,2)) | R16: =ROUND(O16*M16,2) -> 0 | S16: =ROUND(F16-R16,2) -> 0
A17: 12 | B17: =固定资产!B17 -> 0 | C17: =固定资产!C17 -> 0 | E17: =固定资产!AA17 -> 0 | F17: =固定资产!P17 -> 0 | G17: =固定资产!D17 -> 0 | H17: =固定资产!E17 -> 0 | K17: =IF(H17=0,0,IF(RIGHT(H17,1)<>"年",H17*12,IF(LEN(H17)=3,VALUE(LEFT(H17,2))*12,IF(LEN(H17)=2,VALUE(LEFT(H17,1))*12,"??")))) -> 0 | L17: =IF(DAY(G17)=1,IF(G17=0,0,DATE(YEAR(G17),MONTH(G17)+K17,DAY(G17))),IF(G17=0,0,DATE(YEAR(G17),MONTH(G17)+K17,DAY(G17)-1))) -> 0 | M17: =MIN(IF(AND(DAY($E$4)=30,DAY(G17)=31),IF(OR(G17=0,G17=$E$4),0,IF(L17>$E$4,VALUE(DATEDIF(G17,MIN($E$4,L17),"m"))+1,VALUE(DATEDIF(G17,MIN($E$4,L17),"m")+2))),IF(OR(G17=0,G17=$E$4),0,IF(L17>$E$4,DATEDIF(G17,MIN($E$4,L17),"m"),VALUE(DATEDIF(G17,MIN($E$4,L17),"m")+1)))),K17) -> 0 | N17: =IF(AND(YEAR(G17)=YEAR($E$4),DAY($E$4)=30,DAY(G17)=31),IF(OR(G17=0,L17<$C$4),0,IF(AND(G17<$C$4,L17>$E$4),VALUE(DATEDIF($C$4,$E$4,"m")+2),IF(AND(G17<$C$4,L17<=$E$4),VALUE(DATEDIF($C$4,L17,"m")+2),IF(AND(G17>=$C$4,L17>$E$4),VALUE(DATEDIF(G17,$E$4,"m")+1),IF(AND(G17>=$C$4,L17<=$E$4),VALUE(DATEDIF(G17,L17,"m")+2),))))),IF(OR(G17=0,L17<$C$4),0,IF(AND(G17<$C$4,L17>$E$4),VALUE(DATEDIF($C$4,$E$4,"m")+1),IF(AND(G17<$C$4,L17<=$E$4),VALUE(DATEDIF($C$4,L17,"m")+1),IF(AND(G17>=$C$4,L17>$E$4),VALUE(DATEDIF(G17,$E$4,"m")),IF(AND(G17>=$C$4,L17<=$E$4),VALUE(DATEDIF(G17,L17,"m")+1),)))))) -> 0 | O17: =IF(K17=0,0,ROUND(((1-I17)/K17)*E17,4)) -> 0 | P17: =ROUND(O17*N17,2) -> 0 | Q17: =IF(J17="","",ROUND(J17-P17,2)) | R17: =ROUND(O17*M17,2) -> 0 | S17: =ROUND(F17-R17,2) -> 0
... A34: 29 | B34: =固定资产!B34 -> 0 | C34: =固定资产!C34 -> 0 | E34: =固定资产!AA34 -> 0 | F34: =固定资产!P34 -> 0 | G34: =固定资产!D34 -> 0 | H34: =固定资产!E34 -> 0 | K34: =IF(H34=0,0,IF(RIGHT(H34,1)<>"年",H34*12,IF(LEN(H34)=3,VALUE(LEFT(H34,2))*12,IF(LEN(H34)=2,VALUE(LEFT(H34,1))*12,"??")))) -> 0 | L34: =IF(DAY(G34)=1,IF(G34=0,0,DATE(YEAR(G34),MONTH(G34)+K34,DAY(G34))),IF(G34=0,0,DATE(YEAR(G34),MONTH(G34)+K34,DAY(G34)-1))) -> 0 | M34: =MIN(IF(AND(DAY($E$4)=30,DAY(G34)=31),IF(OR(G34=0,G34=$E$4),0,IF(L34>$E$4,VALUE(DATEDIF(G34,MIN($E$4,L34),"m"))+1,VALUE(DATEDIF(G34,MIN($E$4,L34),"m")+2))),IF(OR(G34=0,G34=$E$4),0,IF(L34>$E$4,DATEDIF(G34,MIN($E$4,L34),"m"),VALUE(DATEDIF(G34,MIN($E$4,L34),"m")+1)))),K34) -> 0 | N34: =IF(AND(YEAR(G34)=YEAR($E$4),DAY($E$4)=30,DAY(G34)=31),IF(OR(G34=0,L34<$C$4),0,IF(AND(G34<$C$4,L34>$E$4),VALUE(DATEDIF($C$4,$E$4,"m")+2),IF(AND(G34<$C$4,L34<=$E$4),VALUE(DATEDIF($C$4,L34,"m")+2),IF(AND(G34>=$C$4,L34>$E$4),VALUE(DATEDIF(G34,$E$4,"m")+1),IF(AND(G34>=$C$4,L34<=$E$4),VALUE(DATEDIF(G34,L34,"m")+2),))))),IF(OR(G34=0,L34<$C$4),0,IF(AND(G34<$C$4,L34>$E$4),VALUE(DATEDIF($C$4,$E$4,"m")+1),IF(AND(G34<$C$4,L34<=$E$4),VALUE(DATEDIF($C$4,L34,"m")+1),IF(AND(G34>=$C$4,L34>$E$4),VALUE(DATEDIF(G34,$E$4,"m")),IF(AND(G34>=$C$4,L34<=$E$4),VALUE(DATEDIF(G34,L34,"m")+1),)))))) -> 0 | O34: =IF(K34=0,0,ROUND(((1-I34)/K34)*E34,4)) -> 0 | P34: =ROUND(O34*N34,2) -> 0 | Q34: =IF(J34="","",ROUND(J34-P34,2)) | R34: =ROUND(O34*M34,2) -> 0 | S34: =ROUND(F34-R34,2) -> 0
A35: 合计 | E35: =SUM(E6:E34) -> 0 | F35: =SUM(F6:F34) -> 0 | J35: =SUM(J6:J34) -> 0 | O35: =SUM(O6:O34) -> 0 | P35: =SUM(P6:P34) -> 0 | Q35: =SUM(Q6:Q34) -> 0 | R35: =SUM(R6:R34) -> 0 | S35: =SUM(S6:S34) -> 0
B37: 审计说明：

Sheet 无形资产
A1: 无形资产明细表
A2: =备忘录!$A$1 -> 被审计单位：福禄福擎网络科技有限公司 | H2: 编制人：刘喜琴 | K2: =备忘录!$C$2 -> 日期：2025/10/30
A3: =备忘录!$A$2 -> 财务报表截止日：2025/9/30 | H3: 复核人：赵玮 | K3: =备忘录!$C$3 -> 日期：2025/10/31
B4: 一、原值
A5: 序号 | B5: 无形资产名称 | C5: 无形资产 类别 | D5: 未审数 | J5: 期初数调整金额 | K5: 本期审计调整 | M5: 审定数
D6: 期初数 | E6: 本期借方 | F6: 本期贷方 | G6: 期末数 | H6: 企业调整 | I6: 期末报表列报 | K6: 借方调整 | L6: 贷方调整 | M6: 期初数 | N6: 本期借方 | O6: 本期贷方 | P6: 期末数
A7: 1 | G7: =ROUND(D7+E7-F7,2) -> 0 | I7: =ROUND(SUM(G7:H7),2) -> 0 | M7: =ROUND(D7+J7,2) -> 0 | N7: =ROUND(E7+K7,2) -> 0 | O7: =ROUND(F7+L7,2) -> 0 | P7: =ROUND(M7+N7-O7,2) -> 0
A8: 2 | G8: =ROUND(D8+E8-F8,2) -> 0 | I8: =ROUND(SUM(G8:H8),2) -> 0 | M8: =ROUND(D8+J8,2) -> 0 | N8: =ROUND(E8+K8,2) -> 0 | O8: =ROUND(F8+L8,2) -> 0 | P8: =ROUND(M8+N8-O8,2) -> 0
B9: 合计 | C9: —— | D9: =ROUND(SUM(D7:D8),2) -> 0 | E9: =ROUND(SUM(E7:E8),2) -> 0 | F9: =ROUND(SUM(F7:F8),2) -> 0 | G9: =ROUND(SUM(G7:G8),2) -> 0 | H9: =ROUND(SUM(H7:H8),2) -> 0 | I9: =ROUND(SUM(I7:I8),2) -> 0 | J9: =ROUND(SUM(J7:J8),2) -> 0 | K9: =ROUND(SUM(K7:K8),2) -> 0 | ... P9: =ROUND(SUM(P7:P8),2) -> 0
B11: 二、累计摊销
A12: 序号 | B12: 无形资产名称 | C12: 无形资产 类别 | D12: 未审数 | J12: 期初数调整金额 | K12: 本期审计调整 | M12: 审定数
D13: 期初数 | E13: 本期借方 | F13: 本期贷方 | G13: 期末数 | H13: 企业调整 | I13: 期末报表列报 | K13: 借方调整 | L13: 贷方调整 | M13: 期初数 | N13: 本期借方 | O13: 本期贷方 | P13: 期末数
A14: 1 | G14: =ROUND(D14-E14+F14,2) -> 0 | I14: =ROUND(SUM(G14:H14),2) -> 0 | M14: =ROUND(D14+J14,2) -> 0 | N14: =ROUND(E14+K14,2) -> 0 | O14: =ROUND(F14+L14,2) -> 0 | P14: =ROUND(M14-N14+O14,2) -> 0
A15: 2 | G15: =D15-E15+F15 -> 0 | I15: =SUM(G15:H15) -> 0 | M15: =ROUND(D15+J15,2) -> 0 | N15: =ROUND(E15+K15,2) -> 0 | O15: =ROUND(F15+L15,2) -> 0 | P15: =ROUND(M15-N15+O15,2) -> 0
B16: 合计 | C16: —— | D16: =ROUND(SUM(D14:D15),2) -> 0 | E16: =ROUND(SUM(E14:E15),2) -> 0 | F16: =ROUND(SUM(F14:F15),2) -> 0 | G16: =ROUND(SUM(G14:G15),2) -> 0 | H16: =ROUND(SUM(H14:H15),2) -> 0 | I16: =ROUND(SUM(I14:I15),2) -> 0 | J16: =ROUND(SUM(J14:J15),2) -> 0 | K16: =ROUND(SUM(K14:K15),2) -> 0 | ... P16: =ROUND(SUM(P14:P15),2) -> 0
B18: 三、减值准备
A19: 序号 | B19: 无形资产名称 | C19: 无形资产 类别 | D19: 未审数 | J19: 期初数调整金额 | K19: 本期审计调整 | M19: 审定数
D20: 期初数 | E20: 本期借方 | F20: 本期贷方 | G20: 期末数 | H20: 企业调整 | I20: 期末报表列报 | K20: 借方调整 | L20: 贷方调整 | M20: 期初数 | N20: 本期借方 | O20: 本期贷方 | P20: 期末数
A21: 1 | G21: =ROUND(D21-E21+F21,2) -> 0 | I21: =ROUND(SUM(G21:H21),2) -> 0 | M21: =ROUND(D21+J21,2) -> 0 | N21: =ROUND(E21+K21,2) -> 0 | O21: =ROUND(F21+L21,2) -> 0 | P21: =ROUND(M21-N21+O21,2) -> 0
A22: 2 | G22: =ROUND(D22-E22+F22,2) -> 0 | I22: =ROUND(SUM(G22:H22),2) -> 0 | M22: =ROUND(D22+J22,2) -> 0 | N22: =ROUND(E22+K22,2) -> 0 | O22: =ROUND(F22+L22,2) -> 0 | P22: =ROUND(M22-N22+O22,2) -> 0
B23: 合计 | C23: —— | D23: =ROUND(SUM(D21:D22),2) -> 0 | E23: =ROUND(SUM(E21:E22),2) -> 0 | F23: =ROUND(SUM(F21:F22),2) -> 0 | G23: =ROUND(SUM(G21:G22),2) -> 0 | H23: =ROUND(SUM(H21:H22),2) -> 0 | I23: =ROUND(SUM(I21:I22),2) -> 0 | J23: =ROUND(SUM(J21:J22),2) -> 0 | K23: =ROUND(SUM(K21:K22),2) -> 0 | ... P23: =ROUND(SUM(P21:P22),2) -> 0
A25: 四、账面净值 | B25: 净值合计 | D25: =ROUND(D9-D16-D23,2) -> 0 | E25: =ROUND(E9-E16-E23,2) -> 0 | F25: =ROUND(F9-F16-F23,2) -> 0 | G25: =ROUND(G9-G16-G23,2) -> 0 | H25: =ROUND(H9-H16-H23,2) -> 0 | I25: =ROUND(I9-I16-I23,2) -> 0 | J25: =ROUND(J9-J16-J23,2) -> 0 | K25: =ROUND(K9-K16-K23,2) -> 0 | ... P25: =ROUND(P9-P16-P23,2) -> 0
D27: 审计说明：
C29: 软件
C30: 土地使用权
C31: 专利权
C32: 非专有技术
C33: 商标权
C34: 著作权
C35: 特许经营权

Sheet 无形资产测算表
A1: 无形资产累计摊销计算表（未计提减值情况下适用）
A2: =备忘录!$A$1 -> 被审计单位：福禄福擎网络科技有限公司 | H2: 编制人：刘喜琴 | N2: =备忘录!$C$2 -> 日期：2025/10/30
A3: =备忘录!$A$2 -> 财务报表截止日：2025/9/30 | H3: 复核人：赵玮 | N3: =备忘录!$C$3 -> 日期：2025/10/31
A4: 期初： | B4: 45658 | C4: 摊销期末： | D4: 45930
A5: 无形资产名称 | B5: 原值 | C5: 累计摊销 | D5: 开始使用日期 | E5: 使用期限（年） | F5: 账面月摊销额 | G5: 当期摊销额 | H5: 摊销期限（月） | I5: 测算到期日 | J5: 已摊销月份 | K5: 剩余摊销月份 | L5: 本期摊销月份 | M5: 月摊销 | N5: 当期摊销费用 | O5: 月摊销额差异 | P5: 累计摊销 | Q5: 当期摊销额差异 | R5: 累计摊销额差异
H6: =IF(E6=0,0,IF(RIGHT(E6,1)<>"年",E6*12,IF(LEN(E6)=3,VALUE(LEFT(E6,2))*12,IF(LEN(E6)=2,VALUE(LEFT(E6,1))*12,"??")))) -> 0 | I6: =IF(DAY(D6)=1,IF(D6=0,0,DATE(YEAR(D6),MONTH(D6)+H6-1,DAY(D6))),IF(D6=0,0,DATE(YEAR(D6),MONTH(D6)+H6-1,DAY(D6)-1))) -> 0 | J6: =IF(D6="",0,MIN(IF(AND(DAY($D$4)=30,DAY(D6)=31),IF(OR(D6=0,D6=$D$4),0,IF(I6>$D$4,VALUE(DATEDIF(D6,MIN($D$4,I6),"m"))+1,VALUE(DATEDIF(D6,MIN($D$4,I6),"m")+2))),IF(OR(D6=0,D6=$D$4),0,IF(I6>$D$4,DATEDIF(D6,MIN($D$4,I6),"m"),VALUE(DATEDIF(D6,MIN($D$4,I6),"m")+1)))),H6)) -> 0 | K6: =IF(J6="",0,H6-J6) -> 0 | L6: =IF(AND(YEAR(D6)=YEAR($D$4),DAY($D$4)=30,DAY(D6)=31),IF(OR(D6=0,I6<$B$4),0,IF(AND(D6<$B$4,I6>$D$4),VALUE(DATEDIF($B$4,$D$4,"m")+2),IF(AND(D6<$B$4,I6<=$D$4),VALUE(DATEDIF($B$4,I6,"m")+2),IF(AND(D6>=$B$4,I6>$D$4),VALUE(DATEDIF(D6,$D$4,"m")+1),IF(AND(D6>=$B$4,I6<=$D$4),VALUE(DATEDIF(D6,I6,"m")+2),))))),IF(OR(D6=0,I6<$B$4),0,IF(AND(D6<$B$4,I6>$D$4),VALUE(DATEDIF($B$4,$D$4,"m")+1),IF(AND(D6<$B$4,I6<=$D$4),VALUE(DATEDIF($B$4,I6,"m")+1),IF(AND(D6>=$B$4,I6>$D$4),VALUE(DATEDIF(D6,$D$4,"m")+1),IF(AND(D6>=$B$4,I6<=$D$4),VALUE(DATEDIF(D6,I6,"m")+1),)))))) -> 0 | M6: =IF(H6=0,0,ROUND(((1-0)/H6)*B6,4)) -> 0 | N6: =L6*M6 -> 0 | O6: =M6-F6 -> 0 | P6: =M6*J6 -> 0 | Q6: =G6-N6 -> 0 | R6: =C6-P6 -> 0
H7: =IF(E7=0,0,IF(RIGHT(E7,1)<>"年",E7*12,IF(LEN(E7)=3,VALUE(LEFT(E7,2))*12,IF(LEN(E7)=2,VALUE(LEFT(E7,1))*12,"??")))) -> 0 | I7: =IF(DAY(D7)=1,IF(D7=0,0,DATE(YEAR(D7),MONTH(D7)+H7-1,DAY(D7))),IF(D7=0,0,DATE(YEAR(D7),MONTH(D7)+H7-1,DAY(D7)-1))) -> 0 | J7: =IF(D7="",0,MIN(IF(AND(DAY($D$4)=30,DAY(D7)=31),IF(OR(D7=0,D7=$D$4),0,IF(I7>$D$4,VALUE(DATEDIF(D7,MIN($D$4,I7),"m"))+1,VALUE(DATEDIF(D7,MIN($D$4,I7),"m")+2))),IF(OR(D7=0,D7=$D$4),0,IF(I7>$D$4,DATEDIF(D7,MIN($D$4,I7),"m"),VALUE(DATEDIF(D7,MIN($D$4,I7),"m")+1)))),H7)) -> 0 | K7: =IF(J7="",0,H7-J7) -> 0 | L7: =IF(AND(YEAR(D7)=YEAR($D$4),DAY($D$4)=30,DAY(D7)=31),IF(OR(D7=0,I7<$B$4),0,IF(AND(D7<$B$4,I7>$D$4),VALUE(DATEDIF($B$4,$D$4,"m")+2),IF(AND(D7<$B$4,I7<=$D$4),VALUE(DATEDIF($B$4,I7,"m")+2),IF(AND(D7>=$B$4,I7>$D$4),VALUE(DATEDIF(D7,$D$4,"m")+1),IF(AND(D7>=$B$4,I7<=$D$4),VALUE(DATEDIF(D7,I7,"m")+2),))))),IF(OR(D7=0,I7<$B$4),0,IF(AND(D7<$B$4,I7>$D$4),VALUE(DATEDIF($B$4,$D$4,"m")+1),IF(AND(D7<$B$4,I7<=$D$4),VALUE(DATEDIF($B$4,I7,"m")+1),IF(AND(D7>=$B$4,I7>$D$4),VALUE(DATEDIF(D7,$D$4,"m")+1),IF(AND(D7>=$B$4,I7<=$D$4),VALUE(DATEDIF(D7,I7,"m")+1),)))))) -> 0 | M7: =IF(H7=0,0,ROUND(((1-0)/H7)*B7,4)) -> 0 | N7: =L7*M7 -> 0 | O7: =M7-F7 -> 0 | P7: =M7*J7 -> 0 | Q7: =G7-N7 -> 0 | R7: =C7-P7 -> 0
A8: 合计 | B8: =SUM(B6:B7) -> 0 | C8: =SUM(C6:C7) -> 0 | D8: —— | E8: —— | F8: =SUM(F6:F7) -> 0 | G8: =SUM(G6:G7) -> 0 | H8: —— | I8: —— | J8: —— | K8: —— | L8: —— | M8: =SUM(M6:M7) -> 0 | N8: =SUM(N6:N7) -> 0 | O8: =SUM(O6:O7) -> 0 | P8: =SUM(P6:P7) -> 0 | Q8: =SUM(Q6:Q7) -> 0 | R8: =SUM(R6:R7) -> 0
B10: 审计说明：

Sheet 应收账款
A1: 应收账款明细表
A2: =备忘录!$A$1 -> 被审计单位：福禄福擎网络科技有限公司 | F2: 编制人：刘喜琴 | K2: =备忘录!$C$2 -> 日期：2025/10/30
A3: =备忘录!$A$2 -> 财务报表截止日：2025/9/30 | F3: 复核人：赵玮 | K3: =备忘录!$C$3 -> 日期：2025/10/31
A4: 序号 | B4: 科目名称 | C4: 核算项目1 | D4: 核算项目2 | E4: 账面数据 | J4: 期末报表列报 | K4: 审计调整 | L4: 期末审定余额 | M4: 余额核对 (√) | N4: 核对确认金额 | O4: 备注 | P4: 重要客户/供应商账龄划分（√） | Q4: 1个月以内 | R4: 2-3月 | S4: 4-6月 | T4: 6个月以上 | U4: 重要客户/供应商背调(√) | V4: 背景调查
E5: 期初金额（取数为：科目余额表期初借方-贷方） | F5: 本期借方 | G5: 本期贷方 | H5: 期末金额 | I5: 企业调整 | V5: 法定代表人 | W5: 成立日期 | X5: 注册地址 | Y5: 注册资本（万元） | Z5: 行业 | AA5: 股权结构 | AB5: 企业规模 | AC5: 员工人数 | AD5: 纳税人资质 | AE5: 经营范围
A6: 1 | H6: =ROUND(E6+F6-G6,2) -> 0 | J6: =H6+I6 -> 0 | L6: =J6+K6 -> 0
A7: 2 | H7: =ROUND(E7+F7-G7,2) -> 0 | J7: =H7+I7 -> 0 | L7: =J7+K7 -> 0
A8: 3 | H8: =ROUND(E8+F8-G8,2) -> 0 | J8: =H8+I8 -> 0 | L8: =J8+K8 -> 0
A9: 4 | H9: =ROUND(E9+F9-G9,2) -> 0 | J9: =H9+I9 -> 0 | L9: =J9+K9 -> 0
A10: 5 | H10: =ROUND(E10+F10-G10,2) -> 0 | J10: =H10+I10 -> 0 | L10: =J10+K10 -> 0
A11: 6 | H11: =ROUND(E11+F11-G11,2) -> 0 | J11: =H11+I11 -> 0 | L11: =J11+K11 -> 0
A12: 7 | H12: =ROUND(E12+F12-G12,2) -> 0 | J12: =H12+I12 -> 0 | L12: =J12+K12 -> 0
A13: 8 | H13: =ROUND(E13+F13-G13,2) -> 0 | J13: =H13+I13 -> 0 | L13: =J13+K13 -> 0
A14: 9 | H14: =ROUND(E14+F14-G14,2) -> 0 | J14: =H14+I14 -> 0 | L14: =J14+K14 -> 0
A15: 10 | H15: =ROUND(E15+F15-G15,2) -> 0 | J15: =H15+I15 -> 0 | L15: =J15+K15 -> 0
A16: 11 | H16: =ROUND(E16+F16-G16,2) -> 0 | J16: =H16+I16 -> 0 | L16: =J16+K16 -> 0
A17: 12 | H17: =ROUND(E17+F17-G17,2) -> 0 | J17: =H17+I17 -> 0 | L17: =J17+K17 -> 0
... A32: 27 | H32: =ROUND(E32+F32-G32,2) -> 0 | J32: =H32+I32 -> 0 | L32: =J32+K32 -> 0
A33: 账面余额总计 | E33: =ROUND(SUM(E6:E32),2) -> 0 | F33: =ROUND(SUM(F6:F32),2) -> 0 | G33: =ROUND(SUM(G6:G32),2) -> 0 | H33: =ROUND(SUM(H6:H32),2) -> 0 | I33: =ROUND(SUM(I6:I32),2) -> 0 | J33: =H33+I33 -> 0 | K33: =ROUND(SUM(K6:K32),2) -> 0 | L33: =J33+K33 -> 0 | N33: =ROUND(SUM(N6:N32),2) -> 0
A34: 坏账准备 | H34: =E34+G34-F34 -> 0 | J34: =H34+I34 -> 0 | L34: =J34+K34 -> 0
A35: 账面价值总计 | E35: =ROUND(E33-E34,2) -> 0 | H35: =ROUND(H33-H34,2) -> 0 | J35: =H35+I35 -> 0 | K35: =ROUND(K33-K34,2) -> 0 | L35: =J35+K35 -> 0
B37: 审计说明：

Sheet 预付账款
B1: 预付账款明细表
A2: =备忘录!$A$1 -> 被审计单位：福禄福擎网络科技有限公司 | F2: 编制人：刘喜琴 | L2: =备忘录!$C$2 -> 日期：2025/10/30
A3: =备忘录!$A$2 -> 财务报表截止日：2025/9/30 | F3: 复核人：赵玮 | L3: =备忘录!$C$3 -> 日期：2025/10/31
A4: 序号 | B4: 科目名称 | C4: 核算项目1 | D4: 核算项目2 | E4: 账面数据 | J4: 期末报表列报 | K4: 审计调整 | L4: 期末审定余额 | M4: 余额核对 (√) | N4: 核对确认金额 | O4: 备注 | P4: 重要客户/供应商账龄划分（√） | Q4: 1个月以内 | R4: 2-3月 | S4: 4-6月 | T4: 6个月以上 | U4: 重要客户/供应商背调(√) | V4: 背景调查
E5: 期初金额（取数为：科目余额表期初借方-贷方） | F5: 本期借方 | G5: 本期贷方 | H5: 期末金额 | I5: 企业调整 | V5: 法定代表人 | W5: 成立日期 | X5: 注册地址 | Y5: 注册资本（万元） | Z5: 行业 | AA5: 股权结构 | AB5: 企业规模 | AC5: 员工人数 | AD5: 纳税人资质 | AE5: 经营范围
A6: 1 | H6: =ROUND(E6+F6-G6,2) -> 0 | J6: =H6+I6 -> 0 | L6: =J6+K6 -> 0
A7: 2 | H7: =ROUND(E7+F7-G7,2) -> 0 | J7: =H7+I7 -> 0 | L7: =J7+K7 -> 0
A8: 3 | H8: =ROUND(E8+F8-G8,2) -> 0 | J8: =H8+I8 -> 0 | L8: =J8+K8 -> 0
A9: 4 | H9: =ROUND(E9+F9-G9,2) -> 0 | J9: =H9+I9 -> 0 | L9: =J9+K9 -> 0
A10: 5 | H10: =ROUND(E10+F10-G10,2) -> 0 | J10: =H10+I10 -> 0 | L10: =J10+K10 -> 0
A11: 6 | H11: =ROUND(E11+F11-G11,2) -> 0 | J11: =H11+I11 -> 0 | L11: =J11+K11 -> 0
A12: 7 | H12: =ROUND(E12+F12-G12,2) -> 0 | J12: =H12+I12 -> 0 | L12: =J12+K12 -> 0
A13: 8 | H13: =ROUND(E13+F13-G13,2) -> 0 | J13: =H13+I13 -> 0 | L13: =J13+K13 -> 0
A14: 9 | H14: =ROUND(E14+F14-G14,2) -> 0 | J14: =H14+I14 -> 0 | L14: =J14+K14 -> 0
A15: 10 | H15: =ROUND(E15+F15-G15,2) -> 0 | J15: =H15+I15 -> 0 | L15: =J15+K15 -> 0
A16: 11 | H16: =ROUND(E16+F16-G16,2) -> 0 | J16: =H16+I16 -> 0 | L16: =J16+K16 -> 0
A17: 12 | H17: =ROUND(E17+F17-G17,2) -> 0 | J17: =H17+I17 -> 0 | L17: =J17+K17 -> 0
... A30: 25 | H30: =ROUND(E30+F30-G30,2) -> 0 | J30: =H30+I30 -> 0 | L30: =J30+K30 -> 0
A31: 账面余额总计 | E31: =ROUND(SUM(E6:E30),2) -> 0 | F31: =ROUND(SUM(F6:F30),2) -> 0 | G31: =ROUND(SUM(G6:G30),2) -> 0 | H31: =ROUND(E31+F31-G31,2) -> 0 | I31: =ROUND(SUM(I4:I30),2) -> 0 | J31: =H31+I31 -> 0 | K31: =ROUND(SUM(K6:K30),2) -> 0 | L31: =J31+K31 -> 0 | N31: =ROUND(SUM(N6:N30),2) -> 0
A32: 坏账准备 | H32: =E32+F32-G32 -> 0 | J32: =H32+I32 -> 0 | L32: =J32+K32 -> 0
A33: 账面价值总计 | E33: =ROUND(E31-E32,2) -> 0 | H33: =ROUND(H31-H32,2) -> 0 | J33: =ROUND(J31-J32,2) -> 0 | K33: =ROUND(K31-K32,2) -> 0 | L33: =ROUND(L31-L32,2) -> 0
B35: 审计说明：

Sheet 其他应收款
A1: 其他应收款明细表
A2: =备忘录!$A$1 -> 被审计单位：福禄福擎网络科技有限公司 | F2: 编制人：刘喜琴 | J2: =备忘录!$C$2 -> 日期：2025/10/30
A3: =备忘录!$A$2 -> 财务报表截止日：2025/9/30 | F3: 复核人：赵玮 | J3: =备忘录!$C$3 -> 日期：2025/10/31
A4: 序号 | B4: 科目名称 | C4: 核算项目1 | D4: 核算项目2 | E4: 账面数据 | J4: 期末报表列报 | K4: 审计调整 | L4: 期末审定余额 | M4: 余额核对 (√) | N4: 核对确认金额 | O4: 备注 | P4: 重要客户/供应商账龄划分（√） | Q4: 1个月以内 | R4: 2-3月 | S4: 4-6月 | T4: 6个月以上 | U4: 重要客户/供应商背调(√) | V4: 背景调查
E5: 期初金额（取数为：科目余额表期初借方-贷方） | F5: 本期借方 | G5: 本期贷方 | H5: 期末金额 | I5: 企业调整 | V5: 法定代表人 | W5: 成立日期 | X5: 注册地址 | Y5: 注册资本（万元） | Z5: 行业 | AA5: 股权结构 | AB5: 企业规模 | AC5: 员工人数 | AD5: 纳税人资质 | AE5: 经营范围
A6: 1 | H6: =ROUND(E6+F6-G6,2) -> 0 | J6: =ROUND(H6+I6,2) -> 0 | L6: =J6+K6 -> 0
A7: 2 | H7: =ROUND(E7+F7-G7,2) -> 0 | J7: =ROUND(H7+I7,2) -> 0 | L7: =J7+K7 -> 0
A8: 3 | H8: =ROUND(E8+F8-G8,2) -> 0 | J8: =ROUND(H8+I8,2) -> 0 | L8: =J8+K8 -> 0
A9: 4 | H9: =ROUND(E9+F9-G9,2) -> 0 | J9: =ROUND(H9+I9,2) -> 0 | L9: =J9+K9 -> 0
A10: 5 | H10: =ROUND(E10+F10-G10,2) -> 0 | J10: =ROUND(H10+I10,2) -> 0 | L10: =J10+K10 -> 0
A11: 6 | H11: =ROUND(E11+F11-G11,2) -> 0 | J11: =ROUND(H11+I11,2) -> 0 | L11: =J11+K11 -> 0
A12: 7 | H12: =ROUND(E12+F12-G12,2) -> 0 | J12: =ROUND(H12+I12,2) -> 0 | L12: =J12+K12 -> 0
A13: 8 | H13: =ROUND(E13+F13-G13,2) -> 0 | J13: =ROUND(H13+I13,2) -> 0 | L13: =J13+K13 -> 0
A14: 9 | H14: =ROUND(E14+F14-G14,2) -> 0 | J14: =ROUND(H14+I14,2) -> 0 | L14: =J14+K14 -> 0
A15: 10 | H15: =ROUND(E15+F15-G15,2) -> 0 | J15: =ROUND(H15+I15,2) -> 0 | L15: =J15+K15 -> 0
A16: 11 | H16: =ROUND(E16+F16-G16,2) -> 0 | J16: =ROUND(H16+I16,2) -> 0 | L16: =J16+K16 -> 0
A17: 12 | H17: =ROUND(E17+F17-G17,2) -> 0 | J17: =ROUND(H17+I17,2) -> 0 | L17: =J17+K17 -> 0
... A145: 140 | H145: =ROUND(E145+F145-G145,2) -> 0 | J145: =ROUND(H145+I145,2) -> 0 | L145: =J145+K145 -> 0
A146: 账面余额总计 | E146: =ROUND(SUM(E6:E145),2) -> 0 | F146: =ROUND(SUM(F6:F145),2) -> 0 | G146: =ROUND(SUM(G6:G145),2) -> 0 | H146: =ROUND(SUM(H6:H145),2) -> 0 | I146: =ROUND(SUM(I6:I145),2) -> 0 | J146: =ROUND(SUM(J6:J145),2) -> 0 | K146: =ROUND(SUM(K6:K145),2) -> 0 | L146: =J146+K146 -> 0 | N146: =ROUND(SUM(N6:N145),2) -> 0
A147: 坏账准备 | H147: =E147+G147-F147 -> 0 | J147: =H147+I147 -> 0 | L147: =J147+K147 -> 0
A148: 账面价值总计 | E148: =ROUND(E146-E147,2) -> 0 | H148: =ROUND(H146-H147,2) -> 0 | I148: =ROUND(I146-I147,2) -> 0 | J148: =ROUND(J146-J147,2) -> 0 | K148: =ROUND(K146-K147,2) -> 0 | L148: =J148+K148 -> 0
B150: 审计说明：

Sheet 关联方交易核对
A1: 关联方交易列示及核对
A2: =备忘录!$A$1 -> 被审计单位：福禄福擎网络科技有限公司 | E2: 编制人：刘喜琴 | H2: =备忘录!$C$2 -> 日期：2025/10/30
A3: =备忘录!$A$2 -> 财务报表截止日：2025/9/30 | E3: 复核人：赵玮 | H3: =备忘录!$C$3 -> 日期：2025/10/31
A4: 编号 | B4: 项目名称 | C4: 关联单位名称 | D4: 关联方关系 | E4: 期末余额 | F4: 款项性质 | G4: 关联方信息
G5: 挂账科目 | H5: 期末金额 | I5: 款项性质 | J5: 核对差异
A6: 1 | B6: 应收账款 | J6: =E6-H6 -> 0
A7: 2 | B7: 应付账款 | J7: =E7-H7 -> 0
A8: 3 | B8: 其他应收款 | J8: =E8-H8 -> 0
A9: 4 | B9: 其他应付款 | J9: =E9-H9 -> 0
A10: 5 | J10: =E10-H10 -> 0
A11: 6 | J11: =E11-H11 -> 0
A12: 7 | J12: =E12-H12 -> 0
A13: 8 | J13: =E13-H13 -> 0
A14: 9 | J14: =E14-H14 -> 0
A15: 10 | J15: =E15-H15 -> 0
A16: 11 | J16: =E16-H16 -> 0
A17: 12 | J17: =E17-H17 -> 0
A18: 13 | J18: =E18-H18 -> 0
A19: 14 | J19: =E19-H19 -> 0
A20: 15 | J20: =E20-H20 -> 0
A21: 合计 | E21: =SUM(E6:E20) -> 0 | H21: =SUM(H6:H20) -> 0 | J21: =SUM(J6:J20) -> 0
B23: 审计说明：

Sheet 应付账款
B1: 应付账款明细表
A2: =备忘录!$A$1 -> 被审计单位：福禄福擎网络科技有限公司 | F2: 编制人：刘喜琴 | M2: =备忘录!$C$2 -> 日期：2025/10/30
A3: =备忘录!$A$2 -> 财务报表截止日：2025/9/30 | F3: 复核人：赵玮 | M3: =备忘录!$C$3 -> 日期：2025/10/31
A4: 序号 | B4: 科目名称 | C4: 核算项目1 | D4: 核算项目2 | E4: 账面数据 | J4: 期末报表列报 | K4: 审计调整 | L4: 期末审定余额 | M4: 余额核对 (√) | N4: 核对确认金额 | O4: 备注 | P4: 重要客户/供应商账龄划分（√） | Q4: 1个月以内 | R4: 2-3月 | S4: 4-6月 | T4: 6个月以上 | U4: 重要客户/供应商背调(√) | V4: 背景调查
E5: 期初金额（取数为：科目余额表期初贷方-借方） | F5: 本期借方 | G5: 本期贷方 | H5: 期末金额 | I5: 企业调整 | V5: 法定代表人 | W5: 成立日期 | X5: 注册地址 | Y5: 注册资本（万元） | Z5: 行业 | AA5: 股权结构 | AB5: 企业规模 | AC5: 员工人数 | AD5: 纳税人资质 | AE5: 经营范围
A6: 1 | H6: =SUM(E6,G6,-F6) -> 0 | J6: =H6+I6 -> 0 | L6: =J6+K6 -> 0
A7: 2 | H7: =SUM(E7,G7,-F7) -> 0 | J7: =H7+I7 -> 0 | L7: =J7+K7 -> 0
A8: 3 | H8: =SUM(E8,G8,-F8) -> 0 | J8: =H8+I8 -> 0 | L8: =J8+K8 -> 0
A9: 4 | H9: =SUM(E9,G9,-F9) -> 0 | J9: =H9+I9 -> 0 | L9: =J9+K9 -> 0
A10: 5 | H10: =SUM(E10,G10,-F10) -> 0 | J10: =H10+I10 -> 0 | L10: =J10+K10 -> 0
A11: 6 | H11: =SUM(E11,G11,-F11) -> 0 | J11: =H11+I11 -> 0 | L11: =J11+K11 -> 0
A12: 7 | H12: =SUM(E12,G12,-F12) -> 0 | J12: =H12+I12 -> 0 | L12: =J12+K12 -> 0
A13: 8 | H13: =SUM(E13,G13,-F13) -> 0 | J13: =H13+I13 -> 0 | L13: =J13+K13 -> 0
A14: 9 | H14: =SUM(E14,G14,-F14) -> 0 | J14: =H14+I14 -> 0 | L14: =J14+K14 -> 0
A15: 10 | H15: =SUM(E15,G15,-F15) -> 0 | J15: =H15+I15 -> 0 | L15: =J15+K15 -> 0
A16: 11 | H16: =SUM(E16,G16,-F16) -> 0 | J16: =H16+I16 -> 0 | L16: =J16+K16 -> 0
A17: 12 | H17: =SUM(E17,G17,-F17) -> 0 | J17: =H17+I17 -> 0 | L17: =J17+K17 -> 0
... A19: 14 | H19: =SUM(E19,G19,-F19) -> 0 | J19: =H19+I19 -> 0 | L19: =J19+K19 -> 0
B20: 合计 | E20: =ROUND(SUM(E6:E19),2) -> 0 | F20: =ROUND(SUM(F6:F19),2) -> 0 | G20: =ROUND(SUM(G6:G19),2) -> 0 | H20: =SUM(E20,G20,-F20) -> 0 | J20: =H20+I20 -> 0 | K20: =ROUND(SUM(K6:K19),2) -> 0 | L20: =J20+K20 -> 0 | N20: =ROUND(SUM(N6:N19),2) -> 0
B22: 审计说明：

Sheet 预收账款
B1: 预收账款明细表
A2: =备忘录!$A$1 -> 被审计单位：福禄福擎网络科技有限公司 | F2: 编制人：刘喜琴 | L2: =备忘录!$C$2 -> 日期：2025/10/30
A3: =备忘录!$A$2 -> 财务报表截止日：2025/9/30 | F3: 复核人：赵玮 | L3: =备忘录!$C$3 -> 日期：2025/10/31
A4: 序号 | B4: 科目名称 | C4: 核算项目1 | D4: 核算项目2 | E4: 账面数据 | J4: 期末报表列报 | K4: 审计调整 | L4: 期末审定余额 | M4: 余额核对 (√) | N4: 核对确认金额 | O4: 备注 | P4: 重要客户/供应商账龄划分（√） | Q4: 1个月以内 | R4: 2-3月 | S4: 4-6月 | T4: 6个月以上 | U4: 重要客户/供应商背调(√) | V4: 背景调查
E5: 期初金额（取数为：科目余额表期初贷方-借方） | F5: 本期借方 | G5: 本期贷方 | H5: 期末金额 | I5: 企业调整 | V5: 法定代表人 | W5: 成立日期 | X5: 注册地址 | Y5: 注册资本（万元） | Z5: 行业 | AA5: 股权结构 | AB5: 企业规模 | AC5: 员工人数 | AD5: 纳税人资质 | AE5: 经营范围
A6: 1 | H6: =SUM(E6,G6,-F6) -> 0 | J6: =H6+I6 -> 0 | L6: =J6+K6 -> 0
A7: 2 | H7: =SUM(E7,G7,-F7) -> 0 | J7: =H7+I7 -> 0 | L7: =J7+K7 -> 0
A8: 3 | H8: =SUM(E8,G8,-F8) -> 0 | J8: =H8+I8 -> 0 | L8: =J8+K8 -> 0
A9: 4 | H9: =SUM(E9,G9,-F9) -> 0 | J9: =H9+I9 -> 0 | L9: =J9+K9 -> 0
A10: 5 | H10: =SUM(E10,G10,-F10) -> 0 | J10: =H10+I10 -> 0 | L10: =J10+K10 -> 0
A11: 6 | H11: =SUM(E11,G11,-F11) -> 0 | J11: =H11+I11 -> 0 | L11: =J11+K11 -> 0
A12: 7 | H12: =SUM(E12,G12,-F12) -> 0 | J12: =H12+I12 -> 0 | L12: =J12+K12 -> 0
A13: 8 | H13: =SUM(E13,G13,-F13) -> 0 | J13: =H13+I13 -> 0 | L13: =J13+K13 -> 0
A14: 9 | H14: =SUM(E14,G14,-F14) -> 0 | J14: =H14+I14 -> 0 | L14: =J14+K14 -> 0
A15: 10 | H15: =SUM(E15,G15,-F15) -> 0 | J15: =H15+I15 -> 0 | L15: =J15+K15 -> 0
A16: 11 | H16: =SUM(E16,G16,-F16) -> 0 | J16: =H16+I16 -> 0 | L16: =J16+K16 -> 0
A17: 12 | H17: =SUM(E17,G17,-F17) -> 0 | J17: =H17+I17 -> 0 | L17: =J17+K17 -> 0
... A25: 20 | H25: =SUM(E25,G25,-F25) -> 0 | J25: =H25+I25 -> 0 | L25: =J25+K25 -> 0
B26: 合计 | E26: =ROUND(SUM(E6:E25),2) -> 0 | F26: =ROUND(SUM(F6:F25),2) -> 0 | G26: =ROUND(SUM(G6:G25),2) -> 0 | H26: =SUM(E26,G26,-F26) -> 0 | J26: =H26+I26 -> 0 | K26: =ROUND(SUM(K6:K25),2) -> 0 | L26: =J26+K26 -> 0 | N26: =ROUND(SUM(N6:N25),2) -> 0
B28: 审计说明：

Sheet 其他应付款
B1: 其他应付款明细表
A2: =备忘录!$A$1 -> 被审计单位：福禄福擎网络科技有限公司 | H2: 编制人：刘喜琴 | N2: =备忘录!$C$2 -> 日期：2025/10/30
A3: =备忘录!$A$2 -> 财务报表截止日：2025/9/30 | H3: 复核人：赵玮 | N3: =备忘录!$C$3 -> 日期：2025/10/31
A4: 序号 | B4: 科目名称 | C4: 核算项目1 | D4: 核算项目2 | E4: 账面数据 | J4: 期末报表列报 | K4: 审计调整 | L4: 期末审定余额 | M4: 余额核对 (√) | N4: 核对确认金额 | O4: 备注 | P4: 重要客户/供应商账龄划分（√） | Q4: 1个月以内 | R4: 2-3月 | S4: 4-6月 | T4: 6个月以上 | U4: 重要客户/供应商背调(√) | V4: 背景调查
E5: 期初金额（取数为：科目余额表期初贷方-借方） | F5: 本期借方 | G5: 本期贷方 | H5: 期末金额 | I5: 企业调整 | V5: 法定代表人 | W5: 成立日期 | X5: 注册地址 | Y5: 注册资本（万元） | Z5: 行业 | AA5: 股权结构 | AB5: 企业规模 | AC5: 员工人数 | AD5: 纳税人资质 | AE5: 经营范围
A6: 1 | H6: =SUM(E6,G6,-F6) -> 0 | J6: =H6+I6 -> 0 | L6: =J6+K6 -> 0
A7: 2 | H7: =SUM(E7,G7,-F7) -> 0 | J7: =H7+I7 -> 0 | L7: =J7+K7 -> 0
A8: 3 | H8: =SUM(E8,G8,-F8) -> 0 | J8: =H8+I8 -> 0 | L8: =J8+K8 -> 0
A9: 4 | H9: =SUM(E9,G9,-F9) -> 0 | J9: =H9+I9 -> 0 | L9: =J9+K9 -> 0
A10: 5 | H10: =SUM(E10,G10,-F10) -> 0 | J10: =H10+I10 -> 0 | L10: =J10+K10 -> 0
A11: 6 | H11: =SUM(E11,G11,-F11) -> 0 | J11: =H11+I11 -> 0 | L11: =J11+K11 -> 0
A12: 7 | H12: =SUM(E12,G12,-F12) -> 0 | J12: =H12+I12 -> 0 | L12: =J12+K12 -> 0
A13: 8 | H13: =SUM(E13,G13,-F13) -> 0 | J13: =H13+I13 -> 0 | L13: =J13+K13 -> 0
A14: 9 | H14: =SUM(E14,G14,-F14) -> 0 | J14: =H14+I14 -> 0 | L14: =J14+K14 -> 0
A15: 10 | H15: =SUM(E15,G15,-F15) -> 0 | J15: =H15+I15 -> 0 | L15: =J15+K15 -> 0
A16: 11 | H16: =SUM(E16,G16,-F16) -> 0 | J16: =H16+I16 -> 0 | L16: =J16+K16 -> 0
A17: 12 | H17: =SUM(E17,G17,-F17) -> 0 | J17: =H17+I17 -> 0 | L17: =J17+K17 -> 0
... A74: 69 | H74: =SUM(E74,G74,-F74) -> 0 | J74: =H74+I74 -> 0 | L74: =J74+K74 -> 0
A75: ———— | B75: 合计 | E75: =ROUND(SUM(E6:E74),2) -> 0 | F75: =ROUND(SUM(F6:F74),2) -> 0 | G75: =ROUND(SUM(G6:G74),2) -> 0 | H75: =ROUND(SUM(H6:H74),2) -> 0 | J75: =H75+I75 -> 0 | K75: =ROUND(SUM(K6:K74),2) -> 0 | L75: =J75+K75 -> 0 | N75: =ROUND(SUM(N6:N74),2) -> 0
B77: 审计说明：

Sheet 长期股权投资
A1: 长期股权投资审定表
A2: =备忘录!$A$1 -> 被审计单位：福禄福擎网络科技有限公司 | D2: 编制人：刘喜琴 | G2: =备忘录!$C$2 -> 日期：2025/10/30
A3: =备忘录!$A$2 -> 财务报表截止日：2025/9/30 | D3: 复核人：赵玮 | G3: =备忘录!$C$3 -> 日期：2025/10/31
A4: 项目名称 | B4: 账面数据
B5: 期初金额 | C5: 本期借方 | D5: 本期贷方 | E5: 期末金额 | F5: 企业调整 | G5: 期末报表列报
A6: 一、账面余额 | B6: =ROUND(SUM(B7:B9),2) -> 0 | C6: =ROUND(SUM(C7:C9),2) -> 0 | D6: =ROUND(SUM(D7:D9),2) -> 0 | E6: =ROUND(SUM(E7:E9),2) -> 0 | F6: =ROUND(SUM(F7:F9),2) -> 0 | G6: =ROUND(SUM(G7:G9),2) -> 0
A7: 对子公司的股资 | E7: =B7+C7-D7 -> 0 | G7: =E7+F7 -> 0
A8: 对合营企业的投资 | E8: =B8+C8-D8 -> 0 | G8: =E8+F8 -> 0
A9: 对联营企业的投资 | E9: =B9+C9-D9 -> 0 | G9: =E9+F9 -> 0
A10: 二、减值准备 | B10: =ROUND(SUM(B11:B13),2) -> 0 | C10: =ROUND(SUM(C11:C13),2) -> 0 | D10: =ROUND(SUM(D11:D13),2) -> 0 | E10: =ROUND(SUM(E11:E13),2) -> 0 | F10: =ROUND(SUM(F11:F13),2) -> 0 | G10: =ROUND(SUM(G11:G13),2) -> 0
A11: 对子公司的股资 | E11: =B11-C11+D11 -> 0 | G11: =E11+F11 -> 0
A12: 对合营企业的投资 | E12: =B12-C12+D12 -> 0 | G12: =E12+F12 -> 0
A13: 对联营企业的投资 | E13: =B13-C13+D13 -> 0 | G13: =E13+F13 -> 0
A14: 三、账面净额 | B14: =ROUND(B6-B10,2) -> 0 | C14: =ROUND(C6-C10,2) -> 0 | D14: =ROUND(D6-D10,2) -> 0 | E14: =ROUND(E6-E10,2) -> 0 | F14: =ROUND(F6-F10,2) -> 0 | G14: =ROUND(G6-G10,2) -> 0

Sheet 长期股权投资明细表
A1: 长期股权投资明细表-子公司
A2: =备忘录!$A$1 -> 被审计单位：福禄福擎网络科技有限公司 | G2: 编制人：刘喜琴 | L2: =备忘录!$C$2 -> 日期：2025/10/30
A3: =备忘录!$A$2 -> 财务报表截止日：2025/9/30 | G3: 复核人：赵玮 | L3: =备忘录!$C$3 -> 日期：2025/10/31
A4: 一、基本情况 | O4: 重要性标准： | Q4: 重要性标准说明：
A5: 子公司名称 | B5: 主要经营地 | C5: 注册地 | D5: 业务性质 | E5: 期初持股比例（%） | G5: 持股比例本期变动（%） | I5: 期末持股比例（%） | K5: 最初投资方式（取得方式） | L5: 最初投资时间 | M5: 投资意图 | N5: 期末被投资单位所有者权益账面价值 | O5: 期末被审计单位享有被投资单位所有权权益账面价值的份额 | P5: 期末累计少数股东权益 | Q5: 是否属于重要非全资子公司 | R5: 初始投资成本 | S5: 本期收到的现金红利 | T5: 获取的投资协议、公司章程、营业执照、组织架构代码证等文件索引 | U5: 备注
E6: 直接 | F6: 间接 | G6: 直接 | H6: 间接 | I6: 直接 | J6: 间接
I7: =ROUND(E7+G7,2) -> 0 | J7: =ROUND(F7+H7,2) -> 0 | P7: =N7-O7 -> 0 | Q7: 不重要

Sheet 应付职工薪酬
A1: 应付职工薪酬明细表
A2: =备忘录!$A$1 -> 被审计单位：福禄福擎网络科技有限公司 | D2: 编制人：刘喜琴 | G2: =备忘录!$C$2 -> 日期：2025/10/30
A3: =备忘录!$A$2 -> 财务报表截止日：2025/9/30 | D3: 复核人：赵玮 | G3: =备忘录!$C$3 -> 日期：2025/10/31
A4: 项目名称 | B4: 未审数 | H4: 本期审计调整 | J4: 期末报表列报审定
B5: 期初金额 | C5: 本期借方 | D5: 本期贷方 | E5: 期末金额 | F5: 企业调整 | G5: 期末报表列报 | H5: 本期借方 | I5: 本期贷方 | J5: 期初金额 | K5: 本期借方 | L5: 本期贷方 | M5: 期末数
A6: 一、短期薪酬小计 | B6: =ROUND(SUM(B7:B9,B14:B16),2) -> 0 | C6: =ROUND(SUM(C7:C9,C14:C16),2) -> 0 | D6: =ROUND(SUM(D7:D9,D14:D16),2) -> 0 | E6: =ROUND(SUM(E7:E9,E14:E16),2) -> 0 | F6: =ROUND(SUM(F7:F9,F14:F16),2) -> 0 | G6: =ROUND(SUM(G7:G9,G14:G16),2) -> 0 | J6: =ROUND(SUM(J7:J9,J14:J16),2) -> 0 | K6: =ROUND(SUM(K7:K9,K14:K16),2) -> 0 | L6: =ROUND(SUM(L7:L9,L14:L16),2) -> 0 | M6: =ROUND(SUM(M7:M9,M14:M16),2) -> 0
A7: 工资、奖金、津贴和补贴 | E7: =ROUND(B7-C7+D7,2) -> 0 | G7: =ROUND(SUM(E7:F7),2) -> 0 | J7: =B7 -> 0 | K7: =C7+H7 -> 0 | L7: =D7+I7 -> 0 | M7: =J7+L7-K7 -> 0
A8: 职工福利费 | E8: =ROUND(B8-C8+D8,2) -> 0 | G8: =ROUND(SUM(E8:F8),2) -> 0 | J8: =B8 -> 0 | K8: =C8+H8 -> 0 | L8: =D8+I8 -> 0 | M8: =J8+L8-K8 -> 0
A9: 社会保险费 | B9: =ROUND(SUM(B10:B13),2) -> 0 | C9: =ROUND(SUM(C10:C13),2) -> 0 | D9: =ROUND(SUM(D10:D13),2) -> 0 | E9: =ROUND(SUM(E10:E13),2) -> 0 | F9: =ROUND(SUM(F10:F13),2) -> 0 | G9: =ROUND(SUM(G10:G13),2) -> 0 | J9: =ROUND(SUM(J10:J13),2) -> 0 | K9: =ROUND(SUM(K10:K13),2) -> 0 | L9: =ROUND(SUM(L10:L13),2) -> 0 | M9: =ROUND(SUM(M10:M13),2) -> 0
A10: 其中：基本医疗保险费 | E10: =ROUND(B10-C10+D10,2) -> 0 | G10: =ROUND(SUM(E10:F10),2) -> 0 | J10: =B10 -> 0 | K10: =C10+H10 -> 0 | L10: =D10+I10 -> 0 | M10: =J10+L10-K10 -> 0
A11: 补充医疗保险费 | E11: =ROUND(B11-C11+D11,2) -> 0 | G11: =ROUND(SUM(E11:F11),2) -> 0 | J11: =B11 -> 0 | K11: =C11+H11 -> 0 | L11: =D11+I11 -> 0 | M11: =J11+L11-K11 -> 0
A12: 工伤保险费 | E12: =ROUND(B12-C12+D12,2) -> 0 | G12: =ROUND(SUM(E12:F12),2) -> 0 | J12: =B12 -> 0 | K12: =C12+H12 -> 0 | L12: =D12+I12 -> 0 | M12: =J12+L12-K12 -> 0
A13: 生育保险费 | E13: =ROUND(B13-C13+D13,2) -> 0 | G13: =ROUND(SUM(E13:F13),2) -> 0 | J13: =B13 -> 0 | K13: =C13+H13 -> 0 | L13: =D13+I13 -> 0 | M13: =J13+L13-K13 -> 0
A14: 住房公积金 | E14: =ROUND(B14-C14+D14,2) -> 0 | G14: =ROUND(SUM(E14:F14),2) -> 0 | J14: =B14 -> 0 | K14: =C14+H14 -> 0 | L14: =D14+I14 -> 0 | M14: =J14+L14-K14 -> 0
A15: 工会经费 | E15: =ROUND(B15-C15+D15,2) -> 0 | G15: =ROUND(SUM(E15:F15),2) -> 0 | J15: =B15 -> 0 | K15: =C15+H15 -> 0 | L15: =D15+I15 -> 0 | M15: =J15+L15-K15 -> 0
A16: 职工教育经费 | E16: =ROUND(B16-C16+D16,2) -> 0 | G16: =ROUND(SUM(E16:F16),2) -> 0 | J16: =B16 -> 0 | K16: =C16+H16 -> 0 | L16: =D16+I16 -> 0 | M16: =J16+L16-K16 -> 0
A17: 二、离职后福利—设定提存计划 | B17: =ROUND(SUM(B18:B20),2) -> 0 | C17: =ROUND(SUM(C18:C20),2) -> 0 | D17: =ROUND(SUM(D18:D20),2) -> 0 | E17: =ROUND(SUM(E18:E20),2) -> 0 | F17: =ROUND(SUM(F18:F20),2) -> 0 | G17: =ROUND(SUM(G18:G20),2) -> 0 | J17: =ROUND(SUM(J18:J20),2) -> 0 | K17: =ROUND(SUM(K18:K20),2) -> 0 | L17: =ROUND(SUM(L18:L20),2) -> 0 | M17: =ROUND(SUM(M18:M20),2) -> 0
A18: 基本养老保险 | E18: =ROUND(B18-C18+D18,2) -> 0 | G18: =ROUND(SUM(E18:F18),2) -> 0 | J18: =B18 -> 0 | K18: =C18+H18 -> 0 | L18: =D18+I18 -> 0 | M18: =J18+L18-K18 -> 0
A19: 失业保险费 | E19: =ROUND(B19-C19+D19,2) -> 0 | G19: =ROUND(SUM(E19:F19),2) -> 0 | J19: =B19 -> 0 | K19: =C19+H19 -> 0 | L19: =D19+I19 -> 0 | M19: =J19+L19-K19 -> 0
A20: 企业年金缴费 | E20: =ROUND(B20-C20+D20,2) -> 0 | G20: =ROUND(SUM(E20:F20),2) -> 0 | J20: =B20 -> 0 | K20: =C20+H20 -> 0 | L20: =D20+I20 -> 0 | M20: =J20+L20-K20 -> 0
A21: 三、离职后福利—设定受益计划 | E21: =ROUND(B21-C21+D21,2) -> 0 | G21: =ROUND(SUM(E21:F21),2) -> 0 | J21: =B21 -> 0 | K21: =C21+H21 -> 0 | L21: =D21+I21 -> 0 | M21: =J21+L21-K21 -> 0
A22: 四、辞退福利 | E22: =ROUND(B22-C22+D22,2) -> 0 | G22: =ROUND(SUM(E22:F22),2) -> 0 | J22: =B22 -> 0 | K22: =C22+H22 -> 0 | L22: =D22+I22 -> 0 | M22: =J22+L22-K22 -> 0
A23: 五、一年内到期的长期职工福利 | E23: =ROUND(B23-C23+D23,2) -> 0 | G23: =ROUND(SUM(E23:F23),2) -> 0 | J23: =B23 -> 0 | K23: =C23+H23 -> 0 | L23: =D23+I23 -> 0 | M23: =J23+L23-K23 -> 0
A24: 合计 | B24: =ROUND(SUM(B6+B17+B22+B23),2) -> 0 | C24: =ROUND(SUM(C6+C17+C22+C23),2) -> 0 | D24: =ROUND(SUM(D6+D17+D22+D23),2) -> 0 | E24: =ROUND(SUM(E6+E17+E22+E23),2) -> 0 | F24: =ROUND(SUM(F6+F17+F22+F23),2) -> 0 | G24: =ROUND(SUM(G6+G17+G22+G23),2) -> 0 | H24: =SUM(H6:H23) -> 0 | I24: =SUM(I6:I23) -> 0 | J24: =ROUND(SUM(J6+J17+J22+J23),2) -> 0 | K24: =ROUND(SUM(K6+K17+K22+K23),2) -> 0 | L24: =ROUND(SUM(L6+L17+L22+L23),2) -> 0 | M24: =ROUND(SUM(M6+M17+M22+M23),2) -> 0
A26: 审计说明：

Sheet 应付职工薪酬检查表
A1: 应付职工薪酬分配检查情况表
A2: =备忘录!$A$1 -> 被审计单位：福禄福擎网络科技有限公司 | C2: 编制人：刘喜琴 | F2: =备忘录!$C$2 -> 日期：2025/10/30
A3: =备忘录!$A$2 -> 财务报表截止日：2025/9/30 | C3: 复核人：赵玮 | F3: =备忘录!$C$3 -> 日期：2025/10/31
A4: 项目名称 | B4: 主营业务成本 | C4: 销售费用 | D4: 管理费用 | E4: 合计 | F4: 检查本期分配是否正确 | G4: 差异
A6: 一、短期薪酬小计 | B6: =ROUND(SUM(B7:B12),2) -> 0 | C6: =ROUND(SUM(C7:C12),2) -> 0 | D6: =ROUND(SUM(D7:D12),2) -> 0 | E6: =SUM(E7:E12) -> 0
A7: 工资、奖金、津贴和补贴 | E7: =B7+C7+D7 -> 0
A8: 职工福利费 | E8: =B8+C8+D8 -> 0
A9: 社会保险费 | E9: =B9+C9+D9 -> 0
A10: 住房公积金 | E10: =B10+C10+D10 -> 0
A11: 工会经费 | E11: =B11+C11+D11 -> 0
A12: 职工教育经费 | E12: =B12+C12+D12 -> 0
A13: 二、离职后福利—设定提存计划 | B13: =ROUND(SUM(B14:B16),2) -> 0 | C13: =ROUND(SUM(C14:C16),2) -> 0 | D13: =ROUND(SUM(D14:D16),2) -> 0 | E13: =ROUND(SUM(E14:E16),2) -> 0
A14: 基本养老保险 | E14: =B14+C14+D14 -> 0
A15: 失业保险费 | E15: =B15+C15+D15 -> 0
A16: 企业年金缴费 | E16: =B16+C16+D16 -> 0
A17: 三、离职后福利—设定受益计划 | E17: =B17+C17+D17 -> 0
A18: 四、辞退福利 | E18: =B18+C18+D18 -> 0
A19: 五、一年内到期的长期职工福利 | E19: =B19+C19+D19 -> 0
A20: 合计 | B20: =ROUND(SUM(B6+B13+B18+B19),2) -> 0 | C20: =ROUND(SUM(C6+C13+C18+C19),2) -> 0 | D20: =ROUND(SUM(D6+D13+D18+D19),2) -> 0 | E20: =ROUND(SUM(E6+E13+E18+E19),2) -> 0
A22: 审计说明：
D24: 借：其他应付款
D25: 贷：银行存款
D27: 借：应付职工薪酬
D28: 贷：其他应付款

Sheet 应交税费
A1: 应交税费明细表
A2: =备忘录!$A$1 -> 被审计单位：福禄福擎网络科技有限公司 | D2: 编制人：刘喜琴 | G2: =备忘录!$C$2 -> 日期：2025/10/30
A3: =备忘录!$A$2 -> 财务报表截止日：2025/9/30 | D3: 复核人：赵玮 | G3: =备忘录!$C$3 -> 日期：2025/10/31
A4: 科目名称 | B4: 账面数据 | F4: 本期审计调整 | H4: 期末报表列报审定
B5: 期初金额（取数为：科目余额表期初贷方-借方） | C5: 本期借方 | D5: 本期贷方 | E5: 期末金额 | F5: 本期借方 | G5: 本期贷方 | H5: 期初金额 | I5: 本期借方 | J5: 本期贷方 | K5: 期末数
A6: 增值税 | E6: =ROUND(B6+D6-C6,2) -> 0 | H6: =B6 -> 0 | I6: =ROUND(C6+F6,2) -> 0 | J6: =ROUND(D6+G6,2) -> 0 | K6: =ROUND(H6+J6-I6,2) -> 0
A7: 个人所得税 | E7: =ROUND(B7+D7-C7,2) -> 0 | H7: =B7 -> 0 | I7: =ROUND(C7+F7,2) -> 0 | J7: =ROUND(D7+G7,2) -> 0 | K7: =ROUND(H7+J7-I7,2) -> 0
A8: 企业所得税 | E8: =ROUND(B8+D8-C8,2) -> 0 | H8: =B8 -> 0 | I8: =ROUND(C8+F8,2) -> 0 | J8: =ROUND(D8+G8,2) -> 0 | K8: =ROUND(H8+J8-I8,2) -> 0
A9: 城市维护建设税 | E9: =ROUND(B9+D9-C9,2) -> 0 | H9: =B9 -> 0 | I9: =ROUND(C9+F9,2) -> 0 | J9: =ROUND(D9+G9,2) -> 0 | K9: =ROUND(H9+J9-I9,2) -> 0
A10: 教育费附加 | E10: =ROUND(B10+D10-C10,2) -> 0 | H10: =B10 -> 0 | I10: =ROUND(C10+F10,2) -> 0 | J10: =ROUND(D10+G10,2) -> 0 | K10: =ROUND(H10+J10-I10,2) -> 0
A11: 地方教育费附加 | E11: =ROUND(B11+D11-C11,2) -> 0 | H11: =B11 -> 0 | I11: =ROUND(C11+F11,2) -> 0 | J11: =ROUND(D11+G11,2) -> 0 | K11: =ROUND(H11+J11-I11,2) -> 0
A12: 印花税 | E12: =ROUND(B12+D12-C12,2) -> 0 | H12: =B12 -> 0 | I12: =ROUND(C12+F12,2) -> 0 | J12: =ROUND(D12+G12,2) -> 0 | K12: =ROUND(H12+J12-I12,2) -> 0
E13: =ROUND(B13+D13-C13,2) -> 0 | H13: =B13 -> 0 | I13: =ROUND(C13+F13,2) -> 0 | J13: =ROUND(D13+G13,2) -> 0 | K13: =ROUND(H13+J13-I13,2) -> 0
E14: =ROUND(B14+D14-C14,2) -> 0 | H14: =B14 -> 0 | I14: =ROUND(C14+F14,2) -> 0 | J14: =ROUND(D14+G14,2) -> 0 | K14: =ROUND(H14+J14-I14,2) -> 0
E15: =ROUND(B15+D15-C15,2) -> 0 | H15: =B15 -> 0 | I15: =ROUND(C15+F15,2) -> 0 | J15: =ROUND(D15+G15,2) -> 0 | K15: =ROUND(H15+J15-I15,2) -> 0
E16: =ROUND(B16+D16-C16,2) -> 0 | H16: =B16 -> 0 | I16: =ROUND(C16+F16,2) -> 0 | J16: =ROUND(D16+G16,2) -> 0 | K16: =ROUND(H16+J16-I16,2) -> 0
E17: =ROUND(B17+D17-C17,2) -> 0 | H17: =B17 -> 0 | I17: =ROUND(C17+F17,2) -> 0 | J17: =ROUND(D17+G17,2) -> 0 | K17: =ROUND(H17+J17-I17,2) -> 0
E18: =ROUND(B18+D18-C18,2) -> 0 | H18: =B18 -> 0 | I18: =ROUND(C18+F18,2) -> 0 | J18: =ROUND(D18+G18,2) -> 0 | K18: =ROUND(H18+J18-I18,2) -> 0
E19: =ROUND(B19+D19-C19,2) -> 0 | H19: =B19 -> 0 | I19: =ROUND(C19+F19,2) -> 0 | J19: =ROUND(D19+G19,2) -> 0 | K19: =ROUND(H19+J19-I19,2) -> 0
A20: 合计 | B20: =ROUND(SUM(B6:B19),2) -> 0 | C20: =ROUND(SUM(C6:C19),2) -> 0 | D20: =ROUND(SUM(D6:D19),2) -> 0 | E20: =ROUND(SUM(E6:E19),2) -> 0 | F20: =ROUND(SUM(F6:F19),2) -> 0 | G20: =ROUND(SUM(G6:G19),2) -> 0 | H20: =ROUND(SUM(H6:H19),2) -> 0 | I20: =ROUND(SUM(I6:I19),2) -> 0 | ... K20: =ROUND(SUM(K6:K19),2) -> 0
B23: 审计说明：
A25: 增值税
A26: 企业所得税
A27: 个人所得税
A28: 城市维护建设税
A29: 教育费附加
A30: 地方教育费附加
A31: 印花税

Sheet 应交增值税明细表
A1: 应交税费明细表
A2: =备忘录!$A$1 -> 被审计单位：福禄福擎网络科技有限公司 | C2: 编制人：刘喜琴 | E2: =备忘录!$C$2 -> 日期：2025/10/30
A3: =备忘录!$A$2 -> 财务报表截止日：2025/9/30 | C3: 复核人：赵玮 | E3: =备忘录!$C$3 -> 日期：2025/10/31 | G3: 账面收入总额
A4: 项目 | B4: 账面数 | C4: 申报数 | D4: 差异 | E4: 审计说明 | G4: 增值税申报表销售总额
A5: 一、应交增值税 | D5: —— | G5: 所得税申报表收入总额
A6: 1．年初未抵扣数(用“-”反映) | D6: =ROUND(B6-C6,2) -> 0 | G6: 账面利润总额
A7: 2．销项税额 | D7: =ROUND(B7-C7,2) -> 0 | G7: 所得税申报表利润总额
A8: 出口退税 | D8: =ROUND(B8-C8,2) -> 0 | G8: 增值税与账面差异 | H8: =H3-H4 -> 0
A9: 进项税额转出 | D9: =ROUND(B9-C9,2) -> 0 | G9: 所得税与账面差异 | H9: =H3-H5 -> 0
A10: 转出多交增值税 | D10: =ROUND(B10-C10,2) -> 0 | G10: 利润与账面差异 | H10: =H6-H7 -> 0
A11: 3．进项税额 | D11: =ROUND(B11-C11,2) -> 0
A12: 已交税金 | D12: =ROUND(B12-C12,2) -> 0
A13: 减免税款 | D13: =ROUND(B13-C13,2) -> 0
A14: 销项税额抵减 | D14: =ROUND(B14-C14,2) -> 0
A15: 出口抵减内销产品应纳税额 | D15: =ROUND(B15-C15,2) -> 0
A16: 出口退税 | D16: =ROUND(B16-C16,2) -> 0
A17: 转出未交增值税 | B17: =B6+B7+B9+B10-B11-B13 -> 0 | C17: =C6+C7+C9-C11-C13 -> 0 | D17: =ROUND(B17-C17,2) -> 0 | E17: =E6+E7+E9+E10-E11-E13 -> 0
A18: 4．期末未抵扣数(多交数用“-”反映) | B18: =B6+B7+B8+B9+B10-B11-B12-B13-B17 -> 0 | C18: =C6+C7+C8+C9+C10-C11-C12-C13-C17 -> 0 | D18: =ROUND(B18-C18,2) -> 0
A19: 二、未交增值税 | B19: —— | C19: —— | D19: —— | E19: ——
A20: 1．年初未交数(多交数以“-”反映) | D20: =ROUND(B20-C20,2) -> 0
A21: 2．本期转入数(多交数以“-”反映) | D21: =ROUND(B21-C21,2) -> 0
A22: 3．本期已交数 | D22: =ROUND(B22-C22,2) -> 0
A23: 4．期末未交数(多交数以“-”反映) | B23: =ROUND(B20+B21-B22,2) -> 0 | C23: =ROUND(C20+C21-C22,2) -> 0 | D23: =ROUND(D20+D21-D22,2) -> 0 | E23: =ROUND(E20+E21-E22,2) -> 0
A24: 三、预交增值税 | B24: —— | C24: —— | D24: —— | E24: ——
A25: 1．年初预交增值税余额 | D25: =ROUND(B25-C25,2) -> 0
A26: 2．本期新增预交增值税 | D26: =ROUND(B26-C26,2) -> 0
A27: 3．预交增值税本期转出 | D27: =ROUND(B27-C27,2) -> 0
A28: 4．年末预交增值税余额 | B28: =ROUND(B25+B26-B27,2) -> 0 | C28: =ROUND(C25+C26-C27,2) -> 0 | D28: =ROUND(D25+D26-D27,2) -> 0 | E28: =ROUND(E25+E26-E27,2) -> 0
A29: 四、待抵扣进项税额 | B29: —— | C29: —— | D29: —— | E29: ——
A30: 1．年初待抵扣进项税额余额 | D30: =ROUND(B30-C30,2) -> 0
A31: 2．本期新增待抵扣进项税额 | D31: =ROUND(B31-C31,2) -> 0
A32: 3．待抵扣进项税额本期转出 | D32: =ROUND(B32-C32,2) -> 0
A33: 4．年末待抵扣进项税额余额 | B33: =ROUND(B30+B31-B32,2) -> 0 | C33: =ROUND(C30+C31-C32,2) -> 0 | D33: =ROUND(D30+D31-D32,2) -> 0 | E33: =ROUND(E30+E31-E32,2) -> 0
A34: 五、待认证进项税额 | B34: —— | C34: —— | D34: —— | E34: ——
A35: 1．年初待认证进项税额余额 | D35: =ROUND(B35-C35,2) -> 0
A36: 2．本期新增待认证进项税额 | D36: =ROUND(B36-C36,2) -> 0
A37: 3．待认证进项税额本期抵扣转出 | D37: =ROUND(B37-C37,2) -> 0
A38: 4．年末待认证进项税额余额 | B38: =ROUND(B35+B36-B37,2) -> 0 | C38: =ROUND(C35+C36-C37,2) -> 0 | D38: =ROUND(D35+D36-D37,2) -> 0 | E38: =ROUND(E35+E36-E37,2) -> 0
A39: 六、待转销项税额 | B39: —— | C39: —— | D39: —— | E39: ——
A40: 1．年初待转销项税额余额 | D40: =ROUND(B40-C40,2) -> 0
A41: 2．本期新增转销项税额 | D41: =ROUND(B41-C41,2) -> 0
A42: 3．本期确认销项税额转出 | D42: =ROUND(B42-C42,2) -> 0
A43: 4．年末待转销项税额余额 | B43: =ROUND(B40+B41-B42,2) -> 0 | C43: =ROUND(C40+C41-C42,2) -> 0 | D43: =ROUND(D40+D41-D42,2) -> 0 | E43: =ROUND(E40+E41-E42,2) -> 0
A44: 七、增值税留抵税额 | B44: —— | C44: —— | D44: —— | E44: ——
A45: 1．年初待转销项税额余额 | D45: =ROUND(B45-C45,2) -> 0
A46: 3．本期抵扣留抵税额转出 | D46: =ROUND(B46-C46,2) -> 0
A47: 1．年末待转销项税额余额 | B47: =ROUND(B45-B46,2) -> 0 | C47: =ROUND(C45-C46,2) -> 0 | D47: =ROUND(D45-D46,2) -> 0 | E47: =ROUND(E45-E46,2) -> 0
A48: 八、简易计税 | B48: —— | C48: —— | D48: —— | E48: ——
A49: 1．年初余额 | D49: =ROUND(B49-C49,2) -> 0
A50: 2．本期计得增值税 | D50: =ROUND(B50-C50,2) -> 0
A51: 3．本期扣减增值税 | D51: =ROUND(B51-C51,2) -> 0
A52: 3．本期预缴(缴纳）增值税 | D52: =ROUND(B52-C52,2) -> 0
A53: 4．年末余额 | B53: =ROUND(B49+B50-B51-B52,2) -> 0 | C53: =ROUND(C49+C50-C51-C52,2) -> 0 | D53: =ROUND(D49+D50-D51-D52,2) -> 0 | E53: =ROUND(E49+E50-E51-E52,2) -> 0
A54: 九、转让金融商品应交增值税 | B54: —— | C54: —— | D54: —— | E54: ——
A55: 1．年初余额 | D55: =ROUND(B55-C55,2) -> 0
A56: 2．本期计得增值税 | D56: =ROUND(B56-C56,2) -> 0
A57: 3．本期预缴(缴纳）增值税 | D57: =ROUND(B57-C57,2) -> 0
A58: 4．年末余额 | B58: =ROUND(B55+B56-B57,2) -> 0 | C58: =ROUND(C55+C56-C57,2) -> 0 | D58: =ROUND(D55+D56-D57,2) -> 0 | E58: =ROUND(E55+E56-E57,2) -> 0
A59: 十、代扣代交增值税
A61: 审计说明：

Sheet 短期借款
A1: 短期借款明细表
A2: =备忘录!$A$1 -> 被审计单位：福禄福擎网络科技有限公司 | G2: 编制人：刘喜琴 | M2: =备忘录!$C$2 -> 日期：2025/10/30
A3: =备忘录!$A$2 -> 财务报表截止日：2025/9/30 | G3: 复核人：赵玮 | M3: =备忘录!$C$3 -> 日期：2025/10/31
C4: 本期起息日 | D4: 45962
C5: 本期计息截止日： | D5: 46325
A6: 序号 | B6: 贷款银行 （按单笔借款填列） | C6: 借款期限 | F6: 期初金额 | G6: 本期借方 | H6: 本期贷方 | I6: 期末金额 | J6: 利息测算 | O6: 借款合同编号 | P6: 借款条件 | Q6: 借款用途 | R6: 担保/抵押/质押合同编号 | S6: 合同信息是否与明细表信息相符
C7: 借款日 | D7: 约定还款日 | E7: 贷款利率(%) | J7: 起息日 | K7: 结算日 | L7: 本期应计利息 | M7: 本期实计利息 | N7: 差异
A8: 1 | J8: =MAX($D$4,C8) -> 45962 | K8: =IF($D$5>D8,MIN($D$5,D8),$D$5) -> 46325 | L8: =MAX(F8,I8,H8)*E8*(K8-J8+1)/365 -> 0 | N8: =M8-L8 -> 0

Sheet 营业收入
A1: 营业收入明细表
A2: =备忘录!$A$1 -> 被审计单位：福禄福擎网络科技有限公司 | D2: 编制人：刘喜琴 | F2: =备忘录!$C$2 -> 日期：2025/10/30
A3: =备忘录!A3 -> 财务报表期间：2025.1-2025.9 | D3: 复核人：赵玮 | F3: =备忘录!$C$3 -> 日期：2025/10/31
A4: 科目名称 | B4: 核算项目1 | C4: 核算项目2 | D4: 本期发生额 | E4: 上期发生额 | F4: 本期与上期的金额变化 | H4: 备注
F5: 增减额 | G5: 变动率
A6: 一、主营业务收入
A7: 主营业务收入_销售收入_销售收入-6% | B7: 商品大类:网娱 | C7: 平台:抖音+WPS网络会员专卖店 | F7: =_wpsfn.ROUNDBANK(D7-E7,2) -> 0 | G7: =IF(E7=0,0,F7/E7) -> 0
A8: 主营业务收入_销售收入_销售收入-6% | B8: 商品大类:网娱 | C8: 平台:福禄开放平台 | F8: =_wpsfn.ROUNDBANK(D8-E8,2) -> 0 | G8: =IF(E8=0,0,F8/E8) -> 0
A9: 主营业务收入_销售收入_销售收入-6% | B9: 商品大类:卡券 | C9: 平台:福禄开放平台 | F9: =_wpsfn.ROUNDBANK(D9-E9,2) -> 0 | G9: =IF(E9=0,0,F9/E9) -> 0
A10: 主营业务收入_技术服务收入_佣金服务 | B10: 商品大类:网娱 | F10: =_wpsfn.ROUNDBANK(D10-E10,2) -> 0 | G10: =IF(E10=0,0,F10/E10) -> 0
A11: 主营业务收入_技术服务收入_平台服务 | B11: 商品大类:网娱 | F11: =_wpsfn.ROUNDBANK(D11-E11,2) -> 0 | G11: =IF(E11=0,0,F11/E11) -> 0
A12: 主营业务收入_技术服务收入_代运营服务 | B12: 商品大类:网娱 | F12: =_wpsfn.ROUNDBANK(D12-E12,2) -> 0 | G12: =IF(E12=0,0,F12/E12) -> 0
F13: =_wpsfn.ROUNDBANK(D13-E13,2) -> 0 | G13: =IF(E13=0,0,F13/E13) -> 0
F14: =_wpsfn.ROUNDBANK(D14-E14,2) -> 0 | G14: =IF(E14=0,0,F14/E14) -> 0
F15: =_wpsfn.ROUNDBANK(D15-E15,2) -> 0 | G15: =IF(E15=0,0,F15/E15) -> 0
F16: =_wpsfn.ROUNDBANK(D16-E16,2) -> 0 | G16: =IF(E16=0,0,F16/E16) -> 0
F17: =_wpsfn.ROUNDBANK(D17-E17,2) -> 0 | G17: =IF(E17=0,0,F17/E17) -> 0
F18: =_wpsfn.ROUNDBANK(D18-E18,2) -> 0 | G18: =IF(E18=0,0,F18/E18) -> 0
A19: 小计 | D19: =SUM(D7:D18) -> 0 | E19: =SUM(E7:E18) -> 0 | F19: =SUM(F7:F18) -> 0
A20: 二、其他业务收入
A21: 其他 | F21: =_wpsfn.ROUNDBANK(D21-E21,2) -> 0 | G21: =IF(E21=0,0,F21/E21) -> 0
F22: =_wpsfn.ROUNDBANK(D22-E22,2) -> 0 | G22: =IF(E22=0,0,F22/E22) -> 0
A23: 小计 | D23: =SUM(D21:D22) -> 0 | E23: =SUM(E21:E22) -> 0 | F23: =SUM(F21:F22) -> 0
A24: 营业收入合计 | D24: =D19+D23 -> 0 | E24: =E19+E23 -> 0 | F24: =F19+F23 -> 0
A26: 审计说明：

Sheet 营业成本
A1: 营业成本明细表
A2: =备忘录!$A$1 -> 被审计单位：福禄福擎网络科技有限公司 | D2: 编制人：刘喜琴 | G2: =备忘录!$C$2 -> 日期：2025/10/30
A3: =备忘录!A3 -> 财务报表期间：2025.1-2025.9 | D3: 复核人：赵玮 | G3: =备忘录!$C$3 -> 日期：2025/10/31
A4: 科目名称 | B4: 核算项目1 | C4: 核算项目2 | D4: 本期发生额 | E4: 上期发生额 | F4: 本期与上期的金额变化 | H4: 备注
F5: 增减额 | G5: 变动率
A6: 一、主营业务成本
A7: 主营业务成本_销售成本_销售成本-6% | B7: 商品大类:网娱 | C7: 平台:抖音+WPS网络会员专卖店 | D7: 1971.42 | F7: =_wpsfn.ROUNDBANK(D7-E7,2) -> 1971.42 | G7: =IF(E7=0,0,F7/E7) -> 0
A8: 主营业务成本_销售成本_销售成本-6% | B8: 商品大类:网娱 | C8: 平台:福禄开放平台 | D8: 116868.97 | F8: =_wpsfn.ROUNDBANK(D8-E8,2) -> 116868.97 | G8: =IF(E8=0,0,F8/E8) -> 0
A9: 主营业务成本_销售成本_销售成本-6% | B9: 商品大类:卡券 | C9: 平台:福禄开放平台 | D9: 100381.97 | F9: =_wpsfn.ROUNDBANK(D9-E9,2) -> 100381.97 | G9: =IF(E9=0,0,F9/E9) -> 0
A10: 主营业务成本_工资性支出_员工工资 | D10: 1261609.1 | F10: =_wpsfn.ROUNDBANK(D10-E10,2) -> 1261609.1 | G10: =IF(E10=0,0,F10/E10) -> 0
A11: 主营业务成本_工资性支出_员工社保 | D11: 121578.3 | F11: =_wpsfn.ROUNDBANK(D11-E11,2) -> 121578.3 | G11: =IF(E11=0,0,F11/E11) -> 0
A12: 主营业务成本_工资性支出_员工公积金 | D12: 17951.2 | F12: =_wpsfn.ROUNDBANK(D12-E12,2) -> 17951.2 | G12: =IF(E12=0,0,F12/E12) -> 0
A13: 主营业务成本_技术服务成本 _代运营服务费 | B13: 商品大类:网娱 | D13: 15834139 | F13: =_wpsfn.ROUNDBANK(D13-E13,2) -> 15834139 | G13: =IF(E13=0,0,F13/E13) -> 0
A14: 主营业务成本_技术服务成本 _代运营服务费 | B14: 商品大类:卡券 | D14: 7288.49 | F14: =_wpsfn.ROUNDBANK(D14-E14,2) -> 7288.49 | G14: =IF(E14=0,0,F14/E14) -> 0
A15: 主营业务成本_技术服务成本 _平台服务成本 | B15: 商品大类:网娱 | D15: 2598796.6 | F15: =_wpsfn.ROUNDBANK(D15-E15,2) -> 2598796.6 | G15: =IF(E15=0,0,F15/E15) -> 0
F16: =_wpsfn.ROUNDBANK(D16-E16,2) -> 0 | G16: =IF(E16=0,0,F16/E16) -> 0
F17: =_wpsfn.ROUNDBANK(D17-E17,2) -> 0 | G17: =IF(E17=0,0,F17/E17) -> 0
F18: =_wpsfn.ROUNDBANK(D18-E18,2) -> 0 | G18: =IF(E18=0,0,F18/E18) -> 0
A19: 小计 | D19: =SUM(D7:D18) -> 20060585 | E19: =SUM(E7:E18) -> 0 | F19: =SUM(F6:F18) -> 20060585
A20: 二、其他业务成本
F21: =_wpsfn.ROUNDBANK(D21-E21,2) -> 0 | G21: =IF(E21=0,0,F21/E21) -> 0
F22: =_wpsfn.ROUNDBANK(D22-E22,2) -> 0 | G22: =IF(E22=0,0,F22/E22) -> 0
A23: 小计 | D23: =SUM(D21:D22) -> 0 | E23: =SUM(E21:E22) -> 0 | F23: =SUM(F21:F22) -> 0
A24: 营业成本合计 | D24: =D19+D23 -> 20060585 | E24: =E19+E23 -> 0 | F24: =F19+F23 -> 20060585
A27: 审计说明：

Sheet 毛利率分析表
A1: 主营业务收入月度毛利率分析表
A2: =备忘录!$A$1 -> 被审计单位：福禄福擎网络科技有限公司 | I2: 编制人：刘喜琴 | P2: =备忘录!$C$2 -> 日期：2025/10/30
A3: =备忘录!A3 -> 财务报表期间：2025.1-2025.9 | I3: 复核人：赵玮 | P3: =备忘录!$C$3 -> 日期：2025/10/31
A4: 月份 | B4: 本期数 | G4: 上期数 | L4: 变动额 | O4: 变动率 | T4: 备注
B5: 主营业务收入 | C5: 主营业务成本 | D5: 月度销售收入占比 | E5: 毛利 | F5: 毛利率 | G5: 主营业务收入 | H5: 主营业务成本 | I5: 月度销售收入占比 | J5: 毛利 | K5: 毛利率 | L5: 主营业务收入 | M5: 主营业务成本 | N5: 毛利 | O5: 主营业务收入 | P5: 主营业务成本 | Q5: 毛利 | R5: 月度销售收入占比 | S5: 毛利率
A6: 1 | D6: =IF(B6=0,0,B6/$B$18) -> 0 | E6: =B6-C6 -> 0 | F6: =IF(B6-C6=0,0,(B6-C6)/B6) -> 0 | I6: =IF(G6=0,0,G6/$G$18) -> 0 | J6: =G6-H6 -> 0 | K6: =IF(G6-H6=0,0,(G6-H6)/G6) -> 0 | L6: =B6-G6 -> 0 | M6: =C6-H6 -> 0 | N6: =E6-J6 -> 0 | O6: =IF(L6=0,0,L6/G6) -> 0 | P6: =IF(M6=0,0,M6/H6) -> 0 | Q6: =IF(N6=0,0,N6/J6) -> 0 | R6: =IF(D6-I6=0,0,(D6-I6)/I6) -> 0 | S6: =IF(F6-K6=0,0,(F6-K6)/K6) -> 0
A7: 2 | D7: =IF(B7=0,0,B7/$B$18) -> 0 | E7: =B7-C7 -> 0 | F7: =IF(B7-C7=0,0,(B7-C7)/B7) -> 0 | I7: =IF(G7=0,0,G7/$G$18) -> 0 | J7: =G7-H7 -> 0 | K7: =IF(G7-H7=0,0,(G7-H7)/G7) -> 0 | L7: =B7-G7 -> 0 | M7: =C7-H7 -> 0 | N7: =E7-J7 -> 0 | O7: =IF(L7=0,0,L7/G7) -> 0 | P7: =IF(M7=0,0,M7/H7) -> 0 | Q7: =IF(N7=0,0,N7/J7) -> 0 | R7: =IF(D7-I7=0,0,(D7-I7)/I7) -> 0 | S7: =IF(F7-K7=0,0,(F7-K7)/K7) -> 0
A8: 3 | D8: =IF(B8=0,0,B8/$B$18) -> 0 | E8: =B8-C8 -> 0 | F8: =IF(B8-C8=0,0,(B8-C8)/B8) -> 0 | I8: =IF(G8=0,0,G8/$G$18) -> 0 | J8: =G8-H8 -> 0 | K8: =IF(G8-H8=0,0,(G8-H8)/G8) -> 0 | L8: =B8-G8 -> 0 | M8: =C8-H8 -> 0 | N8: =E8-J8 -> 0 | O8: =IF(L8=0,0,L8/G8) -> 0 | P8: =IF(M8=0,0,M8/H8) -> 0 | Q8: =IF(N8=0,0,N8/J8) -> 0 | R8: =IF(D8-I8=0,0,(D8-I8)/I8) -> 0 | S8: =IF(F8-K8=0,0,(F8-K8)/K8) -> 0
A9: 4 | D9: =IF(B9=0,0,B9/$B$18) -> 0 | E9: =B9-C9 -> 0 | F9: =IF(B9-C9=0,0,(B9-C9)/B9) -> 0 | I9: =IF(G9=0,0,G9/$G$18) -> 0 | J9: =G9-H9 -> 0 | K9: =IF(G9-H9=0,0,(G9-H9)/G9) -> 0 | L9: =B9-G9 -> 0 | M9: =C9-H9 -> 0 | N9: =E9-J9 -> 0 | O9: =IF(L9=0,0,L9/G9) -> 0 | P9: =IF(M9=0,0,M9/H9) -> 0 | Q9: =IF(N9=0,0,N9/J9) -> 0 | R9: =IF(D9-I9=0,0,(D9-I9)/I9) -> 0 | S9: =IF(F9-K9=0,0,(F9-K9)/K9) -> 0
A10: 5 | D10: =IF(B10=0,0,B10/$B$18) -> 0 | E10: =B10-C10 -> 0 | F10: =IF(B10-C10=0,0,(B10-C10)/B10) -> 0 | I10: =IF(G10=0,0,G10/$G$18) -> 0 | J10: =G10-H10 -> 0 | K10: =IF(G10-H10=0,0,(G10-H10)/G10) -> 0 | L10: =B10-G10 -> 0 | M10: =C10-H10 -> 0 | N10: =E10-J10 -> 0 | O10: =IF(L10=0,0,L10/G10) -> 0 | P10: =IF(M10=0,0,M10/H10) -> 0 | Q10: =IF(N10=0,0,N10/J10) -> 0 | R10: =IF(D10-I10=0,0,(D10-I10)/I10) -> 0 | S10: =IF(F10-K10=0,0,(F10-K10)/K10) -> 0
A11: 6 | D11: =IF(B11=0,0,B11/$B$18) -> 0 | E11: =B11-C11 -> 0 | F11: =IF(B11-C11=0,0,(B11-C11)/B11) -> 0 | I11: =IF(G11=0,0,G11/$G$18) -> 0 | J11: =G11-H11 -> 0 | K11: =IF(G11-H11=0,0,(G11-H11)/G11) -> 0 | L11: =B11-G11 -> 0 | M11: =C11-H11 -> 0 | N11: =E11-J11 -> 0 | O11: =IF(L11=0,0,L11/G11) -> 0 | P11: =IF(M11=0,0,M11/H11) -> 0 | Q11: =IF(N11=0,0,N11/J11) -> 0 | R11: =IF(D11-I11=0,0,(D11-I11)/I11) -> 0 | S11: =IF(F11-K11=0,0,(F11-K11)/K11) -> 0
A12: 7 | D12: =IF(B12=0,0,B12/$B$18) -> 0 | E12: =B12-C12 -> 0 | F12: =IF(B12-C12=0,0,(B12-C12)/B12) -> 0 | I12: =IF(G12=0,0,G12/$G$18) -> 0 | J12: =G12-H12 -> 0 | K12: =IF(G12-H12=0,0,(G12-H12)/G12) -> 0 | L12: =B12-G12 -> 0 | M12: =C12-H12 -> 0 | N12: =E12-J12 -> 0 | O12: =IF(L12=0,0,L12/G12) -> 0 | P12: =IF(M12=0,0,M12/H12) -> 0 | Q12: =IF(N12=0,0,N12/J12) -> 0 | R12: =IF(D12-I12=0,0,(D12-I12)/I12) -> 0 | S12: =IF(F12-K12=0,0,(F12-K12)/K12) -> 0
A13: 8 | D13: =IF(B13=0,0,B13/$B$18) -> 0 | E13: =B13-C13 -> 0 | F13: =IF(B13-C13=0,0,(B13-C13)/B13) -> 0 | I13: =IF(G13=0,0,G13/$G$18) -> 0 | J13: =G13-H13 -> 0 | K13: =IF(G13-H13=0,0,(G13-H13)/G13) -> 0 | L13: =B13-G13 -> 0 | M13: =C13-H13 -> 0 | N13: =E13-J13 -> 0 | O13: =IF(L13=0,0,L13/G13) -> 0 | P13: =IF(M13=0,0,M13/H13) -> 0 | Q13: =IF(N13=0,0,N13/J13) -> 0 | R13: =IF(D13-I13=0,0,(D13-I13)/I13) -> 0 | S13: =IF(F13-K13=0,0,(F13-K13)/K13) -> 0
A14: 9 | D14: =IF(B14=0,0,B14/$B$18) -> 0 | E14: =B14-C14 -> 0 | F14: =IF(B14-C14=0,0,(B14-C14)/B14) -> 0 | I14: =IF(G14=0,0,G14/$G$18) -> 0 | J14: =G14-H14 -> 0 | K14: =IF(G14-H14=0,0,(G14-H14)/G14) -> 0 | L14: =B14-G14 -> 0 | M14: =C14-H14 -> 0 | N14: =E14-J14 -> 0 | O14: =IF(L14=0,0,L14/G14) -> 0 | P14: =IF(M14=0,0,M14/H14) -> 0 | Q14: =IF(N14=0,0,N14/J14) -> 0 | R14: =IF(D14-I14=0,0,(D14-I14)/I14) -> 0 | S14: =IF(F14-K14=0,0,(F14-K14)/K14) -> 0
A15: 10 | D15: =IF(B15=0,0,B15/$B$18) -> 0 | E15: =B15-C15 -> 0 | F15: =IF(B15-C15=0,0,(B15-C15)/B15) -> 0 | I15: =IF(G15=0,0,G15/$G$18) -> 0 | J15: =G15-H15 -> 0 | K15: =IF(G15-H15=0,0,(G15-H15)/G15) -> 0 | L15: =B15-G15 -> 0 | M15: =C15-H15 -> 0 | N15: =E15-J15 -> 0 | O15: =IF(L15=0,0,L15/G15) -> 0 | P15: =IF(M15=0,0,M15/H15) -> 0 | Q15: =IF(N15=0,0,N15/J15) -> 0 | R15: =IF(D15-I15=0,0,(D15-I15)/I15) -> 0 | S15: =IF(F15-K15=0,0,(F15-K15)/K15) -> 0
A16: 11 | D16: =IF(B16=0,0,B16/$B$18) -> 0 | E16: =B16-C16 -> 0 | F16: =IF(B16-C16=0,0,(B16-C16)/B16) -> 0 | I16: =IF(G16=0,0,G16/$G$18) -> 0 | J16: =G16-H16 -> 0 | K16: =IF(G16-H16=0,0,(G16-H16)/G16) -> 0 | L16: =B16-G16 -> 0 | M16: =C16-H16 -> 0 | N16: =E16-J16 -> 0 | O16: =IF(L16=0,0,L16/G16) -> 0 | P16: =IF(M16=0,0,M16/H16) -> 0 | Q16: =IF(N16=0,0,N16/J16) -> 0 | R16: =IF(D16-I16=0,0,(D16-I16)/I16) -> 0 | S16: =IF(F16-K16=0,0,(F16-K16)/K16) -> 0
A17: 12 | D17: =IF(B17=0,0,B17/$B$18) -> 0 | E17: =B17-C17 -> 0 | F17: =IF(B17-C17=0,0,(B17-C17)/B17) -> 0 | I17: =IF(G17=0,0,G17/$G$18) -> 0 | J17: =G17-H17 -> 0 | K17: =IF(G17-H17=0,0,(G17-H17)/G17) -> 0 | L17: =B17-G17 -> 0 | M17: =C17-H17 -> 0 | N17: =E17-J17 -> 0 | O17: =IF(L17=0,0,L17/G17) -> 0 | P17: =IF(M17=0,0,M17/H17) -> 0 | Q17: =IF(N17=0,0,N17/J17) -> 0 | R17: =IF(D17-I17=0,0,(D17-I17)/I17) -> 0 | S17: =IF(F17-K17=0,0,(F17-K17)/K17) -> 0
A18: 合计 | B18: =SUM(B6:B17) -> 0 | C18: =SUM(C6:C17) -> 0 | E18: =SUM(E6:E17) -> 0 | G18: =SUM(G6:G17) -> 0 | H18: =SUM(H6:H17) -> 0 | J18: =SUM(J6:J17) -> 0 | L18: =SUM(L6:L17) -> 0 | M18: =SUM(M6:M17) -> 0 | N18: =SUM(N6:N17) -> 0 | O18: =IF(B18-G18=0,0,(B18-G18)/G18) -> 0 | P18: =IF(C18-H18=0,0,(C18-H18)/H18) -> 0 | Q18: =IF(C18-H18=0,0,(C18-H18)/H18) -> 0 | S18: =IF(F18-K18=0,0,(F18-K18)/K18) -> 0
B20: 审计说明：

Sheet 销售费用
A1: 销售费用明细表
A2: =备忘录!$A$1 -> 被审计单位：福禄福擎网络科技有限公司 | D2: 编制人：刘喜琴 | G2: =备忘录!$C$2 -> 日期：2025/10/30 | I2: 往来科目需要明细一点，填的时候标出重点查看费用
A3: =备忘录!A3 -> 财务报表期间：2025.1-2025.9 | D3: 复核人：赵玮 | G3: =备忘录!$C$3 -> 日期：2025/10/31
A4: 序号 | B4: 科目名称 | C4: 本期发生额 | D4: 上期发生额 | E4: 结构比 | F4: 发生变动额 | G4: 发生额变动率 | H4: 变动原因分析及取得的支持性文件说明
A6: 1 | B6: 销售费用_工资性支出 | E6: =IF($C$22=0,0,C6/$C$22) -> 0 | F6: =ROUND(C6-D6,2) -> 0 | G6: =ROUND(F6/D6,2) -> #DIV/0!
A7: 2 | B7: 销售费用_营销费 | E7: =IF($C$22=0,0,C7/$C$22) -> 0 | F7: =ROUND(C7-D7,2) -> 0 | G7: =ROUND(F7/D7,2) -> #DIV/0!
A8: 3 | B8: 销售费用_测试费 | E8: =IF($C$22=0,0,C8/$C$22) -> 0 | F8: =ROUND(C8-D8,2) -> 0 | G8: =ROUND(F8/D8,2) -> #DIV/0!
A9: 4 | B9: 销售费用_办公费 | E9: =IF($C$22=0,0,C9/$C$22) -> 0 | F9: =ROUND(C9-D9,2) -> 0 | G9: =ROUND(F9/D9,2) -> #DIV/0!
A10: 5 | B10: 销售费用_中介机构服务费 | E10: =IF($C$22=0,0,C10/$C$22) -> 0 | F10: =ROUND(C10-D10,2) -> 0 | G10: =ROUND(F10/D10,2) -> #DIV/0!
A11: 6 | B11: 销售费用_设备折旧费 | E11: =IF($C$22=0,0,C11/$C$22) -> 0 | F11: =ROUND(C11-D11,2) -> 0 | G11: =ROUND(F11/D11,2) -> #DIV/0!
A12: 7 | E12: =IF($C$22=0,0,C12/$C$22) -> 0 | F12: =ROUND(C12-D12,2) -> 0 | G12: =ROUND(F12/D12,2) -> #DIV/0!
A13: 8 | E13: =IF($C$22=0,0,C13/$C$22) -> 0 | F13: =ROUND(C13-D13,2) -> 0 | G13: =ROUND(F13/D13,2) -> #DIV/0!
A14: 9 | E14: =IF($C$22=0,0,C14/$C$22) -> 0 | F14: =ROUND(C14-D14,2) -> 0 | G14: =ROUND(F14/D14,2) -> #DIV/0!
A15: 10 | E15: =IF($C$22=0,0,C15/$C$22) -> 0 | F15: =ROUND(C15-D15,2) -> 0 | G15: =ROUND(F15/D15,2) -> #DIV/0!
A16: 11 | E16: =IF($C$22=0,0,C16/$C$22) -> 0 | F16: =ROUND(C16-D16,2) -> 0 | G16: =ROUND(F16/D16,2) -> #DIV/0!
A17: 12 | E17: =IF($C$22=0,0,C17/$C$22) -> 0 | F17: =ROUND(C17-D17,2) -> 0 | G17: =ROUND(F17/D17,2) -> #DIV/0!
A18: 13 | E18: =IF($C$22=0,0,C18/$C$22) -> 0 | F18: =ROUND(C18-D18,2) -> 0 | G18: =ROUND(F18/D18,2) -> #DIV/0!
A19: 14 | E19: =IF($C$22=0,0,C19/$C$22) -> 0 | F19: =ROUND(C19-D19,2) -> 0 | G19: =ROUND(F19/D19,2) -> #DIV/0!
A20: 15 | E20: =IF($C$22=0,0,C20/$C$22) -> 0 | F20: =ROUND(C20-D20,2) -> 0 | G20: =ROUND(F20/D20,2) -> #DIV/0!
A21: 16 | E21: =IF($C$22=0,0,C21/$C$22) -> 0 | F21: =ROUND(C21-D21,2) -> 0 | G21: =ROUND(F21/D21,2) -> #DIV/0!
A22: 合计 | C22: =SUM(C6:C21) -> 0 | D22: =SUM(D6:D21) -> 0 | F22: =SUM(F6:F21) -> 0
B24: 审计说明：

Sheet 销售费用比例分析
B1: 销售费用占营业收入比率分析
A2: =备忘录!$A$1 -> 被审计单位：福禄福擎网络科技有限公司 | F2: 编制人：刘喜琴 | I2: =备忘录!$C$2 -> 日期：2025/10/30
A3: =备忘录!A3 -> 财务报表期间：2025.1-2025.9 | F3: 复核人：赵玮 | I3: =备忘录!$C$3 -> 日期：2025/10/31
A4: 序号 | B4: 科目名称 | C4: 本期发生额 | F4: 上期发生额 | I4: 占营业收入比率的增加 | J4: 占主营业务收入比率的增加 | K4: 变动原因分析及取得的支持性文件说明
C5: 本期审定数 | D5: 占营业收入比率 | E5: 占主营业务收入比率 | F5: 上期审定数 | G5: 占营业收入比率 | H5: 占主营业务收入比率
B6: 营业收入 | C6: =营业收入!D24 -> 0 | F6: =营业收入!E24 -> 0
B7: 主营业务收入 | C7: =营业收入!D19 -> 0 | F7: =营业收入!E19 -> 0
B8: 销售费用明细：
A9: =销售费用!A6 -> 1 | B9: =销售费用!B6 -> 销售费用_工资性支出 | C9: =销售费用!C6 -> 0 | D9: =IF($C$6=0,0,C9/$C$6) -> 0 | E9: =IF($C$7=0,0,C9/$C$7) -> 0 | F9: =销售费用!D6 -> 0 | G9: =IF($F$6=0,0,F9/$F$6) -> 0 | H9: =IF($F$7=0,0,F9/$F$7) -> 0 | I9: =D9-G9 -> 0 | J9: =E9-H9 -> 0
A10: =销售费用!A7 -> 2 | B10: =销售费用!B7 -> 销售费用_营销费 | C10: =销售费用!C7 -> 0 | D10: =IF($C$6=0,0,C10/$C$6) -> 0 | E10: =IF($C$7=0,0,C10/$C$7) -> 0 | F10: =销售费用!D7 -> 0 | G10: =IF($F$6=0,0,F10/$F$6) -> 0 | H10: =IF($F$7=0,0,F10/$F$7) -> 0 | I10: =D10-G10 -> 0 | J10: =E10-H10 -> 0
A11: =销售费用!A8 -> 3 | B11: =销售费用!B8 -> 销售费用_测试费 | C11: =销售费用!C8 -> 0 | D11: =IF($C$6=0,0,C11/$C$6) -> 0 | E11: =IF($C$7=0,0,C11/$C$7) -> 0 | F11: =销售费用!D8 -> 0 | G11: =IF($F$6=0,0,F11/$F$6) -> 0 | H11: =IF($F$7=0,0,F11/$F$7) -> 0 | I11: =D11-G11 -> 0 | J11: =E11-H11 -> 0
A12: =销售费用!A9 -> 4 | B12: =销售费用!B9 -> 销售费用_办公费 | C12: =销售费用!C9 -> 0 | D12: =IF($C$6=0,0,C12/$C$6) -> 0 | E12: =IF($C$7=0,0,C12/$C$7) -> 0 | F12: =销售费用!D9 -> 0 | G12: =IF($F$6=0,0,F12/$F$6) -> 0 | H12: =IF($F$7=0,0,F12/$F$7) -> 0 | I12: =D12-G12 -> 0 | J12: =E12-H12 -> 0
A13: =销售费用!A10 -> 5 | B13: =销售费用!B10 -> 销售费用_中介机构服务费 | C13: =销售费用!C10 -> 0 | D13: =IF($C$6=0,0,C13/$C$6) -> 0 | E13: =IF($C$7=0,0,C13/$C$7) -> 0 | F13: =销售费用!D10 -> 0 | G13: =IF($F$6=0,0,F13/$F$6) -> 0 | H13: =IF($F$7=0,0,F13/$F$7) -> 0 | I13: =D13-G13 -> 0 | J13: =E13-H13 -> 0
A14: =销售费用!A11 -> 6 | B14: =销售费用!B11 -> 销售费用_设备折旧费 | C14: =销售费用!C11 -> 0 | D14: =IF($C$6=0,0,C14/$C$6) -> 0 | E14: =IF($C$7=0,0,C14/$C$7) -> 0 | F14: =销售费用!D11 -> 0 | G14: =IF($F$6=0,0,F14/$F$6) -> 0 | H14: =IF($F$7=0,0,F14/$F$7) -> 0 | I14: =D14-G14 -> 0 | J14: =E14-H14 -> 0
A15: =销售费用!A12 -> 7 | B15: =销售费用!B12 -> 0 | C15: =销售费用!C12 -> 0 | D15: =IF($C$6=0,0,C15/$C$6) -> 0 | E15: =IF($C$7=0,0,C15/$C$7) -> 0 | F15: =销售费用!D12 -> 0 | G15: =IF($F$6=0,0,F15/$F$6) -> 0 | H15: =IF($F$7=0,0,F15/$F$7) -> 0 | I15: =D15-G15 -> 0 | J15: =E15-H15 -> 0
A16: =销售费用!A13 -> 8 | B16: =销售费用!B13 -> 0 | C16: =销售费用!C13 -> 0 | D16: =IF($C$6=0,0,C16/$C$6) -> 0 | E16: =IF($C$7=0,0,C16/$C$7) -> 0 | F16: =销售费用!D13 -> 0 | G16: =IF($F$6=0,0,F16/$F$6) -> 0 | H16: =IF($F$7=0,0,F16/$F$7) -> 0 | I16: =D16-G16 -> 0 | J16: =E16-H16 -> 0
A17: =销售费用!A14 -> 9 | B17: =销售费用!B14 -> 0 | C17: =销售费用!C14 -> 0 | D17: =IF($C$6=0,0,C17/$C$6) -> 0 | E17: =IF($C$7=0,0,C17/$C$7) -> 0 | F17: =销售费用!D14 -> 0 | G17: =IF($F$6=0,0,F17/$F$6) -> 0 | H17: =IF($F$7=0,0,F17/$F$7) -> 0 | I17: =D17-G17 -> 0 | J17: =E17-H17 -> 0
A18: =销售费用!A15 -> 10 | B18: =销售费用!B15 -> 0 | C18: =销售费用!C15 -> 0 | D18: =IF($C$6=0,0,C18/$C$6) -> 0 | E18: =IF($C$7=0,0,C18/$C$7) -> 0 | F18: =销售费用!D15 -> 0 | G18: =IF($F$6=0,0,F18/$F$6) -> 0 | H18: =IF($F$7=0,0,F18/$F$7) -> 0 | I18: =D18-G18 -> 0 | J18: =E18-H18 -> 0
A19: =销售费用!A16 -> 11 | B19: =销售费用!B16 -> 0 | C19: =销售费用!C16 -> 0 | D19: =IF($C$6=0,0,C19/$C$6) -> 0 | E19: =IF($C$7=0,0,C19/$C$7) -> 0 | F19: =销售费用!D16 -> 0 | G19: =IF($F$6=0,0,F19/$F$6) -> 0 | H19: =IF($F$7=0,0,F19/$F$7) -> 0 | I19: =D19-G19 -> 0 | J19: =E19-H19 -> 0
A20: =销售费用!A17 -> 12 | B20: =销售费用!B17 -> 0 | C20: =销售费用!C17 -> 0 | D20: =IF($C$6=0,0,C20/$C$6) -> 0 | E20: =IF($C$7=0,0,C20/$C$7) -> 0 | F20: =销售费用!D17 -> 0 | G20: =IF($F$6=0,0,F20/$F$6) -> 0 | H20: =IF($F$7=0,0,F20/$F$7) -> 0 | I20: =D20-G20 -> 0 | J20: =E20-H20 -> 0
... A24: =销售费用!A21 -> 16 | B24: =销售费用!B21 -> 0 | C24: =销售费用!C21 -> 0 | D24: =IF($C$6=0,0,C24/$C$6) -> 0 | E24: =IF($C$7=0,0,C24/$C$7) -> 0 | F24: =销售费用!D21 -> 0 | G24: =IF($F$6=0,0,F24/$F$6) -> 0 | H24: =IF($F$7=0,0,F24/$F$7) -> 0 | I24: =D24-G24 -> 0 | J24: =E24-H24 -> 0
A25: 合计 | C25: =SUM(C9:C24) -> 0 | D25: =IF($C$6=0,0,C25/$C$6) -> 0 | E25: =IF($C$7=0,0,C25/$C$7) -> 0 | F25: =SUM(F9:F24) -> 0 | G25: =IF($F$6=0,0,F25/$F$6) -> 0 | H25: =IF($F$7=0,0,F25/$F$7) -> 0 | I25: =D25-G25 -> 0 | J25: =E25-H25 -> 0

Sheet 管理费用
A1: 管理费用明细表
A2: =备忘录!$A$1 -> 被审计单位：福禄福擎网络科技有限公司 | D2: 编制人：刘喜琴 | G2: =备忘录!$C$2 -> 日期：2025/10/30
A3: =备忘录!A3 -> 财务报表期间：2025.1-2025.9 | D3: 复核人：赵玮 | G3: =备忘录!$C$3 -> 日期：2025/10/31
A4: 序号 | B4: 科目名称 | C4: 本期发生额 | D4: 上期发生额 | E4: 结构比 | F4: 发生变动额 | G4: 发生额变动率 | H4: 变动原因分析及取得的支持性文件说明
A6: 1 | B6: 管理费用_工资性支出 | E6: =IF($C$21=0,0,C6/$C$21) -> 0 | F6: =ROUND(C6-D6,2) -> 0 | G6: =ROUND(F6/D6,2) -> #DIV/0!
A7: 2 | B7: 管理费用_房租物业费 | E7: =IF($C$21=0,0,C7/$C$21) -> 0 | F7: =ROUND(C7-D7,2) -> 0 | G7: =ROUND(F7/D7,2) -> #DIV/0!
A8: 3 | B8: 管理费用_水电费 | E8: =IF($C$21=0,0,C8/$C$21) -> 0 | F8: =ROUND(C8-D8,2) -> 0 | G8: =ROUND(F8/D8,2) -> #DIV/0!
A9: 4 | B9: 管理费用_办公费 | E9: =IF($C$21=0,0,C9/$C$21) -> 0 | F9: =ROUND(C9-D9,2) -> 0 | G9: =ROUND(F9/D9,2) -> #DIV/0!
A10: 5 | B10: 管理费用_中介机构服务费 | E10: =IF($C$21=0,0,C10/$C$21) -> 0 | F10: =ROUND(C10-D10,2) -> 0 | G10: =ROUND(F10/D10,2) -> #DIV/0!
A11: 6 | B11: 管理费用_设备折旧费 | E11: =IF($C$21=0,0,C11/$C$21) -> 0 | F11: =ROUND(C11-D11,2) -> 0 | G11: =ROUND(F11/D11,2) -> #DIV/0!
A12: 7 | B12: 管理费用_软件摊销 | E12: =IF($C$21=0,0,C12/$C$21) -> 0 | F12: =ROUND(C12-D12,2) -> 0 | G12: =ROUND(F12/D12,2) -> #DIV/0!
A13: 8 | B13: 管理费用_研发费 | E13: =IF($C$21=0,0,C13/$C$21) -> 0 | F13: =ROUND(C13-D13,2) -> 0 | G13: =ROUND(F13/D13,2) -> #DIV/0!
A14: 9 | B14: 管理费用_劳务派遣服务费 | E14: =IF($C$21=0,0,C14/$C$21) -> 0 | F14: =ROUND(C14-D14,2) -> 0 | G14: =ROUND(F14/D14,2) -> #DIV/0!
A15: 10 | B15: 管理费用_软件服务费 | E15: =IF($C$21=0,0,C15/$C$21) -> 0 | F15: =ROUND(C15-D15,2) -> 0 | G15: =ROUND(F15/D15,2) -> #DIV/0!
A16: 11 | E16: =IF($C$21=0,0,C16/$C$21) -> 0 | F16: =ROUND(C16-D16,2) -> 0 | G16: =ROUND(F16/D16,2) -> #DIV/0!
A17: 12 | E17: =IF($C$21=0,0,C17/$C$21) -> 0 | F17: =ROUND(C17-D17,2) -> 0 | G17: =ROUND(F17/D17,2) -> #DIV/0!
A18: 13 | E18: =IF($C$21=0,0,C18/$C$21) -> 0 | F18: =ROUND(C18-D18,2) -> 0 | G18: =ROUND(F18/D18,2) -> #DIV/0!
A19: 14 | E19: =IF($C$21=0,0,C19/$C$21) -> 0 | F19: =ROUND(C19-D19,2) -> 0 | G19: =ROUND(F19/D19,2) -> #DIV/0!
A20: 15 | E20: =IF($C$21=0,0,C20/$C$21) -> 0 | F20: =ROUND(C20-D20,2) -> 0 | G20: =ROUND(F20/D20,2) -> #DIV/0!
A21: 合计 | C21: =SUM(C6:C20) -> 0 | D21: =SUM(D6:D20) -> 0 | F21: =SUM(F6:F20) -> 0
B23: 审计说明：

Sheet 管理费用比例分析
B1: 管理费用占营业收入比率分析
A2: =备忘录!$A$1 -> 被审计单位：福禄福擎网络科技有限公司 | F2: 编制人：刘喜琴 | I2: =备忘录!$C$2 -> 日期：2025/10/30
A3: =备忘录!A3 -> 财务报表期间：2025.1-2025.9 | F3: 复核人：赵玮 | I3: =备忘录!$C$3 -> 日期：2025/10/31
A4: 序号 | B4: 科目名称 | C4: 本期发生额 | F4: 上期发生额 | I4: 占营业收入比率的增加 | J4: 占主营业务收入比率的增加 | K4: 变动原因分析及取得的支持性文件说明
C5: 本期审定数 | D5: 占营业收入比率 | E5: 占主营业务收入比率 | F5: 上期审定数 | G5: 占营业收入比率 | H5: 占主营业务收入比率
B6: 营业收入 | C6: =营业收入!D24 -> 0 | F6: =营业收入!E24 -> 0
B7: 主营业务收入 | C7: =营业收入!D19 -> 0 | F7: =营业收入!E19 -> 0
B8: 管理费用明细：
A9: =管理费用!A6 -> 1 | B9: =管理费用!B6 -> 管理费用_工资性支出 | C9: =管理费用!C6 -> 0 | D9: =IF($C$6=0,0,C9/$C$6) -> 0 | E9: =IF($C$7=0,0,C9/$C$7) -> 0 | F9: =管理费用!D6 -> 0 | G9: =IF($F$6=0,0,F9/$F$6) -> 0 | H9: =IF($F$7=0,0,F9/$F$7) -> 0 | I9: =D9-G9 -> 0 | J9: =E9-H9 -> 0
A10: =管理费用!A7 -> 2 | B10: =管理费用!B7 -> 管理费用_房租物业费 | C10: =管理费用!C7 -> 0 | D10: =IF($C$6=0,0,C10/$C$6) -> 0 | E10: =IF($C$7=0,0,C10/$C$7) -> 0 | F10: =管理费用!D7 -> 0 | G10: =IF($F$6=0,0,F10/$F$6) -> 0 | H10: =IF($F$7=0,0,F10/$F$7) -> 0 | I10: =D10-G10 -> 0 | J10: =E10-H10 -> 0
A11: =管理费用!A8 -> 3 | B11: =管理费用!B8 -> 管理费用_水电费 | C11: =管理费用!C8 -> 0 | D11: =IF($C$6=0,0,C11/$C$6) -> 0 | E11: =IF($C$7=0,0,C11/$C$7) -> 0 | F11: =管理费用!D8 -> 0 | G11: =IF($F$6=0,0,F11/$F$6) -> 0 | H11: =IF($F$7=0,0,F11/$F$7) -> 0 | I11: =D11-G11 -> 0 | J11: =E11-H11 -> 0
A12: =管理费用!A9 -> 4 | B12: =管理费用!B9 -> 管理费用_办公费 | C12: =管理费用!C9 -> 0 | D12: =IF($C$6=0,0,C12/$C$6) -> 0 | E12: =IF($C$7=0,0,C12/$C$7) -> 0 | F12: =管理费用!D9 -> 0 | G12: =IF($F$6=0,0,F12/$F$6) -> 0 | H12: =IF($F$7=0,0,F12/$F$7) -> 0 | I12: =D12-G12 -> 0 | J12: =E12-H12 -> 0
A13: =管理费用!A10 -> 5 | B13: =管理费用!B10 -> 管理费用_中介机构服务费 | C13: =管理费用!C10 -> 0 | D13: =IF($C$6=0,0,C13/$C$6) -> 0 | E13: =IF($C$7=0,0,C13/$C$7) -> 0 | F13: =管理费用!D10 -> 0 | G13: =IF($F$6=0,0,F13/$F$6) -> 0 | H13: =IF($F$7=0,0,F13/$F$7) -> 0 | I13: =D13-G13 -> 0 | J13: =E13-H13 -> 0
A14: =管理费用!A11 -> 6 | B14: =管理费用!B11 -> 管理费用_设备折旧费 | C14: =管理费用!C11 -> 0 | D14: =IF($C$6=0,0,C14/$C$6) -> 0 | E14: =IF($C$7=0,0,C14/$C$7) -> 0 | F14: =管理费用!D11 -> 0 | G14: =IF($F$6=0,0,F14/$F$6) -> 0 | H14: =IF($F$7=0,0,F14/$F$7) -> 0 | I14: =D14-G14 -> 0 | J14: =E14-H14 -> 0
A15: =管理费用!A12 -> 7 | B15: =管理费用!B12 -> 管理费用_软件摊销 | C15: =管理费用!C12 -> 0 | D15: =IF($C$6=0,0,C15/$C$6) -> 0 | E15: =IF($C$7=0,0,C15/$C$7) -> 0 | F15: =管理费用!D12 -> 0 | G15: =IF($F$6=0,0,F15/$F$6) -> 0 | H15: =IF($F$7=0,0,F15/$F$7) -> 0 | I15: =D15-G15 -> 0 | J15: =E15-H15 -> 0
A16: =管理费用!A13 -> 8 | B16: =管理费用!B13 -> 管理费用_研发费 | C16: =管理费用!C13 -> 0 | D16: =IF($C$6=0,0,C16/$C$6) -> 0 | E16: =IF($C$7=0,0,C16/$C$7) -> 0 | F16: =管理费用!D13 -> 0 | G16: =IF($F$6=0,0,F16/$F$6) -> 0 | H16: =IF($F$7=0,0,F16/$F$7) -> 0 | I16: =D16-G16 -> 0 | J16: =E16-H16 -> 0
A17: =管理费用!A14 -> 9 | B17: =管理费用!B14 -> 管理费用_劳务派遣服务费 | C17: =管理费用!C14 -> 0 | D17: =IF($C$6=0,0,C17/$C$6) -> 0 | E17: =IF($C$7=0,0,C17/$C$7) -> 0 | F17: =管理费用!D14 -> 0 | G17: =IF($F$6=0,0,F17/$F$6) -> 0 | H17: =IF($F$7=0,0,F17/$F$7) -> 0 | I17: =D17-G17 -> 0 | J17: =E17-H17 -> 0
A18: =管理费用!A15 -> 10 | B18: =管理费用!B15 -> 管理费用_软件服务费 | C18: =管理费用!C15 -> 0 | D18: =IF($C$6=0,0,C18/$C$6) -> 0 | E18: =IF($C$7=0,0,C18/$C$7) -> 0 | F18: =管理费用!D15 -> 0 | G18: =IF($F$6=0,0,F18/$F$6) -> 0 | H18: =IF($F$7=0,0,F18/$F$7) -> 0 | I18: =D18-G18 -> 0 | J18: =E18-H18 -> 0
A19: =管理费用!A16 -> 11 | B19: =管理费用!B16 -> 0 | C19: =管理费用!C16 -> 0 | D19: =IF($C$6=0,0,C19/$C$6) -> 0 | E19: =IF($C$7=0,0,C19/$C$7) -> 0 | F19: =管理费用!D16 -> 0 | G19: =IF($F$6=0,0,F19/$F$6) -> 0 | H19: =IF($F$7=0,0,F19/$F$7) -> 0 | I19: =D19-G19 -> 0 | J19: =E19-H19 -> 0
A20: =管理费用!A17 -> 12 | B20: =管理费用!B17 -> 0 | C20: =管理费用!C17 -> 0 | D20: =IF($C$6=0,0,C20/$C$6) -> 0 | E20: =IF($C$7=0,0,C20/$C$7) -> 0 | F20: =管理费用!D17 -> 0 | G20: =IF($F$6=0,0,F20/$F$6) -> 0 | H20: =IF($F$7=0,0,F20/$F$7) -> 0 | I20: =D20-G20 -> 0 | J20: =E20-H20 -> 0
... A23: =管理费用!A20 -> 15 | B23: =管理费用!B20 -> 0 | C23: =管理费用!C20 -> 0 | D23: =IF($C$6=0,0,C23/$C$6) -> 0 | E23: =IF($C$7=0,0,C23/$C$7) -> 0 | F23: =管理费用!D20 -> 0 | G23: =IF($F$6=0,0,F23/$F$6) -> 0 | H23: =IF($F$7=0,0,F23/$F$7) -> 0 | I23: =D23-G23 -> 0 | J23: =E23-H23 -> 0
A24: 合计 | C24: =SUM(C9:C23) -> 0 | D24: =IF($C$6=0,0,C24/$C$6) -> 0 | E24: =IF($C$7=0,0,C24/$C$7) -> 0 | F24: =SUM(F9:F23) -> 0 | G24: =IF($F$6=0,0,F24/$F$6) -> 0 | H24: =IF($F$7=0,0,F24/$F$7) -> 0 | I24: =D24-G24 -> 0 | J24: =E24-H24 -> 0
B26: 审计说明：

Sheet 财务费用
A1: 财务费用明细表
A2: =备忘录!$A$1 -> 被审计单位：福禄福擎网络科技有限公司 | D2: 编制人：刘喜琴 | G2: =备忘录!$C$2 -> 日期：2025/10/30
A3: =备忘录!A3 -> 财务报表期间：2025.1-2025.9 | D3: 复核人：赵玮 | G3: =备忘录!$C$3 -> 日期：2025/10/31
A4: 科目名称 | B4: 本期发生额 | C4: 上期发生额 | D4: 结构比 | E4: 发生变动额 | F4: 发生额变动率 | G4: 变动原因分析及取得的支持性文件说明
A6: 利息支出 | D6: =IF($B$12=0,0,B6/$B$12) -> 0 | E6: =ROUND(B6-C6,2) -> 0 | F6: =ROUND(E6/C6,2) -> #DIV/0!
A7: 减：利息收入 | D7: =IF($B$12=0,0,B7/$B$12) -> 0 | E7: =ROUND(B7-C7,2) -> 0 | F7: =ROUND(E7/C7,2) -> #DIV/0! | H7: 注：利息收入账面为负数，填此表要转换成正数
A8: 汇兑损失 | D8: =IF($B$12=0,0,B8/$B$12) -> 0 | E8: =ROUND(B8-C8,2) -> 0 | F8: =ROUND(E8/C8,2) -> #DIV/0!
A9: 减：汇兑收益 | D9: =IF($B$12=0,0,B9/$B$12) -> 0 | E9: =ROUND(B9-C9,2) -> 0 | F9: =ROUND(E9/C9,2) -> #DIV/0!
A10: 银行手续费 | D10: =IF($B$12=0,0,B10/$B$12) -> 0 | E10: =ROUND(B10-C10,2) -> 0 | F10: =ROUND(E10/C10,2) -> #DIV/0!
A11: 其他 | D11: =IF($B$12=0,0,B11/$B$12) -> 0 | E11: =ROUND(B11-C11,2) -> 0 | F11: =ROUND(E11/C11,2) -> #DIV/0!
A12: 合计 | B12: =ROUND(B6-B7+B8-B9+SUM(B10:B11),2) -> 0 | C12: =ROUND(C6-C7+C8-C9+SUM(C10:C11),2) -> 0 | E12: =SUM(E6:E11) -> 0
A14: 审计说明：

Sheet 营业外收入
A1: 营业外收入明细表
A2: =备忘录!$A$1 -> 被审计单位：福禄福擎网络科技有限公司 | D2: 编制人：刘喜琴 | G2: =备忘录!$C$2 -> 日期：2025/10/30
A3: =备忘录!A3 -> 财务报表期间：2025.1-2025.9 | D3: 复核人：赵玮 | G3: =备忘录!$C$3 -> 日期：2025/10/31
A4: 科目名称 | B4: 本期发生额 | C4: 上期发生额 | D4: 结构比 | E4: 发生变动额 | F4: 发生额变动率 | G4: 变动原因分析及取得的支持性文件说明
D6: =IF($B$12=0,0,B6/$B$12) -> 0 | E6: =ROUND(B6-C6,2) -> 0 | F6: =ROUND(E6/C6,2) -> #DIV/0!
D7: =IF($B$12=0,0,B7/$B$12) -> 0 | E7: =ROUND(B7-C7,2) -> 0 | F7: =ROUND(E7/C7,2) -> #DIV/0!
D8: =IF($B$12=0,0,B8/$B$12) -> 0 | E8: =ROUND(B8-C8,2) -> 0 | F8: =ROUND(E8/C8,2) -> #DIV/0!
D9: =IF($B$12=0,0,B9/$B$12) -> 0 | E9: =ROUND(B9-C9,2) -> 0 | F9: =ROUND(E9/C9,2) -> #DIV/0!
D10: =IF($B$12=0,0,B10/$B$12) -> 0 | E10: =ROUND(B10-C10,2) -> 0 | F10: =ROUND(E10/C10,2) -> #DIV/0!
D11: =IF($B$12=0,0,B11/$B$12) -> 0 | E11: =ROUND(B11-C11,2) -> 0 | F11: =ROUND(E11/C11,2) -> #DIV/0!
A12: 合计 | B12: =SUM(B6:B11) -> 0 | C12: =SUM(C6:C11) -> 0 | E12: =SUM(E6:E11) -> 0
A14: 审计说明：

Sheet 营业外支出
A1: 营业外支出明细表
A2: =备忘录!$A$1 -> 被审计单位：福禄福擎网络科技有限公司 | D2: 编制人：刘喜琴 | G2: =备忘录!$C$2 -> 日期：2025/10/30
A3: =备忘录!A3 -> 财务报表期间：2025.1-2025.9 | D3: 复核人：赵玮 | G3: =备忘录!$C$3 -> 日期：2025/10/31
A4: 科目名称 | B4: 本期发生额 | C4: 上期发生额 | D4: 结构比 | E4: 发生变动额 | F4: 发生额变动率 | G4: 变动原因分析及取得的支持性文件说明
D6: =IF($B$12=0,0,B6/$B$12) -> 0 | E6: =ROUND(B6-C6,2) -> 0 | F6: =ROUND(E6/C6,2) -> #DIV/0!
D7: =IF($B$12=0,0,B7/$B$12) -> 0 | E7: =ROUND(B7-C7,2) -> 0 | F7: =ROUND(E7/C7,2) -> #DIV/0!
D8: =IF($B$12=0,0,B8/$B$12) -> 0 | E8: =ROUND(B8-C8,2) -> 0 | F8: =ROUND(E8/C8,2) -> #DIV/0!
D9: =IF($B$12=0,0,B9/$B$12) -> 0 | E9: =ROUND(B9-C9,2) -> 0 | F9: =ROUND(E9/C9,2) -> #DIV/0!
D10: =IF($B$12=0,0,B10/$B$12) -> 0 | E10: =ROUND(B10-C10,2) -> 0 | F10: =ROUND(E10/C10,2) -> #DIV/0!
D11: =IF($B$12=0,0,B11/$B$12) -> 0 | E11: =ROUND(B11-C11,2) -> 0 | F11: =ROUND(E11/C11,2) -> #DIV/0!
A12: 合计 | B12: =SUM(B6:B11) -> 0 | C12: =SUM(C6:C11) -> 0 | E12: =SUM(E6:E11) -> 0
A14: 审计说明：
